/*     */ package li.cil.oc.integration;public final class Mods$ { public static final Mods$ MODULE$; private final Set<ModProxy> handlers; private final ArrayBuffer<Mods.ModBase> li$cil$oc$integration$Mods$$knownMods; private final Mods.SimpleMod Ae2Fc; private final Mods.SimpleMod AgriCraft; private final Mods.SimpleMod AppliedEnergistics2; private final Mods.SimpleMod AvaritiaAddons; private final Mods.SimpleMod BattleGear2; private final Mods.SimpleMod BetterRecords; private final Mods.SimpleMod BloodMagic; private final Mods.SimpleMod BluePower; private final Mods.SimpleMod BuildCraft; private final Mods.SimpleMod BuildCraftLibrary; private final Mods.SimpleMod BuildCraftRecipes; private final Mods.SimpleMod BuildCraftTiles; private final Mods.SimpleMod BuildCraftTools; private final Mods.SimpleMod BuildCraftTransport; private final Mods.SimpleMod CoFHEnergy; private final Mods.SimpleMod CoFHItem; private final Mods.SimpleMod CoFHTileEntity; private final Mods.SimpleMod CoFHTransport; private final Mods.SimpleMod ColoredLights; private final Mods.SimpleMod ComputerCraft;
/*     */   private final Mods.SimpleMod CraftingCosts;
/*     */   private final Mods.ClassBasedMod DeepStorageUnit;
/*     */   private final Mods.SimpleMod ElectricalAge;
/*     */   private final Mods.SimpleMod EnderIO;
/*     */   private final Mods.SimpleMod EnderStorage;
/*     */   private final Mods.SimpleMod ExtraCells;
/*     */   private final Mods.SimpleMod Factorization;
/*     */   private final Mods.SimpleMod Forestry;
/*     */   
/*     */   private Set<ModProxy> handlers() {
/*  12 */     return this.handlers;
/*     */   } private final Mods.SimpleMod ForgeMultipart; private final Mods.SimpleMod Galacticraft; private final Mods.ClassBasedMod GregTech; private final Mods.SimpleMod IndustrialCraft2; private final Mods.SimpleMod IndustrialCraft2Classic; private final Mods.SimpleMod IngameWiki; private final Mods.SimpleMod Mekanism; private final Mods.SimpleMod MekanismGas; private final Mods.SimpleMod Minecraft; private final Mods.SimpleMod MineFactoryReloaded; private final Mods.SimpleMod Mystcraft; private final Mods.SimpleMod NotEnoughItems; private final Mods.SimpleMod NotEnoughKeys; private final Mods.SimpleMod OpenComputers; private final Mods.SimpleMod PortalGun; private final Mods.SimpleMod ProjectRedCore; private final Mods.SimpleMod ProjectRedTransmission; private final Mods.SimpleMod Railcraft; private final Mods.SimpleMod RedLogic; private final Mods.SimpleMod RotaryCraft; private final Mods.ModBase StargateTech2; private final Mods.SimpleMod Thaumcraft; private final Mods.SimpleMod ThaumicEnergistics; private final Mods.SimpleMod ThermalExpansion; private final Mods.SimpleMod TinkersConstruct; private final Mods.SimpleMod TIS3D; private final Mods.SimpleMod TMechWorks; private final Mods.SimpleMod VersionChecker; private final Mods.SimpleMod Waila; private final Mods.SimpleMod WirelessRedstoneCBE; private final Mods.SimpleMod WirelessRedstoneSVE; private final ModProxy[] Proxies; public ArrayBuffer<Mods.ModBase> li$cil$oc$integration$Mods$$knownMods() {
/*  14 */     return this.li$cil$oc$integration$Mods$$knownMods;
/*     */   }
/*     */   
/*     */   public ArrayBuffer<Mods.ModBase> All() {
/*  18 */     return (ArrayBuffer<Mods.ModBase>)li$cil$oc$integration$Mods$$knownMods().clone();
/*     */   }
/*  20 */   public Mods.SimpleMod Ae2Fc() { return this.Ae2Fc; }
/*  21 */   public Mods.SimpleMod AgriCraft() { return this.AgriCraft; }
/*  22 */   public Mods.SimpleMod AppliedEnergistics2() { return this.AppliedEnergistics2; }
/*  23 */   public Mods.SimpleMod AvaritiaAddons() { return this.AvaritiaAddons; }
/*  24 */   public Mods.SimpleMod BattleGear2() { return this.BattleGear2; }
/*  25 */   public Mods.SimpleMod BetterRecords() { return this.BetterRecords; }
/*  26 */   public Mods.SimpleMod BloodMagic() { return this.BloodMagic; }
/*  27 */   public Mods.SimpleMod BluePower() { return this.BluePower; }
/*  28 */   public Mods.SimpleMod BuildCraft() { return this.BuildCraft; }
/*  29 */   public Mods.SimpleMod BuildCraftLibrary() { return this.BuildCraftLibrary; }
/*  30 */   public Mods.SimpleMod BuildCraftRecipes() { return this.BuildCraftRecipes; }
/*  31 */   public Mods.SimpleMod BuildCraftTiles() { return this.BuildCraftTiles; }
/*  32 */   public Mods.SimpleMod BuildCraftTools() { return this.BuildCraftTools; }
/*  33 */   public Mods.SimpleMod BuildCraftTransport() { return this.BuildCraftTransport; }
/*  34 */   public Mods.SimpleMod CoFHEnergy() { return this.CoFHEnergy; }
/*  35 */   public Mods.SimpleMod CoFHItem() { return this.CoFHItem; }
/*  36 */   public Mods.SimpleMod CoFHTileEntity() { return this.CoFHTileEntity; }
/*  37 */   public Mods.SimpleMod CoFHTransport() { return this.CoFHTransport; }
/*  38 */   public Mods.SimpleMod ColoredLights() { return this.ColoredLights; }
/*  39 */   public Mods.SimpleMod ComputerCraft() { return this.ComputerCraft; }
/*  40 */   public Mods.SimpleMod CraftingCosts() { return this.CraftingCosts; }
/*  41 */   public Mods.ClassBasedMod DeepStorageUnit() { return this.DeepStorageUnit; }
/*  42 */   public Mods.SimpleMod ElectricalAge() { return this.ElectricalAge; }
/*  43 */   public Mods.SimpleMod EnderIO() { return this.EnderIO; }
/*  44 */   public Mods.SimpleMod EnderStorage() { return this.EnderStorage; }
/*  45 */   public Mods.SimpleMod ExtraCells() { return this.ExtraCells; }
/*  46 */   public Mods.SimpleMod Factorization() { return this.Factorization; }
/*  47 */   public Mods.SimpleMod Forestry() { return this.Forestry; }
/*  48 */   public Mods.SimpleMod ForgeMultipart() { return this.ForgeMultipart; }
/*  49 */   public Mods.SimpleMod Galacticraft() { return this.Galacticraft; }
/*  50 */   public Mods.ClassBasedMod GregTech() { return this.GregTech; }
/*  51 */   public Mods.SimpleMod IndustrialCraft2() { return this.IndustrialCraft2; }
/*  52 */   public Mods.SimpleMod IndustrialCraft2Classic() { return this.IndustrialCraft2Classic; }
/*  53 */   public Mods.SimpleMod IngameWiki() { return this.IngameWiki; }
/*  54 */   public Mods.SimpleMod Mekanism() { return this.Mekanism; }
/*  55 */   public Mods.SimpleMod MekanismGas() { return this.MekanismGas; }
/*  56 */   public Mods.SimpleMod Minecraft() { return this.Minecraft; }
/*  57 */   public Mods.SimpleMod MineFactoryReloaded() { return this.MineFactoryReloaded; }
/*  58 */   public Mods.SimpleMod Mystcraft() { return this.Mystcraft; }
/*  59 */   public Mods.SimpleMod NotEnoughItems() { return this.NotEnoughItems; }
/*  60 */   public Mods.SimpleMod NotEnoughKeys() { return this.NotEnoughKeys; }
/*  61 */   public Mods.SimpleMod OpenComputers() { return this.OpenComputers; }
/*  62 */   public Mods.SimpleMod PortalGun() { return this.PortalGun; }
/*  63 */   public Mods.SimpleMod ProjectRedCore() { return this.ProjectRedCore; }
/*  64 */   public Mods.SimpleMod ProjectRedTransmission() { return this.ProjectRedTransmission; }
/*  65 */   public Mods.SimpleMod Railcraft() { return this.Railcraft; }
/*  66 */   public Mods.SimpleMod RedLogic() { return this.RedLogic; }
/*  67 */   public Mods.SimpleMod RotaryCraft() { return this.RotaryCraft; }
/*  68 */   public Mods.ModBase StargateTech2() { return this.StargateTech2; } public final class Mods$$anon$1 implements Mods.ModBase { private boolean isModAvailable_; private boolean li$cil$oc$integration$Mods$ModBase$$powerDisabled; private volatile boolean bitmap$0; public boolean li$cil$oc$integration$Mods$ModBase$$powerDisabled() { return this.li$cil$oc$integration$Mods$ModBase$$powerDisabled; } @TraitSetter public void li$cil$oc$integration$Mods$ModBase$$powerDisabled_$eq(boolean x$1) { this.li$cil$oc$integration$Mods$ModBase$$powerDisabled = x$1; } public boolean isAvailable() { return Mods.ModBase$class.isAvailable(this); } public void disablePower() { Mods.ModBase$class.disablePower(this); } public Option<ModContainer> container() { return Mods.ModBase$class.container(this); } public Option<ArtifactVersion> version() { return Mods.ModBase$class.version(this); } public Mods$$anon$1() { Mods.ModBase$class.$init$(this); }
/*  69 */     public String id() { return "StargateTech2"; } private boolean isModAvailable_$lzycompute() { // Byte code:
/*     */       //   0: aload_0
/*     */       //   1: dup
/*     */       //   2: astore_1
/*     */       //   3: monitorenter
/*     */       //   4: aload_0
/*     */       //   5: getfield bitmap$0 : Z
/*     */       //   8: ifne -> 64
/*     */       //   11: aload_0
/*     */       //   12: ldc 'StargateTech2'
/*     */       //   14: invokestatic isModLoaded : (Ljava/lang/String;)Z
/*     */       //   17: ifeq -> 55
/*     */       //   20: invokestatic instance : ()Lcpw/mods/fml/common/Loader;
/*     */       //   23: invokevirtual getIndexedModList : ()Ljava/util/Map;
/*     */       //   26: ldc 'StargateTech2'
/*     */       //   28: invokeinterface get : (Ljava/lang/Object;)Ljava/lang/Object;
/*     */       //   33: checkcast cpw/mods/fml/common/ModContainer
/*     */       //   36: astore_2
/*     */       //   37: aload_2
/*     */       //   38: invokeinterface getVersion : ()Ljava/lang/String;
/*     */       //   43: ldc '0.7.'
/*     */       //   45: invokevirtual startsWith : (Ljava/lang/String;)Z
/*     */       //   48: ifeq -> 55
/*     */       //   51: iconst_1
/*     */       //   52: goto -> 56
/*     */       //   55: iconst_0
/*     */       //   56: putfield isModAvailable_ : Z
/*     */       //   59: aload_0
/*     */       //   60: iconst_1
/*     */       //   61: putfield bitmap$0 : Z
/*     */       //   64: getstatic scala/runtime/BoxedUnit.UNIT : Lscala/runtime/BoxedUnit;
/*     */       //   67: pop
/*     */       //   68: aload_1
/*     */       //   69: monitorexit
/*     */       //   70: aload_0
/*     */       //   71: getfield isModAvailable_ : Z
/*     */       //   74: ireturn
/*     */       //   75: aload_1
/*     */       //   76: monitorexit
/*     */       //   77: athrow
/*     */       // Line number table:
/*     */       //   Java source line number -> byte code offset
/*     */       //   #71	-> 0
/*     */       //   #72	-> 20
/*     */       //   #73	-> 37
/*     */       //   #71	-> 51
/*     */       // Local variable table:
/*     */       //   start	length	slot	name	descriptor
/*     */       //   0	78	0	this	Lli/cil/oc/integration/Mods$$anon$1;
/*     */       //   37	11	2	mod	Lcpw/mods/fml/common/ModContainer;
/*     */       // Exception table:
/*     */       //   from	to	target	type
/*     */       //   4	70	75	finally }
/*     */     private boolean isModAvailable_() {
/*  71 */       return this.bitmap$0 ? this.isModAvailable_ : isModAvailable_$lzycompute();
/*     */     }
/*     */ 
/*     */     
/*     */     public boolean isModAvailable() {
/*  76 */       return isModAvailable_();
/*     */     } }
/*  78 */   public Mods.SimpleMod Thaumcraft() { return this.Thaumcraft; }
/*  79 */   public Mods.SimpleMod ThaumicEnergistics() { return this.ThaumicEnergistics; }
/*  80 */   public Mods.SimpleMod ThermalExpansion() { return this.ThermalExpansion; }
/*  81 */   public Mods.SimpleMod TinkersConstruct() { return this.TinkersConstruct; }
/*  82 */   public Mods.SimpleMod TIS3D() { return this.TIS3D; }
/*  83 */   public Mods.SimpleMod TMechWorks() { return this.TMechWorks; }
/*  84 */   public Mods.SimpleMod VersionChecker() { return this.VersionChecker; }
/*  85 */   public Mods.SimpleMod Waila() { return this.Waila; }
/*  86 */   public Mods.SimpleMod WirelessRedstoneCBE() { return this.WirelessRedstoneCBE; } public Mods.SimpleMod WirelessRedstoneSVE() {
/*  87 */     return this.WirelessRedstoneSVE;
/*     */   }
/*     */   
/*     */   public ModProxy[] Proxies() {
/*  91 */     return this.Proxies;
/*     */   }
/*     */ 
/*     */ 
/*     */ 
/*     */ 
/*     */ 
/*     */ 
/*     */ 
/*     */ 
/*     */ 
/*     */ 
/*     */ 
/*     */ 
/*     */ 
/*     */ 
/*     */ 
/*     */ 
/*     */ 
/*     */ 
/*     */ 
/*     */ 
/*     */ 
/*     */ 
/*     */ 
/*     */ 
/*     */ 
/*     */ 
/*     */ 
/*     */ 
/*     */ 
/*     */ 
/*     */ 
/*     */ 
/*     */ 
/*     */ 
/*     */ 
/*     */ 
/*     */ 
/*     */ 
/*     */ 
/*     */ 
/*     */ 
/*     */ 
/*     */ 
/*     */ 
/*     */ 
/*     */ 
/*     */ 
/*     */ 
/*     */ 
/*     */ 
/*     */ 
/*     */ 
/*     */ 
/*     */ 
/*     */ 
/*     */ 
/*     */   
/*     */   public void init()
/*     */   {
/* 152 */     scala.Predef$.MODULE$.refArrayOps((Object[])Proxies()).foreach((Function1)new Mods$$anonfun$init$1()); } public final class Mods$$anonfun$init$1 extends AbstractFunction1<ModProxy, BoxedUnit> implements Serializable { public static final long serialVersionUID = 0L; public final void apply(ModProxy proxy) {
/* 153 */       Mods$.MODULE$.li$cil$oc$integration$Mods$$tryInit(proxy);
/*     */     } }
/*     */ 
/*     */ 
/*     */ 
/*     */ 
/*     */ 
/*     */ 
/*     */ 
/*     */ 
/*     */ 
/*     */ 
/*     */ 
/*     */ 
/*     */ 
/*     */ 
/*     */ 
/*     */ 
/*     */ 
/*     */ 
/*     */ 
/*     */ 
/*     */ 
/*     */ 
/*     */ 
/*     */ 
/*     */ 
/*     */ 
/*     */ 
/*     */ 
/*     */ 
/*     */ 
/*     */ 
/*     */ 
/*     */ 
/*     */ 
/*     */ 
/*     */ 
/*     */ 
/*     */ 
/*     */ 
/*     */ 
/*     */ 
/*     */ 
/*     */ 
/*     */ 
/*     */ 
/*     */ 
/*     */ 
/*     */ 
/*     */ 
/*     */ 
/*     */ 
/*     */ 
/*     */ 
/*     */ 
/*     */ 
/*     */ 
/*     */ 
/*     */ 
/*     */   
/*     */   public void li$cil$oc$integration$Mods$$tryInit(ModProxy mod) {
/*     */     // Byte code:
/*     */     //   0: getstatic li/cil/oc/Settings$.MODULE$ : Lli/cil/oc/Settings$;
/*     */     //   3: invokevirtual get : ()Lli/cil/oc/Settings;
/*     */     //   6: invokevirtual modBlacklist : ()Ljava/util/List;
/*     */     //   9: aload_1
/*     */     //   10: invokeinterface getMod : ()Lli/cil/oc/integration/Mod;
/*     */     //   15: invokeinterface id : ()Ljava/lang/String;
/*     */     //   20: invokeinterface contains : (Ljava/lang/Object;)Z
/*     */     //   25: istore_2
/*     */     //   26: aload_1
/*     */     //   27: invokeinterface getMod : ()Lli/cil/oc/integration/Mod;
/*     */     //   32: ifnull -> 68
/*     */     //   35: aload_1
/*     */     //   36: invokeinterface getMod : ()Lli/cil/oc/integration/Mod;
/*     */     //   41: aload_0
/*     */     //   42: invokevirtual Minecraft : ()Lli/cil/oc/integration/Mods$SimpleMod;
/*     */     //   45: astore #4
/*     */     //   47: dup
/*     */     //   48: ifnonnull -> 60
/*     */     //   51: pop
/*     */     //   52: aload #4
/*     */     //   54: ifnull -> 68
/*     */     //   57: goto -> 72
/*     */     //   60: aload #4
/*     */     //   62: invokevirtual equals : (Ljava/lang/Object;)Z
/*     */     //   65: ifeq -> 72
/*     */     //   68: iconst_1
/*     */     //   69: goto -> 73
/*     */     //   72: iconst_0
/*     */     //   73: istore_3
/*     */     //   74: iload_2
/*     */     //   75: ifne -> 262
/*     */     //   78: iload_3
/*     */     //   79: ifne -> 96
/*     */     //   82: aload_1
/*     */     //   83: invokeinterface getMod : ()Lli/cil/oc/integration/Mod;
/*     */     //   88: invokeinterface isModAvailable : ()Z
/*     */     //   93: ifeq -> 262
/*     */     //   96: aload_0
/*     */     //   97: invokespecial handlers : ()Lscala/collection/mutable/Set;
/*     */     //   100: aload_1
/*     */     //   101: invokeinterface add : (Ljava/lang/Object;)Z
/*     */     //   106: ifeq -> 262
/*     */     //   109: getstatic li/cil/oc/OpenComputers$.MODULE$ : Lli/cil/oc/OpenComputers$;
/*     */     //   112: invokevirtual log : ()Lorg/apache/logging/log4j/Logger;
/*     */     //   115: new scala/StringContext
/*     */     //   118: dup
/*     */     //   119: getstatic scala/Predef$.MODULE$ : Lscala/Predef$;
/*     */     //   122: iconst_2
/*     */     //   123: anewarray java/lang/String
/*     */     //   126: dup
/*     */     //   127: iconst_0
/*     */     //   128: ldc_w 'Initializing mod integration for ''
/*     */     //   131: aastore
/*     */     //   132: dup
/*     */     //   133: iconst_1
/*     */     //   134: ldc_w ''.'
/*     */     //   137: aastore
/*     */     //   138: checkcast [Ljava/lang/Object;
/*     */     //   141: invokevirtual wrapRefArray : ([Ljava/lang/Object;)Lscala/collection/mutable/WrappedArray;
/*     */     //   144: invokespecial <init> : (Lscala/collection/Seq;)V
/*     */     //   147: getstatic scala/Predef$.MODULE$ : Lscala/Predef$;
/*     */     //   150: iconst_1
/*     */     //   151: anewarray java/lang/Object
/*     */     //   154: dup
/*     */     //   155: iconst_0
/*     */     //   156: aload_1
/*     */     //   157: invokeinterface getMod : ()Lli/cil/oc/integration/Mod;
/*     */     //   162: invokeinterface id : ()Ljava/lang/String;
/*     */     //   167: aastore
/*     */     //   168: invokevirtual genericWrapArray : (Ljava/lang/Object;)Lscala/collection/mutable/WrappedArray;
/*     */     //   171: invokevirtual s : (Lscala/collection/Seq;)Ljava/lang/String;
/*     */     //   174: invokeinterface debug : (Ljava/lang/String;)V
/*     */     //   179: aload_1
/*     */     //   180: invokeinterface initialize : ()V
/*     */     //   185: goto -> 262
/*     */     //   188: astore #5
/*     */     //   190: getstatic li/cil/oc/OpenComputers$.MODULE$ : Lli/cil/oc/OpenComputers$;
/*     */     //   193: invokevirtual log : ()Lorg/apache/logging/log4j/Logger;
/*     */     //   196: new scala/StringContext
/*     */     //   199: dup
/*     */     //   200: getstatic scala/Predef$.MODULE$ : Lscala/Predef$;
/*     */     //   203: iconst_2
/*     */     //   204: anewarray java/lang/String
/*     */     //   207: dup
/*     */     //   208: iconst_0
/*     */     //   209: ldc_w 'Error initializing integration for ''
/*     */     //   212: aastore
/*     */     //   213: dup
/*     */     //   214: iconst_1
/*     */     //   215: ldc_w '''
/*     */     //   218: aastore
/*     */     //   219: checkcast [Ljava/lang/Object;
/*     */     //   222: invokevirtual wrapRefArray : ([Ljava/lang/Object;)Lscala/collection/mutable/WrappedArray;
/*     */     //   225: invokespecial <init> : (Lscala/collection/Seq;)V
/*     */     //   228: getstatic scala/Predef$.MODULE$ : Lscala/Predef$;
/*     */     //   231: iconst_1
/*     */     //   232: anewarray java/lang/Object
/*     */     //   235: dup
/*     */     //   236: iconst_0
/*     */     //   237: aload_1
/*     */     //   238: invokeinterface getMod : ()Lli/cil/oc/integration/Mod;
/*     */     //   243: invokeinterface id : ()Ljava/lang/String;
/*     */     //   248: aastore
/*     */     //   249: invokevirtual genericWrapArray : (Ljava/lang/Object;)Lscala/collection/mutable/WrappedArray;
/*     */     //   252: invokevirtual s : (Lscala/collection/Seq;)Ljava/lang/String;
/*     */     //   255: aload #5
/*     */     //   257: invokeinterface warn : (Ljava/lang/String;Ljava/lang/Throwable;)V
/*     */     //   262: return
/*     */     // Line number table:
/*     */     //   Java source line number -> byte code offset
/*     */     //   #158	-> 0
/*     */     //   #159	-> 26
/*     */     //   #160	-> 74
/*     */     //   #161	-> 109
/*     */     //   #162	-> 179
/*     */     //   #163	-> 188
/*     */     //   #164	-> 190
/*     */     //   #157	-> 262
/*     */     // Local variable table:
/*     */     //   start	length	slot	name	descriptor
/*     */     //   0	263	0	this	Lli/cil/oc/integration/Mods$;
/*     */     //   0	263	1	mod	Lli/cil/oc/integration/ModProxy;
/*     */     //   26	237	2	isBlacklisted	Z
/*     */     //   74	189	3	alwaysEnabled	Z
/*     */     // Exception table:
/*     */     //   from	to	target	type
/*     */     //   179	188	188	finally
/*     */   }
/*     */ 
/*     */ 
/*     */ 
/*     */ 
/*     */ 
/*     */ 
/*     */ 
/*     */ 
/*     */ 
/*     */ 
/*     */ 
/*     */ 
/*     */ 
/*     */ 
/*     */ 
/*     */ 
/*     */ 
/*     */ 
/*     */ 
/*     */ 
/*     */ 
/*     */ 
/*     */ 
/*     */ 
/*     */ 
/*     */ 
/*     */ 
/*     */ 
/*     */ 
/*     */ 
/*     */ 
/*     */ 
/*     */ 
/*     */ 
/*     */ 
/*     */ 
/*     */ 
/*     */ 
/*     */ 
/*     */ 
/*     */ 
/*     */ 
/*     */ 
/*     */ 
/*     */ 
/*     */ 
/*     */ 
/*     */ 
/*     */ 
/*     */ 
/*     */ 
/*     */ 
/*     */ 
/*     */ 
/*     */ 
/*     */ 
/*     */   
/*     */   private Mods$() {
/* 275 */     MODULE$ = this;
/*     */     this.handlers = scala.collection.mutable.Set$.MODULE$.empty();
/*     */     this.li$cil$oc$integration$Mods$$knownMods = (ArrayBuffer<Mods.ModBase>)scala.collection.mutable.ArrayBuffer$.MODULE$.empty();
/*     */     this.Ae2Fc = new Mods.SimpleMod("ae2fc", Mods.SimpleMod$.MODULE$.$lessinit$greater$default$2());
/*     */     this.AgriCraft = new Mods.SimpleMod("AgriCraft", "@[1.4.0,)");
/*     */     this.AppliedEnergistics2 = new Mods.SimpleMod("appliedenergistics2", "@[rv1,)");
/*     */     this.AvaritiaAddons = new Mods.SimpleMod("avaritiaddons", Mods.SimpleMod$.MODULE$.$lessinit$greater$default$2());
/*     */     this.BattleGear2 = new Mods.SimpleMod("battlegear2", Mods.SimpleMod$.MODULE$.$lessinit$greater$default$2());
/*     */     this.BetterRecords = new Mods.SimpleMod("betterrecords", Mods.SimpleMod$.MODULE$.$lessinit$greater$default$2());
/*     */     this.BloodMagic = new Mods.SimpleMod("AWWayofTime", Mods.SimpleMod$.MODULE$.$lessinit$greater$default$2());
/*     */     this.BluePower = new Mods.SimpleMod("bluepowerAPI", "@[0.2.928,)");
/*     */     this.BuildCraft = new Mods.SimpleMod("BuildCraft|Core", Mods.SimpleMod$.MODULE$.$lessinit$greater$default$2());
/*     */     this.BuildCraftLibrary = new Mods.SimpleMod("BuildCraftAPI|library", "@[7.0.9,)");
/*     */     this.BuildCraftRecipes = new Mods.SimpleMod("BuildCraftAPI|recipes", Mods.SimpleMod$.MODULE$.$lessinit$greater$default$2());
/*     */     this.BuildCraftTiles = new Mods.SimpleMod("BuildCraftAPI|tiles", Mods.SimpleMod$.MODULE$.$lessinit$greater$default$2());
/*     */     this.BuildCraftTools = new Mods.SimpleMod("BuildCraftAPI|tools", Mods.SimpleMod$.MODULE$.$lessinit$greater$default$2());
/*     */     this.BuildCraftTransport = new Mods.SimpleMod("BuildCraftAPI|transport", Mods.SimpleMod$.MODULE$.$lessinit$greater$default$2());
/*     */     this.CoFHEnergy = new Mods.SimpleMod("CoFHAPI|energy", Mods.SimpleMod$.MODULE$.$lessinit$greater$default$2());
/*     */     this.CoFHItem = new Mods.SimpleMod("CoFHAPI|item", Mods.SimpleMod$.MODULE$.$lessinit$greater$default$2());
/*     */     this.CoFHTileEntity = new Mods.SimpleMod("CoFHAPI|tileentity", Mods.SimpleMod$.MODULE$.$lessinit$greater$default$2());
/*     */     this.CoFHTransport = new Mods.SimpleMod("CoFHAPI|transport", Mods.SimpleMod$.MODULE$.$lessinit$greater$default$2());
/*     */     this.ColoredLights = new Mods.SimpleMod("easycoloredlights", Mods.SimpleMod$.MODULE$.$lessinit$greater$default$2());
/*     */     this.ComputerCraft = new Mods.SimpleMod("ComputerCraft", "@[1.73,)");
/*     */     this.CraftingCosts = new Mods.SimpleMod("CraftingCosts", Mods.SimpleMod$.MODULE$.$lessinit$greater$default$2());
/*     */     (new String[1])[0] = "powercrystals.minefactoryreloaded.api.IDeepStorageUnit";
/*     */     this.DeepStorageUnit = new Mods.ClassBasedMod("MineFactoryReloaded|DeepStorageUnit", (Seq<String>)scala.Predef$.MODULE$.wrapRefArray((Object[])new String[1]));
/*     */     this.ElectricalAge = new Mods.SimpleMod("Eln", Mods.SimpleMod$.MODULE$.$lessinit$greater$default$2());
/*     */     this.EnderIO = new Mods.SimpleMod("EnderIO", "@[2.2,)");
/*     */     this.EnderStorage = new Mods.SimpleMod("EnderStorage", Mods.SimpleMod$.MODULE$.$lessinit$greater$default$2());
/*     */     this.ExtraCells = new Mods.SimpleMod("extracells", "@[2.2.73,)");
/*     */     this.Factorization = new Mods.SimpleMod("factorization", Mods.SimpleMod$.MODULE$.$lessinit$greater$default$2());
/*     */     this.Forestry = new Mods.SimpleMod("Forestry", "@[4.0,)");
/*     */     this.ForgeMultipart = new Mods.SimpleMod("ForgeMultipart", Mods.SimpleMod$.MODULE$.$lessinit$greater$default$2());
/*     */     this.Galacticraft = new Mods.SimpleMod("Galacticraft API", Mods.SimpleMod$.MODULE$.$lessinit$greater$default$2());
/*     */     (new String[1])[0] = "gregtech.api.GregTechAPI";
/*     */     this.GregTech = new Mods.ClassBasedMod("gregtech", (Seq<String>)scala.Predef$.MODULE$.wrapRefArray((Object[])new String[1]));
/*     */     this.IndustrialCraft2 = new Mods.SimpleMod("IC2", Mods.SimpleMod$.MODULE$.$lessinit$greater$default$2());
/*     */     this.IndustrialCraft2Classic = new Mods.SimpleMod("IC2-Classic", Mods.SimpleMod$.MODULE$.$lessinit$greater$default$2());
/*     */     this.IngameWiki = new Mods.SimpleMod("IGWMod", "@[1.1.3,)");
/*     */     this.Mekanism = new Mods.SimpleMod("Mekanism", Mods.SimpleMod$.MODULE$.$lessinit$greater$default$2());
/*     */     this.MekanismGas = new Mods.SimpleMod("MekanismAPI|gas", Mods.SimpleMod$.MODULE$.$lessinit$greater$default$2());
/*     */     this.Minecraft = new Mods.SimpleMod("Minecraft", Mods.SimpleMod$.MODULE$.$lessinit$greater$default$2());
/*     */     this.MineFactoryReloaded = new Mods.SimpleMod("MineFactoryReloaded", Mods.SimpleMod$.MODULE$.$lessinit$greater$default$2());
/*     */     this.Mystcraft = new Mods.SimpleMod("Mystcraft", Mods.SimpleMod$.MODULE$.$lessinit$greater$default$2());
/*     */     this.NotEnoughItems = new Mods.SimpleMod("NotEnoughItems", Mods.SimpleMod$.MODULE$.$lessinit$greater$default$2());
/*     */     this.NotEnoughKeys = new Mods.SimpleMod("notenoughkeys", Mods.SimpleMod$.MODULE$.$lessinit$greater$default$2());
/*     */     this.OpenComputers = new Mods.SimpleMod("OpenComputers", Mods.SimpleMod$.MODULE$.$lessinit$greater$default$2());
/*     */     this.PortalGun = new Mods.SimpleMod("PortalGun", Mods.SimpleMod$.MODULE$.$lessinit$greater$default$2());
/*     */     this.ProjectRedCore = new Mods.SimpleMod("ProjRed|Core", Mods.SimpleMod$.MODULE$.$lessinit$greater$default$2());
/*     */     this.ProjectRedTransmission = new Mods.SimpleMod("ProjRed|Transmission", Mods.SimpleMod$.MODULE$.$lessinit$greater$default$2());
/*     */     this.Railcraft = new Mods.SimpleMod("Railcraft", Mods.SimpleMod$.MODULE$.$lessinit$greater$default$2());
/*     */     this.RedLogic = new Mods.SimpleMod("RedLogic", Mods.SimpleMod$.MODULE$.$lessinit$greater$default$2());
/*     */     this.RotaryCraft = new Mods.SimpleMod("RotaryCraft", Mods.SimpleMod$.MODULE$.$lessinit$greater$default$2());
/*     */     this.StargateTech2 = new Mods$$anon$1();
/*     */     this.Thaumcraft = new Mods.SimpleMod("Thaumcraft", Mods.SimpleMod$.MODULE$.$lessinit$greater$default$2());
/*     */     this.ThaumicEnergistics = new Mods.SimpleMod("thaumicenergistics", Mods.SimpleMod$.MODULE$.$lessinit$greater$default$2());
/*     */     this.ThermalExpansion = new Mods.SimpleMod("ThermalExpansion", Mods.SimpleMod$.MODULE$.$lessinit$greater$default$2());
/*     */     this.TinkersConstruct = new Mods.SimpleMod("TConstruct", Mods.SimpleMod$.MODULE$.$lessinit$greater$default$2());
/*     */     this.TIS3D = new Mods.SimpleMod("tis3d", "@[0.7,)");
/*     */     this.TMechWorks = new Mods.SimpleMod("TMechworks", Mods.SimpleMod$.MODULE$.$lessinit$greater$default$2());
/*     */     this.VersionChecker = new Mods.SimpleMod("VersionChecker", Mods.SimpleMod$.MODULE$.$lessinit$greater$default$2());
/*     */     this.Waila = new Mods.SimpleMod("Waila", Mods.SimpleMod$.MODULE$.$lessinit$greater$default$2());
/*     */     this.WirelessRedstoneCBE = new Mods.SimpleMod("WR-CBE|Core", Mods.SimpleMod$.MODULE$.$lessinit$greater$default$2());
/*     */     this.WirelessRedstoneSVE = new Mods.SimpleMod("WirelessRedstoneCore", Mods.SimpleMod$.MODULE$.$lessinit$greater$default$2());
/*     */     (new ModProxy[48])[0] = (ModProxy)ModAgriCraft$.MODULE$;
/*     */     (new ModProxy[48])[1] = (ModProxy)ModAe2fc$.MODULE$;
/*     */     (new ModProxy[48])[2] = (ModProxy)ModAppEng$.MODULE$;
/*     */     (new ModProxy[48])[3] = (ModProxy)ModAvaritiaAddons$.MODULE$;
/*     */     (new ModProxy[48])[4] = (ModProxy)ModBetterRecords$.MODULE$;
/*     */     (new ModProxy[48])[5] = (ModProxy)ModBloodMagic$.MODULE$;
/*     */     (new ModProxy[48])[6] = (ModProxy)ModBluePower$.MODULE$;
/*     */     (new ModProxy[48])[7] = (ModProxy)ModBuildCraftAPILibrary$.MODULE$;
/*     */     (new ModProxy[48])[8] = (ModProxy)ModBuildCraftRecipes$.MODULE$;
/*     */     (new ModProxy[48])[9] = (ModProxy)ModBuildCraftAPITools$.MODULE$;
/*     */     (new ModProxy[48])[10] = (ModProxy)ModBuildCraftAPITiles$.MODULE$;
/*     */     (new ModProxy[48])[11] = (ModProxy)ModBuildCraftAPITransport$.MODULE$;
/*     */     (new ModProxy[48])[12] = (ModProxy)ModCoFHEnergy$.MODULE$;
/*     */     (new ModProxy[48])[13] = (ModProxy)ModCoFHItem$.MODULE$;
/*     */     (new ModProxy[48])[14] = (ModProxy)ModCoFHTileEntity$.MODULE$;
/*     */     (new ModProxy[48])[15] = (ModProxy)ModCoFHTransport$.MODULE$;
/*     */     (new ModProxy[48])[16] = (ModProxy)ModExtraCells$.MODULE$;
/*     */     (new ModProxy[48])[17] = (ModProxy)ModEnderIO$.MODULE$;
/*     */     (new ModProxy[48])[18] = (ModProxy)ModEnderStorage$.MODULE$;
/*     */     (new ModProxy[48])[19] = (ModProxy)ModDeepStorageUnit$.MODULE$;
/*     */     (new ModProxy[48])[20] = (ModProxy)ModForestry$.MODULE$;
/*     */     (new ModProxy[48])[21] = (ModProxy)ModForgeMultipart$.MODULE$;
/*     */     (new ModProxy[48])[22] = (ModProxy)ModGalacticraft$.MODULE$;
/*     */     (new ModProxy[48])[23] = (ModProxy)ModGregtech$.MODULE$;
/*     */     (new ModProxy[48])[24] = (ModProxy)ModIndustrialCraft2$.MODULE$;
/*     */     (new ModProxy[48])[25] = (ModProxy)ModMekanism$.MODULE$;
/*     */     (new ModProxy[48])[26] = (ModProxy)ModMekanismGas$.MODULE$;
/*     */     (new ModProxy[48])[27] = (ModProxy)ModMineFactoryReloaded$.MODULE$;
/*     */     (new ModProxy[48])[28] = (ModProxy)ModMystcraft$.MODULE$;
/*     */     (new ModProxy[48])[29] = (ModProxy)ModNotEnoughKeys$.MODULE$;
/*     */     (new ModProxy[48])[30] = (ModProxy)ModProjectRed$.MODULE$;
/*     */     (new ModProxy[48])[31] = (ModProxy)ModRailcraft$.MODULE$;
/*     */     (new ModProxy[48])[32] = (ModProxy)ModRedLogic$.MODULE$;
/*     */     (new ModProxy[48])[33] = (ModProxy)ModRotaryCraft$.MODULE$;
/*     */     (new ModProxy[48])[34] = (ModProxy)ModStargateTech2$.MODULE$;
/*     */     (new ModProxy[48])[35] = (ModProxy)ModThaumcraft$.MODULE$;
/*     */     (new ModProxy[48])[36] = (ModProxy)ModThaumicEnergistics$.MODULE$;
/*     */     (new ModProxy[48])[37] = (ModProxy)ModThermalExpansion$.MODULE$;
/*     */     (new ModProxy[48])[38] = (ModProxy)ModTinkersConstruct$.MODULE$;
/*     */     (new ModProxy[48])[39] = (ModProxy)ModTIS3D$.MODULE$;
/*     */     (new ModProxy[48])[40] = (ModProxy)ModTMechworks$.MODULE$;
/*     */     (new ModProxy[48])[41] = (ModProxy)ModVanilla$.MODULE$;
/*     */     (new ModProxy[48])[42] = (ModProxy)ModWaila$.MODULE$;
/*     */     (new ModProxy[48])[43] = (ModProxy)ModWRCBE$.MODULE$;
/*     */     (new ModProxy[48])[44] = (ModProxy)ModWRSVE$.MODULE$;
/*     */     (new ModProxy[48])[45] = (ModProxy)ModComputerCraft$.MODULE$;
/*     */     (new ModProxy[48])[46] = (ModProxy)ModOpenComputers$.MODULE$;
/*     */     (new ModProxy[48])[47] = (ModProxy)ModIngameWiki$.MODULE$;
/*     */     this.Proxies = new ModProxy[48];
/*     */   } }


/* Location:              C:\Users\shame\AppData\Roaming\PrismLauncher\instances\GT_New_Horizons_2.7.4_Java_17-21\.minecraft\mods\OpenComputers-1.10.30-GTNH.jar!\li\cil\oc\integration\Mods$.class
 * Java compiler version: 8 (52.0)
 * JD-Core Version:       1.1.3
 */