/*     */ package li.cil.oc.server.component.traits;@ScalaSignature(bytes = "\006\001\005\035eaB\001\003!\003\r\ta\004\002\030/>\024H\016Z%om\026tGo\034:z\003:\fG.\037;jGNT!a\001\003\002\rQ\024\030-\033;t\025\t)a!A\005d_6\004xN\\3oi*\021q\001C\001\007g\026\024h/\032:\013\005%Q\021AA8d\025\tYA\"A\002dS2T\021!D\001\003Y&\034\001aE\003\001!YQR\004\005\002\022)5\t!CC\001\024\003\025\0318-\0317b\023\t)\"C\001\004B]f\024VM\032\t\003/ai\021AA\005\0033\t\021!bV8sY\022\fu/\031:f!\t92$\003\002\035\005\tq1+\0333f%\026\034HO]5di\026$\007CA\f\037\023\ty\"A\001\007OKR<xN]6Bo\006\024X\rC\003\"\001\021\005!%\001\004%S:LG\017\n\013\002GA\021\021\003J\005\003KI\021A!\0268ji\")q\005\001C\001Q\005\001r-\032;J]Z,g\016^8ssNK'0\032\013\004S12\004cA\t+!%\0211F\005\002\006\003J\024\030-\037\005\006[\031\002\rAL\001\bG>tG/\032=u!\tyC'D\0011\025\t\t$'A\004nC\016D\027N\\3\013\005MB\021aA1qS&\021Q\007\r\002\b\007>tG/\032=u\021\0259d\0051\0019\003\021\t'oZ:\021\005=J\024B\001\0361\005%\t%oZ;nK:$8\017\013\003'y}\002\005CA\030>\023\tq\004G\001\005DC2d'-Y2l\003\r!wnY\021\002\003\006ig-\0368di&|g\016K:jI\026Td.^7cKJL#H\\;nE\026\024\b%L\027!\017\026$\b\005\0365fA9,XNY3sA=4\007e\0357piN\004\023N\034\021uQ\026\004\023N\034<f]R|'/\037\021p]\002\"\b.\032\021ta\026\034\027NZ5fI\002\032\030\016Z3!_\032\004C\017[3!I\0264\030nY3/\021\025\031\005\001\"\001E\003A9W\r^*m_R\034F/Y2l'&TX\rF\002*\013\032CQ!\f\"A\0029BQa\016\"A\002aBCA\021\037@\021\006\n\021*AA\rMVt7\r^5p]\"\032\030\016Z3;]Vl'-\032:-AMdw\016\036\036ok6\024WM]\025;]Vl'-\032:![5\002s)\032;!]Vl'-\032:!_\032\004\023\016^3ng\002Jg\016\t;iK\002\032\b/Z2jM&,G\rI:m_R\004sN\032\021uQ\026\004\023N\034<f]R|'/\037\021p]\002\"\b.\032\021ta\026\034\027NZ5fI\002\032\030\016Z3!_\032\004C\017[3!I\0264\030nY3/\021\025Y\005\001\"\001M\003M9W\r^*m_Rl\025\r_*uC\016\\7+\033>f)\rISJ\024\005\006[)\003\rA\f\005\006o)\003\r\001\017\025\005\025rz\004+I\001R\003\005Eb-\0368di&|g\016K:jI\026Td.^7cKJd\003e\0357pijrW/\0342fe&Rd.^7cKJ\004S&\f\021HKR\004C\017[3![\006D\030.\\;nA9,XNY3sA=4\007%\033;f[N\004\023N\034\021uQ\026\0043\017]3dS\032LW\r\032\021tY>$\be\0344!i\",\007%\0338wK:$xN]=!_:\004C\017[3!gB,7-\0334jK\022\0043/\0333fA=4\007\005\0365fA\021,g/[2f]!)1\013\001C\001)\006i1m\\7qCJ,7\013^1dWN$2!K+W\021\025i#\0131\001/\021\0259$\0131\0019Q\021\021Fh\020-\"\003e\013\021Q\0254v]\016$\030n\0348)g&$WM\0178v[\n,'\017\f\021tY>$\030I\0178v[\n,'\017\f\021tY>$(I\0178v[\n,'o\027\027!G\",7m\033(C)j\022wn\0347fC:ld-\0317tKvK#HY8pY\026\fg\016I\027.A\035+G\017I<iKRDWM\035\021uQ\026\004\023\016^3ng\002Jg\016\t;iK\002\"xo\034\021ta\026\034\027NZ5fI\002\032Hn\034;tA=4\007\005\0365fA%tg/\0328u_JL\be\0348!i\",\007e\0359fG&4\027.\0323!g&$W\rI8gAQDW\r\t3fm&\034W\rI1sK\002zg\r\t;iK\002\032\030-\\3!if\004XM\f\005\0067\002!\t\001X\001\027G>l\007/\031:f'R\f7m\033+p\t\006$\030MY1tKR\031\021&\0300\t\0135R\006\031\001\030\t\013]R\006\031\001\035)\tict\bY\021\002C\006\t)NZ;oGRLwN\034\025tS\022,'H\\;nE\026\024H\006I:m_RTd.^7cKJd\003\005\0322BI\022\024Xm]:;gR\024\030N\\4-A\021\0247\013\\8uu9,XNY3s72\0023\r[3dW:\023EK\0172p_2,\027M\\\037gC2\034X-X\025;E>|G.Z1oA5j\003eQ8na\006\024X\rI1oA%$X-\034\021j]\002\"\b.\032\021ta\026\034\027NZ5fI\002\032Hn\034;!S:\004C\017[3!S:4XM\034;pef\004sN\034\021uQ\026\0043\017]3dS\032LW\r\032\021tS\022,\007e^5uQ\002zg.\032\021j]\002\"\b.\032\021eCR\f'-Y:fA]LG\017\033\021uQ\026\0043\017]3dS\032LW\r\032\021bI\022\024Xm]:/\021\025\031\007\001\"\001e\003M\t'/Z*uC\016\\7/R9vSZ\fG.\0328u)\rISM\032\005\006[\t\004\rA\f\005\006o\t\004\r\001\017\025\005Erz\004.I\001j\003\005\025f-\0368di&|g\016K:jI\026Td.^7cKJd\003e\0357pi\006Sd.^7cKJd\003e\0357pi\nSd.^7cKJL#HY8pY\026\fg\016I\027.A\035+G\017I<iKRDWM\035\021uQ\026\004\023\016^3ng\002Jg\016\t;iK\002\"xo\034\021ta\026\034\027NZ5fI\002\032Hn\034;tA=4\007\005\0365fA%tg/\0328u_JL\be\0348!i\",\007e\0359fG&4\027.\0323!g&$W\rI8gAQDW\r\t3fm&\034W\rI1sK\002*\027/^5wC2,g\016\036\021)Q\0064X\rI:iCJ,G\rI(sK\022K7\r^5p]\006\024\030\020I%Eg&r\003\"B6\001\t\003a\027aE:fiN#\030mY6ESN\004H.Y=OC6,GcA\025n]\")QF\033a\001]!)qG\033a\001q!\"!\016P qC\005\t\030!!\fgk:\034G/[8oQMLG-\032\036ok6\024WM\035\027!g2|GO\0178v[\n,'\017\f\021mC\n,GNO:ue&tw-\013\036c_>dW-\0318![5\0023\t[1oO\026\004C\017[3!I&\034\b\017\\1zA9\fW.\032\021pM\002\"\b.\032\021ti\006\0347\016I5oAQDW\rI5om\026tGo\034:zA=t\007\005\0365fAM\004XmY5gS\026$\007e]5eK\002zg\r\t;iK\002\"WM^5dK:BQa\035\001\005\002Q\fabZ3u'R\f7m[%o'2|G\017F\002*kZDQ!\f:A\0029BQa\016:A\002aBCA\035\037@q\006\n\0210AA\001MVt7\r^5p]\"\032\030\016Z3;]Vl'-\032:-AMdw\016\036\036ok6\024WM]\025;i\006\024G.\032\021.[\001:U\r\036\021bA\021,7o\031:jaRLwN\034\021pM\002\"\b.\032\021ti\006\0347\016I5oAQDW\rI5om\026tGo\034:zA=t\007\005\0365fAM\004XmY5gS\026$\007e]5eK\002zg\r\t;iK\002\"WM^5dK:BQa\037\001\005\002q\fAbZ3u\0032d7\013^1dWN$2!K?\021\025i#\0201\001/\021\0259$\0201\0019Q\025QHhPA\001C\t\t\031!A<gk:\034G/[8oQMLG-\032\036ok6\024WM]\025;kN,'\017Z1uC\002jS\006I$fi\002\n\007\005Z3tGJL\007\017^5p]\002zg\rI1mY\002\032H/Y2lg\002Jg\016\t;iK\002JgN^3oi>\024\030\020I8oAQDW\rI:qK\016Lg-[3eAMLG-\032\021pM\002\"\b.\032\021eKZL7-\032\030\t\017\005\035\001\001\"\001\002\n\005\001r-\032;J]Z,g\016^8ss:\013W.\032\013\006S\005-\021Q\002\005\007[\005\025\001\031\001\030\t\r]\n)\0011\0019Q\031\t)\001P \002\022\005\022\0211C\001gMVt7\r^5p]\"\032\030\016Z3;]Vl'-\032:*uM$(/\0338hA5j\003eR3uAQDW\r\t;iK\002r\027-\\3!_\032\004C\017[3!S:4XM\034;pef\004sN\034\021uQ\026\0043\017]3dS\032LW\r\032\021tS\022,\007e\0344!i\",\007\005Z3wS\016,g\006C\004\002\030\001!\t!!\007\002\013M$xN]3\025\013%\nY\"!\b\t\r5\n)\0021\001/\021\0319\024Q\003a\001q!2\021Q\003\037@\003C\t#!a\t\002\003C2WO\\2uS>t\007f]5eKjrW/\0342fe2\0023\017\\8uu9,XNY3sY\001\"'-\0213ee\026\0348OO:ue&tw\r\f\021eENcw\016\036\036ok6\024WM]\025;E>|G.Z1oA5j\003e\025;pe\026\004\023M\034\021ji\026l\007e\035;bG.\004C-Z:de&\004H/[8oA%t\007\005\0365fAM\004XmY5gS\026$\007e\0357pi\002zg\r\t;iK\002\"\027\r^1cCN,\007e^5uQ\002\"\b.\032\021ta\026\034\027NZ5fI\002\nG\r\032:fgNt\003bBA\024\001\021%\021\021F\001\f[\006L\030J\034;fe\006\034G\017\006\004\002,\005E\022Q\n\t\004#\0055\022bAA\030%\t9!i\\8mK\006t\007\002CA\032\003K\001\r!!\016\002\tMLG-\032\t\005\003o\tI%\004\002\002:)!\0211HA\037\003\021)H/\0337\013\t\005}\022\021I\001\007G>lWn\0348\013\t\005\r\023QI\001\017[&tWm\031:bMR4wN]4f\025\t\t9%A\002oKRLA!a\023\002:\tqai\034:hK\022K'/Z2uS>t\007\002CA(\003K\001\r!!\025\002\003\031\004B!a\025\002X5\021\021Q\013\006\004\003wA\021\002BA-\003+\022q\"\0238wK:$xN]=T_V\0248-\032\005\b\003;\002A\021BA0\003M9\030\016\0365J]Z,g\016^8ssN{WO]2f)\025I\023\021MA2\021!\t\031$a\027A\002\005U\002\002CA(\0037\002\r!!\032\021\rE\t9'!\025*\023\r\tIG\005\002\n\rVt7\r^5p]FBq!!\034\001\t\023\ty'A\007xSRD\027J\034<f]R|'/\037\013\006S\005E\0241\017\005\t\003g\tY\0071\001\0026!A\021qJA6\001\004\t)\b\005\004\022\003O\n9(\013\t\005\003s\n\031)\004\002\002|)!\021QPA@\003%IgN^3oi>\024\030P\003\003\002\002\006\025\023!C7j]\026\034'/\0314u\023\021\t))a\037\003\025%KeN^3oi>\024\030\020")
/*     */ public interface WorldInventoryAnalytics extends WorldAware, SideRestricted, NetworkAware { @Callback(doc = "function(side:number):number -- Get the number of slots in the inventory on the specified side of the device.")
/*     */   Object[] getInventorySize(Context paramContext, Arguments paramArguments); @Callback(doc = "function(side:number, slot:number):number -- Get number of items in the specified slot of the inventory on the specified side of the device.")
/*     */   Object[] getSlotStackSize(Context paramContext, Arguments paramArguments); @Callback(doc = "function(side:number, slot:number):number -- Get the maximum number of items in the specified slot of the inventory on the specified side of the device.")
/*     */   Object[] getSlotMaxStackSize(Context paramContext, Arguments paramArguments);
/*     */   @Callback(doc = "function(side:number, slotA:number, slotB:number[, checkNBT:boolean=false]):boolean -- Get whether the items in the two specified slots of the inventory on the specified side of the device are of the same type.")
/*     */   Object[] compareStacks(Context paramContext, Arguments paramArguments);
/*     */   @Callback(doc = "function(side:number, slot:number, dbAddress:string, dbSlot:number[, checkNBT:boolean=false]):boolean -- Compare an item in the specified slot in the inventory on the specified side with one in the database with the specified address.")
/*     */   Object[] compareStackToDatabase(Context paramContext, Arguments paramArguments);
/*     */   @Callback(doc = "function(side:number, slotA:number, slotB:number):boolean -- Get whether the items in the two specified slots of the inventory on the specified side of the device are equivalent (have shared OreDictionary IDs).")
/*     */   Object[] areStacksEquivalent(Context paramContext, Arguments paramArguments);
/*     */   @Callback(doc = "function(side:number, slot:number, label:string):boolean -- Change the display name of the stack in the inventory on the specified side of the device.")
/*     */   Object[] setStackDisplayName(Context paramContext, Arguments paramArguments);
/*     */   @Callback(doc = "function(side:number, slot:number):table -- Get a description of the stack in the inventory on the specified side of the device.")
/*     */   Object[] getStackInSlot(Context paramContext, Arguments paramArguments);
/*     */   @Callback(doc = "function(side:number):userdata -- Get a description of all stacks in the inventory on the specified side of the device.")
/*     */   Object[] getAllStacks(Context paramContext, Arguments paramArguments);
/*     */   @Callback(doc = "function(side:number):string -- Get the the name of the inventory on the specified side of the device.")
/*     */   Object[] getInventoryName(Context paramContext, Arguments paramArguments);
/*     */   @Callback(doc = "function(side:number, slot:number, dbAddress:string, dbSlot:number):boolean -- Store an item stack description in the specified slot of the database with the specified address.")
/*     */   Object[] store(Context paramContext, Arguments paramArguments);
/*     */   public final class WorldInventoryAnalytics$$anonfun$getInventorySize$1 extends AbstractFunction1<IInventory, Object[]> implements Serializable { public final Object[] apply(IInventory inventory) {
/*  23 */       return package$.MODULE$.result((Seq)Predef$.MODULE$.genericWrapArray(new Object[] { BoxesRunTime.boxToInteger(inventory.func_70302_i_()) }));
/*     */     }
/*     */     public static final long serialVersionUID = 0L;
/*     */     public WorldInventoryAnalytics$$anonfun$getInventorySize$1(WorldInventoryAnalytics $outer) {} }
/*     */   public final class WorldInventoryAnalytics$$anonfun$getSlotStackSize$1 extends AbstractFunction1<IInventory, Object[]> implements Serializable { public static final long serialVersionUID = 0L; private final Arguments args$1;
/*     */     public final Object[] apply(IInventory inventory) {
/*  29 */       return package$.MODULE$.result((Seq)Predef$.MODULE$.genericWrapArray(new Object[] { Option$.MODULE$.apply(inventory.func_70301_a(ExtendedArguments$.MODULE$.extendedArguments(this.args$1).checkSlot(inventory, 1))).fold((Function0)new WorldInventoryAnalytics$$anonfun$getSlotStackSize$1$$anonfun$apply$1(this), (Function1)new WorldInventoryAnalytics$$anonfun$getSlotStackSize$1$$anonfun$apply$4(this)) })); } public WorldInventoryAnalytics$$anonfun$getSlotStackSize$1(WorldInventoryAnalytics $outer, Arguments args$1) {} public final class WorldInventoryAnalytics$$anonfun$getSlotStackSize$1$$anonfun$apply$1 extends AbstractFunction0.mcI.sp implements Serializable { public static final long serialVersionUID = 0L; public final int apply() { return apply$mcI$sp(); } public int apply$mcI$sp() { return 0; } public WorldInventoryAnalytics$$anonfun$getSlotStackSize$1$$anonfun$apply$1(WorldInventoryAnalytics$$anonfun$getSlotStackSize$1 $outer) {} } public final class WorldInventoryAnalytics$$anonfun$getSlotStackSize$1$$anonfun$apply$4 extends AbstractFunction1<ItemStack, Object> implements Serializable { public static final long serialVersionUID = 0L; public final int apply(ItemStack x$1) { return x$1.field_77994_a; }
/*     */       
/*     */       public WorldInventoryAnalytics$$anonfun$getSlotStackSize$1$$anonfun$apply$4(WorldInventoryAnalytics$$anonfun$getSlotStackSize$1 $outer) {} } }
/*     */   public final class WorldInventoryAnalytics$$anonfun$getSlotMaxStackSize$1 extends AbstractFunction1<IInventory, Object[]> implements Serializable { public static final long serialVersionUID = 0L;
/*     */     private final Arguments args$2;
/*     */     
/*  35 */     public final Object[] apply(IInventory inventory) { return package$.MODULE$.result((Seq)Predef$.MODULE$.genericWrapArray(new Object[] { Option$.MODULE$.apply(inventory.func_70301_a(ExtendedArguments$.MODULE$.extendedArguments(this.args$2).checkSlot(inventory, 1))).fold((Function0)new WorldInventoryAnalytics$$anonfun$getSlotMaxStackSize$1$$anonfun$apply$2(this), (Function1)new WorldInventoryAnalytics$$anonfun$getSlotMaxStackSize$1$$anonfun$apply$5(this)) })); } public WorldInventoryAnalytics$$anonfun$getSlotMaxStackSize$1(WorldInventoryAnalytics $outer, Arguments args$2) {} public final class WorldInventoryAnalytics$$anonfun$getSlotMaxStackSize$1$$anonfun$apply$2 extends AbstractFunction0.mcI.sp implements Serializable { public static final long serialVersionUID = 0L; public final int apply() { return apply$mcI$sp(); } public int apply$mcI$sp() { return 0; } public WorldInventoryAnalytics$$anonfun$getSlotMaxStackSize$1$$anonfun$apply$2(WorldInventoryAnalytics$$anonfun$getSlotMaxStackSize$1 $outer) {} } public final class WorldInventoryAnalytics$$anonfun$getSlotMaxStackSize$1$$anonfun$apply$5 extends AbstractFunction1<ItemStack, Object> implements Serializable { public static final long serialVersionUID = 0L; public final int apply(ItemStack x$2) { return x$2.func_77976_d(); }
/*     */       
/*     */       public WorldInventoryAnalytics$$anonfun$getSlotMaxStackSize$1$$anonfun$apply$5(WorldInventoryAnalytics$$anonfun$getSlotMaxStackSize$1 $outer) {} } }
/*     */   public final class WorldInventoryAnalytics$$anonfun$compareStacks$1 extends AbstractFunction1<IInventory, Object[]> implements Serializable { public static final long serialVersionUID = 0L; private final Arguments args$3;
/*     */     public WorldInventoryAnalytics$$anonfun$compareStacks$1(WorldInventoryAnalytics $outer, Arguments args$3) {}
/*     */     
/*     */     public final Object[] apply(IInventory inventory) {
/*  42 */       ItemStack stackA = inventory.func_70301_a(ExtendedArguments$.MODULE$.extendedArguments(this.args$3).checkSlot(inventory, 1));
/*  43 */       ItemStack stackB = inventory.func_70301_a(ExtendedArguments$.MODULE$.extendedArguments(this.args$3).checkSlot(inventory, 2));
/*  44 */       ItemStack itemStack1 = stackB; if (stackA == null) { if (itemStack1 != null) { if (InventoryUtils$.MODULE$.haveSameItemType(stackA, stackB, this.args$3.optBoolean(3, false))); false[stackA] = BoxesRunTime.boxToBoolean(false); return Predef$.MODULE$.result((Seq)(new Object[1]).genericWrapArray(new Object[1])); }  } else if (!stackA.equals(itemStack1)) { if (InventoryUtils$.MODULE$.haveSameItemType(stackA, stackB, this.args$3.optBoolean(3, false))); false[stackA] = BoxesRunTime.boxToBoolean(false); return Predef$.MODULE$.result((Seq)(new Object[1]).genericWrapArray(new Object[1])); }
/*     */     
/*     */     } }
/*     */   public final class WorldInventoryAnalytics$$anonfun$compareStackToDatabase$1 extends AbstractFunction1<IInventory, Object[]> implements Serializable { public static final long serialVersionUID = 0L;
/*     */     public final Arguments args$4;
/*     */     
/*     */     public WorldInventoryAnalytics$$anonfun$compareStackToDatabase$1(WorldInventoryAnalytics $outer, Arguments args$4) {}
/*     */     
/*  52 */     public final Object[] apply(IInventory inventory) { int slot = ExtendedArguments$.MODULE$.extendedArguments(this.args$4).checkSlot(inventory, 1);
/*  53 */       String dbAddress = this.args$4.checkString(2);
/*  54 */       ItemStack stack = inventory.func_70301_a(slot);
/*  55 */       return DatabaseAccess$.MODULE$.withDatabase(this.$outer.node(), dbAddress, (Function1)new WorldInventoryAnalytics$$anonfun$compareStackToDatabase$1$$anonfun$apply$6(this, stack)); } public final class WorldInventoryAnalytics$$anonfun$compareStackToDatabase$1$$anonfun$apply$6 extends AbstractFunction1<UpgradeDatabase, Object[]> implements Serializable { public static final long serialVersionUID = 0L; private final ItemStack stack$1; public WorldInventoryAnalytics$$anonfun$compareStackToDatabase$1$$anonfun$apply$6(WorldInventoryAnalytics$$anonfun$compareStackToDatabase$1 $outer, ItemStack stack$1) {} public final Object[] apply(UpgradeDatabase database) {
/*  56 */         int dbSlot = ExtendedArguments$.MODULE$.extendedArguments(this.$outer.args$4).checkSlot(database.data(), 3);
/*  57 */         ItemStack dbStack = database.getStackInSlot(dbSlot);
/*  58 */         return package$.MODULE$.result((Seq)Predef$.MODULE$.genericWrapArray(new Object[] { BoxesRunTime.boxToBoolean(InventoryUtils$.MODULE$.haveSameItemType(this.stack$1, dbStack, this.$outer.args$4.optBoolean(4, false))) }));
/*     */       } }
/*     */      }
/*     */   
/*     */   public final class WorldInventoryAnalytics$$anonfun$areStacksEquivalent$1 extends AbstractFunction1<IInventory, Object[]> implements Serializable {
/*     */     public static final long serialVersionUID = 0L;
/*     */     private final Arguments args$5;
/*     */     
/*     */     public WorldInventoryAnalytics$$anonfun$areStacksEquivalent$1(WorldInventoryAnalytics $outer, Arguments args$5) {}
/*     */     
/*     */     public final Object[] apply(IInventory inventory) {
/*     */       // Byte code:
/*     */       //   0: aload_1
/*     */       //   1: getstatic li/cil/oc/util/ExtendedArguments$.MODULE$ : Lli/cil/oc/util/ExtendedArguments$;
/*     */       //   4: aload_0
/*     */       //   5: getfield args$5 : Lli/cil/oc/api/machine/Arguments;
/*     */       //   8: invokevirtual extendedArguments : (Lli/cil/oc/api/machine/Arguments;)Lli/cil/oc/util/ExtendedArguments$ExtendedArguments;
/*     */       //   11: aload_1
/*     */       //   12: iconst_1
/*     */       //   13: invokevirtual checkSlot : (Lnet/minecraft/inventory/IInventory;I)I
/*     */       //   16: invokeinterface func_70301_a : (I)Lnet/minecraft/item/ItemStack;
/*     */       //   21: astore_2
/*     */       //   22: aload_1
/*     */       //   23: getstatic li/cil/oc/util/ExtendedArguments$.MODULE$ : Lli/cil/oc/util/ExtendedArguments$;
/*     */       //   26: aload_0
/*     */       //   27: getfield args$5 : Lli/cil/oc/api/machine/Arguments;
/*     */       //   30: invokevirtual extendedArguments : (Lli/cil/oc/api/machine/Arguments;)Lli/cil/oc/util/ExtendedArguments$ExtendedArguments;
/*     */       //   33: aload_1
/*     */       //   34: iconst_2
/*     */       //   35: invokevirtual checkSlot : (Lnet/minecraft/inventory/IInventory;I)I
/*     */       //   38: invokeinterface func_70301_a : (I)Lnet/minecraft/item/ItemStack;
/*     */       //   43: astore_3
/*     */       //   44: getstatic li/cil/oc/server/component/package$.MODULE$ : Lli/cil/oc/server/component/package$;
/*     */       //   47: getstatic scala/Predef$.MODULE$ : Lscala/Predef$;
/*     */       //   50: iconst_1
/*     */       //   51: anewarray java/lang/Object
/*     */       //   54: dup
/*     */       //   55: iconst_0
/*     */       //   56: aload_2
/*     */       //   57: aload_3
/*     */       //   58: astore #4
/*     */       //   60: dup
/*     */       //   61: ifnonnull -> 73
/*     */       //   64: pop
/*     */       //   65: aload #4
/*     */       //   67: ifnull -> 131
/*     */       //   70: goto -> 81
/*     */       //   73: aload #4
/*     */       //   75: invokevirtual equals : (Ljava/lang/Object;)Z
/*     */       //   78: ifne -> 131
/*     */       //   81: aload_2
/*     */       //   82: ifnull -> 135
/*     */       //   85: aload_3
/*     */       //   86: ifnull -> 135
/*     */       //   89: getstatic scala/Predef$.MODULE$ : Lscala/Predef$;
/*     */       //   92: getstatic scala/Predef$.MODULE$ : Lscala/Predef$;
/*     */       //   95: aload_2
/*     */       //   96: invokestatic getOreIDs : (Lnet/minecraft/item/ItemStack;)[I
/*     */       //   99: invokevirtual intArrayOps : ([I)Lscala/collection/mutable/ArrayOps;
/*     */       //   102: getstatic scala/Predef$.MODULE$ : Lscala/Predef$;
/*     */       //   105: aload_3
/*     */       //   106: invokestatic getOreIDs : (Lnet/minecraft/item/ItemStack;)[I
/*     */       //   109: invokevirtual wrapIntArray : ([I)Lscala/collection/mutable/WrappedArray;
/*     */       //   112: invokeinterface intersect : (Lscala/collection/GenSeq;)Ljava/lang/Object;
/*     */       //   117: checkcast [I
/*     */       //   120: invokevirtual intArrayOps : ([I)Lscala/collection/mutable/ArrayOps;
/*     */       //   123: invokeinterface nonEmpty : ()Z
/*     */       //   128: ifeq -> 135
/*     */       //   131: iconst_1
/*     */       //   132: goto -> 136
/*     */       //   135: iconst_0
/*     */       //   136: invokestatic boxToBoolean : (Z)Ljava/lang/Boolean;
/*     */       //   139: aastore
/*     */       //   140: invokevirtual genericWrapArray : (Ljava/lang/Object;)Lscala/collection/mutable/WrappedArray;
/*     */       //   143: invokevirtual result : (Lscala/collection/Seq;)[Ljava/lang/Object;
/*     */       //   146: areturn
/*     */       // Line number table:
/*     */       //   Java source line number -> byte code offset
/*     */       //   #67	-> 0
/*     */       //   #68	-> 22
/*     */       //   #69	-> 44
/*     */       //   #70	-> 81
/*     */       //   #71	-> 89
/*     */       //   #69	-> 131
/*     */       // Local variable table:
/*     */       //   start	length	slot	name	descriptor
/*     */       //   0	147	0	this	Lli/cil/oc/server/component/traits/WorldInventoryAnalytics$$anonfun$areStacksEquivalent$1;
/*     */       //   0	147	1	inventory	Lnet/minecraft/inventory/IInventory;
/*     */       //   22	124	2	stackA	Lnet/minecraft/item/ItemStack;
/*     */       //   44	102	3	stackB	Lnet/minecraft/item/ItemStack;
/*     */     }
/*     */   }
/*     */   
/*     */   public final class WorldInventoryAnalytics$$anonfun$setStackDisplayName$1 extends AbstractFunction1<IInventory, Object[]> implements Serializable { public static final long serialVersionUID = 0L;
/*     */     private final String label$1;
/*     */     private final Arguments args$6;
/*     */     
/*     */     public WorldInventoryAnalytics$$anonfun$setStackDisplayName$1(WorldInventoryAnalytics $outer, String label$1, Arguments args$6) {}
/*     */     
/*     */     public final Object[] apply(IInventory inventory) {
/*  80 */       ItemStack stack = inventory.func_70301_a(ExtendedArguments$.MODULE$.extendedArguments(this.args$6).checkSlot(inventory, 1));
/*     */ 
/*     */ 
/*     */       
/*  84 */       if (stack.func_82837_s())
/*  85 */         stack.func_135074_t(); 
/*     */       (new StringOps(Predef$.MODULE$.augmentString(this.label$1))).nonEmpty() ? stack.func_151001_c(this.label$1) : BoxedUnit.UNIT;
/*  87 */       return (stack != null && stack.field_77994_a > 0) ? package$.MODULE$.result((Seq)Predef$.MODULE$.genericWrapArray(new Object[] { BoxesRunTime.boxToBoolean(true)
/*     */             
/*  89 */             })) : package$.MODULE$.result((Seq)Predef$.MODULE$.genericWrapArray(new Object[] { BoxesRunTime.boxToBoolean(false) }));
/*     */     } }
/*     */   
/*     */   public final class WorldInventoryAnalytics$$anonfun$getStackInSlot$1 extends AbstractFunction1<IInventory, Object[]> implements Serializable { public static final long serialVersionUID = 0L;
/*     */     private final Arguments args$7;
/*     */     
/*     */     public final Object[] apply(IInventory inventory) {
/*  96 */       return package$.MODULE$.result((Seq)Predef$.MODULE$.genericWrapArray(new Object[] { inventory.func_70301_a(ExtendedArguments$.MODULE$.extendedArguments(this.args$7).checkSlot(inventory, 1)) }));
/*     */     }
/*     */     public WorldInventoryAnalytics$$anonfun$getStackInSlot$1(WorldInventoryAnalytics $outer, Arguments args$7) {} }
/*     */   public final class WorldInventoryAnalytics$$anonfun$getAllStacks$1 extends AbstractFunction1<IInventory, Object[]> implements Serializable { public static final long serialVersionUID = 0L;
/*     */     
/*     */     public WorldInventoryAnalytics$$anonfun$getAllStacks$1(WorldInventoryAnalytics $outer) {}
/*     */     
/*     */     public final Object[] apply(IInventory inventory) {
/* 104 */       ItemStack[] stacks = new ItemStack[inventory.func_70302_i_()]; RichInt$.MODULE$
/* 105 */         .until$extension0(Predef$.MODULE$.intWrapper(0), inventory.func_70302_i_()).foreach$mVc$sp((Function1)new WorldInventoryAnalytics$$anonfun$getAllStacks$1$$anonfun$apply$3(this, stacks, inventory));
/*     */ 
/*     */       
/* 108 */       return package$.MODULE$.result((Seq)Predef$.MODULE$.genericWrapArray(new Object[] { new ItemStackArrayValue(stacks) }));
/*     */     }
/*     */     public final class WorldInventoryAnalytics$$anonfun$getAllStacks$1$$anonfun$apply$3 extends AbstractFunction1.mcVI.sp implements Serializable {
/*     */       public static final long serialVersionUID = 0L; private final ItemStack[] stacks$1; private final IInventory inventory$1;
/*     */       public final void apply(int i) {
/*     */         apply$mcVI$sp(i);
/*     */       }
/*     */       public WorldInventoryAnalytics$$anonfun$getAllStacks$1$$anonfun$apply$3(WorldInventoryAnalytics$$anonfun$getAllStacks$1 $outer, ItemStack[] stacks$1, IInventory inventory$1) {}
/*     */       public void apply$mcVI$sp(int i) {
/*     */         this.stacks$1[i] = this.inventory$1.func_70301_a(i);
/*     */       } } }
/*     */   public final class WorldInventoryAnalytics$$anonfun$getInventoryName$1 extends AbstractFunction1<InventorySource, Object[]> implements Serializable { public static final long serialVersionUID = 0L;
/*     */     
/*     */     public final Object[] apply(InventorySource x0$1) {
/*     */       Object[] arrayOfObject;
/* 123 */       InventorySource inventorySource = x0$1;
/* 124 */       if (inventorySource instanceof BlockInventorySource) { Object[] arrayOfObject1; BlockInventorySource blockInventorySource = (BlockInventorySource)inventorySource; BlockPosition position = blockInventorySource.position(); Option option = WorldInventoryAnalytics$class.blockAt$1(this.$outer, position);
/* 125 */         if (option instanceof Some) { Some some = (Some)option; Block block = (Block)some.x(); arrayOfObject1 = package$.MODULE$.result((Seq)Predef$.MODULE$.genericWrapArray(new Object[] { block.func_149739_a() })); }
/* 126 */         else { arrayOfObject1 = package$.MODULE$.result((Seq)Predef$.MODULE$.genericWrapArray(new Object[] { Unit$.MODULE$, "Unknown" })); }
/*     */          arrayOfObject = arrayOfObject1; }
/* 128 */       else if (inventorySource instanceof EntityInventorySource) { EntityInventorySource entityInventorySource = (EntityInventorySource)inventorySource; Entity entity = entityInventorySource.entity(); arrayOfObject = package$.MODULE$.result((Seq)Predef$.MODULE$.genericWrapArray(new Object[] { EntityList.func_75621_b(entity) })); }
/* 129 */       else { arrayOfObject = package$.MODULE$.result((Seq)Predef$.MODULE$.genericWrapArray(new Object[] { Unit$.MODULE$, "Unknown" })); }
/*     */       
/*     */       return arrayOfObject;
/*     */     }
/*     */     public WorldInventoryAnalytics$$anonfun$getInventoryName$1(WorldInventoryAnalytics $outer) {} }
/*     */   public final class null extends AbstractFunction1<UpgradeDatabase, Object[]> implements Serializable { public static final long serialVersionUID = 0L; private final ItemStack stack$2; private final Arguments args$8;
/*     */     
/*     */     public null(WorldInventoryAnalytics $outer, ItemStack stack$2, Arguments args$8) {}
/*     */     
/*     */     public final Object[] apply(UpgradeDatabase database) {
/* 139 */       int dbSlot = ExtendedArguments$.MODULE$.extendedArguments(this.args$8).checkSlot(database.data(), 3);
/* 140 */       boolean nonEmpty = !(database.getStackInSlot(dbSlot) == null);
/* 141 */       database.setStackInSlot(dbSlot, this.stack$2.func_77946_l());
/* 142 */       return package$.MODULE$.result((Seq)Predef$.MODULE$.genericWrapArray(new Object[] { BoxesRunTime.boxToBoolean(nonEmpty) }));
/*     */     } } public final class WorldInventoryAnalytics$$anonfun$store$1 extends AbstractFunction1<IInventory, Object[]> implements Serializable { public static final long serialVersionUID = 0L; private final String dbAddress$1; private final Arguments args$8; public final Object[] apply(IInventory inventory) {
/* 144 */       return WorldInventoryAnalytics$class.store$1(this.$outer, inventory.func_70301_a(ExtendedArguments$.MODULE$.extendedArguments(this.args$8).checkSlot(inventory, 1)), this.dbAddress$1, this.args$8);
/*     */     }
/*     */ 
/*     */     
/*     */     public WorldInventoryAnalytics$$anonfun$store$1(WorldInventoryAnalytics $outer, String dbAddress$1, Arguments args$8) {} }
/*     */ 
/*     */ 
/*     */   
/*     */   public final class WorldInventoryAnalytics$$anonfun$withInventory$1
/*     */     extends AbstractFunction1<InventorySource, Object[]>
/*     */     implements Serializable
/*     */   {
/*     */     public static final long serialVersionUID = 0L;
/*     */     
/*     */     private final Function1 f$1;
/*     */ 
/*     */     
/*     */     public final Object[] apply(InventorySource is) {
/* 162 */       return (Object[])this.f$1.apply(is.inventory());
/*     */     }
/*     */     
/*     */     public WorldInventoryAnalytics$$anonfun$withInventory$1(WorldInventoryAnalytics $outer, Function1 f$1) {}
/*     */   } }


/* Location:              C:\Users\shame\AppData\Roaming\PrismLauncher\instances\GT_New_Horizons_2.7.4_Java_17-21\.minecraft\mods\OpenComputers-1.10.30-GTNH.jar!\li\cil\oc\server\component\traits\WorldInventoryAnalytics.class
 * Java compiler version: 8 (52.0)
 * JD-Core Version:       1.1.3
 */