/*    */ package li.cil.oc.common.tileentity.traits;
/*    */ @ScalaSignature(bytes = "\006\001\005=haB\001\003!\003\r\ta\004\002\023\007>l\007o\0348f]RLeN^3oi>\024\030P\003\002\004\t\0051AO]1jiNT!!\002\004\002\025QLG.Z3oi&$\030P\003\002\b\021\00511m\\7n_:T!!\003\006\002\005=\034'BA\006\r\003\r\031\027\016\034\006\002\033\005\021A.[\002\001'\025\001\001#G\017!!\t\tr#D\001\023\025\t)1C\003\002\025+\005IQ.\0338fGJ\fg\r\036\006\002-\005\031a.\032;\n\005a\021\"A\003+jY\026,e\016^5usB\021!dG\007\002\005%\021AD\001\002\f\013:4\030N]8o[\026tG\017\005\002\033=%\021qD\001\002\n\023:4XM\034;pef\004\"!\t\023\016\003\tR!a\t\004\002\023%tg/\0328u_JL\030BA\001#\021\0251\003\001\"\001(\003\031!\023N\\5uIQ\t\001\006\005\002*Y5\t!FC\001,\003\025\0318-\0317b\023\ti#F\001\003V]&$\b\"B\030\001\t\003\002\024\001\0025pgR,\022!\r\t\0035\001A\001b\r\001\t\006\004%I\001N\001\026a\026tG-\0338h%\026lwN^1mg\006\033G/^1m+\005)\004c\001\034<{5\tqG\003\0029s\0059Q.\036;bE2,'B\001\036+\003)\031w\016\0347fGRLwN\\\005\003y]\0221\"\021:sCf\024UO\0324feB\031\021F\020!\n\005}R#AB(qi&|g\016\005\002B\t6\t!I\003\002D'\005!\021\016^3n\023\t)%IA\005Ji\026l7\013^1dW\"Aq\t\001E\001B\003&Q'\001\fqK:$\027N\\4SK6|g/\0317t\003\016$X/\0317!\021!I\005\001#b\001\n\023!\024!\0059f]\022LgnZ!eIN\f5\r^;bY\"A1\n\001E\001B\003&Q'\001\nqK:$\027N\\4BI\022\034\030i\031;vC2\004\003bB'\001\001\004%IAT\001\020kB$\027\r^3TG\",G-\0367fIV\tq\n\005\002*!&\021\021K\013\002\b\005>|G.Z1o\021\035\031\006\0011A\005\nQ\0131#\0369eCR,7k\0315fIVdW\rZ0%KF$\"\001K+\t\017Y\023\026\021!a\001\037\006\031\001\020J\031\t\ra\003\001\025)\003P\003A)\b\017Z1uKN\033\007.\0323vY\026$\007\005C\003[\001\021\005A'A\bqK:$\027N\\4SK6|g/\0317t\021\025a\006\001\"\0015\003-\001XM\0343j]\036\fE\rZ:\t\013y\003A\021B0\002\025\005$'.^:u'&TX-\006\002aOR\021\001&\031\005\006Ev\003\raY\001\007EV4g-\032:\021\007YZD\rE\002*}\025\004\"AZ4\r\001\021)\001.\030b\001S\n\tA+\005\002k[B\021\021f[\005\003Y*\022qAT8uQ&tw\r\005\002*]&\021qN\013\002\004\003:L\b\"B9\001\t\0239\023!F1qa2L\030J\034<f]R|'/_\"iC:<Wm\035\005\006g\002!IaJ\001\030g\016DW\rZ;mK&sg/\0328u_JL8\t[1oO\026DQ!\036\001\005RY\f1b\0348Ji\026l\027\t\0323fIR\031\001f\036?\t\013a$\b\031A=\002\tMdw\016\036\t\003SiL!a\037\026\003\007%sG\017C\003~i\002\007\001)A\003ti\006\0347\016\003\004\000\001\021E\023\021A\001\016_:LE/Z7SK6|g/\0323\025\013!\n\031!!\002\t\013at\b\031A=\t\013ut\b\031\001!\t\017\005%\001\001\"\025\002\f\005!1/\031<f)\035A\023QBA\021\003_A\001\"a\004\002\b\001\007\021\021C\001\nG>l\007o\0348f]R\004B!a\005\002\0365\021\021Q\003\006\005\003/\tI\"A\004oKR<xN]6\013\007\005m\001\"A\002ba&LA!a\b\002\026\t\021R*\0318bO\026$WI\034<je>tW.\0328u\021!\t\031#a\002A\002\005\025\022A\0023sSZ,'\017\005\003\002(\005-RBAA\025\025\021\t\031#!\007\n\t\0055\022\021\006\002\005\023R,W\016\003\004~\003\017\001\r\001\021\005\007\003g\001A\021K\024\002\025%t\027\016^5bY&TX\r\003\004\0028\001!\teJ\001\bI&\034\bo\\:f\021\035\tY\004\001C!\003{\t\021b\0348D_:tWm\031;\025\007!\ny\004\003\005\002B\005e\002\031AA\"\003\021qw\016Z3\021\t\005M\021QI\005\005\003\017\n)B\001\003O_\022,\007bBA&\001\021\005\023QJ\001\r_:$\025n]2p]:,7\r\036\013\004Q\005=\003\002CA!\003\023\002\r!a\021\t\017\005M\003\001\"\021\002V\005\031rO]5uKR{gJ\021+G_J\034E.[3oiR\031\001&a\026\t\021\005e\023\021\013a\001\0037\n1A\0342u!\021\ti&!\031\016\005\005}#bAA-'%!\0211MA0\0059q%\t\026+bO\016{W\016]8v]\022Dq!a\032\001\t\003\nI'\001\013sK\006$gI]8n\035\n#fi\034:DY&,g\016\036\013\004Q\005-\004\002CA-\003K\002\r!a\027)\021\005\025\024qNAD\003\023\003B!!\035\002\0046\021\0211\017\006\005\003k\n9(\001\006sK2\fWO\\2iKJTA!!\037\002|\005\031a-\0347\013\t\005u\024qP\001\005[>$7O\003\002\002\002\006\0311\r]<\n\t\005\025\0251\017\002\t'&$Wm\0248ms\006)a/\0317vK\022\022\0211R\005\005\003\033\013y)\001\004D\031&+e\n\026\006\005\003#\013\031(\001\003TS\022,\007BDAK\001A\005\031\021!A\005\n\005]\025QT\001\024gV\004XM\035\023p]&#X-\034*f[>4X\r\032\013\006Q\005e\0251\024\005\007q\006M\005\031A=\t\ru\f\031\n1\001A\023\tyH\005\003\b\002\"\002\001\n1!A\001\n\023\t\031+!+\002#M,\b/\032:%_:LE/Z7BI\022,G\rF\003)\003K\0139\013\003\004y\003?\003\r!\037\005\007{\006}\005\031\001!\n\005U$\003BDAW\001A\005\031\021!A\005\n\005=\026qW\001\013gV\004XM\035\023tCZ,Gc\002\025\0022\006M\026Q\027\005\t\003\037\tY\0131\001\002\022!A\0211EAV\001\004\t)\003\003\004~\003W\003\r\001Q\005\004\003\023!\003\"DA^\001A\005\031\021!A\005\n\035\ni,\001\ttkB,'\017J5oSRL\027\r\\5{K&\031\0211G\016\t\033\005\005\007\001%A\002\002\003%IaJAb\0035\031X\017]3sI\021L7\017]8tK&\031\021qG\016\t\035\005\035\007\001%A\002\002\003%I!!3\002N\006y1/\0369fe\022zgnQ8o]\026\034G\017F\002)\003\027D\001\"!\021\002F\002\007\0211I\005\004\003wY\002BDAi\001A\005\031\021!A\005\n\005M\027q[\001\023gV\004XM\035\023p]\022K7oY8o]\026\034G\017F\002)\003+D\001\"!\021\002P\002\007\0211I\005\004\003\027Z\002BDAn\001A\005\031\021!A\005\n\005u\027\021]\001\032gV\004XM\035\023xe&$X\rV8O\005R3uN]\"mS\026tG\017F\002)\003?D\001\"!\027\002Z\002\007\0211L\005\005\003'\n\031/\003\002\031\005!q\021q\035\001\021\002\007\005\t\021\"\003\002j\0065\030AG:va\026\024HE]3bI\032\023x.\034(C)\032{'o\0217jK:$Hc\001\025\002l\"A\021\021LAs\001\004\tY&\003\003\002h\005\r\b")
/*    */ public interface ComponentInventory extends Environment, Inventory, ComponentInventory { ComponentInventory host();
/*    */   ArrayBuffer<Option<ItemStack>> li$cil$oc$common$tileentity$traits$ComponentInventory$$pendingRemovalsActual();
/*    */   ArrayBuffer<Option<ItemStack>> li$cil$oc$common$tileentity$traits$ComponentInventory$$pendingAddsActual();
/*    */   boolean li$cil$oc$common$tileentity$traits$ComponentInventory$$updateScheduled();
/*    */   @TraitSetter
/*    */   void li$cil$oc$common$tileentity$traits$ComponentInventory$$updateScheduled_$eq(boolean paramBoolean);
/*    */   ArrayBuffer<Option<ItemStack>> pendingRemovals();
/*    */   ArrayBuffer<Option<ItemStack>> pendingAdds();
/*    */   void onItemAdded(int paramInt, ItemStack paramItemStack);
/*    */   void onItemRemoved(int paramInt, ItemStack paramItemStack);
/*    */   void save(ManagedEnvironment paramManagedEnvironment, Item paramItem, ItemStack paramItemStack);
/*    */   void initialize();
/*    */   void dispose();
/*    */   void onConnect(Node paramNode);
/*    */   void onDisconnect(Node paramNode);
/*    */   
/*    */   void writeToNBTForClient(NBTTagCompound paramNBTTagCompound);
/*    */   
/*    */   @SideOnly(Side.CLIENT)
/*    */   void readFromNBTForClient(NBTTagCompound paramNBTTagCompound);
/*    */   
/* 24 */   public final class ComponentInventory$$anonfun$li$cil$oc$common$tileentity$traits$ComponentInventory$$pendingRemovalsActual$1 extends AbstractFunction0<Option<ItemStack>> implements Serializable { public final Option<ItemStack> apply() { return (Option<ItemStack>)None$.MODULE$; } public static final long serialVersionUID = 0L; public ComponentInventory$$anonfun$li$cil$oc$common$tileentity$traits$ComponentInventory$$pendingRemovalsActual$1(ComponentInventory $outer) {} } public final class ComponentInventory$$anonfun$li$cil$oc$common$tileentity$traits$ComponentInventory$$pendingAddsActual$1 extends AbstractFunction0<Option<ItemStack>> implements Serializable { public static final long serialVersionUID = 0L; public final Option<ItemStack> apply() {
/* 25 */       return (Option<ItemStack>)None$.MODULE$;
/*    */     }
/*    */ 
/*    */     
/*    */     public ComponentInventory$$anonfun$li$cil$oc$common$tileentity$traits$ComponentInventory$$pendingAddsActual$1(ComponentInventory $outer) {} }
/*    */ 
/*    */ 
/*    */   
/*    */   public final class ComponentInventory$$anonfun$adjustSize$1
/*    */     extends AbstractFunction1<Object, ArrayBuffer<Option<Object>>>
/*    */     implements Serializable
/*    */   {
/*    */     public static final long serialVersionUID = 0L;
/*    */     
/*    */     private final ArrayBuffer buffer$1;
/*    */     
/*    */     public ComponentInventory$$anonfun$adjustSize$1(ComponentInventory $outer, ArrayBuffer buffer$1) {}
/*    */     
/*    */     public final ArrayBuffer<Option<Object>> apply(int i) {
/* 44 */       return this.buffer$1.$plus$eq(None$.MODULE$);
/*    */     } }
/*    */   
/*    */   public final class ComponentInventory$$anonfun$li$cil$oc$common$tileentity$traits$ComponentInventory$$applyInventoryChanges$1 extends AbstractFunction1.mcVI.sp implements Serializable {
/*    */     public static final long serialVersionUID = 0L;
/*    */     
/*    */     public final void apply(int slot) {
/* 51 */       apply$mcVI$sp(slot);
/*    */     }
/*    */ 
/*    */     
/*    */     public ComponentInventory$$anonfun$li$cil$oc$common$tileentity$traits$ComponentInventory$$applyInventoryChanges$1(ComponentInventory $outer) {}
/*    */ 
/*    */     
/*    */     public void apply$mcVI$sp(int slot) {
/*    */       // Byte code:
/*    */       //   0: new scala/Tuple2
/*    */       //   3: dup
/*    */       //   4: aload_0
/*    */       //   5: getfield $outer : Lli/cil/oc/common/tileentity/traits/ComponentInventory;
/*    */       //   8: invokeinterface pendingRemovals : ()Lscala/collection/mutable/ArrayBuffer;
/*    */       //   13: iload_1
/*    */       //   14: invokevirtual apply : (I)Ljava/lang/Object;
/*    */       //   17: aload_0
/*    */       //   18: getfield $outer : Lli/cil/oc/common/tileentity/traits/ComponentInventory;
/*    */       //   21: invokeinterface pendingAdds : ()Lscala/collection/mutable/ArrayBuffer;
/*    */       //   26: iload_1
/*    */       //   27: invokevirtual apply : (I)Ljava/lang/Object;
/*    */       //   30: invokespecial <init> : (Ljava/lang/Object;Ljava/lang/Object;)V
/*    */       //   33: astore_2
/*    */       //   34: aload_2
/*    */       //   35: ifnull -> 161
/*    */       //   38: aload_2
/*    */       //   39: invokevirtual _1 : ()Ljava/lang/Object;
/*    */       //   42: checkcast scala/Option
/*    */       //   45: astore_3
/*    */       //   46: aload_2
/*    */       //   47: invokevirtual _2 : ()Ljava/lang/Object;
/*    */       //   50: checkcast scala/Option
/*    */       //   53: astore #4
/*    */       //   55: aload_3
/*    */       //   56: instanceof scala/Some
/*    */       //   59: ifeq -> 161
/*    */       //   62: aload_3
/*    */       //   63: checkcast scala/Some
/*    */       //   66: astore #5
/*    */       //   68: aload #5
/*    */       //   70: invokevirtual x : ()Ljava/lang/Object;
/*    */       //   73: checkcast net/minecraft/item/ItemStack
/*    */       //   76: astore #6
/*    */       //   78: aload #4
/*    */       //   80: instanceof scala/Some
/*    */       //   83: ifeq -> 161
/*    */       //   86: aload #4
/*    */       //   88: checkcast scala/Some
/*    */       //   91: astore #7
/*    */       //   93: aload #7
/*    */       //   95: invokevirtual x : ()Ljava/lang/Object;
/*    */       //   98: checkcast net/minecraft/item/ItemStack
/*    */       //   101: astore #8
/*    */       //   103: aload #6
/*    */       //   105: aload #8
/*    */       //   107: invokevirtual func_77969_a : (Lnet/minecraft/item/ItemStack;)Z
/*    */       //   110: ifeq -> 129
/*    */       //   113: aload #6
/*    */       //   115: aload #8
/*    */       //   117: invokestatic func_77970_a : (Lnet/minecraft/item/ItemStack;Lnet/minecraft/item/ItemStack;)Z
/*    */       //   120: ifeq -> 129
/*    */       //   123: getstatic scala/runtime/BoxedUnit.UNIT : Lscala/runtime/BoxedUnit;
/*    */       //   126: goto -> 156
/*    */       //   129: aload_0
/*    */       //   130: getfield $outer : Lli/cil/oc/common/tileentity/traits/ComponentInventory;
/*    */       //   133: iload_1
/*    */       //   134: aload #6
/*    */       //   136: invokeinterface li$cil$oc$common$tileentity$traits$ComponentInventory$$super$onItemRemoved : (ILnet/minecraft/item/ItemStack;)V
/*    */       //   141: aload_0
/*    */       //   142: getfield $outer : Lli/cil/oc/common/tileentity/traits/ComponentInventory;
/*    */       //   145: iload_1
/*    */       //   146: aload #8
/*    */       //   148: invokeinterface li$cil$oc$common$tileentity$traits$ComponentInventory$$super$onItemAdded : (ILnet/minecraft/item/ItemStack;)V
/*    */       //   153: getstatic scala/runtime/BoxedUnit.UNIT : Lscala/runtime/BoxedUnit;
/*    */       //   156: astore #9
/*    */       //   158: goto -> 322
/*    */       //   161: aload_2
/*    */       //   162: ifnull -> 239
/*    */       //   165: aload_2
/*    */       //   166: invokevirtual _1 : ()Ljava/lang/Object;
/*    */       //   169: checkcast scala/Option
/*    */       //   172: astore #10
/*    */       //   174: aload_2
/*    */       //   175: invokevirtual _2 : ()Ljava/lang/Object;
/*    */       //   178: checkcast scala/Option
/*    */       //   181: astore #11
/*    */       //   183: aload #10
/*    */       //   185: instanceof scala/Some
/*    */       //   188: ifeq -> 239
/*    */       //   191: aload #10
/*    */       //   193: checkcast scala/Some
/*    */       //   196: astore #12
/*    */       //   198: aload #12
/*    */       //   200: invokevirtual x : ()Ljava/lang/Object;
/*    */       //   203: checkcast net/minecraft/item/ItemStack
/*    */       //   206: astore #13
/*    */       //   208: getstatic scala/None$.MODULE$ : Lscala/None$;
/*    */       //   211: aload #11
/*    */       //   213: invokevirtual equals : (Ljava/lang/Object;)Z
/*    */       //   216: ifeq -> 239
/*    */       //   219: aload_0
/*    */       //   220: getfield $outer : Lli/cil/oc/common/tileentity/traits/ComponentInventory;
/*    */       //   223: iload_1
/*    */       //   224: aload #13
/*    */       //   226: invokeinterface li$cil$oc$common$tileentity$traits$ComponentInventory$$super$onItemRemoved : (ILnet/minecraft/item/ItemStack;)V
/*    */       //   231: getstatic scala/runtime/BoxedUnit.UNIT : Lscala/runtime/BoxedUnit;
/*    */       //   234: astore #9
/*    */       //   236: goto -> 322
/*    */       //   239: aload_2
/*    */       //   240: ifnull -> 317
/*    */       //   243: aload_2
/*    */       //   244: invokevirtual _1 : ()Ljava/lang/Object;
/*    */       //   247: checkcast scala/Option
/*    */       //   250: astore #14
/*    */       //   252: aload_2
/*    */       //   253: invokevirtual _2 : ()Ljava/lang/Object;
/*    */       //   256: checkcast scala/Option
/*    */       //   259: astore #15
/*    */       //   261: getstatic scala/None$.MODULE$ : Lscala/None$;
/*    */       //   264: aload #14
/*    */       //   266: invokevirtual equals : (Ljava/lang/Object;)Z
/*    */       //   269: ifeq -> 317
/*    */       //   272: aload #15
/*    */       //   274: instanceof scala/Some
/*    */       //   277: ifeq -> 317
/*    */       //   280: aload #15
/*    */       //   282: checkcast scala/Some
/*    */       //   285: astore #16
/*    */       //   287: aload #16
/*    */       //   289: invokevirtual x : ()Ljava/lang/Object;
/*    */       //   292: checkcast net/minecraft/item/ItemStack
/*    */       //   295: astore #17
/*    */       //   297: aload_0
/*    */       //   298: getfield $outer : Lli/cil/oc/common/tileentity/traits/ComponentInventory;
/*    */       //   301: iload_1
/*    */       //   302: aload #17
/*    */       //   304: invokeinterface li$cil$oc$common$tileentity$traits$ComponentInventory$$super$onItemAdded : (ILnet/minecraft/item/ItemStack;)V
/*    */       //   309: getstatic scala/runtime/BoxedUnit.UNIT : Lscala/runtime/BoxedUnit;
/*    */       //   312: astore #9
/*    */       //   314: goto -> 322
/*    */       //   317: getstatic scala/runtime/BoxedUnit.UNIT : Lscala/runtime/BoxedUnit;
/*    */       //   320: astore #9
/*    */       //   322: aload_0
/*    */       //   323: getfield $outer : Lli/cil/oc/common/tileentity/traits/ComponentInventory;
/*    */       //   326: invokeinterface pendingRemovals : ()Lscala/collection/mutable/ArrayBuffer;
/*    */       //   331: iload_1
/*    */       //   332: getstatic scala/None$.MODULE$ : Lscala/None$;
/*    */       //   335: invokevirtual update : (ILjava/lang/Object;)V
/*    */       //   338: aload_0
/*    */       //   339: getfield $outer : Lli/cil/oc/common/tileentity/traits/ComponentInventory;
/*    */       //   342: invokeinterface pendingAdds : ()Lscala/collection/mutable/ArrayBuffer;
/*    */       //   347: iload_1
/*    */       //   348: getstatic scala/None$.MODULE$ : Lscala/None$;
/*    */       //   351: invokevirtual update : (ILjava/lang/Object;)V
/*    */       //   354: return
/*    */       // Line number table:
/*    */       //   Java source line number -> byte code offset
/*    */       //   #52	-> 0
/*    */       //   #53	-> 38
/*    */       //   #54	-> 103
/*    */       //   #55	-> 129
/*    */       //   #56	-> 141
/*    */       //   #54	-> 156
/*    */       //   #52	-> 161
/*    */       //   #58	-> 165
/*    */       //   #59	-> 219
/*    */       //   #52	-> 239
/*    */       //   #60	-> 243
/*    */       //   #61	-> 297
/*    */       //   #62	-> 317
/*    */       //   #65	-> 322
/*    */       //   #66	-> 338
/*    */       // Local variable table:
/*    */       //   start	length	slot	name	descriptor
/*    */       //   0	355	0	this	Lli/cil/oc/common/tileentity/traits/ComponentInventory$$anonfun$li$cil$oc$common$tileentity$traits$ComponentInventory$$applyInventoryChanges$1;
/*    */       //   0	355	1	slot	I
/*    */       //   78	277	6	removed	Lnet/minecraft/item/ItemStack;
/*    */       //   103	252	8	added	Lnet/minecraft/item/ItemStack;
/*    */       //   208	147	13	removed	Lnet/minecraft/item/ItemStack;
/*    */       //   297	58	17	added	Lnet/minecraft/item/ItemStack;
/*    */     }
/*    */   }
/*    */ 
/*    */   
/*    */   public final class ComponentInventory$$anonfun$scheduleInventoryChange$1
/*    */     extends AbstractFunction0.mcV.sp
/*    */     implements Serializable
/*    */   {
/*    */     public static final long serialVersionUID = 0L;
/*    */ 
/*    */     
/*    */     public final void apply()
/*    */     {
/* 73 */       apply$mcV$sp(); } public void apply$mcV$sp() { ComponentInventory$class.li$cil$oc$common$tileentity$traits$ComponentInventory$$applyInventoryChanges(this.$outer); }
/*    */ 
/*    */     
/*    */     public ComponentInventory$$anonfun$scheduleInventoryChange$1(ComponentInventory $outer) {}
/*    */   } }


/* Location:              C:\Users\shame\AppData\Roaming\PrismLauncher\instances\GT_New_Horizons_2.7.4_Java_17-21\.minecraft\mods\OpenComputers-1.10.30-GTNH.jar!\li\cil\oc\common\tileentity\traits\ComponentInventory.class
 * Java compiler version: 8 (52.0)
 * JD-Core Version:       1.1.3
 */