/*     */ package li.cil.oc.common.tileentity.traits;@ScalaSignature(bytes = "\006\001\tecaB\001\003!\003\r\ta\004\002\004\021V\024'BA\002\005\003\031!(/Y5ug*\021QAB\001\013i&dW-\0328uSRL(BA\004\t\003\031\031w.\\7p]*\021\021BC\001\003_\016T!a\003\007\002\007\rLGNC\001\016\003\ta\027n\001\001\024\t\001\001\022$\b\t\003#]i\021A\005\006\003\013MQ!\001F\013\002\0235Lg.Z2sC\032$(\"\001\f\002\0079,G/\003\002\031%\tQA+\0337f\013:$\030\016^=\021\005iYR\"\001\002\n\005q\021!aC#om&\024xN\\7f]R\004\"AH\022\016\003}Q!\001I\021\002\0179,Go^8sW*\021!\005C\001\004CBL\027B\001\023 \005A\031\026\016Z3e\013:4\030N]8o[\026tG\017C\003'\001\021\005q%\001\004%S:LG\017\n\013\002QA\021\021\006L\007\002U)\t1&A\003tG\006d\027-\003\002.U\t!QK\\5u\021\025y\003\001\"\0211\003\021qw\016Z3\025\003E\002\"A\b\032\n\005Mz\"\001\002(pI\026DQ!\016\001\005RY\n1\"[:D_:tWm\031;fIV\tq\007\005\002*q%\021\021H\013\002\b\005>|G.Z1o\021\035Y\004A1A\005\022q\nQ\001\0357vON,\022!\020\t\004Sy\002\025BA +\005\025\t%O]1z!\t\t%)D\001\001\r\021\031\005\001\003#\003\tAcWoZ\n\004\005\026k\005C\001$L\033\0059%B\001%J\003\021a\027M\\4\013\003)\013AA[1wC&\021Aj\022\002\007\037\nTWm\031;\021\005yq\025B\001\017 \021!\001&I!b\001\n\003\t\026\001B:jI\026,\022A\025\t\003'fk\021\001\026\006\003+Z\013A!\036;jY*\021qa\026\006\0031V\ta\"\\5oK\016\024\030M\032;g_J<W-\003\002[)\nqai\034:hK\022K'/Z2uS>t\007\002\003/C\005\003\005\013\021\002*\002\013MLG-\032\021\t\013y\023E\021A0\002\rqJg.\033;?)\t\001\005\rC\003Q;\002\007!\013C\0040\005\n\007I\021\0012\026\003EBa\001\032\"!\002\023\t\024!\0028pI\026\004\003\"\0024C\t\003:\027!C8o\033\026\0348/Y4f)\tA\003\016C\003jK\002\007!.A\004nKN\034\030mZ3\021\005yY\027B\0017 \005\035iUm]:bO\026DQA\034\"\005B=\f\021b\0348D_:tWm\031;\025\005!\002\b\"B\030n\001\004\t\004\"\002:C\t\003\032\030\001D8o\t&\0348m\0348oK\016$HC\001\025u\021\025y\023\0171\0012\021\0251(\t\"\0017\003%I7\017\025:j[\006\024\030\020C\003y\005\022\005A(\001\013qYV<7/\0238Pi\",'OT3uo>\0248n\035\005\007u\002\001\013\021B\037\002\rAdWoZ:!\021\035a\bA1A\005\002u\fQ!];fk\026,\022A \t\006\006%\021QB\007\003\003\003QA!a\001\002\006\0059Q.\036;bE2,'bAA\004U\005Q1m\0347mK\016$\030n\0348\n\t\005-\021\021\001\002\006#V,W/\032\t\bS\005=\0211CA\r\023\r\t\tB\013\002\007)V\004H.\032\032\021\t%\n)BU\005\004\003/Q#AB(qi&|g\016E\002\037\0037I1!!\b \005\031\001\026mY6fi\"9\021\021\005\001!\002\023q\030AB9vKV,\007\005C\005\002&\001\001\r\021\"\001\002(\005aQ.\031=Rk\026,XmU5{KV\021\021\021\006\t\004S\005-\022bAA\027U\t\031\021J\034;\t\023\005E\002\0011A\005\002\005M\022\001E7bqF+X-^3TSj,w\fJ3r)\rA\023Q\007\005\013\003o\ty#!AA\002\005%\022a\001=%c!A\0211\b\001!B\023\tI#A\007nCb\fV/Z;f'&TX\r\t\005\n\003\001\001\031!C\001\003O\t!B]3mCf$U\r\\1z\021%\t\031\005\001a\001\n\003\t)%\001\bsK2\f\027\020R3mCf|F%Z9\025\007!\n9\005\003\006\0028\005\005\023\021!a\001\003SA\001\"a\023\001A\003&\021\021F\001\fe\026d\027-\037#fY\006L\b\005C\005\002P\001\001\r\021\"\001\002(\005Y!/\0327bs\006kw.\0368u\021%\t\031\006\001a\001\n\003\t)&A\bsK2\f\0270Q7pk:$x\fJ3r)\rA\023q\013\005\013\003o\t\t&!AA\002\005%\002\002CA.\001\001\006K!!\013\002\031I,G.Y=B[>,h\016\036\021\t\023\005}\003\0011A\005\002\005\035\022!\004:fY\006L8i\\8mI><h\016C\005\002d\001\001\r\021\"\001\002f\005\t\"/\0327bs\016{w\016\0343po:|F%Z9\025\007!\n9\007\003\006\0028\005\005\024\021!a\001\003SA\001\"a\033\001A\003&\021\021F\001\017e\026d\027-_\"p_2$wn\0368!\021%\ty\007\001b\001\n\003\t\t(\001\nqC\016\\W\r^:QKJ\034\025p\0317f\003Z<WCAA:!\021\t)(!\037\016\005\005]$BA+\t\023\021\tY(a\036\003\0335{g/\0338h\003Z,'/Y4f\021!\ty\b\001Q\001\n\005M\024a\0059bG.,Go\035)fe\016K8\r\\3Bm\036\004\003bBAB\001\021E\021qE\001\016cV,W/\032\"bg\026\034\026N_3\t\017\005\035\005\001\"\005\002(\005\031\022/^3vKNK'0\032)feV\003xM]1eK\"9\0211\022\001\005\022\005\035\022A\004:fY\006L()Y:f\t\026d\027-\037\005\b\003\037\003A\021CAI\003Q\021X\r\\1z\t\026d\027-\037)feV\003xM]1eKV\021\0211\023\t\004S\005U\025bAALU\t1Ai\\;cY\026Dq!a'\001\t#\t9#A\bsK2\f\027PQ1tK\006kw.\0368u\021\035\ty\n\001C\t\003O\tQC]3mCf\fUn\\;oiB+'/\0269he\006$W\rC\004\002$\002!\t%!*\002\025\r\fgnQ8o]\026\034G\017F\0028\003OCa\001UAQ\001\004\021\006\006CAQ\003W\013\031-!2\021\t\0055\026qX\007\003\003_SA!!-\0024\006Q!/\0327bk:\034\007.\032:\013\t\005U\026qW\001\004M6d'\002BA]\003w\013A!\\8eg*\021\021QX\001\004GB<\030\002BAa\003_\023\001bU5eK>sG._\001\006m\006dW/\032\023\003\003\017LA!!3\002L\00611\tT%F\035RSA!!4\0020\006!1+\0333f\021\035\t\t\016\001C!\003'\f\021b]5eK\022tu\016Z3\025\007E\n)\016\003\004Q\003\037\004\rA\025\005\007\0033\004A\021I\024\002\031U\004H-\031;f\013:$\030\016^=\t\017\005u\007\001\"\001\002`\006\001BO]=F]F,X-^3QC\016\\W\r\036\013\006o\005\005\030Q\035\005\t\003G\fY\0161\001\002\024\005Q1o\\;sG\026\034\026\016Z3\t\021\005\035\0301\034a\001\0033\ta\001]1dW\026$\bbBAv\001\021E\021Q^\001\fe\026d\027-\037)bG.,G\017F\003)\003_\f\t\020\003\005\002d\006%\b\031AA\n\021!\t9/!;A\002\005e\001bBA{\001\021\005\023q_\001\025e\026\fGM\022:p[:\023EKR8s'\026\024h/\032:\025\007!\nI\020\003\005\002|\006M\b\031AA\003\rq'\r\036\t\005\003\024\031!\004\002\003\002)\031\0211`\n\n\t\t\025!\021\001\002\017\035\n#F+Y4D_6\004x.\0368e\021\035\021I\001\001C!\005\027\t1c\036:ji\026$vN\024\"U\r>\0248+\032:wKJ$2\001\013B\007\021!\tYPa\002A\002\005u\bb\002B\t\001\021E!1C\001\013GJ,\027\r^3QYV<Gc\001!\003\026!1\001Ka\004A\002ICqA!\007\001\t#\021Y\"A\007p]BcWoZ\"p]:,7\r\036\013\006Q\tu!\021\005\005\b\005?\0219\0021\001A\003\021\001H.^4\t\r=\0229\0021\0012\021\035\021)\003\001C\t\005O\t\001c\0348QYV<G)[:d_:tWm\031;\025\013!\022ICa\013\t\017\t}!1\005a\001\001\"1qFa\tA\002EBqAa\f\001\t#\021\t$A\007p]BcWoZ'fgN\fw-\032\013\006Q\tM\"Q\007\005\b\005?\021i\0031\001A\021\031I'Q\006a\001U\"9!\021\b\001\005\022\tm\022AC2sK\006$XMT8eKR\031\021G!\020\t\017\t}!q\007a\001\001\"i!\021\t\001\021\002\007\005\t\021\"\003(\005\007\n!c];qKJ$S\017\0353bi\026,e\016^5us&\031\021\021\\\016\t\035\t\035\003\001%A\002\002\003%IA!\023\003N\005Q2/\0369fe\022\022X-\0313Ge>lgJ\021+G_J\034VM\035<feR\031\001Fa\023\t\021\005m(Q\ta\001\003{L1!!>\034\0219\021\t\006\001I\001\004\003\005I\021\002B*\005/\n\021d];qKJ$sO]5uKR{gJ\021+G_J\034VM\035<feR\031\001F!\026\t\021\005m(q\na\001\003{L1A!\003\034\001")
/*     */ public interface Hub extends Environment, SidedEnvironment { void li$cil$oc$common$tileentity$traits$Hub$_setter_$plugs_$eq(Plug[] paramArrayOfPlug); void li$cil$oc$common$tileentity$traits$Hub$_setter_$queue_$eq(Queue paramQueue); void li$cil$oc$common$tileentity$traits$Hub$_setter_$packetsPerCycleAvg_$eq(MovingAverage paramMovingAverage); Node node(); boolean isConnected(); Plug[] plugs(); Queue<Tuple2<Option<ForgeDirection>, Packet>> queue(); int maxQueueSize(); @TraitSetter
/*     */   void maxQueueSize_$eq(int paramInt); int relayDelay(); @TraitSetter
/*     */   void relayDelay_$eq(int paramInt); int relayAmount(); @TraitSetter
/*     */   void relayAmount_$eq(int paramInt); int relayCooldown(); @TraitSetter
/*     */   void relayCooldown_$eq(int paramInt); MovingAverage packetsPerCycleAvg(); int queueBaseSize(); int queueSizePerUpgrade(); int relayBaseDelay(); double relayDelayPerUpgrade(); int relayBaseAmount(); int relayAmountPerUpgrade(); @SideOnly(Side.CLIENT)
/*     */   boolean canConnect(ForgeDirection paramForgeDirection);
/*     */   Node sidedNode(ForgeDirection paramForgeDirection);
/*     */   void updateEntity();
/*     */   boolean tryEnqueuePacket(Option<ForgeDirection> paramOption, Packet paramPacket);
/*     */   void relayPacket(Option<ForgeDirection> paramOption, Packet paramPacket);
/*     */   void readFromNBTForServer(NBTTagCompound paramNBTTagCompound);
/*     */   void writeToNBTForServer(NBTTagCompound paramNBTTagCompound);
/*     */   Plug createPlug(ForgeDirection paramForgeDirection);
/*     */   void onPlugConnect(Plug paramPlug, Node paramNode);
/*     */   void onPlugDisconnect(Plug paramPlug, Node paramNode);
/*     */   void onPlugMessage(Plug paramPlug, Message paramMessage);
/*     */   Node createNode(Plug paramPlug);
/*     */   public final class Hub$$anonfun$isConnected$1 extends AbstractFunction1<Plug, Object> implements Serializable { public static final long serialVersionUID = 0L;
/*     */     public final boolean apply(Hub.Plug plug) {
/*  21 */       return !(plug == null || 
/*  22 */         plug.node() == null || 
/*  23 */         plug.node().address() == null || 
/*  24 */         plug.node().network() == null);
/*     */     } public Hub$$anonfun$isConnected$1(Hub $outer) {} } public final class Hub$$anonfun$1 extends AbstractFunction1<ForgeDirection, Plug> implements Serializable { public static final long serialVersionUID = 0L; public final Hub.Plug apply(ForgeDirection side) {
/*  26 */       return this.$outer.createPlug(side);
/*     */     }
/*     */ 
/*     */ 
/*     */ 
/*     */ 
/*     */ 
/*     */ 
/*     */ 
/*     */ 
/*     */ 
/*     */ 
/*     */ 
/*     */ 
/*     */     
/*     */     public Hub$$anonfun$1(Hub $outer) {} }
/*     */ 
/*     */ 
/*     */ 
/*     */ 
/*     */ 
/*     */ 
/*     */ 
/*     */ 
/*     */ 
/*     */ 
/*     */ 
/*     */ 
/*     */   
/*     */   public final class Hub$$anonfun$updateEntity$1
/*     */     extends AbstractFunction1.mcVI.sp
/*     */     implements Serializable
/*     */   {
/*     */     public static final long serialVersionUID = 0L;
/*     */ 
/*     */ 
/*     */ 
/*     */ 
/*     */ 
/*     */ 
/*     */ 
/*     */ 
/*     */ 
/*     */ 
/*     */ 
/*     */     
/*     */     public final void apply(int i)
/*     */     {
/*  74 */       apply$mcVI$sp(i); } public Hub$$anonfun$updateEntity$1(Hub $outer) {} public void apply$mcVI$sp(int i) {
/*  75 */       Tuple2 tuple2 = (Tuple2)this.$outer.queue().dequeue(); if (tuple2 != null) { Option sourceSide = (Option)tuple2._1(); Packet packet = (Packet)tuple2._2(); Tuple2 tuple22 = new Tuple2(sourceSide, packet), tuple21 = tuple22; Option<ForgeDirection> option = (Option)tuple21._1(); Packet packet1 = (Packet)tuple21._2();
/*  76 */         this.$outer.relayPacket(option, packet1);
/*     */         return; }
/*     */       
/*     */       throw new MatchError(tuple2);
/*     */     }
/*     */   }
/*     */ 
/*     */   
/*     */   public final class Hub$$anonfun$relayPacket$1
/*     */     extends AbstractFunction1<ForgeDirection, BoxedUnit>
/*     */     implements Serializable
/*     */   {
/*     */     public static final long serialVersionUID = 0L;
/*     */     
/*     */     private final Option sourceSide$1;
/*     */     
/*     */     private final Packet packet$1;
/*     */ 
/*     */     
/*     */     public Hub$$anonfun$relayPacket$1(Hub $outer, Option sourceSide$1, Packet packet$1) {}
/*     */ 
/*     */     
/*     */     public final void apply(ForgeDirection side) {
/*     */       // Byte code:
/*     */       //   0: aload_0
/*     */       //   1: getfield sourceSide$1 : Lscala/Option;
/*     */       //   4: invokevirtual isEmpty : ()Z
/*     */       //   7: ifne -> 38
/*     */       //   10: aload_0
/*     */       //   11: getfield sourceSide$1 : Lscala/Option;
/*     */       //   14: invokevirtual get : ()Ljava/lang/Object;
/*     */       //   17: aload_1
/*     */       //   18: astore_2
/*     */       //   19: dup
/*     */       //   20: ifnonnull -> 31
/*     */       //   23: pop
/*     */       //   24: aload_2
/*     */       //   25: ifnull -> 72
/*     */       //   28: goto -> 38
/*     */       //   31: aload_2
/*     */       //   32: invokevirtual equals : (Ljava/lang/Object;)Z
/*     */       //   35: ifne -> 72
/*     */       //   38: aload_0
/*     */       //   39: getfield $outer : Lli/cil/oc/common/tileentity/traits/Hub;
/*     */       //   42: aload_1
/*     */       //   43: invokeinterface sidedNode : (Lnet/minecraftforge/common/util/ForgeDirection;)Lli/cil/oc/api/network/Node;
/*     */       //   48: astore_3
/*     */       //   49: aload_3
/*     */       //   50: ifnull -> 72
/*     */       //   53: aload_3
/*     */       //   54: ldc 'network.message'
/*     */       //   56: iconst_1
/*     */       //   57: anewarray java/lang/Object
/*     */       //   60: dup
/*     */       //   61: iconst_0
/*     */       //   62: aload_0
/*     */       //   63: getfield packet$1 : Lli/cil/oc/api/network/Packet;
/*     */       //   66: aastore
/*     */       //   67: invokeinterface sendToReachable : (Ljava/lang/String;[Ljava/lang/Object;)V
/*     */       //   72: return
/*     */       // Line number table:
/*     */       //   Java source line number -> byte code offset
/*     */       //   #101	-> 0
/*     */       //   #102	-> 38
/*     */       //   #103	-> 49
/*     */       //   #104	-> 53
/*     */       //   #101	-> 72
/*     */       // Local variable table:
/*     */       //   start	length	slot	name	descriptor
/*     */       //   0	73	0	this	Lli/cil/oc/common/tileentity/traits/Hub$$anonfun$relayPacket$1;
/*     */       //   0	73	1	side	Lnet/minecraftforge/common/util/ForgeDirection;
/*     */       //   49	24	3	node	Lli/cil/oc/api/network/Node;
/*     */     }
/*     */   }
/*     */ 
/*     */   
/*     */   public final class Hub$$anonfun$readFromNBTForServer$1
/*     */     extends AbstractFunction1<Tuple2<NBTTagCompound, Object>, BoxedUnit>
/*     */     implements Serializable
/*     */   {
/*     */     public static final long serialVersionUID = 0L;
/*     */ 
/*     */     
/*     */     public final void apply(Tuple2 x0$2)
/*     */     {
/* 113 */       Tuple2 tuple2 = x0$2; if (tuple2 != null) {
/* 114 */         NBTTagCompound tag = (NBTTagCompound)tuple2._1(); int index = tuple2._2$mcI$sp(); this.$outer.plugs()[index].node().load(tag); BoxedUnit boxedUnit = BoxedUnit.UNIT;
/*     */         return;
/*     */       } 
/*     */       throw new MatchError(tuple2); } public Hub$$anonfun$readFromNBTForServer$1(Hub $outer) {} } public final class Hub$$anonfun$readFromNBTForServer$2 extends AbstractFunction1<NBTTagCompound, BoxedUnit> implements Serializable { public static final long serialVersionUID = 0L; public Hub$$anonfun$readFromNBTForServer$2(Hub $outer) {} public final void apply(NBTTagCompound tag) {
/* 118 */       Option side = ExtendedNBT$.MODULE$.extendNBTTagCompound(tag).getDirection("side");
/* 119 */       Packet packet = Network.newPacket(tag);
/* 120 */       this.$outer.queue().$plus$eq(Predef$ArrowAssoc$.MODULE$.$minus$greater$extension(Predef$.MODULE$.ArrowAssoc(side), packet));
/*     */     } }
/*     */ 
/*     */   
/*     */   public final class Hub$$anonfun$writeToNBTForServer$1
/*     */     extends AbstractFunction1<Plug, NBTTagCompound>
/*     */     implements Serializable {
/*     */     public static final long serialVersionUID = 0L;
/*     */     
/*     */     public Hub$$anonfun$writeToNBTForServer$1(Hub $outer) {}
/*     */     
/*     */     public final NBTTagCompound apply(Hub.Plug plug) {
/* 132 */       NBTTagCompound plugNbt = new NBTTagCompound();
/* 133 */       if (plug.node() != null)
/* 134 */         plug.node().save(plugNbt); 
/* 135 */       return plugNbt;
/*     */     } } public final class Hub$$anonfun$writeToNBTForServer$2 extends AbstractFunction1<Tuple2<Option<ForgeDirection>, Packet>, NBTTagCompound> implements Serializable { public static final long serialVersionUID = 0L; public final NBTTagCompound apply(Tuple2 x0$1) {
/* 137 */       Tuple2 tuple2 = x0$1; if (tuple2 != null) {
/* 138 */         Option sourceSide = (Option)tuple2._1(); Packet packet = (Packet)tuple2._2();
/* 139 */         NBTTagCompound tag = new NBTTagCompound();
/* 140 */         ExtendedNBT$.MODULE$.extendNBTTagCompound(tag).setDirection("side", sourceSide);
/* 141 */         packet.save(tag);
/* 142 */         return tag;
/*     */       } 
/*     */       throw new MatchError(tuple2);
/*     */     }
/*     */     
/*     */     public Hub$$anonfun$writeToNBTForServer$2(Hub $outer) {} }
/*     */ 
/*     */   
/*     */   public class Plug implements Environment {
/*     */     private final ForgeDirection side;
/*     */     private final Node node;
/*     */     
/* 154 */     public ForgeDirection side() { return this.side; }
/* 155 */     public Plug(Hub $outer, ForgeDirection side) { this.node = $outer.createNode(this); } public Node node() { return this.node; }
/*     */     
/*     */     public void onMessage(Message message) {
/* 158 */       if (isPrimary())
/* 159 */         li$cil$oc$common$tileentity$traits$Hub$Plug$$$outer().onPlugMessage(this, message); 
/*     */     }
/*     */     
/*     */     public void onConnect(Node node) {
/* 163 */       li$cil$oc$common$tileentity$traits$Hub$Plug$$$outer().onPlugConnect(this, node);
/*     */     } public void onDisconnect(Node node) {
/* 165 */       li$cil$oc$common$tileentity$traits$Hub$Plug$$$outer().onPlugDisconnect(this, node);
/*     */     }
/* 167 */     public boolean isPrimary() { Plug plug = this; if (li$cil$oc$common$tileentity$traits$Hub$Plug$$$outer().plugs()[Predef$.MODULE$.refArrayOps((Object[])li$cil$oc$common$tileentity$traits$Hub$Plug$$$outer().plugs()).indexWhere((Function1)new Hub$Plug$$anonfun$isPrimary$1(this))] == null) { li$cil$oc$common$tileentity$traits$Hub$Plug$$$outer().plugs()[Predef$.MODULE$.refArrayOps((Object[])li$cil$oc$common$tileentity$traits$Hub$Plug$$$outer().plugs()).indexWhere((Function1)new Hub$Plug$$anonfun$isPrimary$1(this))]; if (plug != null); } else if (li$cil$oc$common$tileentity$traits$Hub$Plug$$$outer().plugs()[Predef$.MODULE$.refArrayOps((Object[])li$cil$oc$common$tileentity$traits$Hub$Plug$$$outer().plugs()).indexWhere((Function1)new Hub$Plug$$anonfun$isPrimary$1(this))].equals(plug)) {  }  } public final class Hub$Plug$$anonfun$isPrimary$1 extends AbstractFunction1<Plug, Object> implements Serializable { public static final long serialVersionUID = 0L; public final boolean apply(Hub.Plug x$2) { Network network = this.$outer.node().network(); if (x$2.node().network() == null) { x$2.node().network(); if (network != null); } else if (x$2.node().network().equals(network))
/*     */         {  }
/* 169 */          } public Hub$Plug$$anonfun$isPrimary$1(Hub.Plug $outer) {} } public Plug[] plugsInOtherNetworks() { return (Plug[])Predef$.MODULE$.refArrayOps((Object[])li$cil$oc$common$tileentity$traits$Hub$Plug$$$outer().plugs()).filter((Function1)new Hub$Plug$$anonfun$plugsInOtherNetworks$1(this)); } public final class Hub$Plug$$anonfun$plugsInOtherNetworks$1 extends AbstractFunction1<Plug, Object> implements Serializable { public static final long serialVersionUID = 0L; public final boolean apply(Hub.Plug x$3) { Network network = this.$outer.node().network(); if (x$3.node().network() == null) { x$3.node().network(); if (network != null); } else if (x$3.node().network().equals(network))
/*     */         {  }
/*     */          }
/*     */       
/*     */       public Hub$Plug$$anonfun$plugsInOtherNetworks$1(Hub.Plug $outer) {} } }
/*     */   public final class Hub$$anonfun$onPlugMessage$1 extends AbstractFunction1<Plug, Object> implements Serializable { public static final long serialVersionUID = 0L; private final Message message$1;
/*     */     
/*     */     public final boolean apply(Hub.Plug x$4) {
/* 177 */       Node node = this.message$1.source(); if (x$4.node() == null) { x$4.node(); if (node != null); } else if (x$4.node().equals(node))
/*     */       {  }
/*     */     
/*     */     }
/*     */     
/*     */     public Hub$$anonfun$onPlugMessage$1(Hub $outer, Message message$1) {} }
/*     */    }


/* Location:              C:\Users\shame\AppData\Roaming\PrismLauncher\instances\GT_New_Horizons_2.7.4_Java_17-21\.minecraft\mods\OpenComputers-1.10.30-GTNH.jar!\li\cil\oc\common\tileentity\traits\Hub.class
 * Java compiler version: 8 (52.0)
 * JD-Core Version:       1.1.3
 */