/*     */ package li.cil.oc.util;@ScalaSignature(bytes = "\006\001\t=g\001B\001\003\001-\021QA\025+sK\026T!a\001\003\002\tU$\030\016\034\006\003\013\031\t!a\\2\013\005\035A\021aA2jY*\t\021\"\001\002mS\016\001QC\001\007$'\t\001Q\002\005\002\017#5\tqBC\001\021\003\025\0318-\0317b\023\t\021rB\001\004B]f\024VM\032\005\t)\001\021)\031!C\005+\005\tQ*F\001\027!\tqq#\003\002\031\037\t\031\021J\034;\t\021i\001!\021!Q\001\nY\t!!\024\021\t\021q\001!Q1A\005\004u\t!bY8pe\022Lg.\031;f+\005q\002\003\002\b C1J!\001I\b\003\023\031+hn\031;j_:\f\004C\001\022$\031\001!Q\001\n\001C\002\025\022A\001R1uCF\021a%\013\t\003\035\035J!\001K\b\003\0179{G\017[5oOB\021aBK\005\003W=\0211!\0218z!\025qQfL\0300\023\tqsB\001\004UkBdWm\r\t\003\035AJ!!M\b\003\r\021{WO\0317f\021!\031\004A!A!\002\023q\022aC2p_J$\027N\\1uK\002BQ!\016\001\005\002Y\na\001P5oSRtDCA\034<)\tA$\bE\002:\001\005j\021A\001\005\0069Q\002\035A\b\005\006)Q\002\rA\006\005\b{\001\021\r\021\"\003?\003\035)g\016\036:jKN,\022a\020\t\005\001\026\013s)D\001B\025\t\0215)A\004nkR\f'\r\\3\013\005\021{\021AC2pY2,7\r^5p]&\021a)\021\002\004\033\006\004\bC\001%J\033\005\001a\001\002&\001\t-\023A\001T3bMN\021\021\n\024\t\003\02163QA\024\001\002\n=\023AAT8eKN\021Q*\004\005\006k5#\t!\025\013\002\031\")1+\024D\001)\0061!m\\;oIN,\022!\026\t\003\021Z3Aa\026\001\0051\nI!+Z2uC:<G.Z\n\003-6A\001B\027,\003\006\004%\taW\001\004[&tW#\001/\021\005!kf\001\0020\001\t}\023Q\001U8j]R\034\"!X\007\t\021\005l&Q1A\005\002\t\f\021\001_\013\002_!AA-\030B\001B\003%q&\001\002yA!Aa-\030BC\002\023\005!-A\001z\021!AWL!A!\002\023y\023AA=!\021!QWL!b\001\n\003\021\027!\001>\t\0211l&\021!Q\001\n=\n!A\037\021\t\013UjF\021\0018\025\tq{\007/\035\005\006C6\004\ra\f\005\006M6\004\ra\f\005\006U6\004\ra\f\005\006ku#\ta\035\013\0039RDQ!\036:A\0021\n\021\001\035\005\0065v#\ta\036\013\0039bDQ!\037<A\002q\013Qa\034;iKJDQa_/\005\002q\f1!\\1y)\taV\020C\003zu\002\007A\f\003\004\000;\022\005\021\021A\001\bCN$V\017\0357f+\005a\003\"CA\003-\n\005\t\025!\003]\003\021i\027N\034\021\t\021m4&Q1A\005\002mC\021\"a\003W\005\003\005\013\021\002/\002\t5\f\007\020\t\005\007kY#\t!a\004\025\013U\013\t\"a\005\t\ri\013i\0011\001]\021\031Y\030Q\002a\0019\"9\021q\003,\005\002\005e\021!C5oG2,H-\0338h)\r)\0261\004\005\b\003;\t)\0021\001V\003\0251\030\r\\;f\021\035\t\tC\026C\001\003G\t!\"\0338uKJ\034Xm\031;t)\021\t)#a\013\021\0079\t9#C\002\002*=\021qAQ8pY\026\fg\016C\004\002\036\005}\001\031A+\t\r\005=b\013\"\001c\003\0311x\016\\;nK\"1qP\026C\001\003g)\"!!\016\021\0139\t9\004\f\027\n\007\005erB\001\004UkBdWM\r\005\b\003{iE\021AA \003%\tG\016\034\"pk:$7\017\006\003\002B\005-\003CBA\"\003\013\nI%D\001D\023\r\t9e\021\002\t\023R,'/\0312mKB1a\"a\016\0026YAq!!\024\002<\001\007a#A\003mKZ,G\016C\004\002R5#\t!a\025\002\r%\034H*Z1g+\t\t)\003C\004\002X53\t!!\027\002\007\005$G\rF\002M\0037Bq!!\b\002V\001\007A\nC\004\002`53\t!!\031\002\rI,Wn\034<f)\021\t\031'!\033\021\t9\t)\007T\005\004\003Oz!AB(qi&|g\016C\004\002\036\005u\003\031\001'\t\017\0055TJ\"\001\002p\005)\021/^3ssR!\021\021OAD!\025\t\031(a!\"\035\021\t)(a \017\t\005]\024QP\007\003\003sR1!a\037\013\003\031a$o\\8u}%\t\001#C\002\002\002>\tq\001]1dW\006<W-\003\003\002H\005\025%bAAA\037!9\021QNA6\001\004)\006BCAF\023\n\025\r\021\"\001\002\016\006!A-\031;b+\005\t\003\"CAI\023\n\005\t\025!\003\"\003\025!\027\r^1!\021%\t)*\023B\001B\003%A,A\003q_&tG\017\003\0046\023\022\005\021\021\024\013\006\017\006m\025Q\024\005\b\003\027\0139\n1\001\"\021\035\t)*a&A\002qCqaU%C\002\023\005A\013C\004\002$&\003\013\021B+\002\017\t|WO\0343tA!1Q(\023C\001\003O+\"!!+\021\013\005\r\023QI$\t\017\005]\023\n\"\001\002.R\031A*a,\t\017\005u\0211\026a\001\031\"9\021qL%\005\002\005MF\003BA2\003kCq!!\b\0022\002\007A\nC\004\002n%#\t!!/\025\t\005E\0241\030\005\b\003[\n9\f1\001V\021\035\ty\f\001Q\001\n}\n\001\"\0328ue&,7\017\t\005\t\003\007\004!\031!C\005+\005\tQ\016C\004\002H\002\001\013\021\002\f\002\0055\004\003\"CAf\001\001\007I\021BAg\003\021\021xn\034;\026\005\005=\007c\001%\002R\0321\0211\033\001\005\003+\024qAT8o\031\026\fgmE\002\002R2Cq!NAi\t\003\tI\016\006\002\002P\"9Q'!5\005\002\005uG\003BAh\003?D\001\"!9\002\\\002\007\0211]\001\006]>$Wm\035\t\005\035\005\025H*C\002\002h>\021!\002\020:fa\026\fG/\0323?\021)\tY/!5C\002\023\005\021Q^\001\tG\"LG\016\032:f]V\021\021q\036\t\005\001\006EH*C\002\002t\006\0231aU3u\021%\t90!5!\002\023\ty/A\005dQ&dGM]3oA!A1+!5A\002\023\005A\013\003\006\002~\006E\007\031!C\001\003\f!BY8v]\022\034x\fJ3r)\021\021\tAa\002\021\0079\021\031!C\002\003\006=\021A!\0268ji\"I!\021BA~\003\003\005\r!V\001\004q\022\n\004\002CAR\003#\004\013\025B+\t\021\005u\022\021\033C!\005\037!B!!\021\003\022!9\021Q\nB\007\001\0041\002\002CA)\003#$\t%a\025\t\021\005]\023\021\033C\001\005/!2\001\024B\r\021\035\tiB!\006A\0021C\001B!\b\002R\022%!qD\001\rk:\034\007.Z2lK\022\fE\r\032\013\005\005\003\021\t\003C\004\002\036\tm\001\031\001'\t\021\005}\023\021\033C\001\005K!B!a\031\003(!9\021Q\004B\022\001\004a\005\002CA7\003#$\tAa\013\025\t\005E$Q\006\005\b\003[\022I\0031\001V\021!\021\t$!5\005\n\005e\027!B:qY&$\b\"\003B\033\001\001\007I\021\002B\034\003!\021xn\034;`I\025\fH\003\002B\001\005sA!B!\003\0034\005\005\t\031AAh\021!\021i\004\001Q!\n\005=\027!\002:p_R\004\003b\002B!\001\021\005!1I\001\006CB\004H.\037\013\005\005\013\0229\005\005\003\017\003Kb\003bBA\017\005\001\r!\t\005\b\003{\001A\021\001B&+\t\t\t\005C\004\002X\001!\tAa\024\025\t\005\025\"\021\013\005\b\003;\021i\0051\001\"\021\035\ty\006\001C\001\005+\"B!!\n\003X!9\021Q\004B*\001\004\t\003bBA7\001\021\005!1\f\013\007\003c\022iF!\031\t\017\t}#\021\fa\001Y\005!aM]8n\021\035\021\031G!\027A\0021\n!\001^8\b\017\t\035\004\001#\003\003j\005)\001k\\5oiB\031\001Ja\033\007\ry\003\001\022\002B7'\r\021Y'\004\005\bk\t-D\021\001B9)\t\021I\007C\005\003v\t-$\031!C\0017\006\001b*Z4bi&4X-\0238gS:LG/\037\005\t\005s\022Y\007)A\0059\006\tb*Z4bi&4X-\0238gS:LG/\037\021\t\023\tu$1\016b\001\n\003Y\026\001\005)pg&$\030N^3J]\032Lg.\033;z\021!\021\tIa\033!\002\023a\026!\005)pg&$\030N^3J]\032Lg.\033;zA\0359!Q\021\001\t\n\t\035\025!\003*fGR\fgn\0327f!\rA%\021\022\004\007/\002AIAa#\024\007\t%U\002C\0046\005\023#\tAa$\025\005\t\035\005\002\003BJ\005\023#\tA!&\002\r\005\024x.\0368e)\r)&q\023\005\t\0053\023\t\n1\001\003\034\0061a/\0317vKN\004R!a\035\002\00423aAa(\001\t\t\005&aC*qY&$(+Z:vYR\0342A!(\016\021-\021)K!(\003\006\004%\t!!<\002\007M,G\017C\006\003*\nu%\021!Q\001\n\005=\030\001B:fi\002B\021b\025BO\005\003\007I\021\001+\t\027\005u(Q\024BA\002\023\005!q\026\013\005\005\003\021\t\fC\005\003\n\t5\026\021!a\001+\"Q\0211\025BO\005\003\005\013\025B+\t\017U\022i\n\"\001\0038R1!\021\030B^\005{\0032\001\023BO\021!\021)K!.A\002\005=\bBB*\0036\002\007Q\013\003\005\002X\tuE\021\001Ba)\021\021\tAa1\t\017\005u!q\030a\001\031\"9\021q\006BO\t\003\021\007\002\003Be\005;#\tAa3\002\037Y|G.^7f\023:\034G.\0363j]\036$2a\fBg\021\035\tiBa2A\0021\003")
/*     */ public class RTree<Data> { private final int li$cil$oc$util$RTree$$M; private final Function1<Data, Tuple3<Object, Object, Object>> coordinate; private final Map<Data, Leaf> entries; private final int li$cil$oc$util$RTree$$m; private NonLeaf root; private volatile Point$ Point$module;
/*     */   private volatile Rectangle$ Rectangle$module;
/*     */   
/*   5 */   public int li$cil$oc$util$RTree$$M() { return this.li$cil$oc$util$RTree$$M; } public Function1<Data, Tuple3<Object, Object, Object>> coordinate() { return this.coordinate; }
/*   6 */   public RTree(int M, Function1<Data, Tuple3<Object, Object, Object>> coordinate) { if (M < 2) throw new IllegalArgumentException("maxEntries must be larger or equal to 2.");
/*     */ 
/*     */     
/*   9 */     this.entries = scala.collection.mutable.Map$.MODULE$.empty();
/*     */     
/*  11 */     this.li$cil$oc$util$RTree$$m = scala.math.package$.MODULE$.max(M / 2, 1);
/*     */     
/*  13 */     this.root = new NonLeaf(); } private Map<Data, Leaf> entries() { return this.entries; } public int li$cil$oc$util$RTree$$m() { return this.li$cil$oc$util$RTree$$m; } private NonLeaf root() { return this.root; } private void root_$eq(NonLeaf x$1) { this.root = x$1; }
/*     */ 
/*     */   
/*  16 */   public synchronized Option<Tuple3<Object, Object, Object>> apply(Object value) { return (Option<Tuple3<Object, Object, Object>>)entries().get(value).fold((Function0)new RTree$$anonfun$apply$1(this), (Function1)new RTree$$anonfun$apply$2(this)); } public final class RTree$$anonfun$apply$1 extends AbstractFunction0<Option<Tuple3<Object, Object, Object>>> implements Serializable { public static final long serialVersionUID = 0L; public final Option<Tuple3<Object, Object, Object>> apply() { return (Option<Tuple3<Object, Object, Object>>)scala.None$.MODULE$; } public RTree$$anonfun$apply$1(RTree $outer) {} } public final class RTree$$anonfun$apply$2 extends AbstractFunction1<Leaf, Some<Tuple3<Object, Object, Object>>> implements Serializable { public static final long serialVersionUID = 0L; public final Some<Tuple3<Object, Object, Object>> apply(RTree.Leaf position) { return new Some(position.bounds().min().asTuple()); }
/*     */     
/*     */     public RTree$$anonfun$apply$2(RTree $outer) {} }
/*     */   public synchronized Iterable<Tuple2<Tuple2<Tuple3<Object, Object, Object>, Tuple3<Object, Object, Object>>, Object>> allBounds() {
/*  20 */     return root().allBounds(0);
/*     */   }
/*     */ 
/*     */ 
/*     */ 
/*     */ 
/*     */ 
/*     */ 
/*     */   
/*     */   public synchronized boolean add(Object value) {
/*     */     // Byte code:
/*     */     //   0: aload_0
/*     */     //   1: aload_1
/*     */     //   2: invokevirtual remove : (Ljava/lang/Object;)Z
/*     */     //   5: istore_2
/*     */     //   6: new li/cil/oc/util/RTree$Leaf
/*     */     //   9: dup
/*     */     //   10: aload_0
/*     */     //   11: aload_1
/*     */     //   12: new li/cil/oc/util/RTree$Point
/*     */     //   15: dup
/*     */     //   16: aload_0
/*     */     //   17: aload_0
/*     */     //   18: invokevirtual coordinate : ()Lscala/Function1;
/*     */     //   21: aload_1
/*     */     //   22: invokeinterface apply : (Ljava/lang/Object;)Ljava/lang/Object;
/*     */     //   27: checkcast scala/Tuple3
/*     */     //   30: invokespecial <init> : (Lli/cil/oc/util/RTree;Lscala/Tuple3;)V
/*     */     //   33: invokespecial <init> : (Lli/cil/oc/util/RTree;Ljava/lang/Object;Lli/cil/oc/util/RTree$Point;)V
/*     */     //   36: astore_3
/*     */     //   37: aload_0
/*     */     //   38: invokespecial entries : ()Lscala/collection/mutable/Map;
/*     */     //   41: getstatic scala/Predef$ArrowAssoc$.MODULE$ : Lscala/Predef$ArrowAssoc$;
/*     */     //   44: getstatic scala/Predef$.MODULE$ : Lscala/Predef$;
/*     */     //   47: aload_1
/*     */     //   48: invokevirtual ArrowAssoc : (Ljava/lang/Object;)Ljava/lang/Object;
/*     */     //   51: aload_3
/*     */     //   52: invokevirtual $minus$greater$extension : (Ljava/lang/Object;Ljava/lang/Object;)Lscala/Tuple2;
/*     */     //   55: invokeinterface $plus$eq : (Lscala/Tuple2;)Lscala/collection/mutable/MapLike;
/*     */     //   60: pop
/*     */     //   61: aload_0
/*     */     //   62: invokespecial root : ()Lli/cil/oc/util/RTree$NonLeaf;
/*     */     //   65: aload_3
/*     */     //   66: invokevirtual add : (Lli/cil/oc/util/RTree$Node;)Lli/cil/oc/util/RTree$Node;
/*     */     //   69: astore #4
/*     */     //   71: aload #4
/*     */     //   73: aload_0
/*     */     //   74: invokespecial root : ()Lli/cil/oc/util/RTree$NonLeaf;
/*     */     //   77: astore #5
/*     */     //   79: dup
/*     */     //   80: ifnonnull -> 92
/*     */     //   83: pop
/*     */     //   84: aload #5
/*     */     //   86: ifnull -> 100
/*     */     //   89: goto -> 108
/*     */     //   92: aload #5
/*     */     //   94: invokevirtual equals : (Ljava/lang/Object;)Z
/*     */     //   97: ifeq -> 108
/*     */     //   100: getstatic scala/runtime/BoxedUnit.UNIT : Lscala/runtime/BoxedUnit;
/*     */     //   103: astore #6
/*     */     //   105: goto -> 150
/*     */     //   108: aload_0
/*     */     //   109: new li/cil/oc/util/RTree$NonLeaf
/*     */     //   112: dup
/*     */     //   113: aload_0
/*     */     //   114: getstatic scala/Predef$.MODULE$ : Lscala/Predef$;
/*     */     //   117: iconst_2
/*     */     //   118: anewarray li/cil/oc/util/RTree$Node
/*     */     //   121: dup
/*     */     //   122: iconst_0
/*     */     //   123: aload #4
/*     */     //   125: aastore
/*     */     //   126: dup
/*     */     //   127: iconst_1
/*     */     //   128: aload_0
/*     */     //   129: invokespecial root : ()Lli/cil/oc/util/RTree$NonLeaf;
/*     */     //   132: aastore
/*     */     //   133: checkcast [Ljava/lang/Object;
/*     */     //   136: invokevirtual wrapRefArray : ([Ljava/lang/Object;)Lscala/collection/mutable/WrappedArray;
/*     */     //   139: invokespecial <init> : (Lli/cil/oc/util/RTree;Lscala/collection/Seq;)V
/*     */     //   142: invokespecial root_$eq : (Lli/cil/oc/util/RTree$NonLeaf;)V
/*     */     //   145: getstatic scala/runtime/BoxedUnit.UNIT : Lscala/runtime/BoxedUnit;
/*     */     //   148: astore #6
/*     */     //   150: iload_2
/*     */     //   151: ifeq -> 158
/*     */     //   154: iconst_0
/*     */     //   155: goto -> 159
/*     */     //   158: iconst_1
/*     */     //   159: ireturn
/*     */     // Line number table:
/*     */     //   Java source line number -> byte code offset
/*     */     //   #23	-> 0
/*     */     //   #24	-> 6
/*     */     //   #25	-> 37
/*     */     //   #26	-> 61
/*     */     //   #27	-> 71
/*     */     //   #28	-> 100
/*     */     //   #27	-> 108
/*     */     //   #30	-> 150
/*     */     //   #22	-> 159
/*     */     // Local variable table:
/*     */     //   start	length	slot	name	descriptor
/*     */     //   0	160	0	this	Lli/cil/oc/util/RTree;
/*     */     //   0	160	1	value	Ljava/lang/Object;
/*     */     //   6	154	2	replaced	Z
/*     */     //   37	123	3	entry	Lli/cil/oc/util/RTree$Leaf;
/*     */   }
/*     */ 
/*     */ 
/*     */ 
/*     */ 
/*     */ 
/*     */ 
/*     */   
/*     */   public synchronized boolean remove(Object value) {
/*     */     // Byte code:
/*     */     //   0: aload_0
/*     */     //   1: invokespecial entries : ()Lscala/collection/mutable/Map;
/*     */     //   4: aload_1
/*     */     //   5: invokeinterface remove : (Ljava/lang/Object;)Lscala/Option;
/*     */     //   10: astore_2
/*     */     //   11: aload_2
/*     */     //   12: instanceof scala/Some
/*     */     //   15: ifeq -> 192
/*     */     //   18: aload_2
/*     */     //   19: checkcast scala/Some
/*     */     //   22: astore_3
/*     */     //   23: aload_3
/*     */     //   24: invokevirtual x : ()Ljava/lang/Object;
/*     */     //   27: checkcast li/cil/oc/util/RTree$Leaf
/*     */     //   30: astore #4
/*     */     //   32: aload_0
/*     */     //   33: invokespecial root : ()Lli/cil/oc/util/RTree$NonLeaf;
/*     */     //   36: aload #4
/*     */     //   38: invokevirtual remove : (Lli/cil/oc/util/RTree$Node;)Lscala/Option;
/*     */     //   41: astore #6
/*     */     //   43: getstatic scala/Predef$.MODULE$ : Lscala/Predef$;
/*     */     //   46: aload #6
/*     */     //   48: aload #4
/*     */     //   50: invokevirtual contains : (Ljava/lang/Object;)Z
/*     */     //   53: ifne -> 68
/*     */     //   56: aload #6
/*     */     //   58: aload_0
/*     */     //   59: invokespecial root : ()Lli/cil/oc/util/RTree$NonLeaf;
/*     */     //   62: invokevirtual contains : (Ljava/lang/Object;)Z
/*     */     //   65: ifeq -> 72
/*     */     //   68: iconst_1
/*     */     //   69: goto -> 73
/*     */     //   72: iconst_0
/*     */     //   73: invokevirtual assert : (Z)V
/*     */     //   76: aload_0
/*     */     //   77: invokespecial root : ()Lli/cil/oc/util/RTree$NonLeaf;
/*     */     //   80: invokevirtual children : ()Lscala/collection/mutable/Set;
/*     */     //   83: invokeinterface headOption : ()Lscala/Option;
/*     */     //   88: astore #7
/*     */     //   90: aload #7
/*     */     //   92: instanceof scala/Some
/*     */     //   95: ifeq -> 160
/*     */     //   98: aload #7
/*     */     //   100: checkcast scala/Some
/*     */     //   103: astore #8
/*     */     //   105: aload #8
/*     */     //   107: invokevirtual x : ()Ljava/lang/Object;
/*     */     //   110: checkcast li/cil/oc/util/RTree$Node
/*     */     //   113: astore #9
/*     */     //   115: aload #9
/*     */     //   117: instanceof li/cil/oc/util/RTree$NonLeaf
/*     */     //   120: ifeq -> 160
/*     */     //   123: aload #9
/*     */     //   125: checkcast li/cil/oc/util/RTree$NonLeaf
/*     */     //   128: astore #10
/*     */     //   130: aload_0
/*     */     //   131: invokespecial root : ()Lli/cil/oc/util/RTree$NonLeaf;
/*     */     //   134: invokevirtual children : ()Lscala/collection/mutable/Set;
/*     */     //   137: invokeinterface size : ()I
/*     */     //   142: iconst_1
/*     */     //   143: if_icmpne -> 160
/*     */     //   146: aload_0
/*     */     //   147: aload #10
/*     */     //   149: invokespecial root_$eq : (Lli/cil/oc/util/RTree$NonLeaf;)V
/*     */     //   152: getstatic scala/runtime/BoxedUnit.UNIT : Lscala/runtime/BoxedUnit;
/*     */     //   155: astore #11
/*     */     //   157: goto -> 186
/*     */     //   160: aload_0
/*     */     //   161: invokespecial root : ()Lli/cil/oc/util/RTree$NonLeaf;
/*     */     //   164: aload_0
/*     */     //   165: invokevirtual li$cil$oc$util$RTree$$Rectangle : ()Lli/cil/oc/util/RTree$Rectangle$;
/*     */     //   168: aload_0
/*     */     //   169: invokespecial root : ()Lli/cil/oc/util/RTree$NonLeaf;
/*     */     //   172: invokevirtual children : ()Lscala/collection/mutable/Set;
/*     */     //   175: invokevirtual around : (Lscala/collection/Iterable;)Lli/cil/oc/util/RTree$Rectangle;
/*     */     //   178: invokevirtual bounds_$eq : (Lli/cil/oc/util/RTree$Rectangle;)V
/*     */     //   181: getstatic scala/runtime/BoxedUnit.UNIT : Lscala/runtime/BoxedUnit;
/*     */     //   184: astore #11
/*     */     //   186: iconst_1
/*     */     //   187: istore #5
/*     */     //   189: goto -> 195
/*     */     //   192: iconst_0
/*     */     //   193: istore #5
/*     */     //   195: iload #5
/*     */     //   197: ireturn
/*     */     // Line number table:
/*     */     //   Java source line number -> byte code offset
/*     */     //   #34	-> 0
/*     */     //   #35	-> 11
/*     */     //   #36	-> 32
/*     */     //   #37	-> 43
/*     */     //   #38	-> 76
/*     */     //   #39	-> 90
/*     */     //   #40	-> 146
/*     */     //   #42	-> 160
/*     */     //   #44	-> 186
/*     */     //   #35	-> 187
/*     */     //   #45	-> 192
/*     */     //   #34	-> 195
/*     */     // Local variable table:
/*     */     //   start	length	slot	name	descriptor
/*     */     //   0	198	0	this	Lli/cil/oc/util/RTree;
/*     */     //   0	198	1	value	Ljava/lang/Object;
/*     */     //   32	166	4	node	Lli/cil/oc/util/RTree$Leaf;
/*     */     //   43	144	6	change	Lscala/Option;
/*     */     //   115	83	9	nonLeaf	Lli/cil/oc/util/RTree$Node;
/*     */   }
/*     */ 
/*     */ 
/*     */ 
/*     */ 
/*     */ 
/*     */ 
/*     */   
/*     */   public synchronized Iterable<Data> query(Tuple3<Object, Object, Object> from, Tuple3<Object, Object, Object> to) {
/*  50 */     return root().query(new Rectangle(this, new Point(from), new Point(to)));
/*     */   }
/*     */   
/*     */   public abstract class Node { public Node(RTree $outer) {}
/*     */     
/*     */     public Iterable<Tuple2<Tuple2<Tuple3<Object, Object, Object>, Tuple3<Object, Object, Object>>, Object>> allBounds(int level) {
/*  56 */       (new Tuple2[1])[0] = new Tuple2(bounds().asTuple(), BoxesRunTime.boxToInteger(level)); return (Iterable<Tuple2<Tuple2<Tuple3<Object, Object, Object>, Tuple3<Object, Object, Object>>, Object>>)scala.package$.MODULE$.Iterable().apply((Seq)scala.Predef$.MODULE$.wrapRefArray((Object[])new Tuple2[1]));
/*     */     } public boolean isLeaf() {
/*  58 */       return true;
/*     */     }
/*     */     
/*     */     public abstract RTree<Data>.Rectangle bounds();
/*     */     
/*     */     public abstract Node add(Node param1Node);
/*     */     
/*     */     public abstract Option<Node> remove(Node param1Node);
/*     */     
/*     */     public abstract Iterable<Data> query(RTree<Data>.Rectangle param1Rectangle); }
/*     */ 
/*     */   
/*     */   public class NonLeaf
/*     */     extends Node
/*     */   {
/*     */     private final Set<RTree<Data>.Node> children;
/*     */     private RTree<Data>.Rectangle bounds;
/*     */     
/*  76 */     public NonLeaf(RTree<Data> $outer) { this.children = scala.collection.mutable.Set$.MODULE$.empty();
/*     */       
/*  78 */       this.bounds = new RTree.Rectangle($outer, $outer.li$cil$oc$util$RTree$$Point().PositiveInfinity(), $outer.li$cil$oc$util$RTree$$Point().NegativeInfinity()); } public NonLeaf(Seq nodes) { this(); nodes.foreach((Function1)new RTree$NonLeaf$$anonfun$$lessinit$greater$1(this)); } public final class RTree$NonLeaf$$anonfun$$lessinit$greater$1 extends AbstractFunction1<RTree<Data>.Node, BoxedUnit> implements Serializable { public static final long serialVersionUID = 0L; public RTree$NonLeaf$$anonfun$$lessinit$greater$1(RTree.NonLeaf $outer) {} public final void apply(RTree.Node child) { this.$outer.children().$plus$eq(child); this.$outer.bounds_$eq(this.$outer.bounds().including(child.bounds())); } } public Set<RTree<Data>.Node> children() { return this.children; } public RTree<Data>.Rectangle bounds() { return this.bounds; } public void bounds_$eq(RTree.Rectangle x$1) { this.bounds = x$1; }
/*     */     
/*  80 */     public Iterable<Tuple2<Tuple2<Tuple3<Object, Object, Object>, Tuple3<Object, Object, Object>>, Object>> allBounds(int level) { return (Iterable<Tuple2<Tuple2<Tuple3<Object, Object, Object>, Tuple3<Object, Object, Object>>, Object>>)super.allBounds(level).$plus$plus((GenTraversableOnce)children().flatMap((Function1)new RTree$NonLeaf$$anonfun$allBounds$1(this, level), scala.collection.mutable.Set$.MODULE$.canBuildFrom()), scala.collection.Iterable$.MODULE$.canBuildFrom()); } public final class RTree$NonLeaf$$anonfun$allBounds$1 extends AbstractFunction1<RTree<Data>.Node, Iterable<Tuple2<Tuple2<Tuple3<Object, Object, Object>, Tuple3<Object, Object, Object>>, Object>>> implements Serializable { public static final long serialVersionUID = 0L; private final int level$1; public final Iterable<Tuple2<Tuple2<Tuple3<Object, Object, Object>, Tuple3<Object, Object, Object>>, Object>> apply(RTree.Node x$1) { return x$1.allBounds(this.level$1 + 1); }
/*     */        public RTree$NonLeaf$$anonfun$allBounds$1(RTree.NonLeaf $outer, int level$1) {} }
/*  82 */     public boolean isLeaf() { return children().headOption().exists((Function1)new RTree$NonLeaf$$anonfun$isLeaf$1(this)); } public final class RTree$NonLeaf$$anonfun$isLeaf$1 extends AbstractFunction1<RTree<Data>.Node, Object> implements Serializable { public static final long serialVersionUID = 0L; public final boolean apply(RTree.Node x$2) { return x$2 instanceof RTree.Leaf; }
/*     */ 
/*     */ 
/*     */ 
/*     */       
/*     */       public RTree$NonLeaf$$anonfun$isLeaf$1(RTree.NonLeaf $outer) {} }
/*     */ 
/*     */ 
/*     */     
/*     */     public RTree<Data>.Node add(RTree.Node value) {
/*     */       // Byte code:
/*     */       //   0: getstatic scala/Predef$.MODULE$ : Lscala/Predef$;
/*     */       //   3: aload_1
/*     */       //   4: aload_0
/*     */       //   5: astore_2
/*     */       //   6: dup
/*     */       //   7: ifnonnull -> 18
/*     */       //   10: pop
/*     */       //   11: aload_2
/*     */       //   12: ifnull -> 25
/*     */       //   15: goto -> 29
/*     */       //   18: aload_2
/*     */       //   19: invokevirtual equals : (Ljava/lang/Object;)Z
/*     */       //   22: ifeq -> 29
/*     */       //   25: iconst_0
/*     */       //   26: goto -> 30
/*     */       //   29: iconst_1
/*     */       //   30: invokevirtual assert : (Z)V
/*     */       //   33: aload_0
/*     */       //   34: aload_1
/*     */       //   35: invokevirtual li$cil$oc$util$RTree$NonLeaf$$uncheckedAdd : (Lli/cil/oc/util/RTree$Node;)V
/*     */       //   38: aload_0
/*     */       //   39: invokevirtual children : ()Lscala/collection/mutable/Set;
/*     */       //   42: invokeinterface size : ()I
/*     */       //   47: aload_0
/*     */       //   48: invokevirtual li$cil$oc$util$RTree$NonLeaf$$$outer : ()Lli/cil/oc/util/RTree;
/*     */       //   51: invokevirtual li$cil$oc$util$RTree$$M : ()I
/*     */       //   54: if_icmple -> 64
/*     */       //   57: aload_0
/*     */       //   58: invokevirtual li$cil$oc$util$RTree$NonLeaf$$split : ()Lli/cil/oc/util/RTree$NonLeaf;
/*     */       //   61: goto -> 80
/*     */       //   64: aload_0
/*     */       //   65: aload_0
/*     */       //   66: invokevirtual bounds : ()Lli/cil/oc/util/RTree$Rectangle;
/*     */       //   69: aload_1
/*     */       //   70: invokevirtual bounds : ()Lli/cil/oc/util/RTree$Rectangle;
/*     */       //   73: invokevirtual including : (Lli/cil/oc/util/RTree$Rectangle;)Lli/cil/oc/util/RTree$Rectangle;
/*     */       //   76: invokevirtual bounds_$eq : (Lli/cil/oc/util/RTree$Rectangle;)V
/*     */       //   79: aload_0
/*     */       //   80: areturn
/*     */       // Line number table:
/*     */       //   Java source line number -> byte code offset
/*     */       //   #85	-> 0
/*     */       //   #86	-> 33
/*     */       //   #87	-> 38
/*     */       //   #88	-> 57
/*     */       //   #91	-> 64
/*     */       //   #92	-> 79
/*     */       //   #84	-> 80
/*     */       // Local variable table:
/*     */       //   start	length	slot	name	descriptor
/*     */       //   0	81	0	this	Lli/cil/oc/util/RTree$NonLeaf;
/*     */       //   0	81	1	value	Lli/cil/oc/util/RTree$Node;
/*     */     }
/*     */ 
/*     */     
/*     */     public void li$cil$oc$util$RTree$NonLeaf$$uncheckedAdd(RTree.Node value) {
/*  97 */       ObjectRef bestChild = ObjectRef.create(null);
/*  98 */       DoubleRef bestGrowth = DoubleRef.create(Double.POSITIVE_INFINITY);
/*  99 */       DoubleRef bestVolume = DoubleRef.create(Double.POSITIVE_INFINITY);
/* 100 */       children().withFilter((Function1)new RTree$NonLeaf$$anonfun$li$cil$oc$util$RTree$NonLeaf$$uncheckedAdd$1(this, (NonLeaf)value)).foreach((Function1)new RTree$NonLeaf$$anonfun$li$cil$oc$util$RTree$NonLeaf$$uncheckedAdd$2(this, value, bestChild, bestGrowth, (NonLeaf)bestVolume));
/*     */ 
/*     */ 
/*     */ 
/*     */ 
/*     */ 
/*     */ 
/*     */ 
/*     */ 
/*     */       
/* 110 */       Option option = (Option)bestChild.elem;
/* 111 */       if (option instanceof Some) { Some some = (Some)option; RTree.Node child = (RTree.Node)some.x();
/* 112 */         children().$plus$eq(child.add(value)); BoxedUnit boxedUnit = BoxedUnit.UNIT; }
/*     */       else
/*     */       
/* 115 */       { children().$plus$eq(value); BoxedUnit boxedUnit = BoxedUnit.UNIT; } 
/*     */     } public final class RTree$NonLeaf$$anonfun$li$cil$oc$util$RTree$NonLeaf$$uncheckedAdd$1 extends AbstractFunction1<RTree<Data>.Node, Object> implements Serializable {
/*     */       public static final long serialVersionUID = 0L; private final RTree.Node value$2; public final boolean apply(RTree.Node child) { return !(child.isLeaf() && !(this.value$2 instanceof RTree.Leaf)); } public RTree$NonLeaf$$anonfun$li$cil$oc$util$RTree$NonLeaf$$uncheckedAdd$1(RTree.NonLeaf $outer, RTree.Node value$2) {} } public final class RTree$NonLeaf$$anonfun$li$cil$oc$util$RTree$NonLeaf$$uncheckedAdd$2 extends AbstractFunction1<RTree<Data>.Node, BoxedUnit> implements Serializable {
/*     */       public static final long serialVersionUID = 0L; private final RTree.Node value$2; private final ObjectRef bestChild$1; private final DoubleRef bestGrowth$1; private final DoubleRef bestVolume$1; public RTree$NonLeaf$$anonfun$li$cil$oc$util$RTree$NonLeaf$$uncheckedAdd$2(RTree.NonLeaf $outer, RTree.Node value$2, ObjectRef bestChild$1, DoubleRef bestGrowth$1, DoubleRef bestVolume$1) {} public final void apply(RTree.Node child) { double oldVolume = child.bounds().volume(); double volume = child.bounds().including(this.value$2.bounds()).volume(); double growth = volume - oldVolume; if (growth < this.bestGrowth$1.elem || (growth == this.bestGrowth$1.elem && volume < this.bestVolume$1.elem)) { this.bestChild$1.elem = new Some(child); this.bestGrowth$1.elem = growth; this.bestVolume$1.elem = volume; }  } }
/* 119 */     public Option<RTree<Data>.Node> remove(RTree.Node value) { Object object = new Object(); try {
/* 120 */         if (bounds().intersects(value.bounds())) children().foreach((Function1)new RTree$NonLeaf$$anonfun$remove$1(this, value, (NonLeaf)object));
/*     */       
/*     */       } catch (NonLocalReturnControl nonLocalReturnControl) {
/*     */         if (nonLocalReturnControl.key() == object) {
/*     */           return (Option<RTree<Data>.Node>)nonLocalReturnControl.value();
/*     */         }
/*     */       } 
/*     */ 
/*     */ 
/*     */ 
/*     */ 
/*     */ 
/*     */ 
/*     */ 
/*     */ 
/*     */ 
/*     */ 
/*     */ 
/*     */ 
/*     */ 
/*     */ 
/*     */ 
/*     */ 
/*     */ 
/*     */ 
/*     */ 
/*     */ 
/*     */ 
/*     */ 
/*     */ 
/*     */ 
/*     */ 
/*     */ 
/*     */ 
/*     */ 
/*     */ 
/*     */ 
/*     */ 
/*     */ 
/*     */ 
/*     */ 
/*     */ 
/*     */ 
/*     */ 
/*     */ 
/*     */ 
/*     */       
/* 167 */       return (Option<RTree<Data>.Node>)scala.None$.MODULE$; } public final class RTree$NonLeaf$$anonfun$remove$1 extends AbstractFunction1<RTree<Data>.Node, BoxedUnit> implements Serializable {
/*     */       public static final long serialVersionUID = 0L; private final RTree.Node value$1; private final Object nonLocalReturnKey1$1; public RTree$NonLeaf$$anonfun$remove$1(RTree.NonLeaf $outer, RTree.Node value$1, Object nonLocalReturnKey1$1) {} public final void apply(RTree.Node child) { // Byte code:
/*     */         //   0: aload_1
/*     */         //   1: aload_0
/*     */         //   2: getfield value$1 : Lli/cil/oc/util/RTree$Node;
/*     */         //   5: invokevirtual remove : (Lli/cil/oc/util/RTree$Node;)Lscala/Option;
/*     */         //   8: astore_2
/*     */         //   9: aload_2
/*     */         //   10: instanceof scala/Some
/*     */         //   13: ifeq -> 533
/*     */         //   16: aload_2
/*     */         //   17: checkcast scala/Some
/*     */         //   20: astore_3
/*     */         //   21: aload_3
/*     */         //   22: invokevirtual x : ()Ljava/lang/Object;
/*     */         //   25: checkcast li/cil/oc/util/RTree$Node
/*     */         //   28: astore #4
/*     */         //   30: aload #4
/*     */         //   32: aload_1
/*     */         //   33: astore #6
/*     */         //   35: dup
/*     */         //   36: ifnonnull -> 48
/*     */         //   39: pop
/*     */         //   40: aload #6
/*     */         //   42: ifnull -> 56
/*     */         //   45: goto -> 333
/*     */         //   48: aload #6
/*     */         //   50: invokevirtual equals : (Ljava/lang/Object;)Z
/*     */         //   53: ifeq -> 333
/*     */         //   56: aload_0
/*     */         //   57: getfield $outer : Lli/cil/oc/util/RTree$NonLeaf;
/*     */         //   60: invokevirtual children : ()Lscala/collection/mutable/Set;
/*     */         //   63: aload_1
/*     */         //   64: invokeinterface $minus$eq : (Ljava/lang/Object;)Lscala/collection/mutable/SetLike;
/*     */         //   69: pop
/*     */         //   70: aload_1
/*     */         //   71: astore #7
/*     */         //   73: aload #7
/*     */         //   75: instanceof li/cil/oc/util/RTree$NonLeaf
/*     */         //   78: ifeq -> 165
/*     */         //   81: aload #7
/*     */         //   83: checkcast li/cil/oc/util/RTree$NonLeaf
/*     */         //   86: astore #8
/*     */         //   88: aload #8
/*     */         //   90: invokevirtual children : ()Lscala/collection/mutable/Set;
/*     */         //   93: new li/cil/oc/util/RTree$NonLeaf$$anonfun$remove$1$$anonfun$apply$3
/*     */         //   96: dup
/*     */         //   97: aload_0
/*     */         //   98: invokespecial <init> : (Lli/cil/oc/util/RTree$NonLeaf$$anonfun$remove$1;)V
/*     */         //   101: invokeinterface foreach : (Lscala/Function1;)V
/*     */         //   106: aload_0
/*     */         //   107: getfield $outer : Lli/cil/oc/util/RTree$NonLeaf;
/*     */         //   110: invokevirtual children : ()Lscala/collection/mutable/Set;
/*     */         //   113: invokeinterface size : ()I
/*     */         //   118: aload_0
/*     */         //   119: getfield $outer : Lli/cil/oc/util/RTree$NonLeaf;
/*     */         //   122: invokevirtual li$cil$oc$util$RTree$NonLeaf$$$outer : ()Lli/cil/oc/util/RTree;
/*     */         //   125: invokevirtual li$cil$oc$util$RTree$$M : ()I
/*     */         //   128: if_icmple -> 157
/*     */         //   131: new scala/runtime/NonLocalReturnControl
/*     */         //   134: dup
/*     */         //   135: aload_0
/*     */         //   136: getfield nonLocalReturnKey1$1 : Ljava/lang/Object;
/*     */         //   139: new scala/Some
/*     */         //   142: dup
/*     */         //   143: aload_0
/*     */         //   144: getfield $outer : Lli/cil/oc/util/RTree$NonLeaf;
/*     */         //   147: invokevirtual li$cil$oc$util$RTree$NonLeaf$$split : ()Lli/cil/oc/util/RTree$NonLeaf;
/*     */         //   150: invokespecial <init> : (Ljava/lang/Object;)V
/*     */         //   153: invokespecial <init> : (Ljava/lang/Object;Ljava/lang/Object;)V
/*     */         //   156: athrow
/*     */         //   157: getstatic scala/runtime/BoxedUnit.UNIT : Lscala/runtime/BoxedUnit;
/*     */         //   160: astore #9
/*     */         //   162: goto -> 225
/*     */         //   165: aload #7
/*     */         //   167: instanceof li/cil/oc/util/RTree$Leaf
/*     */         //   170: ifeq -> 323
/*     */         //   173: aload #7
/*     */         //   175: checkcast li/cil/oc/util/RTree$Leaf
/*     */         //   178: astore #10
/*     */         //   180: getstatic scala/Predef$.MODULE$ : Lscala/Predef$;
/*     */         //   183: aload #10
/*     */         //   185: aload_0
/*     */         //   186: getfield value$1 : Lli/cil/oc/util/RTree$Node;
/*     */         //   189: astore #11
/*     */         //   191: dup
/*     */         //   192: ifnonnull -> 204
/*     */         //   195: pop
/*     */         //   196: aload #11
/*     */         //   198: ifnull -> 212
/*     */         //   201: goto -> 216
/*     */         //   204: aload #11
/*     */         //   206: invokevirtual equals : (Ljava/lang/Object;)Z
/*     */         //   209: ifeq -> 216
/*     */         //   212: iconst_1
/*     */         //   213: goto -> 217
/*     */         //   216: iconst_0
/*     */         //   217: invokevirtual assert : (Z)V
/*     */         //   220: getstatic scala/runtime/BoxedUnit.UNIT : Lscala/runtime/BoxedUnit;
/*     */         //   223: astore #9
/*     */         //   225: aload_0
/*     */         //   226: getfield $outer : Lli/cil/oc/util/RTree$NonLeaf;
/*     */         //   229: invokevirtual children : ()Lscala/collection/mutable/Set;
/*     */         //   232: invokeinterface size : ()I
/*     */         //   237: aload_0
/*     */         //   238: getfield $outer : Lli/cil/oc/util/RTree$NonLeaf;
/*     */         //   241: invokevirtual li$cil$oc$util$RTree$NonLeaf$$$outer : ()Lli/cil/oc/util/RTree;
/*     */         //   244: invokevirtual li$cil$oc$util$RTree$$m : ()I
/*     */         //   247: if_icmpge -> 273
/*     */         //   250: new scala/runtime/NonLocalReturnControl
/*     */         //   253: dup
/*     */         //   254: aload_0
/*     */         //   255: getfield nonLocalReturnKey1$1 : Ljava/lang/Object;
/*     */         //   258: new scala/Some
/*     */         //   261: dup
/*     */         //   262: aload_0
/*     */         //   263: getfield $outer : Lli/cil/oc/util/RTree$NonLeaf;
/*     */         //   266: invokespecial <init> : (Ljava/lang/Object;)V
/*     */         //   269: invokespecial <init> : (Ljava/lang/Object;Ljava/lang/Object;)V
/*     */         //   272: athrow
/*     */         //   273: aload_0
/*     */         //   274: getfield $outer : Lli/cil/oc/util/RTree$NonLeaf;
/*     */         //   277: aload_0
/*     */         //   278: getfield $outer : Lli/cil/oc/util/RTree$NonLeaf;
/*     */         //   281: invokevirtual li$cil$oc$util$RTree$NonLeaf$$$outer : ()Lli/cil/oc/util/RTree;
/*     */         //   284: invokevirtual li$cil$oc$util$RTree$$Rectangle : ()Lli/cil/oc/util/RTree$Rectangle$;
/*     */         //   287: aload_0
/*     */         //   288: getfield $outer : Lli/cil/oc/util/RTree$NonLeaf;
/*     */         //   291: invokevirtual children : ()Lscala/collection/mutable/Set;
/*     */         //   294: invokevirtual around : (Lscala/collection/Iterable;)Lli/cil/oc/util/RTree$Rectangle;
/*     */         //   297: invokevirtual bounds_$eq : (Lli/cil/oc/util/RTree$Rectangle;)V
/*     */         //   300: new scala/runtime/NonLocalReturnControl
/*     */         //   303: dup
/*     */         //   304: aload_0
/*     */         //   305: getfield nonLocalReturnKey1$1 : Ljava/lang/Object;
/*     */         //   308: new scala/Some
/*     */         //   311: dup
/*     */         //   312: aload_0
/*     */         //   313: getfield value$1 : Lli/cil/oc/util/RTree$Node;
/*     */         //   316: invokespecial <init> : (Ljava/lang/Object;)V
/*     */         //   319: invokespecial <init> : (Ljava/lang/Object;Ljava/lang/Object;)V
/*     */         //   322: athrow
/*     */         //   323: new scala/MatchError
/*     */         //   326: dup
/*     */         //   327: aload #7
/*     */         //   329: invokespecial <init> : (Ljava/lang/Object;)V
/*     */         //   332: athrow
/*     */         //   333: aload #4
/*     */         //   335: aload_0
/*     */         //   336: getfield value$1 : Lli/cil/oc/util/RTree$Node;
/*     */         //   339: astore #12
/*     */         //   341: dup
/*     */         //   342: ifnonnull -> 354
/*     */         //   345: pop
/*     */         //   346: aload #12
/*     */         //   348: ifnull -> 362
/*     */         //   351: goto -> 412
/*     */         //   354: aload #12
/*     */         //   356: invokevirtual equals : (Ljava/lang/Object;)Z
/*     */         //   359: ifeq -> 412
/*     */         //   362: aload_0
/*     */         //   363: getfield $outer : Lli/cil/oc/util/RTree$NonLeaf;
/*     */         //   366: aload_0
/*     */         //   367: getfield $outer : Lli/cil/oc/util/RTree$NonLeaf;
/*     */         //   370: invokevirtual li$cil$oc$util$RTree$NonLeaf$$$outer : ()Lli/cil/oc/util/RTree;
/*     */         //   373: invokevirtual li$cil$oc$util$RTree$$Rectangle : ()Lli/cil/oc/util/RTree$Rectangle$;
/*     */         //   376: aload_0
/*     */         //   377: getfield $outer : Lli/cil/oc/util/RTree$NonLeaf;
/*     */         //   380: invokevirtual children : ()Lscala/collection/mutable/Set;
/*     */         //   383: invokevirtual around : (Lscala/collection/Iterable;)Lli/cil/oc/util/RTree$Rectangle;
/*     */         //   386: invokevirtual bounds_$eq : (Lli/cil/oc/util/RTree$Rectangle;)V
/*     */         //   389: new scala/runtime/NonLocalReturnControl
/*     */         //   392: dup
/*     */         //   393: aload_0
/*     */         //   394: getfield nonLocalReturnKey1$1 : Ljava/lang/Object;
/*     */         //   397: new scala/Some
/*     */         //   400: dup
/*     */         //   401: aload_0
/*     */         //   402: getfield value$1 : Lli/cil/oc/util/RTree$Node;
/*     */         //   405: invokespecial <init> : (Ljava/lang/Object;)V
/*     */         //   408: invokespecial <init> : (Ljava/lang/Object;Ljava/lang/Object;)V
/*     */         //   411: athrow
/*     */         //   412: getstatic scala/Predef$.MODULE$ : Lscala/Predef$;
/*     */         //   415: aload #4
/*     */         //   417: instanceof li/cil/oc/util/RTree$NonLeaf
/*     */         //   420: invokevirtual assert : (Z)V
/*     */         //   423: aload_0
/*     */         //   424: getfield $outer : Lli/cil/oc/util/RTree$NonLeaf;
/*     */         //   427: aload #4
/*     */         //   429: invokevirtual li$cil$oc$util$RTree$NonLeaf$$uncheckedAdd : (Lli/cil/oc/util/RTree$Node;)V
/*     */         //   432: aload_0
/*     */         //   433: getfield $outer : Lli/cil/oc/util/RTree$NonLeaf;
/*     */         //   436: invokevirtual children : ()Lscala/collection/mutable/Set;
/*     */         //   439: invokeinterface size : ()I
/*     */         //   444: aload_0
/*     */         //   445: getfield $outer : Lli/cil/oc/util/RTree$NonLeaf;
/*     */         //   448: invokevirtual li$cil$oc$util$RTree$NonLeaf$$$outer : ()Lli/cil/oc/util/RTree;
/*     */         //   451: invokevirtual li$cil$oc$util$RTree$$M : ()I
/*     */         //   454: if_icmple -> 483
/*     */         //   457: new scala/runtime/NonLocalReturnControl
/*     */         //   460: dup
/*     */         //   461: aload_0
/*     */         //   462: getfield nonLocalReturnKey1$1 : Ljava/lang/Object;
/*     */         //   465: new scala/Some
/*     */         //   468: dup
/*     */         //   469: aload_0
/*     */         //   470: getfield $outer : Lli/cil/oc/util/RTree$NonLeaf;
/*     */         //   473: invokevirtual li$cil$oc$util$RTree$NonLeaf$$split : ()Lli/cil/oc/util/RTree$NonLeaf;
/*     */         //   476: invokespecial <init> : (Ljava/lang/Object;)V
/*     */         //   479: invokespecial <init> : (Ljava/lang/Object;Ljava/lang/Object;)V
/*     */         //   482: athrow
/*     */         //   483: aload_0
/*     */         //   484: getfield $outer : Lli/cil/oc/util/RTree$NonLeaf;
/*     */         //   487: aload_0
/*     */         //   488: getfield $outer : Lli/cil/oc/util/RTree$NonLeaf;
/*     */         //   491: invokevirtual li$cil$oc$util$RTree$NonLeaf$$$outer : ()Lli/cil/oc/util/RTree;
/*     */         //   494: invokevirtual li$cil$oc$util$RTree$$Rectangle : ()Lli/cil/oc/util/RTree$Rectangle$;
/*     */         //   497: aload_0
/*     */         //   498: getfield $outer : Lli/cil/oc/util/RTree$NonLeaf;
/*     */         //   501: invokevirtual children : ()Lscala/collection/mutable/Set;
/*     */         //   504: invokevirtual around : (Lscala/collection/Iterable;)Lli/cil/oc/util/RTree$Rectangle;
/*     */         //   507: invokevirtual bounds_$eq : (Lli/cil/oc/util/RTree$Rectangle;)V
/*     */         //   510: new scala/runtime/NonLocalReturnControl
/*     */         //   513: dup
/*     */         //   514: aload_0
/*     */         //   515: getfield nonLocalReturnKey1$1 : Ljava/lang/Object;
/*     */         //   518: new scala/Some
/*     */         //   521: dup
/*     */         //   522: aload_0
/*     */         //   523: getfield value$1 : Lli/cil/oc/util/RTree$Node;
/*     */         //   526: invokespecial <init> : (Ljava/lang/Object;)V
/*     */         //   529: invokespecial <init> : (Ljava/lang/Object;Ljava/lang/Object;)V
/*     */         //   532: athrow
/*     */         //   533: getstatic scala/runtime/BoxedUnit.UNIT : Lscala/runtime/BoxedUnit;
/*     */         //   536: astore #5
/*     */         //   538: return
/*     */         // Line number table:
/*     */         //   Java source line number -> byte code offset
/*     */         //   #121	-> 0
/*     */         //   #122	-> 9
/*     */         //   #123	-> 30
/*     */         //   #125	-> 56
/*     */         //   #126	-> 70
/*     */         //   #127	-> 73
/*     */         //   #128	-> 88
/*     */         //   #131	-> 106
/*     */         //   #133	-> 131
/*     */         //   #131	-> 157
/*     */         //   #127	-> 160
/*     */         //   #135	-> 165
/*     */         //   #137	-> 225
/*     */         //   #139	-> 250
/*     */         //   #142	-> 273
/*     */         //   #143	-> 300
/*     */         //   #126	-> 323
/*     */         //   #145	-> 333
/*     */         //   #147	-> 362
/*     */         //   #148	-> 389
/*     */         //   #152	-> 412
/*     */         //   #153	-> 423
/*     */         //   #154	-> 432
/*     */         //   #156	-> 457
/*     */         //   #160	-> 483
/*     */         //   #161	-> 510
/*     */         //   #164	-> 533
/*     */         //   #121	-> 538
/*     */         // Local variable table:
/*     */         //   start	length	slot	name	descriptor
/*     */         //   0	539	0	this	Lli/cil/oc/util/RTree$NonLeaf$$anonfun$remove$1;
/*     */         //   0	539	1	child	Lli/cil/oc/util/RTree$Node;
/*     */         //   30	509	4	change	Lli/cil/oc/util/RTree$Node; } public final class RTree$NonLeaf$$anonfun$remove$1$$anonfun$apply$3 extends AbstractFunction1<RTree<Data>.Node, BoxedUnit> implements Serializable {
/*     */         public static final long serialVersionUID = 0L; public RTree$NonLeaf$$anonfun$remove$1$$anonfun$apply$3(RTree$NonLeaf$$anonfun$remove$1 $outer) {}
/*     */         public final void apply(RTree.Node child) { this.$outer.li$cil$oc$util$RTree$NonLeaf$$anonfun$$$outer().li$cil$oc$util$RTree$NonLeaf$$uncheckedAdd(child); } } }
/* 171 */     public Iterable<Data> query(RTree.Rectangle query) { return query.intersects(bounds()) ? 
/* 172 */         (Iterable<Data>)children().foldRight(scala.package$.MODULE$.Iterable().empty(), (Function2)new RTree$NonLeaf$$anonfun$query$1(this, (NonLeaf)query)) : 
/* 173 */         (Iterable<Data>)scala.package$.MODULE$.Iterable().empty(); } public final class RTree$NonLeaf$$anonfun$query$1 extends AbstractFunction2<RTree<Data>.Node, Iterable<Data>, Iterable<Data>> implements Serializable {
/*     */       public static final long serialVersionUID = 0L; private final RTree.Rectangle query$1; public final Iterable<Data> apply(RTree.Node child, Iterable result) { return (Iterable<Data>)result.$plus$plus((GenTraversableOnce)child.query(this.query$1), scala.collection.Iterable$.MODULE$.canBuildFrom()); }
/*     */       public RTree$NonLeaf$$anonfun$query$1(RTree.NonLeaf $outer, RTree.Rectangle query$1) {} }
/* 176 */     public NonLeaf li$cil$oc$util$RTree$NonLeaf$$split() { RTree.Node[] values = (RTree.Node[])children().toArray(scala.reflect.ClassTag$.MODULE$.apply(RTree.Node.class));
/* 177 */       ObjectRef seed1 = ObjectRef.create(scala.None$.MODULE$);
/* 178 */       ObjectRef seed2 = ObjectRef.create(scala.None$.MODULE$);
/* 179 */       DoubleRef worst = DoubleRef.create(Double.NEGATIVE_INFINITY);
/* 180 */       scala.Predef$.MODULE$.refArrayOps((Object[])values).indices().foreach$mVc$sp((Function1)new RTree$NonLeaf$$anonfun$li$cil$oc$util$RTree$NonLeaf$$split$1(this, values, seed1, seed2, (NonLeaf)worst));
/*     */ 
/*     */ 
/*     */ 
/*     */ 
/*     */ 
/*     */ 
/*     */ 
/*     */ 
/*     */ 
/*     */ 
/*     */ 
/*     */ 
/*     */ 
/*     */       
/* 195 */       Tuple2 tuple2 = new Tuple2(seed1.elem, seed2.elem); if (tuple2 != null) {
/* 196 */         Option option1 = (Option)tuple2._1(), option2 = (Option)tuple2._2(); if (option1 instanceof Some) { Some some = (Some)option1; RTree.Node s1 = (RTree.Node)some.x(); if (option2 instanceof Some) { Some some1 = (Some)option2; RTree.Node s2 = (RTree.Node)some1.x();
/* 197 */             (new RTree.Node[1])[0] = s1; RTree.SplitResult r1 = new RTree.SplitResult(li$cil$oc$util$RTree$NonLeaf$$$outer(), (Set<RTree<Data>.Node>)scala.collection.mutable.Set$.MODULE$.apply((Seq)scala.Predef$.MODULE$.wrapRefArray((Object[])new RTree.Node[1])), s1.bounds());
/* 198 */             (new RTree.Node[1])[0] = s2; RTree.SplitResult r2 = new RTree.SplitResult(li$cil$oc$util$RTree$NonLeaf$$$outer(), (Set<RTree<Data>.Node>)scala.collection.mutable.Set$.MODULE$.apply((Seq)scala.Predef$.MODULE$.wrapRefArray((Object[])new RTree.Node[1])), s2.bounds());
/*     */             
/* 200 */             Set list = scala.collection.mutable.Set$.MODULE$.empty().$plus$plus((GenTraversableOnce)scala.Predef$.MODULE$.refArrayOps((Object[])values));
/* 201 */             list.$minus$eq(s1);
/* 202 */             list.$minus$eq(s2);
/* 203 */             while (list.nonEmpty()) {
/* 204 */               if (li$cil$oc$util$RTree$NonLeaf$$$outer().li$cil$oc$util$RTree$$m() - r1.set().size() >= list.size()) {
/* 205 */                 list.foreach((Function1)new RTree$NonLeaf$$anonfun$li$cil$oc$util$RTree$NonLeaf$$split$2(this, (NonLeaf)r1));
/* 206 */                 list.clear(); continue;
/*     */               } 
/* 208 */               if (li$cil$oc$util$RTree$NonLeaf$$$outer().li$cil$oc$util$RTree$$m() - r2.set().size() >= list.size()) {
/* 209 */                 list.foreach((Function1)new RTree$NonLeaf$$anonfun$li$cil$oc$util$RTree$NonLeaf$$split$3(this, (NonLeaf)r2));
/* 210 */                 list.clear();
/*     */                 continue;
/*     */               } 
/* 213 */               ObjectRef bestValue = ObjectRef.create(scala.None$.MODULE$);
/* 214 */               ObjectRef r = ObjectRef.create(r1);
/* 215 */               DoubleRef best = DoubleRef.create(Double.NEGATIVE_INFINITY);
/* 216 */               list.foreach((Function1)new RTree$NonLeaf$$anonfun$li$cil$oc$util$RTree$NonLeaf$$split$4(this, r1, r2, bestValue, r, (NonLeaf)best));
/*     */ 
/*     */ 
/*     */ 
/*     */ 
/*     */ 
/*     */ 
/*     */ 
/*     */ 
/*     */ 
/*     */ 
/*     */               
/* 228 */               Option option = (Option)bestValue.elem;
/* 229 */               if (option instanceof Some) { Some some2 = (Some)option; RTree.Node value = (RTree.Node)some2.x();
/* 230 */                 list.$minus$eq(value);
/* 231 */                 ((RTree.SplitResult)r.elem).add(value); BoxedUnit boxedUnit = BoxedUnit.UNIT; continue; }
/* 232 */                throw new AssertionError();
/*     */             } 
/*     */ 
/*     */ 
/*     */             
/* 237 */             children().clear();
/* 238 */             children().$plus$plus$eq((TraversableOnce)r1.set());
/* 239 */             bounds_$eq(r1.bounds());
/*     */             
/* 241 */             NonLeaf LL = new NonLeaf();
/* 242 */             LL.children().$plus$plus$eq((TraversableOnce)r2.set());
/* 243 */             LL.bounds_$eq(r2.bounds());
/* 244 */             return LL; }  } 
/* 245 */       }  throw new AssertionError(); } public final class RTree$NonLeaf$$anonfun$li$cil$oc$util$RTree$NonLeaf$$split$1 extends AbstractFunction1.mcVI.sp implements Serializable {
/*     */       public static final long serialVersionUID = 0L; public final RTree.Node[] values$1; public final ObjectRef seed1$1; public final ObjectRef seed2$1; public final DoubleRef worst$1; public final void apply(int i) { apply$mcVI$sp(i); } public RTree$NonLeaf$$anonfun$li$cil$oc$util$RTree$NonLeaf$$split$1(RTree.NonLeaf $outer, RTree.Node[] values$1, ObjectRef seed1$1, ObjectRef seed2$1, DoubleRef worst$1) {} public void apply$mcVI$sp(int i) { RTree.Node si = this.values$1[i]; scala.runtime.RichInt$.MODULE$.until$extension0(scala.Predef$.MODULE$.intWrapper(i + 1), this.values$1.length).foreach$mVc$sp((Function1)new RTree$NonLeaf$$anonfun$li$cil$oc$util$RTree$NonLeaf$$split$1$$anonfun$apply$mcVI$sp$1(this, (NonLeaf$$anonfun$li$cil$oc$util$RTree$NonLeaf$$split$1)si)); } public final class RTree$NonLeaf$$anonfun$li$cil$oc$util$RTree$NonLeaf$$split$1$$anonfun$apply$mcVI$sp$1 extends AbstractFunction1.mcVI.sp implements Serializable {
/*     */         public static final long serialVersionUID = 0L; private final RTree.Node si$1; public final void apply(int j) { apply$mcVI$sp(j); } public RTree$NonLeaf$$anonfun$li$cil$oc$util$RTree$NonLeaf$$split$1$$anonfun$apply$mcVI$sp$1(RTree$NonLeaf$$anonfun$li$cil$oc$util$RTree$NonLeaf$$split$1 $outer, RTree.Node si$1) {} public void apply$mcVI$sp(int j) { RTree.Node sj = this.$outer.values$1[j]; double vol1 = this.si$1.bounds().volume(); double vol2 = sj.bounds().volume(); double vol = this.si$1.bounds().including(sj.bounds()).volume(); double d = vol - vol1 - vol2; if (d > this.$outer.worst$1.elem) { this.$outer.seed1$1.elem = new Some(this.si$1); this.$outer.seed2$1.elem = new Some(sj); this.$outer.worst$1.elem = d; }  } } } public final class RTree$NonLeaf$$anonfun$li$cil$oc$util$RTree$NonLeaf$$split$2 extends AbstractFunction1<RTree<Data>.Node, BoxedUnit> implements Serializable {
/*     */       public static final long serialVersionUID = 0L; private final RTree.SplitResult r1$1; public final void apply(RTree.Node value) { this.r1$1.add(value); } public RTree$NonLeaf$$anonfun$li$cil$oc$util$RTree$NonLeaf$$split$2(RTree.NonLeaf $outer, RTree.SplitResult r1$1) {} } public final class RTree$NonLeaf$$anonfun$li$cil$oc$util$RTree$NonLeaf$$split$3 extends AbstractFunction1<RTree<Data>.Node, BoxedUnit> implements Serializable {
/*     */       public static final long serialVersionUID = 0L; private final RTree.SplitResult r2$1; public final void apply(RTree.Node value) { this.r2$1.add(value); } public RTree$NonLeaf$$anonfun$li$cil$oc$util$RTree$NonLeaf$$split$3(RTree.NonLeaf $outer, RTree.SplitResult r2$1) {} } public final class RTree$NonLeaf$$anonfun$li$cil$oc$util$RTree$NonLeaf$$split$4 extends AbstractFunction1<RTree<Data>.Node, BoxedUnit> implements Serializable { public static final long serialVersionUID = 0L; private final RTree.SplitResult r1$1; private final RTree.SplitResult r2$1; private final ObjectRef bestValue$1; private final ObjectRef r$1; private final DoubleRef best$1; public RTree$NonLeaf$$anonfun$li$cil$oc$util$RTree$NonLeaf$$split$4(RTree.NonLeaf $outer, RTree.SplitResult r1$1, RTree.SplitResult r2$1, ObjectRef bestValue$1, ObjectRef r$1, DoubleRef best$1) {} public final void apply(RTree.Node value) { double newVol1 = this.r1$1.volumeIncluding(value); double newVol2 = this.r2$1.volumeIncluding(value); double growth1 = newVol1 - this.r1$1.volume(); double growth2 = newVol2 - this.r2$1.volume(); double d = scala.math.package$.MODULE$.abs(growth2 - growth1); if (d > this.best$1.elem) { this.bestValue$1.elem = new Some(value); this.r$1.elem = (growth1 < growth2 || (growth1 == growth2 && newVol1 < newVol2)) ? this.r1$1 : this.r2$1; this.best$1.elem = d; }  } }
/* 250 */   } public class Leaf extends Node { private final Data data; public Data data() { return this.data; } private final RTree<Data>.Rectangle bounds; public Leaf(RTree<Data> $outer, Object data, RTree.Point point) { super($outer);
/* 251 */       this.bounds = new RTree.Rectangle($outer, point, point); } public RTree<Data>.Rectangle bounds() { return this.bounds; }
/*     */      public Iterable<Leaf> entries() {
/* 253 */       (new Leaf[1])[0] = this; return (Iterable<Leaf>)scala.package$.MODULE$.Iterable().apply((Seq)scala.Predef$.MODULE$.wrapRefArray((Object[])new Leaf[1]));
/*     */     } public RTree<Data>.Node add(RTree.Node value) {
/* 255 */       return value;
/*     */     }
/*     */     public Option<RTree<Data>.Node> remove(RTree.Node value) {
/* 258 */       Leaf leaf = this; if (value == null) { if (leaf != null); } else if (value.equals(leaf))
/*     */       {  }
/*     */     
/*     */     } public Iterable<Data> query(RTree.Rectangle query) {
/* 262 */       return query.intersects(bounds()) ? (Iterable<Data>)scala.package$.MODULE$.Iterable().apply((Seq)scala.Predef$.MODULE$.genericWrapArray(new Object[] { data()
/* 263 */             })) : (Iterable<Data>)scala.package$.MODULE$.Iterable().empty();
/*     */     } }
/*     */   public class Point { private final double x; private final double y; private final double z;
/* 266 */     public double x() { return this.x; } public double y() { return this.y; } public double z() { return this.z; } public Point(RTree $outer, double x, double y, double z) {} public Point(Tuple3 p) {
/* 267 */       this(BoxesRunTime.unboxToDouble(p._1()), BoxesRunTime.unboxToDouble(p._2()), BoxesRunTime.unboxToDouble(p._3()));
/*     */     } public Point min(Point other) {
/* 269 */       return new Point(scala.math.package$.MODULE$.min(x(), other.x()), scala.math.package$.MODULE$.min(y(), other.y()), scala.math.package$.MODULE$.min(z(), other.z()));
/*     */     } public Point max(Point other) {
/* 271 */       return new Point(scala.math.package$.MODULE$.max(x(), other.x()), scala.math.package$.MODULE$.max(y(), other.y()), scala.math.package$.MODULE$.max(z(), other.z()));
/*     */     } public Tuple3<Object, Object, Object> asTuple() {
/* 273 */       return new Tuple3(BoxesRunTime.boxToDouble(x()), BoxesRunTime.boxToDouble(y()), BoxesRunTime.boxToDouble(z()));
/*     */     } }
/*     */   
/* 276 */   private Point$ li$cil$oc$util$RTree$$Point$lzycompute() { synchronized (this) { if (this.Point$module == null) this.Point$module = new Point$(this);  null; return this.Point$module; }  } public Point$ li$cil$oc$util$RTree$$Point() { return (this.Point$module == null) ? li$cil$oc$util$RTree$$Point$lzycompute() : this.Point$module; }
/* 277 */    public class Point$ { private final RTree<Data>.Point NegativeInfinity = new RTree.Point(Double.NEGATIVE_INFINITY, Double.NEGATIVE_INFINITY, Double.NEGATIVE_INFINITY); public RTree<Data>.Point NegativeInfinity() { return this.NegativeInfinity; }
/* 278 */      private final RTree<Data>.Point PositiveInfinity = new RTree.Point(Double.POSITIVE_INFINITY, Double.POSITIVE_INFINITY, Double.POSITIVE_INFINITY); public RTree<Data>.Point PositiveInfinity() { return this.PositiveInfinity; }
/*     */      public Point$(RTree<Data> $outer) {} }
/*     */   public class Rectangle { private final RTree<Data>.Point min; private final RTree<Data>.Point max;
/* 281 */     public RTree<Data>.Point min() { return this.min; } public RTree<Data>.Point max() { return this.max; } public Rectangle(RTree $outer, RTree.Point min, RTree.Point max) {} public Rectangle including(Rectangle value) {
/* 282 */       return new Rectangle(li$cil$oc$util$RTree$Rectangle$$$outer(), value.min().min(min()), value.max().max(max()));
/*     */     }
/*     */     public boolean intersects(Rectangle value) {
/* 285 */       return (value.min().x() <= max().x() && value.min().y() <= max().y() && value.min().z() <= max().z() && 
/* 286 */         value.max().x() >= min().x() && value.max().y() >= min().y() && value.max().z() >= min().z());
/*     */     }
/*     */     public double volume() {
/* 289 */       double sx = max().x() - min().x();
/* 290 */       double sy = max().y() - min().y();
/* 291 */       double sz = max().z() - min().z();
/* 292 */       return sx * sy * sz;
/*     */     }
/*     */     public Tuple2<Tuple3<Object, Object, Object>, Tuple3<Object, Object, Object>> asTuple() {
/* 295 */       return new Tuple2(new Tuple3(BoxesRunTime.boxToDouble(min().x()), BoxesRunTime.boxToDouble(min().y()), BoxesRunTime.boxToDouble(min().z())), new Tuple3(BoxesRunTime.boxToDouble(max().x()), BoxesRunTime.boxToDouble(max().y()), BoxesRunTime.boxToDouble(max().z())));
/*     */     } }
/*     */   
/* 298 */   private Rectangle$ li$cil$oc$util$RTree$$Rectangle$lzycompute() { synchronized (this) { if (this.Rectangle$module == null) this.Rectangle$module = new Rectangle$(this);  null; return this.Rectangle$module; }  } public Rectangle$ li$cil$oc$util$RTree$$Rectangle() { return (this.Rectangle$module == null) ? li$cil$oc$util$RTree$$Rectangle$lzycompute() : this.Rectangle$module; }
/*     */    public class Rectangle$ { public Rectangle$(RTree $outer) {}
/* 300 */     public RTree<Data>.Rectangle around(Iterable values) { ObjectRef min = ObjectRef.create(this.$outer.li$cil$oc$util$RTree$$Point().PositiveInfinity());
/* 301 */       ObjectRef max = ObjectRef.create(this.$outer.li$cil$oc$util$RTree$$Point().NegativeInfinity());
/* 302 */       values.foreach((Function1)new RTree$Rectangle$$anonfun$around$1(this, min, (Rectangle$)max));
/*     */ 
/*     */ 
/*     */       
/* 306 */       return new RTree.Rectangle(this.$outer, (RTree.Point)min.elem, (RTree.Point)max.elem); } public final class RTree$Rectangle$$anonfun$around$1 extends AbstractFunction1<RTree<Data>.Node, BoxedUnit> implements Serializable {
/*     */       public static final long serialVersionUID = 0L; private final ObjectRef min$1; private final ObjectRef max$1; public RTree$Rectangle$$anonfun$around$1(RTree.Rectangle$ $outer, ObjectRef min$1, ObjectRef max$1) {} public final void apply(RTree.Node value) { this.min$1.elem = value.bounds().min().min((RTree.Point)this.min$1.elem);
/*     */         this.max$1.elem = value.bounds().max().max((RTree.Point)this.max$1.elem); } } }
/*     */   public class SplitResult { private final Set<RTree<Data>.Node> set; private RTree<Data>.Rectangle bounds;
/* 310 */     public Set<RTree<Data>.Node> set() { return this.set; } public RTree<Data>.Rectangle bounds() { return this.bounds; } public void bounds_$eq(RTree.Rectangle x$1) { this.bounds = x$1; }
/*     */      public SplitResult(RTree $outer, Set<RTree<Data>.Node> set, RTree.Rectangle bounds) {} public void add(RTree.Node value) {
/* 312 */       set().$plus$eq(value);
/* 313 */       bounds_$eq(bounds().including(value.bounds()));
/*     */     }
/*     */     public double volume() {
/* 316 */       return bounds().volume();
/*     */     } public double volumeIncluding(RTree.Node value) {
/* 318 */       return bounds().including(value.bounds()).volume();
/*     */     } }
/*     */    }


/* Location:              C:\Users\shame\AppData\Roaming\PrismLauncher\instances\GT_New_Horizons_2.7.4_Java_17-21\.minecraft\mods\OpenComputers-1.10.30-GTNH.jar!\li\cil\o\\util\RTree.class
 * Java compiler version: 8 (52.0)
 * JD-Core Version:       1.1.3
 */