/*     */ package li.cil.oc.common.tileentity;
/*     */ 
/*     */ 
/*     */ @ScalaSignature(bytes = "\006\001\ree\001B\001\003\0015\021q\"T5de>\034wN\034;s_2dWM\035\006\003\007\021\t!\002^5mK\026tG/\033;z\025\t)a!\001\004d_6lwN\034\006\003\017!\t!a\\2\013\005%Q\021aA2jY*\t1\"\001\002mS\016\0011\003\003\001\017/u\0013%\013\031\021\005=)R\"\001\t\013\005\r\t\"B\001\n\024\003%i\027N\\3de\0064GOC\001\025\003\rqW\r^\005\003-A\021!\002V5mK\026sG/\033;z!\tA2$D\001\032\025\tQ\"!\001\004ue\006LGo]\005\0039e\021Q\002U8xKJ\f5mY3qi>\024\bC\001\r\037\023\ty\022DA\002Ik\n\004\"\001G\021\n\005\tJ\"\001C\"p[B,H/\032:\021\005\021:S\"A\023\013\005\031\n\022!C5om\026tGo\034:z\023\tASEA\bJ'&$W\rZ%om\026tGo\034:z!\tQs&D\001,\025\taS&\001\005j]R,'O\\1m\025\tqc!A\002ba&L!!A\026\021\005E\"T\"\001\032\013\005Mj\023A\0023sSZ,'/\003\0026e\tQA)\032<jG\026LeNZ8\t\013]\002A\021\001\035\002\rqJg.\033;?)\005I\004C\001\036\001\033\005\021\001b\002\037\001\005\004%\t!P\001\005S:4w.F\001?!\tyD)D\001A\025\t\t%)\001\003eCR\f'BA\"\005\003\021IG/Z7\n\005\025\003%aE'jGJ|7m\0348ue>dG.\032:ECR\f\007BB$\001A\003%a(A\003j]\032|\007\005C\003J\001\021\005#*\001\003o_\022,G#A&\021\0051{U\"A'\013\0039\013Qa]2bY\006L!\001U'\003\t9+H\016\034\005\b%\002\021\r\021\"\001T\003-yW\017\0369viNKG-Z:\026\003Q\0032\001T+X\023\t1VJA\003BeJ\f\027\020\005\002M1&\021\021,\024\002\b\005>|G.Z1o\021\031Y\006\001)A\005)\006aq.\036;qkR\034\026\016Z3tA!9Q\f\001b\001\n\003q\026aC:o_>\004XM\035(pI\026,\022a\030\t\003A\016l\021!\031\006\003E6\nqA\\3uo>\0248.\003\002eC\n\0212i\\7q_:,g\016^\"p]:,7\r^8s\021\0311\007\001)A\005?\006a1O\\8pa\026\024hj\0343fA!9\001\016\001b\001\n\003I\027AD2p[B|g.\0328u\035>$Wm]\013\002UB\031A*V6\021\005\001d\027BA7b\005%\031u.\0349p]\026tG\017\003\004p\001\001\006IA[\001\020G>l\007o\0348f]Rtu\016Z3tA!)\021\017\001C!e\006!A/[3s)\005\031\bC\001'u\023\t)XJA\002J]RDQa\036\001\005Ra\f\001B];o'>,h\016Z\013\002s:\021AJ_\005\003w6\013AAT8oK\"AQ\020\001EC\002\0235a0\001\006eKZL7-Z%oM>,\022a \t\t\003\003\tY!a\004\002\0205\021\0211\001\006\005\003\013\t9!A\005j[6,H/\0312mK*\031\021\021B'\002\025\r|G\016\\3di&|g.\003\003\002\016\005\r!aA'baB!\021\021CA\016\033\t\t\031B\003\003\002\026\005]\021\001\0027b]\036T!!!\007\002\t)\fg/Y\005\005\003;\t\031B\001\004TiJLgn\032\005\n\003C\001\001\022!Q!\016}\f1\002Z3wS\016,\027J\0344pA!9\021Q\005\001\005B\005\035\022!D4fi\022+g/[2f\023:4w\016\006\002\002*AA\0211FA\031\003g\t\031$\004\002\002.)!\021qFA\f\003\021)H/\0337\n\t\0055\021Q\006\t\005\003k\tYDD\002M\003oI1!!\017N\003\031\001&/\0323fM&!\021QDA\037\025\r\tI$\024\005\b\003\003\002A\021IA\"\003)\031\027M\\\"p]:,7\r\036\013\004/\006\025\003\002CA$\003\001\r!!\023\002\tMLG-\032\t\005\003\027\n)&\004\002\002N)!\021qFA(\025\r)\021\021\013\006\004\003'\032\022AD7j]\026\034'/\0314uM>\024x-Z\005\005\003/\niE\001\bG_J<W\rR5sK\016$\030n\0348)\021\005}\0221LA:\003k\002B!!\030\002p5\021\021q\f\006\005\003C\n\031'\001\006sK2\fWO\\2iKJTA!!\032\002h\005\031a-\0347\013\t\005%\0241N\001\005[>$7O\003\002\002n\005\0311\r]<\n\t\005E\024q\f\002\t'&$Wm\0248ms\006)a/\0317vK\022\022\021qO\005\005\003s\nY(\001\004D\031&+e\n\026\006\005\003{\ny&\001\003TS\022,\007bBAA\001\021\005\0231Q\001\ng&$W\r\032(pI\026$B!!\"\002\fB\031\001-a\"\n\007\005%\025M\001\003O_\022,\007\002CA$\003\002\r!!\023\t\017\005=\005\001\"\025\002\022\006a\001.Y:D_:tWm\031;peR\031q+a%\t\021\005\035\023Q\022a\001\003\023B\003\"!$\002\\\005M\024Q\017\005\b\0033\003A\021KAN\003%\031wN\0348fGR|'\017\006\003\002\036\006%\006#\002'\002 \006\r\026bAAQ\033\n1q\n\035;j_:\0042\001YAS\023\r\t9+\031\002\n\007>tg.Z2u_JD\001\"a\022\002\030\002\007\021\021\n\005\b\003[\003A\021IAX\003A)g.\032:hsRC'o\\;hQB,H/\006\002\0022B\031A*a-\n\007\005UVJ\001\004E_V\024G.\032\005\b\003s\003A\021IA^\003!9W\r^,pe2$WCAA_!\021\ty,!2\016\005\005\005'bAAb#\005)qo\034:mI&!\021qYAa\005\0259vN\0357e\021\035\tY\r\001C!\003\033\f\021b\0348B]\006d\027P_3\025\031\005=\027\021[Ar\003K\fy/a=\021\t1+\026Q\021\005\t\003'\fI\r1\001\002V\0061\001\017\\1zKJ\004B!a6\002`6\021\021\021\034\006\005\003'\fYNC\002\002^F\ta!\0328uSRL\030\002BAq\0033\024A\"\0228uSRL\b\013\\1zKJDq!a\022\002J\002\0071\017\003\005\002h\006%\007\031AAu\003\021A\027\016\036-\021\0071\013Y/C\002\002n6\023QA\0227pCRD\001\"!=\002J\002\007\021\021^\001\005Q&$\030\f\003\005\002v\006%\007\031AAu\003\021A\027\016\036.\t\017\005e\b\001\"\021\002|\006\021\022N\034;fe:\fGnQ8na>tWM\034;t)\t\ti\020\005\004\002\022\005}(1A\005\005\005\003\t\031B\001\005Ji\026\024\030M\0317f!\021\021)A!\003\016\005\t\035!BA\"\022\023\021\021YAa\002\003\023%#X-\\*uC\016\\\007b\002B\b\001\021\005#\021C\001\016G>l\007o\0348f]R\034Fn\034;\025\007M\024\031\002\003\005\003\026\t5\001\031AA\032\003\035\tG\r\032:fgNDqA!\007\001\t\003\021Y\"A\003ti\006\024H\017\006\004\003\036\t\025\"Q\007\t\005\031V\023y\002E\002M\005CI1Aa\tN\005\031\te.\037*fM\"A!q\005B\f\001\004\021I#A\004d_:$X\r\037;\021\t\t-\"\021G\007\003\005[Q1Aa\f.\003\035i\027m\0315j]\026LAAa\r\003.\t91i\0348uKb$\b\002\003B\034\005/\001\rA!\017\002\t\005\024xm\035\t\005\005W\021Y$\003\003\003>\t5\"!C!sOVlWM\034;tQ!\0219B!\021\003H\t%\003\003\002B\026\005\007JAA!\022\003.\tA1)\0317mE\006\0347.A\002e_\016\f#Aa\023\002)\032,hn\031;j_:D\023F\0172p_2,\027M\034\021.[\001\032F/\031:ug\002\"\b.\032\021nS\016\024xnY8oiJ|G\016\\3s]\001\022V\r^;s]N\004CO];fA%4\007\005\0365fAM$\030\r^3!G\"\fgnZ3e]!9!q\n\001\005\002\tE\023\001B:u_B$bA!\b\003T\tU\003\002\003B\024\005\033\002\rA!\013\t\021\t]\"Q\na\001\005sA\003B!\024\003B\t\035#\021L\021\003\0057\n1KZ;oGRLwN\034\025*u\t|w\016\\3b]\002jS\006I*u_B\034\b\005\0365fA5L7M]8d_:$(o\0347mKJt\003EU3ukJt7\017\t;sk\026\004\023N\032\021uQ\026\0043\017^1uK\002\032\007.\0318hK\022t\003b\002B0\001\021\005!\021M\001\nSN\024VO\0348j]\036$bA!\b\003d\t\025\004\002\003B\024\005;\002\rA!\013\t\021\t]\"Q\fa\001\005sACB!\030\003B\t%$1\016B$\005[\na\001Z5sK\016$\030$A\001\"\005\t=\024!\0224v]\016$\030n\0348)Si\022wn\0347fC:\004S&\f\021SKR,(O\\:!o\",G\017[3sAQDW\rI7jGJ|7m\0348ue>dG.\032:!SN\004#/\0368oS:<g\006C\004\003t\001!\tA!\036\002\0231\f7\017^#se>\024HC\002B\017\005o\022I\b\003\005\003(\tE\004\031\001B\025\021!\0219D!\035A\002\te\002\006\004B9\005\003\022IGa\033\003H\tu\024E\001B@\003M3WO\\2uS>t\007&\013\036tiJLgn\032\021.[\001\022V\r^;s]N\004C\017[3!e\026\f7o\0348!i\",\007%\\5de>\034wN\034;s_2dWM\035\021de\006\034\b.\0323-A%4\007%\0319qY&\034\027M\0317f]!9!1\021\001\005\002\t\025\025AC5t'&$Wm\0249f]R1!Q\004BD\005\023C\001Ba\n\003\002\002\007!\021\006\005\t\005o\021\t\t1\001\003:!b!\021\021B!\005S\022YGa\022\003\016\006\022!qR\001_MVt7\r^5p]\"\032\030\016Z3;]Vl'-\032:*u\t|w\016\\3b]\002jS\006I$fi\002:\b.\032;iKJ\004c.\032;x_J\\\007%\\3tg\006<Wm\035\021be\026\0043/\0328uAYL\027\r\t;iK\002\032\b/Z2jM&,G\rI:jI\026t\003b\002BJ\001\021\005!QS\001\fg\026$8+\0333f\037B,g\016\006\004\003\036\t]%\021\024\005\t\005O\021\t\n1\001\003*!A!q\007BI\001\004\021I\004\013\005\003\022\n\005#q\tBOC\t\021y*\0017gk:\034G/[8oQMLG-\032\036ok6\024WM\035\027!_B,gN\0172p_2,\027M\\\025;E>|G.Z1oA5j\003eU3uA]DW\r\0365fe\002rW\r^<pe.\004S.Z:tC\036,7\017I1sK\002\032XM\034;!m&\f\007\005\0365fAM\004XmY5gS\026$\007e]5eK:BqAa)\001\t\003\022)+A\005dC:,\006\017Z1uKR\tq\013C\004\003*\002!\tEa+\002\031U\004H-\031;f\013:$\030\016^=\025\005\t5\006c\001'\0030&\031!\021W'\003\tUs\027\016\036\005\b\005k\003A\021\013B\\\003=\031wN\0348fGRLE/Z7O_\022,G\003\002BW\005sCq!\023BZ\001\004\t)\tC\004\003>\002!\tFa0\002\025\r\024X-\031;f\035>$W\r\006\003\002\006\n\005\007\002\003Bb\005w\003\rA!2\002\tAdWo\032\t\005\005\017\024I-D\001\001\023\r\021YM\b\002\005!2,x\rC\004\003P\002!\tF!5\002\033=t\007\013\\;h\007>tg.Z2u)\031\021iKa5\003V\"A!1\031Bg\001\004\021)\rC\004J\005\033\004\r!!\"\t\017\te\007\001\"\025\003\\\006\001rN\034)mk\036$\025n]2p]:,7\r\036\013\007\005[\023iNa8\t\021\t\r'q\033a\001\005\013Dq!\023Bl\001\004\t)\tC\004\003d\002!\tF!:\002\033=t\007\013\\;h\033\026\0348/Y4f)\031\021iKa:\003j\"A!1\031Bq\001\004\021)\r\003\005\003l\n\005\b\031\001Bw\003\035iWm]:bO\026\0042\001\031Bx\023\r\021\t0\031\002\b\033\026\0348/Y4f\021\035\021)\020\001C!\005o\f\021b\0348NKN\034\030mZ3\025\t\t5&\021 \005\t\005W\024\031\0201\001\003n\"9!Q \001\005B\t}\030\001\006:fC\0224%o\\7O\005R3uN]*feZ,'\017\006\003\003.\016\005\001\002CB\002\005w\004\ra!\002\002\0079\024G\017\005\003\004\b\r-QBAB\005\025\r\031\031!E\005\005\007\033\031IA\001\bO\005R#\026mZ\"p[B|WO\0343\t\017\rE\001\001\"\021\004\024\005\031rO]5uKR{gJ\021+G_J\034VM\035<feR!!QVB\013\021!\031\031aa\004A\002\r\025\001bBB\r\001\021\00531D\001\025e\026\fGM\022:p[:\023EKR8s\0072LWM\034;\025\t\t56Q\004\005\t\007\007\0319\0021\001\004\006!B1qCA.\003g\n)\bC\004\004$\001!\te!\n\002']\024\030\016^3U_:\023EKR8s\0072LWM\034;\025\t\t56q\005\005\t\007\007\031\t\0031\001\004\006!911\006\001\005B\r5\022!B5uK6\034XCAB\030!\021aUk!\r\021\0131\013yJa\001\t\017\rU\002\001\"\021\0048\005YQ\017\0353bi\026LE/Z7t)\031\021ik!\017\004>!911HB\032\001\004\031\030\001B:m_RD\001ba\020\0044\001\007!1A\001\006gR\f7m\033\005\007\007\007\002A\021\t:\002!\035,GoU5{K&sg/\0328u_JL\bbBB$\001\021\0053\021J\001\023SNLE/Z7WC2LGMR8s'2|G\017F\003X\007\027\032i\005C\004\004<\r\025\003\031A:\t\021\r}2Q\ta\001\005\007Aqa!\025\001\t\003\032\031&\001\rtKRLeN^3oi>\024\030p\0257pi\016{g\016^3oiN$bA!,\004V\r]\003bBB\036\007\037\002\ra\035\005\t\007\031y\0051\001\003\004!911\f\001\005B\ru\023!\0043fGJ\034F/Y2l'&TX\rF\003L\007?\032\t\007C\004\004<\re\003\031A:\t\017\r\r4\021\fa\001g\0061\021-\\8v]RDqaa\032\001\t\003\032I'A\fhKR\034F/Y2l\023:\034Fn\034;P]\016cwn]5oOR\0311ja\033\t\017\rm2Q\ra\001g\"91q\016\001\005B\rE\024AG4fi\006\0337-Z:tS\ndWm\0257piN4%o\\7TS\022,G\003BB:\007k\0022\001T+t\021\035\t9e!\034A\002MDqa!\037\001\t\003\032Y(\001\bdC:,\005\020\036:bGRLE/Z7\025\017]\033iha \004\002\"911HB<\001\004\031\b\002CB \007o\002\rAa\001\t\017\005\0353q\017a\001g\"91Q\021\001\005B\r\035\025!D2b]&s7/\032:u\023R,W\016F\004X\007\023\033Yi!$\t\017\rm21\021a\001g\"A1qHBB\001\004\021\031\001C\004\002H\r\r\005\031A:\t\017\rE\005\001\"\001\004\024\006a1\r[1oO\026,U\t\025*P\033R!1\021GBK\021!\0319ja$A\002\t\r\021!\0038fo\026+\007O]8n\001")
/*     */ public class Microcontroller extends TileEntity implements PowerAcceptor, Hub, Computer, ISidedInventory, Microcontroller, DeviceInfo {
/*     */   private final MicrocontrollerData info;
/*     */   private final boolean[] outputSides;
/*     */   private final ComponentConnector snooperNode;
/*     */   private final Component[] componentNodes;
/*     */   private Map<String, String> deviceInfo;
/*     */   private final Machine li$cil$oc$common$tileentity$traits$Computer$$_machine;
/*     */   private boolean li$cil$oc$common$tileentity$traits$Computer$$_isRunning;
/*     */   private boolean hasErrored;
/*     */   private final Set<String> li$cil$oc$common$tileentity$traits$Computer$$_users;
/*     */   private boolean _isAbstractBusAvailable;
/*     */   private final Object[] fakeInterface;
/*     */   private final int[][] _bundledInput;
/*     */   private final int[][] _rednetInput;
/*     */   private final int[][] _bundledOutput;
/*     */   private final int[] _input;
/*     */   private final int[] _output;
/*     */   private boolean _isOutputEnabled;
/*     */   private boolean shouldUpdateInput;
/*     */   private final ForgeDirection[] li$cil$oc$common$tileentity$traits$Rotatable$$pitch2Direction;
/*     */   private final ForgeDirection[] li$cil$oc$common$tileentity$traits$Rotatable$$yaw2Direction;
/*     */   private ForgeDirection li$cil$oc$common$tileentity$traits$Rotatable$$_pitch;
/*     */   private ForgeDirection li$cil$oc$common$tileentity$traits$Rotatable$$_yaw;
/*     */   private final ArrayBuffer<Option<ItemStack>> li$cil$oc$common$tileentity$traits$ComponentInventory$$pendingRemovalsActual;
/*     */   private final ArrayBuffer<Option<ItemStack>> li$cil$oc$common$tileentity$traits$ComponentInventory$$pendingAddsActual;
/*     */   
/*  31 */   private Machine li$cil$oc$common$tileentity$traits$Computer$$_machine$lzycompute() { synchronized (this) { if ((byte)(this.bitmap$0 & 0x2) == 0) { this.li$cil$oc$common$tileentity$traits$Computer$$_machine = Computer.class.li$cil$oc$common$tileentity$traits$Computer$$_machine(this); this.bitmap$0 = (byte)(this.bitmap$0 | 0x2); }  return this.li$cil$oc$common$tileentity$traits$Computer$$_machine; }  } private boolean li$cil$oc$common$tileentity$traits$ComponentInventory$$updateScheduled; private Option<ManagedEnvironment>[] li$cil$oc$common$inventory$ComponentInventory$$_components; private boolean isSizeInventoryReady; private final ArrayBuffer<ManagedEnvironment> updatingComponents; private final Option<ItemStack>[] li$cil$oc$common$tileentity$traits$Inventory$$inventory; private final Hub.Plug[] plugs; private final Queue<Tuple2<Option<ForgeDirection>, Packet>> queue; private int maxQueueSize; private int relayDelay; private int relayAmount; private int relayCooldown; private final MovingAverage packetsPerCycleAvg; private boolean isChangeScheduled; private boolean moving; private int li$cil$oc$common$tileentity$traits$power$RotaryCraft$$omega; private int li$cil$oc$common$tileentity$traits$power$RotaryCraft$$torque; private long li$cil$oc$common$tileentity$traits$power$RotaryCraft$$power; private int li$cil$oc$common$tileentity$traits$power$RotaryCraft$$alpha; private double li$cil$oc$common$tileentity$traits$power$IndustrialCraft2Classic$$conversionBuffer; private double li$cil$oc$common$tileentity$traits$power$IndustrialCraft2Experimental$$conversionBuffer; private boolean addedToIC2PowerGrid; @Method(modid = "factorization") private final Object li$cil$oc$common$tileentity$traits$power$Factorization$$charge; private Option<Object> li$cil$oc$common$tileentity$traits$power$AppliedEnergistics2$$node; private volatile byte bitmap$0; public Machine li$cil$oc$common$tileentity$traits$Computer$$_machine() { return ((byte)(this.bitmap$0 & 0x2) == 0) ? li$cil$oc$common$tileentity$traits$Computer$$_machine$lzycompute() : this.li$cil$oc$common$tileentity$traits$Computer$$_machine; } public boolean li$cil$oc$common$tileentity$traits$Computer$$_isRunning() { return this.li$cil$oc$common$tileentity$traits$Computer$$_isRunning; } public void li$cil$oc$common$tileentity$traits$Computer$$_isRunning_$eq(boolean x$1) { this.li$cil$oc$common$tileentity$traits$Computer$$_isRunning = x$1; } public boolean hasErrored() { return this.hasErrored; } public void hasErrored_$eq(boolean x$1) { this.hasErrored = x$1; } public Set<String> li$cil$oc$common$tileentity$traits$Computer$$_users() { return this.li$cil$oc$common$tileentity$traits$Computer$$_users; } public void li$cil$oc$common$tileentity$traits$Computer$_setter_$li$cil$oc$common$tileentity$traits$Computer$$_users_$eq(Set<String> x$1) { this.li$cil$oc$common$tileentity$traits$Computer$$_users = x$1; } public Machine machine() { return Computer.class.machine(this); } public boolean canInteract(String player) { return Computer.class.canInteract(this, player); } public boolean isRunning() { return Computer.class.isRunning(this); } public void setRunning(boolean value) { Computer.class.setRunning(this, value); } @SideOnly(Side.CLIENT) public void setUsers(Iterable list) { Computer.class.setUsers(this, list); } public EnumSet<StateAware.State> getCurrentState() { return Computer.class.getCurrentState(this); } public Iterable<ManagedEnvironment> installedComponents() { return Computer.class.installedComponents(this); } public void onMachineConnect(Node node) { Computer.class.onMachineConnect(this, node); } public void onMachineDisconnect(Node node) { Computer.class.onMachineDisconnect(this, node); } public boolean hasAbstractBusCard() { return Computer.class.hasAbstractBusCard(this); } public boolean hasRedstoneCard() { return Computer.class.hasRedstoneCard(this); } public void updateComputer() { Computer.class.updateComputer(this); } public void onRunningChanged() { Computer.class.onRunningChanged(this); } public void dispose() { Computer.class.dispose(this); } public void func_70296_d() { Computer.class.markDirty(this); } public boolean func_70300_a(EntityPlayer player) { return Computer.class.isUseableByPlayer(this, player); } public void onRotationChanged() { Computer.class.onRotationChanged(this); } public void onRedstoneInputChanged(RedstoneChangedEventArgs args) { Computer.class.onRedstoneInputChanged(this, args); } @Method(modid = "BuildCraft|Core") public boolean hasWork() { return StateAware.class.hasWork((StateAware)this); } public boolean _isAbstractBusAvailable() { return this._isAbstractBusAvailable; } public void _isAbstractBusAvailable_$eq(boolean x$1) { this._isAbstractBusAvailable = x$1; } private Object[] fakeInterface$lzycompute() { synchronized (this) { if ((byte)(this.bitmap$0 & 0x4) == 0) { this.fakeInterface = AbstractBusAware.class.fakeInterface((AbstractBusAware)this); this.bitmap$0 = (byte)(this.bitmap$0 | 0x4); }  return this.fakeInterface; }  } public Object[] fakeInterface() { return ((byte)(this.bitmap$0 & 0x4) == 0) ? fakeInterface$lzycompute() : this.fakeInterface; } @Method(modid = "StargateTech2") public IBusInterface[] getInterfaces(int side) { return AbstractBusAware.class.getInterfaces((AbstractBusAware)this, side); } public int getXCoord() { return AbstractBusAware.class.getXCoord((AbstractBusAware)this); } public int getYCoord() { return AbstractBusAware.class.getYCoord((AbstractBusAware)this); } public int getZCoord() { return AbstractBusAware.class.getZCoord((AbstractBusAware)this); } public boolean isAbstractBusAvailable() { return AbstractBusAware.class.isAbstractBusAvailable((AbstractBusAware)this); } public AbstractBusAware isAbstractBusAvailable_$eq(boolean value) { return AbstractBusAware.class.isAbstractBusAvailable_$eq((AbstractBusAware)this, value); } public void onDisconnect(Node node) { AbstractBusAware.class.onDisconnect((AbstractBusAware)this, node); } public int[][] _bundledInput() { return this._bundledInput; } public int[][] _rednetInput() { return this._rednetInput; } public int[][] _bundledOutput() { return this._bundledOutput; } public void li$cil$oc$common$tileentity$traits$BundledRedstoneAware$_setter_$_bundledInput_$eq(int[][] x$1) { this._bundledInput = x$1; } public void li$cil$oc$common$tileentity$traits$BundledRedstoneAware$_setter_$_rednetInput_$eq(int[][] x$1) { this._rednetInput = x$1; } public void li$cil$oc$common$tileentity$traits$BundledRedstoneAware$_setter_$_bundledOutput_$eq(int[][] x$1) { this._bundledOutput = x$1; } public void setOutputEnabled(boolean value) { BundledRedstoneAware.class.setOutputEnabled((BundledRedstoneAware)this, value); } public int[][] getBundledInput() { return BundledRedstoneAware.class.getBundledInput((BundledRedstoneAware)this); } public int[] getBundledInput(ForgeDirection side) { return BundledRedstoneAware.class.getBundledInput((BundledRedstoneAware)this, side); } public int getBundledInput(ForgeDirection side, int color) { return BundledRedstoneAware.class.getBundledInput((BundledRedstoneAware)this, side, color); } public void setBundledInput(ForgeDirection side, int color, int newValue) { BundledRedstoneAware.class.setBundledInput((BundledRedstoneAware)this, side, color, newValue); } public void setBundledInput(ForgeDirection side, int[] newBundledInput) { BundledRedstoneAware.class.setBundledInput((BundledRedstoneAware)this, side, newBundledInput); } public void setRednetInput(ForgeDirection side, int color, int value) { BundledRedstoneAware.class.setRednetInput((BundledRedstoneAware)this, side, color, value); } public void updateInput(int[][] inputs, ForgeDirection side, int color, int newValue) { BundledRedstoneAware.class.updateInput((BundledRedstoneAware)this, inputs, side, color, newValue); } public int[][] getBundledOutput() { return BundledRedstoneAware.class.getBundledOutput((BundledRedstoneAware)this); } public int[] getBundledOutput(ForgeDirection side) { return BundledRedstoneAware.class.getBundledOutput((BundledRedstoneAware)this, side); } public int getBundledOutput(ForgeDirection side, int color) { return BundledRedstoneAware.class.getBundledOutput((BundledRedstoneAware)this, side, color); } public void notifyChangedSide(ForgeDirection side) { BundledRedstoneAware.class.notifyChangedSide((BundledRedstoneAware)this, side); } public boolean setBundledOutput(ForgeDirection side, int color, int value) { return BundledRedstoneAware.class.setBundledOutput((BundledRedstoneAware)this, side, color, value); } public boolean setBundledOutput(ForgeDirection side, Map values) { return BundledRedstoneAware.class.setBundledOutput((BundledRedstoneAware)this, side, values); } public boolean setBundledOutput(Map values) { return BundledRedstoneAware.class.setBundledOutput((BundledRedstoneAware)this, values); } public void updateRedstoneInput(ForgeDirection side) { BundledRedstoneAware.class.updateRedstoneInput((BundledRedstoneAware)this, side); } public void onRedstoneOutputEnabledChanged() { BundledRedstoneAware.class.onRedstoneOutputEnabledChanged((BundledRedstoneAware)this); } @Method(modid = "RedLogic") public byte[] getBundledCableStrength(int blockFace, int toDirection) { return BundledRedstoneAware.class.getBundledCableStrength((BundledRedstoneAware)this, blockFace, toDirection); } @Method(modid = "RedLogic") public void onBundledInputChanged() { BundledRedstoneAware.class.onBundledInputChanged((BundledRedstoneAware)this); } @Method(modid = "ProjRed|Transmission") public boolean canConnectBundled(int side) { return BundledRedstoneAware.class.canConnectBundled((BundledRedstoneAware)this, side); } @Method(modid = "ProjRed|Transmission") public byte[] getBundledSignal(int side) { return BundledRedstoneAware.class.getBundledSignal((BundledRedstoneAware)this, side); } public int[] _input() { return this._input; } public int[] _output() { return this._output; } public boolean _isOutputEnabled() { return this._isOutputEnabled; } public void _isOutputEnabled_$eq(boolean x$1) { this._isOutputEnabled = x$1; } public boolean shouldUpdateInput() { return this.shouldUpdateInput; } public void shouldUpdateInput_$eq(boolean x$1) { this.shouldUpdateInput = x$1; } public void li$cil$oc$common$tileentity$traits$RedstoneAware$_setter_$_input_$eq(int[] x$1) { this._input = x$1; } public void li$cil$oc$common$tileentity$traits$RedstoneAware$_setter_$_output_$eq(int[] x$1) { this._output = x$1; } public boolean isOutputEnabled() { return RedstoneAware.class.isOutputEnabled((RedstoneAware)this); } public Option<Object> getObjectFuzzy(Map map, int key) { return RedstoneAware.class.getObjectFuzzy((RedstoneAware)this, map, key); } public Option<Object> valueToInt(Object value) { return RedstoneAware.class.valueToInt((RedstoneAware)this, value); } public int[] getInput() { return RedstoneAware.class.getInput((RedstoneAware)this); } public int getInput(ForgeDirection side) { return RedstoneAware.class.getInput((RedstoneAware)this, side); } public void setInput(ForgeDirection side, int newInput) { RedstoneAware.class.setInput((RedstoneAware)this, side, newInput); } public void setInput(int[] values) { RedstoneAware.class.setInput((RedstoneAware)this, values); } public int maxInput() { return RedstoneAware.class.maxInput((RedstoneAware)this); } public int[] getOutput() { return RedstoneAware.class.getOutput((RedstoneAware)this); } public int getOutput(ForgeDirection side) { return RedstoneAware.class.getOutput((RedstoneAware)this, side); } public boolean setOutput(ForgeDirection side, int value) { return RedstoneAware.class.setOutput((RedstoneAware)this, side, value); } public boolean setOutput(Map values) { return RedstoneAware.class.setOutput((RedstoneAware)this, values); } public void checkRedstoneInputChanged() { RedstoneAware.class.checkRedstoneInputChanged((RedstoneAware)this); } public void func_145829_t() { RedstoneAware.class.validate((RedstoneAware)this); } public void onRedstoneOutputChanged(ForgeDirection side) { RedstoneAware.class.onRedstoneOutputChanged((RedstoneAware)this, side); } @Method(modid = "RedLogic") public boolean connects(IWire wire, int blockFace, int fromDirection) { return RedstoneAware.class.connects((RedstoneAware)this, wire, blockFace, fromDirection); } @Method(modid = "RedLogic") public boolean connectsAroundCorner(IWire wire, int blockFace, int fromDirection) { return RedstoneAware.class.connectsAroundCorner((RedstoneAware)this, wire, blockFace, fromDirection); } @Method(modid = "RedLogic") public short getEmittedSignalStrength(int blockFace, int toDirection) { return RedstoneAware.class.getEmittedSignalStrength((RedstoneAware)this, blockFace, toDirection); } @Method(modid = "RedLogic") public void onRedstoneInputChanged() { RedstoneAware.class.onRedstoneInputChanged((RedstoneAware)this); } public ForgeDirection[] li$cil$oc$common$tileentity$traits$Rotatable$$pitch2Direction() { return this.li$cil$oc$common$tileentity$traits$Rotatable$$pitch2Direction; } public ForgeDirection[] li$cil$oc$common$tileentity$traits$Rotatable$$yaw2Direction() { return this.li$cil$oc$common$tileentity$traits$Rotatable$$yaw2Direction; } public ForgeDirection li$cil$oc$common$tileentity$traits$Rotatable$$_pitch() { return this.li$cil$oc$common$tileentity$traits$Rotatable$$_pitch; } public void li$cil$oc$common$tileentity$traits$Rotatable$$_pitch_$eq(ForgeDirection x$1) { this.li$cil$oc$common$tileentity$traits$Rotatable$$_pitch = x$1; } public ForgeDirection li$cil$oc$common$tileentity$traits$Rotatable$$_yaw() { return this.li$cil$oc$common$tileentity$traits$Rotatable$$_yaw; } public void li$cil$oc$common$tileentity$traits$Rotatable$$_yaw_$eq(ForgeDirection x$1) { this.li$cil$oc$common$tileentity$traits$Rotatable$$_yaw = x$1; } public void li$cil$oc$common$tileentity$traits$Rotatable$_setter_$li$cil$oc$common$tileentity$traits$Rotatable$$pitch2Direction_$eq(ForgeDirection[] x$1) { this.li$cil$oc$common$tileentity$traits$Rotatable$$pitch2Direction = x$1; } public void li$cil$oc$common$tileentity$traits$Rotatable$_setter_$li$cil$oc$common$tileentity$traits$Rotatable$$yaw2Direction_$eq(ForgeDirection[] x$1) { this.li$cil$oc$common$tileentity$traits$Rotatable$$yaw2Direction = x$1; } public ForgeDirection pitch() { return Rotatable.class.pitch((Rotatable)this); } public void pitch_$eq(ForgeDirection value) { Rotatable.class.pitch_$eq((Rotatable)this, value); } public ForgeDirection yaw() { return Rotatable.class.yaw((Rotatable)this); } public void yaw_$eq(ForgeDirection value) { Rotatable.class.yaw_$eq((Rotatable)this, value); } public boolean setFromEntityPitchAndYaw(Entity entity) { return Rotatable.class.setFromEntityPitchAndYaw((Rotatable)this, entity); } public boolean setFromFacing(ForgeDirection value) { return Rotatable.class.setFromFacing((Rotatable)this, value); } public boolean invertRotation() { return Rotatable.class.invertRotation((Rotatable)this); } public ForgeDirection facing() { return Rotatable.class.facing((Rotatable)this); } public boolean rotate(ForgeDirection axis) { return Rotatable.class.rotate((Rotatable)this, axis); } public ForgeDirection toLocal(ForgeDirection value) { return Rotatable.class.toLocal((Rotatable)this, value); } public ForgeDirection toGlobal(ForgeDirection value) { return Rotatable.class.toGlobal((Rotatable)this, value); } public ForgeDirection[] validFacings() { return Rotatable.class.validFacings((Rotatable)this); } private ArrayBuffer li$cil$oc$common$tileentity$traits$ComponentInventory$$pendingRemovalsActual$lzycompute() { synchronized (this) { if ((byte)(this.bitmap$0 & 0x8) == 0) { this.li$cil$oc$common$tileentity$traits$ComponentInventory$$pendingRemovalsActual = ComponentInventory.class.li$cil$oc$common$tileentity$traits$ComponentInventory$$pendingRemovalsActual((ComponentInventory)this); this.bitmap$0 = (byte)(this.bitmap$0 | 0x8); }  return this.li$cil$oc$common$tileentity$traits$ComponentInventory$$pendingRemovalsActual; }  } public ArrayBuffer<Option<ItemStack>> li$cil$oc$common$tileentity$traits$ComponentInventory$$pendingRemovalsActual() { return ((byte)(this.bitmap$0 & 0x8) == 0) ? li$cil$oc$common$tileentity$traits$ComponentInventory$$pendingRemovalsActual$lzycompute() : this.li$cil$oc$common$tileentity$traits$ComponentInventory$$pendingRemovalsActual; } private ArrayBuffer li$cil$oc$common$tileentity$traits$ComponentInventory$$pendingAddsActual$lzycompute() { synchronized (this) { if ((byte)(this.bitmap$0 & 0x10) == 0) { this.li$cil$oc$common$tileentity$traits$ComponentInventory$$pendingAddsActual = ComponentInventory.class.li$cil$oc$common$tileentity$traits$ComponentInventory$$pendingAddsActual((ComponentInventory)this); this.bitmap$0 = (byte)(this.bitmap$0 | 0x10); }  return this.li$cil$oc$common$tileentity$traits$ComponentInventory$$pendingAddsActual; }  } public ArrayBuffer<Option<ItemStack>> li$cil$oc$common$tileentity$traits$ComponentInventory$$pendingAddsActual() { return ((byte)(this.bitmap$0 & 0x10) == 0) ? li$cil$oc$common$tileentity$traits$ComponentInventory$$pendingAddsActual$lzycompute() : this.li$cil$oc$common$tileentity$traits$ComponentInventory$$pendingAddsActual; } public boolean li$cil$oc$common$tileentity$traits$ComponentInventory$$updateScheduled() { return this.li$cil$oc$common$tileentity$traits$ComponentInventory$$updateScheduled; } public void li$cil$oc$common$tileentity$traits$ComponentInventory$$updateScheduled_$eq(boolean x$1) { this.li$cil$oc$common$tileentity$traits$ComponentInventory$$updateScheduled = x$1; } public ComponentInventory host() { return ComponentInventory.class.host((ComponentInventory)this); } public ArrayBuffer<Option<ItemStack>> pendingRemovals() { return ComponentInventory.class.pendingRemovals((ComponentInventory)this); } public ArrayBuffer<Option<ItemStack>> pendingAdds() { return ComponentInventory.class.pendingAdds((ComponentInventory)this); } public void onItemAdded(int slot, ItemStack stack) { ComponentInventory.class.onItemAdded((ComponentInventory)this, slot, stack); } public void onItemRemoved(int slot, ItemStack stack) { ComponentInventory.class.onItemRemoved((ComponentInventory)this, slot, stack); } public void save(ManagedEnvironment component, Item driver, ItemStack stack) { ComponentInventory.class.save((ComponentInventory)this, component, driver, stack); } public void initialize() { ComponentInventory.class.initialize((ComponentInventory)this); } public void onConnect(Node node) { ComponentInventory.class.onConnect((ComponentInventory)this, node); } public Option<ManagedEnvironment>[] li$cil$oc$common$inventory$ComponentInventory$$_components() { return this.li$cil$oc$common$inventory$ComponentInventory$$_components; } @TraitSetter public void li$cil$oc$common$inventory$ComponentInventory$$_components_$eq(Option[] x$1) { this.li$cil$oc$common$inventory$ComponentInventory$$_components = (Option<ManagedEnvironment>[])x$1; } public boolean isSizeInventoryReady() { return this.isSizeInventoryReady; } @TraitSetter public void isSizeInventoryReady_$eq(boolean x$1) { this.isSizeInventoryReady = x$1; } public ArrayBuffer<ManagedEnvironment> updatingComponents() { return this.updatingComponents; } public void li$cil$oc$common$inventory$ComponentInventory$_setter_$updatingComponents_$eq(ArrayBuffer<ManagedEnvironment> x$1) { this.updatingComponents = x$1; } public Option<ManagedEnvironment>[] components() { return (Option<ManagedEnvironment>[])ComponentInventory.class.components((ComponentInventory)this); } public void updateComponents() { ComponentInventory.class.updateComponents((ComponentInventory)this); } public void connectComponents() { ComponentInventory.class.connectComponents((ComponentInventory)this); } public void disconnectComponents() { ComponentInventory.class.disconnectComponents((ComponentInventory)this); } public void save(NBTTagCompound nbt) { ComponentInventory.class.save((ComponentInventory)this, nbt); } public void saveComponents() { ComponentInventory.class.saveComponents((ComponentInventory)this); } public int func_70297_j_() { return ComponentInventory.class.getInventoryStackLimit((ComponentInventory)this); } public boolean isComponentSlot(int slot, ItemStack stack) { return ComponentInventory.class.isComponentSlot((ComponentInventory)this, slot, stack); } public NBTTagCompound dataTag(Item driver, ItemStack stack) { return ComponentInventory.class.dataTag((ComponentInventory)this, driver, stack); } public void applyLifecycleState(Object component, Lifecycle.LifecycleState state) { ComponentInventory.class.applyLifecycleState((ComponentInventory)this, component, state); } private Option[] li$cil$oc$common$tileentity$traits$Inventory$$inventory$lzycompute() { synchronized (this) { if ((byte)(this.bitmap$0 & 0x20) == 0) { this.li$cil$oc$common$tileentity$traits$Inventory$$inventory = (Option<ItemStack>[])Inventory.class.li$cil$oc$common$tileentity$traits$Inventory$$inventory((Inventory)this); this.bitmap$0 = (byte)(this.bitmap$0 | 0x20); }  return (Option[])this.li$cil$oc$common$tileentity$traits$Inventory$$inventory; }  } public Option<ItemStack>[] li$cil$oc$common$tileentity$traits$Inventory$$inventory() { return ((byte)(this.bitmap$0 & 0x20) == 0) ? (Option<ItemStack>[])li$cil$oc$common$tileentity$traits$Inventory$$inventory$lzycompute() : this.li$cil$oc$common$tileentity$traits$Inventory$$inventory; } public boolean dropSlot(int slot, int count, Option direction) { return Inventory.class.dropSlot((Inventory)this, slot, count, direction); } public void dropAllSlots() { Inventory.class.dropAllSlots((Inventory)this); } public EntityItem spawnStackInWorld(ItemStack stack, Option direction) { return Inventory.class.spawnStackInWorld((Inventory)this, stack, direction); } public int dropSlot$default$2() { return Inventory.class.dropSlot$default$2((Inventory)this); } public Option<ForgeDirection> dropSlot$default$3() { return Inventory.class.dropSlot$default$3((Inventory)this); } public Option<ForgeDirection> spawnStackInWorld$default$2() { return Inventory.class.spawnStackInWorld$default$2((Inventory)this); } public ItemStack func_70301_a(int slot) { return Inventory.class.getStackInSlot((Inventory)this, slot); } public String func_145825_b() { return Inventory.class.getInventoryName((Inventory)this); } public String inventoryName() { return Inventory.class.inventoryName((Inventory)this); } public void load(NBTTagCompound nbt) { Inventory.class.load((Inventory)this, nbt); } public boolean func_145818_k_() { return SimpleInventory.class.hasCustomInventoryName((SimpleInventory)this); } public int getInventoryStackRequired() { return SimpleInventory.class.getInventoryStackRequired((SimpleInventory)this); } public void func_70295_k_() { SimpleInventory.class.openInventory((SimpleInventory)this); } public void func_70305_f() { SimpleInventory.class.closeInventory((SimpleInventory)this); } public Hub.Plug[] plugs() { return this.plugs; } public Queue<Tuple2<Option<ForgeDirection>, Packet>> queue() { return this.queue; } public int maxQueueSize() { return this.maxQueueSize; } public void maxQueueSize_$eq(int x$1) { this.maxQueueSize = x$1; } public int relayDelay() { return this.relayDelay; } public void relayDelay_$eq(int x$1) { this.relayDelay = x$1; } public int relayAmount() { return this.relayAmount; } public void relayAmount_$eq(int x$1) { this.relayAmount = x$1; } public int relayCooldown() { return this.relayCooldown; } public void relayCooldown_$eq(int x$1) { this.relayCooldown = x$1; } public MovingAverage packetsPerCycleAvg() { return this.packetsPerCycleAvg; } public void li$cil$oc$common$tileentity$traits$Hub$_setter_$plugs_$eq(Hub.Plug[] x$1) { this.plugs = x$1; } public void li$cil$oc$common$tileentity$traits$Hub$_setter_$queue_$eq(Queue<Tuple2<Option<ForgeDirection>, Packet>> x$1) { this.queue = x$1; } public void li$cil$oc$common$tileentity$traits$Hub$_setter_$packetsPerCycleAvg_$eq(MovingAverage x$1) { this.packetsPerCycleAvg = x$1; } public boolean isConnected() { return Hub.class.isConnected(this); } public int queueBaseSize() { return Hub.class.queueBaseSize(this); } public int queueSizePerUpgrade() { return Hub.class.queueSizePerUpgrade(this); } public int relayBaseDelay() { return Hub.class.relayBaseDelay(this); } public double relayDelayPerUpgrade() { return Hub.class.relayDelayPerUpgrade(this); } public int relayBaseAmount() { return Hub.class.relayBaseAmount(this); } public int relayAmountPerUpgrade() { return Hub.class.relayAmountPerUpgrade(this); } public boolean tryEnqueuePacket(Option sourceSide, Packet packet) { return Hub.class.tryEnqueuePacket(this, sourceSide, packet); } public void relayPacket(Option sourceSide, Packet packet) { Hub.class.relayPacket(this, sourceSide, packet); } public Hub.Plug createPlug(ForgeDirection side) { return Hub.class.createPlug(this, side); } public boolean isChangeScheduled() { return this.isChangeScheduled; } public void isChangeScheduled_$eq(boolean x$1) { this.isChangeScheduled = x$1; } public boolean moving() { return this.moving; } public void moving_$eq(boolean x$1) { this.moving = x$1; } public double xPosition() { return Environment.class.xPosition((Environment)this); } public double yPosition() { return Environment.class.yPosition((Environment)this); } public double zPosition() { return Environment.class.zPosition((Environment)this); } public void markChanged() { Environment.class.markChanged((Environment)this); } @Method(modid = "appliedenergistics2") public boolean prepareToMove() { return Environment.class.prepareToMove((Environment)this); } @Method(modid = "appliedenergistics2") public void doneMoving() { Environment.class.doneMoving((Environment)this); } public Object[] result(Seq args) { return Environment.class.result((Environment)this, args); } public int li$cil$oc$common$tileentity$traits$power$RotaryCraft$$omega() { return this.li$cil$oc$common$tileentity$traits$power$RotaryCraft$$omega; } public void li$cil$oc$common$tileentity$traits$power$RotaryCraft$$omega_$eq(int x$1) { this.li$cil$oc$common$tileentity$traits$power$RotaryCraft$$omega = x$1; } public int li$cil$oc$common$tileentity$traits$power$RotaryCraft$$torque() { return this.li$cil$oc$common$tileentity$traits$power$RotaryCraft$$torque; } public void li$cil$oc$common$tileentity$traits$power$RotaryCraft$$torque_$eq(int x$1) { this.li$cil$oc$common$tileentity$traits$power$RotaryCraft$$torque = x$1; } public long li$cil$oc$common$tileentity$traits$power$RotaryCraft$$power() { return this.li$cil$oc$common$tileentity$traits$power$RotaryCraft$$power; } public void li$cil$oc$common$tileentity$traits$power$RotaryCraft$$power_$eq(long x$1) { this.li$cil$oc$common$tileentity$traits$power$RotaryCraft$$power = x$1; } public int li$cil$oc$common$tileentity$traits$power$RotaryCraft$$alpha() { return this.li$cil$oc$common$tileentity$traits$power$RotaryCraft$$alpha; } public void li$cil$oc$common$tileentity$traits$power$RotaryCraft$$alpha_$eq(int x$1) { this.li$cil$oc$common$tileentity$traits$power$RotaryCraft$$alpha = x$1; } @Method(modid = "RotaryCraft") public int getOmega() { return RotaryCraft.class.getOmega((RotaryCraft)this); } @Method(modid = "RotaryCraft") public int getTorque() { return RotaryCraft.class.getTorque((RotaryCraft)this); } @Method(modid = "RotaryCraft") public long getPower() { return RotaryCraft.class.getPower((RotaryCraft)this); } @Method(modid = "RotaryCraft") public String getName() { return RotaryCraft.class.getName((RotaryCraft)this); } @Method(modid = "RotaryCraft") public int getIORenderAlpha() { return RotaryCraft.class.getIORenderAlpha((RotaryCraft)this); } @Method(modid = "RotaryCraft") public void setIORenderAlpha(int value) { RotaryCraft.class.setIORenderAlpha((RotaryCraft)this, value); } @Method(modid = "RotaryCraft") public void setOmega(int value) { RotaryCraft.class.setOmega((RotaryCraft)this, value); } @Method(modid = "RotaryCraft") public void setTorque(int value) { RotaryCraft.class.setTorque((RotaryCraft)this, value); } @Method(modid = "RotaryCraft") public void setPower(long value) { RotaryCraft.class.setPower((RotaryCraft)this, value); } @Method(modid = "RotaryCraft") public void noInputMachine() { RotaryCraft.class.noInputMachine((RotaryCraft)this); } @Method(modid = "RotaryCraft") public boolean canReadFrom(ForgeDirection forgeDirection) { return RotaryCraft.class.canReadFrom((RotaryCraft)this, forgeDirection); } @Method(modid = "RotaryCraft") public boolean isReceiving() { return RotaryCraft.class.isReceiving((RotaryCraft)this); } @Method(modid = "RotaryCraft") public int getMinTorque(int available) { return RotaryCraft.class.getMinTorque((RotaryCraft)this, available); } @Method(modid = "CoFHAPI|energy") public boolean canConnectEnergy(ForgeDirection from) { return RedstoneFlux.class.canConnectEnergy((RedstoneFlux)this, from); } @Method(modid = "CoFHAPI|energy") public int receiveEnergy(ForgeDirection from, int maxReceive, boolean simulate) { return RedstoneFlux.class.receiveEnergy((RedstoneFlux)this, from, maxReceive, simulate); } @Method(modid = "CoFHAPI|energy") public int getEnergyStored(ForgeDirection from) { return RedstoneFlux.class.getEnergyStored((RedstoneFlux)this, from); } @Method(modid = "CoFHAPI|energy") public int getMaxEnergyStored(ForgeDirection from) { return RedstoneFlux.class.getMaxEnergyStored((RedstoneFlux)this, from); } @Method(modid = "CoFHAPI|energy") public int extractEnergy(ForgeDirection from, int maxExtract, boolean simulate) { return RedstoneFlux.class.extractEnergy((RedstoneFlux)this, from, maxExtract, simulate); } @Method(modid = "Mekanism") public boolean canReceiveEnergy(ForgeDirection side) { return Mekanism.class.canReceiveEnergy((Mekanism)this, side); } @Method(modid = "Mekanism") public double transferEnergyToAcceptor(ForgeDirection side, double amount) { return Mekanism.class.transferEnergyToAcceptor((Mekanism)this, side, amount); } @Method(modid = "Mekanism") public double getMaxEnergy() { return Mekanism.class.getMaxEnergy((Mekanism)this); } @Method(modid = "Mekanism") public double getEnergy() { return Mekanism.class.getEnergy((Mekanism)this); } @Method(modid = "Mekanism") public void setEnergy(double energy) { Mekanism.class.setEnergy((Mekanism)this, energy); } public double li$cil$oc$common$tileentity$traits$power$IndustrialCraft2Classic$$conversionBuffer() { return this.li$cil$oc$common$tileentity$traits$power$IndustrialCraft2Classic$$conversionBuffer; } public void li$cil$oc$common$tileentity$traits$power$IndustrialCraft2Classic$$conversionBuffer_$eq(double x$1) { this.li$cil$oc$common$tileentity$traits$power$IndustrialCraft2Classic$$conversionBuffer = x$1; } public void func_145843_s() { IndustrialCraft2Classic.class.invalidate((IndustrialCraft2Classic)this); } public void onChunkUnload() { IndustrialCraft2Classic.class.onChunkUnload((IndustrialCraft2Classic)this); } @Method(modid = "IC2-Classic") public boolean isAddedToEnergyNet() { return IndustrialCraft2Classic.class.isAddedToEnergyNet((IndustrialCraft2Classic)this); } @Method(modid = "IC2-Classic") public int getMaxSafeInput() { return IndustrialCraft2Classic.class.getMaxSafeInput((IndustrialCraft2Classic)this); } @Method(modid = "IC2-Classic") public boolean acceptsEnergyFrom(TileEntity emitter, Direction direction) { return IndustrialCraft2Classic.class.acceptsEnergyFrom((IndustrialCraft2Classic)this, emitter, direction); } @Method(modid = "IC2-Classic") public boolean injectEnergy(Direction directionFrom, int amount) { return IndustrialCraft2Classic.class.injectEnergy((IndustrialCraft2Classic)this, directionFrom, amount); } @Method(modid = "IC2-Classic") public int demandsEnergy() { return IndustrialCraft2Classic.class.demandsEnergy((IndustrialCraft2Classic)this); } public double li$cil$oc$common$tileentity$traits$power$IndustrialCraft2Experimental$$conversionBuffer() { return this.li$cil$oc$common$tileentity$traits$power$IndustrialCraft2Experimental$$conversionBuffer; } public void li$cil$oc$common$tileentity$traits$power$IndustrialCraft2Experimental$$conversionBuffer_$eq(double x$1) { this.li$cil$oc$common$tileentity$traits$power$IndustrialCraft2Experimental$$conversionBuffer = x$1; } @Method(modid = "IC2") public int getSinkTier() { return IndustrialCraft2Experimental.class.getSinkTier((IndustrialCraft2Experimental)this); } @Method(modid = "IC2") public boolean acceptsEnergyFrom(TileEntity emitter, ForgeDirection direction) { return IndustrialCraft2Experimental.class.acceptsEnergyFrom((IndustrialCraft2Experimental)this, emitter, direction); } @Method(modid = "IC2") public double injectEnergy(ForgeDirection directionFrom, double amount, double voltage) { return IndustrialCraft2Experimental.class.injectEnergy((IndustrialCraft2Experimental)this, directionFrom, amount, voltage); } @Method(modid = "IC2") public double getDemandedEnergy() { return IndustrialCraft2Experimental.class.getDemandedEnergy((IndustrialCraft2Experimental)this); } public boolean addedToIC2PowerGrid() { return this.addedToIC2PowerGrid; } public void addedToIC2PowerGrid_$eq(boolean x$1) { this.addedToIC2PowerGrid = x$1; } @Method(modid = "Galacticraft API") public boolean nodeAvailable(EnergySource from) { return Galacticraft.class.nodeAvailable((Galacticraft)this, from); } @Method(modid = "Galacticraft API") public float receiveEnergyGC(EnergySource from, float amount, boolean simulate) { return Galacticraft.class.receiveEnergyGC((Galacticraft)this, from, amount, simulate); } @Method(modid = "Galacticraft API") public float getEnergyStoredGC(EnergySource from) { return Galacticraft.class.getEnergyStoredGC((Galacticraft)this, from); } @Method(modid = "Galacticraft API") public float getMaxEnergyStoredGC(EnergySource from) { return Galacticraft.class.getMaxEnergyStoredGC((Galacticraft)this, from); } @Method(modid = "Galacticraft API") public float extractEnergyGC(EnergySource from, float amount, boolean simulate) { return Galacticraft.class.extractEnergyGC((Galacticraft)this, from, amount, simulate); } @Method(modid = "Galacticraft API") public boolean canConnect(ForgeDirection from, NetworkType networkType) { return Galacticraft.class.canConnect((Galacticraft)this, from, networkType); } private Object li$cil$oc$common$tileentity$traits$power$Factorization$$charge$lzycompute() { synchronized (this) { if ((byte)(this.bitmap$0 & 0x40) == 0) { this.li$cil$oc$common$tileentity$traits$power$Factorization$$charge = Factorization.class.li$cil$oc$common$tileentity$traits$power$Factorization$$charge((Factorization)this); this.bitmap$0 = (byte)(this.bitmap$0 | 0x40); }  return this.li$cil$oc$common$tileentity$traits$power$Factorization$$charge; }  } public Object li$cil$oc$common$tileentity$traits$power$Factorization$$charge() { return ((byte)(this.bitmap$0 & 0x40) == 0) ? li$cil$oc$common$tileentity$traits$power$Factorization$$charge$lzycompute() : this.li$cil$oc$common$tileentity$traits$power$Factorization$$charge; } @Method(modid = "factorization") public Charge getCharge() { return Factorization.class.getCharge((Factorization)this); } @Method(modid = "factorization") public String getInfo() { return Factorization.class.getInfo((Factorization)this); } @Method(modid = "factorization") public Coord getCoord() { return Factorization.class.getCoord((Factorization)this); } public Option<Object> li$cil$oc$common$tileentity$traits$power$AppliedEnergistics2$$node() { return this.li$cil$oc$common$tileentity$traits$power$AppliedEnergistics2$$node; } public void li$cil$oc$common$tileentity$traits$power$AppliedEnergistics2$$node_$eq(Option<Object> x$1) { this.li$cil$oc$common$tileentity$traits$power$AppliedEnergistics2$$node = x$1; } @Method(modid = "appliedenergistics2") public IGridNode getGridNode(ForgeDirection side) { return AppliedEnergistics2.class.getGridNode((AppliedEnergistics2)this, side); } @Method(modid = "appliedenergistics2") public AECableType getCableConnectionType(ForgeDirection side) { return AppliedEnergistics2.class.getCableConnectionType((AppliedEnergistics2)this, side); } @Method(modid = "appliedenergistics2") public void securityBreak() { AppliedEnergistics2.class.securityBreak((AppliedEnergistics2)this); } public void tryAllSides(Function2 provider, Function1 fromOther, Function1 toOther) { Common.class.tryAllSides((Common)this, provider, fromOther, toOther); } public boolean canConnectPower(ForgeDirection side) { return Common.class.canConnectPower((Common)this, side); } public double tryChangeBuffer(ForgeDirection side, double amount, boolean doReceive) { return Common.class.tryChangeBuffer((Common)this, side, amount, doReceive); } public double globalBuffer(ForgeDirection side) { return Common.class.globalBuffer((Common)this, side); } public double globalBufferSize(ForgeDirection side) { return Common.class.globalBufferSize((Common)this, side); } public double globalDemand(ForgeDirection side) { return Common.class.globalDemand((Common)this, side); } public boolean tryChangeBuffer$default$3() { return Common.class.tryChangeBuffer$default$3((Common)this); } public World world() { return TileEntity.class.world((TileEntity)this); } public int x() { return TileEntity.class.x((TileEntity)this); } public int y() { return TileEntity.class.y((TileEntity)this); } public int z() { return TileEntity.class.z((TileEntity)this); } public BlockPosition position() { return TileEntity.class.position((TileEntity)this); } public Block block() { return TileEntity.class.block((TileEntity)this); } public boolean isClient() { return TileEntity.class.isClient((TileEntity)this); } public boolean isServer() { return TileEntity.class.isServer((TileEntity)this); } public void func_145839_a(NBTTagCompound nbt) { TileEntity.class.readFromNBT((TileEntity)this, nbt); } public void func_145841_b(NBTTagCompound nbt) { TileEntity.class.writeToNBT((TileEntity)this, nbt); } public Packet func_145844_m() { return TileEntity.class.getDescriptionPacket((TileEntity)this); } public void onDataPacket(NetworkManager manager, S35PacketUpdateTileEntity packet) { TileEntity.class.onDataPacket((TileEntity)this, manager, packet); } public Microcontroller() { TileEntity.class.$init$((TileEntity)this); Common.class.$init$((Common)this); AppliedEnergistics2.class.$init$((AppliedEnergistics2)this); Factorization.class.$init$((Factorization)this); Galacticraft.class.$init$((Galacticraft)this); IndustrialCraft2Common.class.$init$((IndustrialCraft2Common)this); IndustrialCraft2Experimental.class.$init$((IndustrialCraft2Experimental)this); IndustrialCraft2Classic.class.$init$((IndustrialCraft2Classic)this); Mekanism.class.$init$((Mekanism)this); RedstoneFlux.class.$init$((RedstoneFlux)this); RotaryCraft.class.$init$((RotaryCraft)this); Environment.class.$init$((Environment)this); Hub.class.$init$(this); SimpleInventory.class.$init$((SimpleInventory)this); Inventory.class.$init$((Inventory)this); Inventory.class.$init$((Inventory)this); ComponentInventory.class.$init$((ComponentInventory)this); ComponentInventory.class.$init$((ComponentInventory)this); RotationAware.class.$init$((RotationAware)this); Rotatable.class.$init$((Rotatable)this); RedstoneAware.class.$init$((RedstoneAware)this); BundledRedstoneAware.class.$init$((BundledRedstoneAware)this); AbstractBusAware.class.$init$((AbstractBusAware)this); StateAware.class.$init$((StateAware)this); Computer.class.$init$(this);
/*  32 */     this.info = new MicrocontrollerData(MicrocontrollerData$.MODULE$.$lessinit$greater$default$1());
/*     */ 
/*     */ 
/*     */     
/*  36 */     this.outputSides = (boolean[])Array$.MODULE$.fill(6, (Function0)new Microcontroller$$anonfun$1(this), ClassTag$.MODULE$.Boolean());
/*     */     
/*  38 */     this.snooperNode = (ComponentConnector)Network.newNode((Environment)this, Visibility.Network)
/*  39 */       .withComponent("microcontroller")
/*  40 */       .withConnector(Settings$.MODULE$.get().bufferMicrocontroller())
/*  41 */       .create();
/*     */     
/*  43 */     this.componentNodes = (Component[])Array$.MODULE$.fill(6, 
/*     */         
/*  45 */         (Function0)new Microcontroller$$anonfun$2(this), ClassTag$.MODULE$.apply(Component.class));
/*     */     
/*  47 */     if (machine() != null)
/*  48 */     { ((Connector)machine().node()).setLocalBufferSize(0.0D);
/*  49 */       machine().setCostPerTick(Settings$.MODULE$.get().microcontrollerCost()); }  } public MicrocontrollerData info() { return this.info; } public Null$ node() { return null; } public boolean[] outputSides() { return this.outputSides; } public final class Microcontroller$$anonfun$1 extends AbstractFunction0.mcZ.sp implements Serializable {
/*     */     public static final long serialVersionUID = 0L; public final boolean apply() { return apply$mcZ$sp(); } public boolean apply$mcZ$sp() { return true; } public Microcontroller$$anonfun$1(Microcontroller $outer) {} } public ComponentConnector snooperNode() { return this.snooperNode; } public Component[] componentNodes() { return this.componentNodes; } public final class Microcontroller$$anonfun$2 extends AbstractFunction0<Component> implements Serializable {
/*     */     public static final long serialVersionUID = 0L; public final Component apply() { return (Component)Network.newNode((Environment)this.$outer, Visibility.Network).withComponent("microcontroller").create(); } public Microcontroller$$anonfun$2(Microcontroller $outer) {} }
/*  52 */   public int tier() { return info().tier(); }
/*     */    public None$ runSound() {
/*  54 */     return None$.MODULE$;
/*     */   }
/*  56 */   private Map deviceInfo$lzycompute() { synchronized (this) { if ((byte)(this.bitmap$0 & 0x1) == 0) { (new Tuple2[5])[0] = Predef$ArrowAssoc$.MODULE$
/*  57 */           .$minus$greater$extension(Predef$.MODULE$.ArrowAssoc("class"), "system");
/*  58 */         (new Tuple2[5])[1] = Predef$ArrowAssoc$.MODULE$.$minus$greater$extension(Predef$.MODULE$.ArrowAssoc("description"), "Microcontroller");
/*  59 */         (new Tuple2[5])[2] = Predef$ArrowAssoc$.MODULE$.$minus$greater$extension(Predef$.MODULE$.ArrowAssoc("vendor"), "MightyPirates GmbH & Co. KG");
/*  60 */         (new Tuple2[5])[3] = Predef$ArrowAssoc$.MODULE$.$minus$greater$extension(Predef$.MODULE$.ArrowAssoc("product"), "Cubicle");
/*  61 */         (new Tuple2[5])[4] = Predef$ArrowAssoc$.MODULE$.$minus$greater$extension(Predef$.MODULE$.ArrowAssoc("capacity"), BoxesRunTime.boxToInteger(func_70302_i_()).toString()); this.deviceInfo = (Map<String, String>)Predef$.MODULE$.Map().apply((Seq)Predef$.MODULE$.wrapRefArray((Object[])new Tuple2[5])); this.bitmap$0 = (byte)(this.bitmap$0 | 0x1); }
/*     */        return this.deviceInfo; }
/*     */      } private final Map<String, String> deviceInfo() { return ((byte)(this.bitmap$0 & 0x1) == 0) ? deviceInfo$lzycompute() : this.deviceInfo; }
/*  64 */   public Map<String, String> getDeviceInfo() { return WrapAsJava$.MODULE$.mapAsJavaMap((Map)deviceInfo()); }
/*     */ 
/*     */   
/*     */   @SideOnly(Side.CLIENT)
/*     */   public boolean canConnect(ForgeDirection side) {
/*  69 */     ForgeDirection forgeDirection = facing(); if (side == null) { if (forgeDirection != null); } else if (side.equals(forgeDirection))
/*     */     {  }
/*  71 */      } public Node sidedNode(ForgeDirection side) { ForgeDirection forgeDirection = facing(); if (side == null) { if (forgeDirection != null); } else if (side.equals(forgeDirection))
/*     */     {  }
/*     */      } @SideOnly(Side.CLIENT)
/*  74 */   public boolean hasConnector(ForgeDirection side) { ForgeDirection forgeDirection = facing(); if (side == null) { if (forgeDirection != null); } else if (side.equals(forgeDirection))
/*     */     {  }
/*  76 */      } public Option<Connector> connector(ForgeDirection side) { ForgeDirection forgeDirection = facing(); if (side == null) { if (forgeDirection != null); } else if (side.equals(forgeDirection))
/*     */     {  }
/*  78 */      } public double energyThroughput() { return Settings$.MODULE$.get().caseRate()[0]; }
/*     */    public World getWorld() {
/*  80 */     return world();
/*     */   }
/*     */ 
/*     */ 
/*     */ 
/*     */   
/*     */   public Node[] onAnalyze(EntityPlayer player, int side, float hitX, float hitY, float hitZ) {
/*     */     // Byte code:
/*     */     //   0: aload_0
/*     */     //   1: aload_1
/*     */     //   2: iload_2
/*     */     //   3: fload_3
/*     */     //   4: fload #4
/*     */     //   6: fload #5
/*     */     //   8: invokestatic onAnalyze : (Lli/cil/oc/common/tileentity/traits/Computer;Lnet/minecraft/entity/player/EntityPlayer;IFFF)[Lli/cil/oc/api/network/Node;
/*     */     //   11: pop
/*     */     //   12: iload_2
/*     */     //   13: invokestatic getOrientation : (I)Lnet/minecraftforge/common/util/ForgeDirection;
/*     */     //   16: aload_0
/*     */     //   17: invokevirtual facing : ()Lnet/minecraftforge/common/util/ForgeDirection;
/*     */     //   20: astore #6
/*     */     //   22: dup
/*     */     //   23: ifnonnull -> 35
/*     */     //   26: pop
/*     */     //   27: aload #6
/*     */     //   29: ifnull -> 43
/*     */     //   32: goto -> 68
/*     */     //   35: aload #6
/*     */     //   37: invokevirtual equals : (Ljava/lang/Object;)Z
/*     */     //   40: ifeq -> 68
/*     */     //   43: iconst_1
/*     */     //   44: anewarray li/cil/oc/api/network/Node
/*     */     //   47: dup
/*     */     //   48: iconst_0
/*     */     //   49: aload_0
/*     */     //   50: invokevirtual machine : ()Lli/cil/oc/api/machine/Machine;
/*     */     //   53: invokeinterface node : ()Lli/cil/oc/api/network/Node;
/*     */     //   58: aastore
/*     */     //   59: checkcast [Ljava/lang/Object;
/*     */     //   62: checkcast [Lli/cil/oc/api/network/Node;
/*     */     //   65: goto -> 87
/*     */     //   68: iconst_1
/*     */     //   69: anewarray li/cil/oc/api/network/Node
/*     */     //   72: dup
/*     */     //   73: iconst_0
/*     */     //   74: aload_0
/*     */     //   75: invokevirtual componentNodes : ()[Lli/cil/oc/api/network/Component;
/*     */     //   78: iload_2
/*     */     //   79: aaload
/*     */     //   80: aastore
/*     */     //   81: checkcast [Ljava/lang/Object;
/*     */     //   84: checkcast [Lli/cil/oc/api/network/Node;
/*     */     //   87: areturn
/*     */     // Line number table:
/*     */     //   Java source line number -> byte code offset
/*     */     //   #85	-> 0
/*     */     //   #86	-> 12
/*     */     //   #89	-> 43
/*     */     //   #87	-> 68
/*     */     //   #84	-> 87
/*     */     // Local variable table:
/*     */     //   start	length	slot	name	descriptor
/*     */     //   0	88	0	this	Lli/cil/oc/common/tileentity/Microcontroller;
/*     */     //   0	88	1	player	Lnet/minecraft/entity/player/EntityPlayer;
/*     */     //   0	88	2	side	I
/*     */     //   0	88	3	hitX	F
/*     */     //   0	88	4	hitY	F
/*     */     //   0	88	5	hitZ	F
/*     */   }
/*     */ 
/*     */ 
/*     */ 
/*     */   
/*     */   public Iterable<ItemStack> internalComponents() {
/*  94 */     return WrapAsJava$.MODULE$.asJavaIterable((Iterable)Predef$.MODULE$.wrapRefArray((Object[])info().components()));
/*     */   }
/*  96 */   public int componentSlot(String address) { return Predef$.MODULE$.refArrayOps((Object[])components()).indexWhere((Function1)new Microcontroller$$anonfun$componentSlot$1(this, address)); } public final class Microcontroller$$anonfun$componentSlot$1 extends AbstractFunction1<Option<ManagedEnvironment>, Object> implements Serializable { public static final long serialVersionUID = 0L; public final String address$1; public final boolean apply(Option x$1) { return x$1.exists((Function1)new Microcontroller$$anonfun$componentSlot$1$$anonfun$apply$1(this)); }
/*     */      public Microcontroller$$anonfun$componentSlot$1(Microcontroller $outer, String address$1) {} public final class Microcontroller$$anonfun$componentSlot$1$$anonfun$apply$1 extends AbstractFunction1<ManagedEnvironment, Object> implements Serializable {
/*     */       public static final long serialVersionUID = 0L; public final boolean apply(ManagedEnvironment env) {
/*     */         // Byte code:
/*     */         //   0: aload_1
/*     */         //   1: invokeinterface node : ()Lli/cil/oc/api/network/Node;
/*     */         //   6: ifnull -> 51
/*     */         //   9: aload_1
/*     */         //   10: invokeinterface node : ()Lli/cil/oc/api/network/Node;
/*     */         //   15: invokeinterface address : ()Ljava/lang/String;
/*     */         //   20: aload_0
/*     */         //   21: getfield $outer : Lli/cil/oc/common/tileentity/Microcontroller$$anonfun$componentSlot$1;
/*     */         //   24: getfield address$1 : Ljava/lang/String;
/*     */         //   27: astore_2
/*     */         //   28: dup
/*     */         //   29: ifnonnull -> 40
/*     */         //   32: pop
/*     */         //   33: aload_2
/*     */         //   34: ifnull -> 47
/*     */         //   37: goto -> 51
/*     */         //   40: aload_2
/*     */         //   41: invokevirtual equals : (Ljava/lang/Object;)Z
/*     */         //   44: ifeq -> 51
/*     */         //   47: iconst_1
/*     */         //   48: goto -> 52
/*     */         //   51: iconst_0
/*     */         //   52: ireturn
/*     */         // Line number table:
/*     */         //   Java source line number -> byte code offset
/*     */         //   #96	-> 0
/*     */         // Local variable table:
/*     */         //   start	length	slot	name	descriptor
/*     */         //   0	53	0	this	Lli/cil/oc/common/tileentity/Microcontroller$$anonfun$componentSlot$1$$anonfun$apply$1;
/*     */         //   0	53	1	env	Lli/cil/oc/api/network/ManagedEnvironment;
/*     */       } public Microcontroller$$anonfun$componentSlot$1$$anonfun$apply$1(Microcontroller$$anonfun$componentSlot$1 $outer) {} } } @Callback(doc = "function():boolean -- Starts the microcontroller. Returns true if the state changed.")
/*     */   public Object[] start(Context context, Arguments args) {
/* 102 */     return result((Seq<Object>)Predef$.MODULE$.genericWrapArray(new Object[] { BoxesRunTime.boxToBoolean((!machine().isPaused() && machine().start())) }));
/*     */   }
/*     */   @Callback(doc = "function():boolean -- Stops the microcontroller. Returns true if the state changed.")
/*     */   public Object[] stop(Context context, Arguments args) {
/* 106 */     return result((Seq<Object>)Predef$.MODULE$.genericWrapArray(new Object[] { BoxesRunTime.boxToBoolean(machine().stop()) }));
/*     */   }
/*     */   @Callback(direct = true, doc = "function():boolean -- Returns whether the microcontroller is running.")
/*     */   public Object[] isRunning(Context context, Arguments args) {
/* 110 */     return result((Seq<Object>)Predef$.MODULE$.genericWrapArray(new Object[] { BoxesRunTime.boxToBoolean(machine().isRunning()) }));
/*     */   }
/*     */   @Callback(direct = true, doc = "function():string -- Returns the reason the microcontroller crashed, if applicable.")
/*     */   public Object[] lastError(Context context, Arguments args) {
/* 114 */     return result((Seq<Object>)Predef$.MODULE$.genericWrapArray(new Object[] { machine().lastError() }));
/*     */   }
/*     */   @Callback(direct = true, doc = "function(side:number):boolean -- Get whether network messages are sent via the specified side.")
/*     */   public Object[] isSideOpen(Context context, Arguments args) {
/* 118 */     (new ForgeDirection[1])[0] = facing(); ForgeDirection side = ExtendedArguments$.MODULE$.extendedArguments(args).checkSideExcept(0, (Seq)Predef$.MODULE$.wrapRefArray((Object[])new ForgeDirection[1]));
/* 119 */     return result((Seq<Object>)Predef$.MODULE$.genericWrapArray(new Object[] { BoxesRunTime.boxToBoolean(outputSides()[side.ordinal()]) }));
/*     */   }
/*     */   
/*     */   @Callback(doc = "function(side:number, open:boolean):boolean -- Set whether network messages are sent via the specified side.")
/*     */   public Object[] setSideOpen(Context context, Arguments args) {
/* 124 */     (new ForgeDirection[1])[0] = facing(); ForgeDirection side = ExtendedArguments$.MODULE$.extendedArguments(args).checkSideExcept(0, (Seq)Predef$.MODULE$.wrapRefArray((Object[])new ForgeDirection[1]));
/* 125 */     boolean oldValue = outputSides()[side.ordinal()];
/* 126 */     outputSides()[side.ordinal()] = args.checkBoolean(1);
/* 127 */     return result((Seq<Object>)Predef$.MODULE$.genericWrapArray(new Object[] { BoxesRunTime.boxToBoolean(oldValue) }));
/*     */   }
/*     */ 
/*     */   
/*     */   public boolean canUpdate() {
/* 132 */     return isServer();
/*     */   }
/*     */   
/* 135 */   public void func_145845_h() { Computer.class.updateEntity(this);
/*     */ 
/*     */     
/* 138 */     if (world().func_82737_E() % Settings$.MODULE$.get().tickFrequency() == false)
/* 139 */       Predef$.MODULE$.refArrayOps((Object[])ForgeDirection.VALID_DIRECTIONS).withFilter((Function1)new Microcontroller$$anonfun$updateEntity$1(this)).foreach((Function1)new Microcontroller$$anonfun$updateEntity$2(this));  } public final class Microcontroller$$anonfun$updateEntity$1 extends AbstractFunction1<ForgeDirection, Object> implements Serializable { public static final long serialVersionUID = 0L; public final boolean apply(ForgeDirection side) { ForgeDirection forgeDirection = this.$outer.facing(); if (side == null) { if (forgeDirection != null); } else if (side.equals(forgeDirection)) {  }
/* 140 */        } public Microcontroller$$anonfun$updateEntity$1(Microcontroller $outer) {} } public final class Microcontroller$$anonfun$updateEntity$2 extends AbstractFunction1<ForgeDirection, Object> implements Serializable { public static final long serialVersionUID = 0L; public Microcontroller$$anonfun$updateEntity$2(Microcontroller $outer) {} public final Object apply(ForgeDirection side) { BoxedUnit boxedUnit; Node node = this.$outer.sidedNode(side);
/* 141 */       if (node instanceof Connector) { Connector connector = (Connector)node;
/* 142 */         double demand = this.$outer.snooperNode().globalBufferSize() - this.$outer.snooperNode().globalBuffer();
/* 143 */         double available = demand + connector.changeBuffer(-demand);
/* 144 */         Double double_ = BoxesRunTime.boxToDouble(this.$outer.snooperNode().changeBuffer(available)); }
/* 145 */       else { boxedUnit = BoxedUnit.UNIT; }
/*     */       
/*     */       return boxedUnit; }
/*     */      }
/*     */ 
/*     */ 
/*     */ 
/*     */   
/*     */   public void connectItemNode(Node node) {
/* 154 */     if (machine() != null && machine().node() != null && node != null) {
/* 155 */       Network.joinNewNetwork(machine().node());
/* 156 */       machine().node().connect(node);
/*     */     } 
/*     */   }
/*     */ 
/*     */ 
/*     */ 
/*     */   
/*     */   public Node createNode(Hub.Plug plug) {
/* 164 */     return Network.newNode((Environment)plug, Visibility.Network).withConnector().create();
/*     */   }
/*     */ 
/*     */   
/*     */   public void onPlugConnect(Hub.Plug plug, Node node) {
/*     */     // Byte code:
/*     */     //   0: aload_0
/*     */     //   1: aload_1
/*     */     //   2: aload_2
/*     */     //   3: invokestatic onPlugConnect : (Lli/cil/oc/common/tileentity/traits/Hub;Lli/cil/oc/common/tileentity/traits/Hub$Plug;Lli/cil/oc/api/network/Node;)V
/*     */     //   6: aload_2
/*     */     //   7: aload_1
/*     */     //   8: invokevirtual node : ()Lli/cil/oc/api/network/Node;
/*     */     //   11: astore_3
/*     */     //   12: dup
/*     */     //   13: ifnonnull -> 24
/*     */     //   16: pop
/*     */     //   17: aload_3
/*     */     //   18: ifnull -> 31
/*     */     //   21: goto -> 65
/*     */     //   24: aload_3
/*     */     //   25: invokevirtual equals : (Ljava/lang/Object;)Z
/*     */     //   28: ifeq -> 65
/*     */     //   31: aload_0
/*     */     //   32: invokevirtual machine : ()Lli/cil/oc/api/machine/Machine;
/*     */     //   35: invokeinterface node : ()Lli/cil/oc/api/network/Node;
/*     */     //   40: invokestatic joinNewNetwork : (Lli/cil/oc/api/network/Node;)V
/*     */     //   43: aload_0
/*     */     //   44: invokevirtual machine : ()Lli/cil/oc/api/machine/Machine;
/*     */     //   47: invokeinterface node : ()Lli/cil/oc/api/network/Node;
/*     */     //   52: aload_0
/*     */     //   53: invokevirtual snooperNode : ()Lli/cil/oc/api/network/ComponentConnector;
/*     */     //   56: invokeinterface connect : (Lli/cil/oc/api/network/Node;)V
/*     */     //   61: aload_0
/*     */     //   62: invokevirtual connectComponents : ()V
/*     */     //   65: aload_1
/*     */     //   66: invokevirtual isPrimary : ()Z
/*     */     //   69: ifeq -> 96
/*     */     //   72: aload_1
/*     */     //   73: invokevirtual node : ()Lli/cil/oc/api/network/Node;
/*     */     //   76: aload_0
/*     */     //   77: invokevirtual componentNodes : ()[Lli/cil/oc/api/network/Component;
/*     */     //   80: aload_1
/*     */     //   81: invokevirtual side : ()Lnet/minecraftforge/common/util/ForgeDirection;
/*     */     //   84: invokevirtual ordinal : ()I
/*     */     //   87: aaload
/*     */     //   88: invokeinterface connect : (Lli/cil/oc/api/network/Node;)V
/*     */     //   93: goto -> 113
/*     */     //   96: aload_0
/*     */     //   97: invokevirtual componentNodes : ()[Lli/cil/oc/api/network/Component;
/*     */     //   100: aload_1
/*     */     //   101: invokevirtual side : ()Lnet/minecraftforge/common/util/ForgeDirection;
/*     */     //   104: invokevirtual ordinal : ()I
/*     */     //   107: aaload
/*     */     //   108: invokeinterface remove : ()V
/*     */     //   113: return
/*     */     // Line number table:
/*     */     //   Java source line number -> byte code offset
/*     */     //   #167	-> 0
/*     */     //   #168	-> 6
/*     */     //   #169	-> 31
/*     */     //   #170	-> 43
/*     */     //   #171	-> 61
/*     */     //   #173	-> 65
/*     */     //   #174	-> 72
/*     */     //   #176	-> 96
/*     */     //   #166	-> 113
/*     */     // Local variable table:
/*     */     //   start	length	slot	name	descriptor
/*     */     //   0	114	0	this	Lli/cil/oc/common/tileentity/Microcontroller;
/*     */     //   0	114	1	plug	Lli/cil/oc/common/tileentity/traits/Hub$Plug;
/*     */     //   0	114	2	node	Lli/cil/oc/api/network/Node;
/*     */   }
/*     */ 
/*     */   
/*     */   public void onPlugDisconnect(Hub.Plug plug, Node node) {
/*     */     // Byte code:
/*     */     //   0: aload_0
/*     */     //   1: aload_1
/*     */     //   2: aload_2
/*     */     //   3: invokestatic onPlugDisconnect : (Lli/cil/oc/common/tileentity/traits/Hub;Lli/cil/oc/common/tileentity/traits/Hub$Plug;Lli/cil/oc/api/network/Node;)V
/*     */     //   6: aload_1
/*     */     //   7: invokevirtual isPrimary : ()Z
/*     */     //   10: ifeq -> 62
/*     */     //   13: aload_2
/*     */     //   14: aload_1
/*     */     //   15: invokevirtual node : ()Lli/cil/oc/api/network/Node;
/*     */     //   18: astore_3
/*     */     //   19: dup
/*     */     //   20: ifnonnull -> 31
/*     */     //   23: pop
/*     */     //   24: aload_3
/*     */     //   25: ifnull -> 62
/*     */     //   28: goto -> 38
/*     */     //   31: aload_3
/*     */     //   32: invokevirtual equals : (Ljava/lang/Object;)Z
/*     */     //   35: ifne -> 62
/*     */     //   38: aload_1
/*     */     //   39: invokevirtual node : ()Lli/cil/oc/api/network/Node;
/*     */     //   42: aload_0
/*     */     //   43: invokevirtual componentNodes : ()[Lli/cil/oc/api/network/Component;
/*     */     //   46: aload_1
/*     */     //   47: invokevirtual side : ()Lnet/minecraftforge/common/util/ForgeDirection;
/*     */     //   50: invokevirtual ordinal : ()I
/*     */     //   53: aaload
/*     */     //   54: invokeinterface connect : (Lli/cil/oc/api/network/Node;)V
/*     */     //   59: goto -> 79
/*     */     //   62: aload_0
/*     */     //   63: invokevirtual componentNodes : ()[Lli/cil/oc/api/network/Component;
/*     */     //   66: aload_1
/*     */     //   67: invokevirtual side : ()Lnet/minecraftforge/common/util/ForgeDirection;
/*     */     //   70: invokevirtual ordinal : ()I
/*     */     //   73: aaload
/*     */     //   74: invokeinterface remove : ()V
/*     */     //   79: aload_2
/*     */     //   80: aload_1
/*     */     //   81: invokevirtual node : ()Lli/cil/oc/api/network/Node;
/*     */     //   84: astore #4
/*     */     //   86: dup
/*     */     //   87: ifnonnull -> 99
/*     */     //   90: pop
/*     */     //   91: aload #4
/*     */     //   93: ifnull -> 107
/*     */     //   96: goto -> 111
/*     */     //   99: aload #4
/*     */     //   101: invokevirtual equals : (Ljava/lang/Object;)Z
/*     */     //   104: ifeq -> 111
/*     */     //   107: aload_0
/*     */     //   108: invokevirtual disconnectComponents : ()V
/*     */     //   111: return
/*     */     // Line number table:
/*     */     //   Java source line number -> byte code offset
/*     */     //   #180	-> 0
/*     */     //   #181	-> 6
/*     */     //   #182	-> 38
/*     */     //   #184	-> 62
/*     */     //   #185	-> 79
/*     */     //   #186	-> 107
/*     */     //   #179	-> 111
/*     */     // Local variable table:
/*     */     //   start	length	slot	name	descriptor
/*     */     //   0	112	0	this	Lli/cil/oc/common/tileentity/Microcontroller;
/*     */     //   0	112	1	plug	Lli/cil/oc/common/tileentity/traits/Hub$Plug;
/*     */     //   0	112	2	node	Lli/cil/oc/api/network/Node;
/*     */   }
/*     */ 
/*     */   
/*     */   public void onPlugMessage(Hub.Plug plug, Message message) {
/*     */     // Byte code:
/*     */     //   0: aload_2
/*     */     //   1: invokeinterface name : ()Ljava/lang/String;
/*     */     //   6: ldc_w 'network.message'
/*     */     //   9: astore_3
/*     */     //   10: dup
/*     */     //   11: ifnonnull -> 22
/*     */     //   14: pop
/*     */     //   15: aload_3
/*     */     //   16: ifnull -> 29
/*     */     //   19: goto -> 93
/*     */     //   22: aload_3
/*     */     //   23: invokevirtual equals : (Ljava/lang/Object;)Z
/*     */     //   26: ifeq -> 93
/*     */     //   29: aload_2
/*     */     //   30: invokeinterface source : ()Lli/cil/oc/api/network/Node;
/*     */     //   35: invokeinterface network : ()Lli/cil/oc/api/network/Network;
/*     */     //   40: aload_0
/*     */     //   41: invokevirtual snooperNode : ()Lli/cil/oc/api/network/ComponentConnector;
/*     */     //   44: invokeinterface network : ()Lli/cil/oc/api/network/Network;
/*     */     //   49: astore #4
/*     */     //   51: dup
/*     */     //   52: ifnonnull -> 64
/*     */     //   55: pop
/*     */     //   56: aload #4
/*     */     //   58: ifnull -> 93
/*     */     //   61: goto -> 72
/*     */     //   64: aload #4
/*     */     //   66: invokevirtual equals : (Ljava/lang/Object;)Z
/*     */     //   69: ifne -> 93
/*     */     //   72: aload_0
/*     */     //   73: invokevirtual snooperNode : ()Lli/cil/oc/api/network/ComponentConnector;
/*     */     //   76: aload_2
/*     */     //   77: invokeinterface name : ()Ljava/lang/String;
/*     */     //   82: aload_2
/*     */     //   83: invokeinterface data : ()[Ljava/lang/Object;
/*     */     //   88: invokeinterface sendToReachable : (Ljava/lang/String;[Ljava/lang/Object;)V
/*     */     //   93: return
/*     */     // Line number table:
/*     */     //   Java source line number -> byte code offset
/*     */     //   #190	-> 0
/*     */     //   #191	-> 72
/*     */     //   #190	-> 93
/*     */     // Local variable table:
/*     */     //   start	length	slot	name	descriptor
/*     */     //   0	94	0	this	Lli/cil/oc/common/tileentity/Microcontroller;
/*     */     //   0	94	1	plug	Lli/cil/oc/common/tileentity/traits/Hub$Plug;
/*     */     //   0	94	2	message	Lli/cil/oc/api/network/Message;
/*     */   }
/*     */ 
/*     */   
/*     */   public void onMessage(Message message) {
/*     */     // Byte code:
/*     */     //   0: aload_1
/*     */     //   1: invokeinterface name : ()Ljava/lang/String;
/*     */     //   6: ldc_w 'network.message'
/*     */     //   9: astore_2
/*     */     //   10: dup
/*     */     //   11: ifnonnull -> 22
/*     */     //   14: pop
/*     */     //   15: aload_2
/*     */     //   16: ifnull -> 29
/*     */     //   19: goto -> 108
/*     */     //   22: aload_2
/*     */     //   23: invokevirtual equals : (Ljava/lang/Object;)Z
/*     */     //   26: ifeq -> 108
/*     */     //   29: aload_1
/*     */     //   30: invokeinterface source : ()Lli/cil/oc/api/network/Node;
/*     */     //   35: invokeinterface network : ()Lli/cil/oc/api/network/Network;
/*     */     //   40: aload_0
/*     */     //   41: invokevirtual snooperNode : ()Lli/cil/oc/api/network/ComponentConnector;
/*     */     //   44: invokeinterface network : ()Lli/cil/oc/api/network/Network;
/*     */     //   49: astore_3
/*     */     //   50: dup
/*     */     //   51: ifnonnull -> 62
/*     */     //   54: pop
/*     */     //   55: aload_3
/*     */     //   56: ifnull -> 69
/*     */     //   59: goto -> 108
/*     */     //   62: aload_3
/*     */     //   63: invokevirtual equals : (Ljava/lang/Object;)Z
/*     */     //   66: ifeq -> 108
/*     */     //   69: getstatic scala/Predef$.MODULE$ : Lscala/Predef$;
/*     */     //   72: getstatic net/minecraftforge/common/util/ForgeDirection.VALID_DIRECTIONS : [Lnet/minecraftforge/common/util/ForgeDirection;
/*     */     //   75: checkcast [Ljava/lang/Object;
/*     */     //   78: invokevirtual refArrayOps : ([Ljava/lang/Object;)Lscala/collection/mutable/ArrayOps;
/*     */     //   81: new li/cil/oc/common/tileentity/Microcontroller$$anonfun$onMessage$1
/*     */     //   84: dup
/*     */     //   85: aload_0
/*     */     //   86: invokespecial <init> : (Lli/cil/oc/common/tileentity/Microcontroller;)V
/*     */     //   89: invokeinterface withFilter : (Lscala/Function1;)Lscala/collection/generic/FilterMonadic;
/*     */     //   94: new li/cil/oc/common/tileentity/Microcontroller$$anonfun$onMessage$2
/*     */     //   97: dup
/*     */     //   98: aload_0
/*     */     //   99: aload_1
/*     */     //   100: invokespecial <init> : (Lli/cil/oc/common/tileentity/Microcontroller;Lli/cil/oc/api/network/Message;)V
/*     */     //   103: invokeinterface foreach : (Lscala/Function1;)V
/*     */     //   108: return
/*     */     // Line number table:
/*     */     //   Java source line number -> byte code offset
/*     */     //   #196	-> 0
/*     */     //   #197	-> 69
/*     */     //   #196	-> 108
/*     */     // Local variable table:
/*     */     //   start	length	slot	name	descriptor
/*     */     //   0	109	0	this	Lli/cil/oc/common/tileentity/Microcontroller;
/*     */     //   0	109	1	message	Lli/cil/oc/api/network/Message;
/*     */   }
/*     */ 
/*     */   
/*     */   public final class Microcontroller$$anonfun$onMessage$1
/*     */     extends AbstractFunction1<ForgeDirection, Object>
/*     */     implements Serializable
/*     */   {
/*     */     public static final long serialVersionUID = 0L;
/*     */ 
/*     */     
/*     */     public final boolean apply(ForgeDirection side)
/*     */     {
/* 197 */       if (this.$outer.outputSides()[side.ordinal()]) { ForgeDirection forgeDirection = this.$outer.facing(); if (side == null) { if (forgeDirection != null); } else if (!side.equals(forgeDirection)) {  }  }  return false; } public Microcontroller$$anonfun$onMessage$1(Microcontroller $outer) {} } public final class Microcontroller$$anonfun$onMessage$2 extends AbstractFunction1<ForgeDirection, BoxedUnit> implements Serializable { public static final long serialVersionUID = 0L; private final Message message$1; public Microcontroller$$anonfun$onMessage$2(Microcontroller $outer, Message message$1) {} public final void apply(ForgeDirection side) {
/* 198 */       this.$outer.sidedNode(side).sendToReachable(this.message$1.name(), this.message$1.data());
/*     */     } }
/*     */ 
/*     */ 
/*     */ 
/*     */ 
/*     */ 
/*     */ 
/*     */   
/*     */   public void readFromNBTForServer(NBTTagCompound nbt) {
/* 208 */     info().load(nbt.func_74775_l((new StringBuilder()).append(Settings$.MODULE$.namespace()).append("info").toString()));
/* 209 */     ExtendedNBT$.MODULE$.extendNBTTagCompound(nbt).getBooleanArray((new StringBuilder()).append(Settings$.MODULE$.namespace()).append("outputs").toString());
/*     */     
/* 211 */     Predef$.MODULE$.refArrayOps((Object[])Predef$.MODULE$.refArrayOps((Object[])ExtendedNBT$.MODULE$.extendNBTTagList(nbt.func_150295_c((new StringBuilder()).append(Settings$.MODULE$.namespace()).append("componentNodes").toString(), 10)).toArray(ClassTag$.MODULE$.apply(NBTTagCompound.class))).zipWithIndex(Array$.MODULE$.canBuildFrom(ClassTag$.MODULE$.apply(Tuple2.class)))).foreach((Function1)new Microcontroller$$anonfun$readFromNBTForServer$1(this));
/*     */ 
/*     */     
/* 214 */     snooperNode().load(nbt.func_74775_l((new StringBuilder()).append(Settings$.MODULE$.namespace()).append("snooper").toString()));
/* 215 */     Computer.class.readFromNBTForServer(this, nbt);
/* 216 */     Network.joinNewNetwork(machine().node());
/* 217 */     machine().node().connect((Node)snooperNode());
/*     */   } public final class Microcontroller$$anonfun$readFromNBTForServer$1 extends AbstractFunction1<Tuple2<NBTTagCompound, Object>, BoxedUnit> implements Serializable {
/*     */     public static final long serialVersionUID = 0L; public final void apply(Tuple2 x0$1) { Tuple2 tuple2 = x0$1; if (tuple2 != null) {
/*     */         NBTTagCompound tag = (NBTTagCompound)tuple2._1(); int index = tuple2._2$mcI$sp(); this.$outer.componentNodes()[index].load(tag); BoxedUnit boxedUnit = BoxedUnit.UNIT; return;
/* 221 */       }  throw new MatchError(tuple2); } public Microcontroller$$anonfun$readFromNBTForServer$1(Microcontroller $outer) {} } public void writeToNBTForServer(NBTTagCompound nbt) { Computer.class.writeToNBTForServer(this, nbt);
/* 222 */     ExtendedNBT$.MODULE$.extendNBTTagCompound(nbt).setNewCompoundTag((new StringBuilder()).append(Settings$.MODULE$.namespace()).append("info").toString(), (Function1)new Microcontroller$$anonfun$writeToNBTForServer$1(this));
/* 223 */     ExtendedNBT$.MODULE$.extendNBTTagCompound(nbt).setBooleanArray((new StringBuilder()).append(Settings$.MODULE$.namespace()).append("outputs").toString(), outputSides());
/* 224 */     ExtendedNBT$.MODULE$.extendNBTTagCompound(nbt).setNewTagList((new StringBuilder()).append(Settings$.MODULE$.namespace()).append("componentNodes").toString(), (Iterable)Predef$.MODULE$.wrapRefArray((Object[])Predef$.MODULE$.refArrayOps((Object[])componentNodes()).map((Function1)new Microcontroller$$anonfun$writeToNBTForServer$2(this), Array$.MODULE$.canBuildFrom(ClassTag$.MODULE$.apply(NBTTagCompound.class)))));
/*     */ 
/*     */ 
/*     */ 
/*     */ 
/*     */ 
/*     */     
/* 231 */     ExtendedNBT$.MODULE$.extendNBTTagCompound(nbt).setNewCompoundTag((new StringBuilder()).append(Settings$.MODULE$.namespace()).append("snooper").toString(), (Function1)new Microcontroller$$anonfun$writeToNBTForServer$3(this)); } public final class Microcontroller$$anonfun$writeToNBTForServer$1 extends AbstractFunction1<NBTTagCompound, BoxedUnit> implements Serializable { public static final long serialVersionUID = 0L; public final void apply(NBTTagCompound nbt) { this.$outer.info().save(nbt); } public Microcontroller$$anonfun$writeToNBTForServer$1(Microcontroller $outer) {} } public final class Microcontroller$$anonfun$writeToNBTForServer$2 extends AbstractFunction1<Component, NBTTagCompound> implements Serializable { public static final long serialVersionUID = 0L; public final NBTTagCompound apply(Component x0$2) { NBTTagCompound nBTTagCompound; Component component = x0$2; if (component != null) { Component component1 = component; NBTTagCompound tag = new NBTTagCompound(); component1.save(tag); nBTTagCompound = tag; } else { nBTTagCompound = new NBTTagCompound(); }  return nBTTagCompound; } public Microcontroller$$anonfun$writeToNBTForServer$2(Microcontroller $outer) {} } public final class Microcontroller$$anonfun$writeToNBTForServer$3 extends AbstractFunction1<NBTTagCompound, BoxedUnit> implements Serializable { public static final long serialVersionUID = 0L; public final void apply(NBTTagCompound x$1) { this.$outer.snooperNode().save(x$1); }
/*     */ 
/*     */     
/*     */     public Microcontroller$$anonfun$writeToNBTForServer$3(Microcontroller $outer) {} }
/*     */   
/*     */   @SideOnly(Side.CLIENT)
/*     */   public void readFromNBTForClient(NBTTagCompound nbt) {
/* 238 */     info().load(nbt.func_74775_l("info"));
/* 239 */     Computer.class.readFromNBTForClient(this, nbt);
/*     */   }
/*     */   
/*     */   public void writeToNBTForClient(NBTTagCompound nbt) {
/* 243 */     Computer.class.writeToNBTForClient(this, nbt);
/* 244 */     ExtendedNBT$.MODULE$.extendNBTTagCompound(nbt).setNewCompoundTag("info", (Function1)new Microcontroller$$anonfun$writeToNBTForClient$1(this)); } public final class Microcontroller$$anonfun$writeToNBTForClient$1 extends AbstractFunction1<NBTTagCompound, BoxedUnit> implements Serializable { public static final long serialVersionUID = 0L; public final void apply(NBTTagCompound nbt) { this.$outer.info().save(nbt); }
/*     */     
/*     */     public Microcontroller$$anonfun$writeToNBTForClient$1(Microcontroller $outer) {} }
/* 247 */   public Option<ItemStack>[] items() { return (Option<ItemStack>[])Predef$.MODULE$.refArrayOps((Object[])info().components()).map((Function1)new Microcontroller$$anonfun$items$1(this), Array$.MODULE$.canBuildFrom(ClassTag$.MODULE$.apply(Option.class))); } public final class Microcontroller$$anonfun$items$1 extends AbstractFunction1<ItemStack, Option<ItemStack>> implements Serializable { public static final long serialVersionUID = 0L; public final Option<ItemStack> apply(ItemStack x$2) { return Option$.MODULE$.apply(x$2); }
/*     */      public Microcontroller$$anonfun$items$1(Microcontroller $outer) {} } public void updateItems(int slot, ItemStack stack) {
/* 249 */     info().components()[slot] = stack;
/*     */   } public int func_70302_i_() {
/* 251 */     return (info().components()).length;
/*     */   } public boolean func_94041_b(int slot, ItemStack stack) {
/* 253 */     return false;
/*     */   }
/*     */   
/*     */   public void func_70299_a(int slot, ItemStack stack) {}
/*     */   
/*     */   public Null$ decrStackSize(int slot, int amount) {
/* 259 */     return null;
/*     */   }
/*     */   public Null$ getStackInSlotOnClosing(int slot) {
/* 262 */     return null;
/*     */   }
/*     */   public int[] func_94128_d(int side) {
/* 265 */     return (int[])Array$.MODULE$.apply((Seq)Nil$.MODULE$, ClassTag$.MODULE$.Int());
/*     */   } public boolean func_102008_b(int slot, ItemStack stack, int side) {
/* 267 */     return false;
/*     */   } public boolean func_102007_a(int slot, ItemStack stack, int side) {
/* 269 */     return false;
/*     */   }
/*     */   
/*     */   public Option<ItemStack> changeEEPROM(ItemStack newEeprom) {
/* 273 */     int oldEepromIndex = Predef$.MODULE$.refArrayOps((Object[])info().components()).indexWhere((Function1)new Microcontroller$$anonfun$3(this));
/*     */     
/* 275 */     ItemStack oldEeprom = info().components()[oldEepromIndex];
/* 276 */     Inventory.class.setInventorySlotContents((Inventory)this, oldEepromIndex, newEeprom);
/*     */ 
/*     */ 
/*     */     
/* 280 */     Predef$.MODULE$.assert((info().components()[func_70302_i_() - 1] == null));
/* 281 */     Inventory.class.setInventorySlotContents((Inventory)this, func_70302_i_() - 1, newEeprom);
/* 282 */     return (oldEepromIndex >= 0) ? (Option<ItemStack>)new Some(oldEeprom) : (Option<ItemStack>)None$.MODULE$;
/*     */   }
/*     */   
/*     */   public final class Microcontroller$$anonfun$3 extends AbstractFunction1<ItemStack, Object> implements Serializable {
/*     */     public static final long serialVersionUID = 0L;
/*     */     
/*     */     public final boolean apply(ItemStack x$3) {
/*     */       ItemInfo itemInfo = Items.get("eeprom");
/*     */       if (Items.get(x$3) == null) {
/*     */         Items.get(x$3);
/*     */         if (itemInfo != null);
/*     */       } else if (Items.get(x$3).equals(itemInfo)) {
/*     */       
/*     */       } 
/*     */     }
/*     */     
/*     */     public Microcontroller$$anonfun$3(Microcontroller $outer) {}
/*     */   }
/*     */ }


/* Location:              C:\Users\shame\AppData\Roaming\PrismLauncher\instances\GT_New_Horizons_2.7.4_Java_17-21\.minecraft\mods\OpenComputers-1.10.30-GTNH.jar!\li\cil\oc\common\tileentity\Microcontroller.class
 * Java compiler version: 8 (52.0)
 * JD-Core Version:       1.1.3
 */