/*     */ package li.cil.oc.common.tileentity;
/*     */ @ScalaSignature(bytes = "\006\001\r]h\001B\001\003\0015\021q\001\025:j]R,'O\003\002\004\t\005QA/\0337fK:$\030\016^=\013\005\0251\021AB2p[6|gN\003\002\b\021\005\021qn\031\006\003\023)\t1aY5m\025\005Y\021A\0017j\007\001\031\022\002\001\b\030;\001\0323F\f\033\021\005=)R\"\001\t\013\005\r\t\"B\001\n\024\003%i\027N\\3de\0064GOC\001\025\003\rqW\r^\005\003-A\021!\002V5mK\026sG/\033;z!\tA2$D\001\032\025\tQ\"!\001\004ue\006LGo]\005\0039e\0211\"\0228wSJ|g.\\3oiB\021\001DH\005\003?e\021\021\"\0238wK:$xN]=\021\005a\t\023B\001\022\032\005%\021v\016^1uC\ndW\r\005\002%S5\tQE\003\002'O\0059a.\032;x_J\\'B\001\025\007\003\r\t\007/[\005\003U\025\022\001cU5eK\022,eN^5s_:lWM\034;\021\005aa\023BA\027\032\005)\031F/\031;f\003^\f'/\032\t\003_Ij\021\001\r\006\003cE\t\021\"\0338wK:$xN]=\n\005M\002$aD%TS\022,G-\0238wK:$xN]=\021\005UBT\"\001\034\013\005]:\023A\0023sSZ,'/\003\002:m\tQA)\032<jG\026LeNZ8\t\013m\002A\021\001\037\002\rqJg.\033;?)\005i\004C\001 \001\033\005\021\001b\002!\001\005\004%\t!Q\001\005]>$W-F\001C!\t!3)\003\002EK\t\0212i\\7q_:,g\016^\"p]:,7\r^8s\021\0311\005\001)A\005\005\006)an\0343fA!9\001\n\001b\001\n\003I\025!E7bq\006kw.\0368u\033\006$XM]5bYV\t!\n\005\002L\0356\tAJC\001N\003\025\0318-\0317b\023\tyEJA\002J]RDa!\025\001!\002\023Q\025AE7bq\006kw.\0368u\033\006$XM]5bY\002Bqa\025\001A\002\023\005\021*\001\bb[>,h\016^'bi\026\024\030.\0317\t\017U\003\001\031!C\001-\006\021\022-\\8v]Rl\025\r^3sS\006dw\fJ3r)\t9&\f\005\002L1&\021\021\f\024\002\005+:LG\017C\004\\)\006\005\t\031\001&\002\007a$\023\007\003\004^\001\001\006KAS\001\020C6|WO\034;NCR,'/[1mA!9q\f\001b\001\n\003I\025\001D7bq\006kw.\0368u\023:\\\007BB1\001A\003%!*A\007nCb\fUn\\;oi&s7\016\t\005\bG\002\001\r\021\"\001J\003%\tWn\\;oi&s7\016C\004f\001\001\007I\021\0014\002\033\005lw.\0368u\023:\\w\fJ3r)\t9v\rC\004\\I\006\005\t\031\001&\t\r%\004\001\025)\003K\003)\tWn\\;oi&s7\016\t\005\bW\002\001\r\021\"\001m\003\021!\027\r^1\026\0035\004\"A\034:\016\003=T!a\0339\013\005E$\021\001B5uK6L!a]8\003\023A\023\030N\034;ECR\f\007bB;\001\001\004%\tA^\001\tI\006$\030m\030\023fcR\021qk\036\005\b7R\f\t\0211\001n\021\031I\b\001)Q\005[\006)A-\031;bA!91\020\001a\001\n\003a\030\001C5t\003\016$\030N^3\026\003u\004\"a\023@\n\005}d%a\002\"p_2,\027M\034\005\n\003\007\001\001\031!C\001\003\013\tA\"[:BGRLg/Z0%KF$2aVA\004\021!Y\026\021AA\001\002\004i\bbBA\006\001\001\006K!`\001\nSN\f5\r^5wK\002B\001\"a\004\001\001\004%\t!S\001\006Y&l\027\016\036\005\n\003'\001\001\031!C\001\003+\t\021\002\\5nSR|F%Z9\025\007]\0139\002\003\005\\\003#\t\t\0211\001K\021\035\tY\002\001Q!\n)\013a\001\\5nSR\004\003\"CA\020\001\001\007I\021AA\021\003\031yW\017\0369viV\021\0211\005\t\006\027\006\025\022\021F\005\004\003Oa%AB(qi&|g\016\005\003\002,\005=RBAA\027\025\t\t\030#\003\003\0022\0055\"!C%uK6\034F/Y2l\021%\t)\004\001a\001\n\003\t9$\001\006pkR\004X\017^0%KF$2aVA\035\021%Y\0261GA\001\002\004\t\031\003\003\005\002>\001\001\013\025BA\022\003\035yW\017\0369vi\002B\021\"!\021\001\001\004%\t!a\021\002'Q|G/\0317SKF,\030N]3e\013:,'oZ=\026\005\005\025\003cA&\002H%\031\021\021\n'\003\r\021{WO\0317f\021%\ti\005\001a\001\n\003\ty%A\fu_R\fGNU3rk&\024X\rZ#oKJ<\027p\030\023fcR\031q+!\025\t\023m\013Y%!AA\002\005\025\003\002CA+\001\001\006K!!\022\002)Q|G/\0317SKF,\030N]3e\013:,'oZ=!\021%\tI\006\001a\001\n\003\t\031%\001\bsKF,\030N]3e\013:,'oZ=\t\023\005u\003\0011A\005\002\005}\023A\005:fcVL'/\0323F]\026\024x-_0%KF$2aVA1\021%Y\0261LA\001\002\004\t)\005\003\005\002f\001\001\013\025BA#\003=\021X-];je\026$WI\\3sOf\004\003\002CA5\001\t\007I\021A%\002\031Mdw\016^'bi\026\024\030.\0317\t\017\0055\004\001)A\005\025\006i1\017\\8u\033\006$XM]5bY\002B\001\"!\035\001\005\004%\t!S\001\bg2|G/\0238l\021\035\t)\b\001Q\001\n)\013\001b\0357pi&s7\016\t\005\t\003s\002!\031!C\001\023\006Q1\017\\8u\037V$\b/\036;\t\017\005u\004\001)A\005\025\006Y1\017\\8u\037V$\b/\036;!\021)\t\t\t\001EC\002\0235\0211Q\001\013I\0264\030nY3J]\032|WCAAC!!\t9)!%\002\026\006UUBAAE\025\021\tY)!$\002\023%lW.\036;bE2,'bAAH\031\006Q1m\0347mK\016$\030n\0348\n\t\005M\025\021\022\002\004\033\006\004\b\003BAL\003Ck!!!'\013\t\005m\025QT\001\005Y\006twM\003\002\002 \006!!.\031<b\023\021\t\031+!'\003\rM#(/\0338h\021)\t9\013\001E\001B\0036\021QQ\001\fI\0264\030nY3J]\032|\007\005C\004\002,\002!\t%!,\002\033\035,G\017R3wS\016,\027J\0344p)\t\ty\013\005\005\0022\006]\026\021XA]\033\t\t\031L\003\003\0026\006u\025\001B;uS2LA!a%\0024B!\0211XAa\035\rY\025QX\005\004\003c\025A\002)sK\022,g-\003\003\002$\006\r'bAA`\031\"9\021q\031\001\005B\005%\027AC2b]\016{gN\\3diR\031Q0a3\t\021\0055\027Q\031a\001\003\037\fAa]5eKB!\021\021[An\033\t\t\031N\003\003\0026\006U'bA\003\002X*\031\021\021\\\n\002\0355Lg.Z2sC\032$hm\034:hK&!\021Q\\Aj\00591uN]4f\t&\024Xm\031;j_:D\003\"!2\002b\006e\0301 \t\005\003G\f)0\004\002\002f*!\021q]Au\003)\021X\r\\1v]\016DWM\035\006\005\003W\fi/A\002g[2TA!a<\002r\006!Qn\0343t\025\t\t\0310A\002da^LA!a>\002f\nA1+\0333f\037:d\0270A\003wC2,X\r\n\002\002~&!\021q B\001\003\031\031E*S#O)*!!1AAs\003\021\031\026\016Z3\t\017\t\035\001\001\"\021\003\n\005I1/\0333fI:{G-\032\013\005\005\027\021\t\002E\002%\005\033I1Aa\004&\005\021qu\016Z3\t\021\0055'Q\001a\001\003\037DqA!\006\001\t\003\0229\"A\bhKR\034UO\035:f]R\034F/\031;f)\t\021I\002\005\004\0022\nm!qD\005\005\005;\t\031LA\004F]Vl7+\032;\021\t\t\005\"\021F\007\003\005GQAA!\n\003(\005Q1\013^1uK\006;\030M]3\013\007\005Uv%\003\003\003,\t\r\"!B*uCR,\007B\002B\030\001\021\005A0\001\005dC:\004&/\0338u\021\031\021\031\004\001C\001y\006Q\021n\035)sS:$\030N\\4\t\017\t]\002\001\"\001\002D\005A\001O]8he\026\0348\017\003\004\003<\001!\t!S\001\016i&lWMU3nC&t\027N\\4\t\017\t}\002\001\"\001\003B\005)!/Z:fiR1!1\tB(\005?\002Ra\023B#\005\023J1Aa\022M\005\025\t%O]1z!\021\t9Ja\023\n\t\t5\023\021\024\002\007\037\nTWm\031;\t\021\tE#Q\ba\001\005'\nqaY8oi\026DH\017\005\003\003V\tmSB\001B,\025\r\021IfJ\001\b[\006\034\007.\0338f\023\021\021iFa\026\003\017\r{g\016^3yi\"A!\021\rB\037\001\004\021\031'\001\003be\036\034\b\003\002B+\005KJAAa\032\003X\tI\021I]4v[\026tGo\035\025\t\005{\021YG!\035\003tA!!Q\013B7\023\021\021yGa\026\003\021\r\013G\016\0342bG.\f1\001Z8dC\t\021)(\0012gk:\034G/[8oQ%\002S&\f\021SKN,Go\035\021uQ\026\0043m\0348gS\036,(/\031;j_:\004sN\032\021uQ\026\004\003O]5oi\026\024\b%\0318eAM$x\016\035\021qe&tG/\0338hA!\032WO\035:f]R\004#n\0342!o&dG\016\t4j]&\034\b.\013\030\t\017\te\004\001\"\001\003|\005A1/\032;MC\n,G\016\006\004\003D\tu$q\020\005\t\005#\0229\b1\001\003T!A!\021\rB<\001\004\021\031\007\013\005\003x\t-$\021\017BBC\t\021))\001\"gk:\034G/[8oQY\fG.^3;gR\024\030N\\4*A5j\003eU3uA\005\004C.\0312fY\0022wN\035\021uQ\026\004#\r\\8dW\002\022W-\0338hAA\024\030N\034;fI:BqA!#\001\t\003\021Y)\001\005hKRd\025MY3m)\031\021\031E!$\003\020\"A!\021\013BD\001\004\021\031\006\003\005\003b\t\035\005\031\001B2Q!\0219Ia\033\003r\tM\025E\001BK\003\0353WO\\2uS>t\007&\013\036tiJLgn\032\021.[\001:U\r\036\021uQ\026\0043-\036:sK:$\b\005\\1cK2\004cm\034:!i\",\007E\0317pG.\004#-Z5oO\002\002(/\0338uK\022t\003b\002BM\001\021\005!1T\001\013g\026$Hk\\8mi&\004HC\002B\"\005;\023y\n\003\005\003R\t]\005\031\001B*\021!\021\tGa&A\002\t\r\004\006\003BL\005W\022\tHa)\"\005\t\025\026\001\0224v]\016$\030n\0348)m\006dW/\032\036tiJLgnZ\025![5\0023+\032;!C\002\"xn\0347uSB\004cm\034:!i\",\007E\0317pG.\004#-Z5oO\002\002(/\0338uK\022t\003b\002BU\001\021\005!1V\001\013O\026$Hk\\8mi&\004HC\002B\"\005[\023y\013\003\005\003R\t\035\006\031\001B*\021!\021\tGa*A\002\t\r\004\006\003BT\005W\022\tHa-\"\005\tU\026!\0234v]\016$\030n\0348)Si\032HO]5oO\002jS\006I$fi\002\"\b.\032\021dkJ\024XM\034;!i>|G\016^5qA\031|'\017\t;iK\002\022Gn\\2lA\t,\027N\\4!aJLg\016^3e]!9!\021\030\001\005\002\tm\026!D:fi2Kw\r\033;MKZ,G\016\006\004\003D\tu&q\030\005\t\005#\0229\f1\001\003T!A!\021\rB\\\001\004\021\031\007\013\005\0038\n-$\021\017BbC\t\021)-A'gk:\034G/[8oQY\fG.^3;]Vl'-\032:*A5j\003eU3uA]D\027\r\036\021mS\036DG\017\t7fm\026d\007\005\0365fAA\024\030N\034;fI\002\022Gn\\2lAMDw.\0367eA!\fg/\032\030\t\017\t%\007\001\"\001\003L\006iq-\032;MS\036DG\017T3wK2$bAa\021\003N\n=\007\002\003B)\005\017\004\rAa\025\t\021\t\005$q\031a\001\005GB\003Ba2\003l\tE$1[\021\003\005+\f\021JZ;oGRLwN\034\025*u9,XNY3sA5j\003eR3uA]D\027n\0315!Y&<\007\016\036\021mKZ,G\016\t;iK\002\002(/\0338uK\022\004#\r\\8dW\002\032\bn\\;mI\002B\027M^3/\021\035\021I\016\001C\001\0057\f!c]3u%\026$7\017^8oK\026k\027\016\036;feR1!1\tBo\005?D\001B!\025\003X\002\007!1\013\005\t\005C\0229\0161\001\003d!B!q\033B6\005c\022\031/\t\002\003f\006\th-\0368di&|g\016\013<bYV,'HY8pY\026\fg\016I8sA9,XNY3sS\001jS\006I*fi\002:\b.\032;iKJ\004C\017[3!aJLg\016^3eA\tdwnY6!g\"|W\017\0343!K6LG\017\t:fIN$xN\\3!o\",g\016I5oA%$8\017I1di&4X\rI:uCR,g\006C\004\003j\002!\tAa;\002#%\034(+\0323ti>tW-R7jiR,'\017\006\004\003D\t5(q\036\005\t\005#\0229\0171\001\003T!A!\021\rBt\001\004\021\031\007\013\005\003h\n-$\021\017BzC\t\021)0\0016gk:\034G/[8oQ%R$m\\8mK\006tG\006\t8v[\n,'\017I\027.A\035+G\017I<iKRDWM\035\021uQ\026\004\003O]5oi\026$\007E\0317pG.\0043\017[8vY\022\004S-\\5uAI,Gm\035;p]\026\004s\017[3oA%t\007%\033;tA\005\034G/\033<fAM$\030\r^3/\021\035\021I\020\001C\001\005w\fQb]3u\005V$Ho\0348N_\022,GC\002B\"\005{\024y\020\003\005\003R\t]\b\031\001B*\021!\021\tGa>A\002\t\r\004\006\003B|\005W\022\tha\001\"\005\r\025\021A\0324v]\016$\030n\0348)m\006dW/\032\036c_>dW-\0318*A5j\003eU3uA]DW\r\0365fe\002\"\b.\032\021qe&tG/\0323!E2|7m\033\021tQ>,H\016\032\021bkR|W.\031;jG\006dG.\037\021sKR,(O\034\021u_\002JGo\035\021pM\032\0043\017^1uK:Bqa!\003\001\t\003\031Y!\001\007jg\n+H\017^8o\033>$W\r\006\004\003D\r51q\002\005\t\005#\0329\0011\001\003T!A!\021MB\004\001\004\021\031\007\013\005\004\b\t-$\021OB\nC\t\031)\"A1gk:\034G/[8oQ%R$m\\8mK\006t\007%L\027!\017\026$\be\0365fi\",'\017\t;iK\002\002(/\0338uK\022\004#\r\\8dW\002\032\bn\\;mI\002\nW\017^8nCRL7-\0317ms\002\022X\r^;s]\002\"x\016I5ug\002zgM\032\021ti\006$XM\f\005\b\0073\001A\021AB\016\0035\031X\r^\"pY2LG-\0312mKR1!1IB\017\007?A\001B!\025\004\030\001\007!1\013\005\t\005C\0329\0021\001\003d!B1q\003B6\005c\032\031#\t\002\004&\005ig-\0368di&|g\016K2pY2LG-Z(gMj\022wn\0347fC:d\003eY8mY&$Wm\0248;E>|G.Z1oS\001jS\006I*fi\002:\b.\032;iKJ\004C\017[3!aJLg\016^3eA\tdwnY6!g\"|W\017\0343!E\026\0043m\0347mS\022\f'\r\\3!_J\004cn\034;/\021\035\031I\003\001C\001\007W\tA\"[:D_2d\027\016Z1cY\026$bAa\021\004.\r=\002\002\003B)\007O\001\rAa\025\t\021\t\0054q\005a\001\005GB\003ba\n\003l\tE41G\021\003\007k\t\021LZ;oGRLwN\034\025*u\t|w\016\\3b]2\002#m\\8mK\006t\007%L\027!\017\026$\be\0365fi\",'\017\t;iK\002\002(/\0338uK\022\004#\r\\8dW\002\032\bn\\;mI\002\022W\rI2pY2LG-\0312mK\002z'\017\t8pi:Bqa!\017\001\t\003\031Y$\001\005bI\022\034\006.\0319f)\031\021\031e!\020\004@!A!\021KB\034\001\004\021\031\006\003\005\003b\r]\002\031\001B2Q!\0319Da\033\003r\r\r\023EAB#\003\005=h-\0368di&|g\016K7j]bSd.^7cKJd\003%\\5o3jrW/\0342fe2\002S.\0338[u9,XNY3sY\001j\027\r\037-;]Vl'-\032:-A5\f\0070\027\036ok6\024WM\035\027![\006D(L\0178v[\n,'\017\f\021uKb$XO]3;gR\024\030N\\4\\Y\001\032H/\031;fu\t|w\016\\3b]v2\027\r\\:f;ncC/\0338uu9,XNY3s;&\002S&\f\021BI\022\034\b%\031\021tQ\006\004X\r\t;pAQDW\r\t9sS:$XM]:!G>tg-[4ve\006$\030n\0348-A=\004H/[8oC2d\027\020I:qK\016Lg-_5oO\002:\b.\032;iKJ\004\023\016\036\021jg\0022wN\035\021uQ\026\004sN\0324!_J\004sN\034\021ti\006$XM\f\005\b\007\023\002A\021AB&\00359W\r^*iCB,7i\\;oiR1!1IB'\007\037B\001B!\025\004H\001\007!1\013\005\t\005C\0329\0051\001\003d!B1q\tB6\005c\032\031&\t\002\004V\005Ye-\0368di&|g\016K\025;]Vl'-\032:![5\002s)\032;!i\",\007E\\;nE\026\024\be\0344!g\"\f\007/Z:!S:\004C\017[3!GV\024(/\0328uA\r|gNZ5hkJ\fG/[8o]!91\021\f\001\005\002\rm\023\001E4fi6\013\007p\0255ba\026\034u.\0368u)\031\021\031e!\030\004`!A!\021KB,\001\004\021\031\006\003\005\003b\r]\003\031\001B2Q!\0319Fa\033\003r\r\r\024EAB3\003y2WO\\2uS>t\007&\013\036ok6\024WM\035\021.[\001:U\r\036\021uQ\026\004S.\031=j[Vl\007%\0317m_^,G\r\t8v[\n,'\017I8gAMD\027\r]3t]!91\021\016\001\005\002\r-\024AB2p[6LG\017\006\004\003D\r54q\016\005\t\005#\0329\0071\001\003T!A!\021MB4\001\004\021\031\007\013\005\004h\t-$\021OB:C\t\031)(\001-gk:\034G/[8oQm\033w.\0368uu9,XNY3s;&R$m\\8mK\006t\007%L\027!\007>lW.\033;!C:$\007EY3hS:\004\003O]5oi&tw\r\t;iK\002\032WO\035:f]R\0043m\0348gS\036,(/\031;j_:t\003bBB=\001\021\00511P\001\007gR\fG/^:\025\r\t\r3QPB@\021!\021\tfa\036A\002\tM\003\002\003B1\007o\002\rAa\031)\021\r]$1\016B9\007\007\013#a!\"\002\003[1WO\\2uS>t\007&\013\036!gR\024\030N\\4-A9,XNY3sA=\024\bEY8pY\026\fg\016I\027.AQCW\rI2veJ,g\016\036\021ti\006$X\rI8gAQDW\r\t9sS:$XM\035\027!A\n,8/_\024!_J\004\003-\0333mK\036b\003EZ8mY><X\r\032\021cs\002\"\b.\032\021qe><'/Z:tA=\024\b%\\8eK2\004c/\0317jI&$\030\020\f\021sKN\004Xm\031;jm\026d\027P\f\005\b\007\023\003A\021IBF\003%\031\027M\\+qI\006$X\rF\001~\021\035\031y\t\001C!\007#\013A\"\0369eCR,WI\034;jif$\022a\026\005\b\007+\003A\021IBL\003Q\021X-\0313Ge>lgJ\021+G_J\034VM\035<feR\031qk!'\t\021\rm51\023a\001\007;\0131A\0342u!\021\031yja)\016\005\r\005&bABN#%!1QUBQ\0059q%\t\026+bO\016{W\016]8v]\022Dqa!+\001\t\003\032Y+A\nxe&$X\rV8O\005R3uN]*feZ,'\017F\002X\007[C\001ba'\004(\002\0071Q\024\005\b\007c\003A\021IBZ\003Q\021X-\0313Ge>lgJ\021+G_J\034E.[3oiR\031qk!.\t\021\rm5q\026a\001\007;C\003ba,\002b\006e\0301 \005\b\007w\003A\021IB_\003M9(/\033;f)>t%\t\026$pe\016c\027.\0328u)\r96q\030\005\t\0077\033I\f1\001\004\036\"911\031\001\005B\r\025\027\001E4fiNK'0Z%om\026tGo\034:z)\005Q\005bBBe\001\021\00531Z\001\023SNLE/Z7WC2LGMR8s'2|G\017F\003~\007\033\034\t\016C\004\004P\016\035\007\031\001&\002\tMdw\016\036\005\t\007'\0349\r1\001\002*\005)1\017^1dW\"91q\033\001\005B\re\027AG4fi\006\0337-Z:tS\ndWm\0257piN4%o\\7TS\022,G\003BBn\007;\004Ba\023B#\025\"9\021QZBk\001\004Q\005bBBq\001\021\00531]\001\017G\006tW\t\037;sC\016$\030\n^3n)\035i8Q]Bt\007SDqaa4\004`\002\007!\n\003\005\004T\016}\007\031AA\025\021\035\tima8A\002)Cqa!<\001\t\003\032y/A\007dC:Len]3si&#X-\034\013\b{\016E81_B{\021\035\031yma;A\002)C\001ba5\004l\002\007\021\021\006\005\b\003\033\034Y\0171\001K\001")
/*     */ public class Printer extends TileEntity implements Environment, Inventory, Rotatable, SidedEnvironment, StateAware, ISidedInventory, DeviceInfo { private final ComponentConnector node;
/*     */   private final int maxAmountMaterial;
/*     */   private int amountMaterial;
/*     */   private final int maxAmountInk;
/*     */   private int amountInk;
/*     */   private PrintData data;
/*     */   private boolean isActive;
/*     */   private int limit;
/*     */   private Option<ItemStack> output;
/*     */   private double totalRequiredEnergy;
/*     */   private double requiredEnergy;
/*     */   private final int slotMaterial;
/*     */   private final int slotInk;
/*     */   private final int slotOutput;
/*     */   private Map<String, String> deviceInfo;
/*     */   private final ForgeDirection[] li$cil$oc$common$tileentity$traits$Rotatable$$pitch2Direction;
/*     */   private final ForgeDirection[] li$cil$oc$common$tileentity$traits$Rotatable$$yaw2Direction;
/*     */   private ForgeDirection li$cil$oc$common$tileentity$traits$Rotatable$$_pitch;
/*     */   private ForgeDirection li$cil$oc$common$tileentity$traits$Rotatable$$_yaw;
/*     */   private final Option<ItemStack>[] li$cil$oc$common$tileentity$traits$Inventory$$inventory;
/*     */   private boolean isChangeScheduled;
/*     */   private boolean moving;
/*     */   private volatile byte bitmap$0;
/*     */   
/*     */   @Method(modid = "BuildCraft|Core")
/*  28 */   public boolean hasWork() { return StateAware.class.hasWork(this); } public ForgeDirection[] li$cil$oc$common$tileentity$traits$Rotatable$$pitch2Direction() { return this.li$cil$oc$common$tileentity$traits$Rotatable$$pitch2Direction; } public ForgeDirection[] li$cil$oc$common$tileentity$traits$Rotatable$$yaw2Direction() { return this.li$cil$oc$common$tileentity$traits$Rotatable$$yaw2Direction; } public ForgeDirection li$cil$oc$common$tileentity$traits$Rotatable$$_pitch() { return this.li$cil$oc$common$tileentity$traits$Rotatable$$_pitch; } public void li$cil$oc$common$tileentity$traits$Rotatable$$_pitch_$eq(ForgeDirection x$1) { this.li$cil$oc$common$tileentity$traits$Rotatable$$_pitch = x$1; } public ForgeDirection li$cil$oc$common$tileentity$traits$Rotatable$$_yaw() { return this.li$cil$oc$common$tileentity$traits$Rotatable$$_yaw; } public void li$cil$oc$common$tileentity$traits$Rotatable$$_yaw_$eq(ForgeDirection x$1) { this.li$cil$oc$common$tileentity$traits$Rotatable$$_yaw = x$1; } public void li$cil$oc$common$tileentity$traits$Rotatable$_setter_$li$cil$oc$common$tileentity$traits$Rotatable$$pitch2Direction_$eq(ForgeDirection[] x$1) { this.li$cil$oc$common$tileentity$traits$Rotatable$$pitch2Direction = x$1; } public void li$cil$oc$common$tileentity$traits$Rotatable$_setter_$li$cil$oc$common$tileentity$traits$Rotatable$$yaw2Direction_$eq(ForgeDirection[] x$1) { this.li$cil$oc$common$tileentity$traits$Rotatable$$yaw2Direction = x$1; } public ForgeDirection pitch() { return Rotatable.class.pitch(this); } public void pitch_$eq(ForgeDirection value) { Rotatable.class.pitch_$eq(this, value); } public ForgeDirection yaw() { return Rotatable.class.yaw(this); } public void yaw_$eq(ForgeDirection value) { Rotatable.class.yaw_$eq(this, value); } public boolean setFromEntityPitchAndYaw(Entity entity) { return Rotatable.class.setFromEntityPitchAndYaw(this, entity); } public boolean setFromFacing(ForgeDirection value) { return Rotatable.class.setFromFacing(this, value); } public boolean invertRotation() { return Rotatable.class.invertRotation(this); } public ForgeDirection facing() { return Rotatable.class.facing(this); } public boolean rotate(ForgeDirection axis) { return Rotatable.class.rotate(this, axis); } public ForgeDirection toLocal(ForgeDirection value) { return Rotatable.class.toLocal(this, value); } public ForgeDirection toGlobal(ForgeDirection value) { return Rotatable.class.toGlobal(this, value); } public ForgeDirection[] validFacings() { return Rotatable.class.validFacings(this); } public void onRotationChanged() { Rotatable.class.onRotationChanged(this); } private Option[] li$cil$oc$common$tileentity$traits$Inventory$$inventory$lzycompute() { synchronized (this) { if ((byte)(this.bitmap$0 & 0x2) == 0) { this.li$cil$oc$common$tileentity$traits$Inventory$$inventory = (Option<ItemStack>[])Inventory.class.li$cil$oc$common$tileentity$traits$Inventory$$inventory(this); this.bitmap$0 = (byte)(this.bitmap$0 | 0x2); }  return (Option[])this.li$cil$oc$common$tileentity$traits$Inventory$$inventory; }  } public Option<ItemStack>[] li$cil$oc$common$tileentity$traits$Inventory$$inventory() { return ((byte)(this.bitmap$0 & 0x2) == 0) ? (Option<ItemStack>[])li$cil$oc$common$tileentity$traits$Inventory$$inventory$lzycompute() : this.li$cil$oc$common$tileentity$traits$Inventory$$inventory; } public Option<ItemStack>[] items() { return (Option<ItemStack>[])Inventory.class.items(this); } public boolean func_70300_a(EntityPlayer player) { return Inventory.class.isUseableByPlayer(this, player); } public boolean dropSlot(int slot, int count, Option direction) { return Inventory.class.dropSlot(this, slot, count, direction); } public void dropAllSlots() { Inventory.class.dropAllSlots(this); } public EntityItem spawnStackInWorld(ItemStack stack, Option direction) { return Inventory.class.spawnStackInWorld(this, stack, direction); } public int dropSlot$default$2() { return Inventory.class.dropSlot$default$2(this); } public Option<ForgeDirection> dropSlot$default$3() { return Inventory.class.dropSlot$default$3(this); } public Option<ForgeDirection> spawnStackInWorld$default$2() { return Inventory.class.spawnStackInWorld$default$2(this); } public void updateItems(int slot, ItemStack stack) { Inventory.class.updateItems((Inventory)this, slot, stack); } public ItemStack func_70301_a(int slot) { return Inventory.class.getStackInSlot((Inventory)this, slot); } public void func_70299_a(int slot, ItemStack stack) { Inventory.class.setInventorySlotContents((Inventory)this, slot, stack); } public String func_145825_b() { return Inventory.class.getInventoryName((Inventory)this); } public String inventoryName() { return Inventory.class.inventoryName((Inventory)this); } public void load(NBTTagCompound nbt) { Inventory.class.load((Inventory)this, nbt); } public void save(NBTTagCompound nbt) { Inventory.class.save((Inventory)this, nbt); } public void onItemAdded(int slot, ItemStack stack) { Inventory.class.onItemAdded((Inventory)this, slot, stack); } public void onItemRemoved(int slot, ItemStack stack) { Inventory.class.onItemRemoved((Inventory)this, slot, stack); } public boolean func_145818_k_() { return SimpleInventory.class.hasCustomInventoryName((SimpleInventory)this); } public int func_70297_j_() { return SimpleInventory.class.getInventoryStackLimit((SimpleInventory)this); } public int getInventoryStackRequired() { return SimpleInventory.class.getInventoryStackRequired((SimpleInventory)this); } public void func_70295_k_() { SimpleInventory.class.openInventory((SimpleInventory)this); } public void func_70305_f() { SimpleInventory.class.closeInventory((SimpleInventory)this); } public ItemStack func_70298_a(int slot, int amount) { return SimpleInventory.class.decrStackSize((SimpleInventory)this, slot, amount); } public ItemStack func_70304_b(int slot) { return SimpleInventory.class.getStackInSlotOnClosing((SimpleInventory)this, slot); } public boolean isChangeScheduled() { return this.isChangeScheduled; } public void isChangeScheduled_$eq(boolean x$1) { this.isChangeScheduled = x$1; } public boolean moving() { return this.moving; } public void moving_$eq(boolean x$1) { this.moving = x$1; } public double xPosition() { return Environment.class.xPosition(this); } public double yPosition() { return Environment.class.yPosition(this); } public double zPosition() { return Environment.class.zPosition(this); } public void markChanged() { Environment.class.markChanged(this); } public boolean isConnected() { return Environment.class.isConnected(this); } public void initialize() { Environment.class.initialize(this); } public void dispose() { Environment.class.dispose(this); } public void onMessage(Message message) { Environment.class.onMessage(this, message); } public void onConnect(Node node) { Environment.class.onConnect(this, node); } public void onDisconnect(Node node) { Environment.class.onDisconnect(this, node); } @Method(modid = "appliedenergistics2") public boolean prepareToMove() { return Environment.class.prepareToMove(this); } @Method(modid = "appliedenergistics2") public void doneMoving() { Environment.class.doneMoving(this); } public Object[] result(Seq args) { return Environment.class.result(this, args); } public World world() { return TileEntity.class.world((TileEntity)this); } public int x() { return TileEntity.class.x((TileEntity)this); } public int y() { return TileEntity.class.y((TileEntity)this); } public int z() { return TileEntity.class.z((TileEntity)this); } public BlockPosition position() { return TileEntity.class.position((TileEntity)this); } public Block block() { return TileEntity.class.block((TileEntity)this); } public boolean isClient() { return TileEntity.class.isClient((TileEntity)this); } public boolean isServer() { return TileEntity.class.isServer((TileEntity)this); } public void func_145829_t() { TileEntity.class.validate((TileEntity)this); } public void func_145843_s() { TileEntity.class.invalidate((TileEntity)this); } public void onChunkUnload() { TileEntity.class.onChunkUnload((TileEntity)this); } public void func_145839_a(NBTTagCompound nbt) { TileEntity.class.readFromNBT((TileEntity)this, nbt); } public void func_145841_b(NBTTagCompound nbt) { TileEntity.class.writeToNBT((TileEntity)this, nbt); } public Packet func_145844_m() { return TileEntity.class.getDescriptionPacket((TileEntity)this); } public void onDataPacket(NetworkManager manager, S35PacketUpdateTileEntity packet) { TileEntity.class.onDataPacket((TileEntity)this, manager, packet); } public Printer() { TileEntity.class.$init$((TileEntity)this); Environment.class.$init$(this); SimpleInventory.class.$init$((SimpleInventory)this); Inventory.class.$init$((Inventory)this); Inventory.class.$init$(this); RotationAware.class.$init$((RotationAware)this); Rotatable.class.$init$(this); StateAware.class.$init$(this);
/*  29 */     this.node = (ComponentConnector)Network.newNode((Environment)this, Visibility.Network)
/*  30 */       .withComponent("printer3d")
/*  31 */       .withConnector(Settings$.MODULE$.get().bufferConverter())
/*  32 */       .create();
/*     */     
/*  34 */     this.maxAmountMaterial = 256000;
/*  35 */     this.amountMaterial = 0;
/*  36 */     this.maxAmountInk = 100000;
/*  37 */     this.amountInk = 0;
/*     */     
/*  39 */     this.data = new PrintData();
/*  40 */     this.isActive = false;
/*  41 */     this.limit = 0;
/*  42 */     this.output = (Option<ItemStack>)None$.MODULE$;
/*  43 */     this.totalRequiredEnergy = 0.0D;
/*  44 */     this.requiredEnergy = 0.0D;
/*     */     
/*  46 */     this.slotMaterial = 0;
/*  47 */     this.slotInk = 1;
/*  48 */     this.slotOutput = 2; } public ComponentConnector node() { return this.node; } public int maxAmountMaterial() { return this.maxAmountMaterial; } public int amountMaterial() { return this.amountMaterial; } public void amountMaterial_$eq(int x$1) { this.amountMaterial = x$1; } public int maxAmountInk() { return this.maxAmountInk; } public int amountInk() { return this.amountInk; } public void amountInk_$eq(int x$1) { this.amountInk = x$1; } public PrintData data() { return this.data; } public void data_$eq(PrintData x$1) { this.data = x$1; } public boolean isActive() { return this.isActive; } public int slotOutput() { return this.slotOutput; }
/*     */   public void isActive_$eq(boolean x$1) { this.isActive = x$1; }
/*  50 */   public int limit() { return this.limit; } public void limit_$eq(int x$1) { this.limit = x$1; } public Option<ItemStack> output() { return this.output; } public void output_$eq(Option<ItemStack> x$1) { this.output = x$1; } public double totalRequiredEnergy() { return this.totalRequiredEnergy; } public void totalRequiredEnergy_$eq(double x$1) { this.totalRequiredEnergy = x$1; } public double requiredEnergy() { return this.requiredEnergy; } public void requiredEnergy_$eq(double x$1) { this.requiredEnergy = x$1; } public int slotMaterial() { return this.slotMaterial; } public int slotInk() { return this.slotInk; } private Map deviceInfo$lzycompute() { synchronized (this) { if ((byte)(this.bitmap$0 & 0x1) == 0) { (new Tuple2[4])[0] = Predef$ArrowAssoc$.MODULE$
/*  51 */           .$minus$greater$extension(Predef$.MODULE$.ArrowAssoc("class"), "printer");
/*  52 */         (new Tuple2[4])[1] = Predef$ArrowAssoc$.MODULE$.$minus$greater$extension(Predef$.MODULE$.ArrowAssoc("description"), "3D Printer");
/*  53 */         (new Tuple2[4])[2] = Predef$ArrowAssoc$.MODULE$.$minus$greater$extension(Predef$.MODULE$.ArrowAssoc("vendor"), "MightyPirates GmbH & Co. KG");
/*  54 */         (new Tuple2[4])[3] = Predef$ArrowAssoc$.MODULE$.$minus$greater$extension(Predef$.MODULE$.ArrowAssoc("product"), "Omni-Materializer T6.1"); this.deviceInfo = (Map<String, String>)Predef$.MODULE$.Map().apply((Seq)Predef$.MODULE$.wrapRefArray((Object[])new Tuple2[4])); this.bitmap$0 = (byte)(this.bitmap$0 | 0x1); }
/*     */        return this.deviceInfo; }
/*     */      } private final Map<String, String> deviceInfo() { return ((byte)(this.bitmap$0 & 0x1) == 0) ? deviceInfo$lzycompute() : this.deviceInfo; }
/*  57 */   public Map<String, String> getDeviceInfo() { return WrapAsJava$.MODULE$.mapAsJavaMap((Map)deviceInfo()); }
/*     */ 
/*     */   
/*     */   @SideOnly(Side.CLIENT)
/*     */   public boolean canConnect(ForgeDirection side) {
/*  62 */     ForgeDirection forgeDirection = ForgeDirection.UP; if (side == null) { if (forgeDirection != null); } else if (side.equals(forgeDirection))
/*     */     {  }
/*  64 */      } public Node sidedNode(ForgeDirection side) { ForgeDirection forgeDirection = ForgeDirection.UP; if (side == null) { if (forgeDirection != null); } else if (side.equals(forgeDirection))
/*     */     {  }
/*     */      } public EnumSet<StateAware.State> getCurrentState() {
/*  67 */     return isPrinting() ? EnumSet.<StateAware.State>of(StateAware.State.IsWorking) : (
/*  68 */       canPrint() ? EnumSet.<StateAware.State>of(StateAware.State.CanWork) : 
/*  69 */       EnumSet.<StateAware.State>noneOf(StateAware.State.class));
/*     */   }
/*     */ 
/*     */   
/*     */   public boolean canPrint() {
/*  74 */     return (data().stateOff().nonEmpty() && data().stateOff().size() <= Settings$.MODULE$.get().maxPrintComplexity() && data().stateOn().size() <= Settings$.MODULE$.get().maxPrintComplexity());
/*     */   } public boolean isPrinting() {
/*  76 */     return output().isDefined();
/*     */   } public double progress() {
/*  78 */     return (true - requiredEnergy() / totalRequiredEnergy()) * 100;
/*     */   } public int timeRemaining() {
/*  80 */     return (int)(requiredEnergy() / Settings$.MODULE$.get().assemblerTickAmount() / 20);
/*     */   }
/*     */ 
/*     */   
/*     */   @Callback(doc = "function() -- Resets the configuration of the printer and stop printing (current job will finish).")
/*     */   public Object[] reset(Context context, Arguments args) {
/*  86 */     data_$eq(new PrintData());
/*  87 */     isActive_$eq(false);
/*  88 */     return null;
/*     */   }
/*     */   
/*     */   @Callback(doc = "function(value:string) -- Set a label for the block being printed.")
/*     */   public Object[] setLabel(Context context, Arguments args) {
/*  93 */     data().label_$eq(Option$.MODULE$.apply(args.optString(0, null)).map((Function1)new Printer$$anonfun$setLabel$2(this)));
/*  94 */     if (BoxesRunTime.unboxToBoolean(data().label().fold((Function0)new Printer$$anonfun$setLabel$1(this), (Function1)new Printer$$anonfun$setLabel$3(this)))) data().label_$eq((Option)None$.MODULE$); 
/*  95 */     isActive_$eq(false);
/*  96 */     return null;
/*     */   } public final class Printer$$anonfun$setLabel$2 extends AbstractFunction1<String, String> implements Serializable {
/*     */     public static final long serialVersionUID = 0L; public final String apply(String x$1) { return (String)(new StringOps(Predef$.MODULE$.augmentString(x$1))).take(24); } public Printer$$anonfun$setLabel$2(Printer $outer) {} } public final class Printer$$anonfun$setLabel$1 extends AbstractFunction0.mcZ.sp implements Serializable {
/*     */     public static final long serialVersionUID = 0L; public final boolean apply() { return apply$mcZ$sp(); } public boolean apply$mcZ$sp() { return false; } public Printer$$anonfun$setLabel$1(Printer $outer) {} } public final class Printer$$anonfun$setLabel$3 extends AbstractFunction1<String, Object> implements Serializable {
/*     */     public static final long serialVersionUID = 0L; public final boolean apply(String x$2) { return x$2.isEmpty(); } public Printer$$anonfun$setLabel$3(Printer $outer) {} }
/* 101 */   @Callback(doc = "function():string -- Get the current label for the block being printed.") public Object[] getLabel(Context context, Arguments args) { return result((Seq<Object>)Predef$.MODULE$.genericWrapArray(new Object[] { data().label().orNull(Predef$.MODULE$.$conforms()) })); }
/*     */ 
/*     */   
/*     */   @Callback(doc = "function(value:string) -- Set a tooltip for the block being printed.")
/*     */   public Object[] setTooltip(Context context, Arguments args) {
/* 106 */     data().tooltip_$eq(Option$.MODULE$.apply(args.optString(0, null)).map((Function1)new Printer$$anonfun$setTooltip$2(this)));
/* 107 */     if (BoxesRunTime.unboxToBoolean(data().tooltip().fold((Function0)new Printer$$anonfun$setTooltip$1(this), (Function1)new Printer$$anonfun$setTooltip$3(this)))) data().tooltip_$eq((Option)None$.MODULE$); 
/* 108 */     isActive_$eq(false);
/* 109 */     return null;
/*     */   } public final class Printer$$anonfun$setTooltip$2 extends AbstractFunction1<String, String> implements Serializable {
/*     */     public static final long serialVersionUID = 0L; public final String apply(String x$3) { return (String)(new StringOps(Predef$.MODULE$.augmentString(x$3))).take(128); } public Printer$$anonfun$setTooltip$2(Printer $outer) {} } public final class Printer$$anonfun$setTooltip$1 extends AbstractFunction0.mcZ.sp implements Serializable {
/*     */     public static final long serialVersionUID = 0L; public final boolean apply() { return apply$mcZ$sp(); } public boolean apply$mcZ$sp() { return false; } public Printer$$anonfun$setTooltip$1(Printer $outer) {} } public final class Printer$$anonfun$setTooltip$3 extends AbstractFunction1<String, Object> implements Serializable {
/*     */     public static final long serialVersionUID = 0L; public final boolean apply(String x$4) { return x$4.isEmpty(); } public Printer$$anonfun$setTooltip$3(Printer $outer) {} }
/* 114 */   @Callback(doc = "function():string -- Get the current tooltip for the block being printed.") public Object[] getTooltip(Context context, Arguments args) { return result((Seq<Object>)Predef$.MODULE$.genericWrapArray(new Object[] { data().tooltip().orNull(Predef$.MODULE$.$conforms()) })); }
/*     */ 
/*     */   
/*     */   @Callback(doc = "function(value:number) -- Set what light level the printed block should have.")
/*     */   public Object[] setLightLevel(Context context, Arguments args) {
/* 119 */     data().lightLevel_$eq(RichInt$.MODULE$.min$extension(Predef$.MODULE$.intWrapper(RichInt$.MODULE$.max$extension(Predef$.MODULE$.intWrapper(args.checkInteger(0)), 0)), Settings$.MODULE$.get().maxPrintLightLevel()));
/* 120 */     isActive_$eq(false);
/* 121 */     return null;
/*     */   }
/*     */   
/*     */   @Callback(doc = "function():number -- Get which light level the printed block should have.")
/*     */   public Object[] getLightLevel(Context context, Arguments args) {
/* 126 */     return result((Seq<Object>)Predef$.MODULE$.genericWrapArray(new Object[] { BoxesRunTime.boxToInteger(data().lightLevel()) }));
/*     */   }
/*     */   
/*     */   @Callback(doc = "function(value:boolean or number) -- Set whether the printed block should emit redstone when in its active state.")
/*     */   public Object[] setRedstoneEmitter(Context context, Arguments args) {
/* 131 */     if (args.isBoolean(0)) { data().redstoneLevel_$eq(args.checkBoolean(0) ? 15 : 0); }
/* 132 */     else { data().redstoneLevel_$eq(RichInt$.MODULE$.min$extension(Predef$.MODULE$.intWrapper(RichInt$.MODULE$.max$extension(Predef$.MODULE$.intWrapper(args.checkInteger(0)), 0)), 15)); }
/* 133 */      isActive_$eq(false);
/* 134 */     return null;
/*     */   }
/*     */   
/*     */   @Callback(doc = "function():boolean, number -- Get whether the printed block should emit redstone when in its active state.")
/*     */   public Object[] isRedstoneEmitter(Context context, Arguments args) {
/* 139 */     return result((Seq<Object>)Predef$.MODULE$.genericWrapArray(new Object[] { BoxesRunTime.boxToBoolean(data().emitRedstone()), BoxesRunTime.boxToInteger(data().redstoneLevel()) }));
/*     */   }
/*     */   
/*     */   @Callback(doc = "function(value:boolean) -- Set whether the printed block should automatically return to its off state.")
/*     */   public Object[] setButtonMode(Context context, Arguments args) {
/* 144 */     data().isButtonMode_$eq(args.checkBoolean(0));
/* 145 */     isActive_$eq(false);
/* 146 */     return null;
/*     */   }
/*     */   
/*     */   @Callback(doc = "function():boolean -- Get whether the printed block should automatically return to its off state.")
/*     */   public Object[] isButtonMode(Context context, Arguments args) {
/* 151 */     return result((Seq<Object>)Predef$.MODULE$.genericWrapArray(new Object[] { BoxesRunTime.boxToBoolean(data().isButtonMode()) }));
/*     */   }
/*     */   
/*     */   @Callback(doc = "function(collideOff:boolean, collideOn:boolean) -- Set whether the printed block should be collidable or not.")
/*     */   public Object[] setCollidable(Context context, Arguments args) {
/* 156 */     Tuple2.mcZZ.sp sp = new Tuple2.mcZZ.sp(args.checkBoolean(0), args.checkBoolean(1)); if (sp != null) { boolean collideOff = sp._1$mcZ$sp(), collideOn = sp._2$mcZ$sp(); Tuple2.mcZZ.sp sp2 = new Tuple2.mcZZ.sp(collideOff, collideOn), sp1 = sp2; boolean bool1 = sp1._1$mcZ$sp(), bool2 = sp1._2$mcZ$sp();
/* 157 */       data().noclipOff_$eq(!bool1);
/* 158 */       data().noclipOn_$eq(!bool2);
/* 159 */       return null; }
/*     */     
/*     */     throw new MatchError(sp);
/*     */   } @Callback(doc = "function():boolean, boolean -- Get whether the printed block should be collidable or not.")
/*     */   public Object[] isCollidable(Context context, Arguments args) {
/* 164 */     return result((Seq<Object>)Predef$.MODULE$.genericWrapArray(new Object[] { BoxesRunTime.boxToBoolean(!data().noclipOff()), BoxesRunTime.boxToBoolean(!data().noclipOn()) }));
/*     */   }
/*     */   
/*     */   @Callback(doc = "function(minX:number, minY:number, minZ:number, maxX:number, maxY:number, maxZ:number, texture:string[, state:boolean=false][,tint:number]) -- Adds a shape to the printers configuration, optionally specifying whether it is for the off or on state.")
/*     */   public Object[] addShape(Context context, Arguments args) {
/* 169 */     if (data().stateOff().size() > Settings$.MODULE$.get().maxPrintComplexity() || data().stateOn().size() > Settings$.MODULE$.get().maxPrintComplexity()) {
/* 170 */       return result((Seq<Object>)Predef$.MODULE$.genericWrapArray(new Object[] { Unit$.MODULE$, "model too complex" }));
/*     */     }
/* 172 */     float minX = RichInt$.MODULE$.min$extension(Predef$.MODULE$.intWrapper(RichInt$.MODULE$.max$extension(Predef$.MODULE$.intWrapper(args.checkInteger(0)), 0)), 16) / 16.0F;
/* 173 */     float minY = RichInt$.MODULE$.min$extension(Predef$.MODULE$.intWrapper(RichInt$.MODULE$.max$extension(Predef$.MODULE$.intWrapper(args.checkInteger(1)), 0)), 16) / 16.0F;
/* 174 */     float minZ = (16 - RichInt$.MODULE$.min$extension(Predef$.MODULE$.intWrapper(RichInt$.MODULE$.max$extension(Predef$.MODULE$.intWrapper(args.checkInteger(2)), 0)), 16)) / 16.0F;
/* 175 */     float maxX = RichInt$.MODULE$.min$extension(Predef$.MODULE$.intWrapper(RichInt$.MODULE$.max$extension(Predef$.MODULE$.intWrapper(args.checkInteger(3)), 0)), 16) / 16.0F;
/* 176 */     float maxY = RichInt$.MODULE$.min$extension(Predef$.MODULE$.intWrapper(RichInt$.MODULE$.max$extension(Predef$.MODULE$.intWrapper(args.checkInteger(4)), 0)), 16) / 16.0F;
/* 177 */     float maxZ = (16 - RichInt$.MODULE$.min$extension(Predef$.MODULE$.intWrapper(RichInt$.MODULE$.max$extension(Predef$.MODULE$.intWrapper(args.checkInteger(5)), 0)), 16)) / 16.0F;
/* 178 */     String texture = (String)(new StringOps(Predef$.MODULE$.augmentString(args.checkString(6)))).take(64);
/* 179 */     boolean state = args.isBoolean(7) ? args.checkBoolean(7) : false;
/* 180 */     Option tint = args.isInteger(7) ? Option$.MODULE$.apply(BoxesRunTime.boxToInteger(args.checkInteger(7))) : (args.isInteger(8) ? Option$.MODULE$.apply(BoxesRunTime.boxToInteger(args.checkInteger(8))) : (Option)None$.MODULE$);
/*     */     
/* 182 */     if (minX == maxX) throw new IllegalArgumentException("empty block"); 
/* 183 */     if (minY == maxY) throw new IllegalArgumentException("empty block"); 
/* 184 */     if (minZ == maxZ) throw new IllegalArgumentException("empty block");
/*     */     
/* 186 */     Set list = state ? data().stateOn() : data().stateOff();
/* 187 */     list.$plus$eq(new PrintData.Shape(AxisAlignedBB.func_72330_a(
/* 188 */             package$.MODULE$.min(minX, maxX), 
/* 189 */             package$.MODULE$.min(minY, maxY), 
/* 190 */             package$.MODULE$.min(minZ, maxZ), 
/* 191 */             package$.MODULE$.max(maxX, minX), 
/* 192 */             package$.MODULE$.max(maxY, minY), 
/* 193 */             package$.MODULE$.max(maxZ, minZ)), 
/* 194 */           texture, tint));
/* 195 */     isActive_$eq(false);
/*     */     
/* 197 */     world().func_147471_g(x(), y(), z());
/*     */     
/* 199 */     return result((Seq<Object>)Predef$.MODULE$.genericWrapArray(new Object[] { BoxesRunTime.boxToBoolean(true) }));
/*     */   }
/*     */   @Callback(doc = "function():number -- Get the number of shapes in the current configuration.")
/*     */   public Object[] getShapeCount(Context context, Arguments args) {
/* 203 */     return result((Seq<Object>)Predef$.MODULE$.genericWrapArray(new Object[] { BoxesRunTime.boxToInteger(data().stateOff().size()), BoxesRunTime.boxToInteger(data().stateOn().size()) }));
/*     */   } @Callback(doc = "function():number -- Get the maximum allowed number of shapes.")
/*     */   public Object[] getMaxShapeCount(Context context, Arguments args) {
/* 206 */     return result((Seq<Object>)Predef$.MODULE$.genericWrapArray(new Object[] { BoxesRunTime.boxToInteger(Settings$.MODULE$.get().maxPrintComplexity()) }));
/*     */   }
/*     */   @Callback(doc = "function([count:number]):boolean -- Commit and begin printing the current configuration.")
/*     */   public Object[] commit(Context context, Arguments args) {
/* 210 */     if (canPrint()) {
/*     */ 
/*     */       
/* 213 */       limit_$eq((int)RichDouble$.MODULE$.min$extension(Predef$.MODULE$.doubleWrapper(RichDouble$.MODULE$.max$extension(Predef$.MODULE$.doubleWrapper(args.optDouble(0, 1.0D)), 0.0D)), 2.147483647E9D));
/* 214 */       isActive_$eq((limit() > 0));
/* 215 */       return result((Seq<Object>)Predef$.MODULE$.genericWrapArray(new Object[] { BoxesRunTime.boxToBoolean(true) }));
/*     */     } 
/*     */     return result((Seq<Object>)Predef$.MODULE$.genericWrapArray(new Object[] { Unit$.MODULE$, "model invalid" }));
/*     */   } @Callback(doc = "function(): string, number or boolean -- The current state of the printer, `busy' or `idle', followed by the progress or model validity, respectively.")
/*     */   public Object[] status(Context context, Arguments args) {
/* 220 */     return isPrinting() ? result((Seq<Object>)Predef$.MODULE$.genericWrapArray(new Object[] { "busy", BoxesRunTime.boxToDouble(progress())
/* 221 */           })) : (canPrint() ? result((Seq<Object>)Predef$.MODULE$.genericWrapArray(new Object[] { "idle", BoxesRunTime.boxToBoolean(true)
/* 222 */           })) : result((Seq<Object>)Predef$.MODULE$.genericWrapArray(new Object[] { "idle", BoxesRunTime.boxToBoolean(false) })));
/*     */   }
/*     */ 
/*     */   
/*     */   public boolean canUpdate() {
/* 227 */     return isServer();
/*     */   }
/*     */   public void func_145845_h() {
/*     */     // Byte code:
/*     */     //   0: aload_0
/*     */     //   1: invokestatic updateEntity : (Lli/cil/oc/common/tileentity/traits/Environment;)V
/*     */     //   4: aload_0
/*     */     //   5: invokevirtual isActive : ()Z
/*     */     //   8: ifeq -> 219
/*     */     //   11: aload_0
/*     */     //   12: invokevirtual output : ()Lscala/Option;
/*     */     //   15: invokevirtual isEmpty : ()Z
/*     */     //   18: ifeq -> 219
/*     */     //   21: aload_0
/*     */     //   22: invokespecial canMergeOutput$1 : ()Z
/*     */     //   25: ifeq -> 219
/*     */     //   28: getstatic li/cil/oc/common/item/data/PrintData$.MODULE$ : Lli/cil/oc/common/item/data/PrintData$;
/*     */     //   31: aload_0
/*     */     //   32: invokevirtual data : ()Lli/cil/oc/common/item/data/PrintData;
/*     */     //   35: invokevirtual computeCosts : (Lli/cil/oc/common/item/data/PrintData;)Lscala/Option;
/*     */     //   38: astore_1
/*     */     //   39: aload_1
/*     */     //   40: instanceof scala/Some
/*     */     //   43: ifeq -> 198
/*     */     //   46: aload_1
/*     */     //   47: checkcast scala/Some
/*     */     //   50: astore_2
/*     */     //   51: aload_2
/*     */     //   52: invokevirtual x : ()Ljava/lang/Object;
/*     */     //   55: checkcast scala/Tuple2
/*     */     //   58: astore_3
/*     */     //   59: aload_3
/*     */     //   60: ifnull -> 198
/*     */     //   63: aload_3
/*     */     //   64: invokevirtual _1$mcI$sp : ()I
/*     */     //   67: istore #4
/*     */     //   69: aload_3
/*     */     //   70: invokevirtual _2$mcI$sp : ()I
/*     */     //   73: istore #5
/*     */     //   75: aload_0
/*     */     //   76: getstatic li/cil/oc/Settings$.MODULE$ : Lli/cil/oc/Settings$;
/*     */     //   79: invokevirtual get : ()Lli/cil/oc/Settings;
/*     */     //   82: invokevirtual printCost : ()D
/*     */     //   85: invokevirtual totalRequiredEnergy_$eq : (D)V
/*     */     //   88: aload_0
/*     */     //   89: aload_0
/*     */     //   90: invokevirtual totalRequiredEnergy : ()D
/*     */     //   93: invokevirtual requiredEnergy_$eq : (D)V
/*     */     //   96: aload_0
/*     */     //   97: invokevirtual amountMaterial : ()I
/*     */     //   100: iload #4
/*     */     //   102: if_icmplt -> 190
/*     */     //   105: aload_0
/*     */     //   106: invokevirtual amountInk : ()I
/*     */     //   109: iload #5
/*     */     //   111: if_icmplt -> 190
/*     */     //   114: aload_0
/*     */     //   115: aload_0
/*     */     //   116: invokevirtual amountMaterial : ()I
/*     */     //   119: iload #4
/*     */     //   121: isub
/*     */     //   122: invokevirtual amountMaterial_$eq : (I)V
/*     */     //   125: aload_0
/*     */     //   126: aload_0
/*     */     //   127: invokevirtual amountInk : ()I
/*     */     //   130: iload #5
/*     */     //   132: isub
/*     */     //   133: invokevirtual amountInk_$eq : (I)V
/*     */     //   136: aload_0
/*     */     //   137: aload_0
/*     */     //   138: invokevirtual limit : ()I
/*     */     //   141: iconst_1
/*     */     //   142: isub
/*     */     //   143: invokevirtual limit_$eq : (I)V
/*     */     //   146: aload_0
/*     */     //   147: getstatic scala/Option$.MODULE$ : Lscala/Option$;
/*     */     //   150: aload_0
/*     */     //   151: invokevirtual data : ()Lli/cil/oc/common/item/data/PrintData;
/*     */     //   154: invokevirtual createItemStack : ()Lnet/minecraft/item/ItemStack;
/*     */     //   157: invokevirtual apply : (Ljava/lang/Object;)Lscala/Option;
/*     */     //   160: invokevirtual output_$eq : (Lscala/Option;)V
/*     */     //   163: aload_0
/*     */     //   164: invokevirtual limit : ()I
/*     */     //   167: iconst_1
/*     */     //   168: if_icmpge -> 176
/*     */     //   171: aload_0
/*     */     //   172: iconst_0
/*     */     //   173: invokevirtual isActive_$eq : (Z)V
/*     */     //   176: getstatic li/cil/oc/server/PacketSender$.MODULE$ : Lli/cil/oc/server/PacketSender$;
/*     */     //   179: aload_0
/*     */     //   180: iconst_1
/*     */     //   181: invokevirtual sendPrinting : (Lli/cil/oc/common/tileentity/Printer;Z)V
/*     */     //   184: getstatic scala/runtime/BoxedUnit.UNIT : Lscala/runtime/BoxedUnit;
/*     */     //   187: goto -> 193
/*     */     //   190: getstatic scala/runtime/BoxedUnit.UNIT : Lscala/runtime/BoxedUnit;
/*     */     //   193: astore #6
/*     */     //   195: goto -> 219
/*     */     //   198: aload_0
/*     */     //   199: iconst_0
/*     */     //   200: invokevirtual isActive_$eq : (Z)V
/*     */     //   203: aload_0
/*     */     //   204: new li/cil/oc/common/item/data/PrintData
/*     */     //   207: dup
/*     */     //   208: invokespecial <init> : ()V
/*     */     //   211: invokevirtual data_$eq : (Lli/cil/oc/common/item/data/PrintData;)V
/*     */     //   214: getstatic scala/runtime/BoxedUnit.UNIT : Lscala/runtime/BoxedUnit;
/*     */     //   217: astore #6
/*     */     //   219: aload_0
/*     */     //   220: invokevirtual output : ()Lscala/Option;
/*     */     //   223: invokevirtual isDefined : ()Z
/*     */     //   226: ifeq -> 430
/*     */     //   229: getstatic scala/math/package$.MODULE$ : Lscala/math/package$;
/*     */     //   232: dconst_1
/*     */     //   233: getstatic scala/math/package$.MODULE$ : Lscala/math/package$;
/*     */     //   236: aload_0
/*     */     //   237: invokevirtual requiredEnergy : ()D
/*     */     //   240: getstatic li/cil/oc/Settings$.MODULE$ : Lli/cil/oc/Settings$;
/*     */     //   243: invokevirtual get : ()Lli/cil/oc/Settings;
/*     */     //   246: invokevirtual printerTickAmount : ()D
/*     */     //   249: invokevirtual min : (DD)D
/*     */     //   252: invokevirtual max : (DD)D
/*     */     //   255: dstore #7
/*     */     //   257: dload #7
/*     */     //   259: getstatic li/cil/oc/Settings$.MODULE$ : Lli/cil/oc/Settings$;
/*     */     //   262: invokevirtual get : ()Lli/cil/oc/Settings;
/*     */     //   265: invokevirtual ignorePower : ()Z
/*     */     //   268: ifeq -> 275
/*     */     //   271: dconst_0
/*     */     //   272: goto -> 287
/*     */     //   275: aload_0
/*     */     //   276: invokevirtual node : ()Lli/cil/oc/api/network/ComponentConnector;
/*     */     //   279: dload #7
/*     */     //   281: dneg
/*     */     //   282: invokeinterface changeBuffer : (D)D
/*     */     //   287: dadd
/*     */     //   288: dstore #9
/*     */     //   290: aload_0
/*     */     //   291: aload_0
/*     */     //   292: invokevirtual requiredEnergy : ()D
/*     */     //   295: dload #9
/*     */     //   297: dsub
/*     */     //   298: invokevirtual requiredEnergy_$eq : (D)V
/*     */     //   301: aload_0
/*     */     //   302: invokevirtual requiredEnergy : ()D
/*     */     //   305: iconst_0
/*     */     //   306: i2d
/*     */     //   307: dcmpg
/*     */     //   308: ifgt -> 399
/*     */     //   311: aload_0
/*     */     //   312: aload_0
/*     */     //   313: invokevirtual slotOutput : ()I
/*     */     //   316: invokevirtual func_70301_a : (I)Lnet/minecraft/item/ItemStack;
/*     */     //   319: astore #11
/*     */     //   321: aload #11
/*     */     //   323: ifnonnull -> 347
/*     */     //   326: aload_0
/*     */     //   327: aload_0
/*     */     //   328: invokevirtual slotOutput : ()I
/*     */     //   331: aload_0
/*     */     //   332: invokevirtual output : ()Lscala/Option;
/*     */     //   335: invokevirtual get : ()Ljava/lang/Object;
/*     */     //   338: checkcast net/minecraft/item/ItemStack
/*     */     //   341: invokevirtual func_70299_a : (ILnet/minecraft/item/ItemStack;)V
/*     */     //   344: goto -> 383
/*     */     //   347: aload #11
/*     */     //   349: getfield field_77994_a : I
/*     */     //   352: aload #11
/*     */     //   354: invokevirtual func_77976_d : ()I
/*     */     //   357: if_icmpge -> 398
/*     */     //   360: aload_0
/*     */     //   361: invokespecial canMergeOutput$1 : ()Z
/*     */     //   364: ifeq -> 398
/*     */     //   367: aload #11
/*     */     //   369: aload #11
/*     */     //   371: getfield field_77994_a : I
/*     */     //   374: iconst_1
/*     */     //   375: iadd
/*     */     //   376: putfield field_77994_a : I
/*     */     //   379: aload_0
/*     */     //   380: invokevirtual func_70296_d : ()V
/*     */     //   383: aload_0
/*     */     //   384: dconst_0
/*     */     //   385: invokevirtual requiredEnergy_$eq : (D)V
/*     */     //   388: aload_0
/*     */     //   389: getstatic scala/None$.MODULE$ : Lscala/None$;
/*     */     //   392: invokevirtual output_$eq : (Lscala/Option;)V
/*     */     //   395: goto -> 399
/*     */     //   398: return
/*     */     //   399: getstatic li/cil/oc/server/PacketSender$.MODULE$ : Lli/cil/oc/server/PacketSender$;
/*     */     //   402: aload_0
/*     */     //   403: dload #9
/*     */     //   405: ldc2_w 0.5
/*     */     //   408: dcmpl
/*     */     //   409: ifle -> 426
/*     */     //   412: aload_0
/*     */     //   413: invokevirtual output : ()Lscala/Option;
/*     */     //   416: invokevirtual isDefined : ()Z
/*     */     //   419: ifeq -> 426
/*     */     //   422: iconst_1
/*     */     //   423: goto -> 427
/*     */     //   426: iconst_0
/*     */     //   427: invokevirtual sendPrinting : (Lli/cil/oc/common/tileentity/Printer;Z)V
/*     */     //   430: getstatic li/cil/oc/common/item/data/PrintData$.MODULE$ : Lli/cil/oc/common/item/data/PrintData$;
/*     */     //   433: aload_0
/*     */     //   434: aload_0
/*     */     //   435: invokevirtual slotMaterial : ()I
/*     */     //   438: invokevirtual func_70301_a : (I)Lnet/minecraft/item/ItemStack;
/*     */     //   441: invokevirtual materialValue : (Lnet/minecraft/item/ItemStack;)I
/*     */     //   444: istore #12
/*     */     //   446: iload #12
/*     */     //   448: iconst_0
/*     */     //   449: if_icmple -> 493
/*     */     //   452: aload_0
/*     */     //   453: invokevirtual maxAmountMaterial : ()I
/*     */     //   456: aload_0
/*     */     //   457: invokevirtual amountMaterial : ()I
/*     */     //   460: isub
/*     */     //   461: iload #12
/*     */     //   463: if_icmplt -> 493
/*     */     //   466: aload_0
/*     */     //   467: aload_0
/*     */     //   468: invokevirtual slotMaterial : ()I
/*     */     //   471: iconst_1
/*     */     //   472: invokevirtual func_70298_a : (II)Lnet/minecraft/item/ItemStack;
/*     */     //   475: astore #13
/*     */     //   477: aload #13
/*     */     //   479: ifnull -> 493
/*     */     //   482: aload_0
/*     */     //   483: aload_0
/*     */     //   484: invokevirtual amountMaterial : ()I
/*     */     //   487: iload #12
/*     */     //   489: iadd
/*     */     //   490: invokevirtual amountMaterial_$eq : (I)V
/*     */     //   493: getstatic li/cil/oc/common/item/data/PrintData$.MODULE$ : Lli/cil/oc/common/item/data/PrintData$;
/*     */     //   496: aload_0
/*     */     //   497: aload_0
/*     */     //   498: invokevirtual slotInk : ()I
/*     */     //   501: invokevirtual func_70301_a : (I)Lnet/minecraft/item/ItemStack;
/*     */     //   504: invokevirtual inkValue : (Lnet/minecraft/item/ItemStack;)I
/*     */     //   507: istore #14
/*     */     //   509: iload #14
/*     */     //   511: iconst_0
/*     */     //   512: if_icmple -> 587
/*     */     //   515: aload_0
/*     */     //   516: invokevirtual maxAmountInk : ()I
/*     */     //   519: aload_0
/*     */     //   520: invokevirtual amountInk : ()I
/*     */     //   523: isub
/*     */     //   524: iload #14
/*     */     //   526: if_icmplt -> 587
/*     */     //   529: aload_0
/*     */     //   530: aload_0
/*     */     //   531: invokevirtual slotInk : ()I
/*     */     //   534: iconst_1
/*     */     //   535: invokevirtual func_70298_a : (II)Lnet/minecraft/item/ItemStack;
/*     */     //   538: astore #15
/*     */     //   540: aload #15
/*     */     //   542: ifnull -> 587
/*     */     //   545: aload_0
/*     */     //   546: aload_0
/*     */     //   547: invokevirtual amountInk : ()I
/*     */     //   550: iload #14
/*     */     //   552: iadd
/*     */     //   553: invokevirtual amountInk_$eq : (I)V
/*     */     //   556: aload #15
/*     */     //   558: invokevirtual func_77973_b : ()Lnet/minecraft/item/Item;
/*     */     //   561: aload #15
/*     */     //   563: invokevirtual hasContainerItem : (Lnet/minecraft/item/ItemStack;)Z
/*     */     //   566: ifeq -> 587
/*     */     //   569: aload_0
/*     */     //   570: aload_0
/*     */     //   571: invokevirtual slotInk : ()I
/*     */     //   574: aload #15
/*     */     //   576: invokevirtual func_77973_b : ()Lnet/minecraft/item/Item;
/*     */     //   579: aload #15
/*     */     //   581: invokevirtual getContainerItem : (Lnet/minecraft/item/ItemStack;)Lnet/minecraft/item/ItemStack;
/*     */     //   584: invokevirtual func_70299_a : (ILnet/minecraft/item/ItemStack;)V
/*     */     //   587: return
/*     */     // Line number table:
/*     */     //   Java source line number -> byte code offset
/*     */     //   #230	-> 0
/*     */     //   #238	-> 4
/*     */     //   #239	-> 28
/*     */     //   #240	-> 39
/*     */     //   #241	-> 75
/*     */     //   #242	-> 88
/*     */     //   #244	-> 96
/*     */     //   #245	-> 114
/*     */     //   #246	-> 125
/*     */     //   #247	-> 136
/*     */     //   #248	-> 146
/*     */     //   #249	-> 163
/*     */     //   #250	-> 176
/*     */     //   #244	-> 190
/*     */     //   #240	-> 193
/*     */     //   #253	-> 198
/*     */     //   #254	-> 203
/*     */     //   #252	-> 217
/*     */     //   #258	-> 219
/*     */     //   #259	-> 229
/*     */     //   #260	-> 257
/*     */     //   #261	-> 290
/*     */     //   #262	-> 301
/*     */     //   #263	-> 311
/*     */     //   #264	-> 321
/*     */     //   #265	-> 326
/*     */     //   #267	-> 347
/*     */     //   #268	-> 367
/*     */     //   #269	-> 379
/*     */     //   #274	-> 383
/*     */     //   #275	-> 388
/*     */     //   #272	-> 398
/*     */     //   #277	-> 399
/*     */     //   #280	-> 430
/*     */     //   #281	-> 446
/*     */     //   #282	-> 466
/*     */     //   #283	-> 477
/*     */     //   #284	-> 482
/*     */     //   #288	-> 493
/*     */     //   #289	-> 509
/*     */     //   #290	-> 529
/*     */     //   #291	-> 540
/*     */     //   #292	-> 545
/*     */     //   #293	-> 556
/*     */     //   #294	-> 569
/*     */     //   #229	-> 587
/*     */     // Local variable table:
/*     */     //   start	length	slot	name	descriptor
/*     */     //   0	588	0	this	Lli/cil/oc/common/tileentity/Printer;
/*     */     //   69	519	4	materialRequired	I
/*     */     //   75	513	5	inkRequired	I
/*     */     //   257	173	7	want	D
/*     */     //   290	140	9	have	D
/*     */     //   321	74	11	result	Lnet/minecraft/item/ItemStack;
/*     */     //   446	142	12	inputValue	I
/*     */     //   477	111	13	material	Lnet/minecraft/item/ItemStack;
/*     */     //   509	79	14	inkValue	I
/*     */     //   540	48	15	material	Lnet/minecraft/item/ItemStack;
/*     */   }
/*     */   private final boolean canMergeOutput$1() {
/* 233 */     ItemStack presentStack = func_70301_a(slotOutput());
/* 234 */     ItemStack outputStack = data().createItemStack();
/* 235 */     return (presentStack == null || (presentStack.func_77969_a(outputStack) && ItemStack.func_77970_a(presentStack, outputStack)));
/*     */   }
/*     */ 
/*     */ 
/*     */ 
/*     */ 
/*     */ 
/*     */ 
/*     */ 
/*     */ 
/*     */ 
/*     */ 
/*     */ 
/*     */ 
/*     */ 
/*     */ 
/*     */ 
/*     */ 
/*     */ 
/*     */ 
/*     */ 
/*     */ 
/*     */ 
/*     */ 
/*     */ 
/*     */ 
/*     */ 
/*     */ 
/*     */ 
/*     */ 
/*     */ 
/*     */ 
/*     */ 
/*     */ 
/*     */ 
/*     */ 
/*     */ 
/*     */ 
/*     */ 
/*     */ 
/*     */ 
/*     */ 
/*     */ 
/*     */ 
/*     */ 
/*     */ 
/*     */ 
/*     */ 
/*     */ 
/*     */ 
/*     */ 
/*     */ 
/*     */ 
/*     */ 
/*     */ 
/*     */ 
/*     */ 
/*     */ 
/*     */ 
/*     */ 
/*     */ 
/*     */ 
/*     */ 
/*     */ 
/*     */   
/*     */   public void readFromNBTForServer(NBTTagCompound nbt) {
/* 301 */     Rotatable.class.readFromNBTForServer(this, nbt);
/* 302 */     amountMaterial_$eq(nbt.func_74762_e((new StringBuilder()).append(Settings$.MODULE$.namespace()).append("amountMaterial").toString()));
/* 303 */     amountInk_$eq(nbt.func_74762_e((new StringBuilder()).append(Settings$.MODULE$.namespace()).append("amountInk").toString()));
/* 304 */     data().load(nbt.func_74775_l((new StringBuilder()).append(Settings$.MODULE$.namespace()).append("data").toString()));
/* 305 */     isActive_$eq(nbt.func_74767_n((new StringBuilder()).append(Settings$.MODULE$.namespace()).append("active").toString()));
/* 306 */     limit_$eq(nbt.func_74762_e((new StringBuilder()).append(Settings$.MODULE$.namespace()).append("limit").toString()));
/* 307 */     if (nbt.func_74764_b((new StringBuilder()).append(Settings$.MODULE$.namespace()).append("output").toString())) {
/* 308 */       output_$eq(Option$.MODULE$.apply(ItemStack.func_77949_a(nbt.func_74775_l((new StringBuilder()).append(Settings$.MODULE$.namespace()).append("output").toString()))));
/*     */     }
/* 310 */     totalRequiredEnergy_$eq(nbt.func_74769_h((new StringBuilder()).append(Settings$.MODULE$.namespace()).append("total").toString()));
/* 311 */     requiredEnergy_$eq(nbt.func_74769_h((new StringBuilder()).append(Settings$.MODULE$.namespace()).append("remaining").toString()));
/*     */   }
/*     */   
/*     */   public void writeToNBTForServer(NBTTagCompound nbt) {
/* 315 */     Rotatable.class.writeToNBTForServer(this, nbt);
/* 316 */     nbt.func_74768_a((new StringBuilder()).append(Settings$.MODULE$.namespace()).append("amountMaterial").toString(), amountMaterial());
/* 317 */     nbt.func_74768_a((new StringBuilder()).append(Settings$.MODULE$.namespace()).append("amountInk").toString(), amountInk());
/* 318 */     PrintData printData = data(); ExtendedNBT$.MODULE$.extendNBTTagCompound(nbt).setNewCompoundTag((new StringBuilder()).append(Settings$.MODULE$.namespace()).append("data").toString(), (Function1)new Printer$$anonfun$writeToNBTForServer$1(this, printData));
/* 319 */     nbt.func_74757_a((new StringBuilder()).append(Settings$.MODULE$.namespace()).append("active").toString(), isActive());
/* 320 */     nbt.func_74768_a((new StringBuilder()).append(Settings$.MODULE$.namespace()).append("limit").toString(), limit());
/* 321 */     output().foreach((Function1)new Printer$$anonfun$writeToNBTForServer$2(this, nbt));
/* 322 */     nbt.func_74780_a((new StringBuilder()).append(Settings$.MODULE$.namespace()).append("total").toString(), totalRequiredEnergy());
/* 323 */     nbt.func_74780_a((new StringBuilder()).append(Settings$.MODULE$.namespace()).append("remaining").toString(), requiredEnergy());
/*     */   } public final class Printer$$anonfun$writeToNBTForServer$1 extends AbstractFunction1<NBTTagCompound, BoxedUnit> implements Serializable {
/*     */     public static final long serialVersionUID = 0L; private final PrintData eta$0$1$1; public final void apply(NBTTagCompound nbt) { this.eta$0$1$1.save(nbt); } public Printer$$anonfun$writeToNBTForServer$1(Printer $outer, PrintData eta$0$1$1) {} } public final class Printer$$anonfun$writeToNBTForServer$2 extends AbstractFunction1<ItemStack, NBTTagCompound> implements Serializable {
/*     */     public static final long serialVersionUID = 0L; private final NBTTagCompound nbt$1; public final NBTTagCompound apply(ItemStack stack) { return ExtendedNBT$.MODULE$.extendNBTTagCompound(this.nbt$1).setNewCompoundTag((new StringBuilder()).append(Settings$.MODULE$.namespace()).append("output").toString(), (Function1)new Printer$$anonfun$writeToNBTForServer$2$$anonfun$apply$1(this, stack)); } public Printer$$anonfun$writeToNBTForServer$2(Printer $outer, NBTTagCompound nbt$1) {} public final class Printer$$anonfun$writeToNBTForServer$2$$anonfun$apply$1 extends AbstractFunction1<NBTTagCompound, NBTTagCompound> implements Serializable {
/*     */       public static final long serialVersionUID = 0L; private final ItemStack stack$1; public final NBTTagCompound apply(NBTTagCompound x$1) { return this.stack$1.func_77955_b(x$1); } public Printer$$anonfun$writeToNBTForServer$2$$anonfun$apply$1(Printer$$anonfun$writeToNBTForServer$2 $outer, ItemStack stack$1) {} } }
/* 328 */   @SideOnly(Side.CLIENT) public void readFromNBTForClient(NBTTagCompound nbt) { Rotatable.class.readFromNBTForClient(this, nbt);
/* 329 */     data().load(nbt.func_74775_l((new StringBuilder()).append(Settings$.MODULE$.namespace()).append("data").toString()));
/* 330 */     requiredEnergy_$eq(nbt.func_74769_h("remaining")); }
/*     */ 
/*     */   
/*     */   public void writeToNBTForClient(NBTTagCompound nbt) {
/* 334 */     Rotatable.class.writeToNBTForClient(this, nbt);
/* 335 */     PrintData printData = data(); ExtendedNBT$.MODULE$.extendNBTTagCompound(nbt).setNewCompoundTag((new StringBuilder()).append(Settings$.MODULE$.namespace()).append("data").toString(), (Function1)new Printer$$anonfun$writeToNBTForClient$1(this, printData));
/* 336 */     nbt.func_74780_a("remaining", requiredEnergy());
/*     */   } public final class Printer$$anonfun$writeToNBTForClient$1 extends AbstractFunction1<NBTTagCompound, BoxedUnit> implements Serializable {
/*     */     public static final long serialVersionUID = 0L; private final PrintData eta$0$2$1; public final void apply(NBTTagCompound nbt) {
/*     */       this.eta$0$2$1.save(nbt);
/*     */     } public Printer$$anonfun$writeToNBTForClient$1(Printer $outer, PrintData eta$0$2$1) {} } public int func_70302_i_() {
/* 341 */     return 3;
/*     */   }
/*     */   public boolean func_94041_b(int slot, ItemStack stack) {
/* 344 */     return (slot == slotMaterial()) ? (
/* 345 */       (PrintData$.MODULE$.materialValue(stack) > 0)) : (
/* 346 */       (slot == slotInk()) ? (
/* 347 */       (PrintData$.MODULE$.inkValue(stack) > 0)) : false);
/*     */   }
/*     */ 
/*     */   
/*     */   public int[] func_94128_d(int side) {
/* 352 */     return new int[] { slotMaterial(), slotInk(), slotOutput() };
/*     */   } public boolean func_102008_b(int slot, ItemStack stack, int side) {
/* 354 */     return !func_94041_b(slot, stack);
/*     */   } public boolean func_102007_a(int slot, ItemStack stack, int side) {
/* 356 */     return (slot != slotOutput());
/*     */   } }


/* Location:              C:\Users\shame\AppData\Roaming\PrismLauncher\instances\GT_New_Horizons_2.7.4_Java_17-21\.minecraft\mods\OpenComputers-1.10.30-GTNH.jar!\li\cil\oc\common\tileentity\Printer.class
 * Java compiler version: 8 (52.0)
 * JD-Core Version:       1.1.3
 */