/*     */ package li.cil.oc.common.tileentity;@ScalaSignature(bytes = "\006\001\025]h\001B\001\003\0015\021QAU8c_RT!a\001\003\002\025QLG.Z3oi&$\030P\003\002\006\r\00511m\\7n_:T!a\002\005\002\005=\034'BA\005\013\003\r\031\027\016\034\006\002\027\005\021A.[\002\001'!\001abF\017!Q=*\004CA\b\026\033\005\001\"BA\002\022\025\t\0212#A\005nS:,7M]1gi*\tA#A\002oKRL!A\006\t\003\025QKG.Z#oi&$\030\020\005\002\03175\t\021D\003\002\033\005\0051AO]1jiNL!\001H\r\003\021\r{W\016];uKJ\004\"\001\007\020\n\005}I\"\001\005)po\026\024\030J\0344pe6\fG/[8o!\t\tc%D\001#\025\t\031C%\001\004gYVLGm\035\006\003KM\ta\"\\5oK\016\024\030M\032;g_J<W-\003\002(E\ti\021J\0227vS\022D\025M\0343mKJ\004\"!\013\030\016\003)R!a\013\027\002\021%tG/\032:oC2T!!\f\004\002\007\005\004\030.\003\002\002UA\021\001gM\007\002c)\021!\007B\001\nS:4XM\034;pefL!\001N\031\003%%sg/\0328u_JL8+\0327fGRLwN\034\t\003aYJ!aN\031\003\033Q\013gn[*fY\026\034G/[8o\021\025I\004\001\"\001;\003\031a\024N\\5u}Q\t1\b\005\002=\0015\t!\001C\005?\001\001\007\t\031!C\001\005)\001O]8ysV\t\001\t\005\002=\003&\021!I\001\002\013%>\024w\016\036)s_bL\b\"\003#\001\001\004\005\r\021\"\001F\003%\001(o\034=z?\022*\027\017\006\002G\031B\021qIS\007\002\021*\t\021*A\003tG\006d\027-\003\002L\021\n!QK\\5u\021\035i5)!AA\002\001\0131\001\037\0232\021\031y\005\001)Q\005\001\0061\001O]8ys\002Bq!\025\001C\002\023\005!+\001\003j]\032|W#A*\021\005QKV\"A+\013\005Y;\026\001\0023bi\006T!\001\027\003\002\t%$X-\\\005\0035V\023\021BU8c_R$\025\r^1\t\rq\003\001\025!\003T\003\025IgNZ8!\021\035q\006A1A\005\002}\0131AY8u+\005\001\007CA1g\033\005\021'BA2e\003%\031w.\0349p]\026tGO\003\002f\r\00511/\032:wKJL!!\0012\t\r!\004\001\025!\003a\003\021\021w\016\036\021\t\013)\004A\021I6\002\tQLWM\035\013\002YB\021q)\\\005\003]\"\0231!\0238u\021\025\001\b\001\"\001r\003)I7o\021:fCRLg/Z\013\002eB\021qi]\005\003i\"\023qAQ8pY\026\fg\016C\004w\001\t\007I\021A<\002%\025\fX/\0339nK:$\030J\034<f]R|'/_\013\002qJ!\0210`A\006\r\021Q8\020\001=\003\031q\022XMZ5oK6,g\016\036 \t\rq\004\001\025!\003y\003M)\027/^5q[\026tG/\0238wK:$xN]=!!\rq\030qA\007\002*!\021\021AA\002\003\021a\027M\\4\013\005\005\025\021\001\0026bm\006L1!!\003\000\005\031y%M[3diB\031\001'!\004\n\007\005=\021G\001\bJ]Z,g\016^8ssB\023x\016_=\t\rIJH\021IA\n+\005Y\004\"CA\f\001\t\007I\021AA\r\0035i\027-\0338J]Z,g\016^8ssV\021\0211\004\n\006\003;i\0301\002\004\007u\006}\001!a\007\t\021\005\005\002\001)A\005\0037\ta\"\\1j]&sg/\0328u_JL\b\005C\0043\003;!\t%a\005\t\023\005\035\002A1A\005\002\005%\022aE1diV\fG.\0238wK:$xN]=TSj,W#\0017\t\017\0055\002\001)A\005Y\006!\022m\031;vC2LeN^3oi>\024\030pU5{K\002Bq!!\r\001\t\003\tI#\001\tnCbLeN^3oi>\024\030pU5{K\"I\021Q\007\001A\002\023\005\021\021F\001\016S:4XM\034;pef\034\026N_3\t\023\005e\002\0011A\005\002\005m\022!E5om\026tGo\034:z'&TXm\030\023fcR\031a)!\020\t\0215\0139$!AA\0021Dq!!\021\001A\003&A.\001\bj]Z,g\016^8ssNK'0\032\021\t\023\005\025\003\0011A\005\002\005%\022\001D:fY\026\034G/\0323TY>$\b\"CA%\001\001\007I\021AA&\003A\031X\r\\3di\026$7\013\\8u?\022*\027\017F\002G\003\033B\001\"TA$\003\003\005\r\001\034\005\b\003#\002\001\025)\003m\0035\031X\r\\3di\026$7\013\\8uA!9\021Q\013\001\005B\005]\023aD:fiN+G.Z2uK\022\034Fn\034;\025\007\031\013I\006C\004\002\\\005M\003\031\0017\002\013%tG-\032=\t\023\005}\003A1A\005\002\005\005\024\001\002;b].,\"!a\031\023\013\005\025T0a\033\007\ri\f9\007AA2\021!\tI\007\001Q\001\n\005\r\024!\002;b].\004\003cA\025\002n%\031\021q\016\026\003\0235+H\016^5UC:\\\007\002CA:\003K\"\t%!\036\002\031\035,GO\0227vS\022$\026M\\6\025\t\005]\024\021\023\n\007\003s\ny(a#\007\013i\004\001!a\036\013\007\005uD\"\001\004=e>|GO\020\t\005\003\003\0139)\004\002\002\004*\031\021Q\021\027\002\0179,Go^8sW&!\021\021RAB\005Ii\025M\\1hK\022,eN^5s_:lWM\034;\021\007\005\ni)C\002\002\020\n\022!\"\023$mk&$G+\0318l\021\035\tY&!\035A\0021D\021\"!&\001\001\004%\t!!\013\002\031M,G.Z2uK\022$\026M\\6\t\023\005e\005\0011A\005\002\005m\025\001E:fY\026\034G/\0323UC:\\w\fJ3r)\r1\025Q\024\005\t\033\006]\025\021!a\001Y\"9\021\021\025\001!B\023a\027!D:fY\026\034G/\0323UC:\\\007\005C\004\002&\002!\t%a*\002\037M,GoU3mK\016$X\r\032+b].$2ARAU\021\035\tY&a)A\0021D\001\"!,\001\001\004%\t!]\001\021e\026tG-\032:j]\036,%O]8sK\022D\021\"!-\001\001\004%\t!a-\002)I,g\016Z3sS:<WI\035:pe\026$w\fJ3r)\r1\025Q\027\005\t\033\006=\026\021!a\001e\"9\021\021\030\001!B\023\021\030!\005:f]\022,'/\0338h\013J\024xN]3eA!1\021Q\030\001\005B-\fabY8na>tWM\034;D_VtG\017C\004\002B\002!\t%a1\002%\035,GoQ8na>tWM\034;J]Ncw\016\036\013\005\003\013\fY\r\005\003\002\002\006\035\027\002BAe\003\007\0231\"\0228wSJ|g.\\3oi\"9\0211LA`\001\004a\007bBAh\001\021\005\023\021[\001\007a2\f\0270\032:\025\005\005M\007\003BAk\0037l!!a6\013\007\005eG-A\003bO\026tG/\003\003\002^\006]'A\002)mCf,'\017C\004\002b\002!\t%a9\002\037MLhn\0315s_:L'0Z*m_R$2ARAs\021\035\t9/a8A\0021\fAa\0357pi\"9\0211\036\001\005\002\0055\030AD2p]R\f\027N\\3s'2|Go]\013\003\003_\004B!!=\003\0029!\0211_A\033\t\t)P\003\003\002x\006e\030!C5n[V$\030M\0317f\025\r\tY\020S\001\013G>dG.Z2uS>t\027\002BA\000\003k\fQAU1oO\026LAAa\001\003\006\tI\021J\\2mkNLg/\032\006\005\003\f)\020C\004\003\n\001!\tAa\003\002\035\r|W\016]8oK:$8\013\\8ugV\021!Q\002\t\005\003g\024y!\003\003\003\022\005U(!\002*b]\036,\007b\002B\013\001\021\005!qC\001\017S:4XM\034;pef\034Fn\034;t+\t\021I\002\005\003\003\034\t\035b\002\002B\017\005GqAAa\b\003\"5\021\0211P\005\002\023&\031!Q\005%\002\017A\f7m[1hK&!!\021\003B\025\025\r\021)\003\023\005\b\005[\001A\021\001B\030\0035\031X\r\036'jO\"$8i\0347peR\031aI!\r\t\017\tM\"1\006a\001Y\006)a/\0317vK\"9!q\007\001\005B\te\022!D:i_VdG-\0218j[\006$X\rF\001s\021\035\021i\004\001C!\005\tAA\\8eKR\021!\021\t\t\005\003\003\023\031%\003\003\003F\005\r%\001\002(pI\026D\021B!\023\001\001\004%\tAa\023\002\031\035dwNY1m\005V4g-\032:\026\005\t5\003cA$\003P%\031!\021\013%\003\r\021{WO\0317f\021%\021)\006\001a\001\n\003\0219&\001\thY>\024\027\r\034\"vM\032,'o\030\023fcR\031aI!\027\t\0235\023\031&!AA\002\t5\003\002\003B/\001\001\006KA!\024\002\033\035dwNY1m\005V4g-\032:!\021%\021\t\007\001a\001\n\003\021Y%\001\thY>\024\027\r\034\"vM\032,'oU5{K\"I!Q\r\001A\002\023\005!qM\001\025O2|'-\0317Ck\0324WM]*ju\026|F%Z9\025\007\031\023I\007C\005N\005G\n\t\0211\001\003N!A!Q\016\001!B\023\021i%A\thY>\024\027\r\034\"vM\032,'oU5{K\002B\021B!\035\001\005\004%\t!!\013\002\0335\f\007pQ8na>tWM\034;t\021\035\021)\b\001Q\001\n1\fa\"\\1y\007>l\007o\0348f]R\034\b\005C\005\003z\001\001\r\021\"\001\003|\005Iqn\0368fe:\013W.Z\013\003\005{\0022A B@\023\r\021\ti \002\007'R\024\030N\\4\t\023\t\025\005\0011A\005\002\t\035\025!D8x]\026\024h*Y7f?\022*\027\017F\002G\005\023C\021\"\024BB\003\003\005\rA! \t\021\t5\005\001)Q\005\005{\n!b\\<oKJt\025-\\3!\021%\021\t\n\001a\001\n\003\021\031*A\005po:,'/V+J\tV\021!Q\023\t\005\005/\023i*\004\002\003\032*!!1TA\002\003\021)H/\0337\n\t\t}%\021\024\002\005+VKE\tC\005\003$\002\001\r\021\"\001\003&\006iqn\0368feV+\026\nR0%KF$2A\022BT\021%i%\021UA\001\002\004\021)\n\003\005\003,\002\001\013\025\002BK\003)ywO\\3s+VKE\t\t\005\n\005_\003\001\031!C\001\003S\t!#\0318j[\006$\030n\0348US\016\\7\017T3gi\"I!1\027\001A\002\023\005!QW\001\027C:LW.\031;j_:$\026nY6t\031\0264Go\030\023fcR\031aIa.\t\0215\023\t,!AA\0021DqAa/\001A\003&A.A\nb]&l\027\r^5p]RK7m[:MK\032$\b\005C\005\003@\002\001\r\021\"\001\002*\005\031\022M\\5nCRLwN\034+jG.\034Hk\034;bY\"I!1\031\001A\002\023\005!QY\001\030C:LW.\031;j_:$\026nY6t)>$\030\r\\0%KF$2A\022Bd\021!i%\021YA\001\002\004a\007b\002Bf\001\001\006K\001\\\001\025C:LW.\031;j_:$\026nY6t)>$\030\r\034\021\t\023\t=\007\0011A\005\002\005%\022!C7pm\0264%o\\7Y\021%\021\031\016\001a\001\n\003\021).A\007n_Z,gI]8n1~#S-\035\013\004\r\n]\007\002C'\003R\006\005\t\031\0017\t\017\tm\007\001)Q\005Y\006QQn\034<f\rJ|W\016\027\021\t\023\t}\007\0011A\005\002\005%\022!C7pm\0264%o\\7Z\021%\021\031\017\001a\001\n\003\021)/A\007n_Z,gI]8n3~#S-\035\013\004\r\n\035\b\002C'\003b\006\005\t\031\0017\t\017\t-\b\001)Q\005Y\006QQn\034<f\rJ|W.\027\021\t\023\t=\b\0011A\005\002\005%\022!C7pm\0264%o\\7[\021%\021\031\020\001a\001\n\003\021)0A\007n_Z,gI]8n5~#S-\035\013\004\r\n]\b\002C'\003r\006\005\t\031\0017\t\017\tm\b\001)Q\005Y\006QQn\034<f\rJ|WN\027\021\t\021\t}\b\0011A\005\002E\fAb]<j]\036Lgn\032+p_2D\021ba\001\001\001\004%\ta!\002\002!M<\030N\\4j]\036$vn\0347`I\025\fHc\001$\004\b!AQj!\001\002\002\003\007!\017C\004\004\f\001\001\013\025\002:\002\033M<\030N\\4j]\036$vn\0347!\021%\031y\001\001a\001\n\003\tI#\001\005ukJt\027\t_5t\021%\031\031\002\001a\001\n\003\031)\"\001\007ukJt\027\t_5t?\022*\027\017F\002G\007/A\001\"TB\t\003\003\005\r\001\034\005\b\0077\001\001\025)\003m\003%!XO\0358Bq&\034\b\005\003\005\004 \001\001\r\021\"\001r\003]\t\007\017\0357jK\022$vn\0347F]\016D\027M\034;nK:$8\017C\005\004$\001\001\r\021\"\001\004&\005Y\022\r\0359mS\026$Gk\\8m\013:\034\007.\0318u[\026tGo]0%KF$2ARB\024\021!i5\021EA\001\002\004\021\bbBB\026\001\001\006KA]\001\031CB\004H.[3e)>|G.\0228dQ\006tG/\\3oiN\004\003BCB\030\001!\025\r\021\"\003\0042\0059\001\017\\1zKJ|VCAAj\021)\031)\004\001E\001B\003&\0211[\001\ta2\f\0270\032:`A!91\021\b\001\005B\rm\022\001\0028b[\026$\"A! \t\017\r}\002\001\"\021\004B\00591/\032;OC6,Gc\001$\004D!A1\021HB\037\001\004\031)\005\005\003\004H\r5cbA$\004J%\03111\n%\002\rA\023X\rZ3g\023\021\021\tia\024\013\007\r-\003\nC\004\004T\001!\te!\026\002\023=t\027I\\1msj,G\003DB,\007;\032ig!\035\004|\r}\004#B$\004Z\t\005\023bAB.\021\n)\021I\035:bs\"A\021qZB)\001\004\031y\006\005\003\004b\r%TBAB2\025\021\tym!\032\013\007\r\035\024#\001\004f]RLG/_\005\005\007W\032\031G\001\007F]RLG/\037)mCf,'\017C\004\004p\rE\003\031\0017\002\tMLG-\032\005\t\007g\032\t\0061\001\004v\005!\001.\033;Y!\r95qO\005\004\007sB%!\002$m_\006$\b\002CB?\007#\002\ra!\036\002\t!LG/\027\005\t\007\003\033\t\0061\001\004v\005!\001.\033;[\021\035\031)\t\001C\001\007\017\013A!\\8wKR\031!o!#\t\021\r-51\021a\001\007\033\013\021\002Z5sK\016$\030n\0348\021\t\r=5QS\007\003\007#SAAa'\004\024*\021Q\001J\005\005\007/\033\tJ\001\bG_J<W\rR5sK\016$\030n\0348\t\r\rm\005\001\"\001r\003=I7/\0218j[\006$\030N\\4N_Z,\007BBBP\001\021\005\021/\001\tjg\006s\027.\\1uS:<7k^5oO\"111\025\001\005\002E\fq\"[:B]&l\027\r^5oOR+(O\034\005\b\007O\003A\021ABU\0031\tg.[7bi\026\034v/\0338h)\r151\026\005\t\007[\033)\0131\001\003N\005AA-\036:bi&|g\016C\004\0042\002!\taa-\002\027\005t\027.\\1uKR+(O\034\013\006\r\016U6\021\030\005\b\007o\033y\0131\001s\003%\031Gn\\2lo&\034X\r\003\005\004.\016=\006\031\001B'\021\035\031i\f\001C\001\007\013ab]3u\003:LW.\031;f\033>4X\rF\003G\007\003\034y\r\003\005\004D\016m\006\031ABc\00311'o\\7Q_NLG/[8o!\021\0319ma3\016\005\r%'b\001BN\r%!1QZBe\0055\021En\\2l!>\034\030\016^5p]\"91\021[B^\001\004a\027!\002;jG.\034\bbBBk\001\021\0051q[\001\020g\026$\030I\\5nCR,7k^5oOR\031ai!7\t\017\rE71\033a\001Y\"91Q\034\001\005\002\r}\027AD:fi\006s\027.\\1uKR+(O\034\013\006\r\016\0058Q\035\005\b\007G\034Y\0161\001m\003\021\t\0070[:\t\017\rE71\034a\001Y\"91\021\036\001\005\n\r-\030a\0059sKB\f'/\032$pe\006s\027.\\1uS>tG#\001$\t\017\r=\b\001\"\021\004r\006\0212\017[8vY\022\024VM\0343fe&s\007+Y:t)\r\02181\037\005\b\007k\034i\0171\001m\003\021\001\030m]:\t\017\re\b\001\"\021\004|\006!r-\032;SK:$WM\035\"pk:$\027N\\4C_b$\"a!@\021\t\r}H1A\007\003\t\003Q1Aa'\022\023\021!)\001\"\001\003\033\005C\030n]!mS\036tW\r\032\"C\021\035!I\001\001C!\007W\fA\"\0369eCR,WI\034;jifDq\001\"\004\001\t#\032Y/\001\bva\022\fG/Z\"p[B,H/\032:\t\017\021E\001\001\"\025\004l\006\001rN\034*v]:LgnZ\"iC:<W\r\032\005\b\t+\001A\021KBv\003)Ig.\033;jC2L'0\032\005\b\t3\001A\021IBv\003\035!\027n\0359pg\026Dq\001\"\b\001\t\003\"y\"\001\013sK\006$gI]8n\035\n#fi\034:TKJ4XM\035\013\004\r\022\005\002\002\003C\022\t7\001\r\001\"\n\002\0079\024G\017\005\003\005(\021-RB\001C\025\025\r!\031#E\005\005\t[!IC\001\bO\005R#\026mZ\"p[B|WO\0343\t\017\021E\002\001\"\021\0054\005\031rO]5uKR{gJ\021+G_J\034VM\035<feR\031a\t\"\016\t\021\021\rBq\006a\001\tKAq\001\"\017\001\t\003\"Y$\001\013sK\006$gI]8n\035\n#fi\034:DY&,g\016\036\013\004\r\022u\002\002\003C\022\to\001\r\001\"\n)\021\021]B\021\tB\032\t3\002B\001b\021\005V5\021AQ\t\006\005\t\017\"I%\001\006sK2\fWO\\2iKJTA\001b\023\005N\005\031a-\0347\013\t\021=C\021K\001\005[>$7O\003\002\005T\005\0311\r]<\n\t\021]CQ\t\002\t'&$Wm\0248ms\022\022A1L\005\005\t;\"y&\001\004D\031&+e\n\026\006\005\tC\")%\001\003TS\022,\007b\002C3\001\021\005CqM\001\024oJLG/\032+p\035\n#fi\034:DY&,g\016\036\013\004\r\022%\004\002\003C\022\tG\002\r\001\"\n\t\017\0215\004\001\"\021\005p\005\001rN\\'bG\"Lg.Z\"p]:,7\r\036\013\004\r\022E\004\002\003B\037\tW\002\rA!\021\t\017\021U\004\001\"\021\005x\005\031rN\\'bG\"Lg.\032#jg\016|gN\\3diR\031a\t\"\037\t\021\tuB1\017a\001\005\003Bq\001\" \001\t#\"y(A\006p]&#X-\\!eI\026$G#\002$\005\002\022\r\005bBAt\tw\002\r\001\034\005\t\t\013#Y\b1\001\005\b\006)1\017^1dWB!A\021\022CG\033\t!YI\003\002Y#%!Aq\022CF\005%IE/Z7Ti\006\0347\016C\004\005\024\002!\t\006\"&\002\033=t\027\n^3n%\026lwN^3e)\0251Eq\023CM\021\035\t9\017\"%A\0021D\001\002\"\"\005\022\002\007Aq\021\005\b\t;\003A\021IBv\003%i\027M]6ESJ$\030\020C\004\005\"\002!\t\006b)\002\037\r|gN\\3di&#X-\034(pI\026$2A\022CS\021!\021i\004b(A\002\t\005\003b\002CU\001\021\005C1V\001\020SN\034u.\0349p]\026tGo\0257piR)!\017\",\0050\"9\021q\035CT\001\004a\007\002\003CC\tO\003\r\001b\"\t\017\021M\006\001\"\001\0056\006\t2m\0348uC&tWM]*m_R$\026\020]3\025\t\tuDq\027\005\b\003O$\t\f1\001m\021\035!Y\f\001C\001\t{\013\021cY8oi\006Lg.\032:TY>$H+[3s)\raGq\030\005\b\003O$I\f1\001m\021\035!\031\r\001C\001\t\013\f!\"[:U_>d7\013\\8u)\r\021Hq\031\005\b\003O$\t\r1\001m\021\035!Y\r\001C\001\t\033\fq\"[:D_:$\030-\0338feNcw\016\036\013\004e\022=\007bBAt\t\023\004\r\001\034\005\b\t'\004A\021\001Ck\003=I7/\0238wK:$xN]=TY>$Hc\001:\005X\"9\021q\035Ci\001\004a\007b\002Cn\001\021\005AQ\\\001\rSN4En\0349qsNcw\016\036\013\004e\022}\007bBAt\t3\004\r\001\034\005\b\tG\004A\021\001Cs\0035I7/\0269he\006$Wm\0257piR\031!\017b:\t\017\005\035H\021\035a\001Y\"9A1\036\001\005B\0215\030!D2p[B|g.\0328u'2|G\017F\002m\t_D\001\002\"=\005j\002\0071QI\001\bC\022$'/Z:t\021\031!)\020\001C!c\006y\001.Y:SK\022\034Ho\0348f\007\006\024H\r\003\004\005z\002!Ia[\001\025G>l\007/\036;f\023:4XM\034;pef\034\026N_3\t\021\021u\b\0011A\005\nE\fQ#\0369eCRLgnZ%om\026tGo\034:z'&TX\rC\005\006\002\001\001\r\021\"\003\006\004\005IR\017\0353bi&tw-\0238wK:$xN]=TSj,w\fJ3r)\r1UQ\001\005\t\033\022}\030\021!a\001e\"9Q\021\002\001!B\023\021\030AF;qI\006$\030N\\4J]Z,g\016^8ssNK'0\032\021\t\017\0255\001\001\"\001\004l\006\031R\017\0353bi\026LeN^3oi>\024\030pU5{K\"IQ\021\003\001A\002\023\005\021\021F\001\021O\026$8+\033>f\023:4XM\034;pefD\021\"\"\006\001\001\004%\t!b\006\002)\035,GoU5{K&sg/\0328u_JLx\fJ3r)\r1U\021\004\005\t\033\026M\021\021!a\001Y\"9QQ\004\001!B\023a\027!E4fiNK'0Z%om\026tGo\034:zA!1Q\021\005\001\005B-\facZ3u\023:4XM\034;pef\034F/Y2l\031&l\027\016\036\005\b\013K\001A\021IC\024\00399W\r^*uC\016\\\027J\\*m_R$B\001b\"\006*!9\021q]C\022\001\004a\007bBC\027\001\021\005SqF\001\031g\026$\030J\034<f]R|'/_*m_R\034uN\034;f]R\034H#\002$\0062\025M\002bBAt\013W\001\r\001\034\005\t\t\013+Y\0031\001\005\b\"9Qq\007\001\005B\025e\022!E5t+N,\027M\0317f\005f\004F.Y=feR\031!/b\017\t\021\005=WQ\007a\001\007?Bq!b\020\001\t\003*\t%\001\njg&#X-\034,bY&$gi\034:TY>$H#\002:\006D\025\025\003bBAt\013{\001\r\001\034\005\t\t\013+i\0041\001\005\b\"9Q\021\n\001\005B\025-\023\001\0033s_B\034Fn\034;\025\017I,i%b\024\006T!9\021q]C$\001\004a\007\"CC)\013\017\002\n\0211\001m\003\025\031w.\0368u\021)\031Y)b\022\021\002\003\007QQ\013\t\006\017\026]3QR\005\004\0133B%AB(qi&|g\016C\004\006^\001!\tea;\002\031\021\024x\016]!mYNcw\016^:\t\017\025\005\004\001\"\021\006d\005q1-\0318FqR\024\030m\031;Ji\026lGc\002:\006f\025\035T\021\016\005\b\003O,y\0061\001m\021!!))b\030A\002\021\035\005bBB8\013?\002\r\001\034\005\b\013[\002A\021IC8\0035\031\027M\\%og\026\024H/\023;f[R9!/\"\035\006t\025U\004bBAt\013W\002\r\001\034\005\t\t\013+Y\0071\001\005\b\"91qNC6\001\004a\007bBC=\001\021\005S1P\001\033O\026$\030iY2fgNL'\r\\3TY>$8O\022:p[NKG-\032\013\005\013{*y\b\005\003H\0073b\007bBB8\013o\002\r\001\034\005\b\013\007\003A\021ACC\003)!(/_$fiR\013gn\033\013\005\013\017+i\tE\003H\013/*II\005\004\006\f\006}\0241\022\004\006u\002\001Q\021\022\005\b\003?*\t\t1\001m\021\035)\t\n\001C\001\003S\t\021\002^1oW\016{WO\034;\t\017\005M\004\001\"\001\006\026R!Q\021RCL\021\035\ty&b%A\0021Dq!b'\001\t\003*i*\001\003gS2dGc\0027\006 \026\rVQ\026\005\t\013C+I\n1\001\004\016\006!aM]8n\021!))+\"'A\002\025\035\026\001\003:fg>,(oY3\021\007\005*I+C\002\006,\n\022!B\0227vS\022\034F/Y2l\021\035)y+\"'A\002I\fa\001Z8GS2d\007bBCZ\001\021\005SQW\001\006IJ\f\027N\034\013\t\013O+9,\"/\006<\"AQ\021UCY\001\004\031i\t\003\005\006&\026E\006\031ACT\021\035)i,\"-A\002I\fq\001Z8Ee\006Lg\016C\004\0064\002!\t%\"1\025\021\025\035V1YCc\013\023D\001\"\")\006@\002\0071Q\022\005\b\013\017,y\f1\001m\003!i\027\r\037#sC&t\007bBC_\013\003\rA\035\005\b\013\033\004A\021ICh\003\035\031\027M\034$jY2$RA]Ci\013'D\001\"\")\006L\002\0071Q\022\005\t\013+,Y\r1\001\006X\006)a\r\\;jIB\031\021%\"7\n\007\025m'EA\003GYVLG\rC\004\006`\002!\t%\"9\002\021\r\fg\016\022:bS:$RA]Cr\013KD\001\"\")\006^\002\0071Q\022\005\t\013+,i\0161\001\006X\"9Q\021\036\001\005B\025-\030aC4fiR\013gn[%oM>$B!\"<\006vB)qi!\027\006pB\031\021%\"=\n\007\025M(EA\007GYVLG\rV1oW&sgm\034\005\t\013C+9\0171\001\004\016\002")
/*     */ public class Robot extends TileEntity implements Computer, PowerInformation, Robot, InventorySelection, TankSelection { private RobotProxy proxy; private final RobotData info; private final li.cil.oc.server.component.Robot bot; private final InventoryProxy equipmentInventory; private final InventoryProxy mainInventory; private final int actualInventorySize; private int inventorySize; private int selectedSlot; private final MultiTank tank;
/*     */   private int selectedTank;
/*     */   private boolean renderingErrored;
/*     */   private double globalBuffer;
/*     */   private double globalBufferSize;
/*     */   private final int maxComponents;
/*     */   private String ownerName;
/*     */   private UUID ownerUUID;
/*     */   private int animationTicksLeft;
/*     */   private int animationTicksTotal;
/*     */   private int moveFromX;
/*     */   private int moveFromY;
/*     */   private int moveFromZ;
/*     */   private boolean swingingTool;
/*     */   private int turnAxis;
/*     */   private boolean appliedToolEnchantments;
/*     */   private Player li$cil$oc$common$tileentity$Robot$$player_;
/*     */   private boolean updatingInventorySize;
/*     */   private int getSizeInventory;
/*     */   private double li$cil$oc$common$tileentity$traits$PowerInformation$$lastSentRatio;
/*     */   private int li$cil$oc$common$tileentity$traits$PowerInformation$$ticksUntilSync;
/*     */   private final Machine li$cil$oc$common$tileentity$traits$Computer$$_machine;
/*     */   private boolean li$cil$oc$common$tileentity$traits$Computer$$_isRunning;
/*     */   private boolean hasErrored;
/*     */   private final Set<String> li$cil$oc$common$tileentity$traits$Computer$$_users;
/*     */   private boolean _isAbstractBusAvailable;
/*     */   private final Object[] fakeInterface;
/*     */   private final int[][] _bundledInput;
/*     */   private final int[][] _rednetInput;
/*     */   private final int[][] _bundledOutput;
/*     */   private final int[] _input;
/*     */   private final int[] _output;
/*     */   private boolean _isOutputEnabled;
/*     */   private boolean shouldUpdateInput;
/*     */   private final ForgeDirection[] li$cil$oc$common$tileentity$traits$Rotatable$$pitch2Direction;
/*     */   private final ForgeDirection[] li$cil$oc$common$tileentity$traits$Rotatable$$yaw2Direction;
/*     */   private ForgeDirection li$cil$oc$common$tileentity$traits$Rotatable$$_pitch;
/*     */   private ForgeDirection li$cil$oc$common$tileentity$traits$Rotatable$$_yaw;
/*     */   private final ArrayBuffer<Option<ItemStack>> li$cil$oc$common$tileentity$traits$ComponentInventory$$pendingRemovalsActual;
/*     */   private final ArrayBuffer<Option<ItemStack>> li$cil$oc$common$tileentity$traits$ComponentInventory$$pendingAddsActual;
/*     */   private boolean li$cil$oc$common$tileentity$traits$ComponentInventory$$updateScheduled;
/*     */   private Option<ManagedEnvironment>[] li$cil$oc$common$inventory$ComponentInventory$$_components;
/*     */   private boolean isSizeInventoryReady;
/*     */   private final ArrayBuffer<ManagedEnvironment> updatingComponents;
/*     */   private final Option<ItemStack>[] li$cil$oc$common$tileentity$traits$Inventory$$inventory;
/*     */   private boolean isChangeScheduled;
/*     */   private boolean moving;
/*     */   private volatile byte bitmap$0;
/*     */   
/*  51 */   public double li$cil$oc$common$tileentity$traits$PowerInformation$$lastSentRatio() { return this.li$cil$oc$common$tileentity$traits$PowerInformation$$lastSentRatio; } public void li$cil$oc$common$tileentity$traits$PowerInformation$$lastSentRatio_$eq(double x$1) { this.li$cil$oc$common$tileentity$traits$PowerInformation$$lastSentRatio = x$1; } public int li$cil$oc$common$tileentity$traits$PowerInformation$$ticksUntilSync() { return this.li$cil$oc$common$tileentity$traits$PowerInformation$$ticksUntilSync; } public void li$cil$oc$common$tileentity$traits$PowerInformation$$ticksUntilSync_$eq(int x$1) { this.li$cil$oc$common$tileentity$traits$PowerInformation$$ticksUntilSync = x$1; } public void updatePowerInformation() { PowerInformation.class.updatePowerInformation(this); } private Machine li$cil$oc$common$tileentity$traits$Computer$$_machine$lzycompute() { synchronized (this) { if ((byte)(this.bitmap$0 & 0x2) == 0) { this.li$cil$oc$common$tileentity$traits$Computer$$_machine = Computer.class.li$cil$oc$common$tileentity$traits$Computer$$_machine(this); this.bitmap$0 = (byte)(this.bitmap$0 | 0x2); }  return this.li$cil$oc$common$tileentity$traits$Computer$$_machine; }  } public Machine li$cil$oc$common$tileentity$traits$Computer$$_machine() { return ((byte)(this.bitmap$0 & 0x2) == 0) ? li$cil$oc$common$tileentity$traits$Computer$$_machine$lzycompute() : this.li$cil$oc$common$tileentity$traits$Computer$$_machine; } public boolean li$cil$oc$common$tileentity$traits$Computer$$_isRunning() { return this.li$cil$oc$common$tileentity$traits$Computer$$_isRunning; } public void li$cil$oc$common$tileentity$traits$Computer$$_isRunning_$eq(boolean x$1) { this.li$cil$oc$common$tileentity$traits$Computer$$_isRunning = x$1; } public boolean hasErrored() { return this.hasErrored; } public void hasErrored_$eq(boolean x$1) { this.hasErrored = x$1; } public Set<String> li$cil$oc$common$tileentity$traits$Computer$$_users() { return this.li$cil$oc$common$tileentity$traits$Computer$$_users; } public void li$cil$oc$common$tileentity$traits$Computer$_setter_$li$cil$oc$common$tileentity$traits$Computer$$_users_$eq(Set<String> x$1) { this.li$cil$oc$common$tileentity$traits$Computer$$_users = x$1; } public Machine machine() { return Computer.class.machine(this); } public Option<String> runSound() { return Computer.class.runSound(this); } public boolean canInteract(String player) { return Computer.class.canInteract(this, player); } public boolean isRunning() { return Computer.class.isRunning(this); } public void setRunning(boolean value) { Computer.class.setRunning(this, value); } @SideOnly(Side.CLIENT) public void setUsers(Iterable list) { Computer.class.setUsers(this, list); } public EnumSet<StateAware.State> getCurrentState() { return Computer.class.getCurrentState(this); } public Iterable<ItemStack> internalComponents() { return Computer.class.internalComponents(this); } public Iterable<ManagedEnvironment> installedComponents() { return Computer.class.installedComponents(this); } public boolean hasAbstractBusCard() { return Computer.class.hasAbstractBusCard(this); } public void onRotationChanged() { Computer.class.onRotationChanged(this); } public void onRedstoneInputChanged(RedstoneChangedEventArgs args) { Computer.class.onRedstoneInputChanged(this, args); } @Method(modid = "BuildCraft|Core") public boolean hasWork() { return StateAware.class.hasWork((StateAware)this); } public boolean _isAbstractBusAvailable() { return this._isAbstractBusAvailable; } public void _isAbstractBusAvailable_$eq(boolean x$1) { this._isAbstractBusAvailable = x$1; } private Object[] fakeInterface$lzycompute() { synchronized (this) { if ((byte)(this.bitmap$0 & 0x4) == 0) { this.fakeInterface = AbstractBusAware.class.fakeInterface((AbstractBusAware)this); this.bitmap$0 = (byte)(this.bitmap$0 | 0x4); }  return this.fakeInterface; }  } public Object[] fakeInterface() { return ((byte)(this.bitmap$0 & 0x4) == 0) ? fakeInterface$lzycompute() : this.fakeInterface; } @Method(modid = "StargateTech2") public IBusInterface[] getInterfaces(int side) { return AbstractBusAware.class.getInterfaces((AbstractBusAware)this, side); } public World getWorld() { return AbstractBusAware.class.getWorld((AbstractBusAware)this); } public int getXCoord() { return AbstractBusAware.class.getXCoord((AbstractBusAware)this); } public int getYCoord() { return AbstractBusAware.class.getYCoord((AbstractBusAware)this); } public int getZCoord() { return AbstractBusAware.class.getZCoord((AbstractBusAware)this); } public boolean isAbstractBusAvailable() { return AbstractBusAware.class.isAbstractBusAvailable((AbstractBusAware)this); } public AbstractBusAware isAbstractBusAvailable_$eq(boolean value) { return AbstractBusAware.class.isAbstractBusAvailable_$eq((AbstractBusAware)this, value); } public void onDisconnect(Node node) { AbstractBusAware.class.onDisconnect((AbstractBusAware)this, node); } public int[][] _bundledInput() { return this._bundledInput; } public int[][] _rednetInput() { return this._rednetInput; } public int[][] _bundledOutput() { return this._bundledOutput; } public void li$cil$oc$common$tileentity$traits$BundledRedstoneAware$_setter_$_bundledInput_$eq(int[][] x$1) { this._bundledInput = x$1; } public void li$cil$oc$common$tileentity$traits$BundledRedstoneAware$_setter_$_rednetInput_$eq(int[][] x$1) { this._rednetInput = x$1; } public void li$cil$oc$common$tileentity$traits$BundledRedstoneAware$_setter_$_bundledOutput_$eq(int[][] x$1) { this._bundledOutput = x$1; } public void setOutputEnabled(boolean value) { BundledRedstoneAware.class.setOutputEnabled((BundledRedstoneAware)this, value); } public int[][] getBundledInput() { return BundledRedstoneAware.class.getBundledInput((BundledRedstoneAware)this); } public int[] getBundledInput(ForgeDirection side) { return BundledRedstoneAware.class.getBundledInput((BundledRedstoneAware)this, side); } public int getBundledInput(ForgeDirection side, int color) { return BundledRedstoneAware.class.getBundledInput((BundledRedstoneAware)this, side, color); } public void setBundledInput(ForgeDirection side, int color, int newValue) { BundledRedstoneAware.class.setBundledInput((BundledRedstoneAware)this, side, color, newValue); } public void setBundledInput(ForgeDirection side, int[] newBundledInput) { BundledRedstoneAware.class.setBundledInput((BundledRedstoneAware)this, side, newBundledInput); } public void setRednetInput(ForgeDirection side, int color, int value) { BundledRedstoneAware.class.setRednetInput((BundledRedstoneAware)this, side, color, value); } public void updateInput(int[][] inputs, ForgeDirection side, int color, int newValue) { BundledRedstoneAware.class.updateInput((BundledRedstoneAware)this, inputs, side, color, newValue); } public int[][] getBundledOutput() { return BundledRedstoneAware.class.getBundledOutput((BundledRedstoneAware)this); } public int[] getBundledOutput(ForgeDirection side) { return BundledRedstoneAware.class.getBundledOutput((BundledRedstoneAware)this, side); } public int getBundledOutput(ForgeDirection side, int color) { return BundledRedstoneAware.class.getBundledOutput((BundledRedstoneAware)this, side, color); } public void notifyChangedSide(ForgeDirection side) { BundledRedstoneAware.class.notifyChangedSide((BundledRedstoneAware)this, side); } public boolean setBundledOutput(ForgeDirection side, int color, int value) { return BundledRedstoneAware.class.setBundledOutput((BundledRedstoneAware)this, side, color, value); } public boolean setBundledOutput(ForgeDirection side, Map values) { return BundledRedstoneAware.class.setBundledOutput((BundledRedstoneAware)this, side, values); } public boolean setBundledOutput(Map values) { return BundledRedstoneAware.class.setBundledOutput((BundledRedstoneAware)this, values); } public void updateRedstoneInput(ForgeDirection side) { BundledRedstoneAware.class.updateRedstoneInput((BundledRedstoneAware)this, side); } public void onRedstoneOutputEnabledChanged() { BundledRedstoneAware.class.onRedstoneOutputEnabledChanged((BundledRedstoneAware)this); } @Method(modid = "RedLogic") public byte[] getBundledCableStrength(int blockFace, int toDirection) { return BundledRedstoneAware.class.getBundledCableStrength((BundledRedstoneAware)this, blockFace, toDirection); } @Method(modid = "RedLogic") public void onBundledInputChanged() { BundledRedstoneAware.class.onBundledInputChanged((BundledRedstoneAware)this); } @Method(modid = "ProjRed|Transmission") public boolean canConnectBundled(int side) { return BundledRedstoneAware.class.canConnectBundled((BundledRedstoneAware)this, side); } @Method(modid = "ProjRed|Transmission") public byte[] getBundledSignal(int side) { return BundledRedstoneAware.class.getBundledSignal((BundledRedstoneAware)this, side); } public int[] _input() { return this._input; } public int[] _output() { return this._output; } public boolean _isOutputEnabled() { return this._isOutputEnabled; } public void _isOutputEnabled_$eq(boolean x$1) { this._isOutputEnabled = x$1; } public boolean shouldUpdateInput() { return this.shouldUpdateInput; } public void shouldUpdateInput_$eq(boolean x$1) { this.shouldUpdateInput = x$1; } public void li$cil$oc$common$tileentity$traits$RedstoneAware$_setter_$_input_$eq(int[] x$1) { this._input = x$1; } public void li$cil$oc$common$tileentity$traits$RedstoneAware$_setter_$_output_$eq(int[] x$1) { this._output = x$1; } public boolean isOutputEnabled() { return RedstoneAware.class.isOutputEnabled((RedstoneAware)this); } public Option<Object> getObjectFuzzy(Map map, int key) { return RedstoneAware.class.getObjectFuzzy((RedstoneAware)this, map, key); } public Option<Object> valueToInt(Object value) { return RedstoneAware.class.valueToInt((RedstoneAware)this, value); } public int[] getInput() { return RedstoneAware.class.getInput((RedstoneAware)this); } public int getInput(ForgeDirection side) { return RedstoneAware.class.getInput((RedstoneAware)this, side); } public void setInput(ForgeDirection side, int newInput) { RedstoneAware.class.setInput((RedstoneAware)this, side, newInput); } public void setInput(int[] values) { RedstoneAware.class.setInput((RedstoneAware)this, values); } public int maxInput() { return RedstoneAware.class.maxInput((RedstoneAware)this); } public int[] getOutput() { return RedstoneAware.class.getOutput((RedstoneAware)this); } public int getOutput(ForgeDirection side) { return RedstoneAware.class.getOutput((RedstoneAware)this, side); } public boolean setOutput(ForgeDirection side, int value) { return RedstoneAware.class.setOutput((RedstoneAware)this, side, value); } public boolean setOutput(Map values) { return RedstoneAware.class.setOutput((RedstoneAware)this, values); } public void checkRedstoneInputChanged() { RedstoneAware.class.checkRedstoneInputChanged((RedstoneAware)this); } public void func_145829_t() { RedstoneAware.class.validate((RedstoneAware)this); } public void onRedstoneOutputChanged(ForgeDirection side) { RedstoneAware.class.onRedstoneOutputChanged((RedstoneAware)this, side); } @Method(modid = "RedLogic") public boolean connects(IWire wire, int blockFace, int fromDirection) { return RedstoneAware.class.connects((RedstoneAware)this, wire, blockFace, fromDirection); } @Method(modid = "RedLogic") public boolean connectsAroundCorner(IWire wire, int blockFace, int fromDirection) { return RedstoneAware.class.connectsAroundCorner((RedstoneAware)this, wire, blockFace, fromDirection); } @Method(modid = "RedLogic") public short getEmittedSignalStrength(int blockFace, int toDirection) { return RedstoneAware.class.getEmittedSignalStrength((RedstoneAware)this, blockFace, toDirection); } @Method(modid = "RedLogic") public void onRedstoneInputChanged() { RedstoneAware.class.onRedstoneInputChanged((RedstoneAware)this); } public ForgeDirection[] li$cil$oc$common$tileentity$traits$Rotatable$$pitch2Direction() { return this.li$cil$oc$common$tileentity$traits$Rotatable$$pitch2Direction; } public ForgeDirection[] li$cil$oc$common$tileentity$traits$Rotatable$$yaw2Direction() { return this.li$cil$oc$common$tileentity$traits$Rotatable$$yaw2Direction; } public ForgeDirection li$cil$oc$common$tileentity$traits$Rotatable$$_pitch() { return this.li$cil$oc$common$tileentity$traits$Rotatable$$_pitch; } public void li$cil$oc$common$tileentity$traits$Rotatable$$_pitch_$eq(ForgeDirection x$1) { this.li$cil$oc$common$tileentity$traits$Rotatable$$_pitch = x$1; } public ForgeDirection li$cil$oc$common$tileentity$traits$Rotatable$$_yaw() { return this.li$cil$oc$common$tileentity$traits$Rotatable$$_yaw; } public void li$cil$oc$common$tileentity$traits$Rotatable$$_yaw_$eq(ForgeDirection x$1) { this.li$cil$oc$common$tileentity$traits$Rotatable$$_yaw = x$1; } public void li$cil$oc$common$tileentity$traits$Rotatable$_setter_$li$cil$oc$common$tileentity$traits$Rotatable$$pitch2Direction_$eq(ForgeDirection[] x$1) { this.li$cil$oc$common$tileentity$traits$Rotatable$$pitch2Direction = x$1; } public void li$cil$oc$common$tileentity$traits$Rotatable$_setter_$li$cil$oc$common$tileentity$traits$Rotatable$$yaw2Direction_$eq(ForgeDirection[] x$1) { this.li$cil$oc$common$tileentity$traits$Rotatable$$yaw2Direction = x$1; } public ForgeDirection pitch() { return Rotatable.class.pitch((Rotatable)this); } public void pitch_$eq(ForgeDirection value) { Rotatable.class.pitch_$eq((Rotatable)this, value); } public ForgeDirection yaw() { return Rotatable.class.yaw((Rotatable)this); } public void yaw_$eq(ForgeDirection value) { Rotatable.class.yaw_$eq((Rotatable)this, value); } public boolean setFromEntityPitchAndYaw(Entity entity) { return Rotatable.class.setFromEntityPitchAndYaw((Rotatable)this, entity); } public boolean setFromFacing(ForgeDirection value) { return Rotatable.class.setFromFacing((Rotatable)this, value); } public boolean invertRotation() { return Rotatable.class.invertRotation((Rotatable)this); } public ForgeDirection facing() { return Rotatable.class.facing((Rotatable)this); } public boolean rotate(ForgeDirection axis) { return Rotatable.class.rotate((Rotatable)this, axis); } public ForgeDirection toLocal(ForgeDirection value) { return Rotatable.class.toLocal((Rotatable)this, value); } public ForgeDirection toGlobal(ForgeDirection value) { return Rotatable.class.toGlobal((Rotatable)this, value); } public ForgeDirection[] validFacings() { return Rotatable.class.validFacings((Rotatable)this); } private ArrayBuffer li$cil$oc$common$tileentity$traits$ComponentInventory$$pendingRemovalsActual$lzycompute() { synchronized (this) { if ((byte)(this.bitmap$0 & 0x8) == 0) { this.li$cil$oc$common$tileentity$traits$ComponentInventory$$pendingRemovalsActual = ComponentInventory.class.li$cil$oc$common$tileentity$traits$ComponentInventory$$pendingRemovalsActual((ComponentInventory)this); this.bitmap$0 = (byte)(this.bitmap$0 | 0x8); }  return this.li$cil$oc$common$tileentity$traits$ComponentInventory$$pendingRemovalsActual; }  } public ArrayBuffer<Option<ItemStack>> li$cil$oc$common$tileentity$traits$ComponentInventory$$pendingRemovalsActual() { return ((byte)(this.bitmap$0 & 0x8) == 0) ? li$cil$oc$common$tileentity$traits$ComponentInventory$$pendingRemovalsActual$lzycompute() : this.li$cil$oc$common$tileentity$traits$ComponentInventory$$pendingRemovalsActual; } private ArrayBuffer li$cil$oc$common$tileentity$traits$ComponentInventory$$pendingAddsActual$lzycompute() { synchronized (this) { if ((byte)(this.bitmap$0 & 0x10) == 0) { this.li$cil$oc$common$tileentity$traits$ComponentInventory$$pendingAddsActual = ComponentInventory.class.li$cil$oc$common$tileentity$traits$ComponentInventory$$pendingAddsActual((ComponentInventory)this); this.bitmap$0 = (byte)(this.bitmap$0 | 0x10); }  return this.li$cil$oc$common$tileentity$traits$ComponentInventory$$pendingAddsActual; }  } public ArrayBuffer<Option<ItemStack>> li$cil$oc$common$tileentity$traits$ComponentInventory$$pendingAddsActual() { return ((byte)(this.bitmap$0 & 0x10) == 0) ? li$cil$oc$common$tileentity$traits$ComponentInventory$$pendingAddsActual$lzycompute() : this.li$cil$oc$common$tileentity$traits$ComponentInventory$$pendingAddsActual; } public boolean li$cil$oc$common$tileentity$traits$ComponentInventory$$updateScheduled() { return this.li$cil$oc$common$tileentity$traits$ComponentInventory$$updateScheduled; } public void li$cil$oc$common$tileentity$traits$ComponentInventory$$updateScheduled_$eq(boolean x$1) { this.li$cil$oc$common$tileentity$traits$ComponentInventory$$updateScheduled = x$1; } public ComponentInventory host() { return ComponentInventory.class.host((ComponentInventory)this); } public ArrayBuffer<Option<ItemStack>> pendingRemovals() { return ComponentInventory.class.pendingRemovals((ComponentInventory)this); } public ArrayBuffer<Option<ItemStack>> pendingAdds() { return ComponentInventory.class.pendingAdds((ComponentInventory)this); } public void save(ManagedEnvironment component, Item driver, ItemStack stack) { ComponentInventory.class.save((ComponentInventory)this, component, driver, stack); } public void onConnect(Node node) { ComponentInventory.class.onConnect((ComponentInventory)this, node); } public Option<ManagedEnvironment>[] li$cil$oc$common$inventory$ComponentInventory$$_components() { return this.li$cil$oc$common$inventory$ComponentInventory$$_components; } @TraitSetter public void li$cil$oc$common$inventory$ComponentInventory$$_components_$eq(Option[] x$1) { this.li$cil$oc$common$inventory$ComponentInventory$$_components = (Option<ManagedEnvironment>[])x$1; } public boolean isSizeInventoryReady() { return this.isSizeInventoryReady; } @TraitSetter public void isSizeInventoryReady_$eq(boolean x$1) { this.isSizeInventoryReady = x$1; } public ArrayBuffer<ManagedEnvironment> updatingComponents() { return this.updatingComponents; } public void li$cil$oc$common$inventory$ComponentInventory$_setter_$updatingComponents_$eq(ArrayBuffer<ManagedEnvironment> x$1) { this.updatingComponents = x$1; } public Option<ManagedEnvironment>[] components() { return (Option<ManagedEnvironment>[])ComponentInventory.class.components((ComponentInventory)this); } public void updateComponents() { ComponentInventory.class.updateComponents((ComponentInventory)this); } public void connectComponents() { ComponentInventory.class.connectComponents((ComponentInventory)this); } public void disconnectComponents() { ComponentInventory.class.disconnectComponents((ComponentInventory)this); } public void save(NBTTagCompound nbt) { ComponentInventory.class.save((ComponentInventory)this, nbt); } public void saveComponents() { ComponentInventory.class.saveComponents((ComponentInventory)this); } public NBTTagCompound dataTag(Item driver, ItemStack stack) { return ComponentInventory.class.dataTag((ComponentInventory)this, driver, stack); } public void applyLifecycleState(Object component, Lifecycle.LifecycleState state) { ComponentInventory.class.applyLifecycleState((ComponentInventory)this, component, state); } private Option[] li$cil$oc$common$tileentity$traits$Inventory$$inventory$lzycompute() { synchronized (this) { if ((byte)(this.bitmap$0 & 0x20) == 0) { this.li$cil$oc$common$tileentity$traits$Inventory$$inventory = (Option<ItemStack>[])Inventory.class.li$cil$oc$common$tileentity$traits$Inventory$$inventory((Inventory)this); this.bitmap$0 = (byte)(this.bitmap$0 | 0x20); }  return (Option[])this.li$cil$oc$common$tileentity$traits$Inventory$$inventory; }  } public Option<ItemStack>[] li$cil$oc$common$tileentity$traits$Inventory$$inventory() { return ((byte)(this.bitmap$0 & 0x20) == 0) ? (Option<ItemStack>[])li$cil$oc$common$tileentity$traits$Inventory$$inventory$lzycompute() : this.li$cil$oc$common$tileentity$traits$Inventory$$inventory; } public Option<ItemStack>[] items() { return (Option<ItemStack>[])Inventory.class.items((Inventory)this); } public EntityItem spawnStackInWorld(ItemStack stack, Option direction) { return Inventory.class.spawnStackInWorld((Inventory)this, stack, direction); } public int dropSlot$default$2() { return Inventory.class.dropSlot$default$2((Inventory)this); } public Option<ForgeDirection> dropSlot$default$3() { return Inventory.class.dropSlot$default$3((Inventory)this); } public Option<ForgeDirection> spawnStackInWorld$default$2() { return Inventory.class.spawnStackInWorld$default$2((Inventory)this); } public void updateItems(int slot, ItemStack stack) { Inventory.class.updateItems((Inventory)this, slot, stack); } public String func_145825_b() { return Inventory.class.getInventoryName((Inventory)this); } public String inventoryName() { return Inventory.class.inventoryName((Inventory)this); } public void load(NBTTagCompound nbt) { Inventory.class.load((Inventory)this, nbt); } public boolean func_145818_k_() { return SimpleInventory.class.hasCustomInventoryName((SimpleInventory)this); } public int getInventoryStackRequired() { return SimpleInventory.class.getInventoryStackRequired((SimpleInventory)this); } public void func_70295_k_() { SimpleInventory.class.openInventory((SimpleInventory)this); } public void func_70305_f() { SimpleInventory.class.closeInventory((SimpleInventory)this); } public ItemStack func_70298_a(int slot, int amount) { return SimpleInventory.class.decrStackSize((SimpleInventory)this, slot, amount); } public ItemStack func_70304_b(int slot) { return SimpleInventory.class.getStackInSlotOnClosing((SimpleInventory)this, slot); } public boolean isChangeScheduled() { return this.isChangeScheduled; } public void isChangeScheduled_$eq(boolean x$1) { this.isChangeScheduled = x$1; } public boolean moving() { return this.moving; } public void moving_$eq(boolean x$1) { this.moving = x$1; } public double xPosition() { return Environment.class.xPosition((Environment)this); } public double yPosition() { return Environment.class.yPosition((Environment)this); } public double zPosition() { return Environment.class.zPosition((Environment)this); } public void markChanged() { Environment.class.markChanged((Environment)this); } public boolean isConnected() { return Environment.class.isConnected((Environment)this); } public void onMessage(Message message) { Environment.class.onMessage((Environment)this, message); } @Method(modid = "appliedenergistics2") public boolean prepareToMove() { return Environment.class.prepareToMove((Environment)this); } @Method(modid = "appliedenergistics2") public void doneMoving() { Environment.class.doneMoving((Environment)this); } public Object[] result(Seq args) { return Environment.class.result((Environment)this, args); } public World world() { return TileEntity.class.world((TileEntity)this); } public int x() { return TileEntity.class.x((TileEntity)this); } public int y() { return TileEntity.class.y((TileEntity)this); } public int z() { return TileEntity.class.z((TileEntity)this); } public BlockPosition position() { return TileEntity.class.position((TileEntity)this); } public Block block() { return TileEntity.class.block((TileEntity)this); } public boolean isClient() { return TileEntity.class.isClient((TileEntity)this); } public boolean isServer() { return TileEntity.class.isServer((TileEntity)this); } public void func_145843_s() { TileEntity.class.invalidate((TileEntity)this); } public void onChunkUnload() { TileEntity.class.onChunkUnload((TileEntity)this); } public void func_145839_a(NBTTagCompound nbt) { TileEntity.class.readFromNBT((TileEntity)this, nbt); } public void func_145841_b(NBTTagCompound nbt) { TileEntity.class.writeToNBT((TileEntity)this, nbt); } public Packet func_145844_m() { return TileEntity.class.getDescriptionPacket((TileEntity)this); } public void onDataPacket(NetworkManager manager, S35PacketUpdateTileEntity packet) { TileEntity.class.onDataPacket((TileEntity)this, manager, packet); } public Robot() { TileEntity.class.$init$((TileEntity)this); Environment.class.$init$((Environment)this); SimpleInventory.class.$init$((SimpleInventory)this); Inventory.class.$init$((Inventory)this); Inventory.class.$init$((Inventory)this); ComponentInventory.class.$init$((ComponentInventory)this); ComponentInventory.class.$init$((ComponentInventory)this); RotationAware.class.$init$((RotationAware)this); Rotatable.class.$init$((Rotatable)this); RedstoneAware.class.$init$((RedstoneAware)this); BundledRedstoneAware.class.$init$((BundledRedstoneAware)this); AbstractBusAware.class.$init$((AbstractBusAware)this); StateAware.class.$init$((StateAware)this); Computer.class.$init$(this); PowerInformation.class.$init$(this);
/*     */ 
/*     */     
/*  54 */     this.info = new RobotData();
/*     */     
/*  56 */     this.bot = isServer() ? new li.cil.oc.server.component.Robot(this) : null;
/*     */     
/*  58 */     if (isServer()) {
/*  59 */       machine().setCostPerTick(Settings$.MODULE$.get().robotCost());
/*     */     }
/*     */ 
/*     */ 
/*     */ 
/*     */ 
/*     */ 
/*     */ 
/*     */     
/*  68 */     this.equipmentInventory = new Robot$$anon$1(this);
/*     */ 
/*     */ 
/*     */ 
/*     */ 
/*     */ 
/*     */     
/*  75 */     this.mainInventory = new Robot$$anon$2(this);
/*     */ 
/*     */ 
/*     */ 
/*     */ 
/*     */ 
/*     */ 
/*     */     
/*  83 */     this.actualInventorySize = 100;
/*     */ 
/*     */ 
/*     */     
/*  87 */     this.inventorySize = -1;
/*     */     
/*  89 */     this.selectedSlot = 0;
/*     */ 
/*     */ 
/*     */ 
/*     */ 
/*     */ 
/*     */ 
/*     */ 
/*     */     
/*  98 */     this.tank = new Robot$$anon$3(this);
/*     */ 
/*     */ 
/*     */ 
/*     */ 
/*     */     
/* 104 */     this.selectedTank = 0;
/*     */ 
/*     */ 
/*     */ 
/*     */     
/* 109 */     this.renderingErrored = false;
/*     */ 
/*     */ 
/*     */ 
/*     */ 
/*     */ 
/*     */ 
/*     */ 
/*     */ 
/*     */ 
/*     */ 
/*     */ 
/*     */ 
/*     */ 
/*     */ 
/*     */ 
/*     */ 
/*     */ 
/*     */ 
/*     */ 
/*     */ 
/*     */ 
/*     */ 
/*     */ 
/*     */ 
/*     */ 
/*     */ 
/*     */ 
/*     */ 
/*     */ 
/*     */ 
/*     */ 
/*     */ 
/*     */ 
/*     */ 
/*     */ 
/*     */ 
/*     */ 
/*     */ 
/*     */     
/* 149 */     this.globalBuffer = 0.0D; this.globalBufferSize = 0.0D;
/*     */     
/* 151 */     this.maxComponents = 32;
/*     */     
/* 153 */     this.ownerName = Settings$.MODULE$.get().fakePlayerName();
/*     */     
/* 155 */     this.ownerUUID = Settings$.MODULE$.get().fakePlayerProfile().getId();
/*     */     
/* 157 */     this.animationTicksLeft = 0;
/*     */     
/* 159 */     this.animationTicksTotal = 0;
/*     */     
/* 161 */     this.moveFromX = Integer.MAX_VALUE; this.moveFromY = Integer.MAX_VALUE; this.moveFromZ = Integer.MAX_VALUE;
/*     */     
/* 163 */     this.swingingTool = false;
/*     */     
/* 165 */     this.turnAxis = 0;
/*     */     
/* 167 */     this.appliedToolEnchantments = false;
/*     */ 
/*     */ 
/*     */ 
/*     */ 
/*     */ 
/*     */ 
/*     */ 
/*     */ 
/*     */ 
/*     */ 
/*     */ 
/*     */ 
/*     */ 
/*     */ 
/*     */ 
/*     */ 
/*     */ 
/*     */ 
/*     */ 
/*     */ 
/*     */ 
/*     */ 
/*     */ 
/*     */ 
/*     */ 
/*     */ 
/*     */ 
/*     */ 
/*     */ 
/*     */ 
/*     */ 
/*     */ 
/*     */ 
/*     */ 
/*     */ 
/*     */ 
/*     */ 
/*     */ 
/*     */ 
/*     */ 
/*     */ 
/*     */ 
/*     */ 
/*     */ 
/*     */ 
/*     */ 
/*     */ 
/*     */ 
/*     */ 
/*     */ 
/*     */ 
/*     */ 
/*     */ 
/*     */ 
/*     */ 
/*     */ 
/*     */ 
/*     */ 
/*     */ 
/*     */ 
/*     */ 
/*     */ 
/*     */ 
/*     */ 
/*     */ 
/*     */ 
/*     */ 
/*     */ 
/*     */ 
/*     */ 
/*     */ 
/*     */ 
/*     */ 
/*     */ 
/*     */ 
/*     */ 
/*     */ 
/*     */ 
/*     */ 
/*     */ 
/*     */ 
/*     */ 
/*     */ 
/*     */ 
/*     */ 
/*     */ 
/*     */ 
/*     */ 
/*     */ 
/*     */ 
/*     */ 
/*     */ 
/*     */ 
/*     */ 
/*     */ 
/*     */ 
/*     */ 
/*     */ 
/*     */ 
/*     */ 
/*     */ 
/*     */ 
/*     */ 
/*     */ 
/*     */ 
/*     */ 
/*     */ 
/*     */ 
/*     */ 
/*     */ 
/*     */ 
/*     */ 
/*     */ 
/*     */ 
/*     */ 
/*     */ 
/*     */ 
/*     */ 
/*     */ 
/*     */ 
/*     */ 
/*     */ 
/*     */ 
/*     */ 
/*     */ 
/*     */ 
/*     */ 
/*     */ 
/*     */ 
/*     */ 
/*     */ 
/*     */ 
/*     */ 
/*     */ 
/*     */ 
/*     */ 
/*     */ 
/*     */ 
/*     */ 
/*     */ 
/*     */ 
/*     */ 
/*     */ 
/*     */ 
/*     */ 
/*     */ 
/*     */ 
/*     */ 
/*     */ 
/*     */ 
/*     */ 
/*     */ 
/*     */ 
/*     */ 
/*     */ 
/*     */ 
/*     */ 
/*     */ 
/*     */ 
/*     */ 
/*     */ 
/*     */ 
/*     */ 
/*     */ 
/*     */ 
/*     */ 
/*     */ 
/*     */ 
/*     */ 
/*     */ 
/*     */ 
/*     */ 
/*     */ 
/*     */ 
/*     */ 
/*     */ 
/*     */ 
/*     */ 
/*     */ 
/*     */ 
/*     */ 
/*     */ 
/*     */ 
/*     */ 
/*     */ 
/*     */ 
/*     */ 
/*     */ 
/*     */ 
/*     */ 
/*     */ 
/*     */ 
/*     */ 
/*     */ 
/*     */ 
/*     */ 
/*     */ 
/*     */ 
/*     */ 
/*     */ 
/*     */ 
/*     */ 
/*     */ 
/*     */ 
/*     */ 
/*     */ 
/*     */ 
/*     */ 
/*     */ 
/*     */ 
/*     */ 
/*     */ 
/*     */ 
/*     */ 
/*     */ 
/*     */ 
/*     */ 
/*     */ 
/*     */ 
/*     */ 
/*     */ 
/*     */ 
/*     */ 
/*     */ 
/*     */ 
/*     */ 
/*     */ 
/*     */ 
/*     */ 
/*     */ 
/*     */ 
/*     */ 
/*     */ 
/*     */ 
/*     */ 
/*     */ 
/*     */ 
/*     */ 
/*     */ 
/*     */ 
/*     */ 
/*     */ 
/*     */ 
/*     */ 
/*     */ 
/*     */ 
/*     */ 
/*     */ 
/*     */ 
/*     */ 
/*     */ 
/*     */ 
/*     */ 
/*     */ 
/*     */ 
/*     */ 
/*     */ 
/*     */ 
/*     */ 
/*     */ 
/*     */ 
/*     */ 
/*     */ 
/*     */ 
/*     */ 
/*     */ 
/*     */ 
/*     */ 
/*     */ 
/*     */ 
/*     */ 
/*     */ 
/*     */ 
/*     */ 
/*     */ 
/*     */ 
/*     */ 
/*     */ 
/*     */ 
/*     */ 
/*     */ 
/*     */ 
/*     */ 
/*     */ 
/*     */ 
/*     */ 
/*     */ 
/*     */ 
/*     */ 
/*     */ 
/*     */ 
/*     */ 
/*     */ 
/*     */ 
/*     */ 
/*     */ 
/*     */ 
/*     */ 
/*     */ 
/*     */ 
/*     */ 
/*     */ 
/*     */ 
/*     */ 
/*     */ 
/*     */ 
/*     */ 
/*     */ 
/*     */ 
/*     */ 
/*     */ 
/*     */ 
/*     */ 
/*     */ 
/*     */ 
/*     */ 
/*     */ 
/*     */ 
/*     */ 
/*     */ 
/*     */ 
/*     */ 
/*     */ 
/*     */ 
/*     */ 
/*     */ 
/*     */ 
/*     */ 
/*     */ 
/*     */ 
/*     */ 
/*     */ 
/*     */ 
/*     */ 
/*     */ 
/*     */ 
/*     */ 
/*     */ 
/*     */ 
/*     */ 
/*     */ 
/*     */ 
/*     */ 
/*     */ 
/*     */ 
/*     */ 
/*     */ 
/*     */ 
/*     */ 
/*     */ 
/*     */ 
/*     */ 
/*     */ 
/*     */ 
/*     */ 
/*     */ 
/*     */ 
/*     */ 
/*     */ 
/*     */ 
/*     */ 
/*     */ 
/*     */ 
/*     */ 
/*     */ 
/*     */ 
/*     */ 
/*     */ 
/*     */ 
/*     */ 
/*     */ 
/*     */ 
/*     */ 
/*     */ 
/*     */ 
/*     */ 
/*     */ 
/*     */ 
/*     */ 
/*     */ 
/*     */ 
/*     */ 
/*     */ 
/*     */ 
/*     */ 
/*     */ 
/*     */ 
/*     */ 
/*     */ 
/*     */ 
/*     */ 
/*     */ 
/*     */ 
/*     */ 
/*     */ 
/*     */ 
/*     */ 
/*     */ 
/*     */ 
/*     */ 
/*     */ 
/*     */ 
/*     */ 
/*     */ 
/*     */ 
/*     */ 
/*     */ 
/*     */ 
/*     */ 
/*     */ 
/*     */ 
/*     */ 
/*     */ 
/*     */ 
/*     */ 
/*     */ 
/*     */ 
/*     */ 
/*     */ 
/*     */ 
/*     */ 
/*     */ 
/*     */ 
/*     */ 
/*     */ 
/*     */ 
/*     */ 
/*     */ 
/*     */ 
/*     */ 
/*     */ 
/*     */ 
/*     */ 
/*     */ 
/*     */ 
/*     */ 
/*     */ 
/*     */ 
/*     */ 
/*     */ 
/*     */ 
/*     */ 
/*     */ 
/*     */ 
/*     */ 
/*     */ 
/*     */ 
/*     */ 
/*     */ 
/*     */ 
/*     */ 
/*     */ 
/*     */ 
/*     */ 
/*     */ 
/*     */ 
/*     */ 
/*     */ 
/*     */ 
/*     */ 
/*     */ 
/*     */ 
/*     */ 
/*     */ 
/*     */ 
/*     */ 
/*     */ 
/*     */ 
/*     */ 
/*     */ 
/*     */ 
/*     */ 
/*     */ 
/*     */ 
/*     */ 
/*     */     
/* 644 */     this.updatingInventorySize = false;
/*     */ 
/*     */ 
/*     */ 
/*     */ 
/*     */ 
/*     */ 
/*     */ 
/*     */ 
/*     */ 
/*     */ 
/*     */ 
/*     */ 
/*     */ 
/*     */ 
/*     */ 
/*     */ 
/*     */ 
/*     */ 
/*     */ 
/*     */ 
/*     */ 
/*     */ 
/*     */ 
/*     */ 
/*     */ 
/*     */ 
/*     */ 
/*     */ 
/*     */ 
/*     */ 
/*     */ 
/*     */ 
/*     */ 
/*     */ 
/*     */     
/* 680 */     this.getSizeInventory = actualInventorySize(); } public RobotProxy proxy() { return this.proxy; } public void proxy_$eq(RobotProxy x$1) { this.proxy = x$1; } public RobotData info() { return this.info; } public li.cil.oc.server.component.Robot bot() { return this.bot; } public int tier() { return info().tier(); } public boolean isCreative() { return (tier() == 3); } public InventoryProxy equipmentInventory() { return this.equipmentInventory; } public final class Robot$$anon$1 implements InventoryProxy { public int offset() { return InventoryProxy.class.offset(this); } public int func_70297_j_() { return InventoryProxy.class.getInventoryStackLimit(this); } public String func_145825_b() { return InventoryProxy.class.getInventoryName(this); } public boolean func_145818_k_() { return InventoryProxy.class.hasCustomInventoryName(this); } public boolean func_70300_a(EntityPlayer player) { return InventoryProxy.class.isUseableByPlayer(this, player); } public boolean func_94041_b(int slot, ItemStack stack) { return InventoryProxy.class.isItemValidForSlot(this, slot, stack); } public ItemStack func_70301_a(int slot) { return InventoryProxy.class.getStackInSlot(this, slot); } public ItemStack func_70298_a(int slot, int amount) { return InventoryProxy.class.decrStackSize(this, slot, amount); } public ItemStack func_70304_b(int slot) { return InventoryProxy.class.getStackInSlotOnClosing(this, slot); } public void func_70299_a(int slot, ItemStack stack) { InventoryProxy.class.setInventorySlotContents(this, slot, stack); } public void func_70296_d() { InventoryProxy.class.markDirty(this); } public void func_70295_k_() { InventoryProxy.class.openInventory(this); } public void func_70305_f() { InventoryProxy.class.closeInventory(this); } public Robot$$anon$1(Robot $outer) { InventoryProxy.class.$init$(this); } public Robot inventory() { return this.$outer; } public int func_70302_i_() { return 4; } } public InventoryProxy mainInventory() { return this.mainInventory; } public final class Robot$$anon$2 implements InventoryProxy { public int func_70297_j_() { return InventoryProxy.class.getInventoryStackLimit(this); } public String func_145825_b() { return InventoryProxy.class.getInventoryName(this); } public boolean func_145818_k_() { return InventoryProxy.class.hasCustomInventoryName(this); } public boolean func_70300_a(EntityPlayer player) { return InventoryProxy.class.isUseableByPlayer(this, player); } public boolean func_94041_b(int slot, ItemStack stack) { return InventoryProxy.class.isItemValidForSlot(this, slot, stack); } public ItemStack func_70301_a(int slot) { return InventoryProxy.class.getStackInSlot(this, slot); } public ItemStack func_70298_a(int slot, int amount) { return InventoryProxy.class.decrStackSize(this, slot, amount); } public ItemStack func_70304_b(int slot) { return InventoryProxy.class.getStackInSlotOnClosing(this, slot); } public void func_70299_a(int slot, ItemStack stack) { InventoryProxy.class.setInventorySlotContents(this, slot, stack); } public void func_70296_d() { InventoryProxy.class.markDirty(this); } public void func_70295_k_() { InventoryProxy.class.openInventory(this); } public void func_70305_f() { InventoryProxy.class.closeInventory(this); } public Robot$$anon$2(Robot $outer) { InventoryProxy.class.$init$(this); } public Robot inventory() { return this.$outer; } public int func_70302_i_() { return this.$outer.inventorySize(); } public int offset() { return this.$outer.equipmentInventory().func_70302_i_(); } } public int actualInventorySize() { return this.actualInventorySize; } public int maxInventorySize() { return actualInventorySize() - equipmentInventory().func_70302_i_() - componentCount(); } public int inventorySize() { return this.inventorySize; } public void inventorySize_$eq(int x$1) { this.inventorySize = x$1; } public int selectedSlot() { return this.selectedSlot; } public void selectedSlot_$eq(int x$1) { this.selectedSlot = x$1; } public void setSelectedSlot(int index) { selectedSlot_$eq(RichInt$.MODULE$.min$extension(Predef$.MODULE$.intWrapper(RichInt$.MODULE$.max$extension(Predef$.MODULE$.intWrapper(index), 0)), mainInventory().func_70302_i_() - 1)); if (world() != null) PacketSender$.MODULE$.sendRobotSelectedSlotChange(this);  } public MultiTank tank() { return this.tank; } public final class Robot$$anon$3 implements MultiTank { public Robot$$anon$3(Robot $outer) {} public int tankCount() { return this.$outer.tankCount(); } public ManagedEnvironment getFluidTank(int index) { return this.$outer.getFluidTank(index); } } public int selectedTank() { return this.selectedTank; } public void selectedTank_$eq(int x$1) { this.selectedTank = x$1; } public void setSelectedTank(int index) { selectedTank_$eq(index); } public boolean renderingErrored() { return this.renderingErrored; } public void renderingErrored_$eq(boolean x$1) { this.renderingErrored = x$1; } public int componentCount() { return (info().components()).length; } public Environment getComponentInSlot(int index) { return (Environment)components()[index].orNull(Predef$.MODULE$.$conforms()); } public Player player() { Player$.MODULE$.updatePositionAndRotation(li$cil$oc$common$tileentity$Robot$$player_(), facing(), facing()); Player$.MODULE$.setInventoryPlayerItems(li$cil$oc$common$tileentity$Robot$$player_()); return li$cil$oc$common$tileentity$Robot$$player_(); } public void synchronizeSlot(int slot) { if (slot >= 0 && slot < func_70302_i_()) synchronized (this) { ItemStack stack = func_70301_a(slot); Option<ManagedEnvironment> option = components()[slot]; if (option instanceof Some) { Some some = (Some)option; ManagedEnvironment component = (ManagedEnvironment)some.x(); save(component, Driver.driverFor(stack, getClass()), stack); BoxedUnit boxedUnit = BoxedUnit.UNIT; } else { BoxedUnit boxedUnit = BoxedUnit.UNIT; }  PacketSender$.MODULE$.sendRobotInventory(this, slot, stack); return; }   } public Range.Inclusive containerSlots() { return RichInt$.MODULE$.to$extension0(Predef$.MODULE$.intWrapper(1), (info().containers()).length); } public Range componentSlots() { return RichInt$.MODULE$.until$extension0(Predef$.MODULE$.intWrapper(func_70302_i_() - componentCount()), func_70302_i_()); } public Range inventorySlots() { return RichInt$.MODULE$.until$extension0(Predef$.MODULE$.intWrapper(equipmentInventory().func_70302_i_()), equipmentInventory().func_70302_i_() + mainInventory().func_70302_i_()); } public void setLightColor(int value) { info().lightColor_$eq(value); PacketSender$.MODULE$.sendRobotLightChange(this); } public boolean shouldAnimate() { return isRunning(); } public Node node() { return isServer() ? machine().node() : null; } public double globalBuffer() { return this.globalBuffer; } public void globalBuffer_$eq(double x$1) { this.globalBuffer = x$1; } public double globalBufferSize() { return this.globalBufferSize; } public void globalBufferSize_$eq(double x$1) { this.globalBufferSize = x$1; } public int maxComponents() { return this.maxComponents; } public String ownerName() { return this.ownerName; } public void ownerName_$eq(String x$1) { this.ownerName = x$1; } public UUID ownerUUID() { return this.ownerUUID; } public void ownerUUID_$eq(UUID x$1) { this.ownerUUID = x$1; } public int animationTicksLeft() { return this.animationTicksLeft; } public void animationTicksLeft_$eq(int x$1) { this.animationTicksLeft = x$1; } public int animationTicksTotal() { return this.animationTicksTotal; } public void animationTicksTotal_$eq(int x$1) { this.animationTicksTotal = x$1; } public int moveFromX() { return this.moveFromX; } public void moveFromX_$eq(int x$1) { this.moveFromX = x$1; } public int moveFromY() { return this.moveFromY; } public void moveFromY_$eq(int x$1) { this.moveFromY = x$1; } public int moveFromZ() { return this.moveFromZ; } public void moveFromZ_$eq(int x$1) { this.moveFromZ = x$1; } public boolean swingingTool() { return this.swingingTool; } public void swingingTool_$eq(boolean x$1) { this.swingingTool = x$1; } public int turnAxis() { return this.turnAxis; } public void turnAxis_$eq(int x$1) { this.turnAxis = x$1; } public boolean appliedToolEnchantments() { return this.appliedToolEnchantments; } public int func_70302_i_() { return this.getSizeInventory; } public void appliedToolEnchantments_$eq(boolean x$1) { this.appliedToolEnchantments = x$1; } private Player li$cil$oc$common$tileentity$Robot$$player_$lzycompute() { synchronized (this) { if ((byte)(this.bitmap$0 & 0x1) == 0) { this.li$cil$oc$common$tileentity$Robot$$player_ = new Player((Agent)this); this.bitmap$0 = (byte)(this.bitmap$0 | 0x1); }  return this.li$cil$oc$common$tileentity$Robot$$player_; }  } public Player li$cil$oc$common$tileentity$Robot$$player_() { return ((byte)(this.bitmap$0 & 0x1) == 0) ? li$cil$oc$common$tileentity$Robot$$player_$lzycompute() : this.li$cil$oc$common$tileentity$Robot$$player_; } public String name() { return info().name(); } public void setName(String name) { info().name_$eq(name); } public Node[] onAnalyze(EntityPlayer player, int side, float hitX, float hitY, float hitZ) { player.func_145747_a((IChatComponent)Localization$Analyzer$.MODULE$.RobotOwner(ownerName())); player.func_145747_a((IChatComponent)Localization$Analyzer$.MODULE$.RobotName(li$cil$oc$common$tileentity$Robot$$player_().func_70005_c_())); MinecraftForge.EVENT_BUS.post((Event)new RobotAnalyzeEvent((Agent)this, player)); return Computer.class.onAnalyze(this, player, side, hitX, hitY, hitZ); } public boolean move(ForgeDirection direction) { // Byte code:
/*     */     //   0: getstatic li/cil/oc/util/BlockPosition$.MODULE$ : Lli/cil/oc/util/BlockPosition$;
/*     */     //   3: aload_0
/*     */     //   4: invokevirtual apply : (Lli/cil/oc/api/network/EnvironmentHost;)Lli/cil/oc/util/BlockPosition;
/*     */     //   7: astore_2
/*     */     //   8: aload_2
/*     */     //   9: aload_1
/*     */     //   10: invokevirtual offset : (Lnet/minecraftforge/common/util/ForgeDirection;)Lli/cil/oc/util/BlockPosition;
/*     */     //   13: astore_3
/*     */     //   14: getstatic li/cil/oc/util/ExtendedWorld$.MODULE$ : Lli/cil/oc/util/ExtendedWorld$;
/*     */     //   17: aload_0
/*     */     //   18: invokevirtual world : ()Lnet/minecraft/world/World;
/*     */     //   21: invokevirtual extendedWorld : (Lnet/minecraft/world/World;)Lli/cil/oc/util/ExtendedWorld$ExtendedWorld;
/*     */     //   24: aload_3
/*     */     //   25: invokevirtual blockExists : (Lli/cil/oc/util/BlockPosition;)Z
/*     */     //   28: ifeq -> 737
/*     */     //   31: aload_0
/*     */     //   32: invokevirtual isServer : ()Z
/*     */     //   35: ifeq -> 68
/*     */     //   38: new li/cil/oc/api/event/RobotMoveEvent$Pre
/*     */     //   41: dup
/*     */     //   42: aload_0
/*     */     //   43: aload_1
/*     */     //   44: invokespecial <init> : (Lli/cil/oc/api/internal/Agent;Lnet/minecraftforge/common/util/ForgeDirection;)V
/*     */     //   47: astore #4
/*     */     //   49: getstatic net/minecraftforge/common/MinecraftForge.EVENT_BUS : Lcpw/mods/fml/common/eventhandler/EventBus;
/*     */     //   52: aload #4
/*     */     //   54: invokevirtual post : (Lcpw/mods/fml/common/eventhandler/Event;)Z
/*     */     //   57: pop
/*     */     //   58: aload #4
/*     */     //   60: invokevirtual isCanceled : ()Z
/*     */     //   63: ifeq -> 68
/*     */     //   66: iconst_0
/*     */     //   67: ireturn
/*     */     //   68: ldc_w 'robot'
/*     */     //   71: invokestatic get : (Ljava/lang/String;)Lli/cil/oc/api/detail/ItemInfo;
/*     */     //   74: invokeinterface block : ()Lnet/minecraft/block/Block;
/*     */     //   79: checkcast li/cil/oc/common/block/RobotProxy
/*     */     //   82: astore #5
/*     */     //   84: ldc_w 'robotAfterimage'
/*     */     //   87: invokestatic get : (Ljava/lang/String;)Lli/cil/oc/api/detail/ItemInfo;
/*     */     //   90: invokeinterface block : ()Lnet/minecraft/block/Block;
/*     */     //   95: checkcast li/cil/oc/common/block/RobotAfterimage
/*     */     //   98: astore #6
/*     */     //   100: getstatic li/cil/oc/util/ExtendedWorld$.MODULE$ : Lli/cil/oc/util/ExtendedWorld$;
/*     */     //   103: aload_0
/*     */     //   104: invokevirtual world : ()Lnet/minecraft/world/World;
/*     */     //   107: invokevirtual extendedWorld : (Lnet/minecraft/world/World;)Lli/cil/oc/util/ExtendedWorld$ExtendedWorld;
/*     */     //   110: aload_3
/*     */     //   111: invokevirtual isAirBlock : (Lli/cil/oc/util/BlockPosition;)Z
/*     */     //   114: istore #7
/*     */     //   116: getstatic li/cil/oc/util/ExtendedWorld$.MODULE$ : Lli/cil/oc/util/ExtendedWorld$;
/*     */     //   119: aload_0
/*     */     //   120: invokevirtual world : ()Lnet/minecraft/world/World;
/*     */     //   123: invokevirtual extendedWorld : (Lnet/minecraft/world/World;)Lli/cil/oc/util/ExtendedWorld$ExtendedWorld;
/*     */     //   126: aload_3
/*     */     //   127: invokevirtual getBlock : (Lli/cil/oc/util/BlockPosition;)Lnet/minecraft/block/Block;
/*     */     //   130: astore #8
/*     */     //   132: getstatic li/cil/oc/util/ExtendedWorld$.MODULE$ : Lli/cil/oc/util/ExtendedWorld$;
/*     */     //   135: aload_0
/*     */     //   136: invokevirtual world : ()Lnet/minecraft/world/World;
/*     */     //   139: invokevirtual extendedWorld : (Lnet/minecraft/world/World;)Lli/cil/oc/util/ExtendedWorld$ExtendedWorld;
/*     */     //   142: aload_3
/*     */     //   143: invokevirtual getBlockMetadata : (Lli/cil/oc/util/BlockPosition;)I
/*     */     //   146: istore #9
/*     */     //   148: aload #5
/*     */     //   150: invokevirtual moving : ()Ljava/lang/ThreadLocal;
/*     */     //   153: new scala/Some
/*     */     //   156: dup
/*     */     //   157: aload_0
/*     */     //   158: invokespecial <init> : (Ljava/lang/Object;)V
/*     */     //   161: invokevirtual set : (Ljava/lang/Object;)V
/*     */     //   164: getstatic li/cil/oc/util/ExtendedWorld$.MODULE$ : Lli/cil/oc/util/ExtendedWorld$;
/*     */     //   167: aload_0
/*     */     //   168: invokevirtual world : ()Lnet/minecraft/world/World;
/*     */     //   171: invokevirtual extendedWorld : (Lnet/minecraft/world/World;)Lli/cil/oc/util/ExtendedWorld$ExtendedWorld;
/*     */     //   174: aload_3
/*     */     //   175: invokevirtual setBlockToAir : (Lli/cil/oc/util/BlockPosition;)Z
/*     */     //   178: pop
/*     */     //   179: getstatic li/cil/oc/util/ExtendedWorld$.MODULE$ : Lli/cil/oc/util/ExtendedWorld$;
/*     */     //   182: aload_0
/*     */     //   183: invokevirtual world : ()Lnet/minecraft/world/World;
/*     */     //   186: invokevirtual extendedWorld : (Lnet/minecraft/world/World;)Lli/cil/oc/util/ExtendedWorld$ExtendedWorld;
/*     */     //   189: aload_3
/*     */     //   190: aload #5
/*     */     //   192: iconst_0
/*     */     //   193: iconst_1
/*     */     //   194: invokevirtual setBlock : (Lli/cil/oc/util/BlockPosition;Lnet/minecraft/block/Block;II)Z
/*     */     //   197: ifeq -> 245
/*     */     //   200: getstatic li/cil/oc/util/ExtendedWorld$.MODULE$ : Lli/cil/oc/util/ExtendedWorld$;
/*     */     //   203: aload_0
/*     */     //   204: invokevirtual world : ()Lnet/minecraft/world/World;
/*     */     //   207: invokevirtual extendedWorld : (Lnet/minecraft/world/World;)Lli/cil/oc/util/ExtendedWorld$ExtendedWorld;
/*     */     //   210: aload_3
/*     */     //   211: invokevirtual getTileEntity : (Lli/cil/oc/util/BlockPosition;)Lnet/minecraft/tileentity/TileEntity;
/*     */     //   214: aload_0
/*     */     //   215: invokevirtual proxy : ()Lli/cil/oc/common/tileentity/RobotProxy;
/*     */     //   218: astore #12
/*     */     //   220: dup
/*     */     //   221: ifnonnull -> 233
/*     */     //   224: pop
/*     */     //   225: aload #12
/*     */     //   227: ifnull -> 241
/*     */     //   230: goto -> 245
/*     */     //   233: aload #12
/*     */     //   235: invokevirtual equals : (Ljava/lang/Object;)Z
/*     */     //   238: ifeq -> 245
/*     */     //   241: iconst_1
/*     */     //   242: goto -> 246
/*     */     //   245: iconst_0
/*     */     //   246: istore #11
/*     */     //   248: iload #11
/*     */     //   250: ifeq -> 669
/*     */     //   253: getstatic scala/Predef$.MODULE$ : Lscala/Predef$;
/*     */     //   256: getstatic li/cil/oc/util/BlockPosition$.MODULE$ : Lli/cil/oc/util/BlockPosition$;
/*     */     //   259: aload_0
/*     */     //   260: invokevirtual apply : (Lli/cil/oc/api/network/EnvironmentHost;)Lli/cil/oc/util/BlockPosition;
/*     */     //   263: aload_3
/*     */     //   264: astore #13
/*     */     //   266: dup
/*     */     //   267: ifnonnull -> 279
/*     */     //   270: pop
/*     */     //   271: aload #13
/*     */     //   273: ifnull -> 287
/*     */     //   276: goto -> 291
/*     */     //   279: aload #13
/*     */     //   281: invokevirtual equals : (Ljava/lang/Object;)Z
/*     */     //   284: ifeq -> 291
/*     */     //   287: iconst_1
/*     */     //   288: goto -> 292
/*     */     //   291: iconst_0
/*     */     //   292: invokevirtual assert : (Z)V
/*     */     //   295: getstatic li/cil/oc/util/ExtendedWorld$.MODULE$ : Lli/cil/oc/util/ExtendedWorld$;
/*     */     //   298: aload_0
/*     */     //   299: invokevirtual world : ()Lnet/minecraft/world/World;
/*     */     //   302: invokevirtual extendedWorld : (Lnet/minecraft/world/World;)Lli/cil/oc/util/ExtendedWorld$ExtendedWorld;
/*     */     //   305: aload_2
/*     */     //   306: getstatic net/minecraft/init/Blocks.field_150350_a : Lnet/minecraft/block/Block;
/*     */     //   309: iconst_0
/*     */     //   310: iconst_1
/*     */     //   311: invokevirtual setBlock : (Lli/cil/oc/util/BlockPosition;Lnet/minecraft/block/Block;II)Z
/*     */     //   314: pop
/*     */     //   315: getstatic li/cil/oc/util/ExtendedWorld$.MODULE$ : Lli/cil/oc/util/ExtendedWorld$;
/*     */     //   318: aload_0
/*     */     //   319: invokevirtual world : ()Lnet/minecraft/world/World;
/*     */     //   322: invokevirtual extendedWorld : (Lnet/minecraft/world/World;)Lli/cil/oc/util/ExtendedWorld$ExtendedWorld;
/*     */     //   325: aload_2
/*     */     //   326: aload #6
/*     */     //   328: iconst_0
/*     */     //   329: iconst_1
/*     */     //   330: invokevirtual setBlock : (Lli/cil/oc/util/BlockPosition;Lnet/minecraft/block/Block;II)Z
/*     */     //   333: pop
/*     */     //   334: getstatic scala/Predef$.MODULE$ : Lscala/Predef$;
/*     */     //   337: getstatic li/cil/oc/util/ExtendedWorld$.MODULE$ : Lli/cil/oc/util/ExtendedWorld$;
/*     */     //   340: aload_0
/*     */     //   341: invokevirtual world : ()Lnet/minecraft/world/World;
/*     */     //   344: invokevirtual extendedWorld : (Lnet/minecraft/world/World;)Lli/cil/oc/util/ExtendedWorld$ExtendedWorld;
/*     */     //   347: aload_2
/*     */     //   348: invokevirtual getBlock : (Lli/cil/oc/util/BlockPosition;)Lnet/minecraft/block/Block;
/*     */     //   351: aload #6
/*     */     //   353: astore #14
/*     */     //   355: dup
/*     */     //   356: ifnonnull -> 368
/*     */     //   359: pop
/*     */     //   360: aload #14
/*     */     //   362: ifnull -> 376
/*     */     //   365: goto -> 380
/*     */     //   368: aload #14
/*     */     //   370: invokevirtual equals : (Ljava/lang/Object;)Z
/*     */     //   373: ifeq -> 380
/*     */     //   376: iconst_1
/*     */     //   377: goto -> 381
/*     */     //   380: iconst_0
/*     */     //   381: invokevirtual assert : (Z)V
/*     */     //   384: getstatic scala/math/package$.MODULE$ : Lscala/math/package$;
/*     */     //   387: getstatic li/cil/oc/Settings$.MODULE$ : Lli/cil/oc/Settings$;
/*     */     //   390: invokevirtual get : ()Lli/cil/oc/Settings;
/*     */     //   393: invokevirtual moveDelay : ()D
/*     */     //   396: bipush #20
/*     */     //   398: i2d
/*     */     //   399: dmul
/*     */     //   400: d2i
/*     */     //   401: iconst_1
/*     */     //   402: invokevirtual max : (II)I
/*     */     //   405: istore #15
/*     */     //   407: aload_0
/*     */     //   408: aload_2
/*     */     //   409: iload #15
/*     */     //   411: invokevirtual setAnimateMove : (Lli/cil/oc/util/BlockPosition;I)V
/*     */     //   414: aload_0
/*     */     //   415: invokevirtual isServer : ()Z
/*     */     //   418: ifeq -> 455
/*     */     //   421: getstatic li/cil/oc/server/PacketSender$.MODULE$ : Lli/cil/oc/server/PacketSender$;
/*     */     //   424: aload_0
/*     */     //   425: aload_2
/*     */     //   426: aload_1
/*     */     //   427: invokevirtual sendRobotMove : (Lli/cil/oc/common/tileentity/Robot;Lli/cil/oc/util/BlockPosition;Lnet/minecraftforge/common/util/ForgeDirection;)V
/*     */     //   430: aload_0
/*     */     //   431: invokevirtual checkRedstoneInputChanged : ()V
/*     */     //   434: getstatic net/minecraftforge/common/MinecraftForge.EVENT_BUS : Lcpw/mods/fml/common/eventhandler/EventBus;
/*     */     //   437: new li/cil/oc/api/event/RobotMoveEvent$Post
/*     */     //   440: dup
/*     */     //   441: aload_0
/*     */     //   442: aload_1
/*     */     //   443: invokespecial <init> : (Lli/cil/oc/api/internal/Agent;Lnet/minecraftforge/common/util/ForgeDirection;)V
/*     */     //   446: invokevirtual post : (Lcpw/mods/fml/common/eventhandler/Event;)Z
/*     */     //   449: invokestatic boxToBoolean : (Z)Ljava/lang/Boolean;
/*     */     //   452: goto -> 644
/*     */     //   455: iload #7
/*     */     //   457: ifne -> 613
/*     */     //   460: aload #8
/*     */     //   462: ifnull -> 613
/*     */     //   465: aload #8
/*     */     //   467: aload #6
/*     */     //   469: astore #16
/*     */     //   471: dup
/*     */     //   472: ifnonnull -> 484
/*     */     //   475: pop
/*     */     //   476: aload #16
/*     */     //   478: ifnull -> 613
/*     */     //   481: goto -> 492
/*     */     //   484: aload #16
/*     */     //   486: invokevirtual equals : (Ljava/lang/Object;)Z
/*     */     //   489: ifne -> 613
/*     */     //   492: aload #8
/*     */     //   494: invokestatic lookupFluidForBlock : (Lnet/minecraft/block/Block;)Lnet/minecraftforge/fluids/Fluid;
/*     */     //   497: ifnonnull -> 547
/*     */     //   500: aload #8
/*     */     //   502: instanceof net/minecraftforge/fluids/BlockFluidBase
/*     */     //   505: ifne -> 547
/*     */     //   508: aload #8
/*     */     //   510: instanceof net/minecraft/block/BlockLiquid
/*     */     //   513: ifne -> 547
/*     */     //   516: getstatic li/cil/oc/util/ExtendedWorld$.MODULE$ : Lli/cil/oc/util/ExtendedWorld$;
/*     */     //   519: aload_0
/*     */     //   520: invokevirtual world : ()Lnet/minecraft/world/World;
/*     */     //   523: invokevirtual extendedWorld : (Lnet/minecraft/world/World;)Lli/cil/oc/util/ExtendedWorld$ExtendedWorld;
/*     */     //   526: sipush #2001
/*     */     //   529: aload_3
/*     */     //   530: aload #8
/*     */     //   532: invokestatic func_149682_b : (Lnet/minecraft/block/Block;)I
/*     */     //   535: iload #9
/*     */     //   537: bipush #12
/*     */     //   539: ishl
/*     */     //   540: iadd
/*     */     //   541: invokevirtual playAuxSFX : (ILli/cil/oc/util/BlockPosition;I)V
/*     */     //   544: goto -> 613
/*     */     //   547: aload_3
/*     */     //   548: invokevirtual toVec3 : ()Lnet/minecraft/util/Vec3;
/*     */     //   551: astore #17
/*     */     //   553: aload_0
/*     */     //   554: invokevirtual world : ()Lnet/minecraft/world/World;
/*     */     //   557: aload #17
/*     */     //   559: getfield field_72450_a : D
/*     */     //   562: aload #17
/*     */     //   564: getfield field_72448_b : D
/*     */     //   567: aload #17
/*     */     //   569: getfield field_72449_c : D
/*     */     //   572: ldc_w 'liquid.water'
/*     */     //   575: aload_0
/*     */     //   576: invokevirtual world : ()Lnet/minecraft/world/World;
/*     */     //   579: getfield field_73012_v : Ljava/util/Random;
/*     */     //   582: invokevirtual nextFloat : ()F
/*     */     //   585: ldc_w 0.25
/*     */     //   588: fmul
/*     */     //   589: ldc_w 0.75
/*     */     //   592: fadd
/*     */     //   593: aload_0
/*     */     //   594: invokevirtual world : ()Lnet/minecraft/world/World;
/*     */     //   597: getfield field_73012_v : Ljava/util/Random;
/*     */     //   600: invokevirtual nextFloat : ()F
/*     */     //   603: fconst_1
/*     */     //   604: fmul
/*     */     //   605: ldc_w 0.5
/*     */     //   608: fadd
/*     */     //   609: iconst_0
/*     */     //   610: invokevirtual func_72980_b : (DDDLjava/lang/String;FFZ)V
/*     */     //   613: getstatic li/cil/oc/util/ExtendedWorld$.MODULE$ : Lli/cil/oc/util/ExtendedWorld$;
/*     */     //   616: aload_0
/*     */     //   617: invokevirtual world : ()Lnet/minecraft/world/World;
/*     */     //   620: invokevirtual extendedWorld : (Lnet/minecraft/world/World;)Lli/cil/oc/util/ExtendedWorld$ExtendedWorld;
/*     */     //   623: aload_2
/*     */     //   624: invokevirtual markBlockForUpdate : (Lli/cil/oc/util/BlockPosition;)V
/*     */     //   627: getstatic li/cil/oc/util/ExtendedWorld$.MODULE$ : Lli/cil/oc/util/ExtendedWorld$;
/*     */     //   630: aload_0
/*     */     //   631: invokevirtual world : ()Lnet/minecraft/world/World;
/*     */     //   634: invokevirtual extendedWorld : (Lnet/minecraft/world/World;)Lli/cil/oc/util/ExtendedWorld$ExtendedWorld;
/*     */     //   637: aload_3
/*     */     //   638: invokevirtual markBlockForUpdate : (Lli/cil/oc/util/BlockPosition;)V
/*     */     //   641: getstatic scala/runtime/BoxedUnit.UNIT : Lscala/runtime/BoxedUnit;
/*     */     //   644: pop
/*     */     //   645: getstatic scala/Predef$.MODULE$ : Lscala/Predef$;
/*     */     //   648: aload_0
/*     */     //   649: invokevirtual func_145837_r : ()Z
/*     */     //   652: ifeq -> 659
/*     */     //   655: iconst_0
/*     */     //   656: goto -> 660
/*     */     //   659: iconst_1
/*     */     //   660: invokevirtual assert : (Z)V
/*     */     //   663: getstatic scala/runtime/BoxedUnit.UNIT : Lscala/runtime/BoxedUnit;
/*     */     //   666: goto -> 686
/*     */     //   669: getstatic li/cil/oc/util/ExtendedWorld$.MODULE$ : Lli/cil/oc/util/ExtendedWorld$;
/*     */     //   672: aload_0
/*     */     //   673: invokevirtual world : ()Lnet/minecraft/world/World;
/*     */     //   676: invokevirtual extendedWorld : (Lnet/minecraft/world/World;)Lli/cil/oc/util/ExtendedWorld$ExtendedWorld;
/*     */     //   679: aload_3
/*     */     //   680: invokevirtual setBlockToAir : (Lli/cil/oc/util/BlockPosition;)Z
/*     */     //   683: invokestatic boxToBoolean : (Z)Ljava/lang/Boolean;
/*     */     //   686: pop
/*     */     //   687: iload #11
/*     */     //   689: ifeq -> 724
/*     */     //   692: aload_0
/*     */     //   693: invokevirtual position : ()Lli/cil/oc/util/BlockPosition;
/*     */     //   696: aload_3
/*     */     //   697: astore #18
/*     */     //   699: dup
/*     */     //   700: ifnonnull -> 712
/*     */     //   703: pop
/*     */     //   704: aload #18
/*     */     //   706: ifnull -> 720
/*     */     //   709: goto -> 724
/*     */     //   712: aload #18
/*     */     //   714: invokevirtual equals : (Ljava/lang/Object;)Z
/*     */     //   717: ifeq -> 724
/*     */     //   720: iconst_1
/*     */     //   721: goto -> 725
/*     */     //   724: iconst_0
/*     */     //   725: aload #5
/*     */     //   727: invokevirtual moving : ()Ljava/lang/ThreadLocal;
/*     */     //   730: getstatic scala/None$.MODULE$ : Lscala/None$;
/*     */     //   733: invokevirtual set : (Ljava/lang/Object;)V
/*     */     //   736: ireturn
/*     */     //   737: iconst_0
/*     */     //   738: ireturn
/*     */     //   739: astore #10
/*     */     //   741: aload #5
/*     */     //   743: invokevirtual moving : ()Ljava/lang/ThreadLocal;
/*     */     //   746: getstatic scala/None$.MODULE$ : Lscala/None$;
/*     */     //   749: invokevirtual set : (Ljava/lang/Object;)V
/*     */     //   752: aload #10
/*     */     //   754: athrow
/*     */     // Line number table:
/*     */     //   Java source line number -> byte code offset
/*     */     //   #185	-> 0
/*     */     //   #186	-> 8
/*     */     //   #187	-> 14
/*     */     //   #191	-> 31
/*     */     //   #192	-> 38
/*     */     //   #193	-> 49
/*     */     //   #194	-> 58
/*     */     //   #197	-> 68
/*     */     //   #198	-> 84
/*     */     //   #199	-> 100
/*     */     //   #200	-> 116
/*     */     //   #201	-> 132
/*     */     //   #206	-> 148
/*     */     //   #211	-> 164
/*     */     //   #214	-> 179
/*     */     //   #215	-> 200
/*     */     //   #214	-> 241
/*     */     //   #216	-> 248
/*     */     //   #217	-> 253
/*     */     //   #218	-> 295
/*     */     //   #219	-> 315
/*     */     //   #220	-> 334
/*     */     //   #222	-> 384
/*     */     //   #223	-> 407
/*     */     //   #224	-> 414
/*     */     //   #225	-> 421
/*     */     //   #226	-> 430
/*     */     //   #227	-> 434
/*     */     //   #224	-> 449
/*     */     //   #231	-> 455
/*     */     //   #232	-> 460
/*     */     //   #233	-> 492
/*     */     //   #234	-> 500
/*     */     //   #235	-> 508
/*     */     //   #236	-> 516
/*     */     //   #239	-> 547
/*     */     //   #240	-> 553
/*     */     //   #241	-> 575
/*     */     //   #240	-> 610
/*     */     //   #245	-> 613
/*     */     //   #246	-> 627
/*     */     //   #229	-> 641
/*     */     //   #224	-> 644
/*     */     //   #248	-> 645
/*     */     //   #216	-> 663
/*     */     //   #251	-> 669
/*     */     //   #216	-> 686
/*     */     //   #253	-> 687
/*     */     //   #256	-> 725
/*     */     //   #188	-> 737
/*     */     //   #256	-> 739
/*     */     // Local variable table:
/*     */     //   start	length	slot	name	descriptor
/*     */     //   0	755	0	this	Lli/cil/oc/common/tileentity/Robot;
/*     */     //   0	755	1	direction	Lnet/minecraftforge/common/util/ForgeDirection;
/*     */     //   8	728	2	oldPosition	Lli/cil/oc/util/BlockPosition;
/*     */     //   14	722	3	newPosition	Lli/cil/oc/util/BlockPosition;
/*     */     //   49	706	4	event	Lli/cil/oc/api/event/RobotMoveEvent$Pre;
/*     */     //   84	652	5	blockRobotProxy	Lli/cil/oc/common/block/RobotProxy;
/*     */     //   100	636	6	blockRobotAfterImage	Lli/cil/oc/common/block/RobotAfterimage;
/*     */     //   116	620	7	wasAir	Z
/*     */     //   132	604	8	block	Lnet/minecraft/block/Block;
/*     */     //   148	588	9	metadata	I
/*     */     //   248	507	11	created	Z
/*     */     //   407	256	15	moveTicks	I
/*     */     //   553	60	17	soundPos	Lnet/minecraft/util/Vec3;
/*     */     // Exception table:
/*     */     //   from	to	target	type
/*     */     //   148	725	739	finally } public boolean isAnimatingMove() { return (animationTicksLeft() > 0 && (moveFromX() != Integer.MAX_VALUE || moveFromY() != Integer.MAX_VALUE || moveFromZ() != Integer.MAX_VALUE)); } public boolean isAnimatingSwing() { return (animationTicksLeft() > 0 && swingingTool()); } public boolean isAnimatingTurn() { return (animationTicksLeft() > 0 && turnAxis() != 0); } public void animateSwing(double duration) { if (items()[0].isDefined()) { setAnimateSwing((int)(duration * 20)); PacketSender$.MODULE$.sendRobotAnimateSwing(this); }  } public void animateTurn(boolean clockwise, double duration) { setAnimateTurn(clockwise ? 1 : -1, (int)(duration * 20)); PacketSender$.MODULE$.sendRobotAnimateTurn(this); } public void setAnimateMove(BlockPosition fromPosition, int ticks) { animationTicksTotal_$eq(ticks + 2); prepareForAnimation(); moveFromX_$eq(fromPosition.x()); moveFromY_$eq(fromPosition.y()); moveFromZ_$eq(fromPosition.z()); } public void setAnimateSwing(int ticks) { animationTicksTotal_$eq(package$.MODULE$.max(ticks, 5)); prepareForAnimation(); swingingTool_$eq(true); } public void setAnimateTurn(int axis, int ticks) { animationTicksTotal_$eq(ticks); prepareForAnimation(); turnAxis_$eq(axis); } private void prepareForAnimation() { animationTicksLeft_$eq(animationTicksTotal()); moveFromX_$eq(2147483647); moveFromY_$eq(2147483647); moveFromZ_$eq(2147483647); swingingTool_$eq(false); turnAxis_$eq(0); } public boolean shouldRenderInPass(int pass) { return true; } public AxisAlignedBB getRenderBoundingBox() { return func_145838_q().func_149668_a(world(), x(), y(), z()).func_72314_b(0.5D, 0.5D, 0.5D); } public void func_145845_h() { if (animationTicksLeft() > 0) { animationTicksLeft_$eq(animationTicksLeft() - 1); if (animationTicksLeft() == 0) { moveFromX_$eq(2147483647); moveFromY_$eq(2147483647); moveFromZ_$eq(2147483647); swingingTool_$eq(false); turnAxis_$eq(0); }  }  Computer.class.updateEntity(this); if (isServer()) { if (world().func_82737_E() % Settings$.MODULE$.get().tickFrequency() == false) { (info().tier() == 3) ? BoxesRunTime.boxToDouble(bot().node().changeBuffer(Double.POSITIVE_INFINITY)) : BoxedUnit.UNIT; globalBuffer_$eq(bot().node().globalBuffer()); globalBufferSize_$eq(bot().node().globalBufferSize()); info().totalEnergy_$eq((int)globalBuffer()); info().robotEnergy_$eq((int)bot().node().localBuffer()); updatePowerInformation(); }  if (!appliedToolEnchantments()) { appliedToolEnchantments_$eq(true); Option option = Option$.MODULE$.apply(func_70301_a(0)); if (option instanceof Some) { Some some = (Some)option; ItemStack item = (ItemStack)some.x(); li$cil$oc$common$tileentity$Robot$$player_().func_110140_aT().func_111147_b(item.func_111283_C()); BoxedUnit boxedUnit = BoxedUnit.UNIT; } else { BoxedUnit boxedUnit = BoxedUnit.UNIT; }  }  } else if (isRunning() && isAnimatingMove()) { Sound$.MODULE$.updatePosition(this); }  RichInt$.MODULE$.until$extension0(Predef$.MODULE$.intWrapper(0), equipmentInventory().func_70302_i_() + mainInventory().func_70302_i_()).foreach$mVc$sp((Function1)new Robot$$anonfun$updateEntity$1(this)); } public final class Robot$$anonfun$updateEntity$1 extends AbstractFunction1.mcVI.sp implements Serializable { public static final long serialVersionUID = 0L; public final void apply(int slot) { apply$mcVI$sp(slot); } public Robot$$anonfun$updateEntity$1(Robot $outer) {} public void apply$mcVI$sp(int slot) { // Byte code:
/*     */       //   0: aload_0
/*     */       //   1: getfield $outer : Lli/cil/oc/common/tileentity/Robot;
/*     */       //   4: iload_1
/*     */       //   5: invokevirtual func_70301_a : (I)Lnet/minecraft/item/ItemStack;
/*     */       //   8: astore_2
/*     */       //   9: aload_2
/*     */       //   10: ifnull -> 67
/*     */       //   13: aload_2
/*     */       //   14: astore_3
/*     */       //   15: aload_3
/*     */       //   16: aload_0
/*     */       //   17: getfield $outer : Lli/cil/oc/common/tileentity/Robot;
/*     */       //   20: invokevirtual world : ()Lnet/minecraft/world/World;
/*     */       //   23: aload_0
/*     */       //   24: getfield $outer : Lli/cil/oc/common/tileentity/Robot;
/*     */       //   27: invokevirtual world : ()Lnet/minecraft/world/World;
/*     */       //   30: getfield field_72995_K : Z
/*     */       //   33: ifeq -> 40
/*     */       //   36: aconst_null
/*     */       //   37: goto -> 47
/*     */       //   40: aload_0
/*     */       //   41: getfield $outer : Lli/cil/oc/common/tileentity/Robot;
/*     */       //   44: invokevirtual li$cil$oc$common$tileentity$Robot$$player_ : ()Lli/cil/oc/server/agent/Player;
/*     */       //   47: iload_1
/*     */       //   48: iload_1
/*     */       //   49: iconst_0
/*     */       //   50: if_icmpne -> 57
/*     */       //   53: iconst_1
/*     */       //   54: goto -> 58
/*     */       //   57: iconst_0
/*     */       //   58: invokevirtual func_77945_a : (Lnet/minecraft/world/World;Lnet/minecraft/entity/Entity;IZ)V
/*     */       //   61: getstatic scala/runtime/BoxedUnit.UNIT : Lscala/runtime/BoxedUnit;
/*     */       //   64: goto -> 80
/*     */       //   67: getstatic scala/runtime/BoxedUnit.UNIT : Lscala/runtime/BoxedUnit;
/*     */       //   70: astore #4
/*     */       //   72: goto -> 82
/*     */       //   75: astore #5
/*     */       //   77: getstatic scala/runtime/BoxedUnit.UNIT : Lscala/runtime/BoxedUnit;
/*     */       //   80: astore #4
/*     */       //   82: return
/*     */       // Line number table:
/*     */       //   Java source line number -> byte code offset
/*     */       //   #352	-> 0
/*     */       //   #353	-> 9
/*     */       //   #356	-> 67
/*     */       //   #354	-> 75
/*     */       //   #353	-> 75
/*     */       //   #353	-> 80
/*     */       //   #352	-> 82
/*     */       // Local variable table:
/*     */       //   start	length	slot	name	descriptor
/*     */       //   0	83	0	this	Lli/cil/oc/common/tileentity/Robot$$anonfun$updateEntity$1;
/*     */       //   0	83	1	slot	I
/*     */       // Exception table:
/*     */       //   from	to	target	type
/*     */       //   15	67	75	java/lang/NullPointerException } } public void updateComputer() {} public void onRunningChanged() { Computer.class.onRunningChanged(this); if (isRunning()) { EventHandler$.MODULE$.onRobotStart(this); } else { EventHandler$.MODULE$.onRobotStopped(this); }  } public void initialize() { if (isServer()) Network.joinNewNetwork(node());  } public void dispose() { // Byte code:
/*     */     //   0: aload_0
/*     */     //   1: invokestatic dispose : (Lli/cil/oc/common/tileentity/traits/Computer;)V
/*     */     //   4: aload_0
/*     */     //   5: invokevirtual isClient : ()Z
/*     */     //   8: ifeq -> 78
/*     */     //   11: invokestatic func_71410_x : ()Lnet/minecraft/client/Minecraft;
/*     */     //   14: getfield field_71462_r : Lnet/minecraft/client/gui/GuiScreen;
/*     */     //   17: astore_1
/*     */     //   18: aload_1
/*     */     //   19: instanceof li/cil/oc/client/gui/Robot
/*     */     //   22: ifeq -> 70
/*     */     //   25: aload_1
/*     */     //   26: checkcast li/cil/oc/client/gui/Robot
/*     */     //   29: astore_2
/*     */     //   30: aload_2
/*     */     //   31: invokevirtual robot : ()Lli/cil/oc/common/tileentity/Robot;
/*     */     //   34: aload_0
/*     */     //   35: astore_3
/*     */     //   36: dup
/*     */     //   37: ifnonnull -> 48
/*     */     //   40: pop
/*     */     //   41: aload_3
/*     */     //   42: ifnull -> 55
/*     */     //   45: goto -> 70
/*     */     //   48: aload_3
/*     */     //   49: invokevirtual equals : (Ljava/lang/Object;)Z
/*     */     //   52: ifeq -> 70
/*     */     //   55: invokestatic func_71410_x : ()Lnet/minecraft/client/Minecraft;
/*     */     //   58: aconst_null
/*     */     //   59: invokevirtual func_147108_a : (Lnet/minecraft/client/gui/GuiScreen;)V
/*     */     //   62: getstatic scala/runtime/BoxedUnit.UNIT : Lscala/runtime/BoxedUnit;
/*     */     //   65: astore #4
/*     */     //   67: goto -> 85
/*     */     //   70: getstatic scala/runtime/BoxedUnit.UNIT : Lscala/runtime/BoxedUnit;
/*     */     //   73: astore #4
/*     */     //   75: goto -> 85
/*     */     //   78: getstatic li/cil/oc/common/EventHandler$.MODULE$ : Lli/cil/oc/common/EventHandler$;
/*     */     //   81: aload_0
/*     */     //   82: invokevirtual onRobotStopped : (Lli/cil/oc/common/tileentity/Robot;)V
/*     */     //   85: return
/*     */     // Line number table:
/*     */     //   Java source line number -> byte code offset
/*     */     //   #380	-> 0
/*     */     //   #381	-> 4
/*     */     //   #382	-> 11
/*     */     //   #383	-> 18
/*     */     //   #384	-> 55
/*     */     //   #385	-> 70
/*     */     //   #388	-> 78
/*     */     //   #379	-> 85
/*     */     // Local variable table:
/*     */     //   start	length	slot	name	descriptor
/*     */     //   0	86	0	this	Lli/cil/oc/common/tileentity/Robot; } public void readFromNBTForServer(NBTTagCompound nbt) { updateInventorySize(); machine().onHostChanged(); bot().load(nbt.func_74775_l((new StringBuilder()).append(Settings$.MODULE$.namespace()).append("robot").toString())); if (nbt.func_74764_b((new StringBuilder()).append(Settings$.MODULE$.namespace()).append("owner").toString())) ownerName_$eq(nbt.func_74779_i((new StringBuilder()).append(Settings$.MODULE$.namespace()).append("owner").toString()));  if (nbt.func_74764_b((new StringBuilder()).append(Settings$.MODULE$.namespace()).append("ownerUuid").toString())) ownerUUID_$eq(UUID.fromString(nbt.func_74779_i((new StringBuilder()).append(Settings$.MODULE$.namespace()).append("ownerUuid").toString())));  if (inventorySize() > 0) selectedSlot_$eq(RichInt$.MODULE$.min$extension(Predef$.MODULE$.intWrapper(RichInt$.MODULE$.max$extension(Predef$.MODULE$.intWrapper(nbt.func_74762_e((new StringBuilder()).append(Settings$.MODULE$.namespace()).append("selectedSlot").toString())), 0)), mainInventory().func_70302_i_() - 1));  selectedTank_$eq(nbt.func_74762_e((new StringBuilder()).append(Settings$.MODULE$.namespace()).append("selectedTank").toString())); animationTicksTotal_$eq(nbt.func_74762_e((new StringBuilder()).append(Settings$.MODULE$.namespace()).append("animationTicksTotal").toString())); animationTicksLeft_$eq(nbt.func_74762_e((new StringBuilder()).append(Settings$.MODULE$.namespace()).append("animationTicksLeft").toString())); if (animationTicksLeft() > 0) { moveFromX_$eq(nbt.func_74762_e((new StringBuilder()).append(Settings$.MODULE$.namespace()).append("moveFromX").toString())); moveFromY_$eq(nbt.func_74762_e((new StringBuilder()).append(Settings$.MODULE$.namespace()).append("moveFromY").toString())); moveFromZ_$eq(nbt.func_74762_e((new StringBuilder()).append(Settings$.MODULE$.namespace()).append("moveFromZ").toString())); swingingTool_$eq(nbt.func_74767_n((new StringBuilder()).append(Settings$.MODULE$.namespace()).append("swingingTool").toString())); turnAxis_$eq(nbt.func_74771_c((new StringBuilder()).append(Settings$.MODULE$.namespace()).append("turnAxis").toString())); }  _isOutputEnabled_$eq(hasRedstoneCard()); _isAbstractBusAvailable_$eq(hasAbstractBusCard()); if (isRunning()) EventHandler$.MODULE$.onRobotStart(this);  } public void writeToNBTForServer(NBTTagCompound nbt) { if (isServer()) synchronized (this) { info().save(nbt); ExtendedNBT$.MODULE$.extendNBTTagCompound(nbt).setNewCompoundTag((new StringBuilder()).append(Settings$.MODULE$.namespace()).append("robot").toString(), (Function1)new Robot$$anonfun$writeToNBTForServer$1(this)); nbt.func_74778_a((new StringBuilder()).append(Settings$.MODULE$.namespace()).append("owner").toString(), ownerName()); nbt.func_74778_a((new StringBuilder()).append(Settings$.MODULE$.namespace()).append("ownerUuid").toString(), ownerUUID().toString()); nbt.func_74768_a((new StringBuilder()).append(Settings$.MODULE$.namespace()).append("selectedSlot").toString(), selectedSlot()); nbt.func_74768_a((new StringBuilder()).append(Settings$.MODULE$.namespace()).append("selectedTank").toString(), selectedTank()); nbt.func_74768_a((new StringBuilder()).append(Settings$.MODULE$.namespace()).append("animationTicksTotal").toString(), animationTicksTotal()); nbt.func_74768_a((new StringBuilder()).append(Settings$.MODULE$.namespace()).append("animationTicksLeft").toString(), animationTicksLeft()); nbt.func_74768_a((new StringBuilder()).append(Settings$.MODULE$.namespace()).append("moveFromX").toString(), moveFromX()); nbt.func_74768_a((new StringBuilder()).append(Settings$.MODULE$.namespace()).append("moveFromY").toString(), moveFromY()); nbt.func_74768_a((new StringBuilder()).append(Settings$.MODULE$.namespace()).append("moveFromZ").toString(), moveFromZ()); nbt.func_74757_a((new StringBuilder()).append(Settings$.MODULE$.namespace()).append("swingingTool").toString(), swingingTool()); nbt.func_74774_a((new StringBuilder()).append(Settings$.MODULE$.namespace()).append("turnAxis").toString(), (byte)turnAxis()); (isAnimatingMove() || isAnimatingSwing() || isAnimatingTurn()) ? BoxedUnit.UNIT : BoxedUnit.UNIT; return; }   } public final class Robot$$anonfun$writeToNBTForServer$1 extends AbstractFunction1<NBTTagCompound, BoxedUnit> implements Serializable { public static final long serialVersionUID = 0L; public final void apply(NBTTagCompound nbt) { this.$outer.bot().save(nbt); } public Robot$$anonfun$writeToNBTForServer$1(Robot $outer) {} } @SideOnly(Side.CLIENT) public void readFromNBTForClient(NBTTagCompound nbt) { PowerInformation.class.readFromNBTForClient(this, nbt); load(nbt); info().load(nbt); updateInventorySize(); selectedSlot_$eq(nbt.func_74762_e("selectedSlot")); animationTicksTotal_$eq(nbt.func_74762_e("animationTicksTotal")); animationTicksLeft_$eq(nbt.func_74762_e("animationTicksLeft")); moveFromX_$eq(nbt.func_74762_e("moveFromX")); moveFromY_$eq(nbt.func_74762_e("moveFromY")); moveFromZ_$eq(nbt.func_74762_e("moveFromZ")); if (animationTicksLeft() > 0) { swingingTool_$eq(nbt.func_74767_n("swingingTool")); turnAxis_$eq(nbt.func_74771_c("turnAxis")); }  connectComponents(); } public synchronized void writeToNBTForClient(NBTTagCompound nbt) { PowerInformation.class.writeToNBTForClient(this, nbt); save(nbt); info().save(nbt); nbt.func_74768_a("selectedSlot", selectedSlot()); if (isAnimatingMove() || isAnimatingSwing() || isAnimatingTurn()) { nbt.func_74768_a("animationTicksTotal", animationTicksTotal()); nbt.func_74768_a("animationTicksLeft", animationTicksLeft()); nbt.func_74768_a("moveFromX", moveFromX()); nbt.func_74768_a("moveFromY", moveFromY()); nbt.func_74768_a("moveFromZ", moveFromZ()); nbt.func_74757_a("swingingTool", swingingTool()); nbt.func_74774_a("turnAxis", (byte)turnAxis()); }  } public void onMachineConnect(Node node) { ComponentInventory.class.onConnect((ComponentInventory)this, node); Node node1 = node(); if (node == null) { if (node1 != null) return;  } else { if (node.equals(node1)) { node.connect((Node)bot().node()); ((Connector)node).setLocalBufferSize(0.0D); return; }  return; }  node.connect((Node)bot().node()); ((Connector)node).setLocalBufferSize(0.0D); } public void onMachineDisconnect(Node node) { AbstractBusAware.class.onDisconnect((AbstractBusAware)this, node); Node node1 = node(); if (node == null) { if (node1 != null) return;  } else { if (node.equals(node1)) { node.remove(); bot().node().remove(); componentSlots().foreach$mVc$sp((Function1)new Robot$$anonfun$onMachineDisconnect$1(this)); return; }  return; }  node.remove(); bot().node().remove(); componentSlots().foreach$mVc$sp((Function1)new Robot$$anonfun$onMachineDisconnect$1(this)); } public final class Robot$$anonfun$onMachineDisconnect$1 extends AbstractFunction1.mcVI.sp implements Serializable { public static final long serialVersionUID = 0L; public final void apply(int slot) { apply$mcVI$sp(slot); } public Robot$$anonfun$onMachineDisconnect$1(Robot $outer) {} public void apply$mcVI$sp(int slot) { Option$.MODULE$.apply(this.$outer.getComponentInSlot(slot)).foreach((Function1)new Robot$$anonfun$onMachineDisconnect$1$$anonfun$apply$mcVI$sp$1(this)); } public final class Robot$$anonfun$onMachineDisconnect$1$$anonfun$apply$mcVI$sp$1 extends AbstractFunction1<Environment, BoxedUnit> implements Serializable { public static final long serialVersionUID = 0L; public final void apply(Environment x$1) { x$1.node().remove(); } public Robot$$anonfun$onMachineDisconnect$1$$anonfun$apply$mcVI$sp$1(Robot$$anonfun$onMachineDisconnect$1 $outer) {} } } public void onItemAdded(int slot, ItemStack stack) { if (isServer()) { if (isToolSlot(slot)) { li$cil$oc$common$tileentity$Robot$$player_().func_110140_aT().func_111147_b(stack.func_111283_C()); PacketSender$.MODULE$.sendRobotInventory(this, slot, stack); }  if (isUpgradeSlot(slot)) PacketSender$.MODULE$.sendRobotInventory(this, slot, stack);  if (isFloppySlot(slot)) Sound$.MODULE$.playDiskInsert((EnvironmentHost)this);  if (isComponentSlot(slot, stack)) { ComponentInventory.class.onItemAdded((ComponentInventory)this, slot, stack); world().func_147459_d(x(), y(), z(), func_145838_q()); }  if (isInventorySlot(slot)) machine().signal("inventory_changed", new Object[] { BoxesRunTime.boxToInteger(slot - equipmentInventory().func_70302_i_() + 1) });  } else { ComponentInventory.class.onItemAdded((ComponentInventory)this, slot, stack); }  } public void onItemRemoved(int slot, ItemStack stack) { ComponentInventory.class.onItemRemoved((ComponentInventory)this, slot, stack); if (isServer()) { if (isToolSlot(slot)) { li$cil$oc$common$tileentity$Robot$$player_().func_110140_aT().func_111148_a(stack.func_111283_C()); PacketSender$.MODULE$.sendRobotInventory(this, slot, null); }  if (isUpgradeSlot(slot)) PacketSender$.MODULE$.sendRobotInventory(this, slot, null);  if (isFloppySlot(slot)) Sound$.MODULE$.playDiskEject((EnvironmentHost)this);  isInventorySlot(slot) ? BoxesRunTime.boxToBoolean(machine().signal("inventory_changed", new Object[] { BoxesRunTime.boxToInteger(slot - equipmentInventory().func_70302_i_() + 1) })) : BoxedUnit.UNIT; if (isComponentSlot(slot, stack)) world().func_147459_d(x(), y(), z(), func_145838_q());  }  } public void func_70296_d() { // Byte code:
/*     */     //   0: aload_0
/*     */     //   1: invokestatic markDirty : (Lli/cil/oc/common/tileentity/traits/Computer;)V
/*     */     //   4: aload_0
/*     */     //   5: invokevirtual inventorySize : ()I
/*     */     //   8: iconst_0
/*     */     //   9: if_icmplt -> 19
/*     */     //   12: aload_0
/*     */     //   13: invokevirtual updateInventorySize : ()V
/*     */     //   16: goto -> 90
/*     */     //   19: aload_0
/*     */     //   20: invokevirtual isClient : ()Z
/*     */     //   23: ifeq -> 90
/*     */     //   26: invokestatic func_71410_x : ()Lnet/minecraft/client/Minecraft;
/*     */     //   29: getfield field_71462_r : Lnet/minecraft/client/gui/GuiScreen;
/*     */     //   32: astore_1
/*     */     //   33: aload_1
/*     */     //   34: instanceof li/cil/oc/client/gui/Robot
/*     */     //   37: ifeq -> 85
/*     */     //   40: aload_1
/*     */     //   41: checkcast li/cil/oc/client/gui/Robot
/*     */     //   44: astore_2
/*     */     //   45: aload_2
/*     */     //   46: invokevirtual robot : ()Lli/cil/oc/common/tileentity/Robot;
/*     */     //   49: aload_0
/*     */     //   50: astore_3
/*     */     //   51: dup
/*     */     //   52: ifnonnull -> 63
/*     */     //   55: pop
/*     */     //   56: aload_3
/*     */     //   57: ifnull -> 70
/*     */     //   60: goto -> 85
/*     */     //   63: aload_3
/*     */     //   64: invokevirtual equals : (Ljava/lang/Object;)Z
/*     */     //   67: ifeq -> 85
/*     */     //   70: invokestatic func_71410_x : ()Lnet/minecraft/client/Minecraft;
/*     */     //   73: aconst_null
/*     */     //   74: invokevirtual func_147108_a : (Lnet/minecraft/client/gui/GuiScreen;)V
/*     */     //   77: getstatic scala/runtime/BoxedUnit.UNIT : Lscala/runtime/BoxedUnit;
/*     */     //   80: astore #4
/*     */     //   82: goto -> 90
/*     */     //   85: getstatic scala/runtime/BoxedUnit.UNIT : Lscala/runtime/BoxedUnit;
/*     */     //   88: astore #4
/*     */     //   90: aload_0
/*     */     //   91: iconst_0
/*     */     //   92: invokevirtual renderingErrored_$eq : (Z)V
/*     */     //   95: return
/*     */     // Line number table:
/*     */     //   Java source line number -> byte code offset
/*     */     //   #554	-> 0
/*     */     //   #559	-> 4
/*     */     //   #560	-> 12
/*     */     //   #562	-> 19
/*     */     //   #563	-> 26
/*     */     //   #564	-> 33
/*     */     //   #565	-> 70
/*     */     //   #566	-> 85
/*     */     //   #569	-> 90
/*     */     // Local variable table:
/*     */     //   start	length	slot	name	descriptor
/*     */     //   0	96	0	this	Lli/cil/oc/common/tileentity/Robot; } public void connectItemNode(Node node) { ComponentInventory.class.connectItemNode((ComponentInventory)this, node); if (node != null) { Environment environment = node.host(); if (environment instanceof TextBuffer) { TextBuffer textBuffer = (TextBuffer)environment; componentSlots().foreach$mVc$sp((Function1)new Robot$$anonfun$connectItemNode$1(this, textBuffer)); BoxedUnit boxedUnit = BoxedUnit.UNIT; } else if (environment instanceof Keyboard) { Keyboard keyboard = (Keyboard)environment; componentSlots().foreach$mVc$sp((Function1)new Robot$$anonfun$connectItemNode$2(this, keyboard)); BoxedUnit boxedUnit = BoxedUnit.UNIT; } else { BoxedUnit boxedUnit = BoxedUnit.UNIT; }  }  } public final class Robot$$anonfun$connectItemNode$1 extends AbstractFunction1.mcVI.sp implements Serializable { public static final long serialVersionUID = 0L; private final TextBuffer x2$1; public final void apply(int slot) { apply$mcVI$sp(slot); } public Robot$$anonfun$connectItemNode$1(Robot $outer, TextBuffer x2$1) {} public void apply$mcVI$sp(int slot) { Environment environment = this.$outer.getComponentInSlot(slot); if (environment instanceof Keyboard) { Keyboard keyboard = (Keyboard)environment; this.x2$1.node().connect(keyboard.node()); BoxedUnit boxedUnit = BoxedUnit.UNIT; } else if (environment instanceof GraphicsCard) { GraphicsCard graphicsCard = (GraphicsCard)environment; this.x2$1.node().connect((Node)graphicsCard.node()); BoxedUnit boxedUnit = BoxedUnit.UNIT; } else { BoxedUnit boxedUnit = BoxedUnit.UNIT; }  } } public final class Robot$$anonfun$connectItemNode$2 extends AbstractFunction1.mcVI.sp implements Serializable { public static final long serialVersionUID = 0L; private final Keyboard x3$1; public final void apply(int slot) { apply$mcVI$sp(slot); } public Robot$$anonfun$connectItemNode$2(Robot $outer, Keyboard x3$1) {} public void apply$mcVI$sp(int slot) { Environment environment = this.$outer.getComponentInSlot(slot); if (environment instanceof TextBuffer) { TextBuffer textBuffer = (TextBuffer)environment; this.x3$1.node().connect(textBuffer.node()); BoxedUnit boxedUnit = BoxedUnit.UNIT; } else { BoxedUnit boxedUnit = BoxedUnit.UNIT; }  } } public boolean isComponentSlot(int slot, ItemStack stack) { return ((SeqLike)containerSlots().$plus$plus((GenTraversableOnce)componentSlots(), IndexedSeq$.MODULE$.canBuildFrom())).contains(BoxesRunTime.boxToInteger(slot)); } public String containerSlotType(int slot) { // Byte code:
/*     */     //   0: aload_0
/*     */     //   1: invokevirtual containerSlots : ()Lscala/collection/immutable/Range$Inclusive;
/*     */     //   4: iload_1
/*     */     //   5: invokevirtual contains : (I)Z
/*     */     //   8: ifeq -> 102
/*     */     //   11: aload_0
/*     */     //   12: invokevirtual info : ()Lli/cil/oc/common/item/data/RobotData;
/*     */     //   15: invokevirtual containers : ()[Lnet/minecraft/item/ItemStack;
/*     */     //   18: iload_1
/*     */     //   19: iconst_1
/*     */     //   20: isub
/*     */     //   21: aaload
/*     */     //   22: astore_2
/*     */     //   23: getstatic scala/Option$.MODULE$ : Lscala/Option$;
/*     */     //   26: aload_2
/*     */     //   27: aload_0
/*     */     //   28: invokevirtual getClass : ()Ljava/lang/Class;
/*     */     //   31: invokestatic driverFor : (Lnet/minecraft/item/ItemStack;Ljava/lang/Class;)Lli/cil/oc/api/driver/Item;
/*     */     //   34: invokevirtual apply : (Ljava/lang/Object;)Lscala/Option;
/*     */     //   37: astore_3
/*     */     //   38: aload_3
/*     */     //   39: instanceof scala/Some
/*     */     //   42: ifeq -> 89
/*     */     //   45: aload_3
/*     */     //   46: checkcast scala/Some
/*     */     //   49: astore #4
/*     */     //   51: aload #4
/*     */     //   53: invokevirtual x : ()Ljava/lang/Object;
/*     */     //   56: checkcast li/cil/oc/api/driver/Item
/*     */     //   59: astore #5
/*     */     //   61: aload #5
/*     */     //   63: instanceof li/cil/oc/api/driver/item/Container
/*     */     //   66: ifeq -> 89
/*     */     //   69: aload #5
/*     */     //   71: checkcast li/cil/oc/api/driver/item/Container
/*     */     //   74: astore #6
/*     */     //   76: aload #6
/*     */     //   78: aload_2
/*     */     //   79: invokeinterface providedSlot : (Lnet/minecraft/item/ItemStack;)Ljava/lang/String;
/*     */     //   84: astore #7
/*     */     //   86: goto -> 97
/*     */     //   89: getstatic li/cil/oc/common/Slot$.MODULE$ : Lli/cil/oc/common/Slot$;
/*     */     //   92: invokevirtual None : ()Ljava/lang/String;
/*     */     //   95: astore #7
/*     */     //   97: aload #7
/*     */     //   99: goto -> 108
/*     */     //   102: getstatic li/cil/oc/common/Slot$.MODULE$ : Lli/cil/oc/common/Slot$;
/*     */     //   105: invokevirtual None : ()Ljava/lang/String;
/*     */     //   108: areturn
/*     */     // Line number table:
/*     */     //   Java source line number -> byte code offset
/*     */     //   #596	-> 0
/*     */     //   #597	-> 11
/*     */     //   #598	-> 23
/*     */     //   #599	-> 38
/*     */     //   #600	-> 89
/*     */     //   #598	-> 97
/*     */     //   #603	-> 102
/*     */     //   #596	-> 108
/*     */     // Local variable table:
/*     */     //   start	length	slot	name	descriptor
/*     */     //   0	109	0	this	Lli/cil/oc/common/tileentity/Robot;
/*     */     //   0	109	1	slot	I
/*     */     //   23	76	2	stack	Lnet/minecraft/item/ItemStack;
/*     */     //   61	48	5	driver	Lli/cil/oc/api/driver/Item; } public int containerSlotTier(int slot) { // Byte code:
/*     */     //   0: aload_0
/*     */     //   1: invokevirtual containerSlots : ()Lscala/collection/immutable/Range$Inclusive;
/*     */     //   4: iload_1
/*     */     //   5: invokevirtual contains : (I)Z
/*     */     //   8: ifeq -> 97
/*     */     //   11: aload_0
/*     */     //   12: invokevirtual info : ()Lli/cil/oc/common/item/data/RobotData;
/*     */     //   15: invokevirtual containers : ()[Lnet/minecraft/item/ItemStack;
/*     */     //   18: iload_1
/*     */     //   19: iconst_1
/*     */     //   20: isub
/*     */     //   21: aaload
/*     */     //   22: astore_2
/*     */     //   23: getstatic scala/Option$.MODULE$ : Lscala/Option$;
/*     */     //   26: aload_2
/*     */     //   27: aload_0
/*     */     //   28: invokevirtual getClass : ()Ljava/lang/Class;
/*     */     //   31: invokestatic driverFor : (Lnet/minecraft/item/ItemStack;Ljava/lang/Class;)Lli/cil/oc/api/driver/Item;
/*     */     //   34: invokevirtual apply : (Ljava/lang/Object;)Lscala/Option;
/*     */     //   37: astore_3
/*     */     //   38: aload_3
/*     */     //   39: instanceof scala/Some
/*     */     //   42: ifeq -> 89
/*     */     //   45: aload_3
/*     */     //   46: checkcast scala/Some
/*     */     //   49: astore #4
/*     */     //   51: aload #4
/*     */     //   53: invokevirtual x : ()Ljava/lang/Object;
/*     */     //   56: checkcast li/cil/oc/api/driver/Item
/*     */     //   59: astore #5
/*     */     //   61: aload #5
/*     */     //   63: instanceof li/cil/oc/api/driver/item/Container
/*     */     //   66: ifeq -> 89
/*     */     //   69: aload #5
/*     */     //   71: checkcast li/cil/oc/api/driver/item/Container
/*     */     //   74: astore #6
/*     */     //   76: aload #6
/*     */     //   78: aload_2
/*     */     //   79: invokeinterface providedTier : (Lnet/minecraft/item/ItemStack;)I
/*     */     //   84: istore #7
/*     */     //   86: goto -> 92
/*     */     //   89: iconst_m1
/*     */     //   90: istore #7
/*     */     //   92: iload #7
/*     */     //   94: goto -> 98
/*     */     //   97: iconst_m1
/*     */     //   98: ireturn
/*     */     // Line number table:
/*     */     //   Java source line number -> byte code offset
/*     */     //   #605	-> 0
/*     */     //   #606	-> 11
/*     */     //   #607	-> 23
/*     */     //   #608	-> 38
/*     */     //   #609	-> 89
/*     */     //   #607	-> 92
/*     */     //   #612	-> 97
/*     */     //   #605	-> 98
/*     */     // Local variable table:
/*     */     //   start	length	slot	name	descriptor
/*     */     //   0	99	0	this	Lli/cil/oc/common/tileentity/Robot;
/*     */     //   0	99	1	slot	I
/*     */     //   23	71	2	stack	Lnet/minecraft/item/ItemStack;
/*     */     //   61	38	5	driver	Lli/cil/oc/api/driver/Item; } public boolean isToolSlot(int slot) { return (slot == 0); } public boolean isContainerSlot(int slot) { return containerSlots().contains(slot); } public boolean isInventorySlot(int slot) { return inventorySlots().contains(slot); } public boolean isFloppySlot(int slot) { // Byte code:
/*     */     //   0: aload_0
/*     */     //   1: iload_1
/*     */     //   2: invokevirtual func_70301_a : (I)Lnet/minecraft/item/ItemStack;
/*     */     //   5: ifnull -> 124
/*     */     //   8: aload_0
/*     */     //   9: iload_1
/*     */     //   10: aload_0
/*     */     //   11: iload_1
/*     */     //   12: invokevirtual func_70301_a : (I)Lnet/minecraft/item/ItemStack;
/*     */     //   15: invokevirtual isComponentSlot : (ILnet/minecraft/item/ItemStack;)Z
/*     */     //   18: ifeq -> 124
/*     */     //   21: aload_0
/*     */     //   22: iload_1
/*     */     //   23: invokevirtual func_70301_a : (I)Lnet/minecraft/item/ItemStack;
/*     */     //   26: astore_2
/*     */     //   27: getstatic scala/Option$.MODULE$ : Lscala/Option$;
/*     */     //   30: aload_2
/*     */     //   31: aload_0
/*     */     //   32: invokevirtual getClass : ()Ljava/lang/Class;
/*     */     //   35: invokestatic driverFor : (Lnet/minecraft/item/ItemStack;Ljava/lang/Class;)Lli/cil/oc/api/driver/Item;
/*     */     //   38: invokevirtual apply : (Ljava/lang/Object;)Lscala/Option;
/*     */     //   41: astore_3
/*     */     //   42: aload_3
/*     */     //   43: instanceof scala/Some
/*     */     //   46: ifeq -> 112
/*     */     //   49: aload_3
/*     */     //   50: checkcast scala/Some
/*     */     //   53: astore #4
/*     */     //   55: aload #4
/*     */     //   57: invokevirtual x : ()Ljava/lang/Object;
/*     */     //   60: checkcast li/cil/oc/api/driver/Item
/*     */     //   63: astore #5
/*     */     //   65: aload #5
/*     */     //   67: aload_2
/*     */     //   68: invokeinterface slot : (Lnet/minecraft/item/ItemStack;)Ljava/lang/String;
/*     */     //   73: getstatic li/cil/oc/common/Slot$.MODULE$ : Lli/cil/oc/common/Slot$;
/*     */     //   76: invokevirtual Floppy : ()Ljava/lang/String;
/*     */     //   79: astore #7
/*     */     //   81: dup
/*     */     //   82: ifnonnull -> 94
/*     */     //   85: pop
/*     */     //   86: aload #7
/*     */     //   88: ifnull -> 102
/*     */     //   91: goto -> 106
/*     */     //   94: aload #7
/*     */     //   96: invokevirtual equals : (Ljava/lang/Object;)Z
/*     */     //   99: ifeq -> 106
/*     */     //   102: iconst_1
/*     */     //   103: goto -> 107
/*     */     //   106: iconst_0
/*     */     //   107: istore #6
/*     */     //   109: goto -> 115
/*     */     //   112: iconst_0
/*     */     //   113: istore #6
/*     */     //   115: iload #6
/*     */     //   117: ifeq -> 124
/*     */     //   120: iconst_1
/*     */     //   121: goto -> 125
/*     */     //   124: iconst_0
/*     */     //   125: ireturn
/*     */     // Line number table:
/*     */     //   Java source line number -> byte code offset
/*     */     //   #620	-> 0
/*     */     //   #621	-> 21
/*     */     //   #622	-> 27
/*     */     //   #623	-> 42
/*     */     //   #624	-> 112
/*     */     //   #622	-> 115
/*     */     //   #620	-> 120
/*     */     // Local variable table:
/*     */     //   start	length	slot	name	descriptor
/*     */     //   0	126	0	this	Lli/cil/oc/common/tileentity/Robot;
/*     */     //   0	126	1	slot	I
/*     */     //   27	90	2	stack	Lnet/minecraft/item/ItemStack;
/*     */     //   65	61	5	driver	Lli/cil/oc/api/driver/Item; } public boolean isUpgradeSlot(int slot) { String str = Slot$.MODULE$.Upgrade(); if (containerSlotType(slot) == null) { containerSlotType(slot); if (str != null); } else if (containerSlotType(slot).equals(str)) {  }  } public int componentSlot(String address) { return Predef$.MODULE$.refArrayOps((Object[])components()).indexWhere((Function1)new Robot$$anonfun$componentSlot$1(this, address)); } public final class Robot$$anonfun$componentSlot$1 extends AbstractFunction1<Option<ManagedEnvironment>, Object> implements Serializable { public static final long serialVersionUID = 0L; public final String address$1; public final boolean apply(Option x$2) { return x$2.exists((Function1)new Robot$$anonfun$componentSlot$1$$anonfun$apply$1(this)); } public Robot$$anonfun$componentSlot$1(Robot $outer, String address$1) {} public final class Robot$$anonfun$componentSlot$1$$anonfun$apply$1 extends AbstractFunction1<ManagedEnvironment, Object> implements Serializable { public static final long serialVersionUID = 0L; public final boolean apply(ManagedEnvironment env) { // Byte code:
/*     */         //   0: aload_1
/*     */         //   1: invokeinterface node : ()Lli/cil/oc/api/network/Node;
/*     */         //   6: ifnull -> 51
/*     */         //   9: aload_1
/*     */         //   10: invokeinterface node : ()Lli/cil/oc/api/network/Node;
/*     */         //   15: invokeinterface address : ()Ljava/lang/String;
/*     */         //   20: aload_0
/*     */         //   21: getfield $outer : Lli/cil/oc/common/tileentity/Robot$$anonfun$componentSlot$1;
/*     */         //   24: getfield address$1 : Ljava/lang/String;
/*     */         //   27: astore_2
/*     */         //   28: dup
/*     */         //   29: ifnonnull -> 40
/*     */         //   32: pop
/*     */         //   33: aload_2
/*     */         //   34: ifnull -> 47
/*     */         //   37: goto -> 51
/*     */         //   40: aload_2
/*     */         //   41: invokevirtual equals : (Ljava/lang/Object;)Z
/*     */         //   44: ifeq -> 51
/*     */         //   47: iconst_1
/*     */         //   48: goto -> 52
/*     */         //   51: iconst_0
/*     */         //   52: ireturn
/*     */         // Line number table:
/*     */         //   Java source line number -> byte code offset
/*     */         //   #632	-> 0
/*     */         // Local variable table:
/*     */         //   start	length	slot	name	descriptor
/*     */         //   0	53	0	this	Lli/cil/oc/common/tileentity/Robot$$anonfun$componentSlot$1$$anonfun$apply$1;
/*     */         //   0	53	1	env	Lli/cil/oc/api/network/ManagedEnvironment; } public Robot$$anonfun$componentSlot$1$$anonfun$apply$1(Robot$$anonfun$componentSlot$1 $outer) {} } } public boolean hasRedstoneCard() { return ((IterableLike)containerSlots().$plus$plus((GenTraversableOnce)componentSlots(), IndexedSeq$.MODULE$.canBuildFrom())).exists((Function1)new Robot$$anonfun$hasRedstoneCard$1(this)); } public final class Robot$$anonfun$hasRedstoneCard$1 extends AbstractFunction1.mcZI.sp implements Serializable { public static final long serialVersionUID = 0L; public final boolean apply(int slot) { return apply$mcZI$sp(slot); } public boolean apply$mcZI$sp(int slot) { return BoxesRunTime.unboxToBoolean(Option$.MODULE$.apply(this.$outer.func_70301_a(slot)).fold((Function0)new Robot$$anonfun$hasRedstoneCard$1$$anonfun$apply$mcZI$sp$1(this), (Function1)new Robot$$anonfun$hasRedstoneCard$1$$anonfun$apply$mcZI$sp$2(this))); } public Robot$$anonfun$hasRedstoneCard$1(Robot $outer) {} public final class Robot$$anonfun$hasRedstoneCard$1$$anonfun$apply$mcZI$sp$1 extends AbstractFunction0.mcZ.sp implements Serializable { public static final long serialVersionUID = 0L; public final boolean apply() { return apply$mcZ$sp(); } public boolean apply$mcZ$sp() { return false; } public Robot$$anonfun$hasRedstoneCard$1$$anonfun$apply$mcZI$sp$1(Robot$$anonfun$hasRedstoneCard$1 $outer) {} } public final class Robot$$anonfun$hasRedstoneCard$1$$anonfun$apply$mcZI$sp$2 extends AbstractFunction1<ItemStack, Object> implements Serializable { public static final long serialVersionUID = 0L; public final boolean apply(ItemStack x$3) { return DriverRedstoneCard$.MODULE$.worksWith(x$3, this.$outer.li$cil$oc$common$tileentity$Robot$$anonfun$$$outer().getClass()); } public Robot$$anonfun$hasRedstoneCard$1$$anonfun$apply$mcZI$sp$2(Robot$$anonfun$hasRedstoneCard$1 $outer) {} } } private int computeInventorySize() { return package$.MODULE$.min(maxInventorySize(), BoxesRunTime.unboxToInt(((TraversableOnce)containerSlots().$plus$plus((GenTraversableOnce)componentSlots(), IndexedSeq$.MODULE$.canBuildFrom())).foldLeft(BoxesRunTime.boxToInteger(0), (Function2)new Robot$$anonfun$computeInventorySize$1(this)))); } public final class Robot$$anonfun$computeInventorySize$1 extends AbstractFunction2.mcIII.sp implements Serializable { public static final long serialVersionUID = 0L; public final int apply(int acc, int slot) { return apply$mcIII$sp(acc, slot); } public int apply$mcIII$sp(int acc, int slot) { // Byte code:
/*     */       //   0: iload_1
/*     */       //   1: getstatic scala/Option$.MODULE$ : Lscala/Option$;
/*     */       //   4: aload_0
/*     */       //   5: getfield $outer : Lli/cil/oc/common/tileentity/Robot;
/*     */       //   8: iload_2
/*     */       //   9: invokevirtual func_70301_a : (I)Lnet/minecraft/item/ItemStack;
/*     */       //   12: invokevirtual apply : (Ljava/lang/Object;)Lscala/Option;
/*     */       //   15: astore_3
/*     */       //   16: aload_3
/*     */       //   17: instanceof scala/Some
/*     */       //   20: ifeq -> 123
/*     */       //   23: aload_3
/*     */       //   24: checkcast scala/Some
/*     */       //   27: astore #4
/*     */       //   29: aload #4
/*     */       //   31: invokevirtual x : ()Ljava/lang/Object;
/*     */       //   34: checkcast net/minecraft/item/ItemStack
/*     */       //   37: astore #5
/*     */       //   39: getstatic scala/Option$.MODULE$ : Lscala/Option$;
/*     */       //   42: aload #5
/*     */       //   44: aload_0
/*     */       //   45: getfield $outer : Lli/cil/oc/common/tileentity/Robot;
/*     */       //   48: invokevirtual getClass : ()Ljava/lang/Class;
/*     */       //   51: invokestatic driverFor : (Lnet/minecraft/item/ItemStack;Ljava/lang/Class;)Lli/cil/oc/api/driver/Item;
/*     */       //   54: invokevirtual apply : (Ljava/lang/Object;)Lscala/Option;
/*     */       //   57: astore #7
/*     */       //   59: aload #7
/*     */       //   61: instanceof scala/Some
/*     */       //   64: ifeq -> 113
/*     */       //   67: aload #7
/*     */       //   69: checkcast scala/Some
/*     */       //   72: astore #8
/*     */       //   74: aload #8
/*     */       //   76: invokevirtual x : ()Ljava/lang/Object;
/*     */       //   79: checkcast li/cil/oc/api/driver/Item
/*     */       //   82: astore #9
/*     */       //   84: aload #9
/*     */       //   86: instanceof li/cil/oc/api/driver/item/Inventory
/*     */       //   89: ifeq -> 113
/*     */       //   92: aload #9
/*     */       //   94: checkcast li/cil/oc/api/driver/item/Inventory
/*     */       //   97: astore #10
/*     */       //   99: aload #10
/*     */       //   101: aload #5
/*     */       //   103: invokeinterface inventoryCapacity : (Lnet/minecraft/item/ItemStack;)I
/*     */       //   108: istore #11
/*     */       //   110: goto -> 116
/*     */       //   113: iconst_0
/*     */       //   114: istore #11
/*     */       //   116: iload #11
/*     */       //   118: istore #6
/*     */       //   120: goto -> 126
/*     */       //   123: iconst_0
/*     */       //   124: istore #6
/*     */       //   126: iload #6
/*     */       //   128: iadd
/*     */       //   129: ireturn
/*     */       // Line number table:
/*     */       //   Java source line number -> byte code offset
/*     */       //   #636	-> 0
/*     */       //   #637	-> 16
/*     */       //   #638	-> 59
/*     */       //   #639	-> 113
/*     */       //   #637	-> 116
/*     */       //   #641	-> 123
/*     */       //   #636	-> 126
/*     */       // Local variable table:
/*     */       //   start	length	slot	name	descriptor
/*     */       //   0	130	0	this	Lli/cil/oc/common/tileentity/Robot$$anonfun$computeInventorySize$1;
/*     */       //   0	130	1	acc	I
/*     */       //   0	130	2	slot	I
/*     */       //   39	91	5	stack	Lnet/minecraft/item/ItemStack;
/* 680 */       //   84	46	9	driver	Lli/cil/oc/api/driver/Item; } public Robot$$anonfun$computeInventorySize$1(Robot $outer) {} } private boolean updatingInventorySize() { return this.updatingInventorySize; } private void updatingInventorySize_$eq(boolean x$1) { this.updatingInventorySize = x$1; } public synchronized void updateInventorySize() { if (!updatingInventorySize()) try { updatingInventorySize_$eq(true); int newInventorySize = computeInventorySize(); if (newInventorySize != inventorySize()) { inventorySize_$eq(newInventorySize); int realSize = equipmentInventory().func_70302_i_() + mainInventory().func_70302_i_(); int oldSelected = selectedSlot(); ArrayBuffer removed = (ArrayBuffer)ArrayBuffer$.MODULE$.empty(); RichInt$.MODULE$.until$extension0(Predef$.MODULE$.intWrapper(realSize), func_70302_i_() - componentCount()).foreach((Function1)new Robot$$anonfun$updateInventorySize$3(this, removed)); int copyComponentCount = package$.MODULE$.min(func_70302_i_(), componentCount()); Array$.MODULE$.copy(components(), func_70302_i_() - copyComponentCount, components(), realSize, copyComponentCount); RichInt$.MODULE$.until$extension0(Predef$.MODULE$.intWrapper(package$.MODULE$.max(0, func_70302_i_() - componentCount())), func_70302_i_()).withFilter((Function1)new Robot$$anonfun$updateInventorySize$1(this, realSize)).foreach((Function1)new Robot$$anonfun$updateInventorySize$2(this)); getSizeInventory_$eq(realSize + componentCount()); if (world() != null && isServer()) { removed.foreach((Function1)new Robot$$anonfun$updateInventorySize$4(this)); setSelectedSlot(oldSelected); }  }  return; } finally { updatingInventorySize_$eq(false); }   } public final class Robot$$anonfun$updateInventorySize$3 extends AbstractFunction1<Object, Object> implements Serializable { public static final long serialVersionUID = 0L; private final ArrayBuffer removed$1; public Robot$$anonfun$updateInventorySize$3(Robot $outer, ArrayBuffer removed$1) {} public final Object apply(int slot) { ItemStack stack = this.$outer.func_70301_a(slot); this.$outer.func_70299_a(slot, null); return (stack == null) ? BoxedUnit.UNIT : this.removed$1.$plus$eq(stack); } } public final class Robot$$anonfun$updateInventorySize$1 extends AbstractFunction1.mcZI.sp implements Serializable { public static final long serialVersionUID = 0L; private final int realSize$1; public final boolean apply(int slot) { return apply$mcZI$sp(slot); } public boolean apply$mcZI$sp(int slot) { return (slot < this.realSize$1 || slot >= this.realSize$1 + this.$outer.componentCount()); } public Robot$$anonfun$updateInventorySize$1(Robot $outer, int realSize$1) {} } public final class Robot$$anonfun$updateInventorySize$2 extends AbstractFunction1.mcVI.sp implements Serializable { public static final long serialVersionUID = 0L; public final void apply(int slot) { apply$mcVI$sp(slot); } public Robot$$anonfun$updateInventorySize$2(Robot $outer) {} public void apply$mcVI$sp(int slot) { this.$outer.components()[slot] = (Option<ManagedEnvironment>)None$.MODULE$; } } public final class Robot$$anonfun$updateInventorySize$4 extends AbstractFunction1<ItemStack, EntityItem> implements Serializable { public static final long serialVersionUID = 0L; public Robot$$anonfun$updateInventorySize$4(Robot $outer) {} public final EntityItem apply(ItemStack stack) { (this.$outer.player()).field_71071_by.func_70441_a(stack); return this.$outer.spawnStackInWorld(stack, Option$.MODULE$.apply(this.$outer.facing())); } } public void getSizeInventory_$eq(int x$1) { this.getSizeInventory = x$1; }
/*     */    public int func_70297_j_() {
/* 682 */     return 64;
/*     */   }
/*     */   public ItemStack func_70301_a(int slot) {
/* 685 */     return (slot >= func_70302_i_()) ? null : (
/* 686 */       (slot >= func_70302_i_() - componentCount()) ? 
/* 687 */       info().components()[slot - func_70302_i_() - componentCount()] : 
/*     */       
/* 689 */       Inventory.class.getStackInSlot((Inventory)this, slot));
/*     */   }
/*     */   
/*     */   public void func_70299_a(int slot, ItemStack stack) {
/* 693 */     if (slot < func_70302_i_() - componentCount() && (func_94041_b(slot, stack) || stack == null))
/* 694 */     { if (stack != null && stack.field_77994_a > 1 && isComponentSlot(slot, stack)) {
/* 695 */         Inventory.class.setInventorySlotContents((Inventory)this, slot, stack.func_77979_a(1));
/* 696 */         if (stack.field_77994_a > 0 && isServer()) {
/* 697 */           (player()).field_71071_by.func_70441_a(stack);
/* 698 */           spawnStackInWorld(stack, Option$.MODULE$.apply(facing()));
/*     */         } 
/*     */       } else {
/* 701 */         Inventory.class.setInventorySlotContents((Inventory)this, slot, stack);
/*     */       }  }
/* 703 */     else if (stack != null && stack.field_77994_a > 0 && !(world()).field_72995_K) { spawnStackInWorld(stack, Option$.MODULE$.apply(ForgeDirection.UP)); }
/*     */   
/*     */   }
/*     */   public boolean func_70300_a(EntityPlayer player) {
/* 707 */     return (Computer.class.isUseableByPlayer(this, player) && (!isCreative() || player.field_71075_bZ.field_75098_d));
/*     */   }
/*     */ 
/*     */ 
/*     */ 
/*     */ 
/*     */ 
/*     */ 
/*     */ 
/*     */ 
/*     */   
/*     */   public boolean func_94041_b(int slot, ItemStack stack) {
/*     */     // Byte code:
/*     */     //   0: new scala/Tuple2
/*     */     //   3: dup
/*     */     //   4: iload_1
/*     */     //   5: invokestatic boxToInteger : (I)Ljava/lang/Integer;
/*     */     //   8: getstatic scala/Option$.MODULE$ : Lscala/Option$;
/*     */     //   11: aload_2
/*     */     //   12: aload_0
/*     */     //   13: invokevirtual getClass : ()Ljava/lang/Class;
/*     */     //   16: invokestatic driverFor : (Lnet/minecraft/item/ItemStack;Ljava/lang/Class;)Lli/cil/oc/api/driver/Item;
/*     */     //   19: invokevirtual apply : (Ljava/lang/Object;)Lscala/Option;
/*     */     //   22: invokespecial <init> : (Ljava/lang/Object;Ljava/lang/Object;)V
/*     */     //   25: astore_3
/*     */     //   26: aload_3
/*     */     //   27: ifnull -> 48
/*     */     //   30: aload_3
/*     */     //   31: invokevirtual _1$mcI$sp : ()I
/*     */     //   34: istore #4
/*     */     //   36: iconst_0
/*     */     //   37: iload #4
/*     */     //   39: if_icmpne -> 48
/*     */     //   42: iconst_1
/*     */     //   43: istore #5
/*     */     //   45: goto -> 249
/*     */     //   48: aload_3
/*     */     //   49: ifnull -> 221
/*     */     //   52: aload_3
/*     */     //   53: invokevirtual _1$mcI$sp : ()I
/*     */     //   56: istore #6
/*     */     //   58: aload_3
/*     */     //   59: invokevirtual _2 : ()Ljava/lang/Object;
/*     */     //   62: checkcast scala/Option
/*     */     //   65: astore #7
/*     */     //   67: aload #7
/*     */     //   69: instanceof scala/Some
/*     */     //   72: ifeq -> 221
/*     */     //   75: aload #7
/*     */     //   77: checkcast scala/Some
/*     */     //   80: astore #8
/*     */     //   82: aload #8
/*     */     //   84: invokevirtual x : ()Ljava/lang/Object;
/*     */     //   87: checkcast li/cil/oc/api/driver/Item
/*     */     //   90: astore #9
/*     */     //   92: aload_0
/*     */     //   93: iload #6
/*     */     //   95: invokevirtual isContainerSlot : (I)Z
/*     */     //   98: ifeq -> 221
/*     */     //   101: aload #9
/*     */     //   103: getstatic li/cil/oc/integration/opencomputers/DriverScreen$.MODULE$ : Lli/cil/oc/integration/opencomputers/DriverScreen$;
/*     */     //   106: astore #10
/*     */     //   108: dup
/*     */     //   109: ifnonnull -> 121
/*     */     //   112: pop
/*     */     //   113: aload #10
/*     */     //   115: ifnull -> 215
/*     */     //   118: goto -> 129
/*     */     //   121: aload #10
/*     */     //   123: invokevirtual equals : (Ljava/lang/Object;)Z
/*     */     //   126: ifne -> 215
/*     */     //   129: aload #9
/*     */     //   131: getstatic li/cil/oc/integration/opencomputers/DriverKeyboard$.MODULE$ : Lli/cil/oc/integration/opencomputers/DriverKeyboard$;
/*     */     //   134: astore #11
/*     */     //   136: dup
/*     */     //   137: ifnonnull -> 149
/*     */     //   140: pop
/*     */     //   141: aload #11
/*     */     //   143: ifnull -> 215
/*     */     //   146: goto -> 157
/*     */     //   149: aload #11
/*     */     //   151: invokevirtual equals : (Ljava/lang/Object;)Z
/*     */     //   154: ifne -> 215
/*     */     //   157: aload #9
/*     */     //   159: aload_2
/*     */     //   160: invokeinterface slot : (Lnet/minecraft/item/ItemStack;)Ljava/lang/String;
/*     */     //   165: aload_0
/*     */     //   166: iload #6
/*     */     //   168: invokevirtual containerSlotType : (I)Ljava/lang/String;
/*     */     //   171: astore #12
/*     */     //   173: dup
/*     */     //   174: ifnonnull -> 186
/*     */     //   177: pop
/*     */     //   178: aload #12
/*     */     //   180: ifnull -> 194
/*     */     //   183: goto -> 215
/*     */     //   186: aload #12
/*     */     //   188: invokevirtual equals : (Ljava/lang/Object;)Z
/*     */     //   191: ifeq -> 215
/*     */     //   194: aload #9
/*     */     //   196: aload_2
/*     */     //   197: invokeinterface tier : (Lnet/minecraft/item/ItemStack;)I
/*     */     //   202: aload_0
/*     */     //   203: iload #6
/*     */     //   205: invokevirtual containerSlotTier : (I)I
/*     */     //   208: if_icmpgt -> 215
/*     */     //   211: iconst_1
/*     */     //   212: goto -> 216
/*     */     //   215: iconst_0
/*     */     //   216: istore #5
/*     */     //   218: goto -> 249
/*     */     //   221: aload_3
/*     */     //   222: ifnull -> 246
/*     */     //   225: aload_3
/*     */     //   226: invokevirtual _1$mcI$sp : ()I
/*     */     //   229: istore #13
/*     */     //   231: aload_0
/*     */     //   232: iload #13
/*     */     //   234: invokevirtual isInventorySlot : (I)Z
/*     */     //   237: ifeq -> 246
/*     */     //   240: iconst_1
/*     */     //   241: istore #5
/*     */     //   243: goto -> 249
/*     */     //   246: iconst_0
/*     */     //   247: istore #5
/*     */     //   249: iload #5
/*     */     //   251: ireturn
/*     */     // Line number table:
/*     */     //   Java source line number -> byte code offset
/*     */     //   #709	-> 0
/*     */     //   #710	-> 30
/*     */     //   #709	-> 48
/*     */     //   #711	-> 52
/*     */     //   #719	-> 101
/*     */     //   #720	-> 129
/*     */     //   #721	-> 157
/*     */     //   #722	-> 194
/*     */     //   #721	-> 211
/*     */     //   #709	-> 221
/*     */     //   #723	-> 225
/*     */     //   #724	-> 246
/*     */     //   #709	-> 249
/*     */     // Local variable table:
/*     */     //   start	length	slot	name	descriptor
/*     */     //   0	252	0	this	Lli/cil/oc/common/tileentity/Robot;
/*     */     //   0	252	1	slot	I
/*     */     //   0	252	2	stack	Lnet/minecraft/item/ItemStack;
/*     */     //   58	194	6	i	I
/*     */     //   92	160	9	driver	Lli/cil/oc/api/driver/Item;
/*     */     //   231	21	13	i	I
/*     */   }
/*     */ 
/*     */ 
/*     */ 
/*     */ 
/*     */ 
/*     */ 
/*     */ 
/*     */   
/*     */   public boolean dropSlot(int slot, int count, Option direction) {
/* 730 */     return InventoryUtils$.MODULE$.dropSlot(BlockPosition$.MODULE$.apply(x(), y(), z(), world()), (IInventory)mainInventory(), slot, count, direction);
/*     */   }
/*     */   
/* 733 */   public void dropAllSlots() { InventoryUtils$.MODULE$.dropSlot(BlockPosition$.MODULE$.apply(x(), y(), z(), world()), (IInventory)this, 0, 2147483647, InventoryUtils$.MODULE$.dropSlot$default$5());
/* 734 */     containerSlots().foreach((Function1)new Robot$$anonfun$dropAllSlots$1(this));
/*     */ 
/*     */     
/* 737 */     InventoryUtils$.MODULE$.dropAllSlots(BlockPosition$.MODULE$.apply(x(), y(), z(), world()), (IInventory)mainInventory()); } public final class Robot$$anonfun$dropAllSlots$1 extends AbstractFunction1.mcZI.sp implements Serializable {
/*     */     public static final long serialVersionUID = 0L; public final boolean apply(int slot) {
/*     */       return apply$mcZI$sp(slot);
/*     */     } public Robot$$anonfun$dropAllSlots$1(Robot $outer) {} public boolean apply$mcZI$sp(int slot) {
/*     */       return InventoryUtils$.MODULE$.dropSlot(BlockPosition$.MODULE$.apply(this.$outer.x(), this.$outer.y(), this.$outer.z(), this.$outer.world()), (IInventory)this.$outer, slot, 2147483647, InventoryUtils$.MODULE$.dropSlot$default$5());
/*     */     } } public boolean func_102008_b(int slot, ItemStack stack, int side) {
/* 743 */     return Predef$.MODULE$.intArrayOps(func_94128_d(side)).contains(BoxesRunTime.boxToInteger(slot));
/*     */   }
/*     */   public boolean func_102007_a(int slot, ItemStack stack, int side) {
/* 746 */     return (Predef$.MODULE$.intArrayOps(func_94128_d(side)).contains(BoxesRunTime.boxToInteger(slot)) && 
/* 747 */       func_94041_b(slot, stack));
/*     */   } public int[] func_94128_d(int side) {
/*     */     int[] arrayOfInt;
/* 750 */     ForgeDirection forgeDirection = toLocal(ForgeDirection.getOrientation(side));
/* 751 */     if (ForgeDirection.WEST.equals(forgeDirection)) { arrayOfInt = new int[] { 0 }; }
/* 752 */     else if (ForgeDirection.EAST.equals(forgeDirection)) { arrayOfInt = (int[])containerSlots().toArray(ClassTag$.MODULE$.Int()); }
/* 753 */     else { arrayOfInt = (int[])inventorySlots().toArray(ClassTag$.MODULE$.Int()); }
/*     */     
/*     */     return arrayOfInt;
/*     */   }
/*     */   
/*     */   public Option<ManagedEnvironment> tryGetTank(int tank) {
/* 759 */     ManagedEnvironment[] tanks = (ManagedEnvironment[])Predef$.MODULE$.refArrayOps((Object[])components()).collect((PartialFunction)new Robot$$anonfun$1(this), Array$.MODULE$.canBuildFrom(ClassTag$.MODULE$.apply(ManagedEnvironment.class)));
/*     */ 
/*     */     
/* 762 */     return (tank < 0 || tank >= tanks.length) ? (Option<ManagedEnvironment>)None$.MODULE$ : 
/* 763 */       Option$.MODULE$.apply(tanks[tank]);
/*     */   } public final class Robot$$anonfun$1 extends AbstractPartialFunction<Option<ManagedEnvironment>, ManagedEnvironment> implements Serializable {
/*     */     public static final long serialVersionUID = 0L; public final <A1 extends Option<ManagedEnvironment>, B1> B1 applyOrElse(Option x1, Function1 default) { Option option = x1; if (option instanceof Some) { Some some = (Some)option; ManagedEnvironment tank = (ManagedEnvironment)some.x(); if (tank instanceof IFluidTank) { ManagedEnvironment managedEnvironment; return (B1)(managedEnvironment = tank); }  }  return (B1)default.apply(x1); } public final boolean isDefinedAt(Option x1) { Option option = x1; if (option instanceof Some) { Some some = (Some)option; ManagedEnvironment tank = (ManagedEnvironment)some.x(); if (tank instanceof IFluidTank) return true;  }  return false; } public Robot$$anonfun$1(Robot $outer) {} }
/* 766 */   public int tankCount() { return Predef$.MODULE$.refArrayOps((Object[])components()).count((Function1)new Robot$$anonfun$tankCount$1(this)); } public final class Robot$$anonfun$tankCount$1 extends AbstractFunction1<Option<ManagedEnvironment>, Object> implements Serializable { public static final long serialVersionUID = 0L; public final boolean apply(Option x0$1) { Option option = x0$1;
/* 767 */       if (option instanceof Some) { Some some = (Some)option; ManagedEnvironment tank = (ManagedEnvironment)some.x(); if (tank instanceof IFluidTank)
/*     */           return true;  }
/*     */       
/*     */       return false; } public Robot$$anonfun$tankCount$1(Robot $outer) {} } public ManagedEnvironment getFluidTank(int tank) {
/* 771 */     return (ManagedEnvironment)tryGetTank(tank).orNull(Predef$.MODULE$.$conforms());
/*     */   }
/*     */   
/*     */   public int fill(ForgeDirection from, FluidStack resource, boolean doFill) {
/*     */     boolean bool;
/* 776 */     Option<ManagedEnvironment> option = tryGetTank(selectedTank());
/* 777 */     if (option instanceof Some) { Some some = (Some)option; ManagedEnvironment t = (ManagedEnvironment)some.x();
/* 778 */       bool = ((IFluidTank)t).fill(resource, doFill); }
/* 779 */     else { bool = false; }
/*     */     
/*     */     return bool;
/*     */   } public FluidStack drain(ForgeDirection from, FluidStack resource, boolean doDrain) {
/* 783 */     Option<ManagedEnvironment> option = tryGetTank(selectedTank());
/* 784 */     if (option instanceof Some) { Some some = (Some)option; ManagedEnvironment t = (ManagedEnvironment)some.x(); if (((IFluidTank)t).getFluid() != null && ((IFluidTank)t).getFluid().isFluidEqual(resource))
/* 785 */         return ((IFluidTank)t).drain(resource.amount, doDrain);  }
/* 786 */      return null;
/*     */   }
/*     */   public FluidStack drain(ForgeDirection from, int maxDrain, boolean doDrain) {
/*     */     FluidStack fluidStack;
/* 790 */     Option<ManagedEnvironment> option = tryGetTank(selectedTank());
/* 791 */     if (option instanceof Some) { Some some = (Some)option; ManagedEnvironment t = (ManagedEnvironment)some.x();
/* 792 */       fluidStack = ((IFluidTank)t).drain(maxDrain, doDrain); }
/* 793 */     else { fluidStack = null; }
/*     */     
/*     */     return fluidStack;
/*     */   }
/*     */ 
/*     */ 
/*     */   
/*     */   public boolean canFill(ForgeDirection from, Fluid fluid) {
/*     */     // Byte code:
/*     */     //   0: aload_0
/*     */     //   1: aload_0
/*     */     //   2: invokevirtual selectedTank : ()I
/*     */     //   5: invokevirtual tryGetTank : (I)Lscala/Option;
/*     */     //   8: astore_3
/*     */     //   9: aload_3
/*     */     //   10: instanceof scala/Some
/*     */     //   13: ifeq -> 92
/*     */     //   16: aload_3
/*     */     //   17: checkcast scala/Some
/*     */     //   20: astore #4
/*     */     //   22: aload #4
/*     */     //   24: invokevirtual x : ()Ljava/lang/Object;
/*     */     //   27: checkcast li/cil/oc/api/network/ManagedEnvironment
/*     */     //   30: astore #5
/*     */     //   32: aload #5
/*     */     //   34: checkcast net/minecraftforge/fluids/IFluidTank
/*     */     //   37: invokeinterface getFluid : ()Lnet/minecraftforge/fluids/FluidStack;
/*     */     //   42: ifnull -> 82
/*     */     //   45: aload #5
/*     */     //   47: checkcast net/minecraftforge/fluids/IFluidTank
/*     */     //   50: invokeinterface getFluid : ()Lnet/minecraftforge/fluids/FluidStack;
/*     */     //   55: invokevirtual getFluid : ()Lnet/minecraftforge/fluids/Fluid;
/*     */     //   58: aload_2
/*     */     //   59: astore #7
/*     */     //   61: dup
/*     */     //   62: ifnonnull -> 74
/*     */     //   65: pop
/*     */     //   66: aload #7
/*     */     //   68: ifnull -> 82
/*     */     //   71: goto -> 86
/*     */     //   74: aload #7
/*     */     //   76: invokevirtual equals : (Ljava/lang/Object;)Z
/*     */     //   79: ifeq -> 86
/*     */     //   82: iconst_1
/*     */     //   83: goto -> 87
/*     */     //   86: iconst_0
/*     */     //   87: istore #6
/*     */     //   89: goto -> 95
/*     */     //   92: iconst_0
/*     */     //   93: istore #6
/*     */     //   95: iload #6
/*     */     //   97: ireturn
/*     */     // Line number table:
/*     */     //   Java source line number -> byte code offset
/*     */     //   #798	-> 0
/*     */     //   #799	-> 9
/*     */     //   #800	-> 92
/*     */     //   #798	-> 95
/*     */     // Local variable table:
/*     */     //   start	length	slot	name	descriptor
/*     */     //   0	98	0	this	Lli/cil/oc/common/tileentity/Robot;
/*     */     //   0	98	1	from	Lnet/minecraftforge/common/util/ForgeDirection;
/*     */     //   0	98	2	fluid	Lnet/minecraftforge/fluids/Fluid;
/*     */     //   32	66	5	t	Lli/cil/oc/api/network/ManagedEnvironment;
/*     */   }
/*     */ 
/*     */   
/*     */   public boolean canDrain(ForgeDirection from, Fluid fluid) {
/*     */     // Byte code:
/*     */     //   0: aload_0
/*     */     //   1: aload_0
/*     */     //   2: invokevirtual selectedTank : ()I
/*     */     //   5: invokevirtual tryGetTank : (I)Lscala/Option;
/*     */     //   8: astore_3
/*     */     //   9: aload_3
/*     */     //   10: instanceof scala/Some
/*     */     //   13: ifeq -> 92
/*     */     //   16: aload_3
/*     */     //   17: checkcast scala/Some
/*     */     //   20: astore #4
/*     */     //   22: aload #4
/*     */     //   24: invokevirtual x : ()Ljava/lang/Object;
/*     */     //   27: checkcast li/cil/oc/api/network/ManagedEnvironment
/*     */     //   30: astore #5
/*     */     //   32: aload #5
/*     */     //   34: checkcast net/minecraftforge/fluids/IFluidTank
/*     */     //   37: invokeinterface getFluid : ()Lnet/minecraftforge/fluids/FluidStack;
/*     */     //   42: ifnull -> 86
/*     */     //   45: aload #5
/*     */     //   47: checkcast net/minecraftforge/fluids/IFluidTank
/*     */     //   50: invokeinterface getFluid : ()Lnet/minecraftforge/fluids/FluidStack;
/*     */     //   55: invokevirtual getFluid : ()Lnet/minecraftforge/fluids/Fluid;
/*     */     //   58: aload_2
/*     */     //   59: astore #7
/*     */     //   61: dup
/*     */     //   62: ifnonnull -> 74
/*     */     //   65: pop
/*     */     //   66: aload #7
/*     */     //   68: ifnull -> 82
/*     */     //   71: goto -> 86
/*     */     //   74: aload #7
/*     */     //   76: invokevirtual equals : (Ljava/lang/Object;)Z
/*     */     //   79: ifeq -> 86
/*     */     //   82: iconst_1
/*     */     //   83: goto -> 87
/*     */     //   86: iconst_0
/*     */     //   87: istore #6
/*     */     //   89: goto -> 95
/*     */     //   92: iconst_0
/*     */     //   93: istore #6
/*     */     //   95: iload #6
/*     */     //   97: ireturn
/*     */     // Line number table:
/*     */     //   Java source line number -> byte code offset
/*     */     //   #805	-> 0
/*     */     //   #806	-> 9
/*     */     //   #807	-> 92
/*     */     //   #805	-> 95
/*     */     // Local variable table:
/*     */     //   start	length	slot	name	descriptor
/*     */     //   0	98	0	this	Lli/cil/oc/common/tileentity/Robot;
/*     */     //   0	98	1	from	Lnet/minecraftforge/common/util/ForgeDirection;
/*     */     //   0	98	2	fluid	Lnet/minecraftforge/fluids/Fluid;
/*     */     //   32	66	5	t	Lli/cil/oc/api/network/ManagedEnvironment;
/*     */   }
/*     */ 
/*     */   
/*     */   public FluidTankInfo[] getTankInfo(ForgeDirection from)
/*     */   {
/* 812 */     return (FluidTankInfo[])Predef$.MODULE$.refArrayOps((Object[])components()).collect((PartialFunction)new Robot$$anonfun$getTankInfo$1(this), Array$.MODULE$.canBuildFrom(ClassTag$.MODULE$.apply(FluidTankInfo.class))); } public final class Robot$$anonfun$getTankInfo$1 extends AbstractPartialFunction<Option<ManagedEnvironment>, FluidTankInfo> implements Serializable { public static final long serialVersionUID = 0L; public final <A1 extends Option<ManagedEnvironment>, B1> B1 applyOrElse(Option x2, Function1 default) { Option option = x2;
/* 813 */       if (option instanceof Some) { Some some = (Some)option; ManagedEnvironment t = (ManagedEnvironment)some.x(); if (t instanceof IFluidTank) { ManagedEnvironment managedEnvironment = t; return (B1)((IFluidTank)managedEnvironment).getInfo(); }  }  return (B1)default.apply(x2); } public final boolean isDefinedAt(Option x2) { Option option = x2; if (option instanceof Some) { Some some = (Some)option; ManagedEnvironment t = (ManagedEnvironment)some.x(); if (t instanceof IFluidTank)
/*     */           return true;  }
/*     */       
/*     */       return false; }
/*     */ 
/*     */     
/*     */     public Robot$$anonfun$getTankInfo$1(Robot $outer) {} }
/*     */    }


/* Location:              C:\Users\shame\AppData\Roaming\PrismLauncher\instances\GT_New_Horizons_2.7.4_Java_17-21\.minecraft\mods\OpenComputers-1.10.30-GTNH.jar!\li\cil\oc\common\tileentity\Robot.class
 * Java compiler version: 8 (52.0)
 * JD-Core Version:       1.1.3
 */