/*     */ package li.cil.oc.common.tileentity;@ScalaSignature(bytes = "\006\001\025Md\001B\001\003\0015\021!BU8c_R\004&o\034=z\025\t\031A!\001\006uS2,WM\034;jifT!!\002\004\002\r\r|W.\\8o\025\t9\001\"\001\002pG*\021\021BC\001\004G&d'\"A\006\002\0051L7\001A\n\b\00199R\004\t\024/!\tyQ#D\001\021\025\t\031\021C\003\002\023'\005IQ.\0338fGJ\fg\r\036\006\002)\005\031a.\032;\n\005Y\001\"A\003+jY\026,e\016^5usB\021\001dG\007\0023)\021!DA\001\007iJ\f\027\016^:\n\005qI\"\001C\"p[B,H/\032:\021\005aq\022BA\020\032\005A\001vn^3s\023:4wN]7bi&|g\016\005\002\"I5\t!E\003\002$#\005I\021N\034<f]R|'/_\005\003K\t\022q\"S*jI\026$\027J\034<f]R|'/\037\t\003O1j\021\001\013\006\003S)\naA\0327vS\022\034(BA\026\024\0039i\027N\\3de\0064GOZ8sO\026L!!\f\025\003\033%3E.^5e\021\006tG\r\\3s!\tyC'D\0011\025\t\t$'\001\005j]R,'O\\1m\025\t\031d!A\002ba&L!!\016\031\003\013I{'m\034;\t\021]\002!Q1A\005\002a\nQA]8c_R,\022!\017\t\003umj\021AA\005\003k\tA\001\"\020\001\003\002\003\006I!O\001\007e>\024w\016\036\021\t\013}\002A\021\001!\002\rqJg.\033;?)\t\t%\t\005\002;\001!)qG\020a\001s!)q\b\001C\001\tR\t\021\tC\004G\001\t\007I\021I$\002\t9|G-Z\013\002\021B\021\021\nT\007\002\025*\0211JM\001\b]\026$xo\034:l\023\ti%JA\005D_6\004xN\\3oi\"1q\n\001Q\001\n!\013QA\\8eK\002BQ!\025\001\005BI\013q!\\1dQ&tW\rF\001T!\t!f+D\001V\025\t\t&'\003\002X+\n9Q*Y2iS:,\007\"B-\001\t\003R\026\001\002;jKJ$\022a\027\t\0039~k\021!\030\006\002=\006)1oY1mC&\021\001-\030\002\004\023:$\b\"\0022\001\t\003\032\027AE3rk&\004X.\0328u\023:4XM\034;pef$\022\001\032\n\004K&\fh\001\0024\001\001\021\024A\002\020:fM&tW-\\3oizJ!\001[\036\002'\025\fX/\0339nK:$\030J\034<f]R|'/\037\021\021\005)|W\"A6\013\0051l\027\001\0027b]\036T\021A\\\001\005U\0064\030-\003\002qW\n1qJ\0316fGR\004\"A\035;\016\003MT!a\t\003\n\005U\034(AD%om\026tGo\034:z!J|\0070\037\005\006G\025$\t\005\017\005\006q\002!\t%_\001\016[\006Lg.\0238wK:$xN]=\025\003i\0242a_5r\r\0211\007\001\001>\n\005u\\\024AD7bS:LeN^3oi>\024\030\020\t\005\006Gm$\t\005\017\005\b\003\003\001A\021IA\002\003\021!\030M\\6\025\005\005\025!#BA\004S\0065a!\0024\001\001\005\025\021bAA\006w\005)A/\0318lAA\031q&a\004\n\007\005E\001GA\005Nk2$\030\016V1oW\"A\021QCA\004\t\003\n9\"\001\007hKR4E.^5e)\006t7\016\006\003\002\032\0055\"CBA\016\003C\t9CB\003g\001\001\tIBC\002\002 1\ta\001\020:p_Rt\004cA%\002$%\031\021Q\005&\003%5\013g.Y4fI\026sg/\033:p]6,g\016\036\t\004O\005%\022bAA\026Q\tQ\021J\0227vS\022$\026M\\6\t\017\005=\0221\003a\0017\006)\021N\0343fq\"1\0211\007\001\005Bi\013Ab]3mK\016$X\rZ*m_RDq!a\016\001\t\003\nI$A\btKR\034V\r\\3di\026$7\013\\8u)\021\tY$!\021\021\007q\013i$C\002\002@u\023A!\0268ji\"9\021qFA\033\001\004Y\006BBA#\001\021\005#,\001\007tK2,7\r^3e)\006t7\016C\004\002J\001!\t%a\023\002\037M,GoU3mK\016$X\r\032+b].$B!a\017\002N!9\021qFA$\001\004Y\006bBA)\001\021\005\0231K\001\007a2\f\0270\032:\025\005\005U\003\003BA,\003Cj!!!\027\013\t\005m\023QL\001\006C\036,g\016\036\006\004\003?2\021AB:feZ,'/\003\003\002d\005e#A\002)mCf,'\017C\004\002h\001!\t%!\033\002\t9\fW.\032\013\003\003W\0022A[A7\023\r\tyg\033\002\007'R\024\030N\\4\t\017\005M\004\001\"\021\002v\00591/\032;OC6,G\003BA\036\003oB\001\"a\032\002r\001\007\021\021\020\t\005\003w\n\tID\002]\003{J1!a ^\003\031\001&/\0323fM&!\021qNAB\025\r\ty(\030\005\b\003\017\003A\021IA5\003%ywO\\3s\035\006lW\rC\004\002\f\002!\t%!$\002\023=<h.\032:V+&#ECAAH!\021\t\t*a&\016\005\005M%bAAK[\006!Q\017^5m\023\021\tI*a%\003\tU+\026\n\022\005\b\003;\003A\021IAP\003E\031wN\0348fGR\034u.\0349p]\026tGo\035\013\003\003wAq!a)\001\t\003\ny*\001\013eSN\034wN\0348fGR\034u.\0349p]\026tGo\035\005\b\003O\003A\021IAU\003%I7OU;o]&tw-\006\002\002,B\031A,!,\n\007\005=VLA\004C_>dW-\0318\t\017\005M\006\001\"\021\0026\006Q1/\032;Sk:t\027N\\4\025\t\005m\022q\027\005\t\003s\013\t\f1\001\002,\006)a/\0317vK\"9\021Q\030\001\005B\005}\026!D:i_VdG-\0218j[\006$X\r\006\002\002,\"1\0211\031\001\005Bi\013abY8na>tWM\034;D_VtG\017C\004\002H\002!\t%!3\002%\035,GoQ8na>tWM\034;J]Ncw\016\036\013\005\003\027\f\t\016E\002J\003\033L1!a4K\005-)eN^5s_:lWM\034;\t\017\005=\022Q\031a\0017\"9\021Q\033\001\005B\005]\027aD:z]\016D'o\0348ju\026\034Fn\034;\025\t\005m\022\021\034\005\b\0037\f\031\0161\001\\\003\021\031Hn\034;\t\017\005}\007\001\"\001\002b\006)1\017^1siR1\0211]Ax\003s\004R\001XAs\003SL1!a:^\005\025\t%O]1z!\ra\0261^\005\004\003[l&AB!osJ+g\r\003\005\002r\006u\007\031AAz\003\035\031wN\034;fqR\0042\001VA{\023\r\t90\026\002\b\007>tG/\032=u\021!\tY0!8A\002\005u\030\001B1sON\0042\001VA\000\023\r\021\t!\026\002\n\003J<W/\\3oiND\003\"!8\003\006\t-!Q\002\t\004)\n\035\021b\001B\005+\nA1)\0317mE\006\0347.A\002e_\016\f#Aa\004\002\025\032,hn\031;j_:D\023F\0172p_2,\027M\034\021.[\001\032F/\031:ug\002\"\b.\032\021s_\n|GO\f\021SKR,(O\\:!iJ,X\rI5gAQDW\rI:uCR,\007e\0315b]\036,GM\f\005\b\005'\001A\021\001B\013\003\021\031Ho\0349\025\r\005\r(q\003B\r\021!\t\tP!\005A\002\005M\b\002CA~\005#\001\r!!@)\021\tE!Q\001B\006\005;\t#Aa\b\002\023\032,hn\031;j_:D\023F\0172p_2,\027M\034\021.[\001\032Fo\0349tAQDW\r\t:pE>$h\006\t*fiV\024hn\035\021ueV,\007%\0334!i\",\007e\035;bi\026\0043\r[1oO\026$g\006C\004\002(\002!\tAa\t\025\r\005\r(Q\005B\024\021!\t\tP!\tA\002\005M\b\002CA~\005C\001\r!!@)\031\t\005\"Q\001B\026\005[\021YAa\f\002\r\021L'/Z2u3\005\t\021E\001B\031\003m2WO\\2uS>t\007&\013\036c_>dW-\0318![5\002#+\032;ve:\034\be\0365fi\",'\017\t;iK\002\022xNY8uA%\034\bE];o]&twM\f\005\b\003g\002A\021\001B\033)\031\t\031Oa\016\003:!A\021\021\037B\032\001\004\t\031\020\003\005\002|\nM\002\031AAQ!\021\031D!\002\003\f\tu\022E\001B \003\0214WO\\2uS>t\007F\\1nKj\0023\017\036:j]\036L#h\035;sS:<\007%L\027!'\026$8\017I1!]\026<\bE\\1nK\002\ng\016\032\021sKR,(O\\:!i\",\007e\0347eA9\fW.\032\030!%>\024w\016\036\021nkN$\bE\\8uA\t,\007E];o]&tw\rC\004\003D\001!\tA!\022\002\017\035,GOT1nKR1\0211\035B$\005\023B\001\"!=\003B\001\007\0211\037\005\t\003w\024\t\0051\001\002~\"B!\021\tB\003\005\027\021i%\t\002\003P\005ac-\0368di&|g\016K\025;gR\024\030N\\4![5\002#+\032;ve:\034\b\005\0365fAI|'m\034;!]\006lWM\f\005\b\005'\002A\021\tB+\003%yg.T3tg\006<W\r\006\003\002<\t]\003\002\003B-\005#\002\rAa\027\002\0175,7o]1hKB\031\021J!\030\n\007\t}#JA\004NKN\034\030mZ3\t\017\t\r\004\001\"\021\002 \006aQ\017\0353bi\026,e\016^5us\"9!q\r\001\005B\005}\025\001\003<bY&$\027\r^3\t\017\t-\004\001\"\021\002 \0069A-[:q_N,\007b\002B8\001\021\005#\021O\001\025e\026\fGM\022:p[:\023EKR8s'\026\024h/\032:\025\t\005m\"1\017\005\t\005k\022i\0071\001\003x\005\031aN\031;\021\t\te$QP\007\003\005wR1A!\036\022\023\021\021yHa\037\003\0359\023E\013V1h\007>l\007o\\;oI\"9!1\021\001\005B\t\025\025aE<sSR,Gk\034(C)\032{'oU3sm\026\024H\003BA\036\005\017C\001B!\036\003\002\002\007!q\017\005\b\005\027\003A\021\tBG\003\021\031\030M^3\025\t\005m\"q\022\005\t\005k\022I\t1\001\003x!9!1\023\001\005B\tU\025\001\0027pC\022$B!a\017\003\030\"A!Q\017BI\001\004\0219\bC\004\003\034\002!\tE!(\002)I,\027\r\032$s_6t%\t\026$pe\016c\027.\0328u)\021\tYDa(\t\021\tU$\021\024a\001\005oB\003B!'\003$\006e&1\030\t\005\005K\0239,\004\002\003(*!!\021\026BV\003)\021X\r\\1v]\016DWM\035\006\005\005[\023y+A\002g[2TAA!-\0034\006!Qn\0343t\025\t\021),A\002da^LAA!/\003(\nA1+\0333f\037:d\027\020\n\002\003>&!!q\030Ba\003\031\031E*S#O)*!!1\031BT\003\021\031\026\016Z3\t\017\t\035\007\001\"\021\003J\006\031rO]5uKR{gJ\021+G_J\034E.[3oiR!\0211\bBf\021!\021)H!2A\002\t]\004b\002Bh\001\021\005#\021[\001\034O\026$X*\031=SK:$WM\035#jgR\fgnY3TcV\f'/\0323\025\005\tM\007c\001/\003V&\031!q[/\003\r\021{WO\0317f\021\035\021Y\016\001C!\005;\fAcZ3u%\026tG-\032:C_VtG-\0338h\005>DHC\001Bp!\021\021\tO!:\016\005\t\r(bAAK#%!!q\035Br\0055\t\0050[:BY&<g.\0323C\005\"9!1\036\001\005B\t5\030AE:i_VdGMU3oI\026\024\030J\034)bgN$B!a+\003p\"9!\021\037Bu\001\004Y\026\001\0029bgNDqA!>\001\t\003\ny*A\005nCJ\\G)\033:us\"9!\021 \001\005B\tm\030!C8o\003:\fG.\037>f)1\021ip!\002\004\026\re11EB\024!\025a\026Q\035B\000!\rI5\021A\005\004\007\007Q%\001\002(pI\026D\001\"!\025\003x\002\0071q\001\t\005\007\023\031\t\"\004\002\004\f)!\021\021KB\007\025\r\031y!E\001\007K:$\030\016^=\n\t\rM11\002\002\r\013:$\030\016^=QY\006LXM\035\005\b\007/\0219\0201\001\\\003\021\031\030\016Z3\t\021\rm!q\037a\001\007;\tA\001[5u1B\031Ala\b\n\007\r\005RLA\003GY>\fG\017\003\005\004&\t]\b\031AB\017\003\021A\027\016^-\t\021\r%\"q\037a\001\007;\tA\001[5u5\"Q1Q\006\001C\002\023E#aa\f\002\r}Kg\016];u+\t\031\t\004\005\003]\003K\\\006\002CB\033\001\001\006Ia!\r\002\017}Kg\016];uA!Q1\021\b\001C\002\023E#aa\f\002\017}{W\017\0369vi\"A1Q\b\001!\002\023\031\t$\001\005`_V$\b/\036;!\021)\031\t\005\001b\001\n#\02211I\001\016?\n,h\016\0327fI&s\007/\036;\026\005\r\025\003#\002/\002f\016E\002\002CB%\001\001\006Ia!\022\002\035}\023WO\0343mK\022Le\016];uA!Q1Q\n\001C\002\023E#aa\021\002\031}\023X\r\0328fi&s\007/\036;\t\021\rE\003\001)A\005\007\013\nQb\030:fI:,G/\0238qkR\004\003BCB+\001\t\007I\021\013\002\004D\005qqLY;oI2,GmT;uaV$\b\002CB-\001\001\006Ia!\022\002\037}\023WO\0343mK\022|U\017\0369vi\002Bqa!\030\001\t\003\nI+A\bjg>+H\017];u\013:\f'\r\\3e\021\035\031\t\007\001C!\007G\n\001c]3u\037V$\b/\036;F]\006\024G.\0323\025\t\005m2Q\r\005\t\003s\033y\0061\001\002,\"91\021\016\001\005B\005}\025!G2iK\016\\'+\0323ti>tW-\0238qkR\034\005.\0318hK\022Dqa!\034\001\t\003\032y'\001\005d_:tWm\031;t)!\tYk!\035\004\016\016E\005\002CB:\007W\002\ra!\036\002\t]L'/\032\t\005\007o\032I)\004\002\004z)!11PB?\003\0319\030N]5oO*\0311ga \013\t\r\00551Q\001\te\026$Gn\\4jG*!1QQBD\003\035IW.\\5cSNT!A!-\n\t\r-5\021\020\002\006\023^K'/\032\005\b\007\037\033Y\0071\001\\\003%\021Gn\\2l\r\006\034W\rC\004\004\024\016-\004\031A.\002\033\031\024x.\034#je\026\034G/[8oQ!\031Yga&\004*\016-\006\003BBM\007GsAaa'\004 6\0211Q\024\006\004\013\t-\026\002BBQ\007;\013\001b\0249uS>t\027\r\\\005\005\007K\0339K\001\004NKRDw\016\032\006\005\007C\033i*A\003n_\022LG-\t\002\004.\006A!+\0323M_\036L7\rC\004\0042\002!\tea-\002)\r|gN\\3diN\f%o\\;oI\016{'O\\3s)!\tYk!.\0048\016e\006\002CB:\007_\003\ra!\036\t\017\r=5q\026a\0017\"911SBX\001\004Y\006\006CBX\007/\033Ika+\t\017\r}\006\001\"\021\004B\0069r-\032;Ck:$G.\0323DC\ndWm\025;sK:<G\017\033\013\007\007\007\034Ym!4\021\013q\013)o!2\021\007q\0339-C\002\004Jv\023AAQ=uK\"91qRB_\001\004Y\006bBBh\007{\003\raW\001\fi>$\025N]3di&|g\016\013\005\004>\016]5\021VBV\021\035\031)\016\001C!\007/\f\001dZ3u\0136LG\017^3e'&<g.\0317TiJ,gn\032;i)\031\031Ina8\004bB\031Ala7\n\007\ruWLA\003TQ>\024H\017C\004\004\020\016M\007\031A.\t\017\r=71\033a\0017\"B11[BL\007S\033Y\013C\004\004h\002!\t%a(\002+=t')\0368eY\026$\027J\0349vi\016C\027M\\4fI\"B1Q]BL\007S\033Y\013C\004\004n\002!\t%a(\002-=t'+\0323ti>tW-\0238qkR\034\005.\0318hK\022D\003ba;\004\030\016%61\026\005\b\007g\004A\021IB{\003\025\001\030\016^2i+\t\0319\020\005\003\004z\016}XBAB~\025\021\t)j!@\013\005\025Q\023\002\002C\001\007w\024aBR8sO\026$\025N]3di&|g\016C\004\005\006\001!\t\005b\002\002\023ALGo\0315`I\025\fH\003BA\036\t\023A\001\"!/\005\004\001\0071q\037\005\b\t\033\001A\021IB{\003\rI\030m\036\005\b\t#\001A\021\tC\n\003\035I\030m^0%KF$B!a\017\005\026!A\021\021\030C\b\001\004\0319\020C\004\005\032\001!\t\005b\007\0021M,GO\022:p[\026sG/\033;z!&$8\r[!oIf\013w\017\006\003\002,\022u\001\002CB\b\t/\001\r\001b\b\021\t\021\005B1E\007\003\007\033IA\001\"\n\004\016\t1QI\034;jifDq\001\"\013\001\t\003\"Y#A\007tKR4%o\\7GC\016Lgn\032\013\005\003W#i\003\003\005\002:\022\035\002\031AB|\021\035!\t\004\001C!\003\013a\"\0338wKJ$(k\034;bi&|g\016C\004\0056\001!\t\005b\016\002\r\031\f7-\0338h)\t\0319\020C\004\005<\001!\t\005\"\020\002\rI|G/\031;f)\021\tY\013b\020\t\021\021\005C\021\ba\001\007o\fA!\031=jg\"9AQ\t\001\005B\021\035\023a\002;p\031>\034\027\r\034\013\005\007o$I\005\003\005\002:\022\r\003\031AB|\021\035!i\005\001C!\t\037\n\001\002^8HY>\024\027\r\034\013\005\007o$\t\006\003\005\002:\022-\003\031AB|\021\035!)\006\001C!\t/\nabZ3u'R\f7m[%o'2|G\017\006\003\005Z\021\025\004\003\002C.\tCj!\001\"\030\013\007\021}\023#\001\003ji\026l\027\002\002C2\t;\022\021\"\023;f[N#\030mY6\t\017\021\035D1\013a\0017\006\t\021\016C\004\005l\001!\t\005\"\034\002\033\021,7M]*uC\016\\7+\033>f)\031!I\006b\034\005r!9\0211\034C5\001\004Y\006b\002C:\tS\002\raW\001\007C6|WO\034;\t\017\021]\004\001\"\021\005z\005A2/\032;J]Z,g\016^8ssNcw\016^\"p]R,g\016^:\025\r\005mB1\020C?\021\035\tY\016\"\036A\002mC\001\002b \005v\001\007A\021L\001\006gR\f7m\033\005\b\t\007\003A\021\tCC\003]9W\r^*uC\016\\\027J\\*m_R|en\0217pg&tw\r\006\003\005Z\021\035\005bBAn\t\003\003\ra\027\005\b\t\027\003A\021IAP\0035y\007/\0328J]Z,g\016^8ss\"9Aq\022\001\005B\005}\025AD2m_N,\027J\034<f]R|'/\037\005\b\t'\003A\021IA`\003YA\027m]\"vgR|W.\0238wK:$xN]=OC6,\007b\002CL\001\021\005C\021T\001\022SN,6/Z1cY\026\024\025\020\0257bs\026\024H\003BAV\t7C\001\"!\025\005\026\002\0071q\001\005\b\t?\003A\021\tCQ\003!!'o\0349TY>$H\003CAV\tG#)\013\"+\t\017\005mGQ\024a\0017\"IAq\025CO!\003\005\raW\001\006G>,h\016\036\005\013\tW#i\n%AA\002\0215\026!\0033je\026\034G/[8o!\025aFqVB|\023\r!\t,\030\002\007\037B$\030n\0348\t\017\021U\006\001\"\021\002 \006aAM]8q\0032d7\013\\8ug\"1A\021\030\001\005Bi\013acZ3u\023:4XM\034;pef\034F/Y2l\031&l\027\016\036\005\b\t{\003A\021\tC`\0035\031w.\0349p]\026tGo\0257piR\0311\f\"1\t\021\021\rG1\030a\001\003s\nq!\0313ee\026\0348\017C\004\005H\002!\t%!\033\002!\035,G/\0238wK:$xN]=OC6,\007B\002Cf\001\021\005#,\001\thKR\034\026N_3J]Z,g\016^8ss\"9Aq\032\001\005B\021E\027AE5t\023R,WNV1mS\0224uN]*m_R$b!a+\005T\022U\007bBAn\t\033\004\ra\027\005\t\t\"i\r1\001\005Z!9A\021\034\001\005B\021m\027AD2b]\026CHO]1di&#X-\034\013\t\003W#i\016b8\005b\"9\0211\034Cl\001\004Y\006\002\003C@\t/\004\r\001\"\027\t\017\r]Aq\033a\0017\"9AQ\035\001\005B\021\035\030!D2b]&s7/\032:u\023R,W\016\006\005\002,\022%H1\036Cw\021\035\tY\016b9A\002mC\001\002b \005d\002\007A\021\f\005\b\007/!\031\0171\001\\\021\035!\t\020\001C!\tg\f!dZ3u\003\016\034Wm]:jE2,7\013\\8ug\032\023x.\\*jI\026$Ba!\r\005v\"91q\003Cx\001\004Y\006b\002C}\001\021\005\023\021V\001\020Q\006\034(+\0323ti>tWmQ1sI\"9AQ \001\005B\021}\030\001D4m_\n\fGNQ;gM\026\024XC\001Bj\021\035)\031\001\001C!\013\013\t\001c\0327pE\006d')\0364gKJ|F%Z9\025\t\005mRq\001\005\t\003s+\t\0011\001\003T\"9Q1\002\001\005B\021}\030\001E4m_\n\fGNQ;gM\026\0248+\033>f\021\035)y\001\001C!\013#\tAc\0327pE\006d')\0364gKJ\034\026N_3`I\025\fH\003BA\036\013'A\001\"!/\006\016\001\007!1\033\005\b\013/\001A\021IC\r\003\0211\027\016\0347\025\017m+Y\"b\b\006*!AQQDC\013\001\004\03190\001\003ge>l\007\002CC\021\013+\001\r!b\t\002\021I,7o\\;sG\026\0042aJC\023\023\r)9\003\013\002\013\r2,\030\016Z*uC\016\\\007\002CC\026\013+\001\r!a+\002\r\021|g)\0337m\021\035)y\003\001C!\013c\tQ\001\032:bS:$\002\"b\t\0064\025URq\007\005\t\013;)i\0031\001\004x\"AQ\021EC\027\001\004)\031\003\003\005\006:\0255\002\031AAV\003\035!w\016\022:bS:Dq!b\f\001\t\003*i\004\006\005\006$\025}R\021IC#\021!)i\"b\017A\002\r]\bbBC\"\013w\001\raW\001\t[\006DHI]1j]\"AQ\021HC\036\001\004\tY\013C\004\006J\001!\t%b\023\002\017\r\fgNR5mYR1\0211VC'\013\037B\001\"\"\b\006H\001\0071q\037\005\t\013#*9\0051\001\006T\005)a\r\\;jIB\031q%\"\026\n\007\025]\003FA\003GYVLG\rC\004\006\\\001!\t%\"\030\002\021\r\fg\016\022:bS:$b!a+\006`\025\005\004\002CC\017\0133\002\raa>\t\021\025ES\021\fa\001\013'Bq!\"\032\001\t\003*9'A\006hKR$\026M\\6J]\032|G\003BC5\013c\002R\001XAs\013W\0022aJC7\023\r)y\007\013\002\016\r2,\030\016\032+b].LeNZ8\t\021\025uQ1\ra\001\007o\004")
/*     */ public class RobotProxy extends TileEntity implements Computer, PowerInformation, Robot { private final Robot robot; private final Component node; private final int[] _input; private final int[] _output; private final int[][] _bundledInput; private final int[][] _rednetInput; private final int[][] _bundledOutput; private double li$cil$oc$common$tileentity$traits$PowerInformation$$lastSentRatio; private int li$cil$oc$common$tileentity$traits$PowerInformation$$ticksUntilSync; private final Machine li$cil$oc$common$tileentity$traits$Computer$$_machine;
/*     */   private boolean li$cil$oc$common$tileentity$traits$Computer$$_isRunning;
/*     */   private boolean hasErrored;
/*     */   private final Set<String> li$cil$oc$common$tileentity$traits$Computer$$_users;
/*     */   private boolean _isAbstractBusAvailable;
/*     */   private final Object[] fakeInterface;
/*     */   private boolean _isOutputEnabled;
/*     */   private boolean shouldUpdateInput;
/*     */   private final ForgeDirection[] li$cil$oc$common$tileentity$traits$Rotatable$$pitch2Direction;
/*     */   private final ForgeDirection[] li$cil$oc$common$tileentity$traits$Rotatable$$yaw2Direction;
/*     */   private ForgeDirection li$cil$oc$common$tileentity$traits$Rotatable$$_pitch;
/*     */   private ForgeDirection li$cil$oc$common$tileentity$traits$Rotatable$$_yaw;
/*     */   private final ArrayBuffer<Option<ItemStack>> li$cil$oc$common$tileentity$traits$ComponentInventory$$pendingRemovalsActual;
/*     */   private final ArrayBuffer<Option<ItemStack>> li$cil$oc$common$tileentity$traits$ComponentInventory$$pendingAddsActual;
/*     */   private boolean li$cil$oc$common$tileentity$traits$ComponentInventory$$updateScheduled;
/*     */   private Option<ManagedEnvironment>[] li$cil$oc$common$inventory$ComponentInventory$$_components;
/*     */   private boolean isSizeInventoryReady;
/*     */   private final ArrayBuffer<ManagedEnvironment> updatingComponents;
/*     */   private final Option<ItemStack>[] li$cil$oc$common$tileentity$traits$Inventory$$inventory;
/*     */   private boolean isChangeScheduled;
/*     */   private boolean moving;
/*     */   private volatile byte bitmap$0;
/*     */   
/*  25 */   public double li$cil$oc$common$tileentity$traits$PowerInformation$$lastSentRatio() { return this.li$cil$oc$common$tileentity$traits$PowerInformation$$lastSentRatio; } public void li$cil$oc$common$tileentity$traits$PowerInformation$$lastSentRatio_$eq(double x$1) { this.li$cil$oc$common$tileentity$traits$PowerInformation$$lastSentRatio = x$1; } public int li$cil$oc$common$tileentity$traits$PowerInformation$$ticksUntilSync() { return this.li$cil$oc$common$tileentity$traits$PowerInformation$$ticksUntilSync; } public void li$cil$oc$common$tileentity$traits$PowerInformation$$ticksUntilSync_$eq(int x$1) { this.li$cil$oc$common$tileentity$traits$PowerInformation$$ticksUntilSync = x$1; } public void updatePowerInformation() { PowerInformation.class.updatePowerInformation(this); } private Machine li$cil$oc$common$tileentity$traits$Computer$$_machine$lzycompute() { synchronized (this) { if ((byte)(this.bitmap$0 & 0x1) == 0) { this.li$cil$oc$common$tileentity$traits$Computer$$_machine = Computer.class.li$cil$oc$common$tileentity$traits$Computer$$_machine(this); this.bitmap$0 = (byte)(this.bitmap$0 | 0x1); }  return this.li$cil$oc$common$tileentity$traits$Computer$$_machine; }  } public Machine li$cil$oc$common$tileentity$traits$Computer$$_machine() { return ((byte)(this.bitmap$0 & 0x1) == 0) ? li$cil$oc$common$tileentity$traits$Computer$$_machine$lzycompute() : this.li$cil$oc$common$tileentity$traits$Computer$$_machine; } public boolean li$cil$oc$common$tileentity$traits$Computer$$_isRunning() { return this.li$cil$oc$common$tileentity$traits$Computer$$_isRunning; } public void li$cil$oc$common$tileentity$traits$Computer$$_isRunning_$eq(boolean x$1) { this.li$cil$oc$common$tileentity$traits$Computer$$_isRunning = x$1; } public boolean hasErrored() { return this.hasErrored; } public void hasErrored_$eq(boolean x$1) { this.hasErrored = x$1; } public Set<String> li$cil$oc$common$tileentity$traits$Computer$$_users() { return this.li$cil$oc$common$tileentity$traits$Computer$$_users; } public void li$cil$oc$common$tileentity$traits$Computer$_setter_$li$cil$oc$common$tileentity$traits$Computer$$_users_$eq(Set<String> x$1) { this.li$cil$oc$common$tileentity$traits$Computer$$_users = x$1; } public Option<String> runSound() { return Computer.class.runSound(this); } public boolean canInteract(String player) { return Computer.class.canInteract(this, player); } @SideOnly(Side.CLIENT) public void setUsers(Iterable list) { Computer.class.setUsers(this, list); } public EnumSet<StateAware.State> getCurrentState() { return Computer.class.getCurrentState(this); } public Iterable<ItemStack> internalComponents() { return Computer.class.internalComponents(this); } public Iterable<ManagedEnvironment> installedComponents() { return Computer.class.installedComponents(this); } public void onMachineConnect(Node node) { Computer.class.onMachineConnect(this, node); } public void onMachineDisconnect(Node node) { Computer.class.onMachineDisconnect(this, node); } public boolean hasAbstractBusCard() { return Computer.class.hasAbstractBusCard(this); } public void updateComputer() { Computer.class.updateComputer(this); } public void onRunningChanged() { Computer.class.onRunningChanged(this); } public void onRotationChanged() { Computer.class.onRotationChanged(this); } public void onRedstoneInputChanged(RedstoneChangedEventArgs args) { Computer.class.onRedstoneInputChanged(this, args); } @Method(modid = "BuildCraft|Core") public boolean hasWork() { return StateAware.class.hasWork((StateAware)this); } public boolean _isAbstractBusAvailable() { return this._isAbstractBusAvailable; } public void _isAbstractBusAvailable_$eq(boolean x$1) { this._isAbstractBusAvailable = x$1; } private Object[] fakeInterface$lzycompute() { synchronized (this) { if ((byte)(this.bitmap$0 & 0x2) == 0) { this.fakeInterface = AbstractBusAware.class.fakeInterface((AbstractBusAware)this); this.bitmap$0 = (byte)(this.bitmap$0 | 0x2); }  return this.fakeInterface; }  } public Object[] fakeInterface() { return ((byte)(this.bitmap$0 & 0x2) == 0) ? fakeInterface$lzycompute() : this.fakeInterface; } @Method(modid = "StargateTech2") public IBusInterface[] getInterfaces(int side) { return AbstractBusAware.class.getInterfaces((AbstractBusAware)this, side); } public World getWorld() { return AbstractBusAware.class.getWorld((AbstractBusAware)this); } public int getXCoord() { return AbstractBusAware.class.getXCoord((AbstractBusAware)this); } public int getYCoord() { return AbstractBusAware.class.getYCoord((AbstractBusAware)this); } public int getZCoord() { return AbstractBusAware.class.getZCoord((AbstractBusAware)this); } public boolean isAbstractBusAvailable() { return AbstractBusAware.class.isAbstractBusAvailable((AbstractBusAware)this); } public AbstractBusAware isAbstractBusAvailable_$eq(boolean value) { return AbstractBusAware.class.isAbstractBusAvailable_$eq((AbstractBusAware)this, value); } public void onDisconnect(Node node) { AbstractBusAware.class.onDisconnect((AbstractBusAware)this, node); } public void li$cil$oc$common$tileentity$traits$BundledRedstoneAware$_setter_$_bundledInput_$eq(int[][] x$1) {} public void li$cil$oc$common$tileentity$traits$BundledRedstoneAware$_setter_$_rednetInput_$eq(int[][] x$1) {} public void li$cil$oc$common$tileentity$traits$BundledRedstoneAware$_setter_$_bundledOutput_$eq(int[][] x$1) {} public int[][] getBundledInput() { return BundledRedstoneAware.class.getBundledInput((BundledRedstoneAware)this); } public int[] getBundledInput(ForgeDirection side) { return BundledRedstoneAware.class.getBundledInput((BundledRedstoneAware)this, side); } public int getBundledInput(ForgeDirection side, int color) { return BundledRedstoneAware.class.getBundledInput((BundledRedstoneAware)this, side, color); } public void setBundledInput(ForgeDirection side, int color, int newValue) { BundledRedstoneAware.class.setBundledInput((BundledRedstoneAware)this, side, color, newValue); } public void setBundledInput(ForgeDirection side, int[] newBundledInput) { BundledRedstoneAware.class.setBundledInput((BundledRedstoneAware)this, side, newBundledInput); } public void setRednetInput(ForgeDirection side, int color, int value) { BundledRedstoneAware.class.setRednetInput((BundledRedstoneAware)this, side, color, value); } public void updateInput(int[][] inputs, ForgeDirection side, int color, int newValue) { BundledRedstoneAware.class.updateInput((BundledRedstoneAware)this, inputs, side, color, newValue); } public int[][] getBundledOutput() { return BundledRedstoneAware.class.getBundledOutput((BundledRedstoneAware)this); } public int[] getBundledOutput(ForgeDirection side) { return BundledRedstoneAware.class.getBundledOutput((BundledRedstoneAware)this, side); } public int getBundledOutput(ForgeDirection side, int color) { return BundledRedstoneAware.class.getBundledOutput((BundledRedstoneAware)this, side, color); } public void notifyChangedSide(ForgeDirection side) { BundledRedstoneAware.class.notifyChangedSide((BundledRedstoneAware)this, side); } public boolean setBundledOutput(ForgeDirection side, int color, int value) { return BundledRedstoneAware.class.setBundledOutput((BundledRedstoneAware)this, side, color, value); } public boolean setBundledOutput(ForgeDirection side, Map values) { return BundledRedstoneAware.class.setBundledOutput((BundledRedstoneAware)this, side, values); } public boolean setBundledOutput(Map values) { return BundledRedstoneAware.class.setBundledOutput((BundledRedstoneAware)this, values); } public void updateRedstoneInput(ForgeDirection side) { BundledRedstoneAware.class.updateRedstoneInput((BundledRedstoneAware)this, side); } public void onRedstoneOutputEnabledChanged() { BundledRedstoneAware.class.onRedstoneOutputEnabledChanged((BundledRedstoneAware)this); } @Method(modid = "ProjRed|Transmission") public boolean canConnectBundled(int side) { return BundledRedstoneAware.class.canConnectBundled((BundledRedstoneAware)this, side); } @Method(modid = "ProjRed|Transmission") public byte[] getBundledSignal(int side) { return BundledRedstoneAware.class.getBundledSignal((BundledRedstoneAware)this, side); } public boolean _isOutputEnabled() { return this._isOutputEnabled; } public void _isOutputEnabled_$eq(boolean x$1) { this._isOutputEnabled = x$1; } public boolean shouldUpdateInput() { return this.shouldUpdateInput; } public void shouldUpdateInput_$eq(boolean x$1) { this.shouldUpdateInput = x$1; } public void li$cil$oc$common$tileentity$traits$RedstoneAware$_setter_$_input_$eq(int[] x$1) {} public void li$cil$oc$common$tileentity$traits$RedstoneAware$_setter_$_output_$eq(int[] x$1) {} public Option<Object> getObjectFuzzy(Map map, int key) { return RedstoneAware.class.getObjectFuzzy((RedstoneAware)this, map, key); } public Option<Object> valueToInt(Object value) { return RedstoneAware.class.valueToInt((RedstoneAware)this, value); } public int[] getInput() { return RedstoneAware.class.getInput((RedstoneAware)this); } public int getInput(ForgeDirection side) { return RedstoneAware.class.getInput((RedstoneAware)this, side); } public void setInput(ForgeDirection side, int newInput) { RedstoneAware.class.setInput((RedstoneAware)this, side, newInput); } public void setInput(int[] values) { RedstoneAware.class.setInput((RedstoneAware)this, values); } public int maxInput() { return RedstoneAware.class.maxInput((RedstoneAware)this); } public int[] getOutput() { return RedstoneAware.class.getOutput((RedstoneAware)this); } public int getOutput(ForgeDirection side) { return RedstoneAware.class.getOutput((RedstoneAware)this, side); } public boolean setOutput(ForgeDirection side, int value) { return RedstoneAware.class.setOutput((RedstoneAware)this, side, value); } public boolean setOutput(Map values) { return RedstoneAware.class.setOutput((RedstoneAware)this, values); } public void onRedstoneOutputChanged(ForgeDirection side) { RedstoneAware.class.onRedstoneOutputChanged((RedstoneAware)this, side); } public ForgeDirection[] li$cil$oc$common$tileentity$traits$Rotatable$$pitch2Direction() { return this.li$cil$oc$common$tileentity$traits$Rotatable$$pitch2Direction; } public ForgeDirection[] li$cil$oc$common$tileentity$traits$Rotatable$$yaw2Direction() { return this.li$cil$oc$common$tileentity$traits$Rotatable$$yaw2Direction; } public ForgeDirection li$cil$oc$common$tileentity$traits$Rotatable$$_pitch() { return this.li$cil$oc$common$tileentity$traits$Rotatable$$_pitch; } public void li$cil$oc$common$tileentity$traits$Rotatable$$_pitch_$eq(ForgeDirection x$1) { this.li$cil$oc$common$tileentity$traits$Rotatable$$_pitch = x$1; } public ForgeDirection li$cil$oc$common$tileentity$traits$Rotatable$$_yaw() { return this.li$cil$oc$common$tileentity$traits$Rotatable$$_yaw; } public void li$cil$oc$common$tileentity$traits$Rotatable$$_yaw_$eq(ForgeDirection x$1) { this.li$cil$oc$common$tileentity$traits$Rotatable$$_yaw = x$1; } public void li$cil$oc$common$tileentity$traits$Rotatable$_setter_$li$cil$oc$common$tileentity$traits$Rotatable$$pitch2Direction_$eq(ForgeDirection[] x$1) { this.li$cil$oc$common$tileentity$traits$Rotatable$$pitch2Direction = x$1; } public void li$cil$oc$common$tileentity$traits$Rotatable$_setter_$li$cil$oc$common$tileentity$traits$Rotatable$$yaw2Direction_$eq(ForgeDirection[] x$1) { this.li$cil$oc$common$tileentity$traits$Rotatable$$yaw2Direction = x$1; } public ForgeDirection[] validFacings() { return Rotatable.class.validFacings((Rotatable)this); } private ArrayBuffer li$cil$oc$common$tileentity$traits$ComponentInventory$$pendingRemovalsActual$lzycompute() { synchronized (this) { if ((byte)(this.bitmap$0 & 0x4) == 0) { this.li$cil$oc$common$tileentity$traits$ComponentInventory$$pendingRemovalsActual = ComponentInventory.class.li$cil$oc$common$tileentity$traits$ComponentInventory$$pendingRemovalsActual((ComponentInventory)this); this.bitmap$0 = (byte)(this.bitmap$0 | 0x4); }  return this.li$cil$oc$common$tileentity$traits$ComponentInventory$$pendingRemovalsActual; }  } public ArrayBuffer<Option<ItemStack>> li$cil$oc$common$tileentity$traits$ComponentInventory$$pendingRemovalsActual() { return ((byte)(this.bitmap$0 & 0x4) == 0) ? li$cil$oc$common$tileentity$traits$ComponentInventory$$pendingRemovalsActual$lzycompute() : this.li$cil$oc$common$tileentity$traits$ComponentInventory$$pendingRemovalsActual; } private ArrayBuffer li$cil$oc$common$tileentity$traits$ComponentInventory$$pendingAddsActual$lzycompute() { synchronized (this) { if ((byte)(this.bitmap$0 & 0x8) == 0) { this.li$cil$oc$common$tileentity$traits$ComponentInventory$$pendingAddsActual = ComponentInventory.class.li$cil$oc$common$tileentity$traits$ComponentInventory$$pendingAddsActual((ComponentInventory)this); this.bitmap$0 = (byte)(this.bitmap$0 | 0x8); }  return this.li$cil$oc$common$tileentity$traits$ComponentInventory$$pendingAddsActual; }  } public ArrayBuffer<Option<ItemStack>> li$cil$oc$common$tileentity$traits$ComponentInventory$$pendingAddsActual() { return ((byte)(this.bitmap$0 & 0x8) == 0) ? li$cil$oc$common$tileentity$traits$ComponentInventory$$pendingAddsActual$lzycompute() : this.li$cil$oc$common$tileentity$traits$ComponentInventory$$pendingAddsActual; } public boolean li$cil$oc$common$tileentity$traits$ComponentInventory$$updateScheduled() { return this.li$cil$oc$common$tileentity$traits$ComponentInventory$$updateScheduled; } public void li$cil$oc$common$tileentity$traits$ComponentInventory$$updateScheduled_$eq(boolean x$1) { this.li$cil$oc$common$tileentity$traits$ComponentInventory$$updateScheduled = x$1; } public ComponentInventory host() { return ComponentInventory.class.host((ComponentInventory)this); } public ArrayBuffer<Option<ItemStack>> pendingRemovals() { return ComponentInventory.class.pendingRemovals((ComponentInventory)this); } public ArrayBuffer<Option<ItemStack>> pendingAdds() { return ComponentInventory.class.pendingAdds((ComponentInventory)this); } public void onItemAdded(int slot, ItemStack stack) { ComponentInventory.class.onItemAdded((ComponentInventory)this, slot, stack); } public void onItemRemoved(int slot, ItemStack stack) { ComponentInventory.class.onItemRemoved((ComponentInventory)this, slot, stack); } public void save(ManagedEnvironment component, Item driver, ItemStack stack) { ComponentInventory.class.save((ComponentInventory)this, component, driver, stack); } public void initialize() { ComponentInventory.class.initialize((ComponentInventory)this); } public void onConnect(Node node) { ComponentInventory.class.onConnect((ComponentInventory)this, node); } public Option<ManagedEnvironment>[] li$cil$oc$common$inventory$ComponentInventory$$_components() { return this.li$cil$oc$common$inventory$ComponentInventory$$_components; } @TraitSetter public void li$cil$oc$common$inventory$ComponentInventory$$_components_$eq(Option[] x$1) { this.li$cil$oc$common$inventory$ComponentInventory$$_components = (Option<ManagedEnvironment>[])x$1; } public boolean isSizeInventoryReady() { return this.isSizeInventoryReady; } @TraitSetter public void isSizeInventoryReady_$eq(boolean x$1) { this.isSizeInventoryReady = x$1; } public ArrayBuffer<ManagedEnvironment> updatingComponents() { return this.updatingComponents; } public void li$cil$oc$common$inventory$ComponentInventory$_setter_$updatingComponents_$eq(ArrayBuffer<ManagedEnvironment> x$1) { this.updatingComponents = x$1; } public Option<ManagedEnvironment>[] components() { return (Option<ManagedEnvironment>[])ComponentInventory.class.components((ComponentInventory)this); } public void updateComponents() { ComponentInventory.class.updateComponents((ComponentInventory)this); } public void saveComponents() { ComponentInventory.class.saveComponents((ComponentInventory)this); } public boolean isComponentSlot(int slot, ItemStack stack) { return ComponentInventory.class.isComponentSlot((ComponentInventory)this, slot, stack); } public void connectItemNode(Node node) { ComponentInventory.class.connectItemNode((ComponentInventory)this, node); } public NBTTagCompound dataTag(Item driver, ItemStack stack) { return ComponentInventory.class.dataTag((ComponentInventory)this, driver, stack); } public void applyLifecycleState(Object component, Lifecycle.LifecycleState state) { ComponentInventory.class.applyLifecycleState((ComponentInventory)this, component, state); } private Option[] li$cil$oc$common$tileentity$traits$Inventory$$inventory$lzycompute() { synchronized (this) { if ((byte)(this.bitmap$0 & 0x10) == 0) { this.li$cil$oc$common$tileentity$traits$Inventory$$inventory = (Option<ItemStack>[])Inventory.class.li$cil$oc$common$tileentity$traits$Inventory$$inventory((Inventory)this); this.bitmap$0 = (byte)(this.bitmap$0 | 0x10); }  return (Option[])this.li$cil$oc$common$tileentity$traits$Inventory$$inventory; }  } public Option<ItemStack>[] li$cil$oc$common$tileentity$traits$Inventory$$inventory() { return ((byte)(this.bitmap$0 & 0x10) == 0) ? (Option<ItemStack>[])li$cil$oc$common$tileentity$traits$Inventory$$inventory$lzycompute() : this.li$cil$oc$common$tileentity$traits$Inventory$$inventory; } public Option<ItemStack>[] items() { return (Option<ItemStack>[])Inventory.class.items((Inventory)this); } public EntityItem spawnStackInWorld(ItemStack stack, Option direction) { return Inventory.class.spawnStackInWorld((Inventory)this, stack, direction); } public int dropSlot$default$2() { return Inventory.class.dropSlot$default$2((Inventory)this); } public Option<ForgeDirection> dropSlot$default$3() { return Inventory.class.dropSlot$default$3((Inventory)this); } public Option<ForgeDirection> spawnStackInWorld$default$2() { return Inventory.class.spawnStackInWorld$default$2((Inventory)this); } public void updateItems(int slot, ItemStack stack) { Inventory.class.updateItems((Inventory)this, slot, stack); } public String inventoryName() { return Inventory.class.inventoryName((Inventory)this); } public int getInventoryStackRequired() { return SimpleInventory.class.getInventoryStackRequired((SimpleInventory)this); } public boolean isChangeScheduled() { return this.isChangeScheduled; } public void isChangeScheduled_$eq(boolean x$1) { this.isChangeScheduled = x$1; } public boolean moving() { return this.moving; } public void moving_$eq(boolean x$1) { this.moving = x$1; } public double xPosition() { return Environment.class.xPosition((Environment)this); } public double yPosition() { return Environment.class.yPosition((Environment)this); } public double zPosition() { return Environment.class.zPosition((Environment)this); } public void markChanged() { Environment.class.markChanged((Environment)this); } public boolean isConnected() { return Environment.class.isConnected((Environment)this); } @Method(modid = "appliedenergistics2") public boolean prepareToMove() { return Environment.class.prepareToMove((Environment)this); } @Method(modid = "appliedenergistics2") public void doneMoving() { Environment.class.doneMoving((Environment)this); } public Object[] result(Seq args) { return Environment.class.result((Environment)this, args); } public World world() { return TileEntity.class.world((TileEntity)this); } public int x() { return TileEntity.class.x((TileEntity)this); } public int y() { return TileEntity.class.y((TileEntity)this); } public int z() { return TileEntity.class.z((TileEntity)this); } public BlockPosition position() { return TileEntity.class.position((TileEntity)this); } public Block block() { return TileEntity.class.block((TileEntity)this); } public boolean isClient() { return TileEntity.class.isClient((TileEntity)this); } public boolean isServer() { return TileEntity.class.isServer((TileEntity)this); } public void func_145843_s() { TileEntity.class.invalidate((TileEntity)this); } public void onChunkUnload() { TileEntity.class.onChunkUnload((TileEntity)this); } public void func_145839_a(NBTTagCompound nbt) { TileEntity.class.readFromNBT((TileEntity)this, nbt); } public void func_145841_b(NBTTagCompound nbt) { TileEntity.class.writeToNBT((TileEntity)this, nbt); } public Packet func_145844_m() { return TileEntity.class.getDescriptionPacket((TileEntity)this); } public void onDataPacket(NetworkManager manager, S35PacketUpdateTileEntity packet) { TileEntity.class.onDataPacket((TileEntity)this, manager, packet); } public Robot robot() { return this.robot; } public RobotProxy(Robot robot) { TileEntity.class.$init$((TileEntity)this); Environment.class.$init$((Environment)this); SimpleInventory.class.$init$((SimpleInventory)this); Inventory.class.$init$((Inventory)this); Inventory.class.$init$((Inventory)this); ComponentInventory.class.$init$((ComponentInventory)this); ComponentInventory.class.$init$((ComponentInventory)this); RotationAware.class.$init$((RotationAware)this); Rotatable.class.$init$((Rotatable)this); RedstoneAware.class.$init$((RedstoneAware)this); BundledRedstoneAware.class.$init$((BundledRedstoneAware)this); AbstractBusAware.class.$init$((AbstractBusAware)this); StateAware.class.$init$((StateAware)this); Computer.class.$init$(this); PowerInformation.class.$init$(this);
/*     */ 
/*     */ 
/*     */ 
/*     */     
/*  30 */     this.node = (Component)Network.newNode((Environment)this, Visibility.Network)
/*  31 */       .withComponent("robot", Visibility.Neighbors)
/*  32 */       .create();
/*     */ 
/*     */ 
/*     */ 
/*     */ 
/*     */ 
/*     */ 
/*     */ 
/*     */ 
/*     */ 
/*     */ 
/*     */ 
/*     */ 
/*     */ 
/*     */ 
/*     */ 
/*     */ 
/*     */ 
/*     */ 
/*     */ 
/*     */ 
/*     */ 
/*     */ 
/*     */ 
/*     */ 
/*     */ 
/*     */ 
/*     */ 
/*     */ 
/*     */ 
/*     */ 
/*     */ 
/*     */ 
/*     */ 
/*     */ 
/*     */ 
/*     */ 
/*     */ 
/*     */ 
/*     */ 
/*     */ 
/*     */ 
/*     */ 
/*     */ 
/*     */ 
/*     */ 
/*     */ 
/*     */ 
/*     */ 
/*     */ 
/*     */ 
/*     */ 
/*     */ 
/*     */ 
/*     */ 
/*     */ 
/*     */ 
/*     */ 
/*     */ 
/*     */ 
/*     */ 
/*     */ 
/*     */ 
/*     */ 
/*     */ 
/*     */ 
/*     */ 
/*     */ 
/*     */ 
/*     */ 
/*     */ 
/*     */ 
/*     */ 
/*     */ 
/*     */ 
/*     */ 
/*     */ 
/*     */ 
/*     */ 
/*     */ 
/*     */ 
/*     */ 
/*     */ 
/*     */ 
/*     */ 
/*     */ 
/*     */ 
/*     */ 
/*     */ 
/*     */ 
/*     */ 
/*     */ 
/*     */ 
/*     */ 
/*     */ 
/*     */ 
/*     */ 
/*     */ 
/*     */ 
/*     */ 
/*     */ 
/*     */ 
/*     */ 
/*     */ 
/*     */ 
/*     */ 
/*     */ 
/*     */ 
/*     */ 
/*     */ 
/*     */ 
/*     */ 
/*     */ 
/*     */ 
/*     */ 
/*     */ 
/*     */ 
/*     */ 
/*     */ 
/*     */ 
/*     */ 
/*     */ 
/*     */ 
/*     */ 
/*     */ 
/*     */ 
/*     */ 
/*     */ 
/*     */ 
/*     */ 
/*     */ 
/*     */ 
/*     */ 
/*     */ 
/*     */ 
/*     */ 
/*     */ 
/*     */ 
/*     */ 
/*     */ 
/*     */ 
/*     */ 
/*     */ 
/*     */ 
/*     */ 
/*     */ 
/*     */ 
/*     */ 
/*     */ 
/*     */ 
/*     */     
/* 183 */     this._input = robot._input();
/*     */     
/* 185 */     this._output = robot._output();
/*     */     
/* 187 */     this._bundledInput = robot._bundledInput();
/*     */     
/* 189 */     this._rednetInput = robot._rednetInput();
/*     */     
/* 191 */     this._bundledOutput = robot._bundledOutput(); } public RobotProxy() { this(new Robot()); } public Component node() { return this.node; } public Machine machine() { return robot().machine(); } public int tier() { return robot().tier(); } public InventoryProxy equipmentInventory() { return robot().equipmentInventory(); } public InventoryProxy mainInventory() { return robot().mainInventory(); } public MultiTank tank() { return robot().tank(); } public int selectedSlot() { return robot().selectedSlot(); } public void setSelectedSlot(int index) { robot().setSelectedSlot(index); } public int selectedTank() { return robot().selectedTank(); } public void setSelectedTank(int index) { robot().setSelectedTank(index); } public Player player() { return robot().player(); } public String name() { return robot().name(); } public void setName(String name) { robot().setName(name); } public String ownerName() { return robot().ownerName(); } public UUID ownerUUID() { return robot().ownerUUID(); } public void connectComponents() {} public void disconnectComponents() {} public boolean isRunning() { return robot().isRunning(); } public void setRunning(boolean value) { robot().setRunning(value); } public boolean shouldAnimate() { return robot().shouldAnimate(); } public int componentCount() { return robot().componentCount(); } public Environment getComponentInSlot(int index) { return robot().getComponentInSlot(index); } public void synchronizeSlot(int slot) { robot().synchronizeSlot(slot); } public int[][] _bundledOutput() { return this._bundledOutput; }
/*     */   @Callback(doc = "function():boolean -- Starts the robot. Returns true if the state changed.") public Object[] start(Context context, Arguments args) { return result((Seq<Object>)Predef$.MODULE$.genericWrapArray(new Object[] { BoxesRunTime.boxToBoolean((!machine().isPaused() && machine().start())) })); }
/*     */   @Callback(doc = "function():boolean -- Stops the robot. Returns true if the state changed.") public Object[] stop(Context context, Arguments args) { return result((Seq<Object>)Predef$.MODULE$.genericWrapArray(new Object[] { BoxesRunTime.boxToBoolean(machine().stop()) })); } @Callback(direct = true, doc = "function():boolean -- Returns whether the robot is running.") public Object[] isRunning(Context context, Arguments args) { return result((Seq<Object>)Predef$.MODULE$.genericWrapArray(new Object[] { BoxesRunTime.boxToBoolean(machine().isRunning()) })); } @Callback(doc = "function(name: string):string -- Sets a new name and returns the old name. Robot must not be running") public Object[] setName(Context context, Arguments args) { String oldName = robot().name(); String newName = args.checkString(0); if (machine().isRunning()) return result((Seq<Object>)Predef$.MODULE$.genericWrapArray(new Object[] { Unit$.MODULE$, "is running" }));  setName(newName); PacketSender$.MODULE$.sendRobotNameChange(robot()); return result((Seq<Object>)Predef$.MODULE$.genericWrapArray(new Object[] { oldName })); } @Callback(doc = "function():string -- Returns the robot name.") public Object[] getName(Context context, Arguments args) { return result((Seq<Object>)Predef$.MODULE$.genericWrapArray(new Object[] { robot().name() })); } public void onMessage(Message message) { // Byte code:
/*     */     //   0: aload_0
/*     */     //   1: aload_1
/*     */     //   2: invokestatic onMessage : (Lli/cil/oc/common/tileentity/traits/Environment;Lli/cil/oc/api/network/Message;)V
/*     */     //   5: aload_1
/*     */     //   6: invokeinterface name : ()Ljava/lang/String;
/*     */     //   11: ldc_w 'network.message'
/*     */     //   14: astore_2
/*     */     //   15: dup
/*     */     //   16: ifnonnull -> 27
/*     */     //   19: pop
/*     */     //   20: aload_2
/*     */     //   21: ifnull -> 34
/*     */     //   24: goto -> 187
/*     */     //   27: aload_2
/*     */     //   28: invokevirtual equals : (Ljava/lang/Object;)Z
/*     */     //   31: ifeq -> 187
/*     */     //   34: aload_1
/*     */     //   35: invokeinterface source : ()Lli/cil/oc/api/network/Node;
/*     */     //   40: aload_0
/*     */     //   41: invokevirtual node : ()Lli/cil/oc/api/network/Component;
/*     */     //   44: astore_3
/*     */     //   45: dup
/*     */     //   46: ifnonnull -> 57
/*     */     //   49: pop
/*     */     //   50: aload_3
/*     */     //   51: ifnull -> 187
/*     */     //   54: goto -> 64
/*     */     //   57: aload_3
/*     */     //   58: invokevirtual equals : (Ljava/lang/Object;)Z
/*     */     //   61: ifne -> 187
/*     */     //   64: aload_1
/*     */     //   65: invokeinterface data : ()[Ljava/lang/Object;
/*     */     //   70: astore #4
/*     */     //   72: getstatic scala/Array$.MODULE$ : Lscala/Array$;
/*     */     //   75: aload #4
/*     */     //   77: invokevirtual unapplySeq : (Ljava/lang/Object;)Lscala/Option;
/*     */     //   80: astore #5
/*     */     //   82: aload #5
/*     */     //   84: invokevirtual isEmpty : ()Z
/*     */     //   87: ifne -> 182
/*     */     //   90: aload #5
/*     */     //   92: invokevirtual get : ()Ljava/lang/Object;
/*     */     //   95: ifnull -> 182
/*     */     //   98: aload #5
/*     */     //   100: invokevirtual get : ()Ljava/lang/Object;
/*     */     //   103: checkcast scala/collection/SeqLike
/*     */     //   106: iconst_1
/*     */     //   107: invokeinterface lengthCompare : (I)I
/*     */     //   112: iconst_0
/*     */     //   113: if_icmpne -> 182
/*     */     //   116: aload #5
/*     */     //   118: invokevirtual get : ()Ljava/lang/Object;
/*     */     //   121: checkcast scala/collection/SeqLike
/*     */     //   124: iconst_0
/*     */     //   125: invokeinterface apply : (I)Ljava/lang/Object;
/*     */     //   130: astore #6
/*     */     //   132: aload #6
/*     */     //   134: instanceof li/cil/oc/api/network/Packet
/*     */     //   137: ifeq -> 182
/*     */     //   140: aload #6
/*     */     //   142: checkcast li/cil/oc/api/network/Packet
/*     */     //   145: astore #7
/*     */     //   147: aload_0
/*     */     //   148: invokevirtual robot : ()Lli/cil/oc/common/tileentity/Robot;
/*     */     //   151: invokevirtual node : ()Lli/cil/oc/api/network/Node;
/*     */     //   154: aload_1
/*     */     //   155: invokeinterface name : ()Ljava/lang/String;
/*     */     //   160: iconst_1
/*     */     //   161: anewarray java/lang/Object
/*     */     //   164: dup
/*     */     //   165: iconst_0
/*     */     //   166: aload #7
/*     */     //   168: aastore
/*     */     //   169: invokeinterface sendToReachable : (Ljava/lang/String;[Ljava/lang/Object;)V
/*     */     //   174: getstatic scala/runtime/BoxedUnit.UNIT : Lscala/runtime/BoxedUnit;
/*     */     //   177: astore #8
/*     */     //   179: goto -> 187
/*     */     //   182: getstatic scala/runtime/BoxedUnit.UNIT : Lscala/runtime/BoxedUnit;
/*     */     //   185: astore #8
/*     */     //   187: return
/*     */     // Line number table:
/*     */     //   Java source line number -> byte code offset
/*     */     //   #110	-> 0
/*     */     //   #111	-> 5
/*     */     //   #112	-> 72
/*     */     //   #113	-> 182
/*     */     //   #109	-> 187
/*     */     // Local variable table:
/*     */     //   start	length	slot	name	descriptor
/*     */     //   0	188	0	this	Lli/cil/oc/common/tileentity/RobotProxy;
/*     */     //   0	188	1	message	Lli/cil/oc/api/network/Message;
/* 193 */     //   132	56	6	packet	Ljava/lang/Object; } public void func_145845_h() { robot().func_145845_h(); } public void func_145829_t() { RedstoneAware.class.validate((RedstoneAware)this); boolean firstProxy = (robot().proxy() == null); robot().proxy_$eq(this); robot().func_145834_a(this.field_145850_b); (robot()).field_145851_c = this.field_145851_c; (robot()).field_145848_d = this.field_145848_d; (robot()).field_145849_e = this.field_145849_e; if (firstProxy) robot().func_145829_t();  if (isServer()) { NBTTagCompound nbt = new NBTTagCompound(); nbt.func_74778_a("address", robot().node().address()); node().load(nbt); }  } public void dispose() { Computer.class.dispose(this); RobotProxy robotProxy = this; if (robot().proxy() == null) { robot().proxy(); if (robotProxy != null) return;  } else { if (robot().proxy().equals(robotProxy)) { robot().dispose(); return; }  return; }  robot().dispose(); } public void readFromNBTForServer(NBTTagCompound nbt) { robot().info().load(nbt); Computer.class.readFromNBTForServer(this, nbt); robot().readFromNBTForServer(nbt); } public void writeToNBTForServer(NBTTagCompound nbt) { Computer.class.writeToNBTForServer(this, nbt); robot().writeToNBTForServer(nbt); } public void save(NBTTagCompound nbt) { robot().save(nbt); } public void load(NBTTagCompound nbt) { robot().load(nbt); } @SideOnly(Side.CLIENT) public void readFromNBTForClient(NBTTagCompound nbt) { robot().readFromNBTForClient(nbt); } public void writeToNBTForClient(NBTTagCompound nbt) { robot().writeToNBTForClient(nbt); } public double func_145833_n() { return robot().func_145833_n(); } public AxisAlignedBB getRenderBoundingBox() { return robot().getRenderBoundingBox(); } public boolean shouldRenderInPass(int pass) { return robot().shouldRenderInPass(pass); } public void func_70296_d() { robot().func_70296_d(); } public Node[] onAnalyze(EntityPlayer player, int side, float hitX, float hitY, float hitZ) { return robot().onAnalyze(player, side, hitX, hitY, hitZ); } public int[] _input() { return this._input; } public int[] _output() { return this._output; } public int[][] _bundledInput() { return this._bundledInput; } public int[][] _rednetInput() { return this._rednetInput; } public boolean isOutputEnabled() { return robot().isOutputEnabled(); }
/*     */    public void setOutputEnabled(boolean value) {
/* 195 */     robot().setOutputEnabled(value);
/*     */   } public void checkRedstoneInputChanged() {
/* 197 */     robot().checkRedstoneInputChanged();
/*     */   } @Method(modid = "RedLogic")
/*     */   public boolean connects(IWire wire, int blockFace, int fromDirection) {
/* 200 */     return robot().connects(wire, blockFace, fromDirection);
/*     */   } @Method(modid = "RedLogic")
/*     */   public boolean connectsAroundCorner(IWire wire, int blockFace, int fromDirection) {
/* 203 */     return robot().connectsAroundCorner(wire, blockFace, fromDirection);
/*     */   } @Method(modid = "RedLogic")
/*     */   public byte[] getBundledCableStrength(int blockFace, int toDirection) {
/* 206 */     return robot().getBundledCableStrength(blockFace, toDirection);
/*     */   } @Method(modid = "RedLogic")
/*     */   public short getEmittedSignalStrength(int blockFace, int toDirection) {
/* 209 */     return robot().getEmittedSignalStrength(blockFace, toDirection);
/*     */   } @Method(modid = "RedLogic")
/*     */   public void onBundledInputChanged() {
/* 212 */     robot().onBundledInputChanged();
/*     */   } @Method(modid = "RedLogic")
/*     */   public void onRedstoneInputChanged() {
/* 215 */     robot().onRedstoneInputChanged();
/*     */   }
/*     */   
/*     */   public ForgeDirection pitch() {
/* 219 */     return robot().pitch();
/*     */   } public void pitch_$eq(ForgeDirection value) {
/* 221 */     robot().pitch_$eq(value);
/*     */   } public ForgeDirection yaw() {
/* 223 */     return robot().yaw();
/*     */   } public void yaw_$eq(ForgeDirection value) {
/* 225 */     robot().yaw_$eq(value);
/*     */   } public boolean setFromEntityPitchAndYaw(Entity entity) {
/* 227 */     return robot().setFromEntityPitchAndYaw(entity);
/*     */   } public boolean setFromFacing(ForgeDirection value) {
/* 229 */     return robot().setFromFacing(value);
/*     */   } public boolean invertRotation() {
/* 231 */     return robot().invertRotation();
/*     */   } public ForgeDirection facing() {
/* 233 */     return robot().facing();
/*     */   } public boolean rotate(ForgeDirection axis) {
/* 235 */     return robot().rotate(axis);
/*     */   } public ForgeDirection toLocal(ForgeDirection value) {
/* 237 */     return robot().toLocal(value);
/*     */   } public ForgeDirection toGlobal(ForgeDirection value) {
/* 239 */     return robot().toGlobal(value);
/*     */   }
/*     */   
/*     */   public ItemStack func_70301_a(int i) {
/* 243 */     return robot().func_70301_a(i);
/*     */   } public ItemStack func_70298_a(int slot, int amount) {
/* 245 */     return robot().func_70298_a(slot, amount);
/*     */   } public void func_70299_a(int slot, ItemStack stack) {
/* 247 */     robot().func_70299_a(slot, stack);
/*     */   } public ItemStack func_70304_b(int slot) {
/* 249 */     return robot().func_70304_b(slot);
/*     */   } public void func_70295_k_() {
/* 251 */     robot().func_70295_k_();
/*     */   } public void func_70305_f() {
/* 253 */     robot().func_70305_f();
/*     */   } public boolean func_145818_k_() {
/* 255 */     return robot().func_145818_k_();
/*     */   } public boolean func_70300_a(EntityPlayer player) {
/* 257 */     return robot().func_70300_a(player);
/*     */   } public boolean dropSlot(int slot, int count, Option<ForgeDirection> direction) {
/* 259 */     return robot().dropSlot(slot, count, direction);
/*     */   } public void dropAllSlots() {
/* 261 */     robot().dropAllSlots();
/*     */   } public int func_70297_j_() {
/* 263 */     return robot().func_70297_j_();
/*     */   } public int componentSlot(String address) {
/* 265 */     return robot().componentSlot(address);
/*     */   } public String func_145825_b() {
/* 267 */     return robot().func_145825_b();
/*     */   } public int func_70302_i_() {
/* 269 */     return robot().func_70302_i_();
/*     */   } public boolean func_94041_b(int slot, ItemStack stack) {
/* 271 */     return robot().func_94041_b(slot, stack);
/*     */   }
/*     */   
/*     */   public boolean func_102008_b(int slot, ItemStack stack, int side) {
/* 275 */     return robot().func_102008_b(slot, stack, side);
/*     */   } public boolean func_102007_a(int slot, ItemStack stack, int side) {
/* 277 */     return robot().func_102007_a(slot, stack, side);
/*     */   } public int[] func_94128_d(int side) {
/* 279 */     return robot().func_94128_d(side);
/*     */   }
/*     */   
/*     */   public boolean hasRedstoneCard() {
/* 283 */     return robot().hasRedstoneCard();
/*     */   }
/*     */   
/*     */   public double globalBuffer() {
/* 287 */     return robot().globalBuffer();
/*     */   } public void globalBuffer_$eq(double value) {
/* 289 */     robot().globalBuffer_$eq(value);
/*     */   } public double globalBufferSize() {
/* 291 */     return robot().globalBufferSize();
/*     */   } public void globalBufferSize_$eq(double value) {
/* 293 */     robot().globalBufferSize_$eq(value);
/*     */   }
/*     */   
/*     */   public int fill(ForgeDirection from, FluidStack resource, boolean doFill) {
/* 297 */     return robot().fill(from, resource, doFill);
/*     */   } public FluidStack drain(ForgeDirection from, FluidStack resource, boolean doDrain) {
/* 299 */     return robot().drain(from, resource, doDrain);
/*     */   } public FluidStack drain(ForgeDirection from, int maxDrain, boolean doDrain) {
/* 301 */     return robot().drain(from, maxDrain, doDrain);
/*     */   } public boolean canFill(ForgeDirection from, Fluid fluid) {
/* 303 */     return robot().canFill(from, fluid);
/*     */   } public boolean canDrain(ForgeDirection from, Fluid fluid) {
/* 305 */     return robot().canDrain(from, fluid);
/*     */   } public FluidTankInfo[] getTankInfo(ForgeDirection from) {
/* 307 */     return robot().getTankInfo(from);
/*     */   } }


/* Location:              C:\Users\shame\AppData\Roaming\PrismLauncher\instances\GT_New_Horizons_2.7.4_Java_17-21\.minecraft\mods\OpenComputers-1.10.30-GTNH.jar!\li\cil\oc\common\tileentity\RobotProxy.class
 * Java compiler version: 8 (52.0)
 * JD-Core Version:       1.1.3
 */