/*     */ package li.cil.oc.common.nanomachines.provider;
/*     */ @ScalaSignature(bytes = "\006\001\005\005w!B\001\003\021\003y\021A\006#jg&tG/Z4sCRLwN\034)s_ZLG-\032:\013\005\r!\021\001\0039s_ZLG-\032:\013\005\0251\021\001\0048b]>l\027m\0315j]\026\034(BA\004\t\003\031\031w.\\7p]*\021\021BC\001\003_\016T!a\003\007\002\007\rLGNC\001\016\003\ta\027n\001\001\021\005A\tR\"\001\002\007\013I\021\001\022A\n\003-\021K7/\0338uK\036\024\030\r^5p]B\023xN^5eKJ\034\"!\005\013\021\005A)\022B\001\f\003\0055\0316-\0317b!J|g/\0333fe\")\001$\005C\0013\0051A(\0338jiz\"\022a\004\005\0067E!\t\005H\001\025GJ,\027\r^3TG\006d\027MQ3iCZLwN]:\025\007u\tI\013E\002\037G\025j\021a\b\006\003A\005\n!bY8mY\026\034G/[8o\025\005\021\023!B:dC2\f\027B\001\023 \005!IE/\032:bE2,\007C\001\024(\033\005\tb\001\002\025\022\001%\022a\003R5tS:$Xm\032:bi&|gNQ3iCZLwN]\n\003O)\002\"a\013\031\016\0031R!!\f\030\002\rA\024XMZ1c\025\ty\003\"A\002ba&L!!\r\027\003!\005\0237\017\036:bGR\024U\r[1wS>\024\b\002C\032(\005\003\005\013\021\002\033\002\rAd\027-_3s!\t)T(D\0017\025\t\031tG\003\0029s\0051QM\034;jifT!AO\036\002\0235Lg.Z2sC\032$(\"\001\037\002\0079,G/\003\002?m\taQI\034;jif\004F.Y=fe\")\001d\nC\001\001R\021Q%\021\005\006g}\002\r\001\016\005\b\007\036\002\r\021\"\001E\003-\021'/Z1lS:<W*\0319\026\003\025\003BAR%L#6\tqI\003\002I?\0059Q.\036;bE2,\027B\001&H\005\ri\025\r\035\t\003\031>k\021!\024\006\003\035\"\tA!\036;jY&\021\001+\024\002\016\0052|7m\033)pg&$\030n\0348\021\005\031\022f\001B*\022\001Q\023Qb\0257po\n\023X-Y6J]\032|7C\001*V!\t1v+D\001\"\023\tA\026E\001\004B]f\024VM\032\005\t5J\023)\031!C\0017\006YA/[7f'R\f'\017^3e+\005a\006C\001,^\023\tq\026E\001\003M_:<\007\002\0031S\005\003\005\013\021\002/\002\031QLW.Z*uCJ$X\r\032\021\t\021\t\024&Q1A\005\002m\013!\002^5nK\n\023xn[3o\021!!'K!A!\002\023a\026a\003;j[\026\024%o\\6f]\002B\001B\032*\003\006\004%\taZ\001\004a>\034X#A&\t\021%\024&\021!Q\001\n-\013A\001]8tA!A1N\025BC\002\023\005A.\001\007pe&<\027N\\1m)>|G.F\001n!\r1f\016]\005\003_\006\022aa\0249uS>t\007CA9u\033\005\021(BA::\003\021IG/Z7\n\005U\024(!C%uK6\034F/Y2l\021!9(K!A!\002\023i\027!D8sS\036Lg.\0317U_>d\007\005\003\005z%\n\025\r\021\"\001{\003\025\021Gn\\2l+\005Y\bC\001?\033\005i(BA=:\023\tyXPA\003CY>\0347\016C\005\002\004I\023\t\021)A\005w\0061!\r\\8dW\002B!\"a\002S\005\013\007I\021AA\005\003\021iW\r^1\026\005\005-\001c\001,\002\016%\031\021qB\021\003\007%sG\017\003\006\002\024I\023\t\021)A\005\003\027\tQ!\\3uC\002Ba\001\007*\005\002\005]A#D)\002\032\005m\021QDA\020\003C\t\031\003\003\004[\003+\001\r\001\030\005\007E\006U\001\031\001/\t\r\031\f)\0021\001L\021\031Y\027Q\003a\001[\"1\0210!\006A\002mD\001\"a\002\002\026\001\007\0211\002\005\n\003O\021\006\031!C\001\003\023\ta\002\\1ti\022\013W.Y4f'\026tG\017C\005\002,I\003\r\021\"\001\002.\005\021B.Y:u\t\006l\027mZ3TK:$x\fJ3r)\021\ty#!\016\021\007Y\013\t$C\002\0024\005\022A!\0268ji\"Q\021qGA\025\003\003\005\r!a\003\002\007a$\023\007\003\005\002<I\003\013\025BA\006\003=a\027m\035;EC6\fw-Z*f]R\004\003bBA %\022\005\021\021I\001\nG\",7m\033+p_2$B!a\021\002JA\031a+!\022\n\007\005\035\023EA\004C_>dW-\0318\t\rM\ni\0041\0015\021\035\tiE\025C\001\003\037\na!\0369eCR,G\003CA\030\003#\ny&!\031\t\021\005M\0231\na\001\003+\nQa^8sY\022\004B!a\026\002\\5\021\021\021\f\006\004\003'J\024\002BA/\0033\022QaV8sY\022DaaMA&\001\004!\004bBA2\003\027\002\r\001X\001\004]><\bbBA4%\022\005\021\021N\001\007M&t\027n\0355\025\r\005=\0221NA7\021!\t\031&!\032A\002\005U\003bB\032\002f\001\007\021q\016\t\004k\005E\024bAA:m\tqQI\034;jif\004F.Y=fe6\003\006\"CA<O\001\007I\021AA=\003=\021'/Z1lS:<W*\0319`I\025\fH\003BA\030\003wB\021\"a\016\002v\005\005\t\031A#\t\017\005}t\005)Q\005\013\006a!M]3bW&tw-T1qA!A\0211Q\024A\002\023\005A)\001\bce\026\f7.\0338h\033\006\004h*Z<\t\023\005\035u\0051A\005\002\005%\025A\0052sK\006\\\027N\\4NCBtUm^0%KF$B!a\f\002\f\"I\021qGAC\003\003\005\r!\022\005\b\003\037;\003\025)\003F\003=\021'/Z1lS:<W*\0319OK^\004\003bBAJO\021\005\023QS\001\n_:$\025n]1cY\026$B!a\f\002\030\"A\021\021TAI\001\004\tY*\001\004sK\006\034xN\034\t\005\003;\013\t+\004\002\002 *\021QAL\005\005\003G\013yJA\007ESN\f'\r\\3SK\006\034xN\034\005\b\003\033:C\021IAT)\t\ty\003C\00345\001\007A\007C\004\002.F!\t%a,\002'I,\027\r\032\"fQ\0064\030n\034:Ge>lgJ\021+\025\013\025\n\t,a-\t\rM\nY\0131\0015\021!\t),a+A\002\005]\026a\0018ciB!\021\021XA_\033\t\tYLC\002\0026fJA!a0\002<\nqaJ\021+UC\036\034u.\0349pk:$\007")
/*     */ public final class DisintegrationProvider { public static DisintegrationBehavior readBehaviorFromNBT(EntityPlayer paramEntityPlayer, NBTTagCompound paramNBTTagCompound) {
/*     */     return DisintegrationProvider$.MODULE$.readBehaviorFromNBT(paramEntityPlayer, paramNBTTagCompound);
/*     */   }
/*     */   
/*     */   public static Iterable<DisintegrationBehavior> createScalaBehaviors(EntityPlayer paramEntityPlayer) {
/*     */     return DisintegrationProvider$.MODULE$.createScalaBehaviors(paramEntityPlayer);
/*     */   }
/*     */   
/*     */   public static Iterable<Behavior> createBehaviors(EntityPlayer paramEntityPlayer) {
/*     */     return DisintegrationProvider$.MODULE$.createBehaviors(paramEntityPlayer);
/*     */   }
/*     */   
/*     */   public static Behavior readFromNBT(EntityPlayer paramEntityPlayer, NBTTagCompound paramNBTTagCompound) {
/*     */     return DisintegrationProvider$.MODULE$.readFromNBT(paramEntityPlayer, paramNBTTagCompound);
/*     */   }
/*     */   
/*     */   public static NBTTagCompound writeToNBT(Behavior paramBehavior) {
/*     */     return DisintegrationProvider$.MODULE$.writeToNBT(paramBehavior);
/*     */   }
/*     */   
/*     */   public static class DisintegrationBehavior extends AbstractBehavior { public final EntityPlayer li$cil$oc$common$nanomachines$provider$DisintegrationProvider$DisintegrationBehavior$$player;
/*     */     private Map<BlockPosition, DisintegrationProvider.SlowBreakInfo> breakingMap;
/*     */     private Map<BlockPosition, DisintegrationProvider.SlowBreakInfo> breakingMapNew;
/*     */     
/*  27 */     public DisintegrationBehavior(EntityPlayer player) { super(player);
/*  28 */       this.breakingMap = Map$.MODULE$.empty();
/*  29 */       this.breakingMapNew = Map$.MODULE$.empty(); } public Map<BlockPosition, DisintegrationProvider.SlowBreakInfo> breakingMap() { return this.breakingMap; } public void breakingMap_$eq(Map<BlockPosition, DisintegrationProvider.SlowBreakInfo> x$1) { this.breakingMap = x$1; } public Map<BlockPosition, DisintegrationProvider.SlowBreakInfo> breakingMapNew() { return this.breakingMapNew; } public void breakingMapNew_$eq(Map<BlockPosition, DisintegrationProvider.SlowBreakInfo> x$1) { this.breakingMapNew = x$1; }
/*     */ 
/*     */     
/*     */     public void onDisable(DisableReason reason)
/*     */     {
/*  34 */       World world = this.li$cil$oc$common$nanomachines$provider$DisintegrationProvider$DisintegrationBehavior$$player.func_130014_f_();
/*  35 */       breakingMap().keys().foreach((Function1)new DisintegrationProvider$DisintegrationBehavior$$anonfun$onDisable$1(this, world));
/*     */ 
/*     */       
/*  38 */       breakingMap().clear();
/*     */     } public final class DisintegrationProvider$DisintegrationBehavior$$anonfun$onDisable$1 extends AbstractFunction1<BlockPosition, BoxedUnit> implements Serializable {
/*     */       public static final long serialVersionUID = 0L; private final World world$1; public DisintegrationProvider$DisintegrationBehavior$$anonfun$onDisable$1(DisintegrationProvider.DisintegrationBehavior $outer, World world$1) {} public final void apply(BlockPosition pos) {
/*     */         ExtendedWorld$.MODULE$.extendedWorld(this.world$1).destroyBlockInWorldPartially(pos.hashCode(), pos, -1);
/*  42 */       } } public void update() { World world = this.li$cil$oc$common$nanomachines$provider$DisintegrationProvider$DisintegrationBehavior$$player.func_130014_f_();
/*  43 */       if (!world.field_72995_K) { EntityPlayer entityPlayer = this.li$cil$oc$common$nanomachines$provider$DisintegrationProvider$DisintegrationBehavior$$player;
/*  44 */         if (entityPlayer instanceof net.minecraftforge.common.util.FakePlayer) { BoxedUnit boxedUnit = BoxedUnit.UNIT; }
/*  45 */         else if (entityPlayer instanceof EntityPlayerMP) { EntityPlayerMP entityPlayerMP = (EntityPlayerMP)entityPlayer;
/*  46 */           long now = world.func_82737_E();
/*     */ 
/*     */           
/*  49 */           BlockPosition blockPos = BlockPosition$.MODULE$.apply((Entity)this.li$cil$oc$common$nanomachines$provider$DisintegrationProvider$DisintegrationBehavior$$player);
/*  50 */           int actualRange = Settings$.MODULE$.get().nanomachineDisintegrationRange() * Nanomachines.getController(this.li$cil$oc$common$nanomachines$provider$DisintegrationProvider$DisintegrationBehavior$$player).getInputCount((Behavior)this); RichInt$.MODULE$
/*  51 */             .to$extension0(Predef$.MODULE$.intWrapper(-actualRange), actualRange).foreach$mVc$sp((Function1)new DisintegrationProvider$DisintegrationBehavior$$anonfun$update$1(this, world, now, blockPos, actualRange));
/*     */ 
/*     */ 
/*     */ 
/*     */ 
/*     */ 
/*     */ 
/*     */ 
/*     */ 
/*     */ 
/*     */ 
/*     */ 
/*     */ 
/*     */ 
/*     */ 
/*     */ 
/*     */ 
/*     */ 
/*     */ 
/*     */ 
/*     */ 
/*     */ 
/*     */ 
/*     */ 
/*     */ 
/*     */ 
/*     */ 
/*     */           
/*  79 */           breakingMap().withFilter((Function1)new DisintegrationProvider$DisintegrationBehavior$$anonfun$update$2(this)).foreach((Function1)new DisintegrationProvider$DisintegrationBehavior$$anonfun$update$3(this, world, now, entityPlayerMP));
/*     */ 
/*     */ 
/*     */ 
/*     */ 
/*     */ 
/*     */ 
/*     */           
/*  87 */           ((IterableLike)breakingMap().keySet().$minus$minus((GenTraversableOnce)breakingMapNew().keySet())).foreach((Function1)new DisintegrationProvider$DisintegrationBehavior$$anonfun$update$4(this, world));
/*     */ 
/*     */ 
/*     */           
/*  91 */           Map<BlockPosition, DisintegrationProvider.SlowBreakInfo> tmp = breakingMap();
/*  92 */           breakingMap().clear();
/*  93 */           breakingMap_$eq(breakingMapNew());
/*  94 */           breakingMapNew_$eq(tmp); BoxedUnit boxedUnit = BoxedUnit.UNIT; }
/*  95 */         else { BoxedUnit boxedUnit = BoxedUnit.UNIT; }  }  } public final class DisintegrationProvider$DisintegrationBehavior$$anonfun$update$1 extends AbstractFunction1.mcVI.sp implements Serializable {
/*     */       public static final long serialVersionUID = 0L; public final World world$2; public final long now$1; public final BlockPosition blockPos$1; public final int actualRange$1; public final void apply(int x) { apply$mcVI$sp(x); } public void apply$mcVI$sp(int x) { RichInt$.MODULE$.to$extension0(Predef$.MODULE$.intWrapper(0), this.actualRange$1 * 2).foreach$mVc$sp((Function1)new DisintegrationProvider$DisintegrationBehavior$$anonfun$update$1$$anonfun$apply$mcVI$sp$1(this, x)); } public DisintegrationProvider$DisintegrationBehavior$$anonfun$update$1(DisintegrationProvider.DisintegrationBehavior $outer, World world$2, long now$1, BlockPosition blockPos$1, int actualRange$1) {} public final class DisintegrationProvider$DisintegrationBehavior$$anonfun$update$1$$anonfun$apply$mcVI$sp$1 extends AbstractFunction1.mcVI.sp implements Serializable {
/*     */         public static final long serialVersionUID = 0L; public final int x$4; public final void apply(int y) { apply$mcVI$sp(y); } public void apply$mcVI$sp(int y) { RichInt$.MODULE$.to$extension0(Predef$.MODULE$.intWrapper(-this.$outer.actualRange$1), this.$outer.actualRange$1).foreach((Function1)new DisintegrationProvider$DisintegrationBehavior$$anonfun$update$1$$anonfun$apply$mcVI$sp$1$$anonfun$apply$mcVI$sp$2(this, y)); } public DisintegrationProvider$DisintegrationBehavior$$anonfun$update$1$$anonfun$apply$mcVI$sp$1(DisintegrationProvider$DisintegrationBehavior$$anonfun$update$1 $outer, int x$4) {} public final class DisintegrationProvider$DisintegrationBehavior$$anonfun$update$1$$anonfun$apply$mcVI$sp$1$$anonfun$apply$mcVI$sp$2 extends AbstractFunction1<Object, Object> implements Serializable {
/*     */           public static final long serialVersionUID = 0L; private final int y$1; public DisintegrationProvider$DisintegrationBehavior$$anonfun$update$1$$anonfun$apply$mcVI$sp$1$$anonfun$apply$mcVI$sp$2(DisintegrationProvider$DisintegrationBehavior$$anonfun$update$1$$anonfun$apply$mcVI$sp$1 $outer, int y$1) {} public final Object apply(int z) { // Byte code:
/*     */             //   0: getstatic li/cil/oc/util/BlockPosition$.MODULE$ : Lli/cil/oc/util/BlockPosition$;
/*     */             //   3: aload_0
/*     */             //   4: getfield $outer : Lli/cil/oc/common/nanomachines/provider/DisintegrationProvider$DisintegrationBehavior$$anonfun$update$1$$anonfun$apply$mcVI$sp$1;
/*     */             //   7: invokevirtual li$cil$oc$common$nanomachines$provider$DisintegrationProvider$DisintegrationBehavior$$anonfun$$anonfun$$$outer : ()Lli/cil/oc/common/nanomachines/provider/DisintegrationProvider$DisintegrationBehavior$$anonfun$update$1;
/*     */             //   10: getfield blockPos$1 : Lli/cil/oc/util/BlockPosition;
/*     */             //   13: aload_0
/*     */             //   14: getfield $outer : Lli/cil/oc/common/nanomachines/provider/DisintegrationProvider$DisintegrationBehavior$$anonfun$update$1$$anonfun$apply$mcVI$sp$1;
/*     */             //   17: getfield x$4 : I
/*     */             //   20: i2d
/*     */             //   21: aload_0
/*     */             //   22: getfield y$1 : I
/*     */             //   25: i2d
/*     */             //   26: iload_1
/*     */             //   27: i2d
/*     */             //   28: invokevirtual offset : (DDD)Lnet/minecraft/util/Vec3;
/*     */             //   31: invokevirtual apply : (Lnet/minecraft/util/Vec3;)Lli/cil/oc/util/BlockPosition;
/*     */             //   34: astore_2
/*     */             //   35: aload_0
/*     */             //   36: getfield $outer : Lli/cil/oc/common/nanomachines/provider/DisintegrationProvider$DisintegrationBehavior$$anonfun$update$1$$anonfun$apply$mcVI$sp$1;
/*     */             //   39: invokevirtual li$cil$oc$common$nanomachines$provider$DisintegrationProvider$DisintegrationBehavior$$anonfun$$anonfun$$$outer : ()Lli/cil/oc/common/nanomachines/provider/DisintegrationProvider$DisintegrationBehavior$$anonfun$update$1;
/*     */             //   42: invokevirtual li$cil$oc$common$nanomachines$provider$DisintegrationProvider$DisintegrationBehavior$$anonfun$$$outer : ()Lli/cil/oc/common/nanomachines/provider/DisintegrationProvider$DisintegrationBehavior;
/*     */             //   45: invokevirtual breakingMap : ()Lscala/collection/mutable/Map;
/*     */             //   48: aload_2
/*     */             //   49: invokeinterface get : (Ljava/lang/Object;)Lscala/Option;
/*     */             //   54: astore_3
/*     */             //   55: aload_3
/*     */             //   56: instanceof scala/Some
/*     */             //   59: ifeq -> 179
/*     */             //   62: aload_3
/*     */             //   63: checkcast scala/Some
/*     */             //   66: astore #4
/*     */             //   68: aload #4
/*     */             //   70: invokevirtual x : ()Ljava/lang/Object;
/*     */             //   73: checkcast li/cil/oc/common/nanomachines/provider/DisintegrationProvider$SlowBreakInfo
/*     */             //   76: astore #5
/*     */             //   78: aload #5
/*     */             //   80: aload_0
/*     */             //   81: getfield $outer : Lli/cil/oc/common/nanomachines/provider/DisintegrationProvider$DisintegrationBehavior$$anonfun$update$1$$anonfun$apply$mcVI$sp$1;
/*     */             //   84: invokevirtual li$cil$oc$common$nanomachines$provider$DisintegrationProvider$DisintegrationBehavior$$anonfun$$anonfun$$$outer : ()Lli/cil/oc/common/nanomachines/provider/DisintegrationProvider$DisintegrationBehavior$$anonfun$update$1;
/*     */             //   87: invokevirtual li$cil$oc$common$nanomachines$provider$DisintegrationProvider$DisintegrationBehavior$$anonfun$$$outer : ()Lli/cil/oc/common/nanomachines/provider/DisintegrationProvider$DisintegrationBehavior;
/*     */             //   90: getfield li$cil$oc$common$nanomachines$provider$DisintegrationProvider$DisintegrationBehavior$$player : Lnet/minecraft/entity/player/EntityPlayer;
/*     */             //   93: invokevirtual checkTool : (Lnet/minecraft/entity/player/EntityPlayer;)Z
/*     */             //   96: ifeq -> 179
/*     */             //   99: aload_0
/*     */             //   100: getfield $outer : Lli/cil/oc/common/nanomachines/provider/DisintegrationProvider$DisintegrationBehavior$$anonfun$update$1$$anonfun$apply$mcVI$sp$1;
/*     */             //   103: invokevirtual li$cil$oc$common$nanomachines$provider$DisintegrationProvider$DisintegrationBehavior$$anonfun$$anonfun$$$outer : ()Lli/cil/oc/common/nanomachines/provider/DisintegrationProvider$DisintegrationBehavior$$anonfun$update$1;
/*     */             //   106: invokevirtual li$cil$oc$common$nanomachines$provider$DisintegrationProvider$DisintegrationBehavior$$anonfun$$$outer : ()Lli/cil/oc/common/nanomachines/provider/DisintegrationProvider$DisintegrationBehavior;
/*     */             //   109: invokevirtual breakingMapNew : ()Lscala/collection/mutable/Map;
/*     */             //   112: getstatic scala/Predef$ArrowAssoc$.MODULE$ : Lscala/Predef$ArrowAssoc$;
/*     */             //   115: getstatic scala/Predef$.MODULE$ : Lscala/Predef$;
/*     */             //   118: aload_2
/*     */             //   119: invokevirtual ArrowAssoc : (Ljava/lang/Object;)Ljava/lang/Object;
/*     */             //   122: aload #5
/*     */             //   124: invokevirtual $minus$greater$extension : (Ljava/lang/Object;Ljava/lang/Object;)Lscala/Tuple2;
/*     */             //   127: invokeinterface $plus$eq : (Lscala/Tuple2;)Lscala/collection/mutable/MapLike;
/*     */             //   132: pop
/*     */             //   133: aload #5
/*     */             //   135: aload_0
/*     */             //   136: getfield $outer : Lli/cil/oc/common/nanomachines/provider/DisintegrationProvider$DisintegrationBehavior$$anonfun$update$1$$anonfun$apply$mcVI$sp$1;
/*     */             //   139: invokevirtual li$cil$oc$common$nanomachines$provider$DisintegrationProvider$DisintegrationBehavior$$anonfun$$anonfun$$$outer : ()Lli/cil/oc/common/nanomachines/provider/DisintegrationProvider$DisintegrationBehavior$$anonfun$update$1;
/*     */             //   142: getfield world$2 : Lnet/minecraft/world/World;
/*     */             //   145: aload_0
/*     */             //   146: getfield $outer : Lli/cil/oc/common/nanomachines/provider/DisintegrationProvider$DisintegrationBehavior$$anonfun$update$1$$anonfun$apply$mcVI$sp$1;
/*     */             //   149: invokevirtual li$cil$oc$common$nanomachines$provider$DisintegrationProvider$DisintegrationBehavior$$anonfun$$anonfun$$$outer : ()Lli/cil/oc/common/nanomachines/provider/DisintegrationProvider$DisintegrationBehavior$$anonfun$update$1;
/*     */             //   152: invokevirtual li$cil$oc$common$nanomachines$provider$DisintegrationProvider$DisintegrationBehavior$$anonfun$$$outer : ()Lli/cil/oc/common/nanomachines/provider/DisintegrationProvider$DisintegrationBehavior;
/*     */             //   155: getfield li$cil$oc$common$nanomachines$provider$DisintegrationProvider$DisintegrationBehavior$$player : Lnet/minecraft/entity/player/EntityPlayer;
/*     */             //   158: aload_0
/*     */             //   159: getfield $outer : Lli/cil/oc/common/nanomachines/provider/DisintegrationProvider$DisintegrationBehavior$$anonfun$update$1$$anonfun$apply$mcVI$sp$1;
/*     */             //   162: invokevirtual li$cil$oc$common$nanomachines$provider$DisintegrationProvider$DisintegrationBehavior$$anonfun$$anonfun$$$outer : ()Lli/cil/oc/common/nanomachines/provider/DisintegrationProvider$DisintegrationBehavior$$anonfun$update$1;
/*     */             //   165: getfield now$1 : J
/*     */             //   168: invokevirtual update : (Lnet/minecraft/world/World;Lnet/minecraft/entity/player/EntityPlayer;J)V
/*     */             //   171: getstatic scala/runtime/BoxedUnit.UNIT : Lscala/runtime/BoxedUnit;
/*     */             //   174: astore #6
/*     */             //   176: goto -> 670
/*     */             //   179: getstatic scala/None$.MODULE$ : Lscala/None$;
/*     */             //   182: aload_3
/*     */             //   183: invokevirtual equals : (Ljava/lang/Object;)Z
/*     */             //   186: ifeq -> 665
/*     */             //   189: aload_0
/*     */             //   190: getfield $outer : Lli/cil/oc/common/nanomachines/provider/DisintegrationProvider$DisintegrationBehavior$$anonfun$update$1$$anonfun$apply$mcVI$sp$1;
/*     */             //   193: invokevirtual li$cil$oc$common$nanomachines$provider$DisintegrationProvider$DisintegrationBehavior$$anonfun$$anonfun$$$outer : ()Lli/cil/oc/common/nanomachines/provider/DisintegrationProvider$DisintegrationBehavior$$anonfun$update$1;
/*     */             //   196: invokevirtual li$cil$oc$common$nanomachines$provider$DisintegrationProvider$DisintegrationBehavior$$anonfun$$$outer : ()Lli/cil/oc/common/nanomachines/provider/DisintegrationProvider$DisintegrationBehavior;
/*     */             //   199: getfield li$cil$oc$common$nanomachines$provider$DisintegrationProvider$DisintegrationBehavior$$player : Lnet/minecraft/entity/player/EntityPlayer;
/*     */             //   202: getstatic net/minecraftforge/event/entity/player/PlayerInteractEvent$Action.LEFT_CLICK_BLOCK : Lnet/minecraftforge/event/entity/player/PlayerInteractEvent$Action;
/*     */             //   205: aload_2
/*     */             //   206: invokevirtual x : ()I
/*     */             //   209: aload_2
/*     */             //   210: invokevirtual y : ()I
/*     */             //   213: aload_2
/*     */             //   214: invokevirtual z : ()I
/*     */             //   217: iconst_0
/*     */             //   218: aload_0
/*     */             //   219: getfield $outer : Lli/cil/oc/common/nanomachines/provider/DisintegrationProvider$DisintegrationBehavior$$anonfun$update$1$$anonfun$apply$mcVI$sp$1;
/*     */             //   222: invokevirtual li$cil$oc$common$nanomachines$provider$DisintegrationProvider$DisintegrationBehavior$$anonfun$$anonfun$$$outer : ()Lli/cil/oc/common/nanomachines/provider/DisintegrationProvider$DisintegrationBehavior$$anonfun$update$1;
/*     */             //   225: getfield world$2 : Lnet/minecraft/world/World;
/*     */             //   228: invokestatic onPlayerInteract : (Lnet/minecraft/entity/player/EntityPlayer;Lnet/minecraftforge/event/entity/player/PlayerInteractEvent$Action;IIIILnet/minecraft/world/World;)Lnet/minecraftforge/event/entity/player/PlayerInteractEvent;
/*     */             //   231: astore #7
/*     */             //   233: aload #7
/*     */             //   235: invokevirtual isCanceled : ()Z
/*     */             //   238: ifne -> 303
/*     */             //   241: aload #7
/*     */             //   243: getfield useBlock : Lcpw/mods/fml/common/eventhandler/Event$Result;
/*     */             //   246: getstatic cpw/mods/fml/common/eventhandler/Event$Result.DENY : Lcpw/mods/fml/common/eventhandler/Event$Result;
/*     */             //   249: astore #9
/*     */             //   251: dup
/*     */             //   252: ifnonnull -> 264
/*     */             //   255: pop
/*     */             //   256: aload #9
/*     */             //   258: ifnull -> 303
/*     */             //   261: goto -> 272
/*     */             //   264: aload #9
/*     */             //   266: invokevirtual equals : (Ljava/lang/Object;)Z
/*     */             //   269: ifne -> 303
/*     */             //   272: aload #7
/*     */             //   274: getfield useItem : Lcpw/mods/fml/common/eventhandler/Event$Result;
/*     */             //   277: getstatic cpw/mods/fml/common/eventhandler/Event$Result.DENY : Lcpw/mods/fml/common/eventhandler/Event$Result;
/*     */             //   280: astore #10
/*     */             //   282: dup
/*     */             //   283: ifnonnull -> 295
/*     */             //   286: pop
/*     */             //   287: aload #10
/*     */             //   289: ifnull -> 303
/*     */             //   292: goto -> 307
/*     */             //   295: aload #10
/*     */             //   297: invokevirtual equals : (Ljava/lang/Object;)Z
/*     */             //   300: ifeq -> 307
/*     */             //   303: iconst_0
/*     */             //   304: goto -> 308
/*     */             //   307: iconst_1
/*     */             //   308: istore #8
/*     */             //   310: aload_0
/*     */             //   311: getfield $outer : Lli/cil/oc/common/nanomachines/provider/DisintegrationProvider$DisintegrationBehavior$$anonfun$update$1$$anonfun$apply$mcVI$sp$1;
/*     */             //   314: invokevirtual li$cil$oc$common$nanomachines$provider$DisintegrationProvider$DisintegrationBehavior$$anonfun$$anonfun$$$outer : ()Lli/cil/oc/common/nanomachines/provider/DisintegrationProvider$DisintegrationBehavior$$anonfun$update$1;
/*     */             //   317: getfield world$2 : Lnet/minecraft/world/World;
/*     */             //   320: invokevirtual func_72912_H : ()Lnet/minecraft/world/storage/WorldInfo;
/*     */             //   323: invokevirtual func_76077_q : ()Lnet/minecraft/world/WorldSettings$GameType;
/*     */             //   326: invokevirtual func_82752_c : ()Z
/*     */             //   329: ifeq -> 367
/*     */             //   332: aload_0
/*     */             //   333: getfield $outer : Lli/cil/oc/common/nanomachines/provider/DisintegrationProvider$DisintegrationBehavior$$anonfun$update$1$$anonfun$apply$mcVI$sp$1;
/*     */             //   336: invokevirtual li$cil$oc$common$nanomachines$provider$DisintegrationProvider$DisintegrationBehavior$$anonfun$$anonfun$$$outer : ()Lli/cil/oc/common/nanomachines/provider/DisintegrationProvider$DisintegrationBehavior$$anonfun$update$1;
/*     */             //   339: invokevirtual li$cil$oc$common$nanomachines$provider$DisintegrationProvider$DisintegrationBehavior$$anonfun$$$outer : ()Lli/cil/oc/common/nanomachines/provider/DisintegrationProvider$DisintegrationBehavior;
/*     */             //   342: getfield li$cil$oc$common$nanomachines$provider$DisintegrationProvider$DisintegrationBehavior$$player : Lnet/minecraft/entity/player/EntityPlayer;
/*     */             //   345: aload_2
/*     */             //   346: invokevirtual x : ()I
/*     */             //   349: aload_2
/*     */             //   350: invokevirtual y : ()I
/*     */             //   353: aload_2
/*     */             //   354: invokevirtual z : ()I
/*     */             //   357: invokevirtual func_82246_f : (III)Z
/*     */             //   360: ifne -> 367
/*     */             //   363: iconst_0
/*     */             //   364: goto -> 368
/*     */             //   367: iconst_1
/*     */             //   368: istore #11
/*     */             //   370: iload #8
/*     */             //   372: ifeq -> 657
/*     */             //   375: iload #11
/*     */             //   377: ifeq -> 657
/*     */             //   380: getstatic li/cil/oc/util/ExtendedWorld$.MODULE$ : Lli/cil/oc/util/ExtendedWorld$;
/*     */             //   383: aload_0
/*     */             //   384: getfield $outer : Lli/cil/oc/common/nanomachines/provider/DisintegrationProvider$DisintegrationBehavior$$anonfun$update$1$$anonfun$apply$mcVI$sp$1;
/*     */             //   387: invokevirtual li$cil$oc$common$nanomachines$provider$DisintegrationProvider$DisintegrationBehavior$$anonfun$$anonfun$$$outer : ()Lli/cil/oc/common/nanomachines/provider/DisintegrationProvider$DisintegrationBehavior$$anonfun$update$1;
/*     */             //   390: getfield world$2 : Lnet/minecraft/world/World;
/*     */             //   393: invokevirtual extendedWorld : (Lnet/minecraft/world/World;)Lli/cil/oc/util/ExtendedWorld$ExtendedWorld;
/*     */             //   396: aload_2
/*     */             //   397: invokevirtual isAirBlock : (Lli/cil/oc/util/BlockPosition;)Z
/*     */             //   400: ifne -> 657
/*     */             //   403: getstatic li/cil/oc/util/ExtendedWorld$.MODULE$ : Lli/cil/oc/util/ExtendedWorld$;
/*     */             //   406: aload_0
/*     */             //   407: getfield $outer : Lli/cil/oc/common/nanomachines/provider/DisintegrationProvider$DisintegrationBehavior$$anonfun$update$1$$anonfun$apply$mcVI$sp$1;
/*     */             //   410: invokevirtual li$cil$oc$common$nanomachines$provider$DisintegrationProvider$DisintegrationBehavior$$anonfun$$anonfun$$$outer : ()Lli/cil/oc/common/nanomachines/provider/DisintegrationProvider$DisintegrationBehavior$$anonfun$update$1;
/*     */             //   413: getfield world$2 : Lnet/minecraft/world/World;
/*     */             //   416: invokevirtual extendedWorld : (Lnet/minecraft/world/World;)Lli/cil/oc/util/ExtendedWorld$ExtendedWorld;
/*     */             //   419: aload_2
/*     */             //   420: invokevirtual getBlock : (Lli/cil/oc/util/BlockPosition;)Lnet/minecraft/block/Block;
/*     */             //   423: astore #12
/*     */             //   425: aload #12
/*     */             //   427: aload_0
/*     */             //   428: getfield $outer : Lli/cil/oc/common/nanomachines/provider/DisintegrationProvider$DisintegrationBehavior$$anonfun$update$1$$anonfun$apply$mcVI$sp$1;
/*     */             //   431: invokevirtual li$cil$oc$common$nanomachines$provider$DisintegrationProvider$DisintegrationBehavior$$anonfun$$anonfun$$$outer : ()Lli/cil/oc/common/nanomachines/provider/DisintegrationProvider$DisintegrationBehavior$$anonfun$update$1;
/*     */             //   434: invokevirtual li$cil$oc$common$nanomachines$provider$DisintegrationProvider$DisintegrationBehavior$$anonfun$$$outer : ()Lli/cil/oc/common/nanomachines/provider/DisintegrationProvider$DisintegrationBehavior;
/*     */             //   437: getfield li$cil$oc$common$nanomachines$provider$DisintegrationProvider$DisintegrationBehavior$$player : Lnet/minecraft/entity/player/EntityPlayer;
/*     */             //   440: aload_0
/*     */             //   441: getfield $outer : Lli/cil/oc/common/nanomachines/provider/DisintegrationProvider$DisintegrationBehavior$$anonfun$update$1$$anonfun$apply$mcVI$sp$1;
/*     */             //   444: invokevirtual li$cil$oc$common$nanomachines$provider$DisintegrationProvider$DisintegrationBehavior$$anonfun$$anonfun$$$outer : ()Lli/cil/oc/common/nanomachines/provider/DisintegrationProvider$DisintegrationBehavior$$anonfun$update$1;
/*     */             //   447: getfield world$2 : Lnet/minecraft/world/World;
/*     */             //   450: aload_2
/*     */             //   451: invokevirtual x : ()I
/*     */             //   454: aload_2
/*     */             //   455: invokevirtual y : ()I
/*     */             //   458: aload_2
/*     */             //   459: invokevirtual z : ()I
/*     */             //   462: invokevirtual func_149737_a : (Lnet/minecraft/entity/player/EntityPlayer;Lnet/minecraft/world/World;III)F
/*     */             //   465: fstore #13
/*     */             //   467: fload #13
/*     */             //   469: iconst_0
/*     */             //   470: i2f
/*     */             //   471: fcmpl
/*     */             //   472: ifle -> 651
/*     */             //   475: iconst_1
/*     */             //   476: i2f
/*     */             //   477: fload #13
/*     */             //   479: fdiv
/*     */             //   480: f2i
/*     */             //   481: istore #14
/*     */             //   483: iload #14
/*     */             //   485: sipush #600
/*     */             //   488: if_icmpge -> 645
/*     */             //   491: getstatic li/cil/oc/util/ExtendedWorld$.MODULE$ : Lli/cil/oc/util/ExtendedWorld$;
/*     */             //   494: aload_0
/*     */             //   495: getfield $outer : Lli/cil/oc/common/nanomachines/provider/DisintegrationProvider$DisintegrationBehavior$$anonfun$update$1$$anonfun$apply$mcVI$sp$1;
/*     */             //   498: invokevirtual li$cil$oc$common$nanomachines$provider$DisintegrationProvider$DisintegrationBehavior$$anonfun$$anonfun$$$outer : ()Lli/cil/oc/common/nanomachines/provider/DisintegrationProvider$DisintegrationBehavior$$anonfun$update$1;
/*     */             //   501: getfield world$2 : Lnet/minecraft/world/World;
/*     */             //   504: invokevirtual extendedWorld : (Lnet/minecraft/world/World;)Lli/cil/oc/util/ExtendedWorld$ExtendedWorld;
/*     */             //   507: aload_2
/*     */             //   508: invokevirtual getBlockMetadata : (Lli/cil/oc/util/BlockPosition;)I
/*     */             //   511: istore #15
/*     */             //   513: new li/cil/oc/common/nanomachines/provider/DisintegrationProvider$SlowBreakInfo
/*     */             //   516: dup
/*     */             //   517: aload_0
/*     */             //   518: getfield $outer : Lli/cil/oc/common/nanomachines/provider/DisintegrationProvider$DisintegrationBehavior$$anonfun$update$1$$anonfun$apply$mcVI$sp$1;
/*     */             //   521: invokevirtual li$cil$oc$common$nanomachines$provider$DisintegrationProvider$DisintegrationBehavior$$anonfun$$anonfun$$$outer : ()Lli/cil/oc/common/nanomachines/provider/DisintegrationProvider$DisintegrationBehavior$$anonfun$update$1;
/*     */             //   524: getfield now$1 : J
/*     */             //   527: aload_0
/*     */             //   528: getfield $outer : Lli/cil/oc/common/nanomachines/provider/DisintegrationProvider$DisintegrationBehavior$$anonfun$update$1$$anonfun$apply$mcVI$sp$1;
/*     */             //   531: invokevirtual li$cil$oc$common$nanomachines$provider$DisintegrationProvider$DisintegrationBehavior$$anonfun$$anonfun$$$outer : ()Lli/cil/oc/common/nanomachines/provider/DisintegrationProvider$DisintegrationBehavior$$anonfun$update$1;
/*     */             //   534: getfield now$1 : J
/*     */             //   537: iload #14
/*     */             //   539: i2l
/*     */             //   540: ladd
/*     */             //   541: aload_2
/*     */             //   542: getstatic scala/Option$.MODULE$ : Lscala/Option$;
/*     */             //   545: aload_0
/*     */             //   546: getfield $outer : Lli/cil/oc/common/nanomachines/provider/DisintegrationProvider$DisintegrationBehavior$$anonfun$update$1$$anonfun$apply$mcVI$sp$1;
/*     */             //   549: invokevirtual li$cil$oc$common$nanomachines$provider$DisintegrationProvider$DisintegrationBehavior$$anonfun$$anonfun$$$outer : ()Lli/cil/oc/common/nanomachines/provider/DisintegrationProvider$DisintegrationBehavior$$anonfun$update$1;
/*     */             //   552: invokevirtual li$cil$oc$common$nanomachines$provider$DisintegrationProvider$DisintegrationBehavior$$anonfun$$$outer : ()Lli/cil/oc/common/nanomachines/provider/DisintegrationProvider$DisintegrationBehavior;
/*     */             //   555: getfield li$cil$oc$common$nanomachines$provider$DisintegrationProvider$DisintegrationBehavior$$player : Lnet/minecraft/entity/player/EntityPlayer;
/*     */             //   558: invokevirtual func_70694_bm : ()Lnet/minecraft/item/ItemStack;
/*     */             //   561: invokevirtual apply : (Ljava/lang/Object;)Lscala/Option;
/*     */             //   564: new li/cil/oc/common/nanomachines/provider/DisintegrationProvider$DisintegrationBehavior$$anonfun$update$1$$anonfun$apply$mcVI$sp$1$$anonfun$apply$mcVI$sp$2$$anonfun$1
/*     */             //   567: dup
/*     */             //   568: aload_0
/*     */             //   569: invokespecial <init> : (Lli/cil/oc/common/nanomachines/provider/DisintegrationProvider$DisintegrationBehavior$$anonfun$update$1$$anonfun$apply$mcVI$sp$1$$anonfun$apply$mcVI$sp$2;)V
/*     */             //   572: invokevirtual map : (Lscala/Function1;)Lscala/Option;
/*     */             //   575: aload #12
/*     */             //   577: iload #15
/*     */             //   579: invokespecial <init> : (JJLli/cil/oc/util/BlockPosition;Lscala/Option;Lnet/minecraft/block/Block;I)V
/*     */             //   582: astore #16
/*     */             //   584: getstatic li/cil/oc/util/ExtendedWorld$.MODULE$ : Lli/cil/oc/util/ExtendedWorld$;
/*     */             //   587: aload_0
/*     */             //   588: getfield $outer : Lli/cil/oc/common/nanomachines/provider/DisintegrationProvider$DisintegrationBehavior$$anonfun$update$1$$anonfun$apply$mcVI$sp$1;
/*     */             //   591: invokevirtual li$cil$oc$common$nanomachines$provider$DisintegrationProvider$DisintegrationBehavior$$anonfun$$anonfun$$$outer : ()Lli/cil/oc/common/nanomachines/provider/DisintegrationProvider$DisintegrationBehavior$$anonfun$update$1;
/*     */             //   594: getfield world$2 : Lnet/minecraft/world/World;
/*     */             //   597: invokevirtual extendedWorld : (Lnet/minecraft/world/World;)Lli/cil/oc/util/ExtendedWorld$ExtendedWorld;
/*     */             //   600: aload_2
/*     */             //   601: invokevirtual hashCode : ()I
/*     */             //   604: aload_2
/*     */             //   605: iconst_0
/*     */             //   606: invokevirtual destroyBlockInWorldPartially : (ILli/cil/oc/util/BlockPosition;I)V
/*     */             //   609: aload_0
/*     */             //   610: getfield $outer : Lli/cil/oc/common/nanomachines/provider/DisintegrationProvider$DisintegrationBehavior$$anonfun$update$1$$anonfun$apply$mcVI$sp$1;
/*     */             //   613: invokevirtual li$cil$oc$common$nanomachines$provider$DisintegrationProvider$DisintegrationBehavior$$anonfun$$anonfun$$$outer : ()Lli/cil/oc/common/nanomachines/provider/DisintegrationProvider$DisintegrationBehavior$$anonfun$update$1;
/*     */             //   616: invokevirtual li$cil$oc$common$nanomachines$provider$DisintegrationProvider$DisintegrationBehavior$$anonfun$$$outer : ()Lli/cil/oc/common/nanomachines/provider/DisintegrationProvider$DisintegrationBehavior;
/*     */             //   619: invokevirtual breakingMapNew : ()Lscala/collection/mutable/Map;
/*     */             //   622: getstatic scala/Predef$ArrowAssoc$.MODULE$ : Lscala/Predef$ArrowAssoc$;
/*     */             //   625: getstatic scala/Predef$.MODULE$ : Lscala/Predef$;
/*     */             //   628: aload_2
/*     */             //   629: invokevirtual ArrowAssoc : (Ljava/lang/Object;)Ljava/lang/Object;
/*     */             //   632: aload #16
/*     */             //   634: invokevirtual $minus$greater$extension : (Ljava/lang/Object;Ljava/lang/Object;)Lscala/Tuple2;
/*     */             //   637: invokeinterface $plus$eq : (Lscala/Tuple2;)Lscala/collection/mutable/MapLike;
/*     */             //   642: goto -> 660
/*     */             //   645: getstatic scala/runtime/BoxedUnit.UNIT : Lscala/runtime/BoxedUnit;
/*     */             //   648: goto -> 660
/*     */             //   651: getstatic scala/runtime/BoxedUnit.UNIT : Lscala/runtime/BoxedUnit;
/*     */             //   654: goto -> 660
/*     */             //   657: getstatic scala/runtime/BoxedUnit.UNIT : Lscala/runtime/BoxedUnit;
/*     */             //   660: astore #6
/*     */             //   662: goto -> 670
/*     */             //   665: getstatic scala/runtime/BoxedUnit.UNIT : Lscala/runtime/BoxedUnit;
/*     */             //   668: astore #6
/*     */             //   670: aload #6
/*     */             //   672: areturn
/*     */             // Line number table:
/*     */             //   Java source line number -> byte code offset
/*     */             //   #52	-> 0
/*     */             //   #53	-> 35
/*     */             //   #54	-> 55
/*     */             //   #55	-> 99
/*     */             //   #56	-> 133
/*     */             //   #54	-> 174
/*     */             //   #57	-> 179
/*     */             //   #58	-> 189
/*     */             //   #59	-> 233
/*     */             //   #60	-> 310
/*     */             //   #61	-> 370
/*     */             //   #62	-> 403
/*     */             //   #63	-> 425
/*     */             //   #64	-> 467
/*     */             //   #65	-> 475
/*     */             //   #66	-> 483
/*     */             //   #67	-> 491
/*     */             //   #68	-> 513
/*     */             //   #69	-> 584
/*     */             //   #70	-> 609
/*     */             //   #66	-> 645
/*     */             //   #64	-> 651
/*     */             //   #61	-> 657
/*     */             //   #57	-> 660
/*     */             //   #74	-> 665
/*     */             //   #53	-> 670
/*     */             // Local variable table:
/*     */             //   start	length	slot	name	descriptor
/*     */             //   0	673	0	this	Lli/cil/oc/common/nanomachines/provider/DisintegrationProvider$DisintegrationBehavior$$anonfun$update$1$$anonfun$apply$mcVI$sp$1$$anonfun$apply$mcVI$sp$2;
/*     */             //   0	673	1	z	I
/*     */             //   35	637	2	pos	Lli/cil/oc/util/BlockPosition;
/*     */             //   78	595	5	info	Lli/cil/oc/common/nanomachines/provider/DisintegrationProvider$SlowBreakInfo;
/*     */             //   233	440	7	event	Lnet/minecraftforge/event/entity/player/PlayerInteractEvent;
/*     */             //   310	363	8	allowed	Z
/*     */             //   370	303	11	adventureOk	Z
/*     */             //   425	248	12	block	Lnet/minecraft/block/Block;
/*     */             //   467	206	13	hardness	F
/*     */             //   483	190	14	timeToBreak	I
/*     */             //   513	129	15	meta	I
/*     */             //   584	58	16	info	Lli/cil/oc/common/nanomachines/provider/DisintegrationProvider$SlowBreakInfo; } public final class DisintegrationProvider$DisintegrationBehavior$$anonfun$update$1$$anonfun$apply$mcVI$sp$1$$anonfun$apply$mcVI$sp$2$$anonfun$1 extends AbstractFunction1<ItemStack, ItemStack> implements Serializable {
/*     */             public static final long serialVersionUID = 0L; public final ItemStack apply(ItemStack x$1) { return x$1.func_77946_l(); } public DisintegrationProvider$DisintegrationBehavior$$anonfun$update$1$$anonfun$apply$mcVI$sp$1$$anonfun$apply$mcVI$sp$2$$anonfun$1(DisintegrationProvider$DisintegrationBehavior$$anonfun$update$1$$anonfun$apply$mcVI$sp$1$$anonfun$apply$mcVI$sp$2 $outer) {} } } } } public final class DisintegrationProvider$DisintegrationBehavior$$anonfun$update$2 extends AbstractFunction1<Tuple2<BlockPosition, DisintegrationProvider.SlowBreakInfo>, Object> implements Serializable {
/* 100 */       public static final long serialVersionUID = 0L; public final boolean apply(Tuple2 check$ifrefutable$1) { boolean bool; Tuple2 tuple2 = check$ifrefutable$1; if (tuple2 != null) { bool = true; } else { bool = false; }  return bool; } public DisintegrationProvider$DisintegrationBehavior$$anonfun$update$2(DisintegrationProvider.DisintegrationBehavior $outer) {} } public final class DisintegrationProvider$DisintegrationBehavior$$anonfun$update$3 extends AbstractFunction1<Tuple2<BlockPosition, DisintegrationProvider.SlowBreakInfo>, BoxedUnit> implements Serializable { public static final long serialVersionUID = 0L; private final World world$2; private final long now$1; private final EntityPlayerMP x3$1; public final void apply(Tuple2 x$2) { Tuple2 tuple2 = x$2; if (tuple2 != null) { BlockPosition pos = (BlockPosition)tuple2._1(); DisintegrationProvider.SlowBreakInfo info = (DisintegrationProvider.SlowBreakInfo)tuple2._2(); this.$outer.breakingMapNew().$minus$eq(pos); info.finish(this.world$2, this.x3$1); BoxedUnit boxedUnit = (info.timeBroken() < this.now$1) ? BoxedUnit.UNIT : BoxedUnit.UNIT; return; }  throw new MatchError(tuple2); } public DisintegrationProvider$DisintegrationBehavior$$anonfun$update$3(DisintegrationProvider.DisintegrationBehavior $outer, World world$2, long now$1, EntityPlayerMP x3$1) {} } public final class DisintegrationProvider$DisintegrationBehavior$$anonfun$update$4 extends AbstractFunction1<BlockPosition, BoxedUnit> implements Serializable { public static final long serialVersionUID = 0L; private final World world$2; public DisintegrationProvider$DisintegrationBehavior$$anonfun$update$4(DisintegrationProvider.DisintegrationBehavior $outer, World world$2) {} public final void apply(BlockPosition pos) { ExtendedWorld$.MODULE$.extendedWorld(this.world$2).destroyBlockInWorldPartially(pos.hashCode(), pos, -1); } } } public static class SlowBreakInfo { private final long timeStarted; private final long timeBroken; private final BlockPosition pos; public long timeStarted() { return this.timeStarted; } private final Option<ItemStack> originalTool; private final Block block; private final int meta; public long timeBroken() { return this.timeBroken; } public BlockPosition pos() { return this.pos; } public Option<ItemStack> originalTool() { return this.originalTool; } public Block block() { return this.block; } public int meta() { return this.meta; }
/* 101 */      private int lastDamageSent = 0; public int lastDamageSent() { return this.lastDamageSent; } public void lastDamageSent_$eq(int x$1) { this.lastDamageSent = x$1; } public boolean checkTool(EntityPlayer player) {
/*     */       // Byte code:
/*     */       //   0: getstatic scala/Option$.MODULE$ : Lscala/Option$;
/*     */       //   3: aload_1
/*     */       //   4: invokevirtual func_70694_bm : ()Lnet/minecraft/item/ItemStack;
/*     */       //   7: invokevirtual apply : (Ljava/lang/Object;)Lscala/Option;
/*     */       //   10: new li/cil/oc/common/nanomachines/provider/DisintegrationProvider$SlowBreakInfo$$anonfun$2
/*     */       //   13: dup
/*     */       //   14: aload_0
/*     */       //   15: invokespecial <init> : (Lli/cil/oc/common/nanomachines/provider/DisintegrationProvider$SlowBreakInfo;)V
/*     */       //   18: invokevirtual map : (Lscala/Function1;)Lscala/Option;
/*     */       //   21: astore_2
/*     */       //   22: new scala/Tuple2
/*     */       //   25: dup
/*     */       //   26: aload_2
/*     */       //   27: aload_0
/*     */       //   28: invokevirtual originalTool : ()Lscala/Option;
/*     */       //   31: invokespecial <init> : (Ljava/lang/Object;Ljava/lang/Object;)V
/*     */       //   34: astore_3
/*     */       //   35: aload_3
/*     */       //   36: ifnull -> 171
/*     */       //   39: aload_3
/*     */       //   40: invokevirtual _1 : ()Ljava/lang/Object;
/*     */       //   43: checkcast scala/Option
/*     */       //   46: astore #4
/*     */       //   48: aload_3
/*     */       //   49: invokevirtual _2 : ()Ljava/lang/Object;
/*     */       //   52: checkcast scala/Option
/*     */       //   55: astore #5
/*     */       //   57: aload #4
/*     */       //   59: instanceof scala/Some
/*     */       //   62: ifeq -> 171
/*     */       //   65: aload #4
/*     */       //   67: checkcast scala/Some
/*     */       //   70: astore #6
/*     */       //   72: aload #6
/*     */       //   74: invokevirtual x : ()Ljava/lang/Object;
/*     */       //   77: checkcast net/minecraft/item/ItemStack
/*     */       //   80: astore #7
/*     */       //   82: aload #5
/*     */       //   84: instanceof scala/Some
/*     */       //   87: ifeq -> 171
/*     */       //   90: aload #5
/*     */       //   92: checkcast scala/Some
/*     */       //   95: astore #8
/*     */       //   97: aload #8
/*     */       //   99: invokevirtual x : ()Ljava/lang/Object;
/*     */       //   102: checkcast net/minecraft/item/ItemStack
/*     */       //   105: astore #9
/*     */       //   107: aload #7
/*     */       //   109: invokevirtual func_77973_b : ()Lnet/minecraft/item/Item;
/*     */       //   112: aload #9
/*     */       //   114: invokevirtual func_77973_b : ()Lnet/minecraft/item/Item;
/*     */       //   117: astore #11
/*     */       //   119: dup
/*     */       //   120: ifnonnull -> 132
/*     */       //   123: pop
/*     */       //   124: aload #11
/*     */       //   126: ifnull -> 140
/*     */       //   129: goto -> 165
/*     */       //   132: aload #11
/*     */       //   134: invokevirtual equals : (Ljava/lang/Object;)Z
/*     */       //   137: ifeq -> 165
/*     */       //   140: aload #7
/*     */       //   142: invokevirtual func_77984_f : ()Z
/*     */       //   145: ifne -> 161
/*     */       //   148: aload #7
/*     */       //   150: invokevirtual func_77960_j : ()I
/*     */       //   153: aload #9
/*     */       //   155: invokevirtual func_77960_j : ()I
/*     */       //   158: if_icmpne -> 165
/*     */       //   161: iconst_1
/*     */       //   162: goto -> 166
/*     */       //   165: iconst_0
/*     */       //   166: istore #10
/*     */       //   168: goto -> 224
/*     */       //   171: aload_3
/*     */       //   172: ifnull -> 221
/*     */       //   175: aload_3
/*     */       //   176: invokevirtual _1 : ()Ljava/lang/Object;
/*     */       //   179: checkcast scala/Option
/*     */       //   182: astore #12
/*     */       //   184: aload_3
/*     */       //   185: invokevirtual _2 : ()Ljava/lang/Object;
/*     */       //   188: checkcast scala/Option
/*     */       //   191: astore #13
/*     */       //   193: getstatic scala/None$.MODULE$ : Lscala/None$;
/*     */       //   196: aload #12
/*     */       //   198: invokevirtual equals : (Ljava/lang/Object;)Z
/*     */       //   201: ifeq -> 221
/*     */       //   204: getstatic scala/None$.MODULE$ : Lscala/None$;
/*     */       //   207: aload #13
/*     */       //   209: invokevirtual equals : (Ljava/lang/Object;)Z
/*     */       //   212: ifeq -> 221
/*     */       //   215: iconst_1
/*     */       //   216: istore #10
/*     */       //   218: goto -> 224
/*     */       //   221: iconst_0
/*     */       //   222: istore #10
/*     */       //   224: iload #10
/*     */       //   226: ireturn
/*     */       // Line number table:
/*     */       //   Java source line number -> byte code offset
/*     */       //   #104	-> 0
/*     */       //   #105	-> 22
/*     */       //   #106	-> 39
/*     */       //   #105	-> 171
/*     */       //   #107	-> 175
/*     */       //   #108	-> 221
/*     */       //   #105	-> 224
/*     */       // Local variable table:
/*     */       //   start	length	slot	name	descriptor
/*     */       //   0	227	0	this	Lli/cil/oc/common/nanomachines/provider/DisintegrationProvider$SlowBreakInfo;
/*     */       //   0	227	1	player	Lnet/minecraft/entity/player/EntityPlayer;
/*     */       //   22	204	2	currentTool	Lscala/Option;
/*     */       //   82	145	7	stackA	Lnet/minecraft/item/ItemStack;
/*     */       //   107	120	9	stackB	Lnet/minecraft/item/ItemStack;
/*     */     } public final class DisintegrationProvider$SlowBreakInfo$$anonfun$2 extends AbstractFunction1<ItemStack, ItemStack> implements Serializable { public static final long serialVersionUID = 0L; public final ItemStack apply(ItemStack x$3) {
/* 104 */         return x$3.func_77946_l();
/*     */       }
/*     */ 
/*     */       
/*     */       public DisintegrationProvider$SlowBreakInfo$$anonfun$2(DisintegrationProvider.SlowBreakInfo $outer) {} }
/*     */ 
/*     */ 
/*     */     
/*     */     public void update(World world, EntityPlayer player, long now) {
/* 113 */       long timeTotal = timeBroken() - timeStarted();
/* 114 */       if (timeTotal > 0L) {
/* 115 */         long timeTaken = now - timeStarted();
/* 116 */         long damage = 10L * timeTaken / timeTotal;
/* 117 */         if (damage != lastDamageSent()) {
/* 118 */           lastDamageSent_$eq((int)damage);
/* 119 */           ExtendedWorld$.MODULE$.extendedWorld(world).destroyBlockInWorldPartially(pos().hashCode(), pos(), lastDamageSent());
/*     */         } 
/*     */       } 
/*     */     }
/*     */     
/*     */     public void finish(World world, EntityPlayerMP player) {
/*     */       // Byte code:
/*     */       //   0: getstatic li/cil/oc/util/ExtendedWorld$.MODULE$ : Lli/cil/oc/util/ExtendedWorld$;
/*     */       //   3: aload_1
/*     */       //   4: invokevirtual extendedWorld : (Lnet/minecraft/world/World;)Lli/cil/oc/util/ExtendedWorld$ExtendedWorld;
/*     */       //   7: aload_0
/*     */       //   8: invokevirtual pos : ()Lli/cil/oc/util/BlockPosition;
/*     */       //   11: invokevirtual getBlock : (Lli/cil/oc/util/BlockPosition;)Lnet/minecraft/block/Block;
/*     */       //   14: aload_0
/*     */       //   15: invokevirtual block : ()Lnet/minecraft/block/Block;
/*     */       //   18: astore #4
/*     */       //   20: dup
/*     */       //   21: ifnonnull -> 33
/*     */       //   24: pop
/*     */       //   25: aload #4
/*     */       //   27: ifnull -> 41
/*     */       //   30: goto -> 66
/*     */       //   33: aload #4
/*     */       //   35: invokevirtual equals : (Ljava/lang/Object;)Z
/*     */       //   38: ifeq -> 66
/*     */       //   41: getstatic li/cil/oc/util/ExtendedWorld$.MODULE$ : Lli/cil/oc/util/ExtendedWorld$;
/*     */       //   44: aload_1
/*     */       //   45: invokevirtual extendedWorld : (Lnet/minecraft/world/World;)Lli/cil/oc/util/ExtendedWorld$ExtendedWorld;
/*     */       //   48: aload_0
/*     */       //   49: invokevirtual pos : ()Lli/cil/oc/util/BlockPosition;
/*     */       //   52: invokevirtual getBlockMetadata : (Lli/cil/oc/util/BlockPosition;)I
/*     */       //   55: aload_0
/*     */       //   56: invokevirtual meta : ()I
/*     */       //   59: if_icmpne -> 66
/*     */       //   62: iconst_1
/*     */       //   63: goto -> 67
/*     */       //   66: iconst_0
/*     */       //   67: istore_3
/*     */       //   68: iload_3
/*     */       //   69: ifeq -> 157
/*     */       //   72: getstatic li/cil/oc/util/ExtendedWorld$.MODULE$ : Lli/cil/oc/util/ExtendedWorld$;
/*     */       //   75: aload_1
/*     */       //   76: invokevirtual extendedWorld : (Lnet/minecraft/world/World;)Lli/cil/oc/util/ExtendedWorld$ExtendedWorld;
/*     */       //   79: aload_0
/*     */       //   80: invokevirtual pos : ()Lli/cil/oc/util/BlockPosition;
/*     */       //   83: invokevirtual hashCode : ()I
/*     */       //   86: aload_0
/*     */       //   87: invokevirtual pos : ()Lli/cil/oc/util/BlockPosition;
/*     */       //   90: iconst_m1
/*     */       //   91: invokevirtual destroyBlockInWorldPartially : (ILli/cil/oc/util/BlockPosition;I)V
/*     */       //   94: aload_2
/*     */       //   95: getfield field_71134_c : Lnet/minecraft/server/management/ItemInWorldManager;
/*     */       //   98: aload_0
/*     */       //   99: invokevirtual pos : ()Lli/cil/oc/util/BlockPosition;
/*     */       //   102: invokevirtual x : ()I
/*     */       //   105: aload_0
/*     */       //   106: invokevirtual pos : ()Lli/cil/oc/util/BlockPosition;
/*     */       //   109: invokevirtual y : ()I
/*     */       //   112: aload_0
/*     */       //   113: invokevirtual pos : ()Lli/cil/oc/util/BlockPosition;
/*     */       //   116: invokevirtual z : ()I
/*     */       //   119: invokevirtual func_73084_b : (III)Z
/*     */       //   122: ifeq -> 157
/*     */       //   125: getstatic li/cil/oc/util/ExtendedWorld$.MODULE$ : Lli/cil/oc/util/ExtendedWorld$;
/*     */       //   128: aload_1
/*     */       //   129: invokevirtual extendedWorld : (Lnet/minecraft/world/World;)Lli/cil/oc/util/ExtendedWorld$ExtendedWorld;
/*     */       //   132: sipush #2001
/*     */       //   135: aload_0
/*     */       //   136: invokevirtual pos : ()Lli/cil/oc/util/BlockPosition;
/*     */       //   139: aload_0
/*     */       //   140: invokevirtual block : ()Lnet/minecraft/block/Block;
/*     */       //   143: invokestatic func_149682_b : (Lnet/minecraft/block/Block;)I
/*     */       //   146: aload_0
/*     */       //   147: invokevirtual meta : ()I
/*     */       //   150: bipush #12
/*     */       //   152: ishl
/*     */       //   153: iadd
/*     */       //   154: invokevirtual playAuxSFX : (ILli/cil/oc/util/BlockPosition;I)V
/*     */       //   157: return
/*     */       // Line number table:
/*     */       //   Java source line number -> byte code offset
/*     */       //   #125	-> 0
/*     */       //   #126	-> 68
/*     */       //   #127	-> 72
/*     */       //   #128	-> 94
/*     */       //   #129	-> 125
/*     */       //   #124	-> 157
/*     */       // Local variable table:
/*     */       //   start	length	slot	name	descriptor
/*     */       //   0	158	0	this	Lli/cil/oc/common/nanomachines/provider/DisintegrationProvider$SlowBreakInfo;
/*     */       //   0	158	1	world	Lnet/minecraft/world/World;
/*     */       //   0	158	2	player	Lnet/minecraft/entity/player/EntityPlayerMP;
/*     */       //   68	90	3	sameBlock	Z
/*     */     }
/*     */     
/*     */     public SlowBreakInfo(long timeStarted, long timeBroken, BlockPosition pos, Option<ItemStack> originalTool, Block block, int meta) {} }
/*     */    }


/* Location:              C:\Users\shame\AppData\Roaming\PrismLauncher\instances\GT_New_Horizons_2.7.4_Java_17-21\.minecraft\mods\OpenComputers-1.10.30-GTNH.jar!\li\cil\oc\common\nanomachines\provider\DisintegrationProvider.class
 * Java compiler version: 8 (52.0)
 * JD-Core Version:       1.1.3
 */