/*    */ package li.cil.oc.common.nanomachines.provider;
/*    */ import net.minecraft.potion.Potion;
/*    */ import scala.Option;
/*    */ @ScalaSignature(bytes = "\006\001\005=t!B\001\003\021\003y\021A\004)pi&|g\016\025:pm&$WM\035\006\003\007\021\t\001\002\035:pm&$WM\035\006\003\013\031\tAB\\1o_6\f7\r[5oKNT!a\002\005\002\r\r|W.\\8o\025\tI!\"\001\002pG*\0211\002D\001\004G&d'\"A\007\002\0051L7\001\001\t\003!Ei\021A\001\004\006%\tA\ta\005\002\017!>$\030n\0348Qe>4\030\016Z3s'\t\tB\003\005\002\021+%\021aC\001\002\016'\016\fG.\031)s_ZLG-\032:\t\013a\tB\021A\r\002\rqJg.\033;?)\005y\001\002C\016\022\021\013\007I\021\001\017\002\037A{G/[8o/\"LG/\0327jgR,\022!\b\t\004=\025:S\"A\020\013\005\001\n\023!C5n[V$\030M\0317f\025\t\0213%\001\006d_2dWm\031;j_:T\021\001J\001\006g\016\fG.Y\005\003M}\0211aU3u!\tAs&D\001*\025\tQ3&\001\004q_RLwN\034\006\003Y5\n\021\"\\5oK\016\024\030M\032;\013\0039\n1A\\3u\023\t\001\024F\001\004Q_RLwN\034\005\teEA\t\021)Q\005;\005\001\002k\034;j_:<\006.\033;fY&\034H\017\t\005\006iE!\t!N\001\016M&dG/\032:Q_RLwN\\:\026\005Y:ECA\0178\021\025A4\0071\001:\003\021a\027n\035;\021\007i\022UI\004\002<\001:\021AhP\007\002{)\021aHD\001\007yI|w\016\036 \n\003\021J!!Q\022\002\017A\f7m[1hK&\0211\t\022\002\t\023R,'/\0312mK*\021\021i\t\t\003\r\036c\001\001B\003Ig\t\007\021JA\001U#\tQe\n\005\002L\0316\t1%\003\002NG\t9aj\034;iS:<\007CA&P\023\t\0016EA\002B]fDQAU\t\005\002M\013\001#[:Q_RLwN\\#mS\036L'\r\\3\025\005Q;\006CA&V\023\t16EA\004C_>dW-\0318\t\013)\n\006\031A\024\t\013e\013B\021\t.\002)\r\024X-\031;f'\016\fG.\031\"fQ\0064\030n\034:t)\tY6\rE\002;\005r\003\"!X1\016\003yS!!B0\013\005\001D\021aA1qS&\021!M\030\002\t\005\026D\027M^5pe\")A\r\027a\001K\0061\001\017\\1zKJ\004\"A\0326\016\003\035T!\001\0325\013\005%\\\023AB3oi&$\0300\003\002lO\naQI\034;jif\004F.Y=fe\")Q.\005C!]\006\021rO]5uK\n+\007.\031<j_J$vN\024\"U)\ry'\017\036\t\003\027BL!!]\022\003\tUs\027\016\036\005\006g2\004\r\001X\001\tE\026D\027M^5pe\")Q\017\034a\001m\006\031aN\031;\021\005]LX\"\001=\013\005U\\\023B\001>y\0059q%\t\026+bO\016{W\016]8v]\022DQ\001`\t\005Bu\f1C]3bI\n+\007.\031<j_J4%o\\7O\005R#RA`A6\003[\0022a`A\001\033\005\tbABA\002#\001\t)A\001\bQ_RLwN\034\"fQ\0064\030n\034:\024\t\005\005\021q\001\t\005\003\023\ty!\004\002\002\f)\031\021QB0\002\rA\024XMZ1c\023\021\t\t\"a\003\003!\005\0237\017\036:bGR\024U\r[1wS>\024\bB\003\026\002\002\t\025\r\021\"\001\002\026U\tq\005\003\006\002\032\005\005!\021!Q\001\n\035\nq\001]8uS>t\007\005C\005e\003\003\021\t\021)A\005K\"9\001$!\001\005\002\005}A#\002@\002\"\005\r\002B\002\026\002\036\001\007q\005\003\004e\003;\001\r!\032\005\013\003O\t\tA1A\005\006\005%\022\001\003#ve\006$\030n\0348\026\005\005-rBAA\027;\t\021\001\fC\005\0022\005\005\001\025!\004\002,\005IA)\036:bi&|g\016\t\005\t\003k\t\t\001\"\001\0028\005I\021-\0349mS\032LWM\035\013\005\003s\ty\004E\002L\003wI1!!\020$\005\rIe\016\036\005\007I\006M\002\031A3\t\021\005\r\023\021\001C!\003\013\n1bZ3u\035\006lW\rS5oiR\021\021q\t\t\005\003\023\nyED\002L\003\027J1!!\024$\003\031\001&/\0323fM&!\021\021KA*\005\031\031FO]5oO*\031\021QJ\022\t\021\005]\023\021\001C!\0033\n\021b\0348ESN\f'\r\\3\025\007=\fY\006\003\005\002^\005U\003\031AA0\003\031\021X-Y:p]B\031Q,!\031\n\007\005\rdLA\007ESN\f'\r\\3SK\006\034xN\034\005\t\003O\n\t\001\"\021\002j\0051Q\017\0353bi\026$\022a\034\005\006In\004\r!\032\005\006kn\004\rA\036")
/*    */ public final class PotionProvider { public static PotionBehavior readBehaviorFromNBT(EntityPlayer paramEntityPlayer, NBTTagCompound paramNBTTagCompound) { return PotionProvider$.MODULE$.readBehaviorFromNBT(paramEntityPlayer, paramNBTTagCompound); } public static void writeBehaviorToNBT(Behavior paramBehavior, NBTTagCompound paramNBTTagCompound) { PotionProvider$.MODULE$.writeBehaviorToNBT(paramBehavior, paramNBTTagCompound); } public static Iterable<Behavior> createScalaBehaviors(EntityPlayer paramEntityPlayer) {
/*    */     return PotionProvider$.MODULE$.createScalaBehaviors(paramEntityPlayer);
/*    */   } public static boolean isPotionEligible(Potion paramPotion) {
/*    */     return PotionProvider$.MODULE$.isPotionEligible(paramPotion);
/*    */   } public static <T> Set<Potion> filterPotions(Iterable<T> paramIterable) {
/*    */     return PotionProvider$.MODULE$.filterPotions(paramIterable);
/*    */   } public static Set<Potion> PotionWhitelist() {
/*    */     return PotionProvider$.MODULE$.PotionWhitelist();
/*    */   } public static Iterable<Behavior> createBehaviors(EntityPlayer paramEntityPlayer) {
/*    */     return PotionProvider$.MODULE$.createBehaviors(paramEntityPlayer);
/*    */   } public static Behavior readFromNBT(EntityPlayer paramEntityPlayer, NBTTagCompound paramNBTTagCompound) {
/*    */     return PotionProvider$.MODULE$.readFromNBT(paramEntityPlayer, paramNBTTagCompound);
/*    */   } public static NBTTagCompound writeToNBT(Behavior paramBehavior) {
/*    */     return PotionProvider$.MODULE$.writeToNBT(paramBehavior);
/*    */   } public final class PotionProvider$$anonfun$filterPotions$2 extends AbstractFunction1<T, Option<Potion>> implements Serializable { public final Option<Potion> apply(Object x0$1) { None$ none$;
/* 20 */       Object object = x0$1;
/* 21 */       if (object instanceof String) { String str = (String)object; Option option = Predef$.MODULE$.refArrayOps((Object[])Potion.field_76425_a).find((Function1)new PotionProvider$$anonfun$filterPotions$2$$anonfun$apply$1(this, str)); }
/* 22 */       else { if (object instanceof Number) { Number number = (Number)object; if (number.intValue() >= 0 && number.intValue() < Potion.field_76425_a.length) return Option$.MODULE$.apply(Potion.field_76425_a[number.intValue()]);  }
/* 23 */          none$ = None$.MODULE$; }  return (Option<Potion>)none$; } public static final long serialVersionUID = 0L; public final class PotionProvider$$anonfun$filterPotions$2$$anonfun$apply$1 extends AbstractFunction1<Potion, Object> implements Serializable {
/*    */       public static final long serialVersionUID = 0L; private final String x2$1; public final boolean apply(Potion p) { // Byte code:
/*    */         //   0: aload_1
/*    */         //   1: ifnull -> 36
/*    */         //   4: aload_1
/*    */         //   5: invokevirtual func_76393_a : ()Ljava/lang/String;
/*    */         //   8: aload_0
/*    */         //   9: getfield x2$1 : Ljava/lang/String;
/*    */         //   12: astore_2
/*    */         //   13: dup
/*    */         //   14: ifnonnull -> 25
/*    */         //   17: pop
/*    */         //   18: aload_2
/*    */         //   19: ifnull -> 32
/*    */         //   22: goto -> 36
/*    */         //   25: aload_2
/*    */         //   26: invokevirtual equals : (Ljava/lang/Object;)Z
/*    */         //   29: ifeq -> 36
/*    */         //   32: iconst_1
/*    */         //   33: goto -> 37
/*    */         //   36: iconst_0
/*    */         //   37: ireturn
/*    */         // Line number table:
/*    */         //   Java source line number -> byte code offset
/*    */         //   #21	-> 0
/*    */         // Local variable table:
/*    */         //   start	length	slot	name	descriptor
/*    */         //   0	38	0	this	Lli/cil/oc/common/nanomachines/provider/PotionProvider$$anonfun$filterPotions$2$$anonfun$apply$1;
/* 24 */         //   0	38	1	p	Lnet/minecraft/potion/Potion; } public PotionProvider$$anonfun$filterPotions$2$$anonfun$apply$1(PotionProvider$$anonfun$filterPotions$2 $outer, String x2$1) {} } } public final class PotionProvider$$anonfun$filterPotions$1 extends AbstractPartialFunction<Option<Potion>, Potion> implements Serializable { public static final long serialVersionUID = 0L; public final <A1 extends Option<Potion>, B1> B1 applyOrElse(Option x1, Function1 default) { Object object; Option option = x1;
/* 25 */       if (option instanceof Some) { Some some = (Some)option; Potion potion = (Potion)some.x(); } else { object = default.apply(x1); }  return (B1)object; } public final boolean isDefinedAt(Option x1) { boolean bool; Option option = x1; if (option instanceof Some) { bool = true; }
/*    */       else
/*    */       { bool = false; }
/*    */       
/*    */       return bool; }
/*    */      }
/*    */   public final class PotionProvider$$anonfun$createScalaBehaviors$1 extends AbstractFunction1<Potion, Object> implements Serializable { public static final long serialVersionUID = 0L;
/* 32 */     public final boolean apply(Potion potion) { return PotionProvider$.MODULE$.isPotionEligible(potion); } } public final class PotionProvider$$anonfun$createScalaBehaviors$2 extends AbstractFunction1<Potion, PotionBehavior> implements Serializable { public static final long serialVersionUID = 0L; private final EntityPlayer player$1; public final PotionProvider.PotionBehavior apply(Potion x$1) { return new PotionProvider.PotionBehavior(x$1, this.player$1); }
/*    */ 
/*    */ 
/*    */     
/*    */     public PotionProvider$$anonfun$createScalaBehaviors$2(EntityPlayer player$1) {} }
/*    */ 
/*    */   
/*    */   public static class PotionBehavior
/*    */     extends AbstractBehavior
/*    */   {
/*    */     private final Potion potion;
/*    */     private final EntityPlayer player;
/*    */     private final int Duration;
/*    */     
/*    */     public Potion potion()
/*    */     {
/* 48 */       return this.potion; } public PotionBehavior(Potion potion, EntityPlayer player) { super(player); } public final int Duration() {
/* 49 */       return 600;
/*    */     } public int amplifier(EntityPlayer player) {
/* 51 */       return Nanomachines.getController(player).getInputCount((Behavior)this) - 1;
/*    */     } public String getNameHint() {
/* 53 */       return (new StringOps(Predef$.MODULE$.augmentString(potion().func_76393_a()))).stripPrefix("potion.");
/*    */     }
/*    */     public void onDisable(DisableReason reason) {
/* 56 */       this.player.func_82170_o((potion()).field_76415_H);
/*    */     }
/*    */     
/*    */     public void update() {
/* 60 */       this.player.func_70690_d(new PotionEffect((potion()).field_76415_H, 600, Settings$.MODULE$.get().enableNanomachinePfx() ? amplifier(this.player) : -1));
/*    */     }
/*    */   } }


/* Location:              C:\Users\shame\AppData\Roaming\PrismLauncher\instances\GT_New_Horizons_2.7.4_Java_17-21\.minecraft\mods\OpenComputers-1.10.30-GTNH.jar!\li\cil\oc\common\nanomachines\provider\PotionProvider.class
 * Java compiler version: 8 (52.0)
 * JD-Core Version:       1.1.3
 */