/*    */ package li.cil.oc.server.network;
/*    */ @ScalaSignature(bytes = "\006\001\005ufaB\001\003!\003\r\t!\004\002\n\007>l\007o\0348f]RT!a\001\003\002\0179,Go^8sW*\021QAB\001\007g\026\024h/\032:\013\005\035A\021AA8d\025\tI!\"A\002dS2T\021aC\001\003Y&\034\001a\005\003\001\035Ya\002CA\b\025\033\005\001\"BA\t\023\003\021a\027M\\4\013\003M\tAA[1wC&\021Q\003\005\002\007\037\nTWm\031;\021\005]YR\"\001\r\013\005\rI\"B\001\016\007\003\r\t\007/[\005\003\003a\001\"!\b\020\016\003\tI!a\b\002\003\t9{G-\032\005\006C\001!\tAI\001\007I%t\027\016\036\023\025\003\r\002\"\001J\024\016\003\025R\021AJ\001\006g\016\fG.Y\005\003Q\025\022A!\0268ji\"9!\006\001b\001\016\003Y\023\001\0028b[\026,\022\001\f\t\003[Ar!\001\n\030\n\005=*\023A\002)sK\022,g-\003\0022e\t11\013\036:j]\036T!aL\023\t\013Q\002A\021A\033\002\025YL7/\0332jY&$\030\020F\0017!\t9r'\003\00291\tQa+[:jE&d\027\016^=\t\021i\002\001R1A\005\nm\n\021bY1mY\n\f7m[:\026\003q\002B!\020\"-\t6\taH\003\002@\001\006I\021.\\7vi\006\024G.\032\006\003\003\026\n!bY8mY\026\034G/[8o\023\t\031eHA\002NCB\004\"!R,\017\005\031#fBA$S\035\tA\025K\004\002J!:\021!j\024\b\003\027:k\021\001\024\006\003\0332\ta\001\020:p_Rt\024\"A\006\n\005%Q\021BA\004\t\023\t)a!\003\002T\t\0059Q.Y2iS:,\027BA+W\003%\031\025\r\0347cC\016\\7O\003\002T\t%\021\001,\027\002\t\007\006dGNY1dW*\021QK\026\005\t7\002A\t\021)Q\005y\005Q1-\0317mE\006\0347n\035\021\t\021u\003\001R1A\005\ny\013Q\001[8tiN,\022a\030\t\005{\tc\003\rE\002%C\016L!AY\023\003\r=\003H/[8o!\t9B-\003\002f1\tYQI\034<je>tW.\0328u\021!9\007\001#A!B\023y\026A\0025pgR\034\b\005C\004j\001\001\007I\021\0026\002\027}3\030n]5cS2LG/_\013\002m!9A\016\001a\001\n\023i\027aD0wSNL'-\0337jif|F%Z9\025\005\rr\007bB8l\003\003\005\rAN\001\004q\022\n\004BB9\001A\003&a'\001\007`m&\034\030NY5mSRL\b\005C\003t\001\021\005A/A\007tKR4\026n]5cS2LG/\037\013\003GUDQA\036:A\002Y\nQA^1mk\026DQ\001\037\001\005\002e\fQbY1o\005\026\034V-\0328Ge>lGC\001>~!\t!30\003\002}K\t9!i\\8mK\006t\007\"\002@x\001\004y\030!B8uQ\026\024\bcA\f\002\002%\021q\004\007\005\b\003\013\001A\021BA\004\003\025\tG\r\032+p)\r\031\023\021\002\005\t\003\027\t\031\0011\001\002\016\005)an\0343fgB)\021qBA\r:!\021\021CA\013\035\rY\0251C\005\002M%\031\021qC\023\002\017A\f7m[1hK&!\0211DA\017\005!IE/\032:bE2,'bAA\fK!9\021\021\005\001\005\n\005\r\022A\003:f[>4XM\022:p[R\0311%!\n\t\021\005-\021q\004a\001\003\033Aq!!\013\001\t\003\nY#A\004nKRDw\016Z:\025\005\0055\002#BA\030\003kaSBAA\031\025\r\t\031DE\001\005kRLG.\003\003\0028\005E\"aA*fi\"9\0211\b\001\005B\005u\022AC1o]>$\030\r^5p]R!\021qHA$!\021\t\t%!\022\016\005\005\r#BA*\032\023\rA\0261\t\005\b\003\023\nI\0041\001-\003\031iW\r\0365pI\"9\021Q\n\001\005B\005=\023AB5om>\\W\r\006\005\002R\005u\023qLA5!\025!\0231KA,\023\r\t)&\n\002\006\003J\024\030-\037\t\004I\005e\023bAA.K\t1\021I\\=SK\032Dq!!\023\002L\001\007A\006\003\005\002b\005-\003\031AA2\003\035\031wN\034;fqR\004B!!\021\002f%!\021qMA\"\005\035\031uN\034;fqRD\001\"a\033\002L\001\007\021QN\001\nCJ<W/\\3oiN\004R\001JA8\003/J1!!\035&\005)a$/\0329fCR,GM\020\005\b\003k\002A\021IA<\003\021aw.\0313\025\007\r\nI\b\003\005\002|\005M\004\031AA?\003\rq'\r\036\t\005\003\nY)\004\002\002\002*!\0211PAB\025\021\t))a\"\002\0235Lg.Z2sC\032$(BAAE\003\rqW\r^\005\005\003\033\013\tI\001\bO\005R#\026mZ\"p[B|WO\0343\t\017\005E\005\001\"\021\002\024\006!1/\031<f)\r\031\023Q\023\005\t\003w\ny\t1\001\002~!9\021\021\024\001\005B\005m\025\001\003;p'R\024\030N\\4\025\005\005u\005cA\b\002 &\021\021\007\005\005\017\003G\003\001\023aA\001\002\023%\021QUAU\003)\031X\017]3sI1|\027\r\032\013\004G\005\035\006\002CA>\003C\003\r!! \n\007\005Ud\004\003\b\002.\002\001\n1!A\001\n\023\ty+a-\002\025M,\b/\032:%g\0064X\rF\002$\003cC\001\"a\037\002,\002\007\021QP\005\004\003#s\002BDA\\\001A\005\031\021!A\005\n\005e\0261X\001\017gV\004XM\035\023u_N#(/\0338h)\005a\023bAAM=\001")
/*    */ public interface Component extends Component, Node { String name();
/*    */   Visibility visibility();
/*    */   Map<String, Callbacks.Callback> li$cil$oc$server$network$Component$$callbacks();
/*    */   Map<String, Option<Environment>> li$cil$oc$server$network$Component$$hosts();
/*    */   Visibility li$cil$oc$server$network$Component$$_visibility();
/*    */   @TraitSetter
/*    */   void li$cil$oc$server$network$Component$$_visibility_$eq(Visibility paramVisibility);
/*    */   void setVisibility(Visibility paramVisibility);
/*    */   boolean canBeSeenFrom(Node paramNode);
/*    */   Set<String> methods();
/*    */   Callback annotation(String paramString);
/*    */   Object[] invoke(String paramString, Context paramContext, Seq<Object> paramSeq);
/*    */   void load(NBTTagCompound paramNBTTagCompound);
/*    */   void save(NBTTagCompound paramNBTTagCompound);
/*    */   String toString();
/*    */   public final class Component$$anonfun$li$cil$oc$server$network$Component$$hosts$1 extends AbstractFunction1<Tuple2<String, Callbacks.Callback>, Tuple2<String, Option<ManagedEnvironment>>> implements Serializable { public static final long serialVersionUID = 0L;
/*    */     private final CompoundBlockEnvironment x2$2;
/*    */     
/*    */     public final Tuple2<String, Option<ManagedEnvironment>> apply(Tuple2 x0$1) {
/*    */       // Byte code:
/*    */       //   0: aload_1
/*    */       //   1: astore_2
/*    */       //   2: aload_2
/*    */       //   3: ifnull -> 303
/*    */       //   6: aload_2
/*    */       //   7: invokevirtual _1 : ()Ljava/lang/Object;
/*    */       //   10: checkcast java/lang/String
/*    */       //   13: astore_3
/*    */       //   14: aload_2
/*    */       //   15: invokevirtual _2 : ()Ljava/lang/Object;
/*    */       //   18: checkcast li/cil/oc/server/machine/Callbacks$Callback
/*    */       //   21: astore #4
/*    */       //   23: aload #4
/*    */       //   25: astore #6
/*    */       //   27: aload #6
/*    */       //   29: instanceof li/cil/oc/server/machine/Callbacks$ComponentCallback
/*    */       //   32: ifeq -> 158
/*    */       //   35: aload #6
/*    */       //   37: checkcast li/cil/oc/server/machine/Callbacks$ComponentCallback
/*    */       //   40: astore #7
/*    */       //   42: aload_0
/*    */       //   43: getfield x2$2 : Lli/cil/oc/server/driver/CompoundBlockEnvironment;
/*    */       //   46: invokevirtual environments : ()Lscala/collection/Seq;
/*    */       //   49: new li/cil/oc/server/network/Component$$anonfun$li$cil$oc$server$network$Component$$hosts$1$$anonfun$1
/*    */       //   52: dup
/*    */       //   53: aload_0
/*    */       //   54: aload #7
/*    */       //   56: invokespecial <init> : (Lli/cil/oc/server/network/Component$$anonfun$li$cil$oc$server$network$Component$$hosts$1;Lli/cil/oc/server/machine/Callbacks$ComponentCallback;)V
/*    */       //   59: invokeinterface find : (Lscala/Function1;)Lscala/Option;
/*    */       //   64: astore #9
/*    */       //   66: aload #9
/*    */       //   68: instanceof scala/Some
/*    */       //   71: ifeq -> 133
/*    */       //   74: aload #9
/*    */       //   76: checkcast scala/Some
/*    */       //   79: astore #10
/*    */       //   81: aload #10
/*    */       //   83: invokevirtual x : ()Ljava/lang/Object;
/*    */       //   86: checkcast scala/Tuple2
/*    */       //   89: astore #11
/*    */       //   91: aload #11
/*    */       //   93: ifnull -> 133
/*    */       //   96: aload #11
/*    */       //   98: invokevirtual _2 : ()Ljava/lang/Object;
/*    */       //   101: checkcast li/cil/oc/api/network/ManagedEnvironment
/*    */       //   104: astore #12
/*    */       //   106: getstatic scala/Predef$ArrowAssoc$.MODULE$ : Lscala/Predef$ArrowAssoc$;
/*    */       //   109: getstatic scala/Predef$.MODULE$ : Lscala/Predef$;
/*    */       //   112: aload_3
/*    */       //   113: invokevirtual ArrowAssoc : (Ljava/lang/Object;)Ljava/lang/Object;
/*    */       //   116: new scala/Some
/*    */       //   119: dup
/*    */       //   120: aload #12
/*    */       //   122: invokespecial <init> : (Ljava/lang/Object;)V
/*    */       //   125: invokevirtual $minus$greater$extension : (Ljava/lang/Object;Ljava/lang/Object;)Lscala/Tuple2;
/*    */       //   128: astore #13
/*    */       //   130: goto -> 151
/*    */       //   133: getstatic scala/Predef$ArrowAssoc$.MODULE$ : Lscala/Predef$ArrowAssoc$;
/*    */       //   136: getstatic scala/Predef$.MODULE$ : Lscala/Predef$;
/*    */       //   139: aload_3
/*    */       //   140: invokevirtual ArrowAssoc : (Ljava/lang/Object;)Ljava/lang/Object;
/*    */       //   143: getstatic scala/None$.MODULE$ : Lscala/None$;
/*    */       //   146: invokevirtual $minus$greater$extension : (Ljava/lang/Object;Ljava/lang/Object;)Lscala/Tuple2;
/*    */       //   149: astore #13
/*    */       //   151: aload #13
/*    */       //   153: astore #8
/*    */       //   155: goto -> 286
/*    */       //   158: aload #6
/*    */       //   160: instanceof li/cil/oc/server/machine/Callbacks$PeripheralCallback
/*    */       //   163: ifeq -> 293
/*    */       //   166: aload #6
/*    */       //   168: checkcast li/cil/oc/server/machine/Callbacks$PeripheralCallback
/*    */       //   171: astore #14
/*    */       //   173: aload_0
/*    */       //   174: getfield x2$2 : Lli/cil/oc/server/driver/CompoundBlockEnvironment;
/*    */       //   177: invokevirtual environments : ()Lscala/collection/Seq;
/*    */       //   180: new li/cil/oc/server/network/Component$$anonfun$li$cil$oc$server$network$Component$$hosts$1$$anonfun$2
/*    */       //   183: dup
/*    */       //   184: aload_0
/*    */       //   185: aload #14
/*    */       //   187: invokespecial <init> : (Lli/cil/oc/server/network/Component$$anonfun$li$cil$oc$server$network$Component$$hosts$1;Lli/cil/oc/server/machine/Callbacks$PeripheralCallback;)V
/*    */       //   190: invokeinterface find : (Lscala/Function1;)Lscala/Option;
/*    */       //   195: astore #15
/*    */       //   197: aload #15
/*    */       //   199: instanceof scala/Some
/*    */       //   202: ifeq -> 264
/*    */       //   205: aload #15
/*    */       //   207: checkcast scala/Some
/*    */       //   210: astore #16
/*    */       //   212: aload #16
/*    */       //   214: invokevirtual x : ()Ljava/lang/Object;
/*    */       //   217: checkcast scala/Tuple2
/*    */       //   220: astore #17
/*    */       //   222: aload #17
/*    */       //   224: ifnull -> 264
/*    */       //   227: aload #17
/*    */       //   229: invokevirtual _2 : ()Ljava/lang/Object;
/*    */       //   232: checkcast li/cil/oc/api/network/ManagedEnvironment
/*    */       //   235: astore #18
/*    */       //   237: getstatic scala/Predef$ArrowAssoc$.MODULE$ : Lscala/Predef$ArrowAssoc$;
/*    */       //   240: getstatic scala/Predef$.MODULE$ : Lscala/Predef$;
/*    */       //   243: aload_3
/*    */       //   244: invokevirtual ArrowAssoc : (Ljava/lang/Object;)Ljava/lang/Object;
/*    */       //   247: new scala/Some
/*    */       //   250: dup
/*    */       //   251: aload #18
/*    */       //   253: invokespecial <init> : (Ljava/lang/Object;)V
/*    */       //   256: invokevirtual $minus$greater$extension : (Ljava/lang/Object;Ljava/lang/Object;)Lscala/Tuple2;
/*    */       //   259: astore #19
/*    */       //   261: goto -> 282
/*    */       //   264: getstatic scala/Predef$ArrowAssoc$.MODULE$ : Lscala/Predef$ArrowAssoc$;
/*    */       //   267: getstatic scala/Predef$.MODULE$ : Lscala/Predef$;
/*    */       //   270: aload_3
/*    */       //   271: invokevirtual ArrowAssoc : (Ljava/lang/Object;)Ljava/lang/Object;
/*    */       //   274: getstatic scala/None$.MODULE$ : Lscala/None$;
/*    */       //   277: invokevirtual $minus$greater$extension : (Ljava/lang/Object;Ljava/lang/Object;)Lscala/Tuple2;
/*    */       //   280: astore #19
/*    */       //   282: aload #19
/*    */       //   284: astore #8
/*    */       //   286: aload #8
/*    */       //   288: astore #5
/*    */       //   290: aload #5
/*    */       //   292: areturn
/*    */       //   293: new scala/MatchError
/*    */       //   296: dup
/*    */       //   297: aload #6
/*    */       //   299: invokespecial <init> : (Ljava/lang/Object;)V
/*    */       //   302: athrow
/*    */       //   303: new scala/MatchError
/*    */       //   306: dup
/*    */       //   307: aload_2
/*    */       //   308: invokespecial <init> : (Ljava/lang/Object;)V
/*    */       //   311: athrow
/*    */       // Line number table:
/*    */       //   Java source line number -> byte code offset
/*    */       //   #29	-> 0
/*    */       //   #30	-> 6
/*    */       //   #31	-> 27
/*    */       //   #32	-> 42
/*    */       //   #35	-> 66
/*    */       //   #36	-> 136
/*    */       //   #32	-> 151
/*    */       //   #38	-> 158
/*    */       //   #39	-> 173
/*    */       //   #43	-> 197
/*    */       //   #44	-> 267
/*    */       //   #39	-> 282
/*    */       //   #30	-> 286
/*    */       //   #29	-> 290
/*    */       //   #30	-> 293
/*    */       //   #29	-> 303
/*    */       // Local variable table:
/*    */       //   start	length	slot	name	descriptor
/*    */       //   0	312	0	this	Lli/cil/oc/server/network/Component$$anonfun$li$cil$oc$server$network$Component$$hosts$1;
/*    */       //   0	312	1	x0$1	Lscala/Tuple2;
/*    */       //   14	298	3	method	Ljava/lang/String;
/*    */       //   23	289	4	callback	Lli/cil/oc/server/machine/Callbacks$Callback;
/*    */       //   106	206	12	environment	Lli/cil/oc/api/network/ManagedEnvironment;
/*    */       //   237	75	18	environment	Lli/cil/oc/api/network/ManagedEnvironment;
/*    */     }
/*    */     
/*    */     public Component$$anonfun$li$cil$oc$server$network$Component$$hosts$1(Component $outer, CompoundBlockEnvironment x2$2) {}
/*    */     
/*    */     public final class Component$$anonfun$li$cil$oc$server$network$Component$$hosts$1$$anonfun$1 extends AbstractFunction1<Tuple2<String, ManagedEnvironment>, Object> implements Serializable { public static final long serialVersionUID = 0L;
/*    */       private final Callbacks.ComponentCallback x2$1;
/*    */       
/*    */       public final boolean apply(Tuple2 x0$2) {
/*    */         // Byte code:
/*    */         //   0: aload_1
/*    */         //   1: astore_2
/*    */         //   2: aload_2
/*    */         //   3: ifnull -> 61
/*    */         //   6: aload_2
/*    */         //   7: invokevirtual _2 : ()Ljava/lang/Object;
/*    */         //   10: checkcast li/cil/oc/api/network/ManagedEnvironment
/*    */         //   13: astore_3
/*    */         //   14: aload_3
/*    */         //   15: invokevirtual getClass : ()Ljava/lang/Class;
/*    */         //   18: aload_0
/*    */         //   19: getfield x2$1 : Lli/cil/oc/server/machine/Callbacks$ComponentCallback;
/*    */         //   22: invokevirtual method : ()Ljava/lang/reflect/Method;
/*    */         //   25: invokevirtual getDeclaringClass : ()Ljava/lang/Class;
/*    */         //   28: astore #5
/*    */         //   30: dup
/*    */         //   31: ifnonnull -> 43
/*    */         //   34: pop
/*    */         //   35: aload #5
/*    */         //   37: ifnull -> 51
/*    */         //   40: goto -> 55
/*    */         //   43: aload #5
/*    */         //   45: invokevirtual equals : (Ljava/lang/Object;)Z
/*    */         //   48: ifeq -> 55
/*    */         //   51: iconst_1
/*    */         //   52: goto -> 56
/*    */         //   55: iconst_0
/*    */         //   56: istore #4
/*    */         //   58: iload #4
/*    */         //   60: ireturn
/*    */         //   61: new scala/MatchError
/*    */         //   64: dup
/*    */         //   65: aload_2
/*    */         //   66: invokespecial <init> : (Ljava/lang/Object;)V
/*    */         //   69: athrow
/*    */         // Line number table:
/*    */         //   Java source line number -> byte code offset
/*    */         //   #32	-> 0
/*    */         //   #33	-> 6
/*    */         //   #32	-> 58
/*    */         // Local variable table:
/*    */         //   start	length	slot	name	descriptor
/*    */         //   0	70	0	this	Lli/cil/oc/server/network/Component$$anonfun$li$cil$oc$server$network$Component$$hosts$1$$anonfun$1;
/*    */         //   0	70	1	x0$2	Lscala/Tuple2;
/*    */         //   14	56	3	environment	Lli/cil/oc/api/network/ManagedEnvironment;
/*    */       }
/*    */       
/*    */       public Component$$anonfun$li$cil$oc$server$network$Component$$hosts$1$$anonfun$1(Component$$anonfun$li$cil$oc$server$network$Component$$hosts$1 $outer, Callbacks.ComponentCallback x2$1) {} }
/*    */     
/*    */     public final class Component$$anonfun$li$cil$oc$server$network$Component$$hosts$1$$anonfun$2 extends AbstractFunction1<Tuple2<String, ManagedEnvironment>, Object> implements Serializable { public static final long serialVersionUID = 0L;
/*    */       
/*    */       public final boolean apply(Tuple2 x0$3) {
/* 39 */         Tuple2 tuple2 = x0$3; if (tuple2 != null) {
/* 40 */           ManagedEnvironment environment = (ManagedEnvironment)tuple2._2(); if (environment instanceof ManagedPeripheral) { ManagedEnvironment managedEnvironment = environment; return Predef$.MODULE$.refArrayOps((Object[])((ManagedPeripheral)managedEnvironment).methods()).contains(this.x3$1.annotation().value()); }
/*    */         
/*    */         } 
/*    */         return false;
/*    */       } private final Callbacks.PeripheralCallback x3$1;
/*    */       public Component$$anonfun$li$cil$oc$server$network$Component$$hosts$1$$anonfun$2(Component$$anonfun$li$cil$oc$server$network$Component$$hosts$1 $outer, Callbacks.PeripheralCallback x3$1) {} } }
/*    */   public final class Component$$anonfun$li$cil$oc$server$network$Component$$hosts$2 extends AbstractFunction1<Tuple2<String, Callbacks.Callback>, Tuple2<String, Some<Environment>>> implements Serializable { public static final long serialVersionUID = 0L;
/*    */     public final Tuple2<String, Some<Environment>> apply(Tuple2 x0$4) {
/* 48 */       Tuple2 tuple2 = x0$4; if (tuple2 != null) {
/* 49 */         String method = (String)tuple2._1(); return Predef$ArrowAssoc$.MODULE$.$minus$greater$extension(Predef$.MODULE$.ArrowAssoc(method), new Some(this.$outer.host()));
/*    */       } 
/*    */       throw new MatchError(tuple2);
/*    */     }
/*    */ 
/*    */ 
/*    */     
/*    */     public Component$$anonfun$li$cil$oc$server$network$Component$$hosts$2(Component $outer) {} }
/*    */ 
/*    */ 
/*    */   
/*    */   public final class Component$$anonfun$setVisibility$1
/*    */     extends AbstractFunction1<Node, Object>
/*    */     implements Serializable
/*    */   {
/*    */     public static final long serialVersionUID = 0L;
/*    */     
/*    */     private final Set neighborSet$1;
/*    */ 
/*    */     
/*    */     public final boolean apply(Node elem) {
/* 70 */       return this.neighborSet$1.contains(elem);
/*    */     }
/*    */ 
/*    */ 
/*    */ 
/*    */     
/*    */     public Component$$anonfun$setVisibility$1(Component $outer, Set neighborSet$1) {}
/*    */   }
/*    */ 
/*    */ 
/*    */   
/*    */   public final class Component$$anonfun$addTo$1
/*    */     extends AbstractFunction1<Node, BoxedUnit>
/*    */     implements Serializable
/*    */   {
/*    */     public static final long serialVersionUID = 0L;
/*    */ 
/*    */ 
/*    */     
/*    */     public final void apply(Node x$1) {
/* 90 */       Environment environment = x$1.host();
/* 91 */       if (environment instanceof Machine) { Machine machine = (Machine)environment; machine.addComponent(this.$outer); BoxedUnit boxedUnit = BoxedUnit.UNIT; }
/* 92 */       else { BoxedUnit boxedUnit = BoxedUnit.UNIT; }
/*    */     
/*    */     } public Component$$anonfun$addTo$1(Component $outer) {} } public final class Component$$anonfun$removeFrom$1 extends AbstractFunction1<Node, BoxedUnit> implements Serializable { public static final long serialVersionUID = 0L; public final void apply(Node x$2) {
/* 95 */       Environment environment = x$2.host();
/* 96 */       if (environment instanceof Machine) { Machine machine = (Machine)environment; machine.removeComponent(this.$outer); BoxedUnit boxedUnit = BoxedUnit.UNIT; }
/* 97 */       else { BoxedUnit boxedUnit = BoxedUnit.UNIT; }
/*    */     
/*    */     }
/*    */     
/*    */     public Component$$anonfun$removeFrom$1(Component $outer) {} }
/*    */    }


/* Location:              C:\Users\shame\AppData\Roaming\PrismLauncher\instances\GT_New_Horizons_2.7.4_Java_17-21\.minecraft\mods\OpenComputers-1.10.30-GTNH.jar!\li\cil\oc\server\network\Component.class
 * Java compiler version: 8 (52.0)
 * JD-Core Version:       1.1.3
 */