/*     */ package li.cil.oc.client.gui;@ScalaSignature(bytes = "\006\001\t%d\001B\001\003\0015\021AAU1dW*\0211\001B\001\004OVL'BA\003\007\003\031\031G.[3oi*\021q\001C\001\003_\016T!!\003\006\002\007\rLGNC\001\f\003\ta\027n\001\001\024\005\001q\001cA\b\021%5\t!!\003\002\022\005\t\031B)\0378b[&\034w)^5D_:$\030-\0338feB\0211\003G\007\002))\021QCF\001\nG>tG/Y5oKJT!a\006\004\002\r\r|W.\\8o\023\t\tA\003\003\005\033\001\t\005\t\025!\003\034\003=\001H.Y=fe&sg/\0328u_JL\bC\001\017&\033\005i\"B\001\020 \003\031\001H.Y=fe*\021\001%I\001\007K:$\030\016^=\013\005\t\032\023!C7j]\026\034'/\0314u\025\005!\023a\0018fi&\021a%\b\002\020\023:4XM\034;pef\004F.Y=fe\"A\001\006\001BC\002\023\005\021&\001\003sC\016\\W#\001\026\021\005-rS\"\001\027\013\00552\022A\003;jY\026,g\016^5us&\021\021\001\f\005\ta\001\021\t\021)A\005U\005)!/Y2lA!)!\007\001C\001g\0051A(\0338jiz\"2\001N\0337!\ty\001\001C\003\033c\001\0071\004C\003)c\001\007!\006C\0049\001\t\007IQA\035\002#\t,8/T1ti\026\024(\t\\1oWV36/F\001;!\031Yd\b\021!A\0016\tAHC\001>\003\025\0318-\0317b\023\tyDH\001\004UkBdW\r\016\t\003w\005K!A\021\037\003\007%sG\017\003\004E\001\001\006iAO\001\023EV\034X*Y:uKJ\024E.\0318l+Z\033\b\005C\004G\001\t\007IQA\035\002'\t,8/T1ti\026\024\bK]3tK:$XKV:\t\r!\003\001\025!\004;\003Q\021Wo]'bgR,'\017\025:fg\026tG/\026,tA!9!\n\001b\001\n\013I\024\001\0052vgNc\027M^3CY\006t7.\026,t\021\031a\005\001)A\007u\005\t\"-^:TY\0064XM\0217b].,fk\035\021\t\0179\003!\031!C\003s\005\021\"-^:TY\0064X\r\025:fg\026tG/\026,t\021\031\001\006\001)A\007u\005\031\"-^:TY\0064X\r\025:fg\026tG/\026,tA!9!\013\001b\001\n\013I\024AE2p]:,7\r^8s\033\006\034H/\032:V-NDa\001\026\001!\002\033Q\024aE2p]:,7\r^8s\033\006\034H/\032:V-N\004\003b\002,\001\005\004%)!O\001\022G>tg.Z2u_J\034F.\031<f+Z\033\bB\002-\001A\0035!(\001\nd_:tWm\031;peNc\027M^3V-N\004\003b\002.\001\005\004%)aW\001\020Q>4XM]'bgR,'oU5{KV\tA\f\005\003<;\002\003\025B\0010=\005\031!V\017\0357fe!1\001\r\001Q\001\016q\013\001\003[8wKJl\025m\035;feNK'0\032\021\t\017\t\004!\031!C\0037\006q\001n\034<feNc\027M^3TSj,\007B\0023\001A\0035A,A\bi_Z,'o\0257bm\026\034\026N_3!\021\0351\007A1A\005\006\035\fQb^5sK6\0137\017^3s+Z\033X#\0015\021\007mJ'(\003\002ky\t)\021I\035:bs\"1A\016\001Q\001\016!\fab^5sK6\0137\017^3s+Z\033\b\005C\004o\001\t\007IQA4\002\031]L'/Z*mCZ,WKV:\t\rA\004\001\025!\004i\00359\030N]3TY\0064X-\026,tA!9!\017\001b\001\n\013\031\030\001\0032vgN#\030M\035;\026\003Q\0042aO5]\021\0311\b\001)A\007i\006I!-^:Ti\006\024H\017\t\005\bq\002\021\r\021\"\002z\003\031\021Wo]$baV\t!pD\001|;\005\031\001BB?\001A\0035!0A\004ckN<\025\r\035\021\t\017}\004!\031!C\003g\006q1m\0348oK\016$xN]*uCJ$\bbBA\002\001\001\006i\001^\001\020G>tg.Z2u_J\034F/\031:uA!I\021q\001\001C\002\023\025\021\021B\001\rG>tg.Z2u_J<\025\r]\013\003\003\027y!!!\004\036\003\tA\001\"!\005\001A\0035\0211B\001\016G>tg.Z2u_J<\025\r\035\021\t\021\005U\001A1A\005\006e\nAB]3mCflu\016Z3V-NDq!!\007\001A\0035!(A\007sK2\f\0270T8eKV36\017\t\005\t\003;\001!\031!C\003g\006Iq/\033:f%\026d\027-\037\005\b\003C\001\001\025!\004u\003)9\030N]3SK2\f\027\020\t\005\n\003K\001!\031!C\003\003O\t\021BY;t)>\034\026\016Z3\026\005\005%\002\003B\036j\003W\001B!!\f\002:5\021\021q\006\006\005\003c\t\031$\001\003vi&d'bA\f\0026)\031\021qG\022\002\0355Lg.Z2sC\032$hm\034:hK&!\0211HA\030\00591uN]4f\t&\024Xm\031;j_:D\001\"a\020\001A\0035\021\021F\001\013EV\034Hk\\*jI\026\004\003\"CA\"\001\t\007IQAA#\003%\031\030\016Z3U_\n+8/\006\002\002HA9\021\021JA*\003W\001UBAA&\025\021\ti%a\024\002\023%lW.\036;bE2,'bAA)y\005Q1m\0347mK\016$\030n\0348\n\t\005U\0231\n\002\004\033\006\004\b\002CA-\001\001\006i!a\022\002\025MLG-\032+p\005V\034\b\005C\006\002^\001\001\r\0211A\005\002\005}\023a\003:fY\006L()\036;u_:,\"!!\031\021\007=\t\031'C\002\002f\t\0211\"S7bO\026\024U\017\036;p]\"Y\021\021\016\001A\002\003\007I\021AA6\003=\021X\r\\1z\005V$Ho\0348`I\025\fH\003BA7\003g\0022aOA8\023\r\t\t\b\020\002\005+:LG\017\003\006\002v\005\035\024\021!a\001\003C\n1\001\037\0232\021!\tI\b\001Q!\n\005\005\024\001\004:fY\006L()\036;u_:\004\003\"CA?\001\001\007I\021AA@\003-9\030N]3CkR$xN\\:\026\005\005\005\005\003B\036j\003\007\003BaO5\002\006B!1([A1\021%\tI\t\001a\001\n\003\tY)A\bxSJ,')\036;u_:\034x\fJ3r)\021\ti'!$\t\025\005U\024qQA\001\002\004\t\t\t\003\005\002\022\002\001\013\025BAA\00319\030N]3CkR$xN\\:!\021\035\t)\n\001C\001\003/\013\001b]5eK:\013W.\032\013\005\0033\0139\013\005\003\002\034\006\005fbA\036\002\036&\031\021q\024\037\002\rA\023X\rZ3g\023\021\t\031+!*\003\rM#(/\0338h\025\r\ty\n\020\005\t\003S\013\031\n1\001\002,\005!1/\0333f\021\035\ti\013\001C\001\003_\013a\"\0328d_\022,')\036;u_:LE\rF\004A\003c\013),!/\t\017\005M\0261\026a\001\001\006IQn\\;oi\006\024G.\032\005\b\003o\013Y\0131\001A\003-\031wN\0348fGR\f'\r\\3\t\017\005m\0261\026a\001\001\006\031!-^:\t\017\005}\006\001\"\001\002B\006qA-Z2pI\026\024U\017\036;p]&#G\003BAb\003\023\004baOAc\001\002\003\025bAAdy\t1A+\0369mKNBq!a3\002>\002\007\001)\001\005ckR$xN\\%e\021\035\ty\r\001C)\003#\fq\"Y2uS>t\007+\032:g_JlW\r\032\013\005\003[\n\031\016\003\005\002V\0065\007\031AAl\003\031\021W\017\036;p]B!\021\021\\Ap\033\t\tYNC\002\004\003;T!!B\021\n\t\005\005\0301\034\002\n\017VL')\036;u_:Dq!!:\001\t\003\n9/\001\006ee\006<8k\031:fK:$\002\"!\034\002j\0065\030\021\037\005\b\003W\f\031\0171\001A\003\031iw.^:f1\"9\021q^Ar\001\004\001\025AB7pkN,\027\f\003\005\002t\006\r\b\031AA{\003\t!G\017E\002<\003oL1!!?=\005\0251En\\1u\021\035\ti\020\001C!\003\fq!\0338ji\036+\030\016\006\002\002n!9!1\001\001\005B\t\025\021\001\b3sC^\034VmY8oI\006\024\030PR8sK\036\024x.\0368e\031\006LXM\035\013\007\003[\0229A!\003\t\017\005-(\021\001a\001\001\"9\021q\036B\001\001\004\001\005b\002B\007\001\021\005\023q`\001\035IJ\fwoU3d_:$\027M]=CC\016\\wM]8v]\022d\025-_3s\021\035\021\t\002\001C\005\005'\t\001\002\032:boJ+7\r\036\013\017\003[\022)B!\007\003\036\t\005\"Q\005B\025\021\035\0219Ba\004A\002\001\013\021\001\037\005\b\0057\021y\0011\001A\003\005I\bb\002B\020\005\037\001\r\001Q\001\002o\"9!1\005B\b\001\004\001\025!\0015\t\017\t\035\"q\002a\001\001\006\tQ\017C\004\003,\t=\001\031\001!\002\003YDABa\f\001!\003\005\t\021!C\001\005c\tA\003\035:pi\026\034G/\0323%EV$Ho\0348MSN$H\003\002B\032\0053\002DA!\016\003HA1!q\007B \005\007j!A!\017\013\t\005E\"1\b\006\003\005{\tAA[1wC&!!\021\tB\035\005\021a\025n\035;\021\t\t\025#q\t\007\001\t1\021IE!\f\002\002\003\005)\021\001B&\005\ty\004'\005\003\003N\tM\003cA\036\003P%\031!\021\013\037\003\0179{G\017[5oOB\0311H!\026\n\007\t]CHA\002B]fD\021\"!\036\003.\005\005\t\031\001\033\t\031\tu\003\001%A\001\002\003%\tAa\030\0023A\024x\016^3di\026$GEZ8oiJ+g\016Z3sKJ|%M\033\013\005\005C\0229\007\005\003\002Z\n\r\024\002\002B3\0037\024ABR8oiJ+g\016Z3sKJD\021\"!\036\003\\\005\005\t\031\001\033")
/*     */ public class Rack extends DynamicGuiContainer<Rack> { private final li.cil.oc.common.tileentity.Rack rack; private final Tuple4<Object, Object, Object, Object> busMasterBlankUVs; private final Tuple4<Object, Object, Object, Object> busMasterPresentUVs; private final Tuple4<Object, Object, Object, Object> busSlaveBlankUVs; private final Tuple4<Object, Object, Object, Object> busSlavePresentUVs; private final Tuple4<Object, Object, Object, Object> connectorMasterUVs; private final Tuple4<Object, Object, Object, Object> connectorSlaveUVs; private final Tuple2<Object, Object> hoverMasterSize; private final Tuple2<Object, Object> hoverSlaveSize;
/*     */   private final Tuple4<Object, Object, Object, Object>[] wireMasterUVs;
/*     */   private final Tuple4<Object, Object, Object, Object>[] wireSlaveUVs;
/*     */   private final Tuple2<Object, Object>[] busStart;
/*     */   private final int busGap;
/*     */   private final Tuple2<Object, Object>[] connectorStart;
/*     */   private final int connectorGap;
/*     */   private final Tuple4<Object, Object, Object, Object> relayModeUVs;
/*     */   private final Tuple2<Object, Object>[] wireRelay;
/*     */   private final ForgeDirection[] busToSide;
/*     */   private final Map<ForgeDirection, Object> sideToBus;
/*     */   private ImageButton relayButton;
/*     */   private ImageButton[][][] wireButtons;
/*     */   
/*  16 */   public li.cil.oc.common.tileentity.Rack rack() { return this.rack; } public Rack(InventoryPlayer playerInventory, li.cil.oc.common.tileentity.Rack rack) { super(new Rack(playerInventory, rack));
/*  17 */     this.field_147000_g = 210;
/*     */     
/*  19 */     this.busMasterBlankUVs = new Tuple4(BoxesRunTime.boxToInteger(195), BoxesRunTime.boxToInteger(14), BoxesRunTime.boxToInteger(3), BoxesRunTime.boxToInteger(5));
/*  20 */     this.busMasterPresentUVs = new Tuple4(BoxesRunTime.boxToInteger(194), BoxesRunTime.boxToInteger(20), BoxesRunTime.boxToInteger(5), BoxesRunTime.boxToInteger(5));
/*  21 */     this.busSlaveBlankUVs = new Tuple4(BoxesRunTime.boxToInteger(195), BoxesRunTime.boxToInteger(1), BoxesRunTime.boxToInteger(3), BoxesRunTime.boxToInteger(4));
/*  22 */     this.busSlavePresentUVs = new Tuple4(BoxesRunTime.boxToInteger(194), BoxesRunTime.boxToInteger(6), BoxesRunTime.boxToInteger(5), BoxesRunTime.boxToInteger(4));
/*     */     
/*  24 */     this.connectorMasterUVs = new Tuple4(BoxesRunTime.boxToInteger(194), BoxesRunTime.boxToInteger(26), BoxesRunTime.boxToInteger(1), BoxesRunTime.boxToInteger(3));
/*  25 */     this.connectorSlaveUVs = new Tuple4(BoxesRunTime.boxToInteger(194), BoxesRunTime.boxToInteger(11), BoxesRunTime.boxToInteger(1), BoxesRunTime.boxToInteger(2));
/*     */     
/*  27 */     this.hoverMasterSize = (Tuple2<Object, Object>)new Tuple2.mcII.sp(3, 3);
/*  28 */     this.hoverSlaveSize = (Tuple2<Object, Object>)new Tuple2.mcII.sp(3, 2);
/*     */     
/*  30 */     (new Tuple4[5])[0] = 
/*  31 */       new Tuple4(BoxesRunTime.boxToInteger(186), BoxesRunTime.boxToInteger(16), BoxesRunTime.boxToInteger(6), BoxesRunTime.boxToInteger(3));
/*  32 */     (new Tuple4[5])[1] = new Tuple4(BoxesRunTime.boxToInteger(186), BoxesRunTime.boxToInteger(20), BoxesRunTime.boxToInteger(6), BoxesRunTime.boxToInteger(3));
/*  33 */     (new Tuple4[5])[2] = new Tuple4(BoxesRunTime.boxToInteger(186), BoxesRunTime.boxToInteger(24), BoxesRunTime.boxToInteger(6), BoxesRunTime.boxToInteger(3));
/*  34 */     (new Tuple4[5])[3] = new Tuple4(BoxesRunTime.boxToInteger(186), BoxesRunTime.boxToInteger(28), BoxesRunTime.boxToInteger(6), BoxesRunTime.boxToInteger(3));
/*  35 */     (new Tuple4[5])[4] = new Tuple4(BoxesRunTime.boxToInteger(186), BoxesRunTime.boxToInteger(32), BoxesRunTime.boxToInteger(6), BoxesRunTime.boxToInteger(3));
/*     */     this.wireMasterUVs = (Tuple4<Object, Object, Object, Object>[])new Tuple4[5];
/*  37 */     (new Tuple4[5])[0] = 
/*  38 */       new Tuple4(BoxesRunTime.boxToInteger(186), BoxesRunTime.boxToInteger(1), BoxesRunTime.boxToInteger(6), BoxesRunTime.boxToInteger(2));
/*  39 */     (new Tuple4[5])[1] = new Tuple4(BoxesRunTime.boxToInteger(186), BoxesRunTime.boxToInteger(4), BoxesRunTime.boxToInteger(6), BoxesRunTime.boxToInteger(2));
/*  40 */     (new Tuple4[5])[2] = new Tuple4(BoxesRunTime.boxToInteger(186), BoxesRunTime.boxToInteger(7), BoxesRunTime.boxToInteger(6), BoxesRunTime.boxToInteger(2));
/*  41 */     (new Tuple4[5])[3] = new Tuple4(BoxesRunTime.boxToInteger(186), BoxesRunTime.boxToInteger(10), BoxesRunTime.boxToInteger(6), BoxesRunTime.boxToInteger(2));
/*  42 */     (new Tuple4[5])[4] = new Tuple4(BoxesRunTime.boxToInteger(186), BoxesRunTime.boxToInteger(13), BoxesRunTime.boxToInteger(6), BoxesRunTime.boxToInteger(2));
/*     */     
/*     */     this.wireSlaveUVs = (Tuple4<Object, Object, Object, Object>[])new Tuple4[5];
/*  45 */     (new Tuple2[5])[0] = 
/*  46 */       (Tuple2)new Tuple2.mcII.sp(45, 22);
/*  47 */     (new Tuple2[5])[1] = (Tuple2)new Tuple2.mcII.sp(56, 22);
/*  48 */     (new Tuple2[5])[2] = (Tuple2)new Tuple2.mcII.sp(67, 22);
/*  49 */     (new Tuple2[5])[3] = (Tuple2)new Tuple2.mcII.sp(78, 22);
/*  50 */     (new Tuple2[5])[4] = (Tuple2)new Tuple2.mcII.sp(89, 22);
/*     */ 
/*     */     
/*     */     this.busStart = (Tuple2<Object, Object>[])new Tuple2[5];
/*     */     
/*  55 */     (new Tuple2[4])[0] = 
/*  56 */       (Tuple2)new Tuple2.mcII.sp(37, 23);
/*  57 */     (new Tuple2[4])[1] = (Tuple2)new Tuple2.mcII.sp(37, 43);
/*  58 */     (new Tuple2[4])[2] = (Tuple2)new Tuple2.mcII.sp(37, 63);
/*  59 */     (new Tuple2[4])[3] = (Tuple2)new Tuple2.mcII.sp(37, 83);
/*     */ 
/*     */     
/*     */     this.connectorStart = (Tuple2<Object, Object>[])new Tuple2[4];
/*     */     
/*  64 */     this.relayModeUVs = new Tuple4(BoxesRunTime.boxToInteger(195), BoxesRunTime.boxToInteger(30), BoxesRunTime.boxToInteger(4), BoxesRunTime.boxToInteger(2));
/*     */     
/*  66 */     (new Tuple2[4])[0] = 
/*  67 */       (Tuple2)new Tuple2.mcII.sp(50, 104);
/*  68 */     (new Tuple2[4])[1] = (Tuple2)new Tuple2.mcII.sp(61, 104);
/*  69 */     (new Tuple2[4])[2] = (Tuple2)new Tuple2.mcII.sp(72, 104);
/*  70 */     (new Tuple2[4])[3] = (Tuple2)new Tuple2.mcII.sp(83, 104);
/*     */     
/*     */     this.wireRelay = (Tuple2<Object, Object>[])new Tuple2[4];
/*  73 */     this.busToSide = (ForgeDirection[])Predef$.MODULE$.refArrayOps((Object[])ForgeDirection.VALID_DIRECTIONS).filter((Function1)new Rack$$anonfun$1(this));
/*  74 */     this.sideToBus = Predef$.MODULE$.refArrayOps((Object[])Predef$.MODULE$.refArrayOps((Object[])busToSide()).zipWithIndex(Array$.MODULE$.canBuildFrom(ClassTag$.MODULE$.apply(Tuple2.class)))).toMap(Predef$.MODULE$.$conforms());
/*     */ 
/*     */ 
/*     */ 
/*     */     
/*  79 */     this.wireButtons = (ImageButton[][][])Array$.MODULE$.fill(rack.func_70302_i_(), (Function0)new Rack$$anonfun$2(this), ClassTag$.MODULE$.apply(ScalaRunTime$.MODULE$.arrayClass(ScalaRunTime$.MODULE$.arrayClass(ImageButton.class)))); } public final Tuple4<Object, Object, Object, Object> busMasterBlankUVs() { return this.busMasterBlankUVs; } public final Tuple4<Object, Object, Object, Object> busMasterPresentUVs() { return this.busMasterPresentUVs; } public final Tuple4<Object, Object, Object, Object> busSlaveBlankUVs() { return this.busSlaveBlankUVs; } public final Tuple4<Object, Object, Object, Object> busSlavePresentUVs() { return this.busSlavePresentUVs; } public final Tuple4<Object, Object, Object, Object> connectorMasterUVs() { return this.connectorMasterUVs; } public final Tuple4<Object, Object, Object, Object> connectorSlaveUVs() { return this.connectorSlaveUVs; } public final Tuple2<Object, Object> hoverMasterSize() { return this.hoverMasterSize; } public final Tuple2<Object, Object> hoverSlaveSize() { return this.hoverSlaveSize; } public final Tuple4<Object, Object, Object, Object>[] wireMasterUVs() { return this.wireMasterUVs; } public final Tuple4<Object, Object, Object, Object>[] wireSlaveUVs() { return this.wireSlaveUVs; } public ImageButton[][][] wireButtons() { return this.wireButtons; } public final Tuple2<Object, Object>[] busStart() { return this.busStart; } public final int busGap() { return 3; } public final Tuple2<Object, Object>[] connectorStart() { return this.connectorStart; } public final int connectorGap() { return 2; } public final Tuple4<Object, Object, Object, Object> relayModeUVs() { return this.relayModeUVs; } public final Tuple2<Object, Object>[] wireRelay() { return this.wireRelay; } public final ForgeDirection[] busToSide() { return this.busToSide; } public final class Rack$$anonfun$1 extends AbstractFunction1<ForgeDirection, Object> implements Serializable { public static final long serialVersionUID = 0L; public final boolean apply(ForgeDirection x$1) { ForgeDirection forgeDirection = ForgeDirection.SOUTH; if (x$1 == null) { if (forgeDirection != null); } else if (x$1.equals(forgeDirection)) {  }  } public Rack$$anonfun$1(Rack $outer) {} } public final Map<ForgeDirection, Object> sideToBus() { return this.sideToBus; } public ImageButton relayButton() { return this.relayButton; } public void relayButton_$eq(ImageButton x$1) { this.relayButton = x$1; } public void wireButtons_$eq(ImageButton[][][] x$1) { this.wireButtons = x$1; } public final class Rack$$anonfun$2 extends AbstractFunction0<ImageButton[][]> implements Serializable { public static final long serialVersionUID = 0L; public final ImageButton[][] apply() { return (ImageButton[][])Array$.MODULE$.fill(4, (Function0)new Rack$$anonfun$2$$anonfun$apply$1(this), ClassTag$.MODULE$.apply(ScalaRunTime$.MODULE$.arrayClass(ImageButton.class))); } public Rack$$anonfun$2(Rack $outer) {} public final class Rack$$anonfun$2$$anonfun$apply$1 extends AbstractFunction0<ImageButton[]> implements Serializable { public static final long serialVersionUID = 0L; public final ImageButton[] apply() { return (ImageButton[])Array$.MODULE$.fill(5, (Function0)new Rack$$anonfun$2$$anonfun$apply$1$$anonfun$apply$2(this), ClassTag$.MODULE$.apply(ImageButton.class)); } public Rack$$anonfun$2$$anonfun$apply$1(Rack$$anonfun$2 $outer) {} public final class Rack$$anonfun$2$$anonfun$apply$1$$anonfun$apply$2 extends AbstractFunction0<ImageButton> implements Serializable { public static final long serialVersionUID = 0L; public final ImageButton apply() { return null; } public Rack$$anonfun$2$$anonfun$apply$1$$anonfun$apply$2(Rack$$anonfun$2$$anonfun$apply$1 $outer) {} } } } public String sideName(ForgeDirection side) {
/*     */     String str;
/*  81 */     ForgeDirection forgeDirection = side;
/*  82 */     if (ForgeDirection.UP.equals(forgeDirection)) { str = Localization$Rack$.MODULE$.Top(); }
/*  83 */     else if (ForgeDirection.DOWN.equals(forgeDirection)) { str = Localization$Rack$.MODULE$.Bottom(); }
/*  84 */     else if (ForgeDirection.EAST.equals(forgeDirection)) { str = Localization$Rack$.MODULE$.Left(); }
/*  85 */     else if (ForgeDirection.WEST.equals(forgeDirection)) { str = Localization$Rack$.MODULE$.Right(); }
/*  86 */     else if (ForgeDirection.NORTH.equals(forgeDirection)) { str = Localization$Rack$.MODULE$.Back(); }
/*  87 */     else { str = Localization$Rack$.MODULE$.None(); }
/*     */     
/*     */     return str;
/*     */   }
/*     */   public int encodeButtonId(int mountable, int connectable, int bus) {
/*  92 */     return 1 + mountable * 4 * 5 + connectable * 5 + bus;
/*     */   }
/*     */ 
/*     */   
/*     */   public Tuple3<Object, Object, Object> decodeButtonId(int buttonId) {
/*  97 */     int bus = (buttonId - 1) % 5;
/*  98 */     int connectable = (buttonId - 1) / 5 % 4;
/*  99 */     int mountable = (buttonId - 1) / 5 / 4;
/* 100 */     return new Tuple3(BoxesRunTime.boxToInteger(mountable), BoxesRunTime.boxToInteger(connectable), BoxesRunTime.boxToInteger(bus));
/*     */   }
/*     */   
/*     */   public void func_146284_a(GuiButton button) {
/* 104 */     if (button.field_146127_k == 0) {
/* 105 */       PacketSender$.MODULE$.sendRackRelayState(rack(), !rack().isRelayEnabled());
/*     */     } else {
/*     */       
/* 108 */       Tuple3<Object, Object, Object> tuple3 = decodeButtonId(button.field_146127_k); if (tuple3 != null) { int mountable = BoxesRunTime.unboxToInt(tuple3._1()), connectable = BoxesRunTime.unboxToInt(tuple3._2()), bus = BoxesRunTime.unboxToInt(tuple3._3()); Tuple3 tuple32 = new Tuple3(BoxesRunTime.boxToInteger(mountable), BoxesRunTime.boxToInteger(connectable), BoxesRunTime.boxToInteger(bus)), tuple31 = tuple32; int i = BoxesRunTime.unboxToInt(tuple31._1()), j = BoxesRunTime.unboxToInt(tuple31._2()), k = BoxesRunTime.unboxToInt(tuple31._3());
/* 109 */         if (rack().nodeMapping()[i][j].contains(busToSide()[k])) {
/* 110 */           PacketSender$.MODULE$.sendRackMountableMapping(rack(), i, j, (Option)None$.MODULE$);
/*     */         } else {
/*     */           
/* 113 */           PacketSender$.MODULE$.sendRackMountableMapping(rack(), i, j, Option$.MODULE$.apply(busToSide()[k]));
/*     */         } 
/*     */         return; }
/*     */       
/*     */       throw new MatchError(tuple3);
/*     */     } 
/* 119 */   } public void func_73863_a(int mouseX, int mouseY, float dt) { RichInt$.MODULE$.until$extension0(Predef$.MODULE$.intWrapper(0), 5).foreach$mVc$sp((Function1)new Rack$$anonfun$drawScreen$1(this));
/*     */ 
/*     */ 
/*     */ 
/*     */ 
/*     */ 
/*     */ 
/*     */     
/* 127 */     (relayButton()).field_146126_j = rack().isRelayEnabled() ? Localization$Rack$.MODULE$.RelayEnabled() : Localization$Rack$.MODULE$.RelayDisabled();
/* 128 */     super.func_73863_a(mouseX, mouseY, dt); } public final class Rack$$anonfun$drawScreen$1 extends AbstractFunction1.mcVI.sp implements Serializable {
/*     */     public static final long serialVersionUID = 0L; public final void apply(int bus) { apply$mcVI$sp(bus); } public Rack$$anonfun$drawScreen$1(Rack $outer) {} public void apply$mcVI$sp(int bus) { RichInt$.MODULE$.until$extension0(Predef$.MODULE$.intWrapper(0), this.$outer.rack().func_70302_i_()).foreach$mVc$sp((Function1)new Rack$$anonfun$drawScreen$1$$anonfun$apply$mcVI$sp$1(this, bus)); } public final class Rack$$anonfun$drawScreen$1$$anonfun$apply$mcVI$sp$1 extends AbstractFunction1.mcVI.sp implements Serializable {
/*     */       public static final long serialVersionUID = 0L; public final int bus$1; public final void apply(int mountable) { apply$mcVI$sp(mountable); } public Rack$$anonfun$drawScreen$1$$anonfun$apply$mcVI$sp$1(Rack$$anonfun$drawScreen$1 $outer, int bus$1) {} public void apply$mcVI$sp(int mountable) { boolean[] presence = this.$outer.li$cil$oc$client$gui$Rack$$anonfun$$$outer().inventoryContainer().nodePresence()[mountable]; RichInt$.MODULE$.until$extension0(Predef$.MODULE$.intWrapper(0), 4).foreach$mVc$sp((Function1)new Rack$$anonfun$drawScreen$1$$anonfun$apply$mcVI$sp$1$$anonfun$apply$mcVI$sp$2(this, presence, mountable)); } public final class Rack$$anonfun$drawScreen$1$$anonfun$apply$mcVI$sp$1$$anonfun$apply$mcVI$sp$2 extends AbstractFunction1.mcVI.sp implements Serializable {
/*     */         public static final long serialVersionUID = 0L; private final boolean[] presence$1; private final int mountable$1; public final void apply(int connectable) { apply$mcVI$sp(connectable); } public Rack$$anonfun$drawScreen$1$$anonfun$apply$mcVI$sp$1$$anonfun$apply$mcVI$sp$2(Rack$$anonfun$drawScreen$1$$anonfun$apply$mcVI$sp$1 $outer, boolean[] presence$1, int mountable$1) {} public void apply$mcVI$sp(int connectable) { (this.$outer.li$cil$oc$client$gui$Rack$$anonfun$$anonfun$$$outer().li$cil$oc$client$gui$Rack$$anonfun$$$outer().wireButtons()[this.mountable$1][connectable][this.$outer.bus$1]).field_146125_m = this.presence$1[connectable]; } } } }
/* 132 */   public void func_73866_w_() { super.func_73866_w_();
/*     */     
/* 134 */     int x$18 = 0, x$19 = this.field_147003_i + 101, x$20 = this.field_147009_r + 96, x$21 = 65, x$22 = 18; ResourceLocation x$23 = Textures$.MODULE$.guiButtonRelay(); String x$24 = Localization$Rack$.MODULE$.RelayDisabled(); int x$25 = 18; boolean x$26 = ImageButton$.MODULE$.$lessinit$greater$default$8(); int x$27 = ImageButton$.MODULE$.$lessinit$greater$default$9(), x$28 = ImageButton$.MODULE$.$lessinit$greater$default$10(), x$29 = ImageButton$.MODULE$.$lessinit$greater$default$11(); relayButton_$eq(new ImageButton(x$18, x$19, x$20, x$21, x$22, x$23, x$24, x$26, x$27, x$28, x$29, x$25));
/* 135 */     add(this.field_146292_n, relayButton());
/*     */     
/* 137 */     Tuple2<Object, Object> tuple2 = hoverMasterSize(); if (tuple2 != null) { int mw = tuple2._1$mcI$sp(), mh = tuple2._2$mcI$sp(); Tuple2.mcII.sp sp2 = new Tuple2.mcII.sp(mw, mh), sp1 = sp2; int i = sp1._1$mcI$sp(), j = sp1._2$mcI$sp();
/* 138 */       Tuple2<Object, Object> tuple21 = hoverSlaveSize(); if (tuple21 != null) { int sw = tuple21._1$mcI$sp(), sh = tuple21._2$mcI$sp(); Tuple2.mcII.sp sp4 = new Tuple2.mcII.sp(sw, sh), sp3 = sp4; int k = sp3._1$mcI$sp(), m = sp3._2$mcI$sp();
/* 139 */         Tuple4<Object, Object, Object, Object> tuple4 = busMasterBlankUVs(); if (tuple4 != null) { int n = BoxesRunTime.unboxToInt(tuple4._4()), i1 = n, mbh = i1;
/* 140 */           Tuple4<Object, Object, Object, Object> tuple41 = busSlaveBlankUVs(); if (tuple41 != null) { int i2 = BoxesRunTime.unboxToInt(tuple41._4()), i3 = i2, sbh = i3; RichInt$.MODULE$
/* 141 */               .until$extension0(Predef$.MODULE$.intWrapper(0), 5).foreach$mVc$sp((Function1)new Rack$$anonfun$initGui$1(this, i, j, k, m, mbh, sbh)); return; }  throw new MatchError(tuple41); }  throw new MatchError(tuple4); }  throw new MatchError(tuple21); }  throw new MatchError(tuple2); } public final class Rack$$anonfun$initGui$1 extends AbstractFunction1.mcVI.sp implements Serializable { public static final long serialVersionUID = 0L; public final int mw$1; public final int mh$1; public final int sw$1; public final int sh$1; public final int mbh$1; public final int sbh$1; public final void apply(int bus) { apply$mcVI$sp(bus); } public Rack$$anonfun$initGui$1(Rack $outer, int mw$1, int mh$1, int sw$1, int sh$1, int mbh$1, int sbh$1) {}
/* 142 */     public void apply$mcVI$sp(int bus) { RichInt$.MODULE$.until$extension0(Predef$.MODULE$.intWrapper(0), this.$outer.rack().func_70302_i_()).foreach$mVc$sp((Function1)new Rack$$anonfun$initGui$1$$anonfun$apply$mcVI$sp$3(this, bus)); } public final class Rack$$anonfun$initGui$1$$anonfun$apply$mcVI$sp$3 extends AbstractFunction1.mcVI.sp implements Serializable { public static final long serialVersionUID = 0L; public final int bus$2; public final void apply(int mountable) { apply$mcVI$sp(mountable); } public Rack$$anonfun$initGui$1$$anonfun$apply$mcVI$sp$3(Rack$$anonfun$initGui$1 $outer, int bus$2) {}
/* 143 */       public void apply$mcVI$sp(int mountable) { int offset = mountable * (this.$outer.mbh$1 + this.$outer.sbh$1 * 3 + 3);
/* 144 */         Tuple2<Object, Object> tuple2 = this.$outer.li$cil$oc$client$gui$Rack$$anonfun$$$outer().busStart()[this.bus$2]; if (tuple2 != null) { int bx = tuple2._1$mcI$sp(), by = tuple2._2$mcI$sp(); Tuple2.mcII.sp sp2 = new Tuple2.mcII.sp(bx, by), sp1 = sp2; int i = sp1._1$mcI$sp(), j = sp1._2$mcI$sp();
/*     */ 
/*     */           
/* 147 */           ImageButton button = new ImageButton(this.$outer.li$cil$oc$client$gui$Rack$$anonfun$$$outer().encodeButtonId(mountable, 0, this.bus$2), (this.$outer.li$cil$oc$client$gui$Rack$$anonfun$$$outer()).field_147003_i + i, (this.$outer.li$cil$oc$client$gui$Rack$$anonfun$$$outer()).field_147009_r + j + offset + 1, this.$outer.mw$1, this.$outer.mh$1, ImageButton$.MODULE$.$lessinit$greater$default$6(), ImageButton$.MODULE$.$lessinit$greater$default$7(), ImageButton$.MODULE$.$lessinit$greater$default$8(), ImageButton$.MODULE$.$lessinit$greater$default$9(), ImageButton$.MODULE$.$lessinit$greater$default$10(), ImageButton$.MODULE$.$lessinit$greater$default$11(), ImageButton$.MODULE$.$lessinit$greater$default$12());
/* 148 */           this.$outer.li$cil$oc$client$gui$Rack$$anonfun$$$outer().add(this.$outer.li$cil$oc$client$gui$Rack$$anonfun$$$outer().protected$buttonList(this.$outer.li$cil$oc$client$gui$Rack$$anonfun$$$outer()), button);
/* 149 */           this.$outer.li$cil$oc$client$gui$Rack$$anonfun$$$outer().wireButtons()[mountable][0][this.bus$2] = button; RichInt$.MODULE$
/*     */ 
/*     */             
/* 152 */             .until$extension0(Predef$.MODULE$.intWrapper(0), 3).foreach$mVc$sp((Function1)new Rack$$anonfun$initGui$1$$anonfun$apply$mcVI$sp$3$$anonfun$apply$mcVI$sp$4(this, offset, i, j, mountable)); return; }  throw new MatchError(tuple2); } public final class Rack$$anonfun$initGui$1$$anonfun$apply$mcVI$sp$3$$anonfun$apply$mcVI$sp$4 extends AbstractFunction1.mcVI.sp implements Serializable { public static final long serialVersionUID = 0L; private final int offset$1; private final int bx$1; private final int by$1; private final int mountable$2; public final void apply(int connectable) { apply$mcVI$sp(connectable); } public Rack$$anonfun$initGui$1$$anonfun$apply$mcVI$sp$3$$anonfun$apply$mcVI$sp$4(Rack$$anonfun$initGui$1$$anonfun$apply$mcVI$sp$3 $outer, int offset$1, int bx$1, int by$1, int mountable$2) {} public void apply$mcVI$sp(int connectable) {
/* 153 */           ImageButton button = new ImageButton(this.$outer.li$cil$oc$client$gui$Rack$$anonfun$$anonfun$$$outer().li$cil$oc$client$gui$Rack$$anonfun$$$outer().encodeButtonId(this.mountable$2, connectable + 1, this.$outer.bus$2), (this.$outer.li$cil$oc$client$gui$Rack$$anonfun$$anonfun$$$outer().li$cil$oc$client$gui$Rack$$anonfun$$$outer()).field_147003_i + this.bx$1, (this.$outer.li$cil$oc$client$gui$Rack$$anonfun$$anonfun$$$outer().li$cil$oc$client$gui$Rack$$anonfun$$$outer()).field_147009_r + this.by$1 + this.offset$1 + 1 + (this.$outer.li$cil$oc$client$gui$Rack$$anonfun$$anonfun$$$outer()).mbh$1 + (this.$outer.li$cil$oc$client$gui$Rack$$anonfun$$anonfun$$$outer()).sbh$1 * connectable, (this.$outer.li$cil$oc$client$gui$Rack$$anonfun$$anonfun$$$outer()).sw$1, (this.$outer.li$cil$oc$client$gui$Rack$$anonfun$$anonfun$$$outer()).sh$1, ImageButton$.MODULE$.$lessinit$greater$default$6(), ImageButton$.MODULE$.$lessinit$greater$default$7(), ImageButton$.MODULE$.$lessinit$greater$default$8(), ImageButton$.MODULE$.$lessinit$greater$default$9(), ImageButton$.MODULE$.$lessinit$greater$default$10(), ImageButton$.MODULE$.$lessinit$greater$default$11(), ImageButton$.MODULE$.$lessinit$greater$default$12());
/* 154 */           this.$outer.li$cil$oc$client$gui$Rack$$anonfun$$anonfun$$$outer().li$cil$oc$client$gui$Rack$$anonfun$$$outer().add(this.$outer.li$cil$oc$client$gui$Rack$$anonfun$$anonfun$$$outer().li$cil$oc$client$gui$Rack$$anonfun$$$outer().protected$buttonList(this.$outer.li$cil$oc$client$gui$Rack$$anonfun$$anonfun$$$outer().li$cil$oc$client$gui$Rack$$anonfun$$$outer()), button);
/* 155 */           this.$outer.li$cil$oc$client$gui$Rack$$anonfun$$anonfun$$$outer().li$cil$oc$client$gui$Rack$$anonfun$$$outer().wireButtons()[this.mountable$2][connectable + 1][this.$outer.bus$2] = button;
/*     */         } }
/*     */        }
/*     */      }
/*     */ 
/*     */   
/*     */   public void drawSecondaryForegroundLayer(int mouseX, int mouseY) {
/* 162 */     super.drawSecondaryForegroundLayer(mouseX, mouseY);
/* 163 */     GL11.glPushAttrib(1048575);
/*     */     
/* 165 */     this.field_146289_q.func_78276_b(
/* 166 */         Localization$.MODULE$.localizeImmediately(rack().func_145825_b()), 
/* 167 */         8, 6, 4210752);
/*     */     
/* 169 */     GL11.glColor3f(1.0F, 1.0F, 1.0F);
/* 170 */     this.field_146297_k.field_71446_o.func_110577_a(Textures$.MODULE$.guiRack());
/*     */     
/* 172 */     if (rack().isRelayEnabled()) {
/* 173 */       Tuple4<Object, Object, Object, Object> tuple41 = relayModeUVs(); if (tuple41 != null) { int left = BoxesRunTime.unboxToInt(tuple41._1()), top = BoxesRunTime.unboxToInt(tuple41._2()), w = BoxesRunTime.unboxToInt(tuple41._3()), h = BoxesRunTime.unboxToInt(tuple41._4()); Tuple4 tuple43 = new Tuple4(BoxesRunTime.boxToInteger(left), BoxesRunTime.boxToInteger(top), BoxesRunTime.boxToInteger(w), BoxesRunTime.boxToInteger(h)), tuple42 = tuple43; int i = BoxesRunTime.unboxToInt(tuple42._1()), j = BoxesRunTime.unboxToInt(tuple42._2()), k = BoxesRunTime.unboxToInt(tuple42._3()), m = BoxesRunTime.unboxToInt(tuple42._4());
/* 174 */         Predef$.MODULE$.refArrayOps((Object[])wireRelay()).withFilter((Function1)new Rack$$anonfun$drawSecondaryForegroundLayer$3(this)).foreach((Function1)new Rack$$anonfun$drawSecondaryForegroundLayer$4(this, i, j, k, m)); }
/*     */       else
/*     */       { throw new MatchError(tuple41); }
/*     */     
/*     */     } 
/* 179 */     Tuple4<Object, Object, Object, Object> tuple4 = connectorMasterUVs(); if (tuple4 != null) { int mcx = BoxesRunTime.unboxToInt(tuple4._1()), mcy = BoxesRunTime.unboxToInt(tuple4._2()), mcw = BoxesRunTime.unboxToInt(tuple4._3()), mch = BoxesRunTime.unboxToInt(tuple4._4()); Tuple4 tuple42 = new Tuple4(BoxesRunTime.boxToInteger(mcx), BoxesRunTime.boxToInteger(mcy), BoxesRunTime.boxToInteger(mcw), BoxesRunTime.boxToInteger(mch)), tuple41 = tuple42; int i = BoxesRunTime.unboxToInt(tuple41._1()), j = BoxesRunTime.unboxToInt(tuple41._2()), k = BoxesRunTime.unboxToInt(tuple41._3()), m = BoxesRunTime.unboxToInt(tuple41._4());
/* 180 */       Tuple4<Object, Object, Object, Object> tuple43 = busMasterBlankUVs(); if (tuple43 != null) { int mbx = BoxesRunTime.unboxToInt(tuple43._1()), mby = BoxesRunTime.unboxToInt(tuple43._2()), mbw = BoxesRunTime.unboxToInt(tuple43._3()), mbh = BoxesRunTime.unboxToInt(tuple43._4()); Tuple4 tuple45 = new Tuple4(BoxesRunTime.boxToInteger(mbx), BoxesRunTime.boxToInteger(mby), BoxesRunTime.boxToInteger(mbw), BoxesRunTime.boxToInteger(mbh)), tuple44 = tuple45; int n = BoxesRunTime.unboxToInt(tuple44._1()), i1 = BoxesRunTime.unboxToInt(tuple44._2()), i2 = BoxesRunTime.unboxToInt(tuple44._3()), i3 = BoxesRunTime.unboxToInt(tuple44._4());
/* 181 */         Tuple4<Object, Object, Object, Object> tuple46 = busMasterPresentUVs(); if (tuple46 != null) { int mpx = BoxesRunTime.unboxToInt(tuple46._1()), mpy = BoxesRunTime.unboxToInt(tuple46._2()), mpw = BoxesRunTime.unboxToInt(tuple46._3()), mph = BoxesRunTime.unboxToInt(tuple46._4()); Tuple4 tuple48 = new Tuple4(BoxesRunTime.boxToInteger(mpx), BoxesRunTime.boxToInteger(mpy), BoxesRunTime.boxToInteger(mpw), BoxesRunTime.boxToInteger(mph)), tuple47 = tuple48; int i4 = BoxesRunTime.unboxToInt(tuple47._1()), i5 = BoxesRunTime.unboxToInt(tuple47._2()), i6 = BoxesRunTime.unboxToInt(tuple47._3()), i7 = BoxesRunTime.unboxToInt(tuple47._4());
/* 182 */           Tuple4<Object, Object, Object, Object> tuple49 = connectorSlaveUVs(); if (tuple49 != null) { int scx = BoxesRunTime.unboxToInt(tuple49._1()), scy = BoxesRunTime.unboxToInt(tuple49._2()), scw = BoxesRunTime.unboxToInt(tuple49._3()), sch = BoxesRunTime.unboxToInt(tuple49._4()); Tuple4 tuple411 = new Tuple4(BoxesRunTime.boxToInteger(scx), BoxesRunTime.boxToInteger(scy), BoxesRunTime.boxToInteger(scw), BoxesRunTime.boxToInteger(sch)), tuple410 = tuple411; int i8 = BoxesRunTime.unboxToInt(tuple410._1()), i9 = BoxesRunTime.unboxToInt(tuple410._2()), i10 = BoxesRunTime.unboxToInt(tuple410._3()), i11 = BoxesRunTime.unboxToInt(tuple410._4());
/* 183 */             Tuple4<Object, Object, Object, Object> tuple412 = busSlaveBlankUVs(); if (tuple412 != null) { int sbx = BoxesRunTime.unboxToInt(tuple412._1()), sby = BoxesRunTime.unboxToInt(tuple412._2()), sbw = BoxesRunTime.unboxToInt(tuple412._3()), sbh = BoxesRunTime.unboxToInt(tuple412._4()); Tuple4 tuple414 = new Tuple4(BoxesRunTime.boxToInteger(sbx), BoxesRunTime.boxToInteger(sby), BoxesRunTime.boxToInteger(sbw), BoxesRunTime.boxToInteger(sbh)), tuple413 = tuple414; int i12 = BoxesRunTime.unboxToInt(tuple413._1()), i13 = BoxesRunTime.unboxToInt(tuple413._2()), i14 = BoxesRunTime.unboxToInt(tuple413._3()), i15 = BoxesRunTime.unboxToInt(tuple413._4());
/* 184 */               Tuple4<Object, Object, Object, Object> tuple415 = busSlavePresentUVs(); if (tuple415 != null) { int spx = BoxesRunTime.unboxToInt(tuple415._1()), spy = BoxesRunTime.unboxToInt(tuple415._2()), spw = BoxesRunTime.unboxToInt(tuple415._3()), sph = BoxesRunTime.unboxToInt(tuple415._4()); Tuple4 tuple417 = new Tuple4(BoxesRunTime.boxToInteger(spx), BoxesRunTime.boxToInteger(spy), BoxesRunTime.boxToInteger(spw), BoxesRunTime.boxToInteger(sph)), tuple416 = tuple417; int i16 = BoxesRunTime.unboxToInt(tuple416._1()), i17 = BoxesRunTime.unboxToInt(tuple416._2()), i18 = BoxesRunTime.unboxToInt(tuple416._3()), i19 = BoxesRunTime.unboxToInt(tuple416._4()); RichInt$.MODULE$
/* 185 */                   .until$extension0(Predef$.MODULE$.intWrapper(0), rack().func_70302_i_()).foreach$mVc$sp((Function1)new Rack$$anonfun$drawSecondaryForegroundLayer$1(this, i, j, k, m, n, i1, i2, i3, i4, i5, i6, i7, i8, i9, i10, i11, i12, i13, i14, i15, i16, i17, i18, i19)); RichInt$.MODULE$
/*     */ 
/*     */ 
/*     */ 
/*     */ 
/*     */ 
/*     */ 
/*     */ 
/*     */ 
/*     */ 
/*     */ 
/*     */ 
/*     */ 
/*     */ 
/*     */ 
/*     */ 
/*     */ 
/*     */ 
/*     */ 
/*     */ 
/*     */ 
/*     */ 
/*     */ 
/*     */ 
/*     */ 
/*     */ 
/*     */ 
/*     */ 
/*     */ 
/*     */ 
/*     */ 
/*     */ 
/*     */ 
/*     */ 
/*     */ 
/*     */ 
/*     */ 
/*     */ 
/*     */ 
/*     */ 
/*     */ 
/*     */ 
/*     */ 
/*     */ 
/*     */ 
/*     */ 
/*     */ 
/*     */ 
/*     */ 
/*     */ 
/*     */ 
/*     */ 
/*     */ 
/*     */ 
/*     */ 
/*     */ 
/*     */ 
/*     */ 
/*     */                   
/* 244 */                   .until$extension0(Predef$.MODULE$.intWrapper(0), 5).foreach((Function1)new Rack$$anonfun$drawSecondaryForegroundLayer$2(this));
/*     */ 
/*     */ 
/*     */ 
/*     */ 
/*     */ 
/*     */ 
/*     */ 
/*     */                 
/* 253 */                 if (relayButton().func_146115_a()) {
/* 254 */                   ArrayList<?> tooltip = new ArrayList();
/* 255 */                   tooltip.addAll(WrapAsJava$.MODULE$.asJavaCollection((new StringOps(Predef$.MODULE$.augmentString(Localization$Rack$.MODULE$.RelayModeTooltip()))).lines().toIterable()));
/* 256 */                   copiedDrawHoveringText(tooltip, mouseX - this.field_147003_i, mouseY - this.field_147009_r, this.field_146289_q);
/*     */                 } 
/*     */                 
/* 259 */                 GL11.glPopAttrib(); return; }  throw new MatchError(tuple415); }  throw new MatchError(tuple412); }  throw new MatchError(tuple49); }  throw new MatchError(tuple46); }  throw new MatchError(tuple43); }  throw new MatchError(tuple4);
/*     */   } public final class Rack$$anonfun$drawSecondaryForegroundLayer$3 extends AbstractFunction1<Tuple2<Object, Object>, Object> implements Serializable {
/*     */     public static final long serialVersionUID = 0L; public final boolean apply(Tuple2 check$ifrefutable$1) { boolean bool; Tuple2 tuple2 = check$ifrefutable$1; if (tuple2 != null) { bool = true; } else { bool = false; }  return bool; } public Rack$$anonfun$drawSecondaryForegroundLayer$3(Rack $outer) {} } public final class Rack$$anonfun$drawSecondaryForegroundLayer$4 extends AbstractFunction1<Tuple2<Object, Object>, BoxedUnit> implements Serializable {
/*     */     public static final long serialVersionUID = 0L; private final int left$1; private final int top$1; private final int w$1; private final int h$1; public final void apply(Tuple2 x$7) { Tuple2 tuple2 = x$7; if (tuple2 != null) { int x = tuple2._1$mcI$sp(), y = tuple2._2$mcI$sp(); this.$outer.li$cil$oc$client$gui$Rack$$drawRect(x, y, this.w$1, this.h$1, this.left$1, this.top$1); BoxedUnit boxedUnit = BoxedUnit.UNIT; return; }  throw new MatchError(tuple2); } public Rack$$anonfun$drawSecondaryForegroundLayer$4(Rack $outer, int left$1, int top$1, int w$1, int h$1) {} }
/* 263 */   public void drawSecondaryBackgroundLayer() { GL11.glColor3f(1.0F, 1.0F, 1.0F);
/* 264 */     this.field_146297_k.field_71446_o.func_110577_a(Textures$.MODULE$.guiRack());
/* 265 */     func_73729_b(this.field_147003_i, this.field_147009_r, 0, 0, this.field_146999_f, this.field_147000_g); }
/*     */ 
/*     */   
/*     */   public void li$cil$oc$client$gui$Rack$$drawRect(int x, int y, int w, int h, int u, int v) {
/* 269 */     float u0 = u / 256.0F;
/* 270 */     float v0 = v / 256.0F;
/* 271 */     float u1 = u0 + w / 256.0F;
/* 272 */     float v1 = v0 + h / 256.0F;
/* 273 */     Tessellator t = Tessellator.field_78398_a;
/* 274 */     t.func_78382_b();
/* 275 */     t.func_78374_a(x, y, windowZ(), u0, v0);
/* 276 */     t.func_78374_a(x, (y + h), windowZ(), u0, v1);
/* 277 */     t.func_78374_a((x + w), (y + h), windowZ(), u1, v1);
/* 278 */     t.func_78374_a((x + w), y, windowZ(), u1, v0);
/* 279 */     t.func_78381_a();
/*     */   }
/*     */   
/*     */   public final class Rack$$anonfun$drawSecondaryForegroundLayer$1 extends AbstractFunction1.mcVI.sp implements Serializable {
/*     */     public static final long serialVersionUID = 0L;
/*     */     private final int mcx$1;
/*     */     private final int mcy$1;
/*     */     public final int mcw$1;
/*     */     public final int mch$1;
/*     */     public final int mbx$1;
/*     */     public final int mby$1;
/*     */     public final int mbw$1;
/*     */     public final int mbh$2;
/*     */     public final int mpx$1;
/*     */     public final int mpy$1;
/*     */     public final int mpw$1;
/*     */     public final int mph$1;
/*     */     public final int scx$1;
/*     */     public final int scy$1;
/*     */     public final int scw$1;
/*     */     public final int sch$1;
/*     */     public final int sbx$1;
/*     */     public final int sby$1;
/*     */     public final int sbw$1;
/*     */     public final int sbh$2;
/*     */     public final int spx$1;
/*     */     public final int spy$1;
/*     */     public final int spw$1;
/*     */     public final int sph$1;
/*     */     
/*     */     public final void apply(int mountable) {
/*     */       apply$mcVI$sp(mountable);
/*     */     }
/*     */     
/*     */     public Rack$$anonfun$drawSecondaryForegroundLayer$1(Rack $outer, int mcx$1, int mcy$1, int mcw$1, int mch$1, int mbx$1, int mby$1, int mbw$1, int mbh$2, int mpx$1, int mpy$1, int mpw$1, int mph$1, int scx$1, int scy$1, int scw$1, int sch$1, int sbx$1, int sby$1, int sbw$1, int sbh$2, int spx$1, int spy$1, int spw$1, int sph$1) {}
/*     */     
/*     */     public void apply$mcVI$sp(int mountable) {
/*     */       // Byte code:
/*     */       //   0: aload_0
/*     */       //   1: getfield $outer : Lli/cil/oc/client/gui/Rack;
/*     */       //   4: invokevirtual inventoryContainer : ()Lnet/minecraft/inventory/Container;
/*     */       //   7: checkcast li/cil/oc/common/container/Rack
/*     */       //   10: invokevirtual nodePresence : ()[[Z
/*     */       //   13: iload_1
/*     */       //   14: aaload
/*     */       //   15: astore_2
/*     */       //   16: aload_0
/*     */       //   17: getfield $outer : Lli/cil/oc/client/gui/Rack;
/*     */       //   20: invokevirtual connectorStart : ()[Lscala/Tuple2;
/*     */       //   23: iload_1
/*     */       //   24: aaload
/*     */       //   25: astore #4
/*     */       //   27: aload #4
/*     */       //   29: ifnull -> 464
/*     */       //   32: aload #4
/*     */       //   34: invokevirtual _1$mcI$sp : ()I
/*     */       //   37: istore #5
/*     */       //   39: aload #4
/*     */       //   41: invokevirtual _2$mcI$sp : ()I
/*     */       //   44: istore #6
/*     */       //   46: new scala/Tuple2$mcII$sp
/*     */       //   49: dup
/*     */       //   50: iload #5
/*     */       //   52: iload #6
/*     */       //   54: invokespecial <init> : (II)V
/*     */       //   57: astore #7
/*     */       //   59: aload #7
/*     */       //   61: astore_3
/*     */       //   62: aload_3
/*     */       //   63: invokevirtual _1$mcI$sp : ()I
/*     */       //   66: istore #8
/*     */       //   68: aload_3
/*     */       //   69: invokevirtual _2$mcI$sp : ()I
/*     */       //   72: istore #9
/*     */       //   74: aload_2
/*     */       //   75: iconst_0
/*     */       //   76: baload
/*     */       //   77: ifeq -> 388
/*     */       //   80: aload_0
/*     */       //   81: getfield $outer : Lli/cil/oc/client/gui/Rack;
/*     */       //   84: iload #8
/*     */       //   86: iload #9
/*     */       //   88: aload_0
/*     */       //   89: getfield mcw$1 : I
/*     */       //   92: aload_0
/*     */       //   93: getfield mch$1 : I
/*     */       //   96: aload_0
/*     */       //   97: getfield mcx$1 : I
/*     */       //   100: aload_0
/*     */       //   101: getfield mcy$1 : I
/*     */       //   104: invokevirtual li$cil$oc$client$gui$Rack$$drawRect : (IIIIII)V
/*     */       //   107: aload_0
/*     */       //   108: getfield $outer : Lli/cil/oc/client/gui/Rack;
/*     */       //   111: invokevirtual rack : ()Lli/cil/oc/common/tileentity/Rack;
/*     */       //   114: invokevirtual nodeMapping : ()[[Lscala/Option;
/*     */       //   117: iload_1
/*     */       //   118: aaload
/*     */       //   119: iconst_0
/*     */       //   120: aaload
/*     */       //   121: astore #10
/*     */       //   123: aload #10
/*     */       //   125: instanceof scala/Some
/*     */       //   128: ifeq -> 353
/*     */       //   131: aload #10
/*     */       //   133: checkcast scala/Some
/*     */       //   136: astore #11
/*     */       //   138: aload #11
/*     */       //   140: invokevirtual x : ()Ljava/lang/Object;
/*     */       //   143: checkcast net/minecraftforge/common/util/ForgeDirection
/*     */       //   146: astore #12
/*     */       //   148: aload_0
/*     */       //   149: getfield $outer : Lli/cil/oc/client/gui/Rack;
/*     */       //   152: invokevirtual sideToBus : ()Lscala/collection/immutable/Map;
/*     */       //   155: aload #12
/*     */       //   157: invokeinterface apply : (Ljava/lang/Object;)Ljava/lang/Object;
/*     */       //   162: invokestatic unboxToInt : (Ljava/lang/Object;)I
/*     */       //   165: istore #14
/*     */       //   167: aload_0
/*     */       //   168: getfield $outer : Lli/cil/oc/client/gui/Rack;
/*     */       //   171: invokevirtual wireMasterUVs : ()[Lscala/Tuple4;
/*     */       //   174: iload #14
/*     */       //   176: aaload
/*     */       //   177: astore #16
/*     */       //   179: aload #16
/*     */       //   181: ifnull -> 343
/*     */       //   184: aload #16
/*     */       //   186: invokevirtual _1 : ()Ljava/lang/Object;
/*     */       //   189: invokestatic unboxToInt : (Ljava/lang/Object;)I
/*     */       //   192: istore #17
/*     */       //   194: aload #16
/*     */       //   196: invokevirtual _2 : ()Ljava/lang/Object;
/*     */       //   199: invokestatic unboxToInt : (Ljava/lang/Object;)I
/*     */       //   202: istore #18
/*     */       //   204: aload #16
/*     */       //   206: invokevirtual _3 : ()Ljava/lang/Object;
/*     */       //   209: invokestatic unboxToInt : (Ljava/lang/Object;)I
/*     */       //   212: istore #19
/*     */       //   214: aload #16
/*     */       //   216: invokevirtual _4 : ()Ljava/lang/Object;
/*     */       //   219: invokestatic unboxToInt : (Ljava/lang/Object;)I
/*     */       //   222: istore #20
/*     */       //   224: new scala/Tuple4
/*     */       //   227: dup
/*     */       //   228: iload #17
/*     */       //   230: invokestatic boxToInteger : (I)Ljava/lang/Integer;
/*     */       //   233: iload #18
/*     */       //   235: invokestatic boxToInteger : (I)Ljava/lang/Integer;
/*     */       //   238: iload #19
/*     */       //   240: invokestatic boxToInteger : (I)Ljava/lang/Integer;
/*     */       //   243: iload #20
/*     */       //   245: invokestatic boxToInteger : (I)Ljava/lang/Integer;
/*     */       //   248: invokespecial <init> : (Ljava/lang/Object;Ljava/lang/Object;Ljava/lang/Object;Ljava/lang/Object;)V
/*     */       //   251: astore #21
/*     */       //   253: aload #21
/*     */       //   255: astore #15
/*     */       //   257: aload #15
/*     */       //   259: invokevirtual _1 : ()Ljava/lang/Object;
/*     */       //   262: invokestatic unboxToInt : (Ljava/lang/Object;)I
/*     */       //   265: istore #22
/*     */       //   267: aload #15
/*     */       //   269: invokevirtual _2 : ()Ljava/lang/Object;
/*     */       //   272: invokestatic unboxToInt : (Ljava/lang/Object;)I
/*     */       //   275: istore #23
/*     */       //   277: aload #15
/*     */       //   279: invokevirtual _3 : ()Ljava/lang/Object;
/*     */       //   282: invokestatic unboxToInt : (Ljava/lang/Object;)I
/*     */       //   285: istore #24
/*     */       //   287: aload #15
/*     */       //   289: invokevirtual _4 : ()Ljava/lang/Object;
/*     */       //   292: invokestatic unboxToInt : (Ljava/lang/Object;)I
/*     */       //   295: istore #25
/*     */       //   297: getstatic scala/runtime/RichInt$.MODULE$ : Lscala/runtime/RichInt$;
/*     */       //   300: getstatic scala/Predef$.MODULE$ : Lscala/Predef$;
/*     */       //   303: iconst_0
/*     */       //   304: invokevirtual intWrapper : (I)I
/*     */       //   307: iload #14
/*     */       //   309: invokevirtual to$extension0 : (II)Lscala/collection/immutable/Range$Inclusive;
/*     */       //   312: new li/cil/oc/client/gui/Rack$$anonfun$drawSecondaryForegroundLayer$1$$anonfun$apply$mcVI$sp$5
/*     */       //   315: dup
/*     */       //   316: aload_0
/*     */       //   317: iload #8
/*     */       //   319: iload #9
/*     */       //   321: iload #22
/*     */       //   323: iload #23
/*     */       //   325: iload #24
/*     */       //   327: iload #25
/*     */       //   329: invokespecial <init> : (Lli/cil/oc/client/gui/Rack$$anonfun$drawSecondaryForegroundLayer$1;IIIIII)V
/*     */       //   332: invokevirtual foreach$mVc$sp : (Lscala/Function1;)V
/*     */       //   335: getstatic scala/runtime/BoxedUnit.UNIT : Lscala/runtime/BoxedUnit;
/*     */       //   338: astore #13
/*     */       //   340: goto -> 358
/*     */       //   343: new scala/MatchError
/*     */       //   346: dup
/*     */       //   347: aload #16
/*     */       //   349: invokespecial <init> : (Ljava/lang/Object;)V
/*     */       //   352: athrow
/*     */       //   353: getstatic scala/runtime/BoxedUnit.UNIT : Lscala/runtime/BoxedUnit;
/*     */       //   356: astore #13
/*     */       //   358: getstatic scala/runtime/RichInt$.MODULE$ : Lscala/runtime/RichInt$;
/*     */       //   361: getstatic scala/Predef$.MODULE$ : Lscala/Predef$;
/*     */       //   364: iconst_1
/*     */       //   365: invokevirtual intWrapper : (I)I
/*     */       //   368: iconst_4
/*     */       //   369: invokevirtual until$extension0 : (II)Lscala/collection/immutable/Range;
/*     */       //   372: new li/cil/oc/client/gui/Rack$$anonfun$drawSecondaryForegroundLayer$1$$anonfun$apply$mcVI$sp$6
/*     */       //   375: dup
/*     */       //   376: aload_0
/*     */       //   377: iload #8
/*     */       //   379: iload #9
/*     */       //   381: iload_1
/*     */       //   382: invokespecial <init> : (Lli/cil/oc/client/gui/Rack$$anonfun$drawSecondaryForegroundLayer$1;III)V
/*     */       //   385: invokevirtual foreach$mVc$sp : (Lscala/Function1;)V
/*     */       //   388: getstatic scala/runtime/RichInt$.MODULE$ : Lscala/runtime/RichInt$;
/*     */       //   391: getstatic scala/Predef$.MODULE$ : Lscala/Predef$;
/*     */       //   394: iconst_1
/*     */       //   395: invokevirtual intWrapper : (I)I
/*     */       //   398: iconst_4
/*     */       //   399: invokevirtual until$extension0 : (II)Lscala/collection/immutable/Range;
/*     */       //   402: new li/cil/oc/client/gui/Rack$$anonfun$drawSecondaryForegroundLayer$1$$anonfun$apply$mcVI$sp$8
/*     */       //   405: dup
/*     */       //   406: aload_0
/*     */       //   407: aload_2
/*     */       //   408: iload #8
/*     */       //   410: iload #9
/*     */       //   412: invokespecial <init> : (Lli/cil/oc/client/gui/Rack$$anonfun$drawSecondaryForegroundLayer$1;[ZII)V
/*     */       //   415: invokevirtual foreach$mVc$sp : (Lscala/Function1;)V
/*     */       //   418: iload_1
/*     */       //   419: aload_0
/*     */       //   420: getfield mbh$2 : I
/*     */       //   423: aload_0
/*     */       //   424: getfield sbh$2 : I
/*     */       //   427: iconst_3
/*     */       //   428: imul
/*     */       //   429: iadd
/*     */       //   430: iconst_3
/*     */       //   431: iadd
/*     */       //   432: imul
/*     */       //   433: istore #26
/*     */       //   435: getstatic scala/runtime/RichInt$.MODULE$ : Lscala/runtime/RichInt$;
/*     */       //   438: getstatic scala/Predef$.MODULE$ : Lscala/Predef$;
/*     */       //   441: iconst_0
/*     */       //   442: invokevirtual intWrapper : (I)I
/*     */       //   445: iconst_5
/*     */       //   446: invokevirtual until$extension0 : (II)Lscala/collection/immutable/Range;
/*     */       //   449: new li/cil/oc/client/gui/Rack$$anonfun$drawSecondaryForegroundLayer$1$$anonfun$apply$mcVI$sp$9
/*     */       //   452: dup
/*     */       //   453: aload_0
/*     */       //   454: aload_2
/*     */       //   455: iload #26
/*     */       //   457: invokespecial <init> : (Lli/cil/oc/client/gui/Rack$$anonfun$drawSecondaryForegroundLayer$1;[ZI)V
/*     */       //   460: invokevirtual foreach$mVc$sp : (Lscala/Function1;)V
/*     */       //   463: return
/*     */       //   464: new scala/MatchError
/*     */       //   467: dup
/*     */       //   468: aload #4
/*     */       //   470: invokespecial <init> : (Ljava/lang/Object;)V
/*     */       //   473: athrow
/*     */       // Line number table:
/*     */       //   Java source line number -> byte code offset
/*     */       //   #186	-> 0
/*     */       //   #189	-> 16
/*     */       //   #190	-> 74
/*     */       //   #191	-> 80
/*     */       //   #192	-> 107
/*     */       //   #193	-> 123
/*     */       //   #194	-> 148
/*     */       //   #195	-> 167
/*     */       //   #196	-> 300
/*     */       //   #193	-> 338
/*     */       //   #195	-> 343
/*     */       //   #200	-> 353
/*     */       //   #202	-> 361
/*     */       //   #216	-> 391
/*     */       //   #224	-> 418
/*     */       //   #225	-> 438
/*     */       //   #189	-> 464
/*     */       // Local variable table:
/*     */       //   start	length	slot	name	descriptor
/*     */       //   0	474	0	this	Lli/cil/oc/client/gui/Rack$$anonfun$drawSecondaryForegroundLayer$1;
/*     */       //   0	474	1	mountable	I
/*     */       //   16	447	2	presence	[Z
/*     */       //   39	435	5	cx	I
/*     */       //   46	428	6	cy	I
/*     */       //   68	395	8	cx	I
/*     */       //   74	389	9	cy	I
/*     */       //   148	326	12	side	Lnet/minecraftforge/common/util/ForgeDirection;
/*     */       //   167	171	14	bus	I
/*     */       //   194	280	17	mwx	I
/*     */       //   204	270	18	mwy	I
/*     */       //   214	260	19	mww	I
/*     */       //   224	250	20	mwh	I
/*     */       //   267	71	22	mwx	I
/*     */       //   277	61	23	mwy	I
/*     */       //   287	51	24	mww	I
/*     */       //   297	41	25	mwh	I
/*     */       //   435	28	26	yOffset	I
/*     */     }
/*     */     
/*     */     public final class Rack$$anonfun$drawSecondaryForegroundLayer$1$$anonfun$apply$mcVI$sp$5 extends AbstractFunction1.mcVI.sp implements Serializable {
/*     */       public static final long serialVersionUID = 0L;
/*     */       private final int cx$1;
/*     */       private final int cy$1;
/*     */       private final int mwx$1;
/*     */       private final int mwy$1;
/*     */       private final int mww$1;
/*     */       private final int mwh$1;
/*     */       
/*     */       public final void apply(int i) {
/*     */         apply$mcVI$sp(i);
/*     */       }
/*     */       
/*     */       public Rack$$anonfun$drawSecondaryForegroundLayer$1$$anonfun$apply$mcVI$sp$5(Rack$$anonfun$drawSecondaryForegroundLayer$1 $outer, int cx$1, int cy$1, int mwx$1, int mwy$1, int mww$1, int mwh$1) {}
/*     */       
/*     */       public void apply$mcVI$sp(int i) {
/*     */         int xOffset = this.$outer.mcw$1 + i * (this.$outer.mpw$1 + this.mww$1);
/*     */         this.$outer.li$cil$oc$client$gui$Rack$$anonfun$$$outer().li$cil$oc$client$gui$Rack$$drawRect(this.cx$1 + xOffset, this.cy$1, this.mww$1, this.mwh$1, this.mwx$1, this.mwy$1);
/*     */       }
/*     */     }
/*     */     
/*     */     public final class Rack$$anonfun$drawSecondaryForegroundLayer$1$$anonfun$apply$mcVI$sp$6 extends AbstractFunction1.mcVI.sp implements Serializable {
/*     */       public static final long serialVersionUID = 0L;
/*     */       public final int cx$1;
/*     */       public final int cy$1;
/*     */       private final int mountable$3;
/*     */       
/*     */       public final void apply(int connectable) {
/*     */         apply$mcVI$sp(connectable);
/*     */       }
/*     */       
/*     */       public Rack$$anonfun$drawSecondaryForegroundLayer$1$$anonfun$apply$mcVI$sp$6(Rack$$anonfun$drawSecondaryForegroundLayer$1 $outer, int cx$1, int cy$1, int mountable$3) {}
/*     */       
/*     */       public void apply$mcVI$sp(int connectable) {
/*     */         Option option = this.$outer.li$cil$oc$client$gui$Rack$$anonfun$$$outer().rack().nodeMapping()[this.mountable$3][connectable];
/*     */         if (option instanceof Some) {
/*     */           Some some = (Some)option;
/*     */           ForgeDirection side = (ForgeDirection)some.x();
/*     */           int bus = BoxesRunTime.unboxToInt(this.$outer.li$cil$oc$client$gui$Rack$$anonfun$$$outer().sideToBus().apply(side));
/*     */           Tuple4<Object, Object, Object, Object> tuple4 = this.$outer.li$cil$oc$client$gui$Rack$$anonfun$$$outer().wireSlaveUVs()[bus];
/*     */           if (tuple4 != null) {
/*     */             int swx = BoxesRunTime.unboxToInt(tuple4._1()), swy = BoxesRunTime.unboxToInt(tuple4._2()), sww = BoxesRunTime.unboxToInt(tuple4._3()), swh = BoxesRunTime.unboxToInt(tuple4._4());
/*     */             Tuple4 tuple42 = new Tuple4(BoxesRunTime.boxToInteger(swx), BoxesRunTime.boxToInteger(swy), BoxesRunTime.boxToInteger(sww), BoxesRunTime.boxToInteger(swh)), tuple41 = tuple42;
/*     */             int i = BoxesRunTime.unboxToInt(tuple41._1()), j = BoxesRunTime.unboxToInt(tuple41._2()), k = BoxesRunTime.unboxToInt(tuple41._3()), m = BoxesRunTime.unboxToInt(tuple41._4());
/*     */             int yOffset = this.$outer.mch$1 + 2 + (this.$outer.sch$1 + 2) * (connectable - 1);
/*     */             RichInt$.MODULE$.to$extension0(Predef$.MODULE$.intWrapper(0), bus).foreach$mVc$sp((Function1)new Rack$$anonfun$drawSecondaryForegroundLayer$1$$anonfun$apply$mcVI$sp$6$$anonfun$apply$mcVI$sp$7(this, i, j, k, m, yOffset));
/*     */             BoxedUnit boxedUnit1 = BoxedUnit.UNIT;
/*     */           } 
/*     */           throw new MatchError(tuple4);
/*     */         } 
/*     */         BoxedUnit boxedUnit = BoxedUnit.UNIT;
/*     */       }
/*     */       
/*     */       public final class Rack$$anonfun$drawSecondaryForegroundLayer$1$$anonfun$apply$mcVI$sp$6$$anonfun$apply$mcVI$sp$7 extends AbstractFunction1.mcVI.sp implements Serializable {
/*     */         public static final long serialVersionUID = 0L;
/*     */         private final int swx$1;
/*     */         private final int swy$1;
/*     */         private final int sww$1;
/*     */         private final int swh$1;
/*     */         private final int yOffset$2;
/*     */         
/*     */         public final void apply(int i) {
/*     */           apply$mcVI$sp(i);
/*     */         }
/*     */         
/*     */         public Rack$$anonfun$drawSecondaryForegroundLayer$1$$anonfun$apply$mcVI$sp$6$$anonfun$apply$mcVI$sp$7(Rack$$anonfun$drawSecondaryForegroundLayer$1$$anonfun$apply$mcVI$sp$6 $outer, int swx$1, int swy$1, int sww$1, int swh$1, int yOffset$2) {}
/*     */         
/*     */         public void apply$mcVI$sp(int i) {
/*     */           int xOffset = (this.$outer.li$cil$oc$client$gui$Rack$$anonfun$$anonfun$$$outer()).scw$1 + i * ((this.$outer.li$cil$oc$client$gui$Rack$$anonfun$$anonfun$$$outer()).spw$1 + this.sww$1);
/*     */           this.$outer.li$cil$oc$client$gui$Rack$$anonfun$$anonfun$$$outer().li$cil$oc$client$gui$Rack$$anonfun$$$outer().li$cil$oc$client$gui$Rack$$drawRect(this.$outer.cx$1 + xOffset, this.$outer.cy$1 + this.yOffset$2, this.sww$1, this.swh$1, this.swx$1, this.swy$1);
/*     */         }
/*     */       }
/*     */     }
/*     */     
/*     */     public final class Rack$$anonfun$drawSecondaryForegroundLayer$1$$anonfun$apply$mcVI$sp$8 extends AbstractFunction1.mcVI.sp implements Serializable {
/*     */       public static final long serialVersionUID = 0L;
/*     */       private final boolean[] presence$2;
/*     */       private final int cx$1;
/*     */       private final int cy$1;
/*     */       
/*     */       public final void apply(int connectable) {
/*     */         apply$mcVI$sp(connectable);
/*     */       }
/*     */       
/*     */       public Rack$$anonfun$drawSecondaryForegroundLayer$1$$anonfun$apply$mcVI$sp$8(Rack$$anonfun$drawSecondaryForegroundLayer$1 $outer, boolean[] presence$2, int cx$1, int cy$1) {}
/*     */       
/*     */       public void apply$mcVI$sp(int connectable) {
/*     */         if (this.presence$2[connectable]) {
/*     */           int yOffset = this.$outer.mch$1 + 2 + (this.$outer.sch$1 + 2) * (connectable - 1);
/*     */           this.$outer.li$cil$oc$client$gui$Rack$$anonfun$$$outer().li$cil$oc$client$gui$Rack$$drawRect(this.cx$1, this.cy$1 + yOffset, this.$outer.scw$1, this.$outer.sch$1, this.$outer.scx$1, this.$outer.scy$1);
/*     */         } 
/*     */       }
/*     */     }
/*     */     
/*     */     public final class Rack$$anonfun$drawSecondaryForegroundLayer$1$$anonfun$apply$mcVI$sp$9 extends AbstractFunction1.mcVI.sp implements Serializable {
/*     */       public static final long serialVersionUID = 0L;
/*     */       public final boolean[] presence$2;
/*     */       public final int yOffset$1;
/*     */       
/*     */       public final void apply(int bus) {
/*     */         apply$mcVI$sp(bus);
/*     */       }
/*     */       
/*     */       public Rack$$anonfun$drawSecondaryForegroundLayer$1$$anonfun$apply$mcVI$sp$9(Rack$$anonfun$drawSecondaryForegroundLayer$1 $outer, boolean[] presence$2, int yOffset$1) {}
/*     */       
/*     */       public void apply$mcVI$sp(int bus) {
/*     */         Tuple2<Object, Object> tuple2 = this.$outer.li$cil$oc$client$gui$Rack$$anonfun$$$outer().busStart()[bus];
/*     */         if (tuple2 != null) {
/*     */           int bx = tuple2._1$mcI$sp(), by = tuple2._2$mcI$sp();
/*     */           Tuple2.mcII.sp sp2 = new Tuple2.mcII.sp(bx, by), sp1 = sp2;
/*     */           int i = sp1._1$mcI$sp(), j = sp1._2$mcI$sp();
/*     */           if (this.presence$2[0]) {
/*     */             this.$outer.li$cil$oc$client$gui$Rack$$anonfun$$$outer().li$cil$oc$client$gui$Rack$$drawRect(i - 1, j + this.yOffset$1, this.$outer.mpw$1, this.$outer.mph$1, this.$outer.mpx$1, this.$outer.mpy$1);
/*     */           } else {
/*     */             this.$outer.li$cil$oc$client$gui$Rack$$anonfun$$$outer().li$cil$oc$client$gui$Rack$$drawRect(i, j + this.yOffset$1, this.$outer.mbw$1, this.$outer.mbh$2, this.$outer.mbx$1, this.$outer.mby$1);
/*     */           } 
/*     */           RichInt$.MODULE$.until$extension0(Predef$.MODULE$.intWrapper(0), 3).foreach$mVc$sp((Function1)new Rack$$anonfun$drawSecondaryForegroundLayer$1$$anonfun$apply$mcVI$sp$9$$anonfun$apply$mcVI$sp$10(this, i, j));
/*     */           return;
/*     */         } 
/*     */         throw new MatchError(tuple2);
/*     */       }
/*     */       
/*     */       public final class Rack$$anonfun$drawSecondaryForegroundLayer$1$$anonfun$apply$mcVI$sp$9$$anonfun$apply$mcVI$sp$10 extends AbstractFunction1.mcVI.sp implements Serializable {
/*     */         public static final long serialVersionUID = 0L;
/*     */         private final int bx$2;
/*     */         private final int by$2;
/*     */         
/*     */         public final void apply(int connectable) {
/*     */           apply$mcVI$sp(connectable);
/*     */         }
/*     */         
/*     */         public Rack$$anonfun$drawSecondaryForegroundLayer$1$$anonfun$apply$mcVI$sp$9$$anonfun$apply$mcVI$sp$10(Rack$$anonfun$drawSecondaryForegroundLayer$1$$anonfun$apply$mcVI$sp$9 $outer, int bx$2, int by$2) {}
/*     */         
/*     */         public void apply$mcVI$sp(int connectable) {
/*     */           if (this.$outer.presence$2[connectable + 1]) {
/*     */             this.$outer.li$cil$oc$client$gui$Rack$$anonfun$$anonfun$$$outer().li$cil$oc$client$gui$Rack$$anonfun$$$outer().li$cil$oc$client$gui$Rack$$drawRect(this.bx$2 - 1, this.by$2 + this.$outer.yOffset$1 + (this.$outer.li$cil$oc$client$gui$Rack$$anonfun$$anonfun$$$outer()).mph$1 + (this.$outer.li$cil$oc$client$gui$Rack$$anonfun$$anonfun$$$outer()).sph$1 * connectable, (this.$outer.li$cil$oc$client$gui$Rack$$anonfun$$anonfun$$$outer()).spw$1, (this.$outer.li$cil$oc$client$gui$Rack$$anonfun$$anonfun$$$outer()).sph$1, (this.$outer.li$cil$oc$client$gui$Rack$$anonfun$$anonfun$$$outer()).spx$1, (this.$outer.li$cil$oc$client$gui$Rack$$anonfun$$anonfun$$$outer()).spy$1);
/*     */           } else {
/*     */             this.$outer.li$cil$oc$client$gui$Rack$$anonfun$$anonfun$$$outer().li$cil$oc$client$gui$Rack$$anonfun$$$outer().li$cil$oc$client$gui$Rack$$drawRect(this.bx$2, this.by$2 + this.$outer.yOffset$1 + (this.$outer.li$cil$oc$client$gui$Rack$$anonfun$$anonfun$$$outer()).mbh$2 + (this.$outer.li$cil$oc$client$gui$Rack$$anonfun$$anonfun$$$outer()).sbh$2 * connectable, (this.$outer.li$cil$oc$client$gui$Rack$$anonfun$$anonfun$$$outer()).sbw$1, (this.$outer.li$cil$oc$client$gui$Rack$$anonfun$$anonfun$$$outer()).sbh$2, (this.$outer.li$cil$oc$client$gui$Rack$$anonfun$$anonfun$$$outer()).sbx$1, (this.$outer.li$cil$oc$client$gui$Rack$$anonfun$$anonfun$$$outer()).sby$1);
/*     */           } 
/*     */         }
/*     */       }
/*     */     }
/*     */   }
/*     */   
/*     */   public final class Rack$$anonfun$drawSecondaryForegroundLayer$2 extends AbstractFunction1.mcII.sp implements Serializable {
/*     */     public static final long serialVersionUID = 0L;
/*     */     
/*     */     public final int apply(int bus) {
/*     */       return apply$mcII$sp(bus);
/*     */     }
/*     */     
/*     */     public Rack$$anonfun$drawSecondaryForegroundLayer$2(Rack $outer) {}
/*     */     
/*     */     public int apply$mcII$sp(int bus) {
/*     */       int x = 122;
/*     */       int y = 20 + bus * 11;
/*     */       return this.$outer.protected$fontRendererObj(this.$outer).func_78276_b(Localization$.MODULE$.localizeImmediately(this.$outer.sideName(this.$outer.busToSide()[bus])), x, y, 4210752);
/*     */     }
/*     */   } }


/* Location:              C:\Users\shame\AppData\Roaming\PrismLauncher\instances\GT_New_Horizons_2.7.4_Java_17-21\.minecraft\mods\OpenComputers-1.10.30-GTNH.jar!\li\cil\oc\client\gui\Rack.class
 * Java compiler version: 8 (52.0)
 * JD-Core Version:       1.1.3
 */