/*     */ package li.cil.oc.client.gui;@ScalaSignature(bytes = "\006\001\005]e\001B\001\003\0015\021aaU2sK\026t'BA\002\005\003\r9W/\033\006\003\013\031\taa\0317jK:$(BA\004\t\003\ty7M\003\002\n\025\005\0311-\0337\013\003-\t!\001\\5\004\001M\031\001A\004\r\021\005=1R\"\001\t\013\005\r\t\"BA\003\023\025\t\031B#A\005nS:,7M]1gi*\tQ#A\002oKRL!a\006\t\003\023\035+\030nU2sK\026t\007CA\r\035\033\005Q\"BA\016\003\003\031!(/Y5ug&\021QD\007\002\f\023:\004X\017\036\"vM\032,'\017\003\005 \001\t\025\r\021\"\001!\003\031\021WO\0324feV\t\021\005\005\002#O5\t1E\003\002%K\005A\021N\034;fe:\fGN\003\002'\r\005\031\021\r]5\n\005!\032#A\003+fqR\024UO\0324fe\"A!\006\001B\001B\003%\021%A\004ck\0324WM\035\021\t\0211\002!Q1A\005\0025\n\001\002[1t\033>,8/Z\013\002]A\021qFM\007\002a)\t\021'A\003tG\006d\027-\003\0024a\t9!i\\8mK\006t\007\002C\033\001\005\003\005\013\021\002\030\002\023!\f7/T8vg\026\004\003\002C\034\001\005\013\007I\021\001\035\002'!\f7oS3zE>\f'\017Z\"bY2\024\027mY6\026\003e\0022a\f\036/\023\tY\004GA\005Gk:\034G/[8oa!AQ\b\001B\001B\003%\021(\001\013iCN\\U-\0372pCJ$7)\0317mE\006\0347\016\t\005\t\001\021)\031!C\001q\005A\001.Y:Q_^,'\017\003\005B\001\t\005\t\025!\003:\003%A\027m\035)po\026\024\b\005C\003D\001\021\005A)\001\004=S:LGO\020\013\006\013\036C\025J\023\t\003\r\002i\021A\001\005\006?\t\003\r!\t\005\006Y\t\003\rA\f\005\006o\t\003\r!\017\005\006\t\003\r!\017\005\006\031\002!\t&L\001\fQ\006\0348*Z=c_\006\024H\rC\003O\001\021Es*A\004ck\0324WM\035-\026\003A\003\"aL)\n\005I\003$aA%oi\")A\013\001C)\037\0069!-\0364gKJL\006b\002,\001\005\004%IaT\001\rEV4g-\032:NCJ<\027N\034\005\0071\002\001\013\021\002)\002\033\t,hMZ3s\033\006\024x-\0338!\021\035Q\006\0011A\005\n5\n\001\002Z5e\0072L7m\033\005\b9\002\001\r\021\"\003^\0031!\027\016Z\"mS\016\\w\fJ3r)\tq\026\r\005\0020?&\021\001\r\r\002\005+:LG\017C\004c7\006\005\t\031\001\030\002\007a$\023\007\003\004e\001\001\006KAL\001\nI&$7\t\\5dW\002BqA\032\001A\002\023%q*A\001y\021\035A\007\0011A\005\n%\fQ\001_0%KF$\"A\0306\t\017\t<\027\021!a\001!\"1A\016\001Q!\nA\013!\001\037\021\t\0179\004\001\031!C\005\037\006\t\021\020C\004q\001\001\007I\021B9\002\013e|F%Z9\025\005y\023\bb\0022p\003\003\005\r\001\025\005\007i\002\001\013\025\002)\002\005e\004\003b\002<\001\001\004%IaT\001\003[bDq\001\037\001A\002\023%\0210\001\004nq~#S-\035\013\003=jDqAY<\002\002\003\007\001\013\003\004}\001\001\006K\001U\001\004[b\004\003b\002@\001\001\004%IaT\001\003[fD\021\"!\001\001\001\004%I!a\001\002\r5Lx\fJ3r)\rq\026Q\001\005\bE~\f\t\0211\001Q\021\035\tI\001\001Q!\nA\0131!\\=!\021\035\ti\001\001C!\003\037\t\001\003[1oI2,Wj\\;tK&s\007/\036;\025\003yCq!a\005\001\t#\n)\"\001\007n_V\034Xm\0217jG.,G\rF\004_\003/\tY\"a\b\t\017\005e\021\021\003a\001!\0061Qn\\;tKbCq!!\b\002\022\001\007\001+\001\004n_V\034X-\027\005\b\003C\t\t\0021\001Q\003\031\021W\017\036;p]\"9\021Q\005\001\005R\005\035\022AD7pkN,7\t\\5dW6{g/\032\013\n=\006%\0221FA\027\003_Aq!!\007\002$\001\007\001\013C\004\002\036\005\r\002\031\001)\t\017\005\005\0221\005a\001!\"A\021\021GA\022\001\004\t\031$A\007uS6,7+\0338dK2\0137\017\036\t\004_\005U\022bAA\034a\t!Aj\0348h\021\035\tY\004\001C)\003{\ta\"\\8vg\026luN^3e\037J,\006\017F\004_\003\t\t%a\021\t\017\005e\021\021\ba\001!\"9\021QDA\035\001\004\001\006bBA\021\003s\001\r\001\025\005\b\003\017\002A\021BA%\003-\031G.[2l\037J$%/Y4\025\017y\013Y%!\024\002P!9\021\021DA#\001\004\001\006bBA\017\003\013\002\r\001\025\005\b\003C\t)\0051\001Q\021\035\t\031\006\001C\005\003+\n1\003^8Ck\0324WM]\"p_J$\027N\\1uKN$b!a\026\002j\005-\004#B\030\002Z\005u\023bAA.a\t1q\n\035;j_:\004raLA0\003G\n\031'C\002\002bA\022a\001V;qY\026\024\004cA\030\002f%\031\021q\r\031\003\r\021{WO\0317f\021\035\tI\"!\025A\002ACq!!\b\002R\001\007\001\013C\004\002p\001!\t%!\035\002\025\021\024\030m^*de\026,g\016F\004_\003g\n)(a\036\t\017\005e\021Q\016a\001!\"9\021QDA7\001\004\001\006\002CA=\003[\002\r!a\037\002\005\021$\bcA\030\002~%\031\021q\020\031\003\013\031cw.\031;\t\017\005\r\005\001\"\021\002\020\005QAM]1x\005V4g-\032:\t\017\005\035\005\001\"\025\002\n\006Q1\r[1oO\026\034\026N_3\025\021\005\r\0241RAH\003'C\001\"!$\002\006\002\007\0211M\001\002o\"A\021\021SAC\001\004\t\031'A\001i\021\035\t)*!\"A\0029\n\021B]3d_6\004\030\016\\3")
/*     */ public class Screen extends GuiScreen implements InputBuffer { private final TextBuffer buffer; private final boolean hasMouse; private final Function0<Object> hasKeyboardCallback; private final Function0<Object> hasPower; private final int bufferMargin; private boolean didClick; private int x; private int y; private int mx; private int my;
/*     */   private final Map<Object, Object> li$cil$oc$client$gui$traits$InputBuffer$$pressedKeys;
/*     */   private long li$cil$oc$client$gui$traits$InputBuffer$$showKeyboardMissing;
/*     */   private boolean guiSizeChanged;
/*     */   private int currentWidth;
/*     */   private int currentHeight;
/*     */   private double scale;
/*     */   
/*  10 */   public Map<Object, Object> li$cil$oc$client$gui$traits$InputBuffer$$pressedKeys() { return this.li$cil$oc$client$gui$traits$InputBuffer$$pressedKeys; } public long li$cil$oc$client$gui$traits$InputBuffer$$showKeyboardMissing() { return this.li$cil$oc$client$gui$traits$InputBuffer$$showKeyboardMissing; } public void li$cil$oc$client$gui$traits$InputBuffer$$showKeyboardMissing_$eq(long x$1) { this.li$cil$oc$client$gui$traits$InputBuffer$$showKeyboardMissing = x$1; } public void li$cil$oc$client$gui$traits$InputBuffer$_setter_$li$cil$oc$client$gui$traits$InputBuffer$$pressedKeys_$eq(Map<Object, Object> x$1) { this.li$cil$oc$client$gui$traits$InputBuffer$$pressedKeys = x$1; } public int bufferColumns() { return InputBuffer.class.bufferColumns(this); } public int bufferRows() { return InputBuffer.class.bufferRows(this); } public boolean func_73868_f() { return InputBuffer.class.doesGuiPauseGame(this); } public void func_73866_w_() { InputBuffer.class.initGui(this); } public void drawBufferLayer() { InputBuffer.class.drawBufferLayer(this); } public void func_146281_b() { InputBuffer.class.onGuiClosed(this); } public void func_146282_l() { InputBuffer.class.handleKeyboardInput(this); } public boolean guiSizeChanged() { return this.guiSizeChanged; } public void guiSizeChanged_$eq(boolean x$1) { this.guiSizeChanged = x$1; } public int currentWidth() { return this.currentWidth; } public void currentWidth_$eq(int x$1) { this.currentWidth = x$1; } public int currentHeight() { return this.currentHeight; } public void currentHeight_$eq(int x$1) { this.currentHeight = x$1; } public double scale() { return this.scale; } public void scale_$eq(double x$1) { this.scale = x$1; } public TextBuffer buffer() { return this.buffer; } public boolean hasMouse() { return this.hasMouse; } public Function0<Object> hasKeyboardCallback() { return this.hasKeyboardCallback; } public Function0<Object> hasPower() { return this.hasPower; } public Screen(TextBuffer buffer, boolean hasMouse, Function0<Object> hasKeyboardCallback, Function0<Object> hasPower) { DisplayBuffer.class.$init$((DisplayBuffer)this); InputBuffer.class.$init$(this);
/*     */ 
/*     */ 
/*     */ 
/*     */ 
/*     */ 
/*     */     
/*  17 */     this.bufferMargin = BufferRenderer$.MODULE$.margin() + BufferRenderer$.MODULE$.innerMargin();
/*     */     
/*  19 */     this.didClick = false;
/*     */     
/*  21 */     this.x = 0; this.y = 0;
/*     */     
/*  23 */     this.mx = -1; this.my = -1; } public boolean hasKeyboard() { return hasKeyboardCallback().apply$mcZ$sp(); } public int bufferX() { return 8 + x(); } public int bufferY() { return 8 + y(); } private int bufferMargin() { return this.bufferMargin; } private boolean didClick() { return this.didClick; } private int mx() { return this.mx; } private void didClick_$eq(boolean x$1) { this.didClick = x$1; } private int x() { return this.x; } private void x_$eq(int x$1) { this.x = x$1; } private int y() { return this.y; } private void y_$eq(int x$1) { this.y = x$1; } private void mx_$eq(int x$1) { this.mx = x$1; } private int my() { return this.my; } private void my_$eq(int x$1) { this.my = x$1; }
/*     */   
/*     */   public void func_146274_d() {
/*  26 */     super.func_146274_d();
/*  27 */     if (hasMouse() && Mouse.hasWheel() && Mouse.getEventDWheel() != 0) {
/*  28 */       int mouseX = Mouse.getEventX() * this.field_146294_l / this.field_146297_k.field_71443_c;
/*  29 */       int mouseY = this.field_146295_m - Mouse.getEventY() * this.field_146295_m / this.field_146297_k.field_71440_d - 1;
/*  30 */       Option<Tuple2<Object, Object>> option = toBufferCoordinates(mouseX, mouseY);
/*  31 */       if (option instanceof Some) { Some some = (Some)option; Tuple2 tuple2 = (Tuple2)some.x(); if (tuple2 != null) { double bx = tuple2._1$mcD$sp(), by = tuple2._2$mcD$sp();
/*  32 */           int scroll = package$.MODULE$.signum(Mouse.getEventDWheel());
/*  33 */           buffer().mouseScroll(bx, by, scroll, null); BoxedUnit boxedUnit1 = BoxedUnit.UNIT; return; }  }
/*  34 */        BoxedUnit boxedUnit = BoxedUnit.UNIT;
/*     */     } 
/*     */   }
/*     */ 
/*     */   
/*     */   public void func_73864_a(int mouseX, int mouseY, int button) {
/*  40 */     InputBuffer.class.mouseClicked(this, mouseX, mouseY, button);
/*  41 */     if (hasMouse() && (
/*  42 */       button == 0 || button == 1)) {
/*  43 */       clickOrDrag(mouseX, mouseY, button);
/*     */     }
/*     */   }
/*     */ 
/*     */   
/*     */   public void func_146273_a(int mouseX, int mouseY, int button, long timeSinceLast) {
/*  49 */     super.func_146273_a(mouseX, mouseY, button, timeSinceLast);
/*  50 */     if (hasMouse() && timeSinceLast > 10L && (
/*  51 */       button == 0 || button == 1)) {
/*  52 */       clickOrDrag(mouseX, mouseY, button);
/*     */     }
/*     */   }
/*     */ 
/*     */ 
/*     */ 
/*     */ 
/*     */ 
/*     */ 
/*     */   
/*     */   public void func_146286_b(int mouseX, int mouseY, int button) {
/*     */     // Byte code:
/*     */     //   0: aload_0
/*     */     //   1: iload_1
/*     */     //   2: iload_2
/*     */     //   3: iload_3
/*     */     //   4: invokespecial func_146286_b : (III)V
/*     */     //   7: aload_0
/*     */     //   8: invokevirtual hasMouse : ()Z
/*     */     //   11: ifeq -> 138
/*     */     //   14: iload_3
/*     */     //   15: iconst_0
/*     */     //   16: if_icmplt -> 138
/*     */     //   19: aload_0
/*     */     //   20: invokespecial didClick : ()Z
/*     */     //   23: ifeq -> 123
/*     */     //   26: aload_0
/*     */     //   27: iload_1
/*     */     //   28: iload_2
/*     */     //   29: invokespecial toBufferCoordinates : (II)Lscala/Option;
/*     */     //   32: astore #4
/*     */     //   34: aload #4
/*     */     //   36: instanceof scala/Some
/*     */     //   39: ifeq -> 101
/*     */     //   42: aload #4
/*     */     //   44: checkcast scala/Some
/*     */     //   47: astore #5
/*     */     //   49: aload #5
/*     */     //   51: invokevirtual x : ()Ljava/lang/Object;
/*     */     //   54: checkcast scala/Tuple2
/*     */     //   57: astore #6
/*     */     //   59: aload #6
/*     */     //   61: ifnull -> 101
/*     */     //   64: aload #6
/*     */     //   66: invokevirtual _1$mcD$sp : ()D
/*     */     //   69: dstore #7
/*     */     //   71: aload #6
/*     */     //   73: invokevirtual _2$mcD$sp : ()D
/*     */     //   76: dstore #9
/*     */     //   78: aload_0
/*     */     //   79: invokevirtual buffer : ()Lli/cil/oc/api/internal/TextBuffer;
/*     */     //   82: dload #7
/*     */     //   84: dload #9
/*     */     //   86: iload_3
/*     */     //   87: aconst_null
/*     */     //   88: invokeinterface mouseUp : (DDILnet/minecraft/entity/player/EntityPlayer;)V
/*     */     //   93: getstatic scala/runtime/BoxedUnit.UNIT : Lscala/runtime/BoxedUnit;
/*     */     //   96: astore #11
/*     */     //   98: goto -> 123
/*     */     //   101: aload_0
/*     */     //   102: invokevirtual buffer : ()Lli/cil/oc/api/internal/TextBuffer;
/*     */     //   105: ldc2_w -1.0
/*     */     //   108: ldc2_w -1.0
/*     */     //   111: iload_3
/*     */     //   112: aconst_null
/*     */     //   113: invokeinterface mouseUp : (DDILnet/minecraft/entity/player/EntityPlayer;)V
/*     */     //   118: getstatic scala/runtime/BoxedUnit.UNIT : Lscala/runtime/BoxedUnit;
/*     */     //   121: astore #11
/*     */     //   123: aload_0
/*     */     //   124: iconst_0
/*     */     //   125: invokespecial didClick_$eq : (Z)V
/*     */     //   128: aload_0
/*     */     //   129: iconst_m1
/*     */     //   130: invokespecial mx_$eq : (I)V
/*     */     //   133: aload_0
/*     */     //   134: iconst_m1
/*     */     //   135: invokespecial my_$eq : (I)V
/*     */     //   138: return
/*     */     // Line number table:
/*     */     //   Java source line number -> byte code offset
/*     */     //   #58	-> 0
/*     */     //   #59	-> 7
/*     */     //   #60	-> 19
/*     */     //   #61	-> 26
/*     */     //   #62	-> 34
/*     */     //   #63	-> 101
/*     */     //   #66	-> 123
/*     */     //   #67	-> 128
/*     */     //   #68	-> 133
/*     */     //   #57	-> 138
/*     */     // Local variable table:
/*     */     //   start	length	slot	name	descriptor
/*     */     //   0	139	0	this	Lli/cil/oc/client/gui/Screen;
/*     */     //   0	139	1	mouseX	I
/*     */     //   0	139	2	mouseY	I
/*     */     //   0	139	3	button	I
/*     */     //   71	68	7	bx	D
/*     */     //   78	61	9	by	D
/*     */   }
/*     */ 
/*     */ 
/*     */ 
/*     */ 
/*     */ 
/*     */ 
/*     */   
/*     */   private void clickOrDrag(int mouseX, int mouseY, int button) {
/*  73 */     Option<Tuple2<Object, Object>> option = toBufferCoordinates(mouseX, mouseY);
/*  74 */     if (option instanceof Some) { Some some = (Some)option; Tuple2 tuple2 = (Tuple2)some.x(); if (tuple2 != null) { double bx = tuple2._1$mcD$sp(), by = tuple2._2$mcD$sp(); if ((int)bx != mx() || (int)(by * 2) != my())
/*  75 */         { if (mx() >= 0 && my() >= 0) { buffer().mouseDrag(bx, by, button, null); }
/*  76 */           else { buffer().mouseDown(bx, by, button, null); }
/*  77 */            didClick_$eq(true);
/*  78 */           mx_$eq((int)bx);
/*  79 */           my_$eq((int)(by * 2)); BoxedUnit boxedUnit1 = BoxedUnit.UNIT; return; }  }  }
/*  80 */      BoxedUnit boxedUnit = BoxedUnit.UNIT;
/*     */   }
/*     */ 
/*     */   
/*     */   private Option<Tuple2<Object, Object>> toBufferCoordinates(int mouseX, int mouseY) {
/*  85 */     double bx = (mouseX - x() - bufferMargin()) / scale() / TextBufferRenderCache$.MODULE$.renderer().charRenderWidth();
/*  86 */     double by = (mouseY - y() - bufferMargin()) / scale() / TextBufferRenderCache$.MODULE$.renderer().charRenderHeight();
/*  87 */     int bw = buffer().getViewportWidth();
/*  88 */     int bh = buffer().getViewportHeight();
/*  89 */     return (bx >= false && by >= false && bx < bw && by < bh) ? (Option<Tuple2<Object, Object>>)new Some(new Tuple2.mcDD.sp(bx, by)) : 
/*  90 */       (Option<Tuple2<Object, Object>>)None$.MODULE$;
/*     */   }
/*     */   
/*     */   public void func_73863_a(int mouseX, int mouseY, float dt) {
/*  94 */     super.func_73863_a(mouseX, mouseY, dt);
/*  95 */     drawBufferLayer();
/*     */   }
/*     */   
/*     */   public void drawBuffer() {
/*  99 */     GL11.glTranslatef(x(), y(), 0.0F);
/* 100 */     BufferRenderer$.MODULE$.drawBackground();
/* 101 */     if (hasPower().apply$mcZ$sp()) {
/* 102 */       GL11.glTranslatef(bufferMargin(), bufferMargin(), 0.0F);
/* 103 */       GL11.glScaled(scale(), scale(), 1.0D);
/* 104 */       RenderState$.MODULE$.makeItBlend();
/* 105 */       BufferRenderer$.MODULE$.drawText(buffer());
/*     */     } 
/*     */   }
/*     */   
/*     */   public double changeSize(double w, double h, boolean recompile) {
/* 110 */     int bw = buffer().renderWidth();
/* 111 */     int bh = buffer().renderHeight();
/* 112 */     double scaleX = package$.MODULE$.min(this.field_146294_l / (bw + bufferMargin() * 2.0D), 1.0D);
/* 113 */     double scaleY = package$.MODULE$.min(this.field_146295_m / (bh + bufferMargin() * 2.0D), 1.0D);
/* 114 */     double scale = package$.MODULE$.min(scaleX, scaleY);
/* 115 */     int innerWidth = (int)(bw * scale);
/* 116 */     int innerHeight = (int)(bh * scale);
/* 117 */     x_$eq((this.field_146294_l - innerWidth + bufferMargin() * 2) / 2);
/* 118 */     y_$eq((this.field_146295_m - innerHeight + bufferMargin() * 2) / 2);
/* 119 */     if (recompile) {
/* 120 */       BufferRenderer$.MODULE$.compileBackground(innerWidth, innerHeight, BufferRenderer$.MODULE$.compileBackground$default$3());
/*     */     }
/* 122 */     return scale;
/*     */   } }


/* Location:              C:\Users\shame\AppData\Roaming\PrismLauncher\instances\GT_New_Horizons_2.7.4_Java_17-21\.minecraft\mods\OpenComputers-1.10.30-GTNH.jar!\li\cil\oc\client\gui\Screen.class
 * Java compiler version: 8 (52.0)
 * JD-Core Version:       1.1.3
 */